Workbook
Name ADVANCE: Masters!$U$3:$U$22
Name AMANAT: Masters!$P$3:$P$32
Name BEPAARI: Masters!$B$3:$B$52
Name CAPITAL: Masters!$P$3:$P$32
Name DUKANDAR: Masters!$J$3:$J$150
Name LOAN: Masters!$P$3:$P$32

Sheet Masters
A1: BEPAARI MASTER | I1: DUKANDAR MASTER | O1: CAPITAL/LOAN/AMANAT | T1: ADVANCE PARTIES | X1: SETTINGS & B/F BALANCES
A2: Sr | B2: Bepaari Name | C2: Comm% | D2: Flat ₹/Goat | E2: Opening Bal | F2: Phone | G2: Remarks | I2: Sr | J2: Dukandar Name | K2: Opening Bal | L2: Phone | M2: Remarks | O2: Sr | P2: Party Name | Q2: Opening Bal | R2: Type | T2: Sr | U2: Party Name | V2: Opening Bal | X2: Commission Rate (%) | Y2: 4
A3: 1 | B3: ABUL HASAN | C3: 4 | E3: 7550 | I3: 1 | J3: SAKIM | K3: 113500 | O3: 1 | P3: MHN CAPITAL | Q3: 4469981 | R3: CAPITAL | T3: 1 | U3: SALIM MANGROL | V3: 50000 | X3: KK Fixed (₹/Bepari) | Y3: 100
A4: 2 | B4: SHARAFAT | C4: 4 | E4: 0 | I4: 2 | J4: SHARIK | K4: 879000 | O4: 2 | P4: SHAKIL GHODEGAON AMANAT | Q4: 2000000 | R4: AMANAT | T4: 2 | U4: MUDASSIR | V4: 25000 | X4: JB Rate (₹/Goat) | Y4: 10
A5: 3 | B5: JUNAID | C5: 4 | E5: 0 | I5: 3 | J5: YUNUS | K5: 94931 | O5: 3 | P5: KMN | Q5: 0 | R5: AMANAT | T5: 3 | U5: AYAAN | V5: 203700
A6: 4 | B6: ANNU SHARIF | C6: 4 | E6: 0 | I6: 4 | J6: MUDASSIR | K6: 516778 | O6: 4 | P6: AYAAN | Q6: 0 | R6: AMANAT | T6: 4 | U6: KMN | V6: 347500 | X6: Opening Cash | Y6: 394666
A7: 5 | B7: GAYYUR | C7: 4 | E7: 142530 | I7: 5 | J7: ARIF | K7: 187650 | O7: 5 | P7: WAHIDA | Q7: 0 | R7: AMANAT | T7: 5 | U7: SANTOSH | V7: 3000 | X7: Opening Bank | Y7: 724604
A8: 6 | B8: KISHOR | C8: 4 | E8: -152964 | I8: 6 | J8: SHOEB BYCULLA | K8: 0 | O8: 6 | P8: TILLA | Q8: 0 | R8: AMANAT | T8: 6 | U8: SHAKIL GHODEGAON | V8: 100000
A9: 7 | B9: MAULANA | C9: 4 | E9: 35330 | I9: 7 | J9: ISLAM D | K9: 100000 | O9: 7 | T9: 7 | X9: --- LIABILITIES B/F ---
A10: 8 | B10: SALIM RAJ | C10: 4 | E10: 0 | I10: 8 | J10: MEHMOOD MADH | K10: 15000 | O10: 8 | T10: 8 | X10: JB Opening (B/F) | Y10: 17100
A11: 9 | B11: ANAS RAJ | C11: 4 | E11: 0 | I11: 9 | J11: MOBIN CHIPLUN | K11: 486250 | O11: 9 | T11: 9 | X11: KK Opening (B/F) | Y11: 10100
A12: 10 | B12: AYAZ | C12: 4 | E12: 1530 | I12: 10 | J12: JALIL | K12: 90950 | O12: 10 | T12: 10 | X12: Zakat Opening (B/F) | Y12: 73111
A13: 11 | B13: NEERAJ | C13: 4 | E13: 0 | I13: 11 | J13: IRFAN JOGESHWARI | K13: 0 | O13: 11 | T13: 11 | X13: Commission Opening (B/F) | Y13: 358808
A14: 12 | B14: CHINTU SHUJALPUR | C14: 4 | E14: 0 | I14: 12 | J14: YUNUS DOMBIVLI | K14: 59662 | O14: 12 | T14: 12
A15: 13 | B15: SANNA | C15: 4 | E15: -14048 | I15: 13 | J15: IFTEKHAR PUNE | K15: 2000 | O15: 13 | T15: 13 | X15: --- ASSETS B/F ---
A16: 14 | B16: WAHID | C16: 4 | E16: -4661 | I16: 14 | J16: LALA/ASIF | K16: 0 | O16: 14 | T16: 14 | X16: Mandi Exp Opening (B/F) | Y16: 24816
A17: 15 | B17: MANSOOR | C17: 4 | E17: -9845 | I17: 15 | J17: JAFER KASHIMIRA | K17: 92500 | O17: 15 | T17: 15 | X17: BF Discount Opening (B/F) | Y17: 17450
A18: 16 | B18: AYAZ PREVIOUS BAL | C18: 4 | E18: -88000 | I18: 16 | J18: HANIF KALAM | K18: 0 | O18: 16 | T18: 16 | X18: MHN Personal Opening (B/F) | Y18: 294265
A19: 17 | B19: SHAKIL SHUJALPUR | C19: 4 | E19: 660 | I19: 17 | J19: SAUD K | K19: 0 | O19: 17 | T19: 17
A20: 18 | B20: USMAN | C20: 4 | E20: 40440 | I20: 18 | J20: AKRAM | K20: 0 | O20: 18 | T20: 18 | X20: SALIM MANGROL RECEIVABLE | Y20: 50000
A21: 19 | B21: JUNAID AMANAT | C21: 4 | E21: -100000 | I21: 19 | J21: WAHID | K21: 4000 | O21: 19 | T21: 19 | X21: MUDASSIR RECEIVABLE | Y21: 25000
A22: 20 | B22: SHARIF RAJ | C22: 4 | E22: 0 | I22: 20 | J22: VAZIR | K22: 134750 | O22: 20 | T22: 20 | X22: KMN RECEIVABLE | Y22: 347500
A23: 21 | C23: 4 | I23: 21 | J23: ISMAIL SOPARA | K23: 0 | O23: 21 | X23: SANTOSH RECEIVABLE | Y23: 3000
A24: 22 | C24: 4 | I24: 22 | J24: ARIF CHINCHOTI | K24: 0 | O24: 22 | X24: SHAKIL GHODEGAON RECEIVABLE | Y24: 100000
A25: 23 | C25: 4 | I25: 23 | J25: NADEEM BHIWANDI | K25: 265000 | O25: 23 | X25: AYAAN RECEIVABLE | Y25: 203700
A26: 24 | C26: 4 | I26: 24 | J26: GABBAR | K26: 33050 | O26: 24
A27: 25 | C27: 4 | I27: 25 | J27: BABU GABBAR | K27: 50000 | O27: 25
A28: 26 | C28: 4 | I28: 26 | J28: BABU TALOJA | K28: 2600 | O28: 26
A29: 27 | C29: 4 | I29: 27 | J29: SHAKIL KON | K29: 34000 | O29: 27
A30: 28 | C30: 4 | I30: 28 | J30: PARVEZ | K30: 0 | O30: 28
A31: 29 | C31: 4 | I31: 29 | J31: I CHO CHO | K31: 20500 | O31: 29
A32: 30 | C32: 4 | I32: 30 | J32: MD VIRAR | K32: 1900 | O32: 30
A33: 31 | C33: 4 | I33: 31 | J33: MAYA | K33: 11000
A34: 32 | C34: 4 | I34: 32 | J34: NAEEM THORPE | K34: 0
A35: 33 | C35: 4 | I35: 33 | J35: CHAND | K35: 59000
A36: 34 | C36: 4 | I36: 34 | J36: ASIF GOREGAON | K36: 57550
A37: 35 | C37: 4 | I37: 35 | J37: SOHAIL MAROL | K37: 0
A38: 36 | C38: 4 | I38: 36 | J38: ANEES KM | K38: 70000
A39: 37 | C39: 4 | I39: 37 | J39: RAFIQ AHMED HAJI | K39: 356250
A40: 38 | C40: 4 | I40: 38 | J40: ABP - MAJEED THANA | K40: 0
A41: 39 | C41: 4 | I41: 39 | J41: ABP - MAJNU | K41: 0
A42: 40 | C42: 4 | I42: 40 | J42: MEHBOOB JOG | K42: 98500
A43: 41 | C43: 4 | I43: 41 | J43: SIRAJ KURLA | K43: 388000
A44: 42 | C44: 4 | I44: 42 | J44: ZUBAIR AZEEZ | K44: 30000
... A46: 44 | C46: 4 | I46: 44 | J46: NAWAZ V | K46: 148800
A47: 45 | C47: 4 | I47: 45 | J47: LIYAQAT | K47: 7500 | Q47: ramesh kalal
A48: 46 | C48: 4 | I48: 46 | J48: HAKIM BOMBAY | K48: 0 | Q48: imran mumbra
A49: 47 | C49: 4 | I49: 47 | J49: JUNAID KHATIK | K49: 0 | Q49: javed thana
A50: 48 | C50: 4 | I50: 48 | J50: MANISH | K50: 0 | Q50: shahnawaz
A51: 49 | C51: 4 | I51: 49 | J51: CASH SALES | K51: 0 | Q51: parola
A52: 50 | C52: 4 | I52: 50 | J52: MAJEED THANA | K52: 0
I53: 51 | J53: RAMESH KALAL | K53: 0
I54: 52 | J54: IMRAN MUMBRA | K54: 0
I55: 53 | J55: JAVED THANA | K55: 0
I56: 54 | J56: SHAHNAWAZ | K56: 0
I57: 55 | J57: PAROLA | K57: 0
I58: 56 | J58: REHAN BYC | K58: 0
I59: 57 | J59: KHALIL | K59: 0
I60: 58 | J60: SARFARAZ | K60: 0
I61: 59 | J61: RAIS PUNE | K61: 0

Sheet Daily_Sales
A1: DAILY SALES (Bepaari to Dukandar)
A3: Sr | B3: Date | C3: Bepaari | D3: Dukandar | E3: Qty | F3: Rate | G3: Gross | H3: Discount | I3: Net
A4: 1 | B4: 46107 | C4: ANAS RAJ | D4: HAKIM BOMBAY | E4: 20 | F4: 11400 | G4: =IF(E4="","",E4*F4) -> 228000 | H4: 2000 | I4: =IF(G4="","",G4-IF(H4="",0,H4)) -> 226000
A5: 2 | B5: 46107 | C5: ANAS RAJ | D5: JUNAID KHATIK | E5: 13 | F5: 8200 | G5: =IF(E5="","",E5*F5) -> 106600 | H5: 650 | I5: =IF(G5="","",G5-IF(H5="",0,H5)) -> 105950
A6: 3 | B6: 46107 | C6: JUNAID | D6: MANISH | E6: 12 | F6: 9500 | G6: =IF(E6="","",E6*F6) -> 114000 | I6: =IF(G6="","",G6-IF(H6="",0,H6)) -> 114000
A7: 4 | B7: 46107 | C7: JUNAID | D7: CASH SALES | E7: 10 | F7: 8500 | G7: =IF(E7="","",E7*F7) -> 85000 | I7: =IF(G7="","",G7-IF(H7="",0,H7)) -> 85000
A8: 5 | B8: 46107 | C8: JUNAID | D8: JALIL | E8: 1 | F8: 6500 | G8: =IF(E8="","",E8*F8) -> 6500 | I8: =IF(G8="","",G8-IF(H8="",0,H8)) -> 6500
A9: 6 | B9: 46107 | C9: SHARIF RAJ | D9: SHOEB BYCULLA | E9: 11 | F9: 10250 | G9: =IF(E9="","",E9*F9) -> 112750 | H9: 2750 | I9: =IF(G9="","",G9-IF(H9="",0,H9)) -> 110000
A10: 7 | B10: 46107 | C10: CHINTU SHUJALPUR | D10: MEHMOOD MADH | E10: 6 | F10: 9350 | G10: =IF(E10="","",E10*F10) -> 56100 | I10: =IF(G10="","",G10-IF(H10="",0,H10)) -> 56100
A11: 8 | B11: 46107 | C11: CHINTU SHUJALPUR | D11: JALIL | E11: 4 | F11: 8750 | G11: =IF(E11="","",E11*F11) -> 35000 | I11: =IF(G11="","",G11-IF(H11="",0,H11)) -> 35000
A12: 9 | B12: 46107 | C12: CHINTU SHUJALPUR | D12: YUNUS | E12: 4 | F12: 8075 | G12: =IF(E12="","",E12*F12) -> 32300 | I12: =IF(G12="","",G12-IF(H12="",0,H12)) -> 32300
A13: 10 | B13: 46107 | C13: CHINTU SHUJALPUR | D13: MAJEED THANA | E13: 10 | F13: 6500 | G13: =IF(E13="","",E13*F13) -> 65000 | I13: =IF(G13="","",G13-IF(H13="",0,H13)) -> 65000
A14: 11 | B14: 46109 | C14: USMAN | D14: GABBAR | E14: 10 | F14: 15500 | G14: =IF(E14="","",E14*F14) -> 155000 | H14: 2000 | I14: =IF(G14="","",G14-IF(H14="",0,H14)) -> 153000
A15: 12 | B15: 46109 | C15: USMAN | D15: YUNUS | E15: 5 | F15: 14000 | G15: =IF(E15="","",E15*F15) -> 70000 | H15: 2500 | I15: =IF(G15="","",G15-IF(H15="",0,H15)) -> 67500
A16: 13 | B16: 46109 | C16: MAULANA | D16: SHAKIL KON | E16: 15 | F16: 13750 | G16: =IF(E16="","",E16*F16) -> 206250 | I16: =IF(G16="","",G16-IF(H16="",0,H16)) -> 206250
A17: 14 | B17: 46109 | C17: MAULANA | D17: NAWAZ V | E17: 11 | F17: 10600 | G17: =IF(E17="","",E17*F17) -> 116600 | H17: 1100 | I17: =IF(G17="","",G17-IF(H17="",0,H17)) -> 115500
A18: 15 | B18: 46109 | C18: ABUL HASAN | D18: PARVEZ | E18: 15 | F18: 15750 | G18: =IF(E18="","",E18*F18) -> 236250 | I18: =IF(G18="","",G18-IF(H18="",0,H18)) -> 236250
A19: 16 | B19: 46109 | C19: ABUL HASAN | D19: PARVEZ | E19: 1 | F19: 12000 | G19: =IF(E19="","",E19*F19) -> 12000 | I19: =IF(G19="","",G19-IF(H19="",0,H19)) -> 12000
A20: 17 | B20: 46109 | C20: ABUL HASAN | D20: RAMESH KALAL | E20: 13 | F20: 9800 | G20: =IF(E20="","",E20*F20) -> 127400 | H20: 1300 | I20: =IF(G20="","",G20-IF(H20="",0,H20)) -> 126100
A21: 18 | B21: 46109 | C21: ABUL HASAN | D21: JUNAID KHATIK | E21: 15 | F21: 7100 | G21: =IF(E21="","",E21*F21) -> 106500 | I21: =IF(G21="","",G21-IF(H21="",0,H21)) -> 106500
A22: 19 | B22: 46109 | C22: SHARIF RAJ | D22: SAUD K | E22: 18 | F22: 8400 | G22: =IF(E22="","",E22*F22) -> 151200 | H22: 7200 | I22: =IF(G22="","",G22-IF(H22="",0,H22)) -> 144000
A23: 20 | B23: 46109 | C23: SHARIF RAJ | D23: SAKIM | E23: 13 | F23: 7600 | G23: =IF(E23="","",E23*F23) -> 98800 | I23: =IF(G23="","",G23-IF(H23="",0,H23)) -> 98800
A24: 21 | B24: 46109 | C24: KISHOR | D24: IMRAN MUMBRA | E24: 21 | F24: 15500 | G24: =IF(E24="","",E24*F24) -> 325500
A25: 22 | B25: 46109 | C25: KISHOR | D25: IMRAN MUMBRA | E25: 1 | F25: 12500 | G25: =IF(E25="","",E25*F25) -> 12500 | I25: =IF(G25="","",G25-IF(H25="",0,H25)) -> 12500
A26: 23 | B26: 46109 | C26: KISHOR | D26: JAVED THANA | E26: 8 | F26: 10500 | G26: =IF(E26="","",E26*F26) -> 84000 | H26: 800 | I26: =IF(G26="","",G26-IF(H26="",0,H26)) -> 83200
A27: 24 | B27: 46109 | C27: KISHOR | D27: CASH SALES | E27: 2 | F27: 21000 | G27: =IF(E27="","",E27*F27) -> 42000 | I27: =IF(G27="","",G27-IF(H27="",0,H27)) -> 42000
A28: 25 | B28: 46109 | C28: JUNAID | D28: MEHMOOD MADH | E28: 14 | F28: 9200 | G28: =IF(E28="","",E28*F28) -> 128800 | I28: =IF(G28="","",G28-IF(H28="",0,H28)) -> 128800
A29: 26 | B29: 46109 | C29: JUNAID | D29: JUNAID KHATIK | E29: 11 | F29: 5750 | G29: =IF(E29="","",E29*F29) -> 63250 | H29: 550 | I29: =IF(G29="","",G29-IF(H29="",0,H29)) -> 62700
A30: 27 | B30: 46109 | C30: JUNAID | D30: YUNUS | E30: 10 | F30: 11500 | G30: =IF(E30="","",E30*F30) -> 115000 | H30: 2500 | I30: =IF(G30="","",G30-IF(H30="",0,H30)) -> 112500
A31: 28 | B31: 46109 | C31: JUNAID | D31: JALIL | E31: 10 | F31: 10500 | G31: =IF(E31="","",E31*F31) -> 105000 | I31: =IF(G31="","",G31-IF(H31="",0,H31)) -> 105000
A32: 29 | B32: 46109 | C32: CHINTU SHUJALPUR | D32: MANISH | E32: 18 | F32: 8750 | G32: =IF(E32="","",E32*F32) -> 157500 | I32: =IF(G32="","",G32-IF(H32="",0,H32)) -> 157500
A33: 30 | B33: 46109 | C33: CHINTU SHUJALPUR | D33: MANISH | E33: 2 | F33: 6000 | G33: =IF(E33="","",E33*F33) -> 12000 | I33: =IF(G33="","",G33-IF(H33="",0,H33)) -> 12000
A34: 31 | B34: 28 | C34: CHINTU SHUJALPUR | D34: YUNUS | E34: 2 | F34: 17000 | G34: =IF(E34="","",E34*F34) -> 34000 | I34: =IF(G34="","",G34-IF(H34="",0,H34)) -> 34000
A35: 32 | B35: 46109 | C35: GAYYUR | D35: SHAHNAWAZ | E35: 5 | F35: 4750 | G35: =IF(E35="","",E35*F35) -> 23750 | I35: =IF(G35="","",G35-IF(H35="",0,H35)) -> 23750
A36: 33 | B36: 46109 | C36: NEERAJ | D36: PAROLA | E36: 5 | F36: 8400 | G36: =IF(E36="","",E36*F36) -> 42000 | I36: =IF(G36="","",G36-IF(H36="",0,H36)) -> 42000
A37: 34 | B37: 46112 | C37: ABUL HASAN | D37: REHAN BYC | E37: 13 | F37: 17200 | G37: =IF(E37="","",E37*F37) -> 223600 | H37: 2600 | I37: =IF(G37="","",G37-IF(H37="",0,H37)) -> 221000
A38: 35 | B38: 46112 | C38: ABUL HASAN | D38: KHALIL | E38: 5 | F38: 7250 | G38: =IF(E38="","",E38*F38) -> 36250 | I38: =IF(G38="","",G38-IF(H38="",0,H38)) -> 36250
A39: 36 | B39: 46112 | C39: GAYYUR | D39: CASH SALES | E39: 1 | F39: 19000 | G39: =IF(E39="","",E39*F39) -> 19000 | I39: =IF(G39="","",G39-IF(H39="",0,H39)) -> 19000
A40: 37 | B40: 46112 | C40: GAYYUR | D40: VAZIR | E40: 15 | F40: 15500 | G40: =IF(E40="","",E40*F40) -> 232500 | I40: =IF(G40="","",G40-IF(H40="",0,H40)) -> 232500
A41: 38 | B41: 46112 | C41: GAYYUR | D41: VAZIR | E41: 1 | F41: 10000 | G41: =IF(E41="","",E41*F41) -> 10000 | I41: =IF(G41="","",G41-IF(H41="",0,H41)) -> 10000
A42: 39 | B42: 46112 | C42: GAYYUR | D42: VAZIR | E42: 13 | F42: 10500 | G42: =IF(E42="","",E42*F42) -> 136500 | I42: =IF(G42="","",G42-IF(H42="",0,H42)) -> 136500
A43: 40 | B43: 46112 | C43: GAYYUR | D43: VAZIR | E43: 2 | F43: 9000 | G43: =IF(E43="","",E43*F43) -> 18000 | I43: =IF(G43="","",G43-IF(H43="",0,H43)) -> 18000
A44: 41 | B44: 46112 | C44: NEERAJ | D44: SARFARAZ | E44: 10 | F44: 11000 | G44: =IF(E44="","",E44*F44) -> 110000 | I44: =IF(G44="","",G44-IF(H44="",0,H44)) -> 110000
A45: 42 | B45: 46112 | C45: NEERAJ | D45: IFTEKHAR PUNE | E45: 18 | F45: 8600 | G45: =IF(E45="","",E45*F45) -> 154800 | I45: =IF(G45="","",G45-IF(H45="",0,H45)) -> 154800
A46: 43 | B46: 46112 | C46: NEERAJ | D46: IFTEKHAR PUNE | E46: 2 | F46: 7000 | G46: =IF(E46="","",E46*F46) -> 14000 | I46: =IF(G46="","",G46-IF(H46="",0,H46)) -> 14000
A47: 44 | B47: 46112 | C47: SALIM RAJ | D47: MUDASSIR | E47: 17 | F47: 11500 | G47: =IF(E47="","",E47*F47) -> 195500 | I47: =IF(G47="","",G47-IF(H47="",0,H47)) -> 195500
A48: 45 | B48: 46112 | C48: JUNAID | D48: RAIS PUNE | E48: 16 | F48: 10400 | G48: =IF(E48="","",E48*F48) -> 166400 | H48: 1600 | I48: =IF(G48="","",G48-IF(H48="",0,H48)) -> 164800
A49: 46 | B49: 46112 | C49: JUNAID | D49: MANISH | E49: 10 | F49: 7500 | G49: =IF(E49="","",E49*F49) -> 75000 | I49: =IF(G49="","",G49-IF(H49="",0,H49)) -> 75000
A50: 47 | B50: 46112 | C50: MAULANA | D50: SAUD K | E50: 15 | F50: 8100 | G50: =IF(E50="","",E50*F50) -> 121500 | H50: 1500 | I50: =IF(G50="","",G50-IF(H50="",0,H50)) -> 120000
A51: 48 | B51: 46112 | C51: CHINTU SHUJALPUR | D51: KHALIL | E51: 12 | F51: 15200 | G51: =IF(E51="","",E51*F51) -> 182400 | I51: =IF(G51="","",G51-IF(H51="",0,H51)) -> 182400
A52: 49 | G52: =IF(E52="","",E52*F52) | I52: =IF(G52="","",G52-IF(H52="",0,H52))
A53: 50 | G53: =IF(E53="","",E53*F53) | I53: =IF(G53="","",G53-IF(H53="",0,H53))
A54: 51 | G54: =IF(E54="","",E54*F54) | I54: =IF(G54="","",G54-IF(H54="",0,H54))
A55: 52 | G55: =IF(E55="","",E55*F55) | I55: =IF(G55="","",G55-IF(H55="",0,H55))
A56: 53 | G56: =IF(E56="","",E56*F56) | I56: =IF(G56="","",G56-IF(H56="",0,H56))
A57: 54 | G57: =IF(E57="","",E57*F57) | I57: =IF(G57="","",G57-IF(H57="",0,H57))
A58: 55 | G58: =IF(E58="","",E58*F58) | I58: =IF(G58="","",G58-IF(H58="",0,H58))
A59: 56 | G59: =IF(E59="","",E59*F59) | I59: =IF(G59="","",G59-IF(H59="",0,H59))
A60: 57 | G60: =IF(E60="","",E60*F60) | I60: =IF(G60="","",G60-IF(H60="",0,H60))
A61: 58 | G61: =IF(E61="","",E61*F61) | I61: =IF(G61="","",G61-IF(H61="",0,H61))
A62: 59 | G62: =IF(E62="","",E62*F62) | I62: =IF(G62="","",G62-IF(H62="",0,H62))
A63: 60 | G63: =IF(E63="","",E63*F63) | I63: =IF(G63="","",G63-IF(H63="",0,H63))
... A503: 500 | G503: =IF(E503="","",E503*F503) | I503: =IF(G503="","",G503-IF(H503="",0,H503))

Sheet Cash_Book
A1: CASH BOOK (All Transactions) | J1: CASH/BANK SUMMARY
A2: Select TYPE first → Party dropdown shows relevant list | I2: Opening Cash | J2: =Masters!$Y$6 -> 394666
A3: Sr | B3: Date | C3: Type | D3: Sub-Type | E3: Party | F3: Particulars | G3: Amount | H3: Mode | I3: Opening Bank | J3: =Masters!$Y$7 -> 724604
A4: 1 | B4: 46107 | C4: DUKANDAR | D4: RECEIPT | E4: YUNUS | G4: 15000 | H4: CASH
A5: 2 | B5: 46107 | C5: DUKANDAR | D5: RECEIPT | E5: YUNUS | F5: 55990-5000 (PAID OBO YUNUS) | G5: 50990 | H5: BANK | I5: Cash OUT | J5: =SUMIFS($G$4:$G$1008,$H$4:$H$1008,"CASH",$D$4:$D$1008,"PAYMENT")+SUMIFS($G$4:$G$1008,$H$4:$H$1008,"CASH",$D$4:$D$1008,"MOTOR")+SUMIFS($G$4:$G$1008,$H$4:$H$1008,"CASH",$D$4:$D$1008,"BHUSSA")+SUMIFS($G$4:$G$1008,$H$4:$H$1008,"CASH",$D$4:$D$1008,"GAWALI")+SUMIFS($G$4:$G$1008,$H$4:$H$1008,"CASH",$D$4:$D$1008,"CASH_ADV")+SUMIFS($G$4:$G$1008,$H$4:$H$1008,"CASH",$D$4:$D$1008,"DISCOUNT")+SUMIFS($G$4:$G$1008,$H$4:$H$1008,"CASH",$D$4:$D$1008,"WITHDRAWN")+SUMIFS($G$4:$G$1008,$H$4:$H$1008,"CASH",$D$4:$D$1008,"REPAID")+SUMIFS($G$4:$G$1008,$H$4:$H$1008,"CASH",$D$4:$D$1008,"GIVEN")+SUMIFS($G$4:$G$1008,$H$4:$H$1008,"CASH",$D$4:$D$1008,"MANDI")+SUMIFS($G$4:$G$1008,$H$4:$H$1008,"CASH",$D$4:$D$1008,"TRAVEL")+SUMIFS($G$4:$G$1008,$H$4:$H$1008,"CASH",$D$4:$D$1008,"FOOD")+SUMIFS($G$4:$G$1008,$H$4:$H$1008,"CASH",$D$4:$D$1008,"SALARY")+SUMIFS($G$4:$G$1008,$H$4:$H$1008,"CASH",$D$4:$D$1008,"BF_DISC")+SUMIFS($G$4:$G$1008,$H$4:$H$1008,"CASH",$D$4:$D$1008,"JB_PAID")+SUMIFS($G$4:$G$1008,$H$4:$H$1008,"CASH",$D$4:$D$1008,"MHN_PERSONAL")+SUMIFS($G$4:$G$1008,$H$4:$H$1008,"CASH",$D$4:$D$1008,"PAID")+SUMIFS($G$4:$G$1008,$H$4:$H$1008,"CASH",$D$4:$D$1008,"MISC")+SUMIFS($G$4:$G$1008,$H$4:$H$1008,"CASH",$D$4:$D$1008,"OTHER") -> 2841919
A6: 3 | B6: 46107 | C6: DUKANDAR | D6: RECEIPT | E6: NADEEM BHIWANDI | G6: 79687 | H6: BANK | I6: Bank OUT | J6: =SUMIFS($G$4:$G$1008,$H$4:$H$1008,"BANK",$D$4:$D$1008,"PAYMENT")+SUMIFS($G$4:$G$1008,$H$4:$H$1008,"BANK",$D$4:$D$1008,"MOTOR")+SUMIFS($G$4:$G$1008,$H$4:$H$1008,"BANK",$D$4:$D$1008,"BHUSSA")+SUMIFS($G$4:$G$1008,$H$4:$H$1008,"BANK",$D$4:$D$1008,"GAWALI")+SUMIFS($G$4:$G$1008,$H$4:$H$1008,"BANK",$D$4:$D$1008,"CASH_ADV")+SUMIFS($G$4:$G$1008,$H$4:$H$1008,"BANK",$D$4:$D$1008,"DISCOUNT")+SUMIFS($G$4:$G$1008,$H$4:$H$1008,"BANK",$D$4:$D$1008,"WITHDRAWN")+SUMIFS($G$4:$G$1008,$H$4:$H$1008,"BANK",$D$4:$D$1008,"REPAID")+SUMIFS($G$4:$G$1008,$H$4:$H$1008,"BANK",$D$4:$D$1008,"GIVEN")+SUMIFS($G$4:$G$1008,$H$4:$H$1008,"BANK",$D$4:$D$1008,"MANDI")+SUMIFS($G$4:$G$1008,$H$4:$H$1008,"BANK",$D$4:$D$1008,"TRAVEL")+SUMIFS($G$4:$G$1008,$H$4:$H$1008,"BANK",$D$4:$D$1008,"FOOD")+SUMIFS($G$4:$G$1008,$H$4:$H$1008,"BANK",$D$4:$D$1008,"SALARY")+SUMIFS($G$4:$G$1008,$H$4:$H$1008,"BANK",$D$4:$D$1008,"BF_DISC")+SUMIFS($G$4:$G$1008,$H$4:$H$1008,"BANK",$D$4:$D$1008,"JB_PAID")+SUMIFS($G$4:$G$1008,$H$4:$H$1008,"BANK",$D$4:$D$1008,"MHN_PERSONAL")+SUMIFS($G$4:$G$1008,$H$4:$H$1008,"BANK",$D$4:$D$1008,"PAID")+SUMIFS($G$4:$G$1008,$H$4:$H$1008,"BANK",$D$4:$D$1008,"MISC")+SUMIFS($G$4:$G$1008,$H$4:$H$1008,"BANK",$D$4:$D$1008,"OTHER")+SUMIFS($G$4:$G$1008,$H$4:$H$1008,"UPI",$D$4:$D$1008,"PAYMENT")+SUMIFS($G$4:$G$1008,$H$4:$H$1008,"UPI",$D$4:$D$1008,"MOTOR")+SUMIFS($G$4:$G$1008,$H$4:$H$1008,"UPI",$D$4:$D$1008,"BHUSSA")+SUMIFS($G$4:$G$1008,$H$4:$H$1008,"UPI",$D$4:$D$1008,"GAWALI")+SUMIFS($G$4:$G$1008,$H$4:$H$1008,"UPI",$D$4:$D$1008,"CASH_ADV")+SUMIFS($G$4:$G$1008,$H$4:$H$1008,"UPI",$D$4:$D$1008,"DISCOUNT")+SUMIFS($G$4:$G$1008,$H$4:$H$1008,"UPI",$D$4:$D$1008,"WITHDRAWN")+SUMIFS($G$4:$G$1008,$H$4:$H$1008,"UPI",$D$4:$D$1008,"REPAID")+SUMIFS($G$4:$G$1008,$H$4:$H$1008,"UPI",$D$4:$D$1008,"GIVEN")+SUMIFS($G$4:$G$1008,$H$4:$H$1008,"UPI",$D$4:$D$1008,"MANDI")+SUMIFS($G$4:$G$1008,$H$4:$H$1008,"UPI",$D$4:$D$1008,"TRAVEL")+SUMIFS($G$4:$G$1008,$H$4:$H$1008,"UPI",$D$4:$D$1008,"FOOD")+SUMIFS($G$4:$G$1008,$H$4:$H$1008,"UPI",$D$4:$D$1008,"SALARY")+SUMIFS($G$4:$G$1008,$H$4:$H$1008,"UPI",$D$4:$D$1008,"BF_DISC")+SUMIFS($G$4:$G$1008,$H$4:$H$1008,"UPI",$D$4:$D$1008,"JB_PAID")+SUMIFS($G$4:$G$1008,$H$4:$H$1008,"UPI",$D$4:$D$1008,"MHN_PERSONAL")+SUMIFS($G$4:$G$1008,$H$4:$H$1008,"UPI",$D$4:$D$1008,"PAID")+SUMIFS($G$4:$G$1008,$H$4:$H$1008,"UPI",$D$4:$D$1008,"MISC")+SUMIFS($G$4:$G$1008,$H$4:$H$1008,"UPI",$D$4:$D$1008,"OTHER")+SUMIFS($G$4:$G$1008,$H$4:$H$1008,"TRANSFER",$D$4:$D$1008,"PAYMENT")+SUMIFS($G$4:$G$1008,$H$4:$H$1008,"TRANSFER",$D$4:$D$1008,"MOTOR")+SUMIFS($G$4:$G$1008,$H$4:$H$1008,"TRANSFER",$D$4:$D$1008,"BHUSSA")+SUMIFS($G$4:$G$1008,$H$4:$H$1008,"TRANSFER",$D$4:$D$1008,"GAWALI")+SUMIFS($G$4:$G$1008,$H$4:$H$1008,"TRANSFER",$D$4:$D$1008,"CASH_ADV")+SUMIFS($G$4:$G$1008,$H$4:$H$1008,"TRANSFER",$D$4:$D$1008,"DISCOUNT")+SUMIFS($G$4:$G$1008,$H$4:$H$1008,"TRANSFER",$D$4:$D$1008,"WITHDRAWN")+SUMIFS($G$4:$G$1008,$H$4:$H$1008,"TRANSFER",$D$4:$D$1008,"REPAID")+SUMIFS($G$4:$G$1008,$H$4:$H$1008,"TRANSFER",$D$4:$D$1008,"GIVEN")+SUMIFS($G$4:$G$1008,$H$4:$H$1008,"TRANSFER",$D$4:$D$1008,"MANDI")+SUMIFS($G$4:$G$1008,$H$4:$H$1008,"TRANSFER",$D$4:$D$1008,"TRAVEL")+SUMIFS($G$4:$G$1008,$H$4:$H$1008,"TRANSFER",$D$4:$D$1008,"FOOD")+SUMIFS($G$4:$G$1008,$H$4:$H$1008,"TRANSFER",$D$4:$D$1008,"SALARY")+SUMIFS($G$4:$G$1008,$H$4:$H$1008,"TRANSFER",$D$4:$D$1008,"BF_DISC")+SUMIFS($G$4:$G$1008,$H$4:$H$1008,"TRANSFER",$D$4:$D$1008,"JB_PAID")+SUMIFS($G$4:$G$1008,$H$4:$H$1008,"TRANSFER",$D$4:$D$1008,"MHN_PERSONAL")+SUMIFS($G$4:$G$1008,$H$4:$H$1008,"TRANSFER",$D$4:$D$1008,"PAID")+SUMIFS($G$4:$G$1008,$H$4:$H$1008,"TRANSFER",$D$4:$D$1008,"MISC")+SUMIFS($G$4:$G$1008,$H$4:$H$1008,"TRANSFER",$D$4:$D$1008,"OTHER") -> 1507354
A7: 4 | B7: 46107 | C7: DUKANDAR | D7: RECEIPT | E7: MEHBOOB JOG | G7: 50000 | H7: CASH | I7: Cash IN | J7: =SUMIFS($G$4:$G$1008,$H$4:$H$1008,"CASH",$D$4:$D$1008,"RECEIPT")+SUMIFS($G$4:$G$1008,$H$4:$H$1008,"CASH",$D$4:$D$1008,"TAKEN")+SUMIFS($G$4:$G$1008,$H$4:$H$1008,"CASH",$D$4:$D$1008,"RECEIVED")+SUMIFS($G$4:$G$1008,$H$4:$H$1008,"CASH",$D$4:$D$1008,"PROVISION") -> 2833988
A8: 5 | B8: 46107 | C8: DUKANDAR | D8: RECEIPT | E8: MEHBOOB JOG | G8: 15000 | H8: BANK | I8: Bank IN | J8: =SUMIFS($G$4:$G$1008,$H$4:$H$1008,"BANK",$D$4:$D$1008,"RECEIPT")+SUMIFS($G$4:$G$1008,$H$4:$H$1008,"BANK",$D$4:$D$1008,"TAKEN")+SUMIFS($G$4:$G$1008,$H$4:$H$1008,"BANK",$D$4:$D$1008,"RECEIVED")+SUMIFS($G$4:$G$1008,$H$4:$H$1008,"BANK",$D$4:$D$1008,"PROVISION")+SUMIFS($G$4:$G$1008,$H$4:$H$1008,"UPI",$D$4:$D$1008,"RECEIPT")+SUMIFS($G$4:$G$1008,$H$4:$H$1008,"UPI",$D$4:$D$1008,"TAKEN")+SUMIFS($G$4:$G$1008,$H$4:$H$1008,"UPI",$D$4:$D$1008,"RECEIVED")+SUMIFS($G$4:$G$1008,$H$4:$H$1008,"UPI",$D$4:$D$1008,"PROVISION")+SUMIFS($G$4:$G$1008,$H$4:$H$1008,"TRANSFER",$D$4:$D$1008,"RECEIPT")+SUMIFS($G$4:$G$1008,$H$4:$H$1008,"TRANSFER",$D$4:$D$1008,"TAKEN")+SUMIFS($G$4:$G$1008,$H$4:$H$1008,"TRANSFER",$D$4:$D$1008,"RECEIVED")+SUMIFS($G$4:$G$1008,$H$4:$H$1008,"TRANSFER",$D$4:$D$1008,"PROVISION") -> 1319978
A9: 6 | B9: 46107 | C9: DUKANDAR | D9: RECEIPT | E9: ISLAM D | G9: 50000 | H9: BANK
A10: 7 | B10: 46107 | C10: DUKANDAR | D10: RECEIPT | E10: ISLAM D | G10: 50000 | H10: BANK | I10: CLOSING CASH | J10: =J2-J5+J7 -> 386735
A11: 8 | B11: 46107 | C11: DUKANDAR | D11: RECEIPT | E11: ARIF | G11: 100000 | H11: BANK | I11: CLOSING BANK | J11: =J3-J6+J8 -> 537228
A12: 9 | B12: 46107 | C12: DUKANDAR | D12: RECEIPT | E12: SAKIM | G12: 50000 | H12: BANK
A13: 10 | B13: 46107 | C13: DUKANDAR | D13: RECEIPT | E13: RAFIQ AHMED HAJI | G13: 100 | H13: BANK
A14: 11 | B14: 46107 | C14: DUKANDAR | D14: RECEIPT | E14: RAFIQ AHMED HAJI | G14: 100 | H14: BANK
A15: 12 | B15: 46107 | C15: DUKANDAR | D15: RECEIPT | E15: RAFIQ AHMED HAJI | G15: 49800 | H15: BANK
A16: 13 | B16: 46107 | C16: DUKANDAR | D16: RECEIPT | E16: RAFIQ AHMED HAJI | G16: 100 | H16: BANK
A17: 14 | B17: 46107 | C17: DUKANDAR | D17: RECEIPT | E17: RAFIQ AHMED HAJI | G17: 49900 | H17: BANK
A18: 15 | B18: 46107 | C18: DUKANDAR | D18: RECEIPT | E18: RAFIQ AHMED HAJI | F18: GPAY TO KMN | G18: 50000 | H18: CASH
A19: 16 | B19: 46107 | C19: DUKANDAR | D19: RECEIPT | E19: RAFIQ AHMED HAJI | F19: GPAY TO AYAAN | G19: 50000 | H19: CASH
A20: 17 | B20: 46107 | C20: ADVANCE | D20: GIVEN | E20: KMN | F20: C/O RAFIQ AHMED HAJI | G20: 50000 | H20: CASH
A21: 18 | B21: 46107 | C21: ADVANCE | D21: GIVEN | E21: AYAAN | F21: C/O RAFIQ AHMED HAJI | G21: 50000 | H21: CASH
A22: 19 | B22: 46107 | C22: DUKANDAR | D22: RECEIPT | E22: JAFER KASHIMIRA | G22: 50000 | H22: CASH
A23: 20 | B23: 46107 | C23: DUKANDAR | D23: RECEIPT | E23: NAWAZ V | G23: 148800 | H23: CASH
A24: 21 | B24: 46107 | C24: DUKANDAR | D24: RECEIPT | E24: CASH SALES | G24: 85000 | H24: CASH
A25: 22 | B25: 46107 | C25: DUKANDAR | D25: BF_DISC | E25: CASH SALES | G25: 200 | H25: CASH
A26: 23 | B26: 46107 | C26: ADVANCE | D26: RECEIVED | E26: SHAKIL GHODEGAON | G26: 100000 | H26: CASH
A27: 24 | B27: 46107 | C27: DUKANDAR | D27: RECEIPT | E27: MEHMOOD MADH | G27: 20000 | H27: CASH
A28: 25 | B28: 46107 | C28: DUKANDAR | D28: RECEIPT | E28: SHARIK | G28: 150000 | H28: CASH
A29: 26 | B29: 46107 | C29: ADVANCE | D29: RECEIVED | E29: AYAAN | F29: PAID TO JUNAID | G29: 100000 | H29: CASH
A30: 27 | B30: 46107 | C30: ADVANCE | D30: RECEIVED | E30: AYAAN | G30: 100000 | H30: CASH
A31: 28 | B31: 46106 | C31: BEPAARI | D31: PAYMENT | E31: ABUL HASAN | G31: 7550 | H31: BANK
A32: 29 | B32: 46107 | C32: EXPENSE | D32: TRAVEL | F32: OLA | G32: 750 | H32: BANK
A33: 30 | B33: 46107 | C33: BEPAARI | D33: PAYMENT | E33: USMAN | G33: 40000 | H33: BANK
A34: 31 | B34: 46107 | C34: BEPAARI | D34: MOTOR | E34: ANAS RAJ | G34: 7920 | H34: BANK
A35: 32 | B35: 46107 | C35: BEPAARI | D35: MOTOR | E35: SHARIF RAJ | G35: 2640 | H35: BANK
A36: 33 | B36: 46107 | C36: BEPAARI | D36: MOTOR | E36: JUNAID | G36: 5520 | H36: BANK
A37: 34 | B37: 46107 | C37: BEPAARI | D37: MOTOR | E37: CHINTU SHUJALPUR | G37: 7200 | H37: BANK
A38: 35 | B38: 46107 | C38: BEPAARI | D38: PAYMENT | E38: ABUL HASAN | G38: 100000 | H38: BANK
A39: 36 | B39: 46107 | C39: EXPENSE | D39: TRAVEL | F39: OLA | G39: 693 | H39: BANK
A40: 37 | B40: 46107 | C40: BEPAARI | D40: PAYMENT | E40: JUNAID | G40: 50000 | H40: CASH
A41: 38 | B41: 46107 | C41: EXPENSE | D41: FOOD | F41: LUNCH | G41: 500 | H41: CASH
A42: 39 | B42: 46107 | C42: BEPAARI | D42: GAWALI | E42: ANAS RAJ | G42: 1980 | H42: CASH
A43: 40 | B43: 46107 | C43: BEPAARI | D43: BHUSSA | E43: ANAS RAJ | G43: 200 | H43: CASH
A44: 41 | B44: 46107 | C44: BEPAARI | D44: GAWALI | E44: SHARIF RAJ | G44: 660 | H44: CASH
A45: 42 | B45: 46107 | C45: BEPAARI | D45: BHUSSA | E45: SHARIF RAJ | G45: 100 | H45: CASH
A46: 43 | B46: 46107 | C46: BEPAARI | D46: GAWALI | E46: CHINTU SHUJALPUR | G46: 1440 | H46: CASH
A47: 44 | B47: 46107 | C47: BEPAARI | D47: BHUSSA | E47: CHINTU SHUJALPUR | G47: 200 | H47: CASH
A48: 45 | B48: 46107 | C48: BEPAARI | D48: GAWALI | E48: JUNAID | G48: 1380 | H48: CASH
A49: 46 | B49: 46107 | C49: BEPAARI | D49: BHUSSA | E49: JUNAID | G49: 150 | H49: CASH
A50: 47 | B50: 46107 | C50: EXPENSE | D50: SALARY | F50: SAEED | G50: 1000 | H50: CASH
A51: 48 | B51: 46107 | C51: BEPAARI | D51: PAYMENT | E51: ANAS RAJ | F51: HAWALA | G51: 200000 | H51: CASH
A52: 49 | B52: 46107 | C52: BEPAARI | D52: PAYMENT | E52: ANAS RAJ | G52: 110686 | H52: BANK
A53: 50 | B53: 46107 | C53: BEPAARI | D53: PAYMENT | E53: CHINTU SHUJALPUR | F53: HAWALA | G53: 100000 | H53: CASH
A54: 51 | B54: 46107 | C54: BEPAARI | D54: PAYMENT | E54: JUNAID | F54: PAID FROM AYAAN A/C | G54: 100000 | H54: CASH
A55: 52 | B55: 46107 | C55: BEPAARI | D55: PAYMENT | E55: CHINTU SHUJALPUR | G55: 100000 | H55: BANK
A56: 53 | B56: 46107 | C56: BEPAARI | D56: PAYMENT | E56: JUNAID | G56: 50000 | H56: BANK
A57: 54 | B57: 46107 | C57: BEPAARI | D57: PAYMENT | E57: SHARIF RAJ | F57: ANNU SHARIF A/C | G57: 54630 | H57: BANK
A58: 55 | B58: 46107 | C58: BEPAARI | D58: PAYMENT | E58: SHARIF RAJ | F58: SHARIF RAJ A/C | G58: 50000 | H58: BANK
A59: 56 | B59: 46107 | C59: BEPAARI | D59: PAYMENT | E59: GAYYUR | G59: 142530 | H59: BANK
A60: 57 | B60: 46107 | C60: EXPENSE | D60: MHN_PERSONAL | F60: Cash taken by MHN | G60: 3900 | H60: CASH
A61: 58 | B61: 46108 | C61: DUKANDAR | D61: RECEIPT | E61: MEHBOOB JOG | G61: 21000 | H61: CASH
A62: 59 | B62: 46109 | C62: DUKANDAR | D62: RECEIPT | E62: YUNUS | G62: 16500 | H62: CASH
A63: 60 | B63: 46109 | C63: DUKANDAR | D63: RECEIPT | E63: YUNUS | G63: 11961 | H63: BANK
A64: 61 | B64: 46109 | C64: DUKANDAR | D64: RECEIPT | E64: ANEES KM | G64: 30000 | H64: BANK
A65: 62 | B65: 46109 | C65: DUKANDAR | D65: RECEIPT | E65: YUNUS DOMBIVLI | G65: 40000 | H65: BANK
A66: 63 | B66: 46109 | C66: ADVANCE | D66: RECEIVED | E66: KMN | G66: 50000 | H66: BANK
A67: 64 | B67: 46109 | C67: DUKANDAR | D67: RECEIPT | E67: RAFIQ AHMED HAJI | G67: 100000 | H67: BANK
A68: 65 | B68: 46109 | C68: DUKANDAR | D68: RECEIPT | E68: JALIL | G68: 50000 | H68: BANK
A69: 66 | B69: 46109 | C69: DUKANDAR | D69: RECEIPT | E69: SHAKIL KON | G69: 34000 | H69: BANK
A70: 67 | B70: 46109 | C70: DUKANDAR | D70: RECEIPT | E70: MEHBOOB JOG | G70: 5000 | H70: BANK
A71: 68 | B71: 46109 | C71: DUKANDAR | D71: RECEIPT | E71: MEHBOOB JOG | G71: 7500 | H71: CASH
A72: 69 | B72: 46109 | C72: EXPENSE | D72: BF_DISC | F72: MEHBOOB JOG. BF | G72: 7500 | H72: CASH
A73: 70 | B73: 46109 | C73: AMANAT | D73: TAKEN | E73: WAHIDA | G73: 5000 | H73: BANK
A74: 71 | B74: 46109 | C74: AMANAT | D74: REPAID | E74: WAHIDA | G74: 5000 | H74: BANK
A75: 72 | B75: 46109 | C75: DUKANDAR | D75: RECEIPT | E75: MOBIN CHIPLUN | G75: 32000 | H75: BANK
A76: 73 | B76: 46109 | C76: DUKANDAR | D76: RECEIPT | E76: NADEEM BHIWANDI | G76: 70000 | H76: BANK
A77: 74 | B77: 46109 | C77: DUKANDAR | D77: RECEIPT | E77: ARIF | G77: 67700 | H77: CASH
A78: 75 | B78: 46109 | C78: DUKANDAR | D78: RECEIPT | E78: WAHID | G78: 4000 | H78: CASH
A79: 76 | B79: 46109 | C79: DUKANDAR | D79: RECEIPT | E79: MOBIN CHIPLUN | G79: 174000 | H79: CASH
A80: 77 | B80: 46109 | C80: DUKANDAR | D80: RECEIPT | E80: CASH SALES | G80: 42000 | H80: CASH
A81: 78 | B81: 46109 | C81: AMANAT | D81: TAKEN | E81: TILLA | G81: 100000 | H81: CASH
A82: 79 | B82: 46109 | C82: BEPAARI | D82: PAYMENT | E82: KISHOR | G82: 100000 | H82: BANK
A83: 80 | B83: 46109 | C83: BEPAARI | D83: MOTOR | E83: USMAN | G83: 4250 | H83: BANK
A84: 81 | B84: 46109 | C84: BEPAARI | D84: MOTOR | E84: MAULANA | G84: 6500 | H84: BANK
... A88: 85 | B88: 46109 | C88: BEPAARI | D88: PAYMENT | E88: CHINTU SHUJALPUR | G88: 50000 | H88: BANK
A89: 86 | B89: 46109 | C89: EXPENSE | D89: TRAVEL | F89: DIESEL | G89: 3769 | H89: BANK
A90: 87 | B90: 46109 | C90: BEPAARI | D90: PAYMENT | E90: ABUL HASAN | F90: HAWALA | G90: 200000 | H90: CASH
A91: 88 | B91: 46109 | C91: BEPAARI | D91: PAYMENT | E91: JUNAID | F91: HAWALA | G91: 200000 | H91: CASH
A92: 89 | B92: 46109 | C92: BEPAARI | D92: PAYMENT | E92: MAULANA | G92: 200000 | H92: CASH
A93: 90 | B93: 46109 | C93: BEPAARI | D93: PAYMENT | E93: USMAN | G93: 150000 | H93: CASH
A94: 91 | B94: 46109 | C94: ZAKAT | D94: PAID | G94: 20000 | H94: BANK
A95: 92 | B95: 46109 | C95: EXPENSE | D95: FOOD | G95: 1000 | H95: CASH
A96: 93 | B96: 46109 | C96: EXPENSE | D96: MANDI | G96: 1000 | H96: CASH
A97: 94 | B97: 46109 | C97: BEPAARI | D97: PAYMENT | E97: KISHOR | G97: 20000 | H97: CASH
A98: 95 | B98: 46109 | C98: EXPENSE | D98: JB_PAID | G98: 4000 | H98: CASH
A99: 96 | B99: 46109 | C99: BEPAARI | D99: PAYMENT | E99: JUNAID | F99: PAID TO RAGHU | G99: 500 | H99: CASH
A100: 97 | B100: 46109 | C100: BEPAARI | D100: PAYMENT | E100: JUNAID | G100: 10000 | H100: CASH
A101: 98 | B101: 46109 | C101: BEPAARI | D101: GAWALI | E101: CHINTU SHUJALPUR | G101: 1320 | H101: CASH
A102: 99 | B102: 46109 | C102: BEPAARI | D102: BHUSSA | E102: CHINTU SHUJALPUR | G102: 100 | H102: CASH
A103: 100 | B103: 46109 | C103: BEPAARI | D103: GAWALI | E103: SHARIF RAJ | G103: 1860 | H103: CASH
...

Sheet Bepaari_Ledger
A1: BEPAARI LEDGER
A2: Commission = Flat ₹/Goat if set, otherwise Comm%
A4: Sr | B4: Bepaari | C4: Comm% | D4: Flat₹ | E4: Opening | F4: Gross Sales | G4: Qty | H4: Commission | I4: KK | J4: JB | K4: Motor | L4: Bhussa | M4: Gawali | N4: Cash/Adv | O4: Other | P4: Tot.Deduct | Q4: Net Payable | R4: Payments | S4: BALANCE
A5: 1 | B5: =IF(Masters!$B$3="","",Masters!$B$3) -> ABUL HASAN | C5: =IF(B5="","",Masters!$C$3) -> 4 | D5: =IF(B5="","",IF(Masters!$D$3="","",Masters!$D$3)) | E5: =IF(B5="",0,Masters!$E$3) -> 7550 | F5: =SUMIF(Daily_Sales!$C$4:$C$503,B5,Daily_Sales!$G$4:$G$503) -> 742000 | G5: =SUMIF(Daily_Sales!$C$4:$C$503,B5,Daily_Sales!$E$4:$E$503) -> 62 | H5: =IF(B5="",0,IF(D5<>"",D5*G5,F5*C5/100)) -> 29680 | I5: =IF(G5>0,Masters!$Y$3,0) -> 100 | J5: =G5*Masters!$Y$4 -> 620 | K5: =SUMIFS(Cash_Book!$G$4:$G$1008,Cash_Book!$C$4:$C$1008,"BEPAARI",Cash_Book!$D$4:$D$1008,"MOTOR",Cash_Book!$E$4:$E$1008,B5) -> 15120 | L5: =SUMIFS(Cash_Book!$G$4:$G$1008,Cash_Book!$C$4:$C$1008,"BEPAARI",Cash_Book!$D$4:$D$1008,"BHUSSA",Cash_Book!$E$4:$E$1008,B5) -> 300 | M5: =SUMIFS(Cash_Book!$G$4:$G$1008,Cash_Book!$C$4:$C$1008,"BEPAARI",Cash_Book!$D$4:$D$1008,"GAWALI",Cash_Book!$E$4:$E$1008,B5) -> 3780 | N5: =SUMIFS(Cash_Book!$G$4:$G$1008,Cash_Book!$C$4:$C$1008,"BEPAARI",Cash_Book!$D$4:$D$1008,"CASH_ADV",Cash_Book!$E$4:$E$1008,B5) -> 0 | O5: =SUMIFS(Cash_Book!$G$4:$G$1008,Cash_Book!$C$4:$C$1008,"BEPAARI",Cash_Book!$D$4:$D$1008,"OTHER",Cash_Book!$E$4:$E$1008,B5) -> 0 | P5: =SUM(H5:O5) -> 49600 | Q5: =IF(B5="","",F5-P5+E5) -> 699950 | R5: =SUMIFS(Cash_Book!$G$4:$G$1008,Cash_Book!$C$4:$C$1008,"BEPAARI",Cash_Book!$D$4:$D$1008,"PAYMENT",Cash_Book!$E$4:$E$1008,B5) -> 556524 | S5: =IF(B5="","",Q5-R5) -> 143426
A6: 2 | B6: =IF(Masters!$B$4="","",Masters!$B$4) -> SHARAFAT | C6: =IF(B6="","",Masters!$C$4) -> 4 | D6: =IF(B6="","",IF(Masters!$D$4="","",Masters!$D$4)) | E6: =IF(B6="",0,Masters!$E$4) -> 0 | F6: =SUMIF(Daily_Sales!$C$4:$C$503,B6,Daily_Sales!$G$4:$G$503) -> 0 | G6: =SUMIF(Daily_Sales!$C$4:$C$503,B6,Daily_Sales!$E$4:$E$503) -> 0 | H6: =IF(B6="",0,IF(D6<>"",D6*G6,F6*C6/100)) -> 0 | I6: =IF(G6>0,Masters!$Y$3,0) -> 0 | J6: =G6*Masters!$Y$4 -> 0 | K6: =SUMIFS(Cash_Book!$G$4:$G$1008,Cash_Book!$C$4:$C$1008,"BEPAARI",Cash_Book!$D$4:$D$1008,"MOTOR",Cash_Book!$E$4:$E$1008,B6) -> 0 | L6: =SUMIFS(Cash_Book!$G$4:$G$1008,Cash_Book!$C$4:$C$1008,"BEPAARI",Cash_Book!$D$4:$D$1008,"BHUSSA",Cash_Book!$E$4:$E$1008,B6) -> 0 | M6: =SUMIFS(Cash_Book!$G$4:$G$1008,Cash_Book!$C$4:$C$1008,"BEPAARI",Cash_Book!$D$4:$D$1008,"GAWALI",Cash_Book!$E$4:$E$1008,B6) -> 0 | N6: =SUMIFS(Cash_Book!$G$4:$G$1008,Cash_Book!$C$4:$C$1008,"BEPAARI",Cash_Book!$D$4:$D$1008,"CASH_ADV",Cash_Book!$E$4:$E$1008,B6) -> 0 | O6: =SUMIFS(Cash_Book!$G$4:$G$1008,Cash_Book!$C$4:$C$1008,"BEPAARI",Cash_Book!$D$4:$D$1008,"OTHER",Cash_Book!$E$4:$E$1008,B6) -> 0 | P6: =SUM(H6:O6) -> 0 | Q6: =IF(B6="","",F6-P6+E6) -> 0 | R6: =SUMIFS(Cash_Book!$G$4:$G$1008,Cash_Book!$C$4:$C$1008,"BEPAARI",Cash_Book!$D$4:$D$1008,"PAYMENT",Cash_Book!$E$4:$E$1008,B6) -> 0 | S6: =IF(B6="","",Q6-R6) -> 0
A7: 3 | B7: =IF(Masters!$B$5="","",Masters!$B$5) -> JUNAID | C7: =IF(B7="","",Masters!$C$5) -> 4 | D7: =IF(B7="","",IF(Masters!$D$5="","",Masters!$D$5)) | E7: =IF(B7="",0,Masters!$E$5) -> 0 | F7: =SUMIF(Daily_Sales!$C$4:$C$503,B7,Daily_Sales!$G$4:$G$503) -> 858950 | G7: =SUMIF(Daily_Sales!$C$4:$C$503,B7,Daily_Sales!$E$4:$E$503) -> 94 | H7: =IF(B7="",0,IF(D7<>"",D7*G7,F7*C7/100)) -> 34358 | I7: =IF(G7>0,Masters!$Y$3,0) -> 100 | J7: =G7*Masters!$Y$4 -> 940 | K7: =SUMIFS(Cash_Book!$G$4:$G$1008,Cash_Book!$C$4:$C$1008,"BEPAARI",Cash_Book!$D$4:$D$1008,"MOTOR",Cash_Book!$E$4:$E$1008,B7) -> 11760 | L7: =SUMIFS(Cash_Book!$G$4:$G$1008,Cash_Book!$C$4:$C$1008,"BEPAARI",Cash_Book!$D$4:$D$1008,"BHUSSA",Cash_Book!$E$4:$E$1008,B7) -> 250 | M7: =SUMIFS(Cash_Book!$G$4:$G$1008,Cash_Book!$C$4:$C$1008,"BEPAARI",Cash_Book!$D$4:$D$1008,"GAWALI",Cash_Book!$E$4:$E$1008,B7) -> 5640 | N7: =SUMIFS(Cash_Book!$G$4:$G$1008,Cash_Book!$C$4:$C$1008,"BEPAARI",Cash_Book!$D$4:$D$1008,"CASH_ADV",Cash_Book!$E$4:$E$1008,B7) -> 0 | O7: =SUMIFS(Cash_Book!$G$4:$G$1008,Cash_Book!$C$4:$C$1008,"BEPAARI",Cash_Book!$D$4:$D$1008,"OTHER",Cash_Book!$E$4:$E$1008,B7) -> 0 | P7: =SUM(H7:O7) -> 53048 | Q7: =IF(B7="","",F7-P7+E7) -> 805902 | R7: =SUMIFS(Cash_Book!$G$4:$G$1008,Cash_Book!$C$4:$C$1008,"BEPAARI",Cash_Book!$D$4:$D$1008,"PAYMENT",Cash_Book!$E$4:$E$1008,B7) -> 610500 | S7: =IF(B7="","",Q7-R7) -> 195402
A8: 4 | B8: =IF(Masters!$B$6="","",Masters!$B$6) -> ANNU SHARIF | C8: =IF(B8="","",Masters!$C$6) -> 4 | D8: =IF(B8="","",IF(Masters!$D$6="","",Masters!$D$6)) | E8: =IF(B8="",0,Masters!$E$6) -> 0 | F8: =SUMIF(Daily_Sales!$C$4:$C$503,B8,Daily_Sales!$G$4:$G$503) -> 0 | G8: =SUMIF(Daily_Sales!$C$4:$C$503,B8,Daily_Sales!$E$4:$E$503) -> 0 | H8: =IF(B8="",0,IF(D8<>"",D8*G8,F8*C8/100)) -> 0 | I8: =IF(G8>0,Masters!$Y$3,0) -> 0 | J8: =G8*Masters!$Y$4 -> 0 | K8: =SUMIFS(Cash_Book!$G$4:$G$1008,Cash_Book!$C$4:$C$1008,"BEPAARI",Cash_Book!$D$4:$D$1008,"MOTOR",Cash_Book!$E$4:$E$1008,B8) -> 0 | L8: =SUMIFS(Cash_Book!$G$4:$G$1008,Cash_Book!$C$4:$C$1008,"BEPAARI",Cash_Book!$D$4:$D$1008,"BHUSSA",Cash_Book!$E$4:$E$1008,B8) -> 0 | M8: =SUMIFS(Cash_Book!$G$4:$G$1008,Cash_Book!$C$4:$C$1008,"BEPAARI",Cash_Book!$D$4:$D$1008,"GAWALI",Cash_Book!$E$4:$E$1008,B8) -> 0 | N8: =SUMIFS(Cash_Book!$G$4:$G$1008,Cash_Book!$C$4:$C$1008,"BEPAARI",Cash_Book!$D$4:$D$1008,"CASH_ADV",Cash_Book!$E$4:$E$1008,B8) -> 0 | O8: =SUMIFS(Cash_Book!$G$4:$G$1008,Cash_Book!$C$4:$C$1008,"BEPAARI",Cash_Book!$D$4:$D$1008,"OTHER",Cash_Book!$E$4:$E$1008,B8) -> 0 | P8: =SUM(H8:O8) -> 0 | Q8: =IF(B8="","",F8-P8+E8) -> 0 | R8: =SUMIFS(Cash_Book!$G$4:$G$1008,Cash_Book!$C$4:$C$1008,"BEPAARI",Cash_Book!$D$4:$D$1008,"PAYMENT",Cash_Book!$E$4:$E$1008,B8) -> 0 | S8: =IF(B8="","",Q8-R8) -> 0
A9: 5 | B9: =IF(Masters!$B$7="","",Masters!$B$7) -> GAYYUR | C9: =IF(B9="","",Masters!$C$7) -> 4 | D9: =IF(B9="","",IF(Masters!$D$7="","",Masters!$D$7)) | E9: =IF(B9="",0,Masters!$E$7) -> 142530 | F9: =SUMIF(Daily_Sales!$C$4:$C$503,B9,Daily_Sales!$G$4:$G$503) -> 439750 | G9: =SUMIF(Daily_Sales!$C$4:$C$503,B9,Daily_Sales!$E$4:$E$503) -> 37 | H9: =IF(B9="",0,IF(D9<>"",D9*G9,F9*C9/100)) -> 17590 | I9: =IF(G9>0,Masters!$Y$3,0) -> 100 | J9: =G9*Masters!$Y$4 -> 370 | K9: =SUMIFS(Cash_Book!$G$4:$G$1008,Cash_Book!$C$4:$C$1008,"BEPAARI",Cash_Book!$D$4:$D$1008,"MOTOR",Cash_Book!$E$4:$E$1008,B9) -> 10320 | L9: =SUMIFS(Cash_Book!$G$4:$G$1008,Cash_Book!$C$4:$C$1008,"BEPAARI",Cash_Book!$D$4:$D$1008,"BHUSSA",Cash_Book!$E$4:$E$1008,B9) -> 0 | M9: =SUMIFS(Cash_Book!$G$4:$G$1008,Cash_Book!$C$4:$C$1008,"BEPAARI",Cash_Book!$D$4:$D$1008,"GAWALI",Cash_Book!$E$4:$E$1008,B9) -> 8660 | N9: =SUMIFS(Cash_Book!$G$4:$G$1008,Cash_Book!$C$4:$C$1008,"BEPAARI",Cash_Book!$D$4:$D$1008,"CASH_ADV",Cash_Book!$E$4:$E$1008,B9) -> 0 | O9: =SUMIFS(Cash_Book!$G$4:$G$1008,Cash_Book!$C$4:$C$1008,"BEPAARI",Cash_Book!$D$4:$D$1008,"OTHER",Cash_Book!$E$4:$E$1008,B9) -> 0 | P9: =SUM(H9:O9) -> 37040 | Q9: =IF(B9="","",F9-P9+E9) -> 545240 | R9: =SUMIFS(Cash_Book!$G$4:$G$1008,Cash_Book!$C$4:$C$1008,"BEPAARI",Cash_Book!$D$4:$D$1008,"PAYMENT",Cash_Book!$E$4:$E$1008,B9) -> 282530 | S9: =IF(B9="","",Q9-R9) -> 262710
A10: 6 | B10: =IF(Masters!$B$8="","",Masters!$B$8) -> KISHOR | C10: =IF(B10="","",Masters!$C$8) -> 4 | D10: =IF(B10="","",IF(Masters!$D$8="","",Masters!$D$8)) | E10: =IF(B10="",0,Masters!$E$8) -> -152964 | F10: =SUMIF(Daily_Sales!$C$4:$C$503,B10,Daily_Sales!$G$4:$G$503) -> 464000 | G10: =SUMIF(Daily_Sales!$C$4:$C$503,B10,Daily_Sales!$E$4:$E$503) -> 32 | H10: =IF(B10="",0,IF(D10<>"",D10*G10,F10*C10/100)) -> 18560 | I10: =IF(G10>0,Masters!$Y$3,0) -> 100 | J10: =G10*Masters!$Y$4 -> 320 | K10: =SUMIFS(Cash_Book!$G$4:$G$1008,Cash_Book!$C$4:$C$1008,"BEPAARI",Cash_Book!$D$4:$D$1008,"MOTOR",Cash_Book!$E$4:$E$1008,B10) -> 7680 | L10: =SUMIFS(Cash_Book!$G$4:$G$1008,Cash_Book!$C$4:$C$1008,"BEPAARI",Cash_Book!$D$4:$D$1008,"BHUSSA",Cash_Book!$E$4:$E$1008,B10) -> 150 | M10: =SUMIFS(Cash_Book!$G$4:$G$1008,Cash_Book!$C$4:$C$1008,"BEPAARI",Cash_Book!$D$4:$D$1008,"GAWALI",Cash_Book!$E$4:$E$1008,B10) -> 1920 | N10: =SUMIFS(Cash_Book!$G$4:$G$1008,Cash_Book!$C$4:$C$1008,"BEPAARI",Cash_Book!$D$4:$D$1008,"CASH_ADV",Cash_Book!$E$4:$E$1008,B10) -> 0 | O10: =SUMIFS(Cash_Book!$G$4:$G$1008,Cash_Book!$C$4:$C$1008,"BEPAARI",Cash_Book!$D$4:$D$1008,"OTHER",Cash_Book!$E$4:$E$1008,B10) -> 0 | P10: =SUM(H10:O10) -> 28730 | Q10: =IF(B10="","",F10-P10+E10) -> 282306 | R10: =SUMIFS(Cash_Book!$G$4:$G$1008,Cash_Book!$C$4:$C$1008,"BEPAARI",Cash_Book!$D$4:$D$1008,"PAYMENT",Cash_Book!$E$4:$E$1008,B10) -> 280000 | S10: =IF(B10="","",Q10-R10) -> 2306
A11: 7 | B11: =IF(Masters!$B$9="","",Masters!$B$9) -> MAULANA | C11: =IF(B11="","",Masters!$C$9) -> 4 | D11: =IF(B11="","",IF(Masters!$D$9="","",Masters!$D$9)) | E11: =IF(B11="",0,Masters!$E$9) -> 35330 | F11: =SUMIF(Daily_Sales!$C$4:$C$503,B11,Daily_Sales!$G$4:$G$503) -> 444350 | G11: =SUMIF(Daily_Sales!$C$4:$C$503,B11,Daily_Sales!$E$4:$E$503) -> 41 | H11: =IF(B11="",0,IF(D11<>"",D11*G11,F11*C11/100)) -> 17774 | I11: =IF(G11>0,Masters!$Y$3,0) -> 100 | J11: =G11*Masters!$Y$4 -> 410 | K11: =SUMIFS(Cash_Book!$G$4:$G$1008,Cash_Book!$C$4:$C$1008,"BEPAARI",Cash_Book!$D$4:$D$1008,"MOTOR",Cash_Book!$E$4:$E$1008,B11) -> 10100 | L11: =SUMIFS(Cash_Book!$G$4:$G$1008,Cash_Book!$C$4:$C$1008,"BEPAARI",Cash_Book!$D$4:$D$1008,"BHUSSA",Cash_Book!$E$4:$E$1008,B11) -> 0 | M11: =SUMIFS(Cash_Book!$G$4:$G$1008,Cash_Book!$C$4:$C$1008,"BEPAARI",Cash_Book!$D$4:$D$1008,"GAWALI",Cash_Book!$E$4:$E$1008,B11) -> 2460 | N11: =SUMIFS(Cash_Book!$G$4:$G$1008,Cash_Book!$C$4:$C$1008,"BEPAARI",Cash_Book!$D$4:$D$1008,"CASH_ADV",Cash_Book!$E$4:$E$1008,B11) -> 0 | O11: =SUMIFS(Cash_Book!$G$4:$G$1008,Cash_Book!$C$4:$C$1008,"BEPAARI",Cash_Book!$D$4:$D$1008,"OTHER",Cash_Book!$E$4:$E$1008,B11) -> 0 | P11: =SUM(H11:O11) -> 30844 | Q11: =IF(B11="","",F11-P11+E11) -> 448836 | R11: =SUMIFS(Cash_Book!$G$4:$G$1008,Cash_Book!$C$4:$C$1008,"BEPAARI",Cash_Book!$D$4:$D$1008,"PAYMENT",Cash_Book!$E$4:$E$1008,B11) -> 300000 | S11: =IF(B11="","",Q11-R11) -> 148836
A12: 8 | B12: =IF(Masters!$B$10="","",Masters!$B$10) -> SALIM RAJ | C12: =IF(B12="","",Masters!$C$10) -> 4 | D12: =IF(B12="","",IF(Masters!$D$10="","",Masters!$D$10)) | E12: =IF(B12="",0,Masters!$E$10) -> 0 | F12: =SUMIF(Daily_Sales!$C$4:$C$503,B12,Daily_Sales!$G$4:$G$503) -> 195500 | G12: =SUMIF(Daily_Sales!$C$4:$C$503,B12,Daily_Sales!$E$4:$E$503) -> 17 | H12: =IF(B12="",0,IF(D12<>"",D12*G12,F12*C12/100)) -> 7820 | I12: =IF(G12>0,Masters!$Y$3,0) -> 100 | J12: =G12*Masters!$Y$4 -> 170 | K12: =SUMIFS(Cash_Book!$G$4:$G$1008,Cash_Book!$C$4:$C$1008,"BEPAARI",Cash_Book!$D$4:$D$1008,"MOTOR",Cash_Book!$E$4:$E$1008,B12) -> 4080 | L12: =SUMIFS(Cash_Book!$G$4:$G$1008,Cash_Book!$C$4:$C$1008,"BEPAARI",Cash_Book!$D$4:$D$1008,"BHUSSA",Cash_Book!$E$4:$E$1008,B12) -> 0 | M12: =SUMIFS(Cash_Book!$G$4:$G$1008,Cash_Book!$C$4:$C$1008,"BEPAARI",Cash_Book!$D$4:$D$1008,"GAWALI",Cash_Book!$E$4:$E$1008,B12) -> 1020 | N12: =SUMIFS(Cash_Book!$G$4:$G$1008,Cash_Book!$C$4:$C$1008,"BEPAARI",Cash_Book!$D$4:$D$1008,"CASH_ADV",Cash_Book!$E$4:$E$1008,B12) -> 0 | O12: =SUMIFS(Cash_Book!$G$4:$G$1008,Cash_Book!$C$4:$C$1008,"BEPAARI",Cash_Book!$D$4:$D$1008,"OTHER",Cash_Book!$E$4:$E$1008,B12) -> 0 | P12: =SUM(H12:O12) -> 13190 | Q12: =IF(B12="","",F12-P12+E12) -> 182310 | R12: =SUMIFS(Cash_Book!$G$4:$G$1008,Cash_Book!$C$4:$C$1008,"BEPAARI",Cash_Book!$D$4:$D$1008,"PAYMENT",Cash_Book!$E$4:$E$1008,B12) -> 0 | S12: =IF(B12="","",Q12-R12) -> 182310
A13: 9 | B13: =IF(Masters!$B$11="","",Masters!$B$11) -> ANAS RAJ | C13: =IF(B13="","",Masters!$C$11) -> 4 | D13: =IF(B13="","",IF(Masters!$D$11="","",Masters!$D$11)) | E13: =IF(B13="",0,Masters!$E$11) -> 0 | F13: =SUMIF(Daily_Sales!$C$4:$C$503,B13,Daily_Sales!$G$4:$G$503) -> 334600 | G13: =SUMIF(Daily_Sales!$C$4:$C$503,B13,Daily_Sales!$E$4:$E$503) -> 33 | H13: =IF(B13="",0,IF(D13<>"",D13*G13,F13*C13/100)) -> 13384 | I13: =IF(G13>0,Masters!$Y$3,0) -> 100 | J13: =G13*Masters!$Y$4 -> 330 | K13: =SUMIFS(Cash_Book!$G$4:$G$1008,Cash_Book!$C$4:$C$1008,"BEPAARI",Cash_Book!$D$4:$D$1008,"MOTOR",Cash_Book!$E$4:$E$1008,B13) -> 7920 | L13: =SUMIFS(Cash_Book!$G$4:$G$1008,Cash_Book!$C$4:$C$1008,"BEPAARI",Cash_Book!$D$4:$D$1008,"BHUSSA",Cash_Book!$E$4:$E$1008,B13) -> 200 | M13: =SUMIFS(Cash_Book!$G$4:$G$1008,Cash_Book!$C$4:$C$1008,"BEPAARI",Cash_Book!$D$4:$D$1008,"GAWALI",Cash_Book!$E$4:$E$1008,B13) -> 1980 | N13: =SUMIFS(Cash_Book!$G$4:$G$1008,Cash_Book!$C$4:$C$1008,"BEPAARI",Cash_Book!$D$4:$D$1008,"CASH_ADV",Cash_Book!$E$4:$E$1008,B13) -> 0 | O13: =SUMIFS(Cash_Book!$G$4:$G$1008,Cash_Book!$C$4:$C$1008,"BEPAARI",Cash_Book!$D$4:$D$1008,"OTHER",Cash_Book!$E$4:$E$1008,B13) -> 0 | P13: =SUM(H13:O13) -> 23914 | Q13: =IF(B13="","",F13-P13+E13) -> 310686 | R13: =SUMIFS(Cash_Book!$G$4:$G$1008,Cash_Book!$C$4:$C$1008,"BEPAARI",Cash_Book!$D$4:$D$1008,"PAYMENT",Cash_Book!$E$4:$E$1008,B13) -> 310686 | S13: =IF(B13="","",Q13-R13) -> 0
A14: 10 | B14: =IF(Masters!$B$12="","",Masters!$B$12) -> AYAZ | C14: =IF(B14="","",Masters!$C$12) -> 4 | D14: =IF(B14="","",IF(Masters!$D$12="","",Masters!$D$12)) | E14: =IF(B14="",0,Masters!$E$12) -> 1530 | F14: =SUMIF(Daily_Sales!$C$4:$C$503,B14,Daily_Sales!$G$4:$G$503) -> 0 | G14: =SUMIF(Daily_Sales!$C$4:$C$503,B14,Daily_Sales!$E$4:$E$503) -> 0 | H14: =IF(B14="",0,IF(D14<>"",D14*G14,F14*C14/100)) -> 0 | I14: =IF(G14>0,Masters!$Y$3,0) -> 0 | J14: =G14*Masters!$Y$4 -> 0 | K14: =SUMIFS(Cash_Book!$G$4:$G$1008,Cash_Book!$C$4:$C$1008,"BEPAARI",Cash_Book!$D$4:$D$1008,"MOTOR",Cash_Book!$E$4:$E$1008,B14) -> 0 | L14: =SUMIFS(Cash_Book!$G$4:$G$1008,Cash_Book!$C$4:$C$1008,"BEPAARI",Cash_Book!$D$4:$D$1008,"BHUSSA",Cash_Book!$E$4:$E$1008,B14) -> 0 | M14: =SUMIFS(Cash_Book!$G$4:$G$1008,Cash_Book!$C$4:$C$1008,"BEPAARI",Cash_Book!$D$4:$D$1008,"GAWALI",Cash_Book!$E$4:$E$1008,B14) -> 0 | N14: =SUMIFS(Cash_Book!$G$4:$G$1008,Cash_Book!$C$4:$C$1008,"BEPAARI",Cash_Book!$D$4:$D$1008,"CASH_ADV",Cash_Book!$E$4:$E$1008,B14) -> 0 | O14: =SUMIFS(Cash_Book!$G$4:$G$1008,Cash_Book!$C$4:$C$1008,"BEPAARI",Cash_Book!$D$4:$D$1008,"OTHER",Cash_Book!$E$4:$E$1008,B14) -> 0 | P14: =SUM(H14:O14) -> 0 | Q14: =IF(B14="","",F14-P14+E14) -> 1530 | R14: =SUMIFS(Cash_Book!$G$4:$G$1008,Cash_Book!$C$4:$C$1008,"BEPAARI",Cash_Book!$D$4:$D$1008,"PAYMENT",Cash_Book!$E$4:$E$1008,B14) -> 0 | S14: =IF(B14="","",Q14-R14) -> 1530
A15: 11 | B15: =IF(Masters!$B$13="","",Masters!$B$13) -> NEERAJ | C15: =IF(B15="","",Masters!$C$13) -> 4 | D15: =IF(B15="","",IF(Masters!$D$13="","",Masters!$D$13)) | E15: =IF(B15="",0,Masters!$E$13) -> 0 | F15: =SUMIF(Daily_Sales!$C$4:$C$503,B15,Daily_Sales!$G$4:$G$503) -> 320800 | G15: =SUMIF(Daily_Sales!$C$4:$C$503,B15,Daily_Sales!$E$4:$E$503) -> 35 | H15: =IF(B15="",0,IF(D15<>"",D15*G15,F15*C15/100)) -> 12832 | I15: =IF(G15>0,Masters!$Y$3,0) -> 100 | J15: =G15*Masters!$Y$4 -> 350 | K15: =SUMIFS(Cash_Book!$G$4:$G$1008,Cash_Book!$C$4:$C$1008,"BEPAARI",Cash_Book!$D$4:$D$1008,"MOTOR",Cash_Book!$E$4:$E$1008,B15) -> 8400 | L15: =SUMIFS(Cash_Book!$G$4:$G$1008,Cash_Book!$C$4:$C$1008,"BEPAARI",Cash_Book!$D$4:$D$1008,"BHUSSA",Cash_Book!$E$4:$E$1008,B15) -> 0 | M15: =SUMIFS(Cash_Book!$G$4:$G$1008,Cash_Book!$C$4:$C$1008,"BEPAARI",Cash_Book!$D$4:$D$1008,"GAWALI",Cash_Book!$E$4:$E$1008,B15) -> 5300 | N15: =SUMIFS(Cash_Book!$G$4:$G$1008,Cash_Book!$C$4:$C$1008,"BEPAARI",Cash_Book!$D$4:$D$1008,"CASH_ADV",Cash_Book!$E$4:$E$1008,B15) -> 0 | O15: =SUMIFS(Cash_Book!$G$4:$G$1008,Cash_Book!$C$4:$C$1008,"BEPAARI",Cash_Book!$D$4:$D$1008,"OTHER",Cash_Book!$E$4:$E$1008,B15) -> 0 | P15: =SUM(H15:O15) -> 26982 | Q15: =IF(B15="","",F15-P15+E15) -> 293818 | R15: =SUMIFS(Cash_Book!$G$4:$G$1008,Cash_Book!$C$4:$C$1008,"BEPAARI",Cash_Book!$D$4:$D$1008,"PAYMENT",Cash_Book!$E$4:$E$1008,B15) -> 232670 | S15: =IF(B15="","",Q15-R15) -> 61148
A16: 12 | B16: =IF(Masters!$B$14="","",Masters!$B$14) -> CHINTU SHUJALPUR | C16: =IF(B16="","",Masters!$C$14) -> 4 | D16: =IF(B16="","",IF(Masters!$D$14="","",Masters!$D$14)) | E16: =IF(B16="",0,Masters!$E$14) -> 0 | F16: =SUMIF(Daily_Sales!$C$4:$C$503,B16,Daily_Sales!$G$4:$G$503) -> 574300 | G16: =SUMIF(Daily_Sales!$C$4:$C$503,B16,Daily_Sales!$E$4:$E$503) -> 58 | H16: =IF(B16="",0,IF(D16<>"",D16*G16,F16*C16/100)) -> 22972 | I16: =IF(G16>0,Masters!$Y$3,0) -> 100 | J16: =G16*Masters!$Y$4 -> 580 | K16: =SUMIFS(Cash_Book!$G$4:$G$1008,Cash_Book!$C$4:$C$1008,"BEPAARI",Cash_Book!$D$4:$D$1008,"MOTOR",Cash_Book!$E$4:$E$1008,B16) -> 15600 | L16: =SUMIFS(Cash_Book!$G$4:$G$1008,Cash_Book!$C$4:$C$1008,"BEPAARI",Cash_Book!$D$4:$D$1008,"BHUSSA",Cash_Book!$E$4:$E$1008,B16) -> 400 | M16: =SUMIFS(Cash_Book!$G$4:$G$1008,Cash_Book!$C$4:$C$1008,"BEPAARI",Cash_Book!$D$4:$D$1008,"GAWALI",Cash_Book!$E$4:$E$1008,B16) -> 3540 | N16: =SUMIFS(Cash_Book!$G$4:$G$1008,Cash_Book!$C$4:$C$1008,"BEPAARI",Cash_Book!$D$4:$D$1008,"CASH_ADV",Cash_Book!$E$4:$E$1008,B16) -> 0 | O16: =SUMIFS(Cash_Book!$G$4:$G$1008,Cash_Book!$C$4:$C$1008,"BEPAARI",Cash_Book!$D$4:$D$1008,"OTHER",Cash_Book!$E$4:$E$1008,B16) -> 0 | P16: =SUM(H16:O16) -> 43192 | Q16: =IF(B16="","",F16-P16+E16) -> 531108 | R16: =SUMIFS(Cash_Book!$G$4:$G$1008,Cash_Book!$C$4:$C$1008,"BEPAARI",Cash_Book!$D$4:$D$1008,"PAYMENT",Cash_Book!$E$4:$E$1008,B16) -> 460024 | S16: =IF(B16="","",Q16-R16) -> 71084
A17: 13 | B17: =IF(Masters!$B$15="","",Masters!$B$15) -> SANNA | C17: =IF(B17="","",Masters!$C$15) -> 4 | D17: =IF(B17="","",IF(Masters!$D$15="","",Masters!$D$15)) | E17: =IF(B17="",0,Masters!$E$15) -> -14048 | F17: =SUMIF(Daily_Sales!$C$4:$C$503,B17,Daily_Sales!$G$4:$G$503) -> 0 | G17: =SUMIF(Daily_Sales!$C$4:$C$503,B17,Daily_Sales!$E$4:$E$503) -> 0 | H17: =IF(B17="",0,IF(D17<>"",D17*G17,F17*C17/100)) -> 0 | I17: =IF(G17>0,Masters!$Y$3,0) -> 0 | J17: =G17*Masters!$Y$4 -> 0 | K17: =SUMIFS(Cash_Book!$G$4:$G$1008,Cash_Book!$C$4:$C$1008,"BEPAARI",Cash_Book!$D$4:$D$1008,"MOTOR",Cash_Book!$E$4:$E$1008,B17) -> 0 | L17: =SUMIFS(Cash_Book!$G$4:$G$1008,Cash_Book!$C$4:$C$1008,"BEPAARI",Cash_Book!$D$4:$D$1008,"BHUSSA",Cash_Book!$E$4:$E$1008,B17) -> 0 | M17: =SUMIFS(Cash_Book!$G$4:$G$1008,Cash_Book!$C$4:$C$1008,"BEPAARI",Cash_Book!$D$4:$D$1008,"GAWALI",Cash_Book!$E$4:$E$1008,B17) -> 0 | N17: =SUMIFS(Cash_Book!$G$4:$G$1008,Cash_Book!$C$4:$C$1008,"BEPAARI",Cash_Book!$D$4:$D$1008,"CASH_ADV",Cash_Book!$E$4:$E$1008,B17) -> 0 | O17: =SUMIFS(Cash_Book!$G$4:$G$1008,Cash_Book!$C$4:$C$1008,"BEPAARI",Cash_Book!$D$4:$D$1008,"OTHER",Cash_Book!$E$4:$E$1008,B17) -> 0 | P17: =SUM(H17:O17) -> 0 | Q17: =IF(B17="","",F17-P17+E17) -> -14048 | R17: =SUMIFS(Cash_Book!$G$4:$G$1008,Cash_Book!$C$4:$C$1008,"BEPAARI",Cash_Book!$D$4:$D$1008,"PAYMENT",Cash_Book!$E$4:$E$1008,B17) -> 0 | S17: =IF(B17="","",Q17-R17) -> -14048
A18: 14 | B18: =IF(Masters!$B$16="","",Masters!$B$16) -> WAHID | C18: =IF(B18="","",Masters!$C$16) -> 4 | D18: =IF(B18="","",IF(Masters!$D$16="","",Masters!$D$16)) | E18: =IF(B18="",0,Masters!$E$16) -> -4661 | F18: =SUMIF(Daily_Sales!$C$4:$C$503,B18,Daily_Sales!$G$4:$G$503) -> 0 | G18: =SUMIF(Daily_Sales!$C$4:$C$503,B18,Daily_Sales!$E$4:$E$503) -> 0 | H18: =IF(B18="",0,IF(D18<>"",D18*G18,F18*C18/100)) -> 0 | I18: =IF(G18>0,Masters!$Y$3,0) -> 0 | J18: =G18*Masters!$Y$4 -> 0 | K18: =SUMIFS(Cash_Book!$G$4:$G$1008,Cash_Book!$C$4:$C$1008,"BEPAARI",Cash_Book!$D$4:$D$1008,"MOTOR",Cash_Book!$E$4:$E$1008,B18) -> 0 | L18: =SUMIFS(Cash_Book!$G$4:$G$1008,Cash_Book!$C$4:$C$1008,"BEPAARI",Cash_Book!$D$4:$D$1008,"BHUSSA",Cash_Book!$E$4:$E$1008,B18) -> 0 | M18: =SUMIFS(Cash_Book!$G$4:$G$1008,Cash_Book!$C$4:$C$1008,"BEPAARI",Cash_Book!$D$4:$D$1008,"GAWALI",Cash_Book!$E$4:$E$1008,B18) -> 0 | N18: =SUMIFS(Cash_Book!$G$4:$G$1008,Cash_Book!$C$4:$C$1008,"BEPAARI",Cash_Book!$D$4:$D$1008,"CASH_ADV",Cash_Book!$E$4:$E$1008,B18) -> 0 | O18: =SUMIFS(Cash_Book!$G$4:$G$1008,Cash_Book!$C$4:$C$1008,"BEPAARI",Cash_Book!$D$4:$D$1008,"OTHER",Cash_Book!$E$4:$E$1008,B18) -> 0 | P18: =SUM(H18:O18) -> 0 | Q18: =IF(B18="","",F18-P18+E18) -> -4661 | R18: =SUMIFS(Cash_Book!$G$4:$G$1008,Cash_Book!$C$4:$C$1008,"BEPAARI",Cash_Book!$D$4:$D$1008,"PAYMENT",Cash_Book!$E$4:$E$1008,B18) -> 0 | S18: =IF(B18="","",Q18-R18) -> -4661
A19: 15 | B19: =IF(Masters!$B$17="","",Masters!$B$17) -> MANSOOR | C19: =IF(B19="","",Masters!$C$17) -> 4 | D19: =IF(B19="","",IF(Masters!$D$17="","",Masters!$D$17)) | E19: =IF(B19="",0,Masters!$E$17) -> -9845 | F19: =SUMIF(Daily_Sales!$C$4:$C$503,B19,Daily_Sales!$G$4:$G$503) -> 0 | G19: =SUMIF(Daily_Sales!$C$4:$C$503,B19,Daily_Sales!$E$4:$E$503) -> 0 | H19: =IF(B19="",0,IF(D19<>"",D19*G19,F19*C19/100)) -> 0 | I19: =IF(G19>0,Masters!$Y$3,0) -> 0 | J19: =G19*Masters!$Y$4 -> 0 | K19: =SUMIFS(Cash_Book!$G$4:$G$1008,Cash_Book!$C$4:$C$1008,"BEPAARI",Cash_Book!$D$4:$D$1008,"MOTOR",Cash_Book!$E$4:$E$1008,B19) -> 0 | L19: =SUMIFS(Cash_Book!$G$4:$G$1008,Cash_Book!$C$4:$C$1008,"BEPAARI",Cash_Book!$D$4:$D$1008,"BHUSSA",Cash_Book!$E$4:$E$1008,B19) -> 0 | M19: =SUMIFS(Cash_Book!$G$4:$G$1008,Cash_Book!$C$4:$C$1008,"BEPAARI",Cash_Book!$D$4:$D$1008,"GAWALI",Cash_Book!$E$4:$E$1008,B19) -> 0 | N19: =SUMIFS(Cash_Book!$G$4:$G$1008,Cash_Book!$C$4:$C$1008,"BEPAARI",Cash_Book!$D$4:$D$1008,"CASH_ADV",Cash_Book!$E$4:$E$1008,B19) -> 0 | O19: =SUMIFS(Cash_Book!$G$4:$G$1008,Cash_Book!$C$4:$C$1008,"BEPAARI",Cash_Book!$D$4:$D$1008,"OTHER",Cash_Book!$E$4:$E$1008,B19) -> 0 | P19: =SUM(H19:O19) -> 0 | Q19: =IF(B19="","",F19-P19+E19) -> -9845 | R19: =SUMIFS(Cash_Book!$G$4:$G$1008,Cash_Book!$C$4:$C$1008,"BEPAARI",Cash_Book!$D$4:$D$1008,"PAYMENT",Cash_Book!$E$4:$E$1008,B19) -> 0 | S19: =IF(B19="","",Q19-R19) -> -9845
A20: 16 | B20: =IF(Masters!$B$18="","",Masters!$B$18) -> AYAZ PREVIOUS BAL | C20: =IF(B20="","",Masters!$C$18) -> 4 | D20: =IF(B20="","",IF(Masters!$D$18="","",Masters!$D$18)) | E20: =IF(B20="",0,Masters!$E$18) -> -88000 | F20: =SUMIF(Daily_Sales!$C$4:$C$503,B20,Daily_Sales!$G$4:$G$503) -> 0 | G20: =SUMIF(Daily_Sales!$C$4:$C$503,B20,Daily_Sales!$E$4:$E$503) -> 0 | H20: =IF(B20="",0,IF(D20<>"",D20*G20,F20*C20/100)) -> 0 | I20: =IF(G20>0,Masters!$Y$3,0) -> 0 | J20: =G20*Masters!$Y$4 -> 0 | K20: =SUMIFS(Cash_Book!$G$4:$G$1008,Cash_Book!$C$4:$C$1008,"BEPAARI",Cash_Book!$D$4:$D$1008,"MOTOR",Cash_Book!$E$4:$E$1008,B20) -> 0 | L20: =SUMIFS(Cash_Book!$G$4:$G$1008,Cash_Book!$C$4:$C$1008,"BEPAARI",Cash_Book!$D$4:$D$1008,"BHUSSA",Cash_Book!$E$4:$E$1008,B20) -> 0 | M20: =SUMIFS(Cash_Book!$G$4:$G$1008,Cash_Book!$C$4:$C$1008,"BEPAARI",Cash_Book!$D$4:$D$1008,"GAWALI",Cash_Book!$E$4:$E$1008,B20) -> 0 | N20: =SUMIFS(Cash_Book!$G$4:$G$1008,Cash_Book!$C$4:$C$1008,"BEPAARI",Cash_Book!$D$4:$D$1008,"CASH_ADV",Cash_Book!$E$4:$E$1008,B20) -> 0 | O20: =SUMIFS(Cash_Book!$G$4:$G$1008,Cash_Book!$C$4:$C$1008,"BEPAARI",Cash_Book!$D$4:$D$1008,"OTHER",Cash_Book!$E$4:$E$1008,B20) -> 0 | P20: =SUM(H20:O20) -> 0 | Q20: =IF(B20="","",F20-P20+E20) -> -88000 | R20: =SUMIFS(Cash_Book!$G$4:$G$1008,Cash_Book!$C$4:$C$1008,"BEPAARI",Cash_Book!$D$4:$D$1008,"PAYMENT",Cash_Book!$E$4:$E$1008,B20) -> 0 | S20: =IF(B20="","",Q20-R20) -> -88000
A21: 17 | B21: =IF(Masters!$B$19="","",Masters!$B$19) -> SHAKIL SHUJALPUR | C21: =IF(B21="","",Masters!$C$19) -> 4 | D21: =IF(B21="","",IF(Masters!$D$19="","",Masters!$D$19)) | E21: =IF(B21="",0,Masters!$E$19) -> 660 | F21: =SUMIF(Daily_Sales!$C$4:$C$503,B21,Daily_Sales!$G$4:$G$503) -> 0 | G21: =SUMIF(Daily_Sales!$C$4:$C$503,B21,Daily_Sales!$E$4:$E$503) -> 0 | H21: =IF(B21="",0,IF(D21<>"",D21*G21,F21*C21/100)) -> 0 | I21: =IF(G21>0,Masters!$Y$3,0) -> 0 | J21: =G21*Masters!$Y$4 -> 0 | K21: =SUMIFS(Cash_Book!$G$4:$G$1008,Cash_Book!$C$4:$C$1008,"BEPAARI",Cash_Book!$D$4:$D$1008,"MOTOR",Cash_Book!$E$4:$E$1008,B21) -> 0 | L21: =SUMIFS(Cash_Book!$G$4:$G$1008,Cash_Book!$C$4:$C$1008,"BEPAARI",Cash_Book!$D$4:$D$1008,"BHUSSA",Cash_Book!$E$4:$E$1008,B21) -> 0 | M21: =SUMIFS(Cash_Book!$G$4:$G$1008,Cash_Book!$C$4:$C$1008,"BEPAARI",Cash_Book!$D$4:$D$1008,"GAWALI",Cash_Book!$E$4:$E$1008,B21) -> 0 | N21: =SUMIFS(Cash_Book!$G$4:$G$1008,Cash_Book!$C$4:$C$1008,"BEPAARI",Cash_Book!$D$4:$D$1008,"CASH_ADV",Cash_Book!$E$4:$E$1008,B21) -> 0 | O21: =SUMIFS(Cash_Book!$G$4:$G$1008,Cash_Book!$C$4:$C$1008,"BEPAARI",Cash_Book!$D$4:$D$1008,"OTHER",Cash_Book!$E$4:$E$1008,B21) -> 0 | P21: =SUM(H21:O21) -> 0 | Q21: =IF(B21="","",F21-P21+E21) -> 660 | R21: =SUMIFS(Cash_Book!$G$4:$G$1008,Cash_Book!$C$4:$C$1008,"BEPAARI",Cash_Book!$D$4:$D$1008,"PAYMENT",Cash_Book!$E$4:$E$1008,B21) -> 0 | S21: =IF(B21="","",Q21-R21) -> 660
A22: 18 | B22: =IF(Masters!$B$20="","",Masters!$B$20) -> USMAN | C22: =IF(B22="","",Masters!$C$20) -> 4 | D22: =IF(B22="","",IF(Masters!$D$20="","",Masters!$D$20)) | E22: =IF(B22="",0,Masters!$E$20) -> 40440 | F22: =SUMIF(Daily_Sales!$C$4:$C$503,B22,Daily_Sales!$G$4:$G$503) -> 225000 | G22: =SUMIF(Daily_Sales!$C$4:$C$503,B22,Daily_Sales!$E$4:$E$503) -> 15 | H22: =IF(B22="",0,IF(D22<>"",D22*G22,F22*C22/100)) -> 9000 | I22: =IF(G22>0,Masters!$Y$3,0) -> 100 | J22: =G22*Masters!$Y$4 -> 150 | K22: =SUMIFS(Cash_Book!$G$4:$G$1008,Cash_Book!$C$4:$C$1008,"BEPAARI",Cash_Book!$D$4:$D$1008,"MOTOR",Cash_Book!$E$4:$E$1008,B22) -> 8090 | L22: =SUMIFS(Cash_Book!$G$4:$G$1008,Cash_Book!$C$4:$C$1008,"BEPAARI",Cash_Book!$D$4:$D$1008,"BHUSSA",Cash_Book!$E$4:$E$1008,B22) -> 130 | M22: =SUMIFS(Cash_Book!$G$4:$G$1008,Cash_Book!$C$4:$C$1008,"BEPAARI",Cash_Book!$D$4:$D$1008,"GAWALI",Cash_Book!$E$4:$E$1008,B22) -> 1980 | N22: =SUMIFS(Cash_Book!$G$4:$G$1008,Cash_Book!$C$4:$C$1008,"BEPAARI",Cash_Book!$D$4:$D$1008,"CASH_ADV",Cash_Book!$E$4:$E$1008,B22) -> 0 | O22: =SUMIFS(Cash_Book!$G$4:$G$1008,Cash_Book!$C$4:$C$1008,"BEPAARI",Cash_Book!$D$4:$D$1008,"OTHER",Cash_Book!$E$4:$E$1008,B22) -> 0 | P22: =SUM(H22:O22) -> 19450 | Q22: =IF(B22="","",F22-P22+E22) -> 245990 | R22: =SUMIFS(Cash_Book!$G$4:$G$1008,Cash_Book!$C$4:$C$1008,"BEPAARI",Cash_Book!$D$4:$D$1008,"PAYMENT",Cash_Book!$E$4:$E$1008,B22) -> 240000 | S22: =IF(B22="","",Q22-R22) -> 5990
A23: 19 | B23: =IF(Masters!$B$21="","",Masters!$B$21) -> JUNAID AMANAT | C23: =IF(B23="","",Masters!$C$21) -> 4 | D23: =IF(B23="","",IF(Masters!$D$21="","",Masters!$D$21)) | E23: =IF(B23="",0,Masters!$E$21) -> -100000 | F23: =SUMIF(Daily_Sales!$C$4:$C$503,B23,Daily_Sales!$G$4:$G$503) -> 0 | G23: =SUMIF(Daily_Sales!$C$4:$C$503,B23,Daily_Sales!$E$4:$E$503) -> 0 | H23: =IF(B23="",0,IF(D23<>"",D23*G23,F23*C23/100)) -> 0 | I23: =IF(G23>0,Masters!$Y$3,0) -> 0 | J23: =G23*Masters!$Y$4 -> 0 | K23: =SUMIFS(Cash_Book!$G$4:$G$1008,Cash_Book!$C$4:$C$1008,"BEPAARI",Cash_Book!$D$4:$D$1008,"MOTOR",Cash_Book!$E$4:$E$1008,B23) -> 0 | L23: =SUMIFS(Cash_Book!$G$4:$G$1008,Cash_Book!$C$4:$C$1008,"BEPAARI",Cash_Book!$D$4:$D$1008,"BHUSSA",Cash_Book!$E$4:$E$1008,B23) -> 0 | M23: =SUMIFS(Cash_Book!$G$4:$G$1008,Cash_Book!$C$4:$C$1008,"BEPAARI",Cash_Book!$D$4:$D$1008,"GAWALI",Cash_Book!$E$4:$E$1008,B23) -> 0 | N23: =SUMIFS(Cash_Book!$G$4:$G$1008,Cash_Book!$C$4:$C$1008,"BEPAARI",Cash_Book!$D$4:$D$1008,"CASH_ADV",Cash_Book!$E$4:$E$1008,B23) -> 0 | O23: =SUMIFS(Cash_Book!$G$4:$G$1008,Cash_Book!$C$4:$C$1008,"BEPAARI",Cash_Book!$D$4:$D$1008,"OTHER",Cash_Book!$E$4:$E$1008,B23) -> 0 | P23: =SUM(H23:O23) -> 0 | Q23: =IF(B23="","",F23-P23+E23) -> -100000 | R23: =SUMIFS(Cash_Book!$G$4:$G$1008,Cash_Book!$C$4:$C$1008,"BEPAARI",Cash_Book!$D$4:$D$1008,"PAYMENT",Cash_Book!$E$4:$E$1008,B23) -> 0 | S23: =IF(B23="","",Q23-R23) -> -100000
A24: 20 | B24: =IF(Masters!$B$22="","",Masters!$B$22) -> SHARIF RAJ | C24: =IF(B24="","",Masters!$C$22) -> 4 | D24: =IF(B24="","",IF(Masters!$D$22="","",Masters!$D$22)) | E24: =IF(B24="",0,Masters!$E$22) -> 0 | F24: =SUMIF(Daily_Sales!$C$4:$C$503,B24,Daily_Sales!$G$4:$G$503) -> 362750 | G24: =SUMIF(Daily_Sales!$C$4:$C$503,B24,Daily_Sales!$E$4:$E$503) -> 42 | H24: =IF(B24="",0,IF(D24<>"",D24*G24,F24*C24/100)) -> 14510 | I24: =IF(G24>0,Masters!$Y$3,0) -> 100 | J24: =G24*Masters!$Y$4 -> 420 | K24: =SUMIFS(Cash_Book!$G$4:$G$1008,Cash_Book!$C$4:$C$1008,"BEPAARI",Cash_Book!$D$4:$D$1008,"MOTOR",Cash_Book!$E$4:$E$1008,B24) -> 10080 | L24: =SUMIFS(Cash_Book!$G$4:$G$1008,Cash_Book!$C$4:$C$1008,"BEPAARI",Cash_Book!$D$4:$D$1008,"BHUSSA",Cash_Book!$E$4:$E$1008,B24) -> 100 | M24: =SUMIFS(Cash_Book!$G$4:$G$1008,Cash_Book!$C$4:$C$1008,"BEPAARI",Cash_Book!$D$4:$D$1008,"GAWALI",Cash_Book!$E$4:$E$1008,B24) -> 2520 | N24: =SUMIFS(Cash_Book!$G$4:$G$1008,Cash_Book!$C$4:$C$1008,"BEPAARI",Cash_Book!$D$4:$D$1008,"CASH_ADV",Cash_Book!$E$4:$E$1008,B24) -> 0 | O24: =SUMIFS(Cash_Book!$G$4:$G$1008,Cash_Book!$C$4:$C$1008,"BEPAARI",Cash_Book!$D$4:$D$1008,"OTHER",Cash_Book!$E$4:$E$1008,B24) -> 0 | P24: =SUM(H24:O24) -> 27730 | Q24: =IF(B24="","",F24-P24+E24) -> 335020 | R24: =SUMIFS(Cash_Book!$G$4:$G$1008,Cash_Book!$C$4:$C$1008,"BEPAARI",Cash_Book!$D$4:$D$1008,"PAYMENT",Cash_Book!$E$4:$E$1008,B24) -> 304630 | S24: =IF(B24="","",Q24-R24) -> 30390
A25: 21 | B25: =IF(Masters!$B$23="","",Masters!$B$23) | C25: =IF(B25="","",Masters!$C$23) | D25: =IF(B25="","",IF(Masters!$D$23="","",Masters!$D$23)) | E25: =IF(B25="",0,Masters!$E$23) -> 0 | F25: =SUMIF(Daily_Sales!$C$4:$C$503,B25,Daily_Sales!$G$4:$G$503) -> 0 | G25: =SUMIF(Daily_Sales!$C$4:$C$503,B25,Daily_Sales!$E$4:$E$503) -> 0 | H25: =IF(B25="",0,IF(D25<>"",D25*G25,F25*C25/100)) -> 0 | I25: =IF(G25>0,Masters!$Y$3,0) -> 0 | J25: =G25*Masters!$Y$4 -> 0 | K25: =SUMIFS(Cash_Book!$G$4:$G$1008,Cash_Book!$C$4:$C$1008,"BEPAARI",Cash_Book!$D$4:$D$1008,"MOTOR",Cash_Book!$E$4:$E$1008,B25) -> 0 | L25: =SUMIFS(Cash_Book!$G$4:$G$1008,Cash_Book!$C$4:$C$1008,"BEPAARI",Cash_Book!$D$4:$D$1008,"BHUSSA",Cash_Book!$E$4:$E$1008,B25) -> 0 | M25: =SUMIFS(Cash_Book!$G$4:$G$1008,Cash_Book!$C$4:$C$1008,"BEPAARI",Cash_Book!$D$4:$D$1008,"GAWALI",Cash_Book!$E$4:$E$1008,B25) -> 0 | N25: =SUMIFS(Cash_Book!$G$4:$G$1008,Cash_Book!$C$4:$C$1008,"BEPAARI",Cash_Book!$D$4:$D$1008,"CASH_ADV",Cash_Book!$E$4:$E$1008,B25) -> 0 | O25: =SUMIFS(Cash_Book!$G$4:$G$1008,Cash_Book!$C$4:$C$1008,"BEPAARI",Cash_Book!$D$4:$D$1008,"OTHER",Cash_Book!$E$4:$E$1008,B25) -> 0 | P25: =SUM(H25:O25) -> 0 | Q25: =IF(B25="","",F25-P25+E25) | R25: =SUMIFS(Cash_Book!$G$4:$G$1008,Cash_Book!$C$4:$C$1008,"BEPAARI",Cash_Book!$D$4:$D$1008,"PAYMENT",Cash_Book!$E$4:$E$1008,B25) -> 0 | S25: =IF(B25="","",Q25-R25)
A26: 22 | B26: =IF(Masters!$B$24="","",Masters!$B$24) | C26: =IF(B26="","",Masters!$C$24) | D26: =IF(B26="","",IF(Masters!$D$24="","",Masters!$D$24)) | E26: =IF(B26="",0,Masters!$E$24) -> 0 | F26: =SUMIF(Daily_Sales!$C$4:$C$503,B26,Daily_Sales!$G$4:$G$503) -> 0 | G26: =SUMIF(Daily_Sales!$C$4:$C$503,B26,Daily_Sales!$E$4:$E$503) -> 0 | H26: =IF(B26="",0,IF(D26<>"",D26*G26,F26*C26/100)) -> 0 | I26: =IF(G26>0,Masters!$Y$3,0) -> 0 | J26: =G26*Masters!$Y$4 -> 0 | K26: =SUMIFS(Cash_Book!$G$4:$G$1008,Cash_Book!$C$4:$C$1008,"BEPAARI",Cash_Book!$D$4:$D$1008,"MOTOR",Cash_Book!$E$4:$E$1008,B26) -> 0 | L26: =SUMIFS(Cash_Book!$G$4:$G$1008,Cash_Book!$C$4:$C$1008,"BEPAARI",Cash_Book!$D$4:$D$1008,"BHUSSA",Cash_Book!$E$4:$E$1008,B26) -> 0 | M26: =SUMIFS(Cash_Book!$G$4:$G$1008,Cash_Book!$C$4:$C$1008,"BEPAARI",Cash_Book!$D$4:$D$1008,"GAWALI",Cash_Book!$E$4:$E$1008,B26) -> 0 | N26: =SUMIFS(Cash_Book!$G$4:$G$1008,Cash_Book!$C$4:$C$1008,"BEPAARI",Cash_Book!$D$4:$D$1008,"CASH_ADV",Cash_Book!$E$4:$E$1008,B26) -> 0 | O26: =SUMIFS(Cash_Book!$G$4:$G$1008,Cash_Book!$C$4:$C$1008,"BEPAARI",Cash_Book!$D$4:$D$1008,"OTHER",Cash_Book!$E$4:$E$1008,B26) -> 0 | P26: =SUM(H26:O26) -> 0 | Q26: =IF(B26="","",F26-P26+E26) | R26: =SUMIFS(Cash_Book!$G$4:$G$1008,Cash_Book!$C$4:$C$1008,"BEPAARI",Cash_Book!$D$4:$D$1008,"PAYMENT",Cash_Book!$E$4:$E$1008,B26) -> 0 | S26: =IF(B26="","",Q26-R26)
A27: 23 | B27: =IF(Masters!$B$25="","",Masters!$B$25) | C27: =IF(B27="","",Masters!$C$25) | D27: =IF(B27="","",IF(Masters!$D$25="","",Masters!$D$25)) | E27: =IF(B27="",0,Masters!$E$25) -> 0 | F27: =SUMIF(Daily_Sales!$C$4:$C$503,B27,Daily_Sales!$G$4:$G$503) -> 0 | G27: =SUMIF(Daily_Sales!$C$4:$C$503,B27,Daily_Sales!$E$4:$E$503) -> 0 | H27: =IF(B27="",0,IF(D27<>"",D27*G27,F27*C27/100)) -> 0 | I27: =IF(G27>0,Masters!$Y$3,0) -> 0 | J27: =G27*Masters!$Y$4 -> 0 | K27: =SUMIFS(Cash_Book!$G$4:$G$1008,Cash_Book!$C$4:$C$1008,"BEPAARI",Cash_Book!$D$4:$D$1008,"MOTOR",Cash_Book!$E$4:$E$1008,B27) -> 0 | L27: =SUMIFS(Cash_Book!$G$4:$G$1008,Cash_Book!$C$4:$C$1008,"BEPAARI",Cash_Book!$D$4:$D$1008,"BHUSSA",Cash_Book!$E$4:$E$1008,B27) -> 0 | M27: =SUMIFS(Cash_Book!$G$4:$G$1008,Cash_Book!$C$4:$C$1008,"BEPAARI",Cash_Book!$D$4:$D$1008,"GAWALI",Cash_Book!$E$4:$E$1008,B27) -> 0 | N27: =SUMIFS(Cash_Book!$G$4:$G$1008,Cash_Book!$C$4:$C$1008,"BEPAARI",Cash_Book!$D$4:$D$1008,"CASH_ADV",Cash_Book!$E$4:$E$1008,B27) -> 0 | O27: =SUMIFS(Cash_Book!$G$4:$G$1008,Cash_Book!$C$4:$C$1008,"BEPAARI",Cash_Book!$D$4:$D$1008,"OTHER",Cash_Book!$E$4:$E$1008,B27) -> 0 | P27: =SUM(H27:O27) -> 0 | Q27: =IF(B27="","",F27-P27+E27) | R27: =SUMIFS(Cash_Book!$G$4:$G$1008,Cash_Book!$C$4:$C$1008,"BEPAARI",Cash_Book!$D$4:$D$1008,"PAYMENT",Cash_Book!$E$4:$E$1008,B27) -> 0 | S27: =IF(B27="","",Q27-R27)
A28: 24 | B28: =IF(Masters!$B$26="","",Masters!$B$26) | C28: =IF(B28="","",Masters!$C$26) | D28: =IF(B28="","",IF(Masters!$D$26="","",Masters!$D$26)) | E28: =IF(B28="",0,Masters!$E$26) -> 0 | F28: =SUMIF(Daily_Sales!$C$4:$C$503,B28,Daily_Sales!$G$4:$G$503) -> 0 | G28: =SUMIF(Daily_Sales!$C$4:$C$503,B28,Daily_Sales!$E$4:$E$503) -> 0 | H28: =IF(B28="",0,IF(D28<>"",D28*G28,F28*C28/100)) -> 0 | I28: =IF(G28>0,Masters!$Y$3,0) -> 0 | J28: =G28*Masters!$Y$4 -> 0 | K28: =SUMIFS(Cash_Book!$G$4:$G$1008,Cash_Book!$C$4:$C$1008,"BEPAARI",Cash_Book!$D$4:$D$1008,"MOTOR",Cash_Book!$E$4:$E$1008,B28) -> 0 | L28: =SUMIFS(Cash_Book!$G$4:$G$1008,Cash_Book!$C$4:$C$1008,"BEPAARI",Cash_Book!$D$4:$D$1008,"BHUSSA",Cash_Book!$E$4:$E$1008,B28) -> 0 | M28: =SUMIFS(Cash_Book!$G$4:$G$1008,Cash_Book!$C$4:$C$1008,"BEPAARI",Cash_Book!$D$4:$D$1008,"GAWALI",Cash_Book!$E$4:$E$1008,B28) -> 0 | N28: =SUMIFS(Cash_Book!$G$4:$G$1008,Cash_Book!$C$4:$C$1008,"BEPAARI",Cash_Book!$D$4:$D$1008,"CASH_ADV",Cash_Book!$E$4:$E$1008,B28) -> 0 | O28: =SUMIFS(Cash_Book!$G$4:$G$1008,Cash_Book!$C$4:$C$1008,"BEPAARI",Cash_Book!$D$4:$D$1008,"OTHER",Cash_Book!$E$4:$E$1008,B28) -> 0 | P28: =SUM(H28:O28) -> 0 | Q28: =IF(B28="","",F28-P28+E28) | R28: =SUMIFS(Cash_Book!$G$4:$G$1008,Cash_Book!$C$4:$C$1008,"BEPAARI",Cash_Book!$D$4:$D$1008,"PAYMENT",Cash_Book!$E$4:$E$1008,B28) -> 0 | S28: =IF(B28="","",Q28-R28)
A29: 25 | B29: =IF(Masters!$B$27="","",Masters!$B$27) | C29: =IF(B29="","",Masters!$C$27) | D29: =IF(B29="","",IF(Masters!$D$27="","",Masters!$D$27)) | E29: =IF(B29="",0,Masters!$E$27) -> 0 | F29: =SUMIF(Daily_Sales!$C$4:$C$503,B29,Daily_Sales!$G$4:$G$503) -> 0 | G29: =SUMIF(Daily_Sales!$C$4:$C$503,B29,Daily_Sales!$E$4:$E$503) -> 0 | H29: =IF(B29="",0,IF(D29<>"",D29*G29,F29*C29/100)) -> 0 | I29: =IF(G29>0,Masters!$Y$3,0) -> 0 | J29: =G29*Masters!$Y$4 -> 0 | K29: =SUMIFS(Cash_Book!$G$4:$G$1008,Cash_Book!$C$4:$C$1008,"BEPAARI",Cash_Book!$D$4:$D$1008,"MOTOR",Cash_Book!$E$4:$E$1008,B29) -> 0 | L29: =SUMIFS(Cash_Book!$G$4:$G$1008,Cash_Book!$C$4:$C$1008,"BEPAARI",Cash_Book!$D$4:$D$1008,"BHUSSA",Cash_Book!$E$4:$E$1008,B29) -> 0 | M29: =SUMIFS(Cash_Book!$G$4:$G$1008,Cash_Book!$C$4:$C$1008,"BEPAARI",Cash_Book!$D$4:$D$1008,"GAWALI",Cash_Book!$E$4:$E$1008,B29) -> 0 | N29: =SUMIFS(Cash_Book!$G$4:$G$1008,Cash_Book!$C$4:$C$1008,"BEPAARI",Cash_Book!$D$4:$D$1008,"CASH_ADV",Cash_Book!$E$4:$E$1008,B29) -> 0 | O29: =SUMIFS(Cash_Book!$G$4:$G$1008,Cash_Book!$C$4:$C$1008,"BEPAARI",Cash_Book!$D$4:$D$1008,"OTHER",Cash_Book!$E$4:$E$1008,B29) -> 0 | P29: =SUM(H29:O29) -> 0 | Q29: =IF(B29="","",F29-P29+E29) | R29: =SUMIFS(Cash_Book!$G$4:$G$1008,Cash_Book!$C$4:$C$1008,"BEPAARI",Cash_Book!$D$4:$D$1008,"PAYMENT",Cash_Book!$E$4:$E$1008,B29) -> 0 | S29: =IF(B29="","",Q29-R29)
A30: 26 | B30: =IF(Masters!$B$28="","",Masters!$B$28) | C30: =IF(B30="","",Masters!$C$28) | D30: =IF(B30="","",IF(Masters!$D$28="","",Masters!$D$28)) | E30: =IF(B30="",0,Masters!$E$28) -> 0 | F30: =SUMIF(Daily_Sales!$C$4:$C$503,B30,Daily_Sales!$G$4:$G$503) -> 0 | G30: =SUMIF(Daily_Sales!$C$4:$C$503,B30,Daily_Sales!$E$4:$E$503) -> 0 | H30: =IF(B30="",0,IF(D30<>"",D30*G30,F30*C30/100)) -> 0 | I30: =IF(G30>0,Masters!$Y$3,0) -> 0 | J30: =G30*Masters!$Y$4 -> 0 | K30: =SUMIFS(Cash_Book!$G$4:$G$1008,Cash_Book!$C$4:$C$1008,"BEPAARI",Cash_Book!$D$4:$D$1008,"MOTOR",Cash_Book!$E$4:$E$1008,B30) -> 0 | L30: =SUMIFS(Cash_Book!$G$4:$G$1008,Cash_Book!$C$4:$C$1008,"BEPAARI",Cash_Book!$D$4:$D$1008,"BHUSSA",Cash_Book!$E$4:$E$1008,B30) -> 0 | M30: =SUMIFS(Cash_Book!$G$4:$G$1008,Cash_Book!$C$4:$C$1008,"BEPAARI",Cash_Book!$D$4:$D$1008,"GAWALI",Cash_Book!$E$4:$E$1008,B30) -> 0 | N30: =SUMIFS(Cash_Book!$G$4:$G$1008,Cash_Book!$C$4:$C$1008,"BEPAARI",Cash_Book!$D$4:$D$1008,"CASH_ADV",Cash_Book!$E$4:$E$1008,B30) -> 0 | O30: =SUMIFS(Cash_Book!$G$4:$G$1008,Cash_Book!$C$4:$C$1008,"BEPAARI",Cash_Book!$D$4:$D$1008,"OTHER",Cash_Book!$E$4:$E$1008,B30) -> 0 | P30: =SUM(H30:O30) -> 0 | Q30: =IF(B30="","",F30-P30+E30) | R30: =SUMIFS(Cash_Book!$G$4:$G$1008,Cash_Book!$C$4:$C$1008,"BEPAARI",Cash_Book!$D$4:$D$1008,"PAYMENT",Cash_Book!$E$4:$E$1008,B30) -> 0 | S30: =IF(B30="","",Q30-R30)
A31: 27 | B31: =IF(Masters!$B$29="","",Masters!$B$29) | C31: =IF(B31="","",Masters!$C$29) | D31: =IF(B31="","",IF(Masters!$D$29="","",Masters!$D$29)) | E31: =IF(B31="",0,Masters!$E$29) -> 0 | F31: =SUMIF(Daily_Sales!$C$4:$C$503,B31,Daily_Sales!$G$4:$G$503) -> 0 | G31: =SUMIF(Daily_Sales!$C$4:$C$503,B31,Daily_Sales!$E$4:$E$503) -> 0 | H31: =IF(B31="",0,IF(D31<>"",D31*G31,F31*C31/100)) -> 0 | I31: =IF(G31>0,Masters!$Y$3,0) -> 0 | J31: =G31*Masters!$Y$4 -> 0 | K31: =SUMIFS(Cash_Book!$G$4:$G$1008,Cash_Book!$C$4:$C$1008,"BEPAARI",Cash_Book!$D$4:$D$1008,"MOTOR",Cash_Book!$E$4:$E$1008,B31) -> 0 | L31: =SUMIFS(Cash_Book!$G$4:$G$1008,Cash_Book!$C$4:$C$1008,"BEPAARI",Cash_Book!$D$4:$D$1008,"BHUSSA",Cash_Book!$E$4:$E$1008,B31) -> 0 | M31: =SUMIFS(Cash_Book!$G$4:$G$1008,Cash_Book!$C$4:$C$1008,"BEPAARI",Cash_Book!$D$4:$D$1008,"GAWALI",Cash_Book!$E$4:$E$1008,B31) -> 0 | N31: =SUMIFS(Cash_Book!$G$4:$G$1008,Cash_Book!$C$4:$C$1008,"BEPAARI",Cash_Book!$D$4:$D$1008,"CASH_ADV",Cash_Book!$E$4:$E$1008,B31) -> 0 | O31: =SUMIFS(Cash_Book!$G$4:$G$1008,Cash_Book!$C$4:$C$1008,"BEPAARI",Cash_Book!$D$4:$D$1008,"OTHER",Cash_Book!$E$4:$E$1008,B31) -> 0 | P31: =SUM(H31:O31) -> 0 | Q31: =IF(B31="","",F31-P31+E31) | R31: =SUMIFS(Cash_Book!$G$4:$G$1008,Cash_Book!$C$4:$C$1008,"BEPAARI",Cash_Book!$D$4:$D$1008,"PAYMENT",Cash_Book!$E$4:$E$1008,B31) -> 0 | S31: =IF(B31="","",Q31-R31)
A32: 28 | B32: =IF(Masters!$B$30="","",Masters!$B$30) | C32: =IF(B32="","",Masters!$C$30) | D32: =IF(B32="","",IF(Masters!$D$30="","",Masters!$D$30)) | E32: =IF(B32="",0,Masters!$E$30) -> 0 | F32: =SUMIF(Daily_Sales!$C$4:$C$503,B32,Daily_Sales!$G$4:$G$503) -> 0 | G32: =SUMIF(Daily_Sales!$C$4:$C$503,B32,Daily_Sales!$E$4:$E$503) -> 0 | H32: =IF(B32="",0,IF(D32<>"",D32*G32,F32*C32/100)) -> 0 | I32: =IF(G32>0,Masters!$Y$3,0) -> 0 | J32: =G32*Masters!$Y$4 -> 0 | K32: =SUMIFS(Cash_Book!$G$4:$G$1008,Cash_Book!$C$4:$C$1008,"BEPAARI",Cash_Book!$D$4:$D$1008,"MOTOR",Cash_Book!$E$4:$E$1008,B32) -> 0 | L32: =SUMIFS(Cash_Book!$G$4:$G$1008,Cash_Book!$C$4:$C$1008,"BEPAARI",Cash_Book!$D$4:$D$1008,"BHUSSA",Cash_Book!$E$4:$E$1008,B32) -> 0 | M32: =SUMIFS(Cash_Book!$G$4:$G$1008,Cash_Book!$C$4:$C$1008,"BEPAARI",Cash_Book!$D$4:$D$1008,"GAWALI",Cash_Book!$E$4:$E$1008,B32) -> 0 | N32: =SUMIFS(Cash_Book!$G$4:$G$1008,Cash_Book!$C$4:$C$1008,"BEPAARI",Cash_Book!$D$4:$D$1008,"CASH_ADV",Cash_Book!$E$4:$E$1008,B32) -> 0 | O32: =SUMIFS(Cash_Book!$G$4:$G$1008,Cash_Book!$C$4:$C$1008,"BEPAARI",Cash_Book!$D$4:$D$1008,"OTHER",Cash_Book!$E$4:$E$1008,B32) -> 0 | P32: =SUM(H32:O32) -> 0 | Q32: =IF(B32="","",F32-P32+E32) | R32: =SUMIFS(Cash_Book!$G$4:$G$1008,Cash_Book!$C$4:$C$1008,"BEPAARI",Cash_Book!$D$4:$D$1008,"PAYMENT",Cash_Book!$E$4:$E$1008,B32) -> 0 | S32: =IF(B32="","",Q32-R32)
A33: 29 | B33: =IF(Masters!$B$31="","",Masters!$B$31) | C33: =IF(B33="","",Masters!$C$31) | D33: =IF(B33="","",IF(Masters!$D$31="","",Masters!$D$31)) | E33: =IF(B33="",0,Masters!$E$31) -> 0 | F33: =SUMIF(Daily_Sales!$C$4:$C$503,B33,Daily_Sales!$G$4:$G$503) -> 0 | G33: =SUMIF(Daily_Sales!$C$4:$C$503,B33,Daily_Sales!$E$4:$E$503) -> 0 | H33: =IF(B33="",0,IF(D33<>"",D33*G33,F33*C33/100)) -> 0 | I33: =IF(G33>0,Masters!$Y$3,0) -> 0 | J33: =G33*Masters!$Y$4 -> 0 | K33: =SUMIFS(Cash_Book!$G$4:$G$1008,Cash_Book!$C$4:$C$1008,"BEPAARI",Cash_Book!$D$4:$D$1008,"MOTOR",Cash_Book!$E$4:$E$1008,B33) -> 0 | L33: =SUMIFS(Cash_Book!$G$4:$G$1008,Cash_Book!$C$4:$C$1008,"BEPAARI",Cash_Book!$D$4:$D$1008,"BHUSSA",Cash_Book!$E$4:$E$1008,B33) -> 0 | M33: =SUMIFS(Cash_Book!$G$4:$G$1008,Cash_Book!$C$4:$C$1008,"BEPAARI",Cash_Book!$D$4:$D$1008,"GAWALI",Cash_Book!$E$4:$E$1008,B33) -> 0 | N33: =SUMIFS(Cash_Book!$G$4:$G$1008,Cash_Book!$C$4:$C$1008,"BEPAARI",Cash_Book!$D$4:$D$1008,"CASH_ADV",Cash_Book!$E$4:$E$1008,B33) -> 0 | O33: =SUMIFS(Cash_Book!$G$4:$G$1008,Cash_Book!$C$4:$C$1008,"BEPAARI",Cash_Book!$D$4:$D$1008,"OTHER",Cash_Book!$E$4:$E$1008,B33) -> 0 | P33: =SUM(H33:O33) -> 0 | Q33: =IF(B33="","",F33-P33+E33) | R33: =SUMIFS(Cash_Book!$G$4:$G$1008,Cash_Book!$C$4:$C$1008,"BEPAARI",Cash_Book!$D$4:$D$1008,"PAYMENT",Cash_Book!$E$4:$E$1008,B33) -> 0 | S33: =IF(B33="","",Q33-R33)
A34: 30 | B34: =IF(Masters!$B$32="","",Masters!$B$32) | C34: =IF(B34="","",Masters!$C$32) | D34: =IF(B34="","",IF(Masters!$D$32="","",Masters!$D$32)) | E34: =IF(B34="",0,Masters!$E$32) -> 0 | F34: =SUMIF(Daily_Sales!$C$4:$C$503,B34,Daily_Sales!$G$4:$G$503) -> 0 | G34: =SUMIF(Daily_Sales!$C$4:$C$503,B34,Daily_Sales!$E$4:$E$503) -> 0 | H34: =IF(B34="",0,IF(D34<>"",D34*G34,F34*C34/100)) -> 0 | I34: =IF(G34>0,Masters!$Y$3,0) -> 0 | J34: =G34*Masters!$Y$4 -> 0 | K34: =SUMIFS(Cash_Book!$G$4:$G$1008,Cash_Book!$C$4:$C$1008,"BEPAARI",Cash_Book!$D$4:$D$1008,"MOTOR",Cash_Book!$E$4:$E$1008,B34) -> 0 | L34: =SUMIFS(Cash_Book!$G$4:$G$1008,Cash_Book!$C$4:$C$1008,"BEPAARI",Cash_Book!$D$4:$D$1008,"BHUSSA",Cash_Book!$E$4:$E$1008,B34) -> 0 | M34: =SUMIFS(Cash_Book!$G$4:$G$1008,Cash_Book!$C$4:$C$1008,"BEPAARI",Cash_Book!$D$4:$D$1008,"GAWALI",Cash_Book!$E$4:$E$1008,B34) -> 0 | N34: =SUMIFS(Cash_Book!$G$4:$G$1008,Cash_Book!$C$4:$C$1008,"BEPAARI",Cash_Book!$D$4:$D$1008,"CASH_ADV",Cash_Book!$E$4:$E$1008,B34) -> 0 | O34: =SUMIFS(Cash_Book!$G$4:$G$1008,Cash_Book!$C$4:$C$1008,"BEPAARI",Cash_Book!$D$4:$D$1008,"OTHER",Cash_Book!$E$4:$E$1008,B34) -> 0 | P34: =SUM(H34:O34) -> 0 | Q34: =IF(B34="","",F34-P34+E34) | R34: =SUMIFS(Cash_Book!$G$4:$G$1008,Cash_Book!$C$4:$C$1008,"BEPAARI",Cash_Book!$D$4:$D$1008,"PAYMENT",Cash_Book!$E$4:$E$1008,B34) -> 0 | S34: =IF(B34="","",Q34-R34)
A35: 31 | B35: =IF(Masters!$B$33="","",Masters!$B$33) | C35: =IF(B35="","",Masters!$C$33) | D35: =IF(B35="","",IF(Masters!$D$33="","",Masters!$D$33)) | E35: =IF(B35="",0,Masters!$E$33) -> 0 | F35: =SUMIF(Daily_Sales!$C$4:$C$503,B35,Daily_Sales!$G$4:$G$503) -> 0 | G35: =SUMIF(Daily_Sales!$C$4:$C$503,B35,Daily_Sales!$E$4:$E$503) -> 0 | H35: =IF(B35="",0,IF(D35<>"",D35*G35,F35*C35/100)) -> 0 | I35: =IF(G35>0,Masters!$Y$3,0) -> 0 | J35: =G35*Masters!$Y$4 -> 0 | K35: =SUMIFS(Cash_Book!$G$4:$G$1008,Cash_Book!$C$4:$C$1008,"BEPAARI",Cash_Book!$D$4:$D$1008,"MOTOR",Cash_Book!$E$4:$E$1008,B35) -> 0 | L35: =SUMIFS(Cash_Book!$G$4:$G$1008,Cash_Book!$C$4:$C$1008,"BEPAARI",Cash_Book!$D$4:$D$1008,"BHUSSA",Cash_Book!$E$4:$E$1008,B35) -> 0 | M35: =SUMIFS(Cash_Book!$G$4:$G$1008,Cash_Book!$C$4:$C$1008,"BEPAARI",Cash_Book!$D$4:$D$1008,"GAWALI",Cash_Book!$E$4:$E$1008,B35) -> 0 | N35: =SUMIFS(Cash_Book!$G$4:$G$1008,Cash_Book!$C$4:$C$1008,"BEPAARI",Cash_Book!$D$4:$D$1008,"CASH_ADV",Cash_Book!$E$4:$E$1008,B35) -> 0 | O35: =SUMIFS(Cash_Book!$G$4:$G$1008,Cash_Book!$C$4:$C$1008,"BEPAARI",Cash_Book!$D$4:$D$1008,"OTHER",Cash_Book!$E$4:$E$1008,B35) -> 0 | P35: =SUM(H35:O35) -> 0 | Q35: =IF(B35="","",F35-P35+E35) | R35: =SUMIFS(Cash_Book!$G$4:$G$1008,Cash_Book!$C$4:$C$1008,"BEPAARI",Cash_Book!$D$4:$D$1008,"PAYMENT",Cash_Book!$E$4:$E$1008,B35) -> 0 | S35: =IF(B35="","",Q35-R35)
A36: 32 | B36: =IF(Masters!$B$34="","",Masters!$B$34) | C36: =IF(B36="","",Masters!$C$34) | D36: =IF(B36="","",IF(Masters!$D$34="","",Masters!$D$34)) | E36: =IF(B36="",0,Masters!$E$34) -> 0 | F36: =SUMIF(Daily_Sales!$C$4:$C$503,B36,Daily_Sales!$G$4:$G$503) -> 0 | G36: =SUMIF(Daily_Sales!$C$4:$C$503,B36,Daily_Sales!$E$4:$E$503) -> 0 | H36: =IF(B36="",0,IF(D36<>"",D36*G36,F36*C36/100)) -> 0 | I36: =IF(G36>0,Masters!$Y$3,0) -> 0 | J36: =G36*Masters!$Y$4 -> 0 | K36: =SUMIFS(Cash_Book!$G$4:$G$1008,Cash_Book!$C$4:$C$1008,"BEPAARI",Cash_Book!$D$4:$D$1008,"MOTOR",Cash_Book!$E$4:$E$1008,B36) -> 0 | L36: =SUMIFS(Cash_Book!$G$4:$G$1008,Cash_Book!$C$4:$C$1008,"BEPAARI",Cash_Book!$D$4:$D$1008,"BHUSSA",Cash_Book!$E$4:$E$1008,B36) -> 0 | M36: =SUMIFS(Cash_Book!$G$4:$G$1008,Cash_Book!$C$4:$C$1008,"BEPAARI",Cash_Book!$D$4:$D$1008,"GAWALI",Cash_Book!$E$4:$E$1008,B36) -> 0 | N36: =SUMIFS(Cash_Book!$G$4:$G$1008,Cash_Book!$C$4:$C$1008,"BEPAARI",Cash_Book!$D$4:$D$1008,"CASH_ADV",Cash_Book!$E$4:$E$1008,B36) -> 0 | O36: =SUMIFS(Cash_Book!$G$4:$G$1008,Cash_Book!$C$4:$C$1008,"BEPAARI",Cash_Book!$D$4:$D$1008,"OTHER",Cash_Book!$E$4:$E$1008,B36) -> 0 | P36: =SUM(H36:O36) -> 0 | Q36: =IF(B36="","",F36-P36+E36) | R36: =SUMIFS(Cash_Book!$G$4:$G$1008,Cash_Book!$C$4:$C$1008,"BEPAARI",Cash_Book!$D$4:$D$1008,"PAYMENT",Cash_Book!$E$4:$E$1008,B36) -> 0 | S36: =IF(B36="","",Q36-R36)
A37: 33 | B37: =IF(Masters!$B$35="","",Masters!$B$35) | C37: =IF(B37="","",Masters!$C$35) | D37: =IF(B37="","",IF(Masters!$D$35="","",Masters!$D$35)) | E37: =IF(B37="",0,Masters!$E$35) -> 0 | F37: =SUMIF(Daily_Sales!$C$4:$C$503,B37,Daily_Sales!$G$4:$G$503) -> 0 | G37: =SUMIF(Daily_Sales!$C$4:$C$503,B37,Daily_Sales!$E$4:$E$503) -> 0 | H37: =IF(B37="",0,IF(D37<>"",D37*G37,F37*C37/100)) -> 0 | I37: =IF(G37>0,Masters!$Y$3,0) -> 0 | J37: =G37*Masters!$Y$4 -> 0 | K37: =SUMIFS(Cash_Book!$G$4:$G$1008,Cash_Book!$C$4:$C$1008,"BEPAARI",Cash_Book!$D$4:$D$1008,"MOTOR",Cash_Book!$E$4:$E$1008,B37) -> 0 | L37: =SUMIFS(Cash_Book!$G$4:$G$1008,Cash_Book!$C$4:$C$1008,"BEPAARI",Cash_Book!$D$4:$D$1008,"BHUSSA",Cash_Book!$E$4:$E$1008,B37) -> 0 | M37: =SUMIFS(Cash_Book!$G$4:$G$1008,Cash_Book!$C$4:$C$1008,"BEPAARI",Cash_Book!$D$4:$D$1008,"GAWALI",Cash_Book!$E$4:$E$1008,B37) -> 0 | N37: =SUMIFS(Cash_Book!$G$4:$G$1008,Cash_Book!$C$4:$C$1008,"BEPAARI",Cash_Book!$D$4:$D$1008,"CASH_ADV",Cash_Book!$E$4:$E$1008,B37) -> 0 | O37: =SUMIFS(Cash_Book!$G$4:$G$1008,Cash_Book!$C$4:$C$1008,"BEPAARI",Cash_Book!$D$4:$D$1008,"OTHER",Cash_Book!$E$4:$E$1008,B37) -> 0 | P37: =SUM(H37:O37) -> 0 | Q37: =IF(B37="","",F37-P37+E37) | R37: =SUMIFS(Cash_Book!$G$4:$G$1008,Cash_Book!$C$4:$C$1008,"BEPAARI",Cash_Book!$D$4:$D$1008,"PAYMENT",Cash_Book!$E$4:$E$1008,B37) -> 0 | S37: =IF(B37="","",Q37-R37)
A38: 34 | B38: =IF(Masters!$B$36="","",Masters!$B$36) | C38: =IF(B38="","",Masters!$C$36) | D38: =IF(B38="","",IF(Masters!$D$36="","",Masters!$D$36)) | E38: =IF(B38="",0,Masters!$E$36) -> 0 | F38: =SUMIF(Daily_Sales!$C$4:$C$503,B38,Daily_Sales!$G$4:$G$503) -> 0 | G38: =SUMIF(Daily_Sales!$C$4:$C$503,B38,Daily_Sales!$E$4:$E$503) -> 0 | H38: =IF(B38="",0,IF(D38<>"",D38*G38,F38*C38/100)) -> 0 | I38: =IF(G38>0,Masters!$Y$3,0) -> 0 | J38: =G38*Masters!$Y$4 -> 0 | K38: =SUMIFS(Cash_Book!$G$4:$G$1008,Cash_Book!$C$4:$C$1008,"BEPAARI",Cash_Book!$D$4:$D$1008,"MOTOR",Cash_Book!$E$4:$E$1008,B38) -> 0 | L38: =SUMIFS(Cash_Book!$G$4:$G$1008,Cash_Book!$C$4:$C$1008,"BEPAARI",Cash_Book!$D$4:$D$1008,"BHUSSA",Cash_Book!$E$4:$E$1008,B38) -> 0 | M38: =SUMIFS(Cash_Book!$G$4:$G$1008,Cash_Book!$C$4:$C$1008,"BEPAARI",Cash_Book!$D$4:$D$1008,"GAWALI",Cash_Book!$E$4:$E$1008,B38) -> 0 | N38: =SUMIFS(Cash_Book!$G$4:$G$1008,Cash_Book!$C$4:$C$1008,"BEPAARI",Cash_Book!$D$4:$D$1008,"CASH_ADV",Cash_Book!$E$4:$E$1008,B38) -> 0 | O38: =SUMIFS(Cash_Book!$G$4:$G$1008,Cash_Book!$C$4:$C$1008,"BEPAARI",Cash_Book!$D$4:$D$1008,"OTHER",Cash_Book!$E$4:$E$1008,B38) -> 0 | P38: =SUM(H38:O38) -> 0 | Q38: =IF(B38="","",F38-P38+E38) | R38: =SUMIFS(Cash_Book!$G$4:$G$1008,Cash_Book!$C$4:$C$1008,"BEPAARI",Cash_Book!$D$4:$D$1008,"PAYMENT",Cash_Book!$E$4:$E$1008,B38) -> 0 | S38: =IF(B38="","",Q38-R38)
A39: 35 | B39: =IF(Masters!$B$37="","",Masters!$B$37) | C39: =IF(B39="","",Masters!$C$37) | D39: =IF(B39="","",IF(Masters!$D$37="","",Masters!$D$37)) | E39: =IF(B39="",0,Masters!$E$37) -> 0 | F39: =SUMIF(Daily_Sales!$C$4:$C$503,B39,Daily_Sales!$G$4:$G$503) -> 0 | G39: =SUMIF(Daily_Sales!$C$4:$C$503,B39,Daily_Sales!$E$4:$E$503) -> 0 | H39: =IF(B39="",0,IF(D39<>"",D39*G39,F39*C39/100)) -> 0 | I39: =IF(G39>0,Masters!$Y$3,0) -> 0 | J39: =G39*Masters!$Y$4 -> 0 | K39: =SUMIFS(Cash_Book!$G$4:$G$1008,Cash_Book!$C$4:$C$1008,"BEPAARI",Cash_Book!$D$4:$D$1008,"MOTOR",Cash_Book!$E$4:$E$1008,B39) -> 0 | L39: =SUMIFS(Cash_Book!$G$4:$G$1008,Cash_Book!$C$4:$C$1008,"BEPAARI",Cash_Book!$D$4:$D$1008,"BHUSSA",Cash_Book!$E$4:$E$1008,B39) -> 0 | M39: =SUMIFS(Cash_Book!$G$4:$G$1008,Cash_Book!$C$4:$C$1008,"BEPAARI",Cash_Book!$D$4:$D$1008,"GAWALI",Cash_Book!$E$4:$E$1008,B39) -> 0 | N39: =SUMIFS(Cash_Book!$G$4:$G$1008,Cash_Book!$C$4:$C$1008,"BEPAARI",Cash_Book!$D$4:$D$1008,"CASH_ADV",Cash_Book!$E$4:$E$1008,B39) -> 0 | O39: =SUMIFS(Cash_Book!$G$4:$G$1008,Cash_Book!$C$4:$C$1008,"BEPAARI",Cash_Book!$D$4:$D$1008,"OTHER",Cash_Book!$E$4:$E$1008,B39) -> 0 | P39: =SUM(H39:O39) -> 0 | Q39: =IF(B39="","",F39-P39+E39) | R39: =SUMIFS(Cash_Book!$G$4:$G$1008,Cash_Book!$C$4:$C$1008,"BEPAARI",Cash_Book!$D$4:$D$1008,"PAYMENT",Cash_Book!$E$4:$E$1008,B39) -> 0 | S39: =IF(B39="","",Q39-R39)
A40: 36 | B40: =IF(Masters!$B$38="","",Masters!$B$38) | C40: =IF(B40="","",Masters!$C$38) | D40: =IF(B40="","",IF(Masters!$D$38="","",Masters!$D$38)) | E40: =IF(B40="",0,Masters!$E$38) -> 0 | F40: =SUMIF(Daily_Sales!$C$4:$C$503,B40,Daily_Sales!$G$4:$G$503) -> 0 | G40: =SUMIF(Daily_Sales!$C$4:$C$503,B40,Daily_Sales!$E$4:$E$503) -> 0 | H40: =IF(B40="",0,IF(D40<>"",D40*G40,F40*C40/100)) -> 0 | I40: =IF(G40>0,Masters!$Y$3,0) -> 0 | J40: =G40*Masters!$Y$4 -> 0 | K40: =SUMIFS(Cash_Book!$G$4:$G$1008,Cash_Book!$C$4:$C$1008,"BEPAARI",Cash_Book!$D$4:$D$1008,"MOTOR",Cash_Book!$E$4:$E$1008,B40) -> 0 | L40: =SUMIFS(Cash_Book!$G$4:$G$1008,Cash_Book!$C$4:$C$1008,"BEPAARI",Cash_Book!$D$4:$D$1008,"BHUSSA",Cash_Book!$E$4:$E$1008,B40) -> 0 | M40: =SUMIFS(Cash_Book!$G$4:$G$1008,Cash_Book!$C$4:$C$1008,"BEPAARI",Cash_Book!$D$4:$D$1008,"GAWALI",Cash_Book!$E$4:$E$1008,B40) -> 0 | N40: =SUMIFS(Cash_Book!$G$4:$G$1008,Cash_Book!$C$4:$C$1008,"BEPAARI",Cash_Book!$D$4:$D$1008,"CASH_ADV",Cash_Book!$E$4:$E$1008,B40) -> 0 | O40: =SUMIFS(Cash_Book!$G$4:$G$1008,Cash_Book!$C$4:$C$1008,"BEPAARI",Cash_Book!$D$4:$D$1008,"OTHER",Cash_Book!$E$4:$E$1008,B40) -> 0 | P40: =SUM(H40:O40) -> 0 | Q40: =IF(B40="","",F40-P40+E40) | R40: =SUMIFS(Cash_Book!$G$4:$G$1008,Cash_Book!$C$4:$C$1008,"BEPAARI",Cash_Book!$D$4:$D$1008,"PAYMENT",Cash_Book!$E$4:$E$1008,B40) -> 0 | S40: =IF(B40="","",Q40-R40)
A41: 37 | B41: =IF(Masters!$B$39="","",Masters!$B$39) | C41: =IF(B41="","",Masters!$C$39) | D41: =IF(B41="","",IF(Masters!$D$39="","",Masters!$D$39)) | E41: =IF(B41="",0,Masters!$E$39) -> 0 | F41: =SUMIF(Daily_Sales!$C$4:$C$503,B41,Daily_Sales!$G$4:$G$503) -> 0 | G41: =SUMIF(Daily_Sales!$C$4:$C$503,B41,Daily_Sales!$E$4:$E$503) -> 0 | H41: =IF(B41="",0,IF(D41<>"",D41*G41,F41*C41/100)) -> 0 | I41: =IF(G41>0,Masters!$Y$3,0) -> 0 | J41: =G41*Masters!$Y$4 -> 0 | K41: =SUMIFS(Cash_Book!$G$4:$G$1008,Cash_Book!$C$4:$C$1008,"BEPAARI",Cash_Book!$D$4:$D$1008,"MOTOR",Cash_Book!$E$4:$E$1008,B41) -> 0 | L41: =SUMIFS(Cash_Book!$G$4:$G$1008,Cash_Book!$C$4:$C$1008,"BEPAARI",Cash_Book!$D$4:$D$1008,"BHUSSA",Cash_Book!$E$4:$E$1008,B41) -> 0 | M41: =SUMIFS(Cash_Book!$G$4:$G$1008,Cash_Book!$C$4:$C$1008,"BEPAARI",Cash_Book!$D$4:$D$1008,"GAWALI",Cash_Book!$E$4:$E$1008,B41) -> 0 | N41: =SUMIFS(Cash_Book!$G$4:$G$1008,Cash_Book!$C$4:$C$1008,"BEPAARI",Cash_Book!$D$4:$D$1008,"CASH_ADV",Cash_Book!$E$4:$E$1008,B41) -> 0 | O41: =SUMIFS(Cash_Book!$G$4:$G$1008,Cash_Book!$C$4:$C$1008,"BEPAARI",Cash_Book!$D$4:$D$1008,"OTHER",Cash_Book!$E$4:$E$1008,B41) -> 0 | P41: =SUM(H41:O41) -> 0 | Q41: =IF(B41="","",F41-P41+E41) | R41: =SUMIFS(Cash_Book!$G$4:$G$1008,Cash_Book!$C$4:$C$1008,"BEPAARI",Cash_Book!$D$4:$D$1008,"PAYMENT",Cash_Book!$E$4:$E$1008,B41) -> 0 | S41: =IF(B41="","",Q41-R41)
A42: 38 | B42: =IF(Masters!$B$40="","",Masters!$B$40) | C42: =IF(B42="","",Masters!$C$40) | D42: =IF(B42="","",IF(Masters!$D$40="","",Masters!$D$40)) | E42: =IF(B42="",0,Masters!$E$40) -> 0 | F42: =SUMIF(Daily_Sales!$C$4:$C$503,B42,Daily_Sales!$G$4:$G$503) -> 0 | G42: =SUMIF(Daily_Sales!$C$4:$C$503,B42,Daily_Sales!$E$4:$E$503) -> 0 | H42: =IF(B42="",0,IF(D42<>"",D42*G42,F42*C42/100)) -> 0 | I42: =IF(G42>0,Masters!$Y$3,0) -> 0 | J42: =G42*Masters!$Y$4 -> 0 | K42: =SUMIFS(Cash_Book!$G$4:$G$1008,Cash_Book!$C$4:$C$1008,"BEPAARI",Cash_Book!$D$4:$D$1008,"MOTOR",Cash_Book!$E$4:$E$1008,B42) -> 0 | L42: =SUMIFS(Cash_Book!$G$4:$G$1008,Cash_Book!$C$4:$C$1008,"BEPAARI",Cash_Book!$D$4:$D$1008,"BHUSSA",Cash_Book!$E$4:$E$1008,B42) -> 0 | M42: =SUMIFS(Cash_Book!$G$4:$G$1008,Cash_Book!$C$4:$C$1008,"BEPAARI",Cash_Book!$D$4:$D$1008,"GAWALI",Cash_Book!$E$4:$E$1008,B42) -> 0 | N42: =SUMIFS(Cash_Book!$G$4:$G$1008,Cash_Book!$C$4:$C$1008,"BEPAARI",Cash_Book!$D$4:$D$1008,"CASH_ADV",Cash_Book!$E$4:$E$1008,B42) -> 0 | O42: =SUMIFS(Cash_Book!$G$4:$G$1008,Cash_Book!$C$4:$C$1008,"BEPAARI",Cash_Book!$D$4:$D$1008,"OTHER",Cash_Book!$E$4:$E$1008,B42) -> 0 | P42: =SUM(H42:O42) -> 0 | Q42: =IF(B42="","",F42-P42+E42) | R42: =SUMIFS(Cash_Book!$G$4:$G$1008,Cash_Book!$C$4:$C$1008,"BEPAARI",Cash_Book!$D$4:$D$1008,"PAYMENT",Cash_Book!$E$4:$E$1008,B42) -> 0 | S42: =IF(B42="","",Q42-R42)
A43: 39 | B43: =IF(Masters!$B$41="","",Masters!$B$41) | C43: =IF(B43="","",Masters!$C$41) | D43: =IF(B43="","",IF(Masters!$D$41="","",Masters!$D$41)) | E43: =IF(B43="",0,Masters!$E$41) -> 0 | F43: =SUMIF(Daily_Sales!$C$4:$C$503,B43,Daily_Sales!$G$4:$G$503) -> 0 | G43: =SUMIF(Daily_Sales!$C$4:$C$503,B43,Daily_Sales!$E$4:$E$503) -> 0 | H43: =IF(B43="",0,IF(D43<>"",D43*G43,F43*C43/100)) -> 0 | I43: =IF(G43>0,Masters!$Y$3,0) -> 0 | J43: =G43*Masters!$Y$4 -> 0 | K43: =SUMIFS(Cash_Book!$G$4:$G$1008,Cash_Book!$C$4:$C$1008,"BEPAARI",Cash_Book!$D$4:$D$1008,"MOTOR",Cash_Book!$E$4:$E$1008,B43) -> 0 | L43: =SUMIFS(Cash_Book!$G$4:$G$1008,Cash_Book!$C$4:$C$1008,"BEPAARI",Cash_Book!$D$4:$D$1008,"BHUSSA",Cash_Book!$E$4:$E$1008,B43) -> 0 | M43: =SUMIFS(Cash_Book!$G$4:$G$1008,Cash_Book!$C$4:$C$1008,"BEPAARI",Cash_Book!$D$4:$D$1008,"GAWALI",Cash_Book!$E$4:$E$1008,B43) -> 0 | N43: =SUMIFS(Cash_Book!$G$4:$G$1008,Cash_Book!$C$4:$C$1008,"BEPAARI",Cash_Book!$D$4:$D$1008,"CASH_ADV",Cash_Book!$E$4:$E$1008,B43) -> 0 | O43: =SUMIFS(Cash_Book!$G$4:$G$1008,Cash_Book!$C$4:$C$1008,"BEPAARI",Cash_Book!$D$4:$D$1008,"OTHER",Cash_Book!$E$4:$E$1008,B43) -> 0 | P43: =SUM(H43:O43) -> 0 | Q43: =IF(B43="","",F43-P43+E43) | R43: =SUMIFS(Cash_Book!$G$4:$G$1008,Cash_Book!$C$4:$C$1008,"BEPAARI",Cash_Book!$D$4:$D$1008,"PAYMENT",Cash_Book!$E$4:$E$1008,B43) -> 0 | S43: =IF(B43="","",Q43-R43)
A44: 40 | B44: =IF(Masters!$B$42="","",Masters!$B$42) | C44: =IF(B44="","",Masters!$C$42) | D44: =IF(B44="","",IF(Masters!$D$42="","",Masters!$D$42)) | E44: =IF(B44="",0,Masters!$E$42) -> 0 | F44: =SUMIF(Daily_Sales!$C$4:$C$503,B44,Daily_Sales!$G$4:$G$503) -> 0 | G44: =SUMIF(Daily_Sales!$C$4:$C$503,B44,Daily_Sales!$E$4:$E$503) -> 0 | H44: =IF(B44="",0,IF(D44<>"",D44*G44,F44*C44/100)) -> 0 | I44: =IF(G44>0,Masters!$Y$3,0) -> 0 | J44: =G44*Masters!$Y$4 -> 0 | K44: =SUMIFS(Cash_Book!$G$4:$G$1008,Cash_Book!$C$4:$C$1008,"BEPAARI",Cash_Book!$D$4:$D$1008,"MOTOR",Cash_Book!$E$4:$E$1008,B44) -> 0 | L44: =SUMIFS(Cash_Book!$G$4:$G$1008,Cash_Book!$C$4:$C$1008,"BEPAARI",Cash_Book!$D$4:$D$1008,"BHUSSA",Cash_Book!$E$4:$E$1008,B44) -> 0 | M44: =SUMIFS(Cash_Book!$G$4:$G$1008,Cash_Book!$C$4:$C$1008,"BEPAARI",Cash_Book!$D$4:$D$1008,"GAWALI",Cash_Book!$E$4:$E$1008,B44) -> 0 | N44: =SUMIFS(Cash_Book!$G$4:$G$1008,Cash_Book!$C$4:$C$1008,"BEPAARI",Cash_Book!$D$4:$D$1008,"CASH_ADV",Cash_Book!$E$4:$E$1008,B44) -> 0 | O44: =SUMIFS(Cash_Book!$G$4:$G$1008,Cash_Book!$C$4:$C$1008,"BEPAARI",Cash_Book!$D$4:$D$1008,"OTHER",Cash_Book!$E$4:$E$1008,B44) -> 0 | P44: =SUM(H44:O44) -> 0 | Q44: =IF(B44="","",F44-P44+E44) | R44: =SUMIFS(Cash_Book!$G$4:$G$1008,Cash_Book!$C$4:$C$1008,"BEPAARI",Cash_Book!$D$4:$D$1008,"PAYMENT",Cash_Book!$E$4:$E$1008,B44) -> 0 | S44: =IF(B44="","",Q44-R44)
A45: 41 | B45: =IF(Masters!$B$43="","",Masters!$B$43) | C45: =IF(B45="","",Masters!$C$43) | D45: =IF(B45="","",IF(Masters!$D$43="","",Masters!$D$43)) | E45: =IF(B45="",0,Masters!$E$43) -> 0 | F45: =SUMIF(Daily_Sales!$C$4:$C$503,B45,Daily_Sales!$G$4:$G$503) -> 0 | G45: =SUMIF(Daily_Sales!$C$4:$C$503,B45,Daily_Sales!$E$4:$E$503) -> 0 | H45: =IF(B45="",0,IF(D45<>"",D45*G45,F45*C45/100)) -> 0 | I45: =IF(G45>0,Masters!$Y$3,0) -> 0 | J45: =G45*Masters!$Y$4 -> 0 | K45: =SUMIFS(Cash_Book!$G$4:$G$1008,Cash_Book!$C$4:$C$1008,"BEPAARI",Cash_Book!$D$4:$D$1008,"MOTOR",Cash_Book!$E$4:$E$1008,B45) -> 0 | L45: =SUMIFS(Cash_Book!$G$4:$G$1008,Cash_Book!$C$4:$C$1008,"BEPAARI",Cash_Book!$D$4:$D$1008,"BHUSSA",Cash_Book!$E$4:$E$1008,B45) -> 0 | M45: =SUMIFS(Cash_Book!$G$4:$G$1008,Cash_Book!$C$4:$C$1008,"BEPAARI",Cash_Book!$D$4:$D$1008,"GAWALI",Cash_Book!$E$4:$E$1008,B45) -> 0 | N45: =SUMIFS(Cash_Book!$G$4:$G$1008,Cash_Book!$C$4:$C$1008,"BEPAARI",Cash_Book!$D$4:$D$1008,"CASH_ADV",Cash_Book!$E$4:$E$1008,B45) -> 0 | O45: =SUMIFS(Cash_Book!$G$4:$G$1008,Cash_Book!$C$4:$C$1008,"BEPAARI",Cash_Book!$D$4:$D$1008,"OTHER",Cash_Book!$E$4:$E$1008,B45) -> 0 | P45: =SUM(H45:O45) -> 0 | Q45: =IF(B45="","",F45-P45+E45) | R45: =SUMIFS(Cash_Book!$G$4:$G$1008,Cash_Book!$C$4:$C$1008,"BEPAARI",Cash_Book!$D$4:$D$1008,"PAYMENT",Cash_Book!$E$4:$E$1008,B45) -> 0 | S45: =IF(B45="","",Q45-R45)
A46: 42 | B46: =IF(Masters!$B$44="","",Masters!$B$44) | C46: =IF(B46="","",Masters!$C$44) | D46: =IF(B46="","",IF(Masters!$D$44="","",Masters!$D$44)) | E46: =IF(B46="",0,Masters!$E$44) -> 0 | F46: =SUMIF(Daily_Sales!$C$4:$C$503,B46,Daily_Sales!$G$4:$G$503) -> 0 | G46: =SUMIF(Daily_Sales!$C$4:$C$503,B46,Daily_Sales!$E$4:$E$503) -> 0 | H46: =IF(B46="",0,IF(D46<>"",D46*G46,F46*C46/100)) -> 0 | I46: =IF(G46>0,Masters!$Y$3,0) -> 0 | J46: =G46*Masters!$Y$4 -> 0 | K46: =SUMIFS(Cash_Book!$G$4:$G$1008,Cash_Book!$C$4:$C$1008,"BEPAARI",Cash_Book!$D$4:$D$1008,"MOTOR",Cash_Book!$E$4:$E$1008,B46) -> 0 | L46: =SUMIFS(Cash_Book!$G$4:$G$1008,Cash_Book!$C$4:$C$1008,"BEPAARI",Cash_Book!$D$4:$D$1008,"BHUSSA",Cash_Book!$E$4:$E$1008,B46) -> 0 | M46: =SUMIFS(Cash_Book!$G$4:$G$1008,Cash_Book!$C$4:$C$1008,"BEPAARI",Cash_Book!$D$4:$D$1008,"GAWALI",Cash_Book!$E$4:$E$1008,B46) -> 0 | N46: =SUMIFS(Cash_Book!$G$4:$G$1008,Cash_Book!$C$4:$C$1008,"BEPAARI",Cash_Book!$D$4:$D$1008,"CASH_ADV",Cash_Book!$E$4:$E$1008,B46) -> 0 | O46: =SUMIFS(Cash_Book!$G$4:$G$1008,Cash_Book!$C$4:$C$1008,"BEPAARI",Cash_Book!$D$4:$D$1008,"OTHER",Cash_Book!$E$4:$E$1008,B46) -> 0 | P46: =SUM(H46:O46) -> 0 | Q46: =IF(B46="","",F46-P46+E46) | R46: =SUMIFS(Cash_Book!$G$4:$G$1008,Cash_Book!$C$4:$C$1008,"BEPAARI",Cash_Book!$D$4:$D$1008,"PAYMENT",Cash_Book!$E$4:$E$1008,B46) -> 0 | S46: =IF(B46="","",Q46-R46)
A47: 43 | B47: =IF(Masters!$B$45="","",Masters!$B$45) | C47: =IF(B47="","",Masters!$C$45) | D47: =IF(B47="","",IF(Masters!$D$45="","",Masters!$D$45)) | E47: =IF(B47="",0,Masters!$E$45) -> 0 | F47: =SUMIF(Daily_Sales!$C$4:$C$503,B47,Daily_Sales!$G$4:$G$503) -> 0 | G47: =SUMIF(Daily_Sales!$C$4:$C$503,B47,Daily_Sales!$E$4:$E$503) -> 0 | H47: =IF(B47="",0,IF(D47<>"",D47*G47,F47*C47/100)) -> 0 | I47: =IF(G47>0,Masters!$Y$3,0) -> 0 | J47: =G47*Masters!$Y$4 -> 0 | K47: =SUMIFS(Cash_Book!$G$4:$G$1008,Cash_Book!$C$4:$C$1008,"BEPAARI",Cash_Book!$D$4:$D$1008,"MOTOR",Cash_Book!$E$4:$E$1008,B47) -> 0 | L47: =SUMIFS(Cash_Book!$G$4:$G$1008,Cash_Book!$C$4:$C$1008,"BEPAARI",Cash_Book!$D$4:$D$1008,"BHUSSA",Cash_Book!$E$4:$E$1008,B47) -> 0 | M47: =SUMIFS(Cash_Book!$G$4:$G$1008,Cash_Book!$C$4:$C$1008,"BEPAARI",Cash_Book!$D$4:$D$1008,"GAWALI",Cash_Book!$E$4:$E$1008,B47) -> 0 | N47: =SUMIFS(Cash_Book!$G$4:$G$1008,Cash_Book!$C$4:$C$1008,"BEPAARI",Cash_Book!$D$4:$D$1008,"CASH_ADV",Cash_Book!$E$4:$E$1008,B47) -> 0 | O47: =SUMIFS(Cash_Book!$G$4:$G$1008,Cash_Book!$C$4:$C$1008,"BEPAARI",Cash_Book!$D$4:$D$1008,"OTHER",Cash_Book!$E$4:$E$1008,B47) -> 0 | P47: =SUM(H47:O47) -> 0 | Q47: =IF(B47="","",F47-P47+E47) | R47: =SUMIFS(Cash_Book!$G$4:$G$1008,Cash_Book!$C$4:$C$1008,"BEPAARI",Cash_Book!$D$4:$D$1008,"PAYMENT",Cash_Book!$E$4:$E$1008,B47) -> 0 | S47: =IF(B47="","",Q47-R47)
A48: 44 | B48: =IF(Masters!$B$46="","",Masters!$B$46) | C48: =IF(B48="","",Masters!$C$46) | D48: =IF(B48="","",IF(Masters!$D$46="","",Masters!$D$46)) | E48: =IF(B48="",0,Masters!$E$46) -> 0 | F48: =SUMIF(Daily_Sales!$C$4:$C$503,B48,Daily_Sales!$G$4:$G$503) -> 0 | G48: =SUMIF(Daily_Sales!$C$4:$C$503,B48,Daily_Sales!$E$4:$E$503) -> 0 | H48: =IF(B48="",0,IF(D48<>"",D48*G48,F48*C48/100)) -> 0 | I48: =IF(G48>0,Masters!$Y$3,0) -> 0 | J48: =G48*Masters!$Y$4 -> 0 | K48: =SUMIFS(Cash_Book!$G$4:$G$1008,Cash_Book!$C$4:$C$1008,"BEPAARI",Cash_Book!$D$4:$D$1008,"MOTOR",Cash_Book!$E$4:$E$1008,B48) -> 0 | L48: =SUMIFS(Cash_Book!$G$4:$G$1008,Cash_Book!$C$4:$C$1008,"BEPAARI",Cash_Book!$D$4:$D$1008,"BHUSSA",Cash_Book!$E$4:$E$1008,B48) -> 0 | M48: =SUMIFS(Cash_Book!$G$4:$G$1008,Cash_Book!$C$4:$C$1008,"BEPAARI",Cash_Book!$D$4:$D$1008,"GAWALI",Cash_Book!$E$4:$E$1008,B48) -> 0 | N48: =SUMIFS(Cash_Book!$G$4:$G$1008,Cash_Book!$C$4:$C$1008,"BEPAARI",Cash_Book!$D$4:$D$1008,"CASH_ADV",Cash_Book!$E$4:$E$1008,B48) -> 0 | O48: =SUMIFS(Cash_Book!$G$4:$G$1008,Cash_Book!$C$4:$C$1008,"BEPAARI",Cash_Book!$D$4:$D$1008,"OTHER",Cash_Book!$E$4:$E$1008,B48) -> 0 | P48: =SUM(H48:O48) -> 0 | Q48: =IF(B48="","",F48-P48+E48) | R48: =SUMIFS(Cash_Book!$G$4:$G$1008,Cash_Book!$C$4:$C$1008,"BEPAARI",Cash_Book!$D$4:$D$1008,"PAYMENT",Cash_Book!$E$4:$E$1008,B48) -> 0 | S48: =IF(B48="","",Q48-R48)
A49: 45 | B49: =IF(Masters!$B$47="","",Masters!$B$47) | C49: =IF(B49="","",Masters!$C$47) | D49: =IF(B49="","",IF(Masters!$D$47="","",Masters!$D$47)) | E49: =IF(B49="",0,Masters!$E$47) -> 0 | F49: =SUMIF(Daily_Sales!$C$4:$C$503,B49,Daily_Sales!$G$4:$G$503) -> 0 | G49: =SUMIF(Daily_Sales!$C$4:$C$503,B49,Daily_Sales!$E$4:$E$503) -> 0 | H49: =IF(B49="",0,IF(D49<>"",D49*G49,F49*C49/100)) -> 0 | I49: =IF(G49>0,Masters!$Y$3,0) -> 0 | J49: =G49*Masters!$Y$4 -> 0 | K49: =SUMIFS(Cash_Book!$G$4:$G$1008,Cash_Book!$C$4:$C$1008,"BEPAARI",Cash_Book!$D$4:$D$1008,"MOTOR",Cash_Book!$E$4:$E$1008,B49) -> 0 | L49: =SUMIFS(Cash_Book!$G$4:$G$1008,Cash_Book!$C$4:$C$1008,"BEPAARI",Cash_Book!$D$4:$D$1008,"BHUSSA",Cash_Book!$E$4:$E$1008,B49) -> 0 | M49: =SUMIFS(Cash_Book!$G$4:$G$1008,Cash_Book!$C$4:$C$1008,"BEPAARI",Cash_Book!$D$4:$D$1008,"GAWALI",Cash_Book!$E$4:$E$1008,B49) -> 0 | N49: =SUMIFS(Cash_Book!$G$4:$G$1008,Cash_Book!$C$4:$C$1008,"BEPAARI",Cash_Book!$D$4:$D$1008,"CASH_ADV",Cash_Book!$E$4:$E$1008,B49) -> 0 | O49: =SUMIFS(Cash_Book!$G$4:$G$1008,Cash_Book!$C$4:$C$1008,"BEPAARI",Cash_Book!$D$4:$D$1008,"OTHER",Cash_Book!$E$4:$E$1008,B49) -> 0 | P49: =SUM(H49:O49) -> 0 | Q49: =IF(B49="","",F49-P49+E49) | R49: =SUMIFS(Cash_Book!$G$4:$G$1008,Cash_Book!$C$4:$C$1008,"BEPAARI",Cash_Book!$D$4:$D$1008,"PAYMENT",Cash_Book!$E$4:$E$1008,B49) -> 0 | S49: =IF(B49="","",Q49-R49)
A50: 46 | B50: =IF(Masters!$B$48="","",Masters!$B$48) | C50: =IF(B50="","",Masters!$C$48) | D50: =IF(B50="","",IF(Masters!$D$48="","",Masters!$D$48)) | E50: =IF(B50="",0,Masters!$E$48) -> 0 | F50: =SUMIF(Daily_Sales!$C$4:$C$503,B50,Daily_Sales!$G$4:$G$503) -> 0 | G50: =SUMIF(Daily_Sales!$C$4:$C$503,B50,Daily_Sales!$E$4:$E$503) -> 0 | H50: =IF(B50="",0,IF(D50<>"",D50*G50,F50*C50/100)) -> 0 | I50: =IF(G50>0,Masters!$Y$3,0) -> 0 | J50: =G50*Masters!$Y$4 -> 0 | K50: =SUMIFS(Cash_Book!$G$4:$G$1008,Cash_Book!$C$4:$C$1008,"BEPAARI",Cash_Book!$D$4:$D$1008,"MOTOR",Cash_Book!$E$4:$E$1008,B50) -> 0 | L50: =SUMIFS(Cash_Book!$G$4:$G$1008,Cash_Book!$C$4:$C$1008,"BEPAARI",Cash_Book!$D$4:$D$1008,"BHUSSA",Cash_Book!$E$4:$E$1008,B50) -> 0 | M50: =SUMIFS(Cash_Book!$G$4:$G$1008,Cash_Book!$C$4:$C$1008,"BEPAARI",Cash_Book!$D$4:$D$1008,"GAWALI",Cash_Book!$E$4:$E$1008,B50) -> 0 | N50: =SUMIFS(Cash_Book!$G$4:$G$1008,Cash_Book!$C$4:$C$1008,"BEPAARI",Cash_Book!$D$4:$D$1008,"CASH_ADV",Cash_Book!$E$4:$E$1008,B50) -> 0 | O50: =SUMIFS(Cash_Book!$G$4:$G$1008,Cash_Book!$C$4:$C$1008,"BEPAARI",Cash_Book!$D$4:$D$1008,"OTHER",Cash_Book!$E$4:$E$1008,B50) -> 0 | P50: =SUM(H50:O50) -> 0 | Q50: =IF(B50="","",F50-P50+E50) | R50: =SUMIFS(Cash_Book!$G$4:$G$1008,Cash_Book!$C$4:$C$1008,"BEPAARI",Cash_Book!$D$4:$D$1008,"PAYMENT",Cash_Book!$E$4:$E$1008,B50) -> 0 | S50: =IF(B50="","",Q50-R50)
A51: 47 | B51: =IF(Masters!$B$49="","",Masters!$B$49) | C51: =IF(B51="","",Masters!$C$49) | D51: =IF(B51="","",IF(Masters!$D$49="","",Masters!$D$49)) | E51: =IF(B51="",0,Masters!$E$49) -> 0 | F51: =SUMIF(Daily_Sales!$C$4:$C$503,B51,Daily_Sales!$G$4:$G$503) -> 0 | G51: =SUMIF(Daily_Sales!$C$4:$C$503,B51,Daily_Sales!$E$4:$E$503) -> 0 | H51: =IF(B51="",0,IF(D51<>"",D51*G51,F51*C51/100)) -> 0 | I51: =IF(G51>0,Masters!$Y$3,0) -> 0 | J51: =G51*Masters!$Y$4 -> 0 | K51: =SUMIFS(Cash_Book!$G$4:$G$1008,Cash_Book!$C$4:$C$1008,"BEPAARI",Cash_Book!$D$4:$D$1008,"MOTOR",Cash_Book!$E$4:$E$1008,B51) -> 0 | L51: =SUMIFS(Cash_Book!$G$4:$G$1008,Cash_Book!$C$4:$C$1008,"BEPAARI",Cash_Book!$D$4:$D$1008,"BHUSSA",Cash_Book!$E$4:$E$1008,B51) -> 0 | M51: =SUMIFS(Cash_Book!$G$4:$G$1008,Cash_Book!$C$4:$C$1008,"BEPAARI",Cash_Book!$D$4:$D$1008,"GAWALI",Cash_Book!$E$4:$E$1008,B51) -> 0 | N51: =SUMIFS(Cash_Book!$G$4:$G$1008,Cash_Book!$C$4:$C$1008,"BEPAARI",Cash_Book!$D$4:$D$1008,"CASH_ADV",Cash_Book!$E$4:$E$1008,B51) -> 0 | O51: =SUMIFS(Cash_Book!$G$4:$G$1008,Cash_Book!$C$4:$C$1008,"BEPAARI",Cash_Book!$D$4:$D$1008,"OTHER",Cash_Book!$E$4:$E$1008,B51) -> 0 | P51: =SUM(H51:O51) -> 0 | Q51: =IF(B51="","",F51-P51+E51) | R51: =SUMIFS(Cash_Book!$G$4:$G$1008,Cash_Book!$C$4:$C$1008,"BEPAARI",Cash_Book!$D$4:$D$1008,"PAYMENT",Cash_Book!$E$4:$E$1008,B51) -> 0 | S51: =IF(B51="","",Q51-R51)
A52: 48 | B52: =IF(Masters!$B$50="","",Masters!$B$50) | C52: =IF(B52="","",Masters!$C$50) | D52: =IF(B52="","",IF(Masters!$D$50="","",Masters!$D$50)) | E52: =IF(B52="",0,Masters!$E$50) -> 0 | F52: =SUMIF(Daily_Sales!$C$4:$C$503,B52,Daily_Sales!$G$4:$G$503) -> 0 | G52: =SUMIF(Daily_Sales!$C$4:$C$503,B52,Daily_Sales!$E$4:$E$503) -> 0 | H52: =IF(B52="",0,IF(D52<>"",D52*G52,F52*C52/100)) -> 0 | I52: =IF(G52>0,Masters!$Y$3,0) -> 0 | J52: =G52*Masters!$Y$4 -> 0 | K52: =SUMIFS(Cash_Book!$G$4:$G$1008,Cash_Book!$C$4:$C$1008,"BEPAARI",Cash_Book!$D$4:$D$1008,"MOTOR",Cash_Book!$E$4:$E$1008,B52) -> 0 | L52: =SUMIFS(Cash_Book!$G$4:$G$1008,Cash_Book!$C$4:$C$1008,"BEPAARI",Cash_Book!$D$4:$D$1008,"BHUSSA",Cash_Book!$E$4:$E$1008,B52) -> 0 | M52: =SUMIFS(Cash_Book!$G$4:$G$1008,Cash_Book!$C$4:$C$1008,"BEPAARI",Cash_Book!$D$4:$D$1008,"GAWALI",Cash_Book!$E$4:$E$1008,B52) -> 0 | N52: =SUMIFS(Cash_Book!$G$4:$G$1008,Cash_Book!$C$4:$C$1008,"BEPAARI",Cash_Book!$D$4:$D$1008,"CASH_ADV",Cash_Book!$E$4:$E$1008,B52) -> 0 | O52: =SUMIFS(Cash_Book!$G$4:$G$1008,Cash_Book!$C$4:$C$1008,"BEPAARI",Cash_Book!$D$4:$D$1008,"OTHER",Cash_Book!$E$4:$E$1008,B52) -> 0 | P52: =SUM(H52:O52) -> 0 | Q52: =IF(B52="","",F52-P52+E52) | R52: =SUMIFS(Cash_Book!$G$4:$G$1008,Cash_Book!$C$4:$C$1008,"BEPAARI",Cash_Book!$D$4:$D$1008,"PAYMENT",Cash_Book!$E$4:$E$1008,B52) -> 0 | S52: =IF(B52="","",Q52-R52)
A53: 49 | B53: =IF(Masters!$B$51="","",Masters!$B$51) | C53: =IF(B53="","",Masters!$C$51) | D53: =IF(B53="","",IF(Masters!$D$51="","",Masters!$D$51)) | E53: =IF(B53="",0,Masters!$E$51) -> 0 | F53: =SUMIF(Daily_Sales!$C$4:$C$503,B53,Daily_Sales!$G$4:$G$503) -> 0 | G53: =SUMIF(Daily_Sales!$C$4:$C$503,B53,Daily_Sales!$E$4:$E$503) -> 0 | H53: =IF(B53="",0,IF(D53<>"",D53*G53,F53*C53/100)) -> 0 | I53: =IF(G53>0,Masters!$Y$3,0) -> 0 | J53: =G53*Masters!$Y$4 -> 0 | K53: =SUMIFS(Cash_Book!$G$4:$G$1008,Cash_Book!$C$4:$C$1008,"BEPAARI",Cash_Book!$D$4:$D$1008,"MOTOR",Cash_Book!$E$4:$E$1008,B53) -> 0 | L53: =SUMIFS(Cash_Book!$G$4:$G$1008,Cash_Book!$C$4:$C$1008,"BEPAARI",Cash_Book!$D$4:$D$1008,"BHUSSA",Cash_Book!$E$4:$E$1008,B53) -> 0 | M53: =SUMIFS(Cash_Book!$G$4:$G$1008,Cash_Book!$C$4:$C$1008,"BEPAARI",Cash_Book!$D$4:$D$1008,"GAWALI",Cash_Book!$E$4:$E$1008,B53) -> 0 | N53: =SUMIFS(Cash_Book!$G$4:$G$1008,Cash_Book!$C$4:$C$1008,"BEPAARI",Cash_Book!$D$4:$D$1008,"CASH_ADV",Cash_Book!$E$4:$E$1008,B53) -> 0 | O53: =SUMIFS(Cash_Book!$G$4:$G$1008,Cash_Book!$C$4:$C$1008,"BEPAARI",Cash_Book!$D$4:$D$1008,"OTHER",Cash_Book!$E$4:$E$1008,B53) -> 0 | P53: =SUM(H53:O53) -> 0 | Q53: =IF(B53="","",F53-P53+E53) | R53: =SUMIFS(Cash_Book!$G$4:$G$1008,Cash_Book!$C$4:$C$1008,"BEPAARI",Cash_Book!$D$4:$D$1008,"PAYMENT",Cash_Book!$E$4:$E$1008,B53) -> 0 | S53: =IF(B53="","",Q53-R53)
A54: 50 | B54: =IF(Masters!$B$52="","",Masters!$B$52) | C54: =IF(B54="","",Masters!$C$52) | D54: =IF(B54="","",IF(Masters!$D$52="","",Masters!$D$52)) | E54: =IF(B54="",0,Masters!$E$52) -> 0 | F54: =SUMIF(Daily_Sales!$C$4:$C$503,B54,Daily_Sales!$G$4:$G$503) -> 0 | G54: =SUMIF(Daily_Sales!$C$4:$C$503,B54,Daily_Sales!$E$4:$E$503) -> 0 | H54: =IF(B54="",0,IF(D54<>"",D54*G54,F54*C54/100)) -> 0 | I54: =IF(G54>0,Masters!$Y$3,0) -> 0 | J54: =G54*Masters!$Y$4 -> 0 | K54: =SUMIFS(Cash_Book!$G$4:$G$1008,Cash_Book!$C$4:$C$1008,"BEPAARI",Cash_Book!$D$4:$D$1008,"MOTOR",Cash_Book!$E$4:$E$1008,B54) -> 0 | L54: =SUMIFS(Cash_Book!$G$4:$G$1008,Cash_Book!$C$4:$C$1008,"BEPAARI",Cash_Book!$D$4:$D$1008,"BHUSSA",Cash_Book!$E$4:$E$1008,B54) -> 0 | M54: =SUMIFS(Cash_Book!$G$4:$G$1008,Cash_Book!$C$4:$C$1008,"BEPAARI",Cash_Book!$D$4:$D$1008,"GAWALI",Cash_Book!$E$4:$E$1008,B54) -> 0 | N54: =SUMIFS(Cash_Book!$G$4:$G$1008,Cash_Book!$C$4:$C$1008,"BEPAARI",Cash_Book!$D$4:$D$1008,"CASH_ADV",Cash_Book!$E$4:$E$1008,B54) -> 0 | O54: =SUMIFS(Cash_Book!$G$4:$G$1008,Cash_Book!$C$4:$C$1008,"BEPAARI",Cash_Book!$D$4:$D$1008,"OTHER",Cash_Book!$E$4:$E$1008,B54) -> 0 | P54: =SUM(H54:O54) -> 0 | Q54: =IF(B54="","",F54-P54+E54) | R54: =SUMIFS(Cash_Book!$G$4:$G$1008,Cash_Book!$C$4:$C$1008,"BEPAARI",Cash_Book!$D$4:$D$1008,"PAYMENT",Cash_Book!$E$4:$E$1008,B54) -> 0 | S54: =IF(B54="","",Q54-R54)
A55: TOTAL | E55: =SUM(E5:E54) -> -141478 | F55: =SUM(F5:F54) -> 4962000 | G55: =SUM(G5:G54) -> 466 | H55: =SUM(H5:H54) -> 198480 | I55: =SUM(I5:I54) -> 1100 | J55: =SUM(J5:J54) -> 4660 | K55: =SUM(K5:K54) -> 109150 | L55: =SUM(L5:L54) -> 1530 | ... S55: =SUM(S5:S54) -> 889238
P57: For Balance Sheet:
Q58: Bepaari Payable (we owe) | S58: =SUMIF(S5:S54,">0",S5:S54) -> 1105792
Q59: Bepaari Overpaid (they owe) | S59: =-SUMIF(S5:S54,"<0",S5:S54) -> 216554

Sheet Dukandar_Ledger
A1: DUKANDAR LEDGER
A3: Sr | B3: Dukandar | C3: Opening | D3: Purchases | E3: Discounts | F3: Net Receivable | G3: Receipts | H3: BALANCE
A4: 1 | B4: =IF(Masters!$J$3="","",Masters!$J$3) -> SAKIM | C4: =IF(B4="",0,Masters!$K$3) -> 113500 | D4: =SUMIF(Daily_Sales!$D$4:$D$503,B4,Daily_Sales!$G$4:$G$503) -> 98800 | E4: =SUMIF(Daily_Sales!$D$4:$D$503,B4,Daily_Sales!$H$4:$H$503) -> 0 | F4: =IF(B4="","",D4-E4+C4) -> 212300 | G4: =SUMIFS(Cash_Book!$G$4:$G$1008,Cash_Book!$C$4:$C$1008,"DUKANDAR",Cash_Book!$D$4:$D$1008,"RECEIPT",Cash_Book!$E$4:$E$1008,B4) -> 50000 | H4: =IF(B4="","",F4-G4) -> 162300
A5: 2 | B5: =IF(Masters!$J$4="","",Masters!$J$4) -> SHARIK | C5: =IF(B5="",0,Masters!$K$4) -> 879000 | D5: =SUMIF(Daily_Sales!$D$4:$D$503,B5,Daily_Sales!$G$4:$G$503) -> 0 | E5: =SUMIF(Daily_Sales!$D$4:$D$503,B5,Daily_Sales!$H$4:$H$503) -> 0 | F5: =IF(B5="","",D5-E5+C5) -> 879000 | G5: =SUMIFS(Cash_Book!$G$4:$G$1008,Cash_Book!$C$4:$C$1008,"DUKANDAR",Cash_Book!$D$4:$D$1008,"RECEIPT",Cash_Book!$E$4:$E$1008,B5) -> 300000 | H5: =IF(B5="","",F5-G5) -> 579000
A6: 3 | B6: =IF(Masters!$J$5="","",Masters!$J$5) -> YUNUS | C6: =IF(B6="",0,Masters!$K$5) -> 94931 | D6: =SUMIF(Daily_Sales!$D$4:$D$503,B6,Daily_Sales!$G$4:$G$503) -> 251300 | E6: =SUMIF(Daily_Sales!$D$4:$D$503,B6,Daily_Sales!$H$4:$H$503) -> 5000 | F6: =IF(B6="","",D6-E6+C6) -> 341231 | G6: =SUMIFS(Cash_Book!$G$4:$G$1008,Cash_Book!$C$4:$C$1008,"DUKANDAR",Cash_Book!$D$4:$D$1008,"RECEIPT",Cash_Book!$E$4:$E$1008,B6) -> 208779 | H6: =IF(B6="","",F6-G6) -> 132452
A7: 4 | B7: =IF(Masters!$J$6="","",Masters!$J$6) -> MUDASSIR | C7: =IF(B7="",0,Masters!$K$6) -> 516778 | D7: =SUMIF(Daily_Sales!$D$4:$D$503,B7,Daily_Sales!$G$4:$G$503) -> 195500 | E7: =SUMIF(Daily_Sales!$D$4:$D$503,B7,Daily_Sales!$H$4:$H$503) -> 0 | F7: =IF(B7="","",D7-E7+C7) -> 712278 | G7: =SUMIFS(Cash_Book!$G$4:$G$1008,Cash_Book!$C$4:$C$1008,"DUKANDAR",Cash_Book!$D$4:$D$1008,"RECEIPT",Cash_Book!$E$4:$E$1008,B7) -> 100000 | H7: =IF(B7="","",F7-G7) -> 612278
A8: 5 | B8: =IF(Masters!$J$7="","",Masters!$J$7) -> ARIF | C8: =IF(B8="",0,Masters!$K$7) -> 187650 | D8: =SUMIF(Daily_Sales!$D$4:$D$503,B8,Daily_Sales!$G$4:$G$503) -> 0 | E8: =SUMIF(Daily_Sales!$D$4:$D$503,B8,Daily_Sales!$H$4:$H$503) -> 0 | F8: =IF(B8="","",D8-E8+C8) -> 187650 | G8: =SUMIFS(Cash_Book!$G$4:$G$1008,Cash_Book!$C$4:$C$1008,"DUKANDAR",Cash_Book!$D$4:$D$1008,"RECEIPT",Cash_Book!$E$4:$E$1008,B8) -> 167700 | H8: =IF(B8="","",F8-G8) -> 19950
A9: 6 | B9: =IF(Masters!$J$8="","",Masters!$J$8) -> SHOEB BYCULLA | C9: =IF(B9="",0,Masters!$K$8) -> 0 | D9: =SUMIF(Daily_Sales!$D$4:$D$503,B9,Daily_Sales!$G$4:$G$503) -> 112750 | E9: =SUMIF(Daily_Sales!$D$4:$D$503,B9,Daily_Sales!$H$4:$H$503) -> 2750 | F9: =IF(B9="","",D9-E9+C9) -> 110000 | G9: =SUMIFS(Cash_Book!$G$4:$G$1008,Cash_Book!$C$4:$C$1008,"DUKANDAR",Cash_Book!$D$4:$D$1008,"RECEIPT",Cash_Book!$E$4:$E$1008,B9) -> 0 | H9: =IF(B9="","",F9-G9) -> 110000
A10: 7 | B10: =IF(Masters!$J$9="","",Masters!$J$9) -> ISLAM D | C10: =IF(B10="",0,Masters!$K$9) -> 100000 | D10: =SUMIF(Daily_Sales!$D$4:$D$503,B10,Daily_Sales!$G$4:$G$503) -> 0 | E10: =SUMIF(Daily_Sales!$D$4:$D$503,B10,Daily_Sales!$H$4:$H$503) -> 0 | F10: =IF(B10="","",D10-E10+C10) -> 100000 | G10: =SUMIFS(Cash_Book!$G$4:$G$1008,Cash_Book!$C$4:$C$1008,"DUKANDAR",Cash_Book!$D$4:$D$1008,"RECEIPT",Cash_Book!$E$4:$E$1008,B10) -> 100000 | H10: =IF(B10="","",F10-G10) -> 0
A11: 8 | B11: =IF(Masters!$J$10="","",Masters!$J$10) -> MEHMOOD MADH | C11: =IF(B11="",0,Masters!$K$10) -> 15000 | D11: =SUMIF(Daily_Sales!$D$4:$D$503,B11,Daily_Sales!$G$4:$G$503) -> 184900 | E11: =SUMIF(Daily_Sales!$D$4:$D$503,B11,Daily_Sales!$H$4:$H$503) -> 0 | F11: =IF(B11="","",D11-E11+C11) -> 199900 | G11: =SUMIFS(Cash_Book!$G$4:$G$1008,Cash_Book!$C$4:$C$1008,"DUKANDAR",Cash_Book!$D$4:$D$1008,"RECEIPT",Cash_Book!$E$4:$E$1008,B11) -> 20000 | H11: =IF(B11="","",F11-G11) -> 179900
A12: 9 | B12: =IF(Masters!$J$11="","",Masters!$J$11) -> MOBIN CHIPLUN | C12: =IF(B12="",0,Masters!$K$11) -> 486250 | D12: =SUMIF(Daily_Sales!$D$4:$D$503,B12,Daily_Sales!$G$4:$G$503) -> 0 | E12: =SUMIF(Daily_Sales!$D$4:$D$503,B12,Daily_Sales!$H$4:$H$503) -> 0 | F12: =IF(B12="","",D12-E12+C12) -> 486250 | G12: =SUMIFS(Cash_Book!$G$4:$G$1008,Cash_Book!$C$4:$C$1008,"DUKANDAR",Cash_Book!$D$4:$D$1008,"RECEIPT",Cash_Book!$E$4:$E$1008,B12) -> 206000 | H12: =IF(B12="","",F12-G12) -> 280250
A13: 10 | B13: =IF(Masters!$J$12="","",Masters!$J$12) -> JALIL | C13: =IF(B13="",0,Masters!$K$12) -> 90950 | D13: =SUMIF(Daily_Sales!$D$4:$D$503,B13,Daily_Sales!$G$4:$G$503) -> 146500 | E13: =SUMIF(Daily_Sales!$D$4:$D$503,B13,Daily_Sales!$H$4:$H$503) -> 0 | F13: =IF(B13="","",D13-E13+C13) -> 237450 | G13: =SUMIFS(Cash_Book!$G$4:$G$1008,Cash_Book!$C$4:$C$1008,"DUKANDAR",Cash_Book!$D$4:$D$1008,"RECEIPT",Cash_Book!$E$4:$E$1008,B13) -> 50000 | H13: =IF(B13="","",F13-G13) -> 187450
A14: 11 | B14: =IF(Masters!$J$13="","",Masters!$J$13) -> IRFAN JOGESHWARI | C14: =IF(B14="",0,Masters!$K$13) -> 0 | D14: =SUMIF(Daily_Sales!$D$4:$D$503,B14,Daily_Sales!$G$4:$G$503) -> 0 | E14: =SUMIF(Daily_Sales!$D$4:$D$503,B14,Daily_Sales!$H$4:$H$503) -> 0 | F14: =IF(B14="","",D14-E14+C14) -> 0 | G14: =SUMIFS(Cash_Book!$G$4:$G$1008,Cash_Book!$C$4:$C$1008,"DUKANDAR",Cash_Book!$D$4:$D$1008,"RECEIPT",Cash_Book!$E$4:$E$1008,B14) -> 0 | H14: =IF(B14="","",F14-G14) -> 0
A15: 12 | B15: =IF(Masters!$J$14="","",Masters!$J$14) -> YUNUS DOMBIVLI | C15: =IF(B15="",0,Masters!$K$14) -> 59662 | D15: =SUMIF(Daily_Sales!$D$4:$D$503,B15,Daily_Sales!$G$4:$G$503) -> 0 | E15: =SUMIF(Daily_Sales!$D$4:$D$503,B15,Daily_Sales!$H$4:$H$503) -> 0 | F15: =IF(B15="","",D15-E15+C15) -> 59662 | G15: =SUMIFS(Cash_Book!$G$4:$G$1008,Cash_Book!$C$4:$C$1008,"DUKANDAR",Cash_Book!$D$4:$D$1008,"RECEIPT",Cash_Book!$E$4:$E$1008,B15) -> 40000 | H15: =IF(B15="","",F15-G15) -> 19662
A16: 13 | B16: =IF(Masters!$J$15="","",Masters!$J$15) -> IFTEKHAR PUNE | C16: =IF(B16="",0,Masters!$K$15) -> 2000 | D16: =SUMIF(Daily_Sales!$D$4:$D$503,B16,Daily_Sales!$G$4:$G$503) -> 168800 | E16: =SUMIF(Daily_Sales!$D$4:$D$503,B16,Daily_Sales!$H$4:$H$503) -> 0 | F16: =IF(B16="","",D16-E16+C16) -> 170800 | G16: =SUMIFS(Cash_Book!$G$4:$G$1008,Cash_Book!$C$4:$C$1008,"DUKANDAR",Cash_Book!$D$4:$D$1008,"RECEIPT",Cash_Book!$E$4:$E$1008,B16) -> 0 | H16: =IF(B16="","",F16-G16) -> 170800
A17: 14 | B17: =IF(Masters!$J$16="","",Masters!$J$16) -> LALA/ASIF | C17: =IF(B17="",0,Masters!$K$16) -> 0 | D17: =SUMIF(Daily_Sales!$D$4:$D$503,B17,Daily_Sales!$G$4:$G$503) -> 0 | E17: =SUMIF(Daily_Sales!$D$4:$D$503,B17,Daily_Sales!$H$4:$H$503) -> 0 | F17: =IF(B17="","",D17-E17+C17) -> 0 | G17: =SUMIFS(Cash_Book!$G$4:$G$1008,Cash_Book!$C$4:$C$1008,"DUKANDAR",Cash_Book!$D$4:$D$1008,"RECEIPT",Cash_Book!$E$4:$E$1008,B17) -> 0 | H17: =IF(B17="","",F17-G17) -> 0
A18: 15 | B18: =IF(Masters!$J$17="","",Masters!$J$17) -> JAFER KASHIMIRA | C18: =IF(B18="",0,Masters!$K$17) -> 92500 | D18: =SUMIF(Daily_Sales!$D$4:$D$503,B18,Daily_Sales!$G$4:$G$503) -> 0 | E18: =SUMIF(Daily_Sales!$D$4:$D$503,B18,Daily_Sales!$H$4:$H$503) -> 0 | F18: =IF(B18="","",D18-E18+C18) -> 92500 | G18: =SUMIFS(Cash_Book!$G$4:$G$1008,Cash_Book!$C$4:$C$1008,"DUKANDAR",Cash_Book!$D$4:$D$1008,"RECEIPT",Cash_Book!$E$4:$E$1008,B18) -> 100000 | H18: =IF(B18="","",F18-G18) -> -7500
A19: 16 | B19: =IF(Masters!$J$18="","",Masters!$J$18) -> HANIF KALAM | C19: =IF(B19="",0,Masters!$K$18) -> 0 | D19: =SUMIF(Daily_Sales!$D$4:$D$503,B19,Daily_Sales!$G$4:$G$503) -> 0 | E19: =SUMIF(Daily_Sales!$D$4:$D$503,B19,Daily_Sales!$H$4:$H$503) -> 0 | F19: =IF(B19="","",D19-E19+C19) -> 0 | G19: =SUMIFS(Cash_Book!$G$4:$G$1008,Cash_Book!$C$4:$C$1008,"DUKANDAR",Cash_Book!$D$4:$D$1008,"RECEIPT",Cash_Book!$E$4:$E$1008,B19) -> 0 | H19: =IF(B19="","",F19-G19) -> 0
A20: 17 | B20: =IF(Masters!$J$19="","",Masters!$J$19) -> SAUD K | C20: =IF(B20="",0,Masters!$K$19) -> 0 | D20: =SUMIF(Daily_Sales!$D$4:$D$503,B20,Daily_Sales!$G$4:$G$503) -> 272700 | E20: =SUMIF(Daily_Sales!$D$4:$D$503,B20,Daily_Sales!$H$4:$H$503) -> 8700 | F20: =IF(B20="","",D20-E20+C20) -> 264000 | G20: =SUMIFS(Cash_Book!$G$4:$G$1008,Cash_Book!$C$4:$C$1008,"DUKANDAR",Cash_Book!$D$4:$D$1008,"RECEIPT",Cash_Book!$E$4:$E$1008,B20) -> 0 | H20: =IF(B20="","",F20-G20) -> 264000
A21: 18 | B21: =IF(Masters!$J$20="","",Masters!$J$20) -> AKRAM | C21: =IF(B21="",0,Masters!$K$20) -> 0 | D21: =SUMIF(Daily_Sales!$D$4:$D$503,B21,Daily_Sales!$G$4:$G$503) -> 0 | E21: =SUMIF(Daily_Sales!$D$4:$D$503,B21,Daily_Sales!$H$4:$H$503) -> 0 | F21: =IF(B21="","",D21-E21+C21) -> 0 | G21: =SUMIFS(Cash_Book!$G$4:$G$1008,Cash_Book!$C$4:$C$1008,"DUKANDAR",Cash_Book!$D$4:$D$1008,"RECEIPT",Cash_Book!$E$4:$E$1008,B21) -> 0 | H21: =IF(B21="","",F21-G21) -> 0
A22: 19 | B22: =IF(Masters!$J$21="","",Masters!$J$21) -> WAHID | C22: =IF(B22="",0,Masters!$K$21) -> 4000 | D22: =SUMIF(Daily_Sales!$D$4:$D$503,B22,Daily_Sales!$G$4:$G$503) -> 0 | E22: =SUMIF(Daily_Sales!$D$4:$D$503,B22,Daily_Sales!$H$4:$H$503) -> 0 | F22: =IF(B22="","",D22-E22+C22) -> 4000 | G22: =SUMIFS(Cash_Book!$G$4:$G$1008,Cash_Book!$C$4:$C$1008,"DUKANDAR",Cash_Book!$D$4:$D$1008,"RECEIPT",Cash_Book!$E$4:$E$1008,B22) -> 4000 | H22: =IF(B22="","",F22-G22) -> 0
A23: 20 | B23: =IF(Masters!$J$22="","",Masters!$J$22) -> VAZIR | C23: =IF(B23="",0,Masters!$K$22) -> 134750 | D23: =SUMIF(Daily_Sales!$D$4:$D$503,B23,Daily_Sales!$G$4:$G$503) -> 397000 | E23: =SUMIF(Daily_Sales!$D$4:$D$503,B23,Daily_Sales!$H$4:$H$503) -> 0 | F23: =IF(B23="","",D23-E23+C23) -> 531750 | G23: =SUMIFS(Cash_Book!$G$4:$G$1008,Cash_Book!$C$4:$C$1008,"DUKANDAR",Cash_Book!$D$4:$D$1008,"RECEIPT",Cash_Book!$E$4:$E$1008,B23) -> 0 | H23: =IF(B23="","",F23-G23) -> 531750
A24: 21 | B24: =IF(Masters!$J$23="","",Masters!$J$23) -> ISMAIL SOPARA | C24: =IF(B24="",0,Masters!$K$23) -> 0 | D24: =SUMIF(Daily_Sales!$D$4:$D$503,B24,Daily_Sales!$G$4:$G$503) -> 0 | E24: =SUMIF(Daily_Sales!$D$4:$D$503,B24,Daily_Sales!$H$4:$H$503) -> 0 | F24: =IF(B24="","",D24-E24+C24) -> 0 | G24: =SUMIFS(Cash_Book!$G$4:$G$1008,Cash_Book!$C$4:$C$1008,"DUKANDAR",Cash_Book!$D$4:$D$1008,"RECEIPT",Cash_Book!$E$4:$E$1008,B24) -> 0 | H24: =IF(B24="","",F24-G24) -> 0
A25: 22 | B25: =IF(Masters!$J$24="","",Masters!$J$24) -> ARIF CHINCHOTI | C25: =IF(B25="",0,Masters!$K$24) -> 0 | D25: =SUMIF(Daily_Sales!$D$4:$D$503,B25,Daily_Sales!$G$4:$G$503) -> 0 | E25: =SUMIF(Daily_Sales!$D$4:$D$503,B25,Daily_Sales!$H$4:$H$503) -> 0 | F25: =IF(B25="","",D25-E25+C25) -> 0 | G25: =SUMIFS(Cash_Book!$G$4:$G$1008,Cash_Book!$C$4:$C$1008,"DUKANDAR",Cash_Book!$D$4:$D$1008,"RECEIPT",Cash_Book!$E$4:$E$1008,B25) -> 0 | H25: =IF(B25="","",F25-G25) -> 0
A26: 23 | B26: =IF(Masters!$J$25="","",Masters!$J$25) -> NADEEM BHIWANDI | C26: =IF(B26="",0,Masters!$K$25) -> 265000 | D26: =SUMIF(Daily_Sales!$D$4:$D$503,B26,Daily_Sales!$G$4:$G$503) -> 0 | E26: =SUMIF(Daily_Sales!$D$4:$D$503,B26,Daily_Sales!$H$4:$H$503) -> 0 | F26: =IF(B26="","",D26-E26+C26) -> 265000 | G26: =SUMIFS(Cash_Book!$G$4:$G$1008,Cash_Book!$C$4:$C$1008,"DUKANDAR",Cash_Book!$D$4:$D$1008,"RECEIPT",Cash_Book!$E$4:$E$1008,B26) -> 229687 | H26: =IF(B26="","",F26-G26) -> 35313
A27: 24 | B27: =IF(Masters!$J$26="","",Masters!$J$26) -> GABBAR | C27: =IF(B27="",0,Masters!$K$26) -> 33050 | D27: =SUMIF(Daily_Sales!$D$4:$D$503,B27,Daily_Sales!$G$4:$G$503) -> 155000 | E27: =SUMIF(Daily_Sales!$D$4:$D$503,B27,Daily_Sales!$H$4:$H$503) -> 2000 | F27: =IF(B27="","",D27-E27+C27) -> 186050 | G27: =SUMIFS(Cash_Book!$G$4:$G$1008,Cash_Book!$C$4:$C$1008,"DUKANDAR",Cash_Book!$D$4:$D$1008,"RECEIPT",Cash_Book!$E$4:$E$1008,B27) -> 0 | H27: =IF(B27="","",F27-G27) -> 186050
A28: 25 | B28: =IF(Masters!$J$27="","",Masters!$J$27) -> BABU GABBAR | C28: =IF(B28="",0,Masters!$K$27) -> 50000 | D28: =SUMIF(Daily_Sales!$D$4:$D$503,B28,Daily_Sales!$G$4:$G$503) -> 0 | E28: =SUMIF(Daily_Sales!$D$4:$D$503,B28,Daily_Sales!$H$4:$H$503) -> 0 | F28: =IF(B28="","",D28-E28+C28) -> 50000 | G28: =SUMIFS(Cash_Book!$G$4:$G$1008,Cash_Book!$C$4:$C$1008,"DUKANDAR",Cash_Book!$D$4:$D$1008,"RECEIPT",Cash_Book!$E$4:$E$1008,B28) -> 0 | H28: =IF(B28="","",F28-G28) -> 50000
A29: 26 | B29: =IF(Masters!$J$28="","",Masters!$J$28) -> BABU TALOJA | C29: =IF(B29="",0,Masters!$K$28) -> 2600 | D29: =SUMIF(Daily_Sales!$D$4:$D$503,B29,Daily_Sales!$G$4:$G$503) -> 0 | E29: =SUMIF(Daily_Sales!$D$4:$D$503,B29,Daily_Sales!$H$4:$H$503) -> 0 | F29: =IF(B29="","",D29-E29+C29) -> 2600 | G29: =SUMIFS(Cash_Book!$G$4:$G$1008,Cash_Book!$C$4:$C$1008,"DUKANDAR",Cash_Book!$D$4:$D$1008,"RECEIPT",Cash_Book!$E$4:$E$1008,B29) -> 0 | H29: =IF(B29="","",F29-G29) -> 2600
A30: 27 | B30: =IF(Masters!$J$29="","",Masters!$J$29) -> SHAKIL KON | C30: =IF(B30="",0,Masters!$K$29) -> 34000 | D30: =SUMIF(Daily_Sales!$D$4:$D$503,B30,Daily_Sales!$G$4:$G$503) -> 206250 | E30: =SUMIF(Daily_Sales!$D$4:$D$503,B30,Daily_Sales!$H$4:$H$503) -> 0 | F30: =IF(B30="","",D30-E30+C30) -> 240250 | G30: =SUMIFS(Cash_Book!$G$4:$G$1008,Cash_Book!$C$4:$C$1008,"DUKANDAR",Cash_Book!$D$4:$D$1008,"RECEIPT",Cash_Book!$E$4:$E$1008,B30) -> 34000 | H30: =IF(B30="","",F30-G30) -> 206250
A31: 28 | B31: =IF(Masters!$J$30="","",Masters!$J$30) -> PARVEZ | C31: =IF(B31="",0,Masters!$K$30) -> 0 | D31: =SUMIF(Daily_Sales!$D$4:$D$503,B31,Daily_Sales!$G$4:$G$503) -> 248250 | E31: =SUMIF(Daily_Sales!$D$4:$D$503,B31,Daily_Sales!$H$4:$H$503) -> 0 | F31: =IF(B31="","",D31-E31+C31) -> 248250 | G31: =SUMIFS(Cash_Book!$G$4:$G$1008,Cash_Book!$C$4:$C$1008,"DUKANDAR",Cash_Book!$D$4:$D$1008,"RECEIPT",Cash_Book!$E$4:$E$1008,B31) -> 0 | H31: =IF(B31="","",F31-G31) -> 248250
A32: 29 | B32: =IF(Masters!$J$31="","",Masters!$J$31) -> I CHO CHO | C32: =IF(B32="",0,Masters!$K$31) -> 20500 | D32: =SUMIF(Daily_Sales!$D$4:$D$503,B32,Daily_Sales!$G$4:$G$503) -> 0 | E32: =SUMIF(Daily_Sales!$D$4:$D$503,B32,Daily_Sales!$H$4:$H$503) -> 0 | F32: =IF(B32="","",D32-E32+C32) -> 20500 | G32: =SUMIFS(Cash_Book!$G$4:$G$1008,Cash_Book!$C$4:$C$1008,"DUKANDAR",Cash_Book!$D$4:$D$1008,"RECEIPT",Cash_Book!$E$4:$E$1008,B32) -> 0 | H32: =IF(B32="","",F32-G32) -> 20500
A33: 30 | B33: =IF(Masters!$J$32="","",Masters!$J$32) -> MD VIRAR | C33: =IF(B33="",0,Masters!$K$32) -> 1900 | D33: =SUMIF(Daily_Sales!$D$4:$D$503,B33,Daily_Sales!$G$4:$G$503) -> 0 | E33: =SUMIF(Daily_Sales!$D$4:$D$503,B33,Daily_Sales!$H$4:$H$503) -> 0 | F33: =IF(B33="","",D33-E33+C33) -> 1900 | G33: =SUMIFS(Cash_Book!$G$4:$G$1008,Cash_Book!$C$4:$C$1008,"DUKANDAR",Cash_Book!$D$4:$D$1008,"RECEIPT",Cash_Book!$E$4:$E$1008,B33) -> 0 | H33: =IF(B33="","",F33-G33) -> 1900
A34: 31 | B34: =IF(Masters!$J$33="","",Masters!$J$33) -> MAYA | C34: =IF(B34="",0,Masters!$K$33) -> 11000 | D34: =SUMIF(Daily_Sales!$D$4:$D$503,B34,Daily_Sales!$G$4:$G$503) -> 0 | E34: =SUMIF(Daily_Sales!$D$4:$D$503,B34,Daily_Sales!$H$4:$H$503) -> 0 | F34: =IF(B34="","",D34-E34+C34) -> 11000 | G34: =SUMIFS(Cash_Book!$G$4:$G$1008,Cash_Book!$C$4:$C$1008,"DUKANDAR",Cash_Book!$D$4:$D$1008,"RECEIPT",Cash_Book!$E$4:$E$1008,B34) -> 0 | H34: =IF(B34="","",F34-G34) -> 11000
A35: 32 | B35: =IF(Masters!$J$34="","",Masters!$J$34) -> NAEEM THORPE | C35: =IF(B35="",0,Masters!$K$34) -> 0 | D35: =SUMIF(Daily_Sales!$D$4:$D$503,B35,Daily_Sales!$G$4:$G$503) -> 0 | E35: =SUMIF(Daily_Sales!$D$4:$D$503,B35,Daily_Sales!$H$4:$H$503) -> 0 | F35: =IF(B35="","",D35-E35+C35) -> 0 | G35: =SUMIFS(Cash_Book!$G$4:$G$1008,Cash_Book!$C$4:$C$1008,"DUKANDAR",Cash_Book!$D$4:$D$1008,"RECEIPT",Cash_Book!$E$4:$E$1008,B35) -> 0 | H35: =IF(B35="","",F35-G35) -> 0
A36: 33 | B36: =IF(Masters!$J$35="","",Masters!$J$35) -> CHAND | C36: =IF(B36="",0,Masters!$K$35) -> 59000 | D36: =SUMIF(Daily_Sales!$D$4:$D$503,B36,Daily_Sales!$G$4:$G$503) -> 0 | E36: =SUMIF(Daily_Sales!$D$4:$D$503,B36,Daily_Sales!$H$4:$H$503) -> 0 | F36: =IF(B36="","",D36-E36+C36) -> 59000 | G36: =SUMIFS(Cash_Book!$G$4:$G$1008,Cash_Book!$C$4:$C$1008,"DUKANDAR",Cash_Book!$D$4:$D$1008,"RECEIPT",Cash_Book!$E$4:$E$1008,B36) -> 50000 | H36: =IF(B36="","",F36-G36) -> 9000
A37: 34 | B37: =IF(Masters!$J$36="","",Masters!$J$36) -> ASIF GOREGAON | C37: =IF(B37="",0,Masters!$K$36) -> 57550 | D37: =SUMIF(Daily_Sales!$D$4:$D$503,B37,Daily_Sales!$G$4:$G$503) -> 0 | E37: =SUMIF(Daily_Sales!$D$4:$D$503,B37,Daily_Sales!$H$4:$H$503) -> 0 | F37: =IF(B37="","",D37-E37+C37) -> 57550 | G37: =SUMIFS(Cash_Book!$G$4:$G$1008,Cash_Book!$C$4:$C$1008,"DUKANDAR",Cash_Book!$D$4:$D$1008,"RECEIPT",Cash_Book!$E$4:$E$1008,B37) -> 0 | H37: =IF(B37="","",F37-G37) -> 57550
A38: 35 | B38: =IF(Masters!$J$37="","",Masters!$J$37) -> SOHAIL MAROL | C38: =IF(B38="",0,Masters!$K$37) -> 0 | D38: =SUMIF(Daily_Sales!$D$4:$D$503,B38,Daily_Sales!$G$4:$G$503) -> 0 | E38: =SUMIF(Daily_Sales!$D$4:$D$503,B38,Daily_Sales!$H$4:$H$503) -> 0 | F38: =IF(B38="","",D38-E38+C38) -> 0 | G38: =SUMIFS(Cash_Book!$G$4:$G$1008,Cash_Book!$C$4:$C$1008,"DUKANDAR",Cash_Book!$D$4:$D$1008,"RECEIPT",Cash_Book!$E$4:$E$1008,B38) -> 0 | H38: =IF(B38="","",F38-G38) -> 0
A39: 36 | B39: =IF(Masters!$J$38="","",Masters!$J$38) -> ANEES KM | C39: =IF(B39="",0,Masters!$K$38) -> 70000 | D39: =SUMIF(Daily_Sales!$D$4:$D$503,B39,Daily_Sales!$G$4:$G$503) -> 0 | E39: =SUMIF(Daily_Sales!$D$4:$D$503,B39,Daily_Sales!$H$4:$H$503) -> 0 | F39: =IF(B39="","",D39-E39+C39) -> 70000 | G39: =SUMIFS(Cash_Book!$G$4:$G$1008,Cash_Book!$C$4:$C$1008,"DUKANDAR",Cash_Book!$D$4:$D$1008,"RECEIPT",Cash_Book!$E$4:$E$1008,B39) -> 30000 | H39: =IF(B39="","",F39-G39) -> 40000
A40: 37 | B40: =IF(Masters!$J$39="","",Masters!$J$39) -> RAFIQ AHMED HAJI | C40: =IF(B40="",0,Masters!$K$39) -> 356250 | D40: =SUMIF(Daily_Sales!$D$4:$D$503,B40,Daily_Sales!$G$4:$G$503) -> 0 | E40: =SUMIF(Daily_Sales!$D$4:$D$503,B40,Daily_Sales!$H$4:$H$503) -> 0 | F40: =IF(B40="","",D40-E40+C40) -> 356250 | G40: =SUMIFS(Cash_Book!$G$4:$G$1008,Cash_Book!$C$4:$C$1008,"DUKANDAR",Cash_Book!$D$4:$D$1008,"RECEIPT",Cash_Book!$E$4:$E$1008,B40) -> 356250 | H40: =IF(B40="","",F40-G40) -> 0
A41: 38 | B41: =IF(Masters!$J$40="","",Masters!$J$40) -> ABP - MAJEED THANA | C41: =IF(B41="",0,Masters!$K$40) -> 0 | D41: =SUMIF(Daily_Sales!$D$4:$D$503,B41,Daily_Sales!$G$4:$G$503) -> 0 | E41: =SUMIF(Daily_Sales!$D$4:$D$503,B41,Daily_Sales!$H$4:$H$503) -> 0 | F41: =IF(B41="","",D41-E41+C41) -> 0 | G41: =SUMIFS(Cash_Book!$G$4:$G$1008,Cash_Book!$C$4:$C$1008,"DUKANDAR",Cash_Book!$D$4:$D$1008,"RECEIPT",Cash_Book!$E$4:$E$1008,B41) -> 0 | H41: =IF(B41="","",F41-G41) -> 0
A42: 39 | B42: =IF(Masters!$J$41="","",Masters!$J$41) -> ABP - MAJNU | C42: =IF(B42="",0,Masters!$K$41) -> 0 | D42: =SUMIF(Daily_Sales!$D$4:$D$503,B42,Daily_Sales!$G$4:$G$503) -> 0 | E42: =SUMIF(Daily_Sales!$D$4:$D$503,B42,Daily_Sales!$H$4:$H$503) -> 0 | F42: =IF(B42="","",D42-E42+C42) -> 0 | G42: =SUMIFS(Cash_Book!$G$4:$G$1008,Cash_Book!$C$4:$C$1008,"DUKANDAR",Cash_Book!$D$4:$D$1008,"RECEIPT",Cash_Book!$E$4:$E$1008,B42) -> 0 | H42: =IF(B42="","",F42-G42) -> 0
A43: 40 | B43: =IF(Masters!$J$42="","",Masters!$J$42) -> MEHBOOB JOG | C43: =IF(B43="",0,Masters!$K$42) -> 98500 | D43: =SUMIF(Daily_Sales!$D$4:$D$503,B43,Daily_Sales!$G$4:$G$503) -> 0 | E43: =SUMIF(Daily_Sales!$D$4:$D$503,B43,Daily_Sales!$H$4:$H$503) -> 0 | F43: =IF(B43="","",D43-E43+C43) -> 98500 | G43: =SUMIFS(Cash_Book!$G$4:$G$1008,Cash_Book!$C$4:$C$1008,"DUKANDAR",Cash_Book!$D$4:$D$1008,"RECEIPT",Cash_Book!$E$4:$E$1008,B43) -> 98500 | H43: =IF(B43="","",F43-G43) -> 0
A44: 41 | B44: =IF(Masters!$J$43="","",Masters!$J$43) -> SIRAJ KURLA | C44: =IF(B44="",0,Masters!$K$43) -> 388000 | D44: =SUMIF(Daily_Sales!$D$4:$D$503,B44,Daily_Sales!$G$4:$G$503) -> 0 | E44: =SUMIF(Daily_Sales!$D$4:$D$503,B44,Daily_Sales!$H$4:$H$503) -> 0 | F44: =IF(B44="","",D44-E44+C44) -> 388000 | G44: =SUMIFS(Cash_Book!$G$4:$G$1008,Cash_Book!$C$4:$C$1008,"DUKANDAR",Cash_Book!$D$4:$D$1008,"RECEIPT",Cash_Book!$E$4:$E$1008,B44) -> 71000 | H44: =IF(B44="","",F44-G44) -> 317000
A45: 42 | B45: =IF(Masters!$J$44="","",Masters!$J$44) -> ZUBAIR AZEEZ | C45: =IF(B45="",0,Masters!$K$44) -> 30000 | D45: =SUMIF(Daily_Sales!$D$4:$D$503,B45,Daily_Sales!$G$4:$G$503) -> 0 | E45: =SUMIF(Daily_Sales!$D$4:$D$503,B45,Daily_Sales!$H$4:$H$503) -> 0 | F45: =IF(B45="","",D45-E45+C45) -> 30000 | G45: =SUMIFS(Cash_Book!$G$4:$G$1008,Cash_Book!$C$4:$C$1008,"DUKANDAR",Cash_Book!$D$4:$D$1008,"RECEIPT",Cash_Book!$E$4:$E$1008,B45) -> 0 | H45: =IF(B45="","",F45-G45) -> 30000
A46: 43 | B46: =IF(Masters!$J$45="","",Masters!$J$45) -> BABBU BYC | C46: =IF(B46="",0,Masters!$K$45) -> 192000 | D46: =SUMIF(Daily_Sales!$D$4:$D$503,B46,Daily_Sales!$G$4:$G$503) -> 0 | E46: =SUMIF(Daily_Sales!$D$4:$D$503,B46,Daily_Sales!$H$4:$H$503) -> 0 | F46: =IF(B46="","",D46-E46+C46) -> 192000 | G46: =SUMIFS(Cash_Book!$G$4:$G$1008,Cash_Book!$C$4:$C$1008,"DUKANDAR",Cash_Book!$D$4:$D$1008,"RECEIPT",Cash_Book!$E$4:$E$1008,B46) -> 100000 | H46: =IF(B46="","",F46-G46) -> 92000
A47: 44 | B47: =IF(Masters!$J$46="","",Masters!$J$46) -> NAWAZ V | C47: =IF(B47="",0,Masters!$K$46) -> 148800 | D47: =SUMIF(Daily_Sales!$D$4:$D$503,B47,Daily_Sales!$G$4:$G$503) -> 116600 | E47: =SUMIF(Daily_Sales!$D$4:$D$503,B47,Daily_Sales!$H$4:$H$503) -> 1100 | F47: =IF(B47="","",D47-E47+C47) -> 264300 | G47: =SUMIFS(Cash_Book!$G$4:$G$1008,Cash_Book!$C$4:$C$1008,"DUKANDAR",Cash_Book!$D$4:$D$1008,"RECEIPT",Cash_Book!$E$4:$E$1008,B47) -> 264300 | H47: =IF(B47="","",F47-G47) -> 0
A48: 45 | B48: =IF(Masters!$J$47="","",Masters!$J$47) -> LIYAQAT | C48: =IF(B48="",0,Masters!$K$47) -> 7500 | D48: =SUMIF(Daily_Sales!$D$4:$D$503,B48,Daily_Sales!$G$4:$G$503) -> 0 | E48: =SUMIF(Daily_Sales!$D$4:$D$503,B48,Daily_Sales!$H$4:$H$503) -> 0 | F48: =IF(B48="","",D48-E48+C48) -> 7500 | G48: =SUMIFS(Cash_Book!$G$4:$G$1008,Cash_Book!$C$4:$C$1008,"DUKANDAR",Cash_Book!$D$4:$D$1008,"RECEIPT",Cash_Book!$E$4:$E$1008,B48) -> 0 | H48: =IF(B48="","",F48-G48) -> 7500
A49: 46 | B49: =IF(Masters!$J$48="","",Masters!$J$48) -> HAKIM BOMBAY | C49: =IF(B49="",0,Masters!$K$48) -> 0 | D49: =SUMIF(Daily_Sales!$D$4:$D$503,B49,Daily_Sales!$G$4:$G$503) -> 228000 | E49: =SUMIF(Daily_Sales!$D$4:$D$503,B49,Daily_Sales!$H$4:$H$503) -> 2000 | F49: =IF(B49="","",D49-E49+C49) -> 226000 | G49: =SUMIFS(Cash_Book!$G$4:$G$1008,Cash_Book!$C$4:$C$1008,"DUKANDAR",Cash_Book!$D$4:$D$1008,"RECEIPT",Cash_Book!$E$4:$E$1008,B49) -> 50000 | H49: =IF(B49="","",F49-G49) -> 176000
A50: 47 | B50: =IF(Masters!$J$49="","",Masters!$J$49) -> JUNAID KHATIK | C50: =IF(B50="",0,Masters!$K$49) -> 0 | D50: =SUMIF(Daily_Sales!$D$4:$D$503,B50,Daily_Sales!$G$4:$G$503) -> 276350 | E50: =SUMIF(Daily_Sales!$D$4:$D$503,B50,Daily_Sales!$H$4:$H$503) -> 1200 | F50: =IF(B50="","",D50-E50+C50) -> 275150 | G50: =SUMIFS(Cash_Book!$G$4:$G$1008,Cash_Book!$C$4:$C$1008,"DUKANDAR",Cash_Book!$D$4:$D$1008,"RECEIPT",Cash_Book!$E$4:$E$1008,B50) -> 140000 | H50: =IF(B50="","",F50-G50) -> 135150
A51: 48 | B51: =IF(Masters!$J$50="","",Masters!$J$50) -> MANISH | C51: =IF(B51="",0,Masters!$K$50) -> 0 | D51: =SUMIF(Daily_Sales!$D$4:$D$503,B51,Daily_Sales!$G$4:$G$503) -> 358500 | E51: =SUMIF(Daily_Sales!$D$4:$D$503,B51,Daily_Sales!$H$4:$H$503) -> 0 | F51: =IF(B51="","",D51-E51+C51) -> 358500 | G51: =SUMIFS(Cash_Book!$G$4:$G$1008,Cash_Book!$C$4:$C$1008,"DUKANDAR",Cash_Book!$D$4:$D$1008,"RECEIPT",Cash_Book!$E$4:$E$1008,B51) -> 0 | H51: =IF(B51="","",F51-G51) -> 358500
A52: 49 | B52: =IF(Masters!$J$51="","",Masters!$J$51) -> CASH SALES | C52: =IF(B52="",0,Masters!$K$51) -> 0 | D52: =SUMIF(Daily_Sales!$D$4:$D$503,B52,Daily_Sales!$G$4:$G$503) -> 146000 | E52: =SUMIF(Daily_Sales!$D$4:$D$503,B52,Daily_Sales!$H$4:$H$503) -> 0 | F52: =IF(B52="","",D52-E52+C52) -> 146000 | G52: =SUMIFS(Cash_Book!$G$4:$G$1008,Cash_Book!$C$4:$C$1008,"DUKANDAR",Cash_Book!$D$4:$D$1008,"RECEIPT",Cash_Book!$E$4:$E$1008,B52) -> 146000 | H52: =IF(B52="","",F52-G52) -> 0
A53: 50 | B53: =IF(Masters!$J$52="","",Masters!$J$52) -> MAJEED THANA | C53: =IF(B53="",0,Masters!$K$52) -> 0 | D53: =SUMIF(Daily_Sales!$D$4:$D$503,B53,Daily_Sales!$G$4:$G$503) -> 65000 | E53: =SUMIF(Daily_Sales!$D$4:$D$503,B53,Daily_Sales!$H$4:$H$503) -> 0 | F53: =IF(B53="","",D53-E53+C53) -> 65000 | G53: =SUMIFS(Cash_Book!$G$4:$G$1008,Cash_Book!$C$4:$C$1008,"DUKANDAR",Cash_Book!$D$4:$D$1008,"RECEIPT",Cash_Book!$E$4:$E$1008,B53) -> 0 | H53: =IF(B53="","",F53-G53) -> 65000
A54: 51 | B54: =IF(Masters!$J$53="","",Masters!$J$53) -> RAMESH KALAL | C54: =IF(B54="",0,Masters!$K$53) -> 0 | D54: =SUMIF(Daily_Sales!$D$4:$D$503,B54,Daily_Sales!$G$4:$G$503) -> 127400 | E54: =SUMIF(Daily_Sales!$D$4:$D$503,B54,Daily_Sales!$H$4:$H$503) -> 1300 | F54: =IF(B54="","",D54-E54+C54) -> 126100 | G54: =SUMIFS(Cash_Book!$G$4:$G$1008,Cash_Book!$C$4:$C$1008,"DUKANDAR",Cash_Book!$D$4:$D$1008,"RECEIPT",Cash_Book!$E$4:$E$1008,B54) -> 0 | H54: =IF(B54="","",F54-G54) -> 126100
A55: 52 | B55: =IF(Masters!$J$54="","",Masters!$J$54) -> IMRAN MUMBRA | C55: =IF(B55="",0,Masters!$K$54) -> 0 | D55: =SUMIF(Daily_Sales!$D$4:$D$503,B55,Daily_Sales!$G$4:$G$503) -> 338000 | E55: =SUMIF(Daily_Sales!$D$4:$D$503,B55,Daily_Sales!$H$4:$H$503) -> 0 | F55: =IF(B55="","",D55-E55+C55) -> 338000 | G55: =SUMIFS(Cash_Book!$G$4:$G$1008,Cash_Book!$C$4:$C$1008,"DUKANDAR",Cash_Book!$D$4:$D$1008,"RECEIPT",Cash_Book!$E$4:$E$1008,B55) -> 0 | H55: =IF(B55="","",F55-G55) -> 338000
A56: 53 | B56: =IF(Masters!$J$55="","",Masters!$J$55) -> JAVED THANA | C56: =IF(B56="",0,Masters!$K$55) -> 0 | D56: =SUMIF(Daily_Sales!$D$4:$D$503,B56,Daily_Sales!$G$4:$G$503) -> 84000 | E56: =SUMIF(Daily_Sales!$D$4:$D$503,B56,Daily_Sales!$H$4:$H$503) -> 800 | F56: =IF(B56="","",D56-E56+C56) -> 83200 | G56: =SUMIFS(Cash_Book!$G$4:$G$1008,Cash_Book!$C$4:$C$1008,"DUKANDAR",Cash_Book!$D$4:$D$1008,"RECEIPT",Cash_Book!$E$4:$E$1008,B56) -> 49000 | H56: =IF(B56="","",F56-G56) -> 34200
A57: 54 | B57: =IF(Masters!$J$56="","",Masters!$J$56) -> SHAHNAWAZ | C57: =IF(B57="",0,Masters!$K$56) -> 0 | D57: =SUMIF(Daily_Sales!$D$4:$D$503,B57,Daily_Sales!$G$4:$G$503) -> 23750 | E57: =SUMIF(Daily_Sales!$D$4:$D$503,B57,Daily_Sales!$H$4:$H$503) -> 0 | F57: =IF(B57="","",D57-E57+C57) -> 23750 | G57: =SUMIFS(Cash_Book!$G$4:$G$1008,Cash_Book!$C$4:$C$1008,"DUKANDAR",Cash_Book!$D$4:$D$1008,"RECEIPT",Cash_Book!$E$4:$E$1008,B57) -> 23750 | H57: =IF(B57="","",F57-G57) -> 0
A58: 55 | B58: =IF(Masters!$J$57="","",Masters!$J$57) -> PAROLA | C58: =IF(B58="",0,Masters!$K$57) -> 0 | D58: =SUMIF(Daily_Sales!$D$4:$D$503,B58,Daily_Sales!$G$4:$G$503) -> 42000 | E58: =SUMIF(Daily_Sales!$D$4:$D$503,B58,Daily_Sales!$H$4:$H$503) -> 0 | F58: =IF(B58="","",D58-E58+C58) -> 42000 | G58: =SUMIFS(Cash_Book!$G$4:$G$1008,Cash_Book!$C$4:$C$1008,"DUKANDAR",Cash_Book!$D$4:$D$1008,"RECEIPT",Cash_Book!$E$4:$E$1008,B58) -> 0 | H58: =IF(B58="","",F58-G58) -> 42000
A59: 55 | B59: {=IF(INDEX(Masters!$J:$J,ROW()-1)="","",INDEX(Masters!$J:$J,ROW()-1))} -> REHAN BYC | C59: {=IF(B59="",0,INDEX(Masters!$K:$K,ROW()-1))} -> 0 | D59: =SUMIF(Daily_Sales!$D$4:$D$503,B59,Daily_Sales!$G$4:$G$503) -> 223600 | E59: =SUMIF(Daily_Sales!$D$4:$D$503,B59,Daily_Sales!$H$4:$H$503) -> 2600 | F59: =IF(B59="","",D59-E59+C59) -> 221000 | G59: =SUMIFS(Cash_Book!$G$4:$G$1008,Cash_Book!$C$4:$C$1008,"DUKANDAR",Cash_Book!$D$4:$D$1008,"RECEIPT",Cash_Book!$E$4:$E$1008,B59) -> 0 | H59: =IF(B59="","",F59-G59) -> 221000
A60: 55 | B60: {=IF(INDEX(Masters!$J:$J,ROW()-1)="","",INDEX(Masters!$J:$J,ROW()-1))} -> KHALIL | C60: {=IF(B60="",0,INDEX(Masters!$K:$K,ROW()-1))} -> 0 | D60: =SUMIF(Daily_Sales!$D$4:$D$503,B60,Daily_Sales!$G$4:$G$503) -> 218650 | E60: =SUMIF(Daily_Sales!$D$4:$D$503,B60,Daily_Sales!$H$4:$H$503) -> 0 | F60: =IF(B60="","",D60-E60+C60) -> 218650 | G60: =SUMIFS(Cash_Book!$G$4:$G$1008,Cash_Book!$C$4:$C$1008,"DUKANDAR",Cash_Book!$D$4:$D$1008,"RECEIPT",Cash_Book!$E$4:$E$1008,B60) -> 0 | H60: =IF(B60="","",F60-G60) -> 218650
A61: 55 | B61: {=IF(INDEX(Masters!$J:$J,ROW()-1)="","",INDEX(Masters!$J:$J,ROW()-1))} -> SARFARAZ | C61: {=IF(B61="",0,INDEX(Masters!$K:$K,ROW()-1))} -> 0 | D61: =SUMIF(Daily_Sales!$D$4:$D$503,B61,Daily_Sales!$G$4:$G$503) -> 110000 | E61: =SUMIF(Daily_Sales!$D$4:$D$503,B61,Daily_Sales!$H$4:$H$503) -> 0 | F61: =IF(B61="","",D61-E61+C61) -> 110000 | G61: =SUMIFS(Cash_Book!$G$4:$G$1008,Cash_Book!$C$4:$C$1008,"DUKANDAR",Cash_Book!$D$4:$D$1008,"RECEIPT",Cash_Book!$E$4:$E$1008,B61) -> 110000 | H61: =IF(B61="","",F61-G61) -> 0
A62: 55 | B62: {=IF(INDEX(Masters!$J:$J,ROW()-1)="","",INDEX(Masters!$J:$J,ROW()-1))} -> RAIS PUNE | C62: {=IF(B62="",0,INDEX(Masters!$K:$K,ROW()-1))} -> 0 | D62: =SUMIF(Daily_Sales!$D$4:$D$503,B62,Daily_Sales!$G$4:$G$503) -> 166400 | E62: =SUMIF(Daily_Sales!$D$4:$D$503,B62,Daily_Sales!$H$4:$H$503) -> 1600 | F62: =IF(B62="","",D62-E62+C62) -> 164800 | G62: =SUMIFS(Cash_Book!$G$4:$G$1008,Cash_Book!$C$4:$C$1008,"DUKANDAR",Cash_Book!$D$4:$D$1008,"RECEIPT",Cash_Book!$E$4:$E$1008,B62) -> 0 | H62: =IF(B62="","",F62-G62) -> 164800
A63: 55 | B63: {=IF(INDEX(Masters!$J:$J,ROW()-1)="","",INDEX(Masters!$J:$J,ROW()-1))} | C63: {=IF(B63="",0,INDEX(Masters!$K:$K,ROW()-1))} -> 0 | D63: =SUMIF(Daily_Sales!$D$4:$D$503,B63,Daily_Sales!$G$4:$G$503) -> 0 | E63: =SUMIF(Daily_Sales!$D$4:$D$503,B63,Daily_Sales!$H$4:$H$503) -> 0 | F63: =IF(B63="","",D63-E63+C63) | G63: =SUMIFS(Cash_Book!$G$4:$G$1008,Cash_Book!$C$4:$C$1008,"DUKANDAR",Cash_Book!$D$4:$D$1008,"RECEIPT",Cash_Book!$E$4:$E$1008,B63) -> 0 | H63: =IF(B63="","",F63-G63)
A64: 55 | B64: {=IF(INDEX(Masters!$J:$J,ROW()-1)="","",INDEX(Masters!$J:$J,ROW()-1))} | C64: {=IF(B64="",0,INDEX(Masters!$K:$K,ROW()-1))} -> 0 | D64: =SUMIF(Daily_Sales!$D$4:$D$503,B64,Daily_Sales!$G$4:$G$503) -> 0 | E64: =SUMIF(Daily_Sales!$D$4:$D$503,B64,Daily_Sales!$H$4:$H$503) -> 0 | F64: =IF(B64="","",D64-E64+C64) | G64: =SUMIFS(Cash_Book!$G$4:$G$1008,Cash_Book!$C$4:$C$1008,"DUKANDAR",Cash_Book!$D$4:$D$1008,"RECEIPT",Cash_Book!$E$4:$E$1008,B64) -> 0 | H64: =IF(B64="","",F64-G64)
A65: 55 | B65: {=IF(INDEX(Masters!$J:$J,ROW()-1)="","",INDEX(Masters!$J:$J,ROW()-1))} | C65: {=IF(B65="",0,INDEX(Masters!$K:$K,ROW()-1))} -> 0 | D65: =SUMIF(Daily_Sales!$D$4:$D$503,B65,Daily_Sales!$G$4:$G$503) -> 0 | E65: =SUMIF(Daily_Sales!$D$4:$D$503,B65,Daily_Sales!$H$4:$H$503) -> 0 | F65: =IF(B65="","",D65-E65+C65) | G65: =SUMIFS(Cash_Book!$G$4:$G$1008,Cash_Book!$C$4:$C$1008,"DUKANDAR",Cash_Book!$D$4:$D$1008,"RECEIPT",Cash_Book!$E$4:$E$1008,B65) -> 0 | H65: =IF(B65="","",F65-G65)
A66: 55 | B66: {=IF(INDEX(Masters!$J:$J,ROW()-1)="","",INDEX(Masters!$J:$J,ROW()-1))} | C66: {=IF(B66="",0,INDEX(Masters!$K:$K,ROW()-1))} -> 0 | D66: =SUMIF(Daily_Sales!$D$4:$D$503,B66,Daily_Sales!$G$4:$G$503) -> 0 | E66: =SUMIF(Daily_Sales!$D$4:$D$503,B66,Daily_Sales!$H$4:$H$503) -> 0 | F66: =IF(B66="","",D66-E66+C66) | G66: =SUMIFS(Cash_Book!$G$4:$G$1008,Cash_Book!$C$4:$C$1008,"DUKANDAR",Cash_Book!$D$4:$D$1008,"RECEIPT",Cash_Book!$E$4:$E$1008,B66) -> 0 | H66: =IF(B66="","",F66-G66)
A67: 55 | B67: {=IF(INDEX(Masters!$J:$J,ROW()-1)="","",INDEX(Masters!$J:$J,ROW()-1))} | C67: {=IF(B67="",0,INDEX(Masters!$K:$K,ROW()-1))} -> 0 | D67: =SUMIF(Daily_Sales!$D$4:$D$503,B67,Daily_Sales!$G$4:$G$503) -> 0 | E67: =SUMIF(Daily_Sales!$D$4:$D$503,B67,Daily_Sales!$H$4:$H$503) -> 0 | F67: =IF(B67="","",D67-E67+C67) | G67: =SUMIFS(Cash_Book!$G$4:$G$1008,Cash_Book!$C$4:$C$1008,"DUKANDAR",Cash_Book!$D$4:$D$1008,"RECEIPT",Cash_Book!$E$4:$E$1008,B67) -> 0 | H67: =IF(B67="","",F67-G67)
A68: 55 | B68: {=IF(INDEX(Masters!$J:$J,ROW()-1)="","",INDEX(Masters!$J:$J,ROW()-1))} | C68: {=IF(B68="",0,INDEX(Masters!$K:$K,ROW()-1))} -> 0 | D68: =SUMIF(Daily_Sales!$D$4:$D$503,B68,Daily_Sales!$G$4:$G$503) -> 0 | E68: =SUMIF(Daily_Sales!$D$4:$D$503,B68,Daily_Sales!$H$4:$H$503) -> 0 | F68: =IF(B68="","",D68-E68+C68) | G68: =SUMIFS(Cash_Book!$G$4:$G$1008,Cash_Book!$C$4:$C$1008,"DUKANDAR",Cash_Book!$D$4:$D$1008,"RECEIPT",Cash_Book!$E$4:$E$1008,B68) -> 0 | H68: =IF(B68="","",F68-G68)
A69: 55 | B69: {=IF(INDEX(Masters!$J:$J,ROW()-1)="","",INDEX(Masters!$J:$J,ROW()-1))} | C69: {=IF(B69="",0,INDEX(Masters!$K:$K,ROW()-1))} -> 0 | D69: =SUMIF(Daily_Sales!$D$4:$D$503,B69,Daily_Sales!$G$4:$G$503) -> 0 | E69: =SUMIF(Daily_Sales!$D$4:$D$503,B69,Daily_Sales!$H$4:$H$503) -> 0 | F69: =IF(B69="","",D69-E69+C69) | G69: =SUMIFS(Cash_Book!$G$4:$G$1008,Cash_Book!$C$4:$C$1008,"DUKANDAR",Cash_Book!$D$4:$D$1008,"RECEIPT",Cash_Book!$E$4:$E$1008,B69) -> 0 | H69: =IF(B69="","",F69-G69)
A70: 55 | B70: {=IF(INDEX(Masters!$J:$J,ROW()-1)="","",INDEX(Masters!$J:$J,ROW()-1))} | C70: {=IF(B70="",0,INDEX(Masters!$K:$K,ROW()-1))} -> 0 | D70: =SUMIF(Daily_Sales!$D$4:$D$503,B70,Daily_Sales!$G$4:$G$503) -> 0 | E70: =SUMIF(Daily_Sales!$D$4:$D$503,B70,Daily_Sales!$H$4:$H$503) -> 0 | F70: =IF(B70="","",D70-E70+C70) | G70: =SUMIFS(Cash_Book!$G$4:$G$1008,Cash_Book!$C$4:$C$1008,"DUKANDAR",Cash_Book!$D$4:$D$1008,"RECEIPT",Cash_Book!$E$4:$E$1008,B70) -> 0 | H70: =IF(B70="","",F70-G70)
... A103: 55 | B103: {=IF(INDEX(Masters!$J:$J,ROW()-1)="","",INDEX(Masters!$J:$J,ROW()-1))} | C103: {=IF(B103="",0,INDEX(Masters!$K:$K,ROW()-1))} -> 0 | D103: =SUMIF(Daily_Sales!$D$4:$D$503,B103,Daily_Sales!$G$4:$G$503) -> 0 | E103: =SUMIF(Daily_Sales!$D$4:$D$503,B103,Daily_Sales!$H$4:$H$503) -> 0 | F103: =IF(B103="","",D103-E103+C103) | G103: =SUMIFS(Cash_Book!$G$4:$G$1008,Cash_Book!$C$4:$C$1008,"DUKANDAR",Cash_Book!$D$4:$D$1008,"RECEIPT",Cash_Book!$E$4:$E$1008,B103) -> 0 | H103: =IF(B103="","",F103-G103)
A104: TOTAL | B104: PATTI | C104: =SUM(C4:C103) -> 4602621 | D104: =SUM(D4:D103) -> 4962000 | E104: =SUM(E4:E103) -> 29050 | F104: =SUM(F4:F103) -> 9535571 | G104: =SUM(G4:G103) -> 3098966 | H104: =SUM(H4:H103) -> 6436605
E106: For Balance Sheet:
F107: Dukandar Receivable (they owe) | H107: =SUMIF(H4:H103,">0",H4:H103) -> 6444105
F108: Dukandar Overpaid (we owe) | H108: =-SUMIF(H4:H103,"<0",H4:H103) -> 7500

Sheet Capital_Loan_Ledger
A1: CAPITAL & LOAN LEDGER
A3: Sr | B3: Party Name | C3: Type | D3: Opening Bal | E3: Taken (+) | F3: Withdrawn/Repaid (-) | G3: CURRENT BALANCE
A4: 1 | B4: =IF(Masters!$P$3="","",Masters!$P$3) -> MHN CAPITAL | C4: =IF(B4="","",Masters!$R$3) -> CAPITAL | D4: =IF(B4="",0,Masters!$Q$3) -> 4469981 | E4: =IF(B4="",0,SUMIFS(Cash_Book!$G$4:$G$1008,Cash_Book!$C$4:$C$1008,C4,Cash_Book!$D$4:$D$1008,"TAKEN",Cash_Book!$E$4:$E$1008,B4)) -> 0 | F4: =IF(B4="",0,SUMIFS(Cash_Book!$G$4:$G$1008,Cash_Book!$C$4:$C$1008,C4,Cash_Book!$D$4:$D$1008,"WITHDRAWN",Cash_Book!$E$4:$E$1008,B4)+SUMIFS(Cash_Book!$G$4:$G$1008,Cash_Book!$C$4:$C$1008,C4,Cash_Book!$D$4:$D$1008,"REPAID",Cash_Book!$E$4:$E$1008,B4)) -> 0 | G4: =IF(B4="","",D4+E4-F4) -> 4469981
A5: 2 | B5: =IF(Masters!$P$4="","",Masters!$P$4) -> SHAKIL GHODEGAON AMANAT | C5: =IF(B5="","",Masters!$R$4) -> AMANAT | D5: =IF(B5="",0,Masters!$Q$4) -> 2000000 | E5: =IF(B5="",0,SUMIFS(Cash_Book!$G$4:$G$1008,Cash_Book!$C$4:$C$1008,C5,Cash_Book!$D$4:$D$1008,"TAKEN",Cash_Book!$E$4:$E$1008,B5)) -> 500000 | F5: =IF(B5="",0,SUMIFS(Cash_Book!$G$4:$G$1008,Cash_Book!$C$4:$C$1008,C5,Cash_Book!$D$4:$D$1008,"WITHDRAWN",Cash_Book!$E$4:$E$1008,B5)+SUMIFS(Cash_Book!$G$4:$G$1008,Cash_Book!$C$4:$C$1008,C5,Cash_Book!$D$4:$D$1008,"REPAID",Cash_Book!$E$4:$E$1008,B5)) -> 0 | G5: =IF(B5="","",D5+E5-F5) -> 2500000
A6: 3 | B6: =IF(Masters!$P$5="","",Masters!$P$5) -> KMN | C6: =IF(B6="","",Masters!$R$5) -> AMANAT | D6: =IF(B6="",0,Masters!$Q$5) -> 0 | E6: =IF(B6="",0,SUMIFS(Cash_Book!$G$4:$G$1008,Cash_Book!$C$4:$C$1008,C6,Cash_Book!$D$4:$D$1008,"TAKEN",Cash_Book!$E$4:$E$1008,B6)) -> 0 | F6: =IF(B6="",0,SUMIFS(Cash_Book!$G$4:$G$1008,Cash_Book!$C$4:$C$1008,C6,Cash_Book!$D$4:$D$1008,"WITHDRAWN",Cash_Book!$E$4:$E$1008,B6)+SUMIFS(Cash_Book!$G$4:$G$1008,Cash_Book!$C$4:$C$1008,C6,Cash_Book!$D$4:$D$1008,"REPAID",Cash_Book!$E$4:$E$1008,B6)) -> 0 | G6: =IF(B6="","",D6+E6-F6) -> 0
A7: 4 | B7: =IF(Masters!$P$6="","",Masters!$P$6) -> AYAAN | C7: =IF(B7="","",Masters!$R$6) -> AMANAT | D7: =IF(B7="",0,Masters!$Q$6) -> 0 | E7: =IF(B7="",0,SUMIFS(Cash_Book!$G$4:$G$1008,Cash_Book!$C$4:$C$1008,C7,Cash_Book!$D$4:$D$1008,"TAKEN",Cash_Book!$E$4:$E$1008,B7)) -> 0 | F7: =IF(B7="",0,SUMIFS(Cash_Book!$G$4:$G$1008,Cash_Book!$C$4:$C$1008,C7,Cash_Book!$D$4:$D$1008,"WITHDRAWN",Cash_Book!$E$4:$E$1008,B7)+SUMIFS(Cash_Book!$G$4:$G$1008,Cash_Book!$C$4:$C$1008,C7,Cash_Book!$D$4:$D$1008,"REPAID",Cash_Book!$E$4:$E$1008,B7)) -> 0 | G7: =IF(B7="","",D7+E7-F7) -> 0
A8: 5 | B8: =IF(Masters!$P$7="","",Masters!$P$7) -> WAHIDA | C8: =IF(B8="","",Masters!$R$7) -> AMANAT | D8: =IF(B8="",0,Masters!$Q$7) -> 0 | E8: =IF(B8="",0,SUMIFS(Cash_Book!$G$4:$G$1008,Cash_Book!$C$4:$C$1008,C8,Cash_Book!$D$4:$D$1008,"TAKEN",Cash_Book!$E$4:$E$1008,B8)) -> 5000 | F8: =IF(B8="",0,SUMIFS(Cash_Book!$G$4:$G$1008,Cash_Book!$C$4:$C$1008,C8,Cash_Book!$D$4:$D$1008,"WITHDRAWN",Cash_Book!$E$4:$E$1008,B8)+SUMIFS(Cash_Book!$G$4:$G$1008,Cash_Book!$C$4:$C$1008,C8,Cash_Book!$D$4:$D$1008,"REPAID",Cash_Book!$E$4:$E$1008,B8)) -> 5000 | G8: =IF(B8="","",D8+E8-F8) -> 0
A9: 6 | B9: =IF(Masters!$P$8="","",Masters!$P$8) -> TILLA | C9: =IF(B9="","",Masters!$R$8) -> AMANAT | D9: =IF(B9="",0,Masters!$Q$8) -> 0 | E9: =IF(B9="",0,SUMIFS(Cash_Book!$G$4:$G$1008,Cash_Book!$C$4:$C$1008,C9,Cash_Book!$D$4:$D$1008,"TAKEN",Cash_Book!$E$4:$E$1008,B9)) -> 100000 | F9: =IF(B9="",0,SUMIFS(Cash_Book!$G$4:$G$1008,Cash_Book!$C$4:$C$1008,C9,Cash_Book!$D$4:$D$1008,"WITHDRAWN",Cash_Book!$E$4:$E$1008,B9)+SUMIFS(Cash_Book!$G$4:$G$1008,Cash_Book!$C$4:$C$1008,C9,Cash_Book!$D$4:$D$1008,"REPAID",Cash_Book!$E$4:$E$1008,B9)) -> 100000 | G9: =IF(B9="","",D9+E9-F9) -> 0
A10: 7 | B10: =IF(Masters!$P$9="","",Masters!$P$9) | C10: =IF(B10="","",Masters!$R$9) | D10: =IF(B10="",0,Masters!$Q$9) -> 0 | E10: =IF(B10="",0,SUMIFS(Cash_Book!$G$4:$G$1008,Cash_Book!$C$4:$C$1008,C10,Cash_Book!$D$4:$D$1008,"TAKEN",Cash_Book!$E$4:$E$1008,B10)) -> 0 | F10: =IF(B10="",0,SUMIFS(Cash_Book!$G$4:$G$1008,Cash_Book!$C$4:$C$1008,C10,Cash_Book!$D$4:$D$1008,"WITHDRAWN",Cash_Book!$E$4:$E$1008,B10)+SUMIFS(Cash_Book!$G$4:$G$1008,Cash_Book!$C$4:$C$1008,C10,Cash_Book!$D$4:$D$1008,"REPAID",Cash_Book!$E$4:$E$1008,B10)) -> 0 | G10: =IF(B10="","",D10+E10-F10)
A11: 8 | B11: =IF(Masters!$P$10="","",Masters!$P$10) | C11: =IF(B11="","",Masters!$R$10) | D11: =IF(B11="",0,Masters!$Q$10) -> 0 | E11: =IF(B11="",0,SUMIFS(Cash_Book!$G$4:$G$1008,Cash_Book!$C$4:$C$1008,C11,Cash_Book!$D$4:$D$1008,"TAKEN",Cash_Book!$E$4:$E$1008,B11)) -> 0 | F11: =IF(B11="",0,SUMIFS(Cash_Book!$G$4:$G$1008,Cash_Book!$C$4:$C$1008,C11,Cash_Book!$D$4:$D$1008,"WITHDRAWN",Cash_Book!$E$4:$E$1008,B11)+SUMIFS(Cash_Book!$G$4:$G$1008,Cash_Book!$C$4:$C$1008,C11,Cash_Book!$D$4:$D$1008,"REPAID",Cash_Book!$E$4:$E$1008,B11)) -> 0 | G11: =IF(B11="","",D11+E11-F11)
A12: 9 | B12: =IF(Masters!$P$11="","",Masters!$P$11) | C12: =IF(B12="","",Masters!$R$11) | D12: =IF(B12="",0,Masters!$Q$11) -> 0 | E12: =IF(B12="",0,SUMIFS(Cash_Book!$G$4:$G$1008,Cash_Book!$C$4:$C$1008,C12,Cash_Book!$D$4:$D$1008,"TAKEN",Cash_Book!$E$4:$E$1008,B12)) -> 0 | F12: =IF(B12="",0,SUMIFS(Cash_Book!$G$4:$G$1008,Cash_Book!$C$4:$C$1008,C12,Cash_Book!$D$4:$D$1008,"WITHDRAWN",Cash_Book!$E$4:$E$1008,B12)+SUMIFS(Cash_Book!$G$4:$G$1008,Cash_Book!$C$4:$C$1008,C12,Cash_Book!$D$4:$D$1008,"REPAID",Cash_Book!$E$4:$E$1008,B12)) -> 0 | G12: =IF(B12="","",D12+E12-F12)
A13: 10 | B13: =IF(Masters!$P$12="","",Masters!$P$12) | C13: =IF(B13="","",Masters!$R$12) | D13: =IF(B13="",0,Masters!$Q$12) -> 0 | E13: =IF(B13="",0,SUMIFS(Cash_Book!$G$4:$G$1008,Cash_Book!$C$4:$C$1008,C13,Cash_Book!$D$4:$D$1008,"TAKEN",Cash_Book!$E$4:$E$1008,B13)) -> 0 | F13: =IF(B13="",0,SUMIFS(Cash_Book!$G$4:$G$1008,Cash_Book!$C$4:$C$1008,C13,Cash_Book!$D$4:$D$1008,"WITHDRAWN",Cash_Book!$E$4:$E$1008,B13)+SUMIFS(Cash_Book!$G$4:$G$1008,Cash_Book!$C$4:$C$1008,C13,Cash_Book!$D$4:$D$1008,"REPAID",Cash_Book!$E$4:$E$1008,B13)) -> 0 | G13: =IF(B13="","",D13+E13-F13)
A14: 11 | B14: =IF(Masters!$P$13="","",Masters!$P$13) | C14: =IF(B14="","",Masters!$R$13) | D14: =IF(B14="",0,Masters!$Q$13) -> 0 | E14: =IF(B14="",0,SUMIFS(Cash_Book!$G$4:$G$1008,Cash_Book!$C$4:$C$1008,C14,Cash_Book!$D$4:$D$1008,"TAKEN",Cash_Book!$E$4:$E$1008,B14)) -> 0 | F14: =IF(B14="",0,SUMIFS(Cash_Book!$G$4:$G$1008,Cash_Book!$C$4:$C$1008,C14,Cash_Book!$D$4:$D$1008,"WITHDRAWN",Cash_Book!$E$4:$E$1008,B14)+SUMIFS(Cash_Book!$G$4:$G$1008,Cash_Book!$C$4:$C$1008,C14,Cash_Book!$D$4:$D$1008,"REPAID",Cash_Book!$E$4:$E$1008,B14)) -> 0 | G14: =IF(B14="","",D14+E14-F14)
A15: 12 | B15: =IF(Masters!$P$14="","",Masters!$P$14) | C15: =IF(B15="","",Masters!$R$14) | D15: =IF(B15="",0,Masters!$Q$14) -> 0 | E15: =IF(B15="",0,SUMIFS(Cash_Book!$G$4:$G$1008,Cash_Book!$C$4:$C$1008,C15,Cash_Book!$D$4:$D$1008,"TAKEN",Cash_Book!$E$4:$E$1008,B15)) -> 0 | F15: =IF(B15="",0,SUMIFS(Cash_Book!$G$4:$G$1008,Cash_Book!$C$4:$C$1008,C15,Cash_Book!$D$4:$D$1008,"WITHDRAWN",Cash_Book!$E$4:$E$1008,B15)+SUMIFS(Cash_Book!$G$4:$G$1008,Cash_Book!$C$4:$C$1008,C15,Cash_Book!$D$4:$D$1008,"REPAID",Cash_Book!$E$4:$E$1008,B15)) -> 0 | G15: =IF(B15="","",D15+E15-F15)
A16: 13 | B16: =IF(Masters!$P$15="","",Masters!$P$15) | C16: =IF(B16="","",Masters!$R$15) | D16: =IF(B16="",0,Masters!$Q$15) -> 0 | E16: =IF(B16="",0,SUMIFS(Cash_Book!$G$4:$G$1008,Cash_Book!$C$4:$C$1008,C16,Cash_Book!$D$4:$D$1008,"TAKEN",Cash_Book!$E$4:$E$1008,B16)) -> 0 | F16: =IF(B16="",0,SUMIFS(Cash_Book!$G$4:$G$1008,Cash_Book!$C$4:$C$1008,C16,Cash_Book!$D$4:$D$1008,"WITHDRAWN",Cash_Book!$E$4:$E$1008,B16)+SUMIFS(Cash_Book!$G$4:$G$1008,Cash_Book!$C$4:$C$1008,C16,Cash_Book!$D$4:$D$1008,"REPAID",Cash_Book!$E$4:$E$1008,B16)) -> 0 | G16: =IF(B16="","",D16+E16-F16)
A17: 14 | B17: =IF(Masters!$P$16="","",Masters!$P$16) | C17: =IF(B17="","",Masters!$R$16) | D17: =IF(B17="",0,Masters!$Q$16) -> 0 | E17: =IF(B17="",0,SUMIFS(Cash_Book!$G$4:$G$1008,Cash_Book!$C$4:$C$1008,C17,Cash_Book!$D$4:$D$1008,"TAKEN",Cash_Book!$E$4:$E$1008,B17)) -> 0 | F17: =IF(B17="",0,SUMIFS(Cash_Book!$G$4:$G$1008,Cash_Book!$C$4:$C$1008,C17,Cash_Book!$D$4:$D$1008,"WITHDRAWN",Cash_Book!$E$4:$E$1008,B17)+SUMIFS(Cash_Book!$G$4:$G$1008,Cash_Book!$C$4:$C$1008,C17,Cash_Book!$D$4:$D$1008,"REPAID",Cash_Book!$E$4:$E$1008,B17)) -> 0 | G17: =IF(B17="","",D17+E17-F17)
A18: 15 | B18: =IF(Masters!$P$17="","",Masters!$P$17) | C18: =IF(B18="","",Masters!$R$17) | D18: =IF(B18="",0,Masters!$Q$17) -> 0 | E18: =IF(B18="",0,SUMIFS(Cash_Book!$G$4:$G$1008,Cash_Book!$C$4:$C$1008,C18,Cash_Book!$D$4:$D$1008,"TAKEN",Cash_Book!$E$4:$E$1008,B18)) -> 0 | F18: =IF(B18="",0,SUMIFS(Cash_Book!$G$4:$G$1008,Cash_Book!$C$4:$C$1008,C18,Cash_Book!$D$4:$D$1008,"WITHDRAWN",Cash_Book!$E$4:$E$1008,B18)+SUMIFS(Cash_Book!$G$4:$G$1008,Cash_Book!$C$4:$C$1008,C18,Cash_Book!$D$4:$D$1008,"REPAID",Cash_Book!$E$4:$E$1008,B18)) -> 0 | G18: =IF(B18="","",D18+E18-F18)
A19: 16 | B19: =IF(Masters!$P$18="","",Masters!$P$18) | C19: =IF(B19="","",Masters!$R$18) | D19: =IF(B19="",0,Masters!$Q$18) -> 0 | E19: =IF(B19="",0,SUMIFS(Cash_Book!$G$4:$G$1008,Cash_Book!$C$4:$C$1008,C19,Cash_Book!$D$4:$D$1008,"TAKEN",Cash_Book!$E$4:$E$1008,B19)) -> 0 | F19: =IF(B19="",0,SUMIFS(Cash_Book!$G$4:$G$1008,Cash_Book!$C$4:$C$1008,C19,Cash_Book!$D$4:$D$1008,"WITHDRAWN",Cash_Book!$E$4:$E$1008,B19)+SUMIFS(Cash_Book!$G$4:$G$1008,Cash_Book!$C$4:$C$1008,C19,Cash_Book!$D$4:$D$1008,"REPAID",Cash_Book!$E$4:$E$1008,B19)) -> 0 | G19: =IF(B19="","",D19+E19-F19)
A20: 17 | B20: =IF(Masters!$P$19="","",Masters!$P$19) | C20: =IF(B20="","",Masters!$R$19) | D20: =IF(B20="",0,Masters!$Q$19) -> 0 | E20: =IF(B20="",0,SUMIFS(Cash_Book!$G$4:$G$1008,Cash_Book!$C$4:$C$1008,C20,Cash_Book!$D$4:$D$1008,"TAKEN",Cash_Book!$E$4:$E$1008,B20)) -> 0 | F20: =IF(B20="",0,SUMIFS(Cash_Book!$G$4:$G$1008,Cash_Book!$C$4:$C$1008,C20,Cash_Book!$D$4:$D$1008,"WITHDRAWN",Cash_Book!$E$4:$E$1008,B20)+SUMIFS(Cash_Book!$G$4:$G$1008,Cash_Book!$C$4:$C$1008,C20,Cash_Book!$D$4:$D$1008,"REPAID",Cash_Book!$E$4:$E$1008,B20)) -> 0 | G20: =IF(B20="","",D20+E20-F20)
A21: 18 | B21: =IF(Masters!$P$20="","",Masters!$P$20) | C21: =IF(B21="","",Masters!$R$20) | D21: =IF(B21="",0,Masters!$Q$20) -> 0 | E21: =IF(B21="",0,SUMIFS(Cash_Book!$G$4:$G$1008,Cash_Book!$C$4:$C$1008,C21,Cash_Book!$D$4:$D$1008,"TAKEN",Cash_Book!$E$4:$E$1008,B21)) -> 0 | F21: =IF(B21="",0,SUMIFS(Cash_Book!$G$4:$G$1008,Cash_Book!$C$4:$C$1008,C21,Cash_Book!$D$4:$D$1008,"WITHDRAWN",Cash_Book!$E$4:$E$1008,B21)+SUMIFS(Cash_Book!$G$4:$G$1008,Cash_Book!$C$4:$C$1008,C21,Cash_Book!$D$4:$D$1008,"REPAID",Cash_Book!$E$4:$E$1008,B21)) -> 0 | G21: =IF(B21="","",D21+E21-F21)
A22: 19 | B22: =IF(Masters!$P$21="","",Masters!$P$21) | C22: =IF(B22="","",Masters!$R$21) | D22: =IF(B22="",0,Masters!$Q$21) -> 0 | E22: =IF(B22="",0,SUMIFS(Cash_Book!$G$4:$G$1008,Cash_Book!$C$4:$C$1008,C22,Cash_Book!$D$4:$D$1008,"TAKEN",Cash_Book!$E$4:$E$1008,B22)) -> 0 | F22: =IF(B22="",0,SUMIFS(Cash_Book!$G$4:$G$1008,Cash_Book!$C$4:$C$1008,C22,Cash_Book!$D$4:$D$1008,"WITHDRAWN",Cash_Book!$E$4:$E$1008,B22)+SUMIFS(Cash_Book!$G$4:$G$1008,Cash_Book!$C$4:$C$1008,C22,Cash_Book!$D$4:$D$1008,"REPAID",Cash_Book!$E$4:$E$1008,B22)) -> 0 | G22: =IF(B22="","",D22+E22-F22)
A23: 20 | B23: =IF(Masters!$P$22="","",Masters!$P$22) | C23: =IF(B23="","",Masters!$R$22) | D23: =IF(B23="",0,Masters!$Q$22) -> 0 | E23: =IF(B23="",0,SUMIFS(Cash_Book!$G$4:$G$1008,Cash_Book!$C$4:$C$1008,C23,Cash_Book!$D$4:$D$1008,"TAKEN",Cash_Book!$E$4:$E$1008,B23)) -> 0 | F23: =IF(B23="",0,SUMIFS(Cash_Book!$G$4:$G$1008,Cash_Book!$C$4:$C$1008,C23,Cash_Book!$D$4:$D$1008,"WITHDRAWN",Cash_Book!$E$4:$E$1008,B23)+SUMIFS(Cash_Book!$G$4:$G$1008,Cash_Book!$C$4:$C$1008,C23,Cash_Book!$D$4:$D$1008,"REPAID",Cash_Book!$E$4:$E$1008,B23)) -> 0 | G23: =IF(B23="","",D23+E23-F23)
A24: 21 | B24: =IF(Masters!$P$23="","",Masters!$P$23) | C24: =IF(B24="","",Masters!$R$23) | D24: =IF(B24="",0,Masters!$Q$23) -> 0 | E24: =IF(B24="",0,SUMIFS(Cash_Book!$G$4:$G$1008,Cash_Book!$C$4:$C$1008,C24,Cash_Book!$D$4:$D$1008,"TAKEN",Cash_Book!$E$4:$E$1008,B24)) -> 0 | F24: =IF(B24="",0,SUMIFS(Cash_Book!$G$4:$G$1008,Cash_Book!$C$4:$C$1008,C24,Cash_Book!$D$4:$D$1008,"WITHDRAWN",Cash_Book!$E$4:$E$1008,B24)+SUMIFS(Cash_Book!$G$4:$G$1008,Cash_Book!$C$4:$C$1008,C24,Cash_Book!$D$4:$D$1008,"REPAID",Cash_Book!$E$4:$E$1008,B24)) -> 0 | G24: =IF(B24="","",D24+E24-F24)
A25: 22 | B25: =IF(Masters!$P$24="","",Masters!$P$24) | C25: =IF(B25="","",Masters!$R$24) | D25: =IF(B25="",0,Masters!$Q$24) -> 0 | E25: =IF(B25="",0,SUMIFS(Cash_Book!$G$4:$G$1008,Cash_Book!$C$4:$C$1008,C25,Cash_Book!$D$4:$D$1008,"TAKEN",Cash_Book!$E$4:$E$1008,B25)) -> 0 | F25: =IF(B25="",0,SUMIFS(Cash_Book!$G$4:$G$1008,Cash_Book!$C$4:$C$1008,C25,Cash_Book!$D$4:$D$1008,"WITHDRAWN",Cash_Book!$E$4:$E$1008,B25)+SUMIFS(Cash_Book!$G$4:$G$1008,Cash_Book!$C$4:$C$1008,C25,Cash_Book!$D$4:$D$1008,"REPAID",Cash_Book!$E$4:$E$1008,B25)) -> 0 | G25: =IF(B25="","",D25+E25-F25)
A26: 23 | B26: =IF(Masters!$P$25="","",Masters!$P$25) | C26: =IF(B26="","",Masters!$R$25) | D26: =IF(B26="",0,Masters!$Q$25) -> 0 | E26: =IF(B26="",0,SUMIFS(Cash_Book!$G$4:$G$1008,Cash_Book!$C$4:$C$1008,C26,Cash_Book!$D$4:$D$1008,"TAKEN",Cash_Book!$E$4:$E$1008,B26)) -> 0 | F26: =IF(B26="",0,SUMIFS(Cash_Book!$G$4:$G$1008,Cash_Book!$C$4:$C$1008,C26,Cash_Book!$D$4:$D$1008,"WITHDRAWN",Cash_Book!$E$4:$E$1008,B26)+SUMIFS(Cash_Book!$G$4:$G$1008,Cash_Book!$C$4:$C$1008,C26,Cash_Book!$D$4:$D$1008,"REPAID",Cash_Book!$E$4:$E$1008,B26)) -> 0 | G26: =IF(B26="","",D26+E26-F26)
A27: 24 | B27: =IF(Masters!$P$26="","",Masters!$P$26) | C27: =IF(B27="","",Masters!$R$26) | D27: =IF(B27="",0,Masters!$Q$26) -> 0 | E27: =IF(B27="",0,SUMIFS(Cash_Book!$G$4:$G$1008,Cash_Book!$C$4:$C$1008,C27,Cash_Book!$D$4:$D$1008,"TAKEN",Cash_Book!$E$4:$E$1008,B27)) -> 0 | F27: =IF(B27="",0,SUMIFS(Cash_Book!$G$4:$G$1008,Cash_Book!$C$4:$C$1008,C27,Cash_Book!$D$4:$D$1008,"WITHDRAWN",Cash_Book!$E$4:$E$1008,B27)+SUMIFS(Cash_Book!$G$4:$G$1008,Cash_Book!$C$4:$C$1008,C27,Cash_Book!$D$4:$D$1008,"REPAID",Cash_Book!$E$4:$E$1008,B27)) -> 0 | G27: =IF(B27="","",D27+E27-F27)
A28: 25 | B28: =IF(Masters!$P$27="","",Masters!$P$27) | C28: =IF(B28="","",Masters!$R$27) | D28: =IF(B28="",0,Masters!$Q$27) -> 0 | E28: =IF(B28="",0,SUMIFS(Cash_Book!$G$4:$G$1008,Cash_Book!$C$4:$C$1008,C28,Cash_Book!$D$4:$D$1008,"TAKEN",Cash_Book!$E$4:$E$1008,B28)) -> 0 | F28: =IF(B28="",0,SUMIFS(Cash_Book!$G$4:$G$1008,Cash_Book!$C$4:$C$1008,C28,Cash_Book!$D$4:$D$1008,"WITHDRAWN",Cash_Book!$E$4:$E$1008,B28)+SUMIFS(Cash_Book!$G$4:$G$1008,Cash_Book!$C$4:$C$1008,C28,Cash_Book!$D$4:$D$1008,"REPAID",Cash_Book!$E$4:$E$1008,B28)) -> 0 | G28: =IF(B28="","",D28+E28-F28)
A29: 26 | B29: =IF(Masters!$P$28="","",Masters!$P$28) | C29: =IF(B29="","",Masters!$R$28) | D29: =IF(B29="",0,Masters!$Q$28) -> 0 | E29: =IF(B29="",0,SUMIFS(Cash_Book!$G$4:$G$1008,Cash_Book!$C$4:$C$1008,C29,Cash_Book!$D$4:$D$1008,"TAKEN",Cash_Book!$E$4:$E$1008,B29)) -> 0 | F29: =IF(B29="",0,SUMIFS(Cash_Book!$G$4:$G$1008,Cash_Book!$C$4:$C$1008,C29,Cash_Book!$D$4:$D$1008,"WITHDRAWN",Cash_Book!$E$4:$E$1008,B29)+SUMIFS(Cash_Book!$G$4:$G$1008,Cash_Book!$C$4:$C$1008,C29,Cash_Book!$D$4:$D$1008,"REPAID",Cash_Book!$E$4:$E$1008,B29)) -> 0 | G29: =IF(B29="","",D29+E29-F29)
A30: 27 | B30: =IF(Masters!$P$29="","",Masters!$P$29) | C30: =IF(B30="","",Masters!$R$29) | D30: =IF(B30="",0,Masters!$Q$29) -> 0 | E30: =IF(B30="",0,SUMIFS(Cash_Book!$G$4:$G$1008,Cash_Book!$C$4:$C$1008,C30,Cash_Book!$D$4:$D$1008,"TAKEN",Cash_Book!$E$4:$E$1008,B30)) -> 0 | F30: =IF(B30="",0,SUMIFS(Cash_Book!$G$4:$G$1008,Cash_Book!$C$4:$C$1008,C30,Cash_Book!$D$4:$D$1008,"WITHDRAWN",Cash_Book!$E$4:$E$1008,B30)+SUMIFS(Cash_Book!$G$4:$G$1008,Cash_Book!$C$4:$C$1008,C30,Cash_Book!$D$4:$D$1008,"REPAID",Cash_Book!$E$4:$E$1008,B30)) -> 0 | G30: =IF(B30="","",D30+E30-F30)
A31: 28 | B31: =IF(Masters!$P$30="","",Masters!$P$30) | C31: =IF(B31="","",Masters!$R$30) | D31: =IF(B31="",0,Masters!$Q$30) -> 0 | E31: =IF(B31="",0,SUMIFS(Cash_Book!$G$4:$G$1008,Cash_Book!$C$4:$C$1008,C31,Cash_Book!$D$4:$D$1008,"TAKEN",Cash_Book!$E$4:$E$1008,B31)) -> 0 | F31: =IF(B31="",0,SUMIFS(Cash_Book!$G$4:$G$1008,Cash_Book!$C$4:$C$1008,C31,Cash_Book!$D$4:$D$1008,"WITHDRAWN",Cash_Book!$E$4:$E$1008,B31)+SUMIFS(Cash_Book!$G$4:$G$1008,Cash_Book!$C$4:$C$1008,C31,Cash_Book!$D$4:$D$1008,"REPAID",Cash_Book!$E$4:$E$1008,B31)) -> 0 | G31: =IF(B31="","",D31+E31-F31)
A32: 29 | B32: =IF(Masters!$P$31="","",Masters!$P$31) | C32: =IF(B32="","",Masters!$R$31) | D32: =IF(B32="",0,Masters!$Q$31) -> 0 | E32: =IF(B32="",0,SUMIFS(Cash_Book!$G$4:$G$1008,Cash_Book!$C$4:$C$1008,C32,Cash_Book!$D$4:$D$1008,"TAKEN",Cash_Book!$E$4:$E$1008,B32)) -> 0 | F32: =IF(B32="",0,SUMIFS(Cash_Book!$G$4:$G$1008,Cash_Book!$C$4:$C$1008,C32,Cash_Book!$D$4:$D$1008,"WITHDRAWN",Cash_Book!$E$4:$E$1008,B32)+SUMIFS(Cash_Book!$G$4:$G$1008,Cash_Book!$C$4:$C$1008,C32,Cash_Book!$D$4:$D$1008,"REPAID",Cash_Book!$E$4:$E$1008,B32)) -> 0 | G32: =IF(B32="","",D32+E32-F32)
A33: 30 | B33: =IF(Masters!$P$32="","",Masters!$P$32) | C33: =IF(B33="","",Masters!$R$32) | D33: =IF(B33="",0,Masters!$Q$32) -> 0 | E33: =IF(B33="",0,SUMIFS(Cash_Book!$G$4:$G$1008,Cash_Book!$C$4:$C$1008,C33,Cash_Book!$D$4:$D$1008,"TAKEN",Cash_Book!$E$4:$E$1008,B33)) -> 0 | F33: =IF(B33="",0,SUMIFS(Cash_Book!$G$4:$G$1008,Cash_Book!$C$4:$C$1008,C33,Cash_Book!$D$4:$D$1008,"WITHDRAWN",Cash_Book!$E$4:$E$1008,B33)+SUMIFS(Cash_Book!$G$4:$G$1008,Cash_Book!$C$4:$C$1008,C33,Cash_Book!$D$4:$D$1008,"REPAID",Cash_Book!$E$4:$E$1008,B33)) -> 0 | G33: =IF(B33="","",D33+E33-F33)
A35: TOTALS BY TYPE:
B36: CAPITAL Total | G36: =SUMIF(C4:C33,"CAPITAL",G4:G33) -> 4469981
B37: LOAN Total | G37: =SUMIF(C4:C33,"LOAN",G4:G33) -> 0
B38: AMANAT Total | G38: =SUMIF(C4:C33,"AMANAT",G4:G33) -> 2500000

Sheet Bepaari_Aakda
A1: BEPAARI SETTLEMENT SLIP (AAKDA)
A3: SELECT BEPAARI: | B3: CHINTU SHUJALPUR
A6: A. SALES
A7: Qty Sold | B7: =SUMIF(Daily_Sales!$C$4:$C$503,$B$3,Daily_Sales!$E$4:$E$503) -> 58
A8: Gross Sales | B8: =SUMIF(Daily_Sales!$C$4:$C$503,$B$3,Daily_Sales!$G$4:$G$503) -> 574300
A10: B. DEDUCTIONS
A11: Commission Type | B11: =IF(IFERROR(INDEX(Masters!$D$3:$D$52,MATCH($B$3,Masters!$B$3:$B$52,0)),"")="","% Based","Flat ₹/Goat") -> % Based
A12: Commission % | B12: =IFERROR(INDEX(Masters!$C$3:$C$52,MATCH($B$3,Masters!$B$3:$B$52,0)),4) -> 4
A13: Flat ₹/Goat | B13: =IFERROR(INDEX(Masters!$D$3:$D$52,MATCH($B$3,Masters!$B$3:$B$52,0)),"") -> 0
A14: Commission Amt | B14: =IFERROR(IF(B13>0,B13*B7,B8*B12/100),B8*B12/100) -> 22972
A15: KK (Fixed) | B15: =IF(B7>0,Masters!$Y$3,0) -> 100
A16: JB | B16: =B7*Masters!$Y$4 -> 580
A17: Motor | B17: =SUMIFS(Cash_Book!$G$4:$G$1008,Cash_Book!$C$4:$C$1008,"BEPAARI",Cash_Book!$D$4:$D$1008,"MOTOR",Cash_Book!$E$4:$E$1008,$B$3) -> 15600
A18: Bhussa | B18: =SUMIFS(Cash_Book!$G$4:$G$1008,Cash_Book!$C$4:$C$1008,"BEPAARI",Cash_Book!$D$4:$D$1008,"BHUSSA",Cash_Book!$E$4:$E$1008,$B$3) -> 400
A19: Gawali | B19: =SUMIFS(Cash_Book!$G$4:$G$1008,Cash_Book!$C$4:$C$1008,"BEPAARI",Cash_Book!$D$4:$D$1008,"GAWALI",Cash_Book!$E$4:$E$1008,$B$3) -> 3540
A20: Cash/Adv | B20: =SUMIFS(Cash_Book!$G$4:$G$1008,Cash_Book!$C$4:$C$1008,"BEPAARI",Cash_Book!$D$4:$D$1008,"CASH_ADV",Cash_Book!$E$4:$E$1008,$B$3) -> 0
A21: TOTAL DEDUCTIONS | B21: =SUM(B14:B20) -> 43192
A23: C. CALCULATION
A24: Gross Sales | B24: =B8 -> 574300
A25: (-) Deductions | B25: =B21 -> 43192
A26: (+) Opening Bal | B26: =IFERROR(INDEX(Masters!$E$3:$E$52,MATCH($B$3,Masters!$B$3:$B$52,0)),0) -> 0
A27: NET PAYABLE | B27: =B24-B25+B26 -> 531108
A29: D. PAYMENTS
A30: Payments Made | B30: =SUMIFS(Cash_Book!$G$4:$G$1008,Cash_Book!$C$4:$C$1008,"BEPAARI",Cash_Book!$D$4:$D$1008,"PAYMENT",Cash_Book!$E$4:$E$1008,$B$3) -> 460024
A32: BALANCE DUE | B32: =B27-B30 -> 71084

Sheet Balance_Sheet
A1: BALANCE SHEET | E1: LIABILITIES = ASSETS
A3: LIABILITIES (We Owe) | D3: ASSETS (We Have / Owed to Us)
A4: Particulars | B4: Amount | D4: Particulars | E4: Amount
A5: CAPITAL | B5: =Capital_Loan_Ledger!G36 -> 4469981 | D5: CASH BALANCE | E5: =Cash_Book!J10 -> 386735
A6: LOANS | B6: =Capital_Loan_Ledger!G37 -> 0 | D6: BANK BALANCE | E6: =Cash_Book!J11 -> 537228
A7: AMANAT | B7: =Capital_Loan_Ledger!G38 -> 2500000
D8: PATTI (Dukandar Receivable) | E8: =Dukandar_Ledger!H107 -> 6444105
A9: BEPAARI PAYABLES | B9: =Bepaari_Ledger!S58 -> 1105792 | D9: BEPAARI ADVANCES (Overpaid) | E9: =Bepaari_Ledger!S59 -> 216554
A10: DUKANDAR ADVANCES (Overpaid) | B10: =Dukandar_Ledger!H108 -> 7500
D11: ADVANCES GIVEN (Net)
A12: JB:
A13: B/F | B13: =Masters!$Y$10 -> 17100 | D13: MANDI EXPENSES:
A14: (+) Collected | B14: =Bepaari_Ledger!J55 -> 4660 | D14: B/F | E14: =Masters!$Y$16 -> 24816
A15: (-) Paid | B15: =-SUMIFS(Cash_Book!$G$4:$G$1008,Cash_Book!$D$4:$D$1008,"JB_PAID") -> -18000 | D15: (+) Current | E15: =SUMIFS(Cash_Book!$G$4:$G$1008,Cash_Book!$D$4:$D$1008,"MANDI")+SUMIFS(Cash_Book!$G$4:$G$1008,Cash_Book!$D$4:$D$1008,"TRAVEL")+SUMIFS(Cash_Book!$G$4:$G$1008,Cash_Book!$D$4:$D$1008,"FOOD")+SUMIFS(Cash_Book!$G$4:$G$1008,Cash_Book!$D$4:$D$1008,"SALARY")+SUMIFS(Cash_Book!$G$4:$G$1008,Cash_Book!$D$4:$D$1008,"MISC")+SUMIFS(Cash_Book!$G$4:$G$1008,Cash_Book!$D$4:$D$1008,"OTHER") -> 14360
A16: JB Total | B16: =B13+B14+B15 -> 3760 | D16: Mandi Total | E16: =E14+E15 -> 39176
A18: KK: | D18: BF DISCOUNT:
A19: B/F | B19: =Masters!$Y$11 -> 10100 | D19: B/F | E19: =Masters!$Y$17 -> 17450
A20: (+) Collected | B20: =Bepaari_Ledger!I55 -> 1100 | D20: (+) Current | E20: =SUMIFS(Cash_Book!$G$4:$G$1008,Cash_Book!$D$4:$D$1008,"BF_DISC") -> 9988
A21: KK Total | B21: =B19+B20 -> 11200 | D21: BF Disc Total | E21: =E19+E20 -> 27438
A23: COMMISSION: | D23: MHN PERSONAL:
A24: B/F | B24: =Masters!$Y$13 -> 358808 | D24: B/F | E24: =Masters!$Y$18 -> 294265
A25: (+) Earned | B25: =Bepaari_Ledger!H55 -> 198480 | D25: (+) Paid | E25: =SUMIFS(Cash_Book!$G$4:$G$1008,Cash_Book!$D$4:$D$1008,"MHN_PERSONAL") -> 4881
A26: (-) Discounts | B26: =-Dukandar_Ledger!E104 -> -29050 | D26: MHN Total | E26: =E24+E25 -> 299146
A27: Commission Total | B27: =B24+B25+B26 -> 528238
D28: SALIM MANGROL RECEIVABLE | E28: =Masters!$V$3+SUMIFS(Cash_Book!$G$4:$G$1008,Cash_Book!$C$4:$C$1008,"ADVANCE",Cash_Book!$D$4:$D$1008,"GIVEN",Cash_Book!$E$4:$E$1008,"SALIM MANGROL")-SUMIFS(Cash_Book!$G$4:$G$1008,Cash_Book!$C$4:$C$1008,"ADVANCE",Cash_Book!$D$4:$D$1008,"RECEIVED",Cash_Book!$E$4:$E$1008,"SALIM MANGROL") -> 50000
A29: ZAKAT PAYABLE: | D29: MUDASSIR RECEIVABLE | E29: =Masters!$V$4+SUMIFS(Cash_Book!$G$4:$G$1008,Cash_Book!$C$4:$C$1008,"ADVANCE",Cash_Book!$D$4:$D$1008,"GIVEN",Cash_Book!$E$4:$E$1008,"MUDASSIR")-SUMIFS(Cash_Book!$G$4:$G$1008,Cash_Book!$C$4:$C$1008,"ADVANCE",Cash_Book!$D$4:$D$1008,"RECEIVED",Cash_Book!$E$4:$E$1008,"MUDASSIR") -> 25000
A30: B/F + Provision - Paid | B30: =Masters!$Y$12+SUMIFS(Cash_Book!$G$4:$G$1008,Cash_Book!$D$4:$D$1008,"PROVISION")-SUMIFS(Cash_Book!$G$4:$G$1008,Cash_Book!$D$4:$D$1008,"PAID") -> 53111 | D30: KMN RECEIVABLE | E30: =Masters!$V$6+SUMIFS(Cash_Book!$G$4:$G$1008,Cash_Book!$C$4:$C$1008,"ADVANCE",Cash_Book!$D$4:$D$1008,"GIVEN",Cash_Book!$E$4:$E$1008,"KMN")-SUMIFS(Cash_Book!$G$4:$G$1008,Cash_Book!$C$4:$C$1008,"ADVANCE",Cash_Book!$D$4:$D$1008,"RECEIVED",Cash_Book!$E$4:$E$1008,"KMN") -> 347500
D31: SANTOSH RECEIVABLE | E31: =Masters!$V$7+SUMIFS(Cash_Book!$G$4:$G$1008,Cash_Book!$C$4:$C$1008,"ADVANCE",Cash_Book!$D$4:$D$1008,"GIVEN",Cash_Book!$E$4:$E$1008,"SANTOSH")-SUMIFS(Cash_Book!$G$4:$G$1008,Cash_Book!$C$4:$C$1008,"ADVANCE",Cash_Book!$D$4:$D$1008,"RECEIVED",Cash_Book!$E$4:$E$1008,"SANTOSH") -> 3000
D32: SHAKIL GHODEGAON RECEIVABLE | E32: =Masters!$V$8+SUMIFS(Cash_Book!$G$4:$G$1008,Cash_Book!$C$4:$C$1008,"ADVANCE",Cash_Book!$D$4:$D$1008,"GIVEN",Cash_Book!$E$4:$E$1008,"SHAKIL GHODEGAON")-SUMIFS(Cash_Book!$G$4:$G$1008,Cash_Book!$C$4:$C$1008,"ADVANCE",Cash_Book!$D$4:$D$1008,"RECEIVED",Cash_Book!$E$4:$E$1008,"SHAKIL GHODEGAON") -> 0
D33: AYAAN RECEIVABLE | E33: =Masters!$V$5+SUMIFS(Cash_Book!$G$4:$G$1008,Cash_Book!$C$4:$C$1008,"ADVANCE",Cash_Book!$D$4:$D$1008,"GIVEN",Cash_Book!$E$4:$E$1008,"AYAAN")-SUMIFS(Cash_Book!$G$4:$G$1008,Cash_Book!$C$4:$C$1008,"ADVANCE",Cash_Book!$D$4:$D$1008,"RECEIVED",Cash_Book!$E$4:$E$1008,"AYAAN") -> 53700
A36: TOTAL LIABILITIES | B36: =B5+B6+B7+B9+B10+B16+B21+B27+B30 -> 8679582 | D36: TOTAL ASSETS | E36: =E5+E6+E8+E9+E11+E16+E21+E26+E28+E29+E30+E31+E32+E33 -> 8429582
A38: DIFFERENCE (Should be 0) | B38: =B36-E36 -> 250000

Sheet Commission_Summary
A1: COMMISSION & PROFIT SUMMARY
A3: GROSS SALES | B3: =Bepaari_Ledger!F55 -> 4962000
A4: TOTAL GOATS SOLD | B4: =Bepaari_Ledger!G55 -> 466
A6: INCOME:
A7: Commission Earned | B7: =Bepaari_Ledger!H55 -> 198480
A8: (-) Discounts Given | B8: =-Dukandar_Ledger!E104 -> -29050
A9: Net Commission | B9: =B6+B7 -> 198480
A10: JB Collected | B10: =Bepaari_Ledger!J55 -> 4660
A11: KK Collected | B11: =Bepaari_Ledger!I55 -> 1100
A12: TOTAL INCOME | B12: =B8+B9+B10 -> 174090
A14: EXPENSES:
A15: Mandi/Business | B15: =SUMIFS(Cash_Book!$G$4:$G$1008,Cash_Book!$D$4:$D$1008,"MANDI")+SUMIFS(Cash_Book!$G$4:$G$1008,Cash_Book!$D$4:$D$1008,"TRAVEL")+SUMIFS(Cash_Book!$G$4:$G$1008,Cash_Book!$D$4:$D$1008,"FOOD")+SUMIFS(Cash_Book!$G$4:$G$1008,Cash_Book!$D$4:$D$1008,"SALARY")+SUMIFS(Cash_Book!$G$4:$G$1008,Cash_Book!$D$4:$D$1008,"MISC")+SUMIFS(Cash_Book!$G$4:$G$1008,Cash_Book!$D$4:$D$1008,"OTHER") -> 14360
A16: BF Discount | B16: =SUMIFS(Cash_Book!$G$4:$G$1008,Cash_Book!$D$4:$D$1008,"BF_DISC") -> 9988
A17: JB Paid | B17: =SUMIFS(Cash_Book!$G$4:$G$1008,Cash_Book!$D$4:$D$1008,"JB_PAID") -> 18000
A18: TOTAL EXPENSES | B18: =B14+B15+B16 -> 24348
A20: NET PROFIT/LOSS | B20: =B11-B17 -> -16900
