Workbook
Name BEPAARI: Masters!$B$3:$B$52
Name DUKANDAR: Masters!$I$3:$I$52
Name CAPITAL: Masters!$O$3:$O$32
Name LOAN: Masters!$O$3:$O$32
Name AMANAT: Masters!$O$3:$O$32
Name ADVANCE: Masters!$T$3:$T$22
Name EXPENSE: Lookups!$B$3:$B$3
Name ZAKAT: Lookups!$B$3:$B$3
Name DRAWINGS: Lookups!$B$3:$B$3
Name OTHER: Lookups!$B$3:$B$3
Name ST_BEPAARI: Lookups!$D$3:$D$8
Name ST_DUKANDAR: Lookups!$E$3:$E$5
Name ST_CAPITAL: Lookups!$F$3:$F$5
Name ST_LOAN: Lookups!$G$3:$G$4
Name ST_AMANAT: Lookups!$G$3:$G$4
Name ST_ADVANCE: Lookups!$H$3:$H$4
Name ST_EXPENSE: Lookups!$I$3:$I$14
Name ST_ZAKAT: Lookups!$J$3:$J$4
Name ST_DRAWINGS: Lookups!$K$3:$K$4
Name ST_OTHER: Lookups!$L$3:$L$4

Sheet Lookups
A1: LOOKUP TABLES (Do not edit)
B2: NO_PARTY | D2: ST_BEPAARI | E2: ST_DUKANDAR | F2: ST_CAPITAL | G2: ST_LOAN | H2: ST_ADVANCE | I2: ST_EXPENSE | J2: ST_ZAKAT | K2: ST_DRAWINGS | L2: ST_OTHER
B3: - | D3: PAYMENT | E3: RECEIPT | F3: TAKEN | G3: TAKEN | H3: GIVEN | I3: MANDI | J3: PROVISION | K3: MHN_PERSONAL | L3: MISC
D4: MOTOR | E4: DISCOUNT | F4: WITHDRAWN | G4: REPAID | H4: RECEIVED | I4: TRAVEL | J4: PAID | K4: ADJUSTED | L4: OTHER
D5: BHUSSA | E5: OTHER | F5: PROFIT_TO_CAP | I5: FOOD
D6: GAWALI | I6: SALARY
D7: CASH_ADV | I7: BF_DISC
D8: OTHER | I8: JB_PAID
I9: JB_WITHDRAW
I10: KK_WITHDRAW
I11: COMM_WITHDRAW
I12: PROFIT_WITHDRAW
I13: MISC
I14: OTHER

Sheet Masters
A1: BEPAARI MASTER | I1: DUKANDAR MASTER | O1: CAPITAL/LOAN/AMANAT | T1: ADVANCE PARTIES | X1: SETTINGS & OPENING BALANCES
A2: Sr | B2: Bepaari Name | C2: Comm% | D2: Flat ₹/Goat | E2: Opening Bal | F2: Phone | G2: Remarks | I2: Sr | J2: Dukandar Name | K2: Opening Bal | L2: Phone | M2: Remarks | O2: Sr | P2: Party Name | Q2: Opening Bal | R2: Type | T2: Sr | U2: Party Name | V2: Opening Bal | X2: Commission Rate (%) | Y2: 4
A3: 1 | B3: ABUL HASAN | C3: 4 | E3: 7550 | I3: 1 | J3: SAKIM | K3: 113500 | O3: 1 | P3: MHN CAPITAL | Q3: 4469981 | R3: CAPITAL | T3: 1 | X3: KK Fixed (₹/Bepari) | Y3: 25
A4: 2 | B4: SHARAFAT | C4: 4 | E4: 0 | I4: 2 | J4: SHARIK | K4: 879000 | O4: 2 | P4: SHAKIL GHODEGAON AMANAT | Q4: 2000000 | R4: AMANAT | T4: 2 | X4: JB Rate (₹/Goat) | Y4: 1
A5: 3 | B5: JUNAID | C5: 4 | E5: 0 | I5: 3 | J5: YUNUS | K5: 94931 | O5: 3 | T5: 3
A6: 4 | B6: ANNU SHARIF | C6: 4 | E6: 0 | I6: 4 | J6: MUDASSIR | K6: 516778 | O6: 4 | T6: 4 | X6: Opening Cash | Y6: 394906
A7: 5 | B7: GAYYUR | C7: 4 | E7: 142530 | I7: 5 | J7: ARIF | K7: 187650 | O7: 5 | T7: 5 | X7: Opening Bank | Y7: 724604
A8: 6 | B8: KISHOR | C8: 4 | E8: -152964 | I8: 6 | J8: SHOEB BYCULLA | K8: 0 | O8: 6 | T8: 6
A9: 7 | B9: MAULANA | C9: 4 | E9: 35330 | I9: 7 | J9: ISLAM D | K9: 100000 | O9: 7 | T9: 7 | X9: --- B/F LIABILITIES ---
A10: 8 | B10: SALIM RAJ | C10: 4 | E10: 0 | I10: 8 | J10: MEHMOOD MADH | K10: 15000 | O10: 8 | T10: 8 | X10: JB Opening (B/F) | Y10: 17100
A11: 9 | B11: ANAS RAJ | C11: 4 | E11: 0 | I11: 9 | J11: MOBIN CHIPLUN | K11: 486250 | O11: 9 | T11: 9 | X11: KK Opening (B/F) | Y11: 10100
A12: 10 | B12: AYAZ | C12: 4 | E12: 1530 | I12: 10 | J12: JALIL | K12: 90950 | O12: 10 | T12: 10 | X12: Zakat Opening (B/F) | Y12: 73111
A13: 11 | B13: NEERAJ | C13: 4 | E13: 0 | I13: 11 | J13: IRFAN JOGESHWARI | K13: 0 | O13: 11 | T13: 11 | X13: Commission Opening (B/F) | Y13: 358808
A14: 12 | B14: CHINTU SHUJALPUR | C14: 4 | E14: 0 | I14: 12 | J14: YUNUS DOMBIVLI | K14: 59662 | O14: 12 | T14: 12
A15: 13 | B15: SANNA | C15: 4 | E15: -14048 | I15: 13 | J15: IFTEKHAR PUNE | K15: 2000 | O15: 13 | T15: 13 | X15: --- B/F ASSETS ---
A16: 14 | B16: WAHID | C16: 4 | E16: -4661 | I16: 14 | J16: LALA/ASIF | K16: 0 | O16: 14 | T16: 14 | X16: Mandi Exp Opening (B/F) | Y16: 17450
A17: 15 | B17: MANSOOR | C17: 4 | E17: -9845 | I17: 15 | J17: JAFER KASHIMIRA | K17: 92500 | O17: 15 | T17: 15 | X17: BF Discount Opening (B/F) | Y17: 24816
A18: 16 | B18: AYAZ PREVIOUS BAL | C18: 4 | E18: -88000 | I18: 16 | J18: HANIF KALAM | K18: 0 | O18: 16 | T18: 16 | X18: MHN Personal Opening (B/F) | Y18: 294265
A19: 17 | B19: SHAKIL SHUJALPUR | C19: 4 | E19: 660 | I19: 17 | J19: SAUD K | K19: 0 | O19: 17 | T19: 17
A20: 18 | B20: USMAN | C20: 4 | E20: 40440 | I20: 18 | J20: AKRAM | K20: 0 | O20: 18 | T20: 18
A21: 19 | C21: 4 | I21: 19 | J21: WAHID | K21: 4000 | O21: 19 | T21: 19
A22: 20 | C22: 4 | I22: 20 | J22: VAZIR | K22: 134750 | O22: 20 | T22: 20
A23: 21 | C23: 4 | I23: 21 | J23: ISMAIL SOPARA | K23: 0 | O23: 21
A24: 22 | C24: 4 | I24: 22 | J24: ARIF CHINCHOTI | K24: 0 | O24: 22
A25: 23 | C25: 4 | I25: 23 | J25: NADEEM BHIWANDI | K25: 265000 | O25: 23
A26: 24 | C26: 4 | I26: 24 | J26: GABBAR | K26: 33050 | O26: 24
A27: 25 | C27: 4 | I27: 25 | J27: BABU GABBAR | K27: 50000 | O27: 25
A28: 26 | C28: 4 | I28: 26 | J28: BABU TALOJA | K28: 2600 | O28: 26
A29: 27 | C29: 4 | I29: 27 | J29: SHAKIL KON | K29: 34000 | O29: 27
A30: 28 | C30: 4 | I30: 28 | J30: PARVEZ | K30: 0 | O30: 28
A31: 29 | C31: 4 | I31: 29 | J31: I CHO CHO | K31: 20500 | O31: 29
A32: 30 | C32: 4 | I32: 30 | J32: MD VIRAR | K32: 1900 | O32: 30
A33: 31 | C33: 4 | I33: 31 | J33: MAYA | K33: 11000
A34: 32 | C34: 4 | I34: 32 | J34: NAEEM THORPE | K34: 0
A35: 33 | C35: 4 | I35: 33 | J35: CHAND | K35: 59000
A36: 34 | C36: 4 | I36: 34 | J36: ASIF GOREGAON | K36: 57550
A37: 35 | C37: 4 | I37: 35 | J37: SOHAIL MAROL | K37: 0
A38: 36 | C38: 4 | I38: 36 | J38: ANEES KM | K38: 70000
A39: 37 | C39: 4 | I39: 37 | J39: RAFIQ AHMED HAJI | K39: 356250
A40: 38 | C40: 4 | I40: 38 | J40: ABP - MAJEED THANA | K40: 0
A41: 39 | C41: 4 | I41: 39 | J41: ABP - MAJNU | K41: 0
A42: 40 | C42: 4 | I42: 40 | J42: MEHBOOB JOG | K42: 98500
A43: 41 | C43: 4 | I43: 41 | J43: SIRAJ KURLA | K43: 388000
A44: 42 | C44: 4 | I44: 42 | J44: ZUBAIR AZEEZ | K44: 30000
... A47: 45 | C47: 4 | I47: 45 | J47: LIYAQAT | K47: 7500
A48: 46 | C48: 4 | I48: 46
A49: 47 | C49: 4 | I49: 47
A50: 48 | C50: 4 | I50: 48
A51: 49 | C51: 4 | I51: 49
A52: 50 | C52: 4 | I52: 50

Sheet Daily_Sales
A1: DAILY SALES (Bepaari to Dukandar)
A3: Sr | B3: Date | C3: Bepaari | D3: Dukandar | E3: Qty | F3: Rate | G3: Gross | H3: Discount | I3: Net
A4: 1 | G4: =IF(E4="","",E4*F4) | I4: =IF(G4="","",G4-IF(H4="",0,H4))
A5: 2 | G5: =IF(E5="","",E5*F5) | I5: =IF(G5="","",G5-IF(H5="",0,H5))
A6: 3 | G6: =IF(E6="","",E6*F6) | I6: =IF(G6="","",G6-IF(H6="",0,H6))
A7: 4 | G7: =IF(E7="","",E7*F7) | I7: =IF(G7="","",G7-IF(H7="",0,H7))
A8: 5 | G8: =IF(E8="","",E8*F8) | I8: =IF(G8="","",G8-IF(H8="",0,H8))
A9: 6 | G9: =IF(E9="","",E9*F9) | I9: =IF(G9="","",G9-IF(H9="",0,H9))
A10: 7 | G10: =IF(E10="","",E10*F10) | I10: =IF(G10="","",G10-IF(H10="",0,H10))
A11: 8 | G11: =IF(E11="","",E11*F11) | I11: =IF(G11="","",G11-IF(H11="",0,H11))
A12: 9 | G12: =IF(E12="","",E12*F12) | I12: =IF(G12="","",G12-IF(H12="",0,H12))
A13: 10 | G13: =IF(E13="","",E13*F13) | I13: =IF(G13="","",G13-IF(H13="",0,H13))
A14: 11 | G14: =IF(E14="","",E14*F14) | I14: =IF(G14="","",G14-IF(H14="",0,H14))
A15: 12 | G15: =IF(E15="","",E15*F15) | I15: =IF(G15="","",G15-IF(H15="",0,H15))
... A503: 500 | G503: =IF(E503="","",E503*F503) | I503: =IF(G503="","",G503-IF(H503="",0,H503))

Sheet Cash_Book
A1: CASH BOOK (All Transactions) | J1: CASH/BANK SUMMARY
A2: Select TYPE first → Sub-Type & Party dropdowns update automatically | I2: Opening Cash | J2: =Masters!$Y$6
A3: Sr | B3: Date | C3: Type | D3: Sub-Type | E3: Party | F3: Particulars | G3: Amount | H3: Mode | I3: Opening Bank | J3: =Masters!$Y$7
A4: 1
A5: 2 | I5: Cash OUT | J5: =SUMIFS(G:G,H:H,"CASH",D:D,"PAYMENT")+SUMIFS(G:G,H:H,"CASH",D:D,"MOTOR")+SUMIFS(G:G,H:H,"CASH",D:D,"BHUSSA")+SUMIFS(G:G,H:H,"CASH",D:D,"GAWALI")+SUMIFS(G:G,H:H,"CASH",D:D,"CASH_ADV")+SUMIFS(G:G,H:H,"CASH",D:D,"DISCOUNT")+SUMIFS(G:G,H:H,"CASH",D:D,"WITHDRAWN")+SUMIFS(G:G,H:H,"CASH",D:D,"REPAID")+SUMIFS(G:G,H:H,"CASH",D:D,"GIVEN")+SUMIFS(G:G,H:H,"CASH",D:D,"MANDI")+SUMIFS(G:G,H:H,"CASH",D:D,"TRAVEL")+SUMIFS(G:G,H:H,"CASH",D:D,"FOOD")+SUMIFS(G:G,H:H,"CASH",D:D,"SALARY")+SUMIFS(G:G,H:H,"CASH",D:D,"BF_DISC")+SUMIFS(G:G,H:H,"CASH",D:D,"JB_PAID")+SUMIFS(G:G,H:H,"CASH",D:D,"JB_WITHDRAW")+SUMIFS(G:G,H:H,"CASH",D:D,"KK_WITHDRAW")+SUMIFS(G:G,H:H,"CASH",D:D,"COMM_WITHDRAW")+SUMIFS(G:G,H:H,"CASH",D:D,"PROFIT_WITHDRAW")+SUMIFS(G:G,H:H,"CASH",D:D,"PAID")+SUMIFS(G:G,H:H,"CASH",D:D,"MISC")+SUMIFS(G:G,H:H,"CASH",D:D,"OTHER")+SUMIFS(G:G,H:H,"CASH",D:D,"MHN_PERSONAL")+SUMIFS(G:G,H:H,"CASH",D:D,"ADJUSTED")+SUMIFS(G:G,H:H,"CASH",D:D,"PROFIT_TO_CAP")
A6: 3 | I6: Bank OUT | J6: =SUMIFS(G:G,H:H,"BANK",D:D,"PAYMENT")+SUMIFS(G:G,H:H,"BANK",D:D,"MOTOR")+SUMIFS(G:G,H:H,"BANK",D:D,"BHUSSA")+SUMIFS(G:G,H:H,"BANK",D:D,"GAWALI")+SUMIFS(G:G,H:H,"BANK",D:D,"CASH_ADV")+SUMIFS(G:G,H:H,"BANK",D:D,"DISCOUNT")+SUMIFS(G:G,H:H,"BANK",D:D,"WITHDRAWN")+SUMIFS(G:G,H:H,"BANK",D:D,"REPAID")+SUMIFS(G:G,H:H,"BANK",D:D,"GIVEN")+SUMIFS(G:G,H:H,"BANK",D:D,"MANDI")+SUMIFS(G:G,H:H,"BANK",D:D,"TRAVEL")+SUMIFS(G:G,H:H,"BANK",D:D,"FOOD")+SUMIFS(G:G,H:H,"BANK",D:D,"SALARY")+SUMIFS(G:G,H:H,"BANK",D:D,"BF_DISC")+SUMIFS(G:G,H:H,"BANK",D:D,"JB_PAID")+SUMIFS(G:G,H:H,"BANK",D:D,"JB_WITHDRAW")+SUMIFS(G:G,H:H,"BANK",D:D,"KK_WITHDRAW")+SUMIFS(G:G,H:H,"BANK",D:D,"COMM_WITHDRAW")+SUMIFS(G:G,H:H,"BANK",D:D,"PROFIT_WITHDRAW")+SUMIFS(G:G,H:H,"BANK",D:D,"PAID")+SUMIFS(G:G,H:H,"BANK",D:D,"MISC")+SUMIFS(G:G,H:H,"BANK",D:D,"OTHER")+SUMIFS(G:G,H:H,"BANK",D:D,"MHN_PERSONAL")+SUMIFS(G:G,H:H,"BANK",D:D,"ADJUSTED")+SUMIFS(G:G,H:H,"BANK",D:D,"PROFIT_TO_CAP")+SUMIFS(G:G,H:H,"UPI",D:D,"PAYMENT")+SUMIFS(G:G,H:H,"UPI",D:D,"MOTOR")+SUMIFS(G:G,H:H,"UPI",D:D,"BHUSSA")+SUMIFS(G:G,H:H,"UPI",D:D,"GAWALI")+SUMIFS(G:G,H:H,"UPI",D:D,"CASH_ADV")+SUMIFS(G:G,H:H,"UPI",D:D,"DISCOUNT")+SUMIFS(G:G,H:H,"UPI",D:D,"WITHDRAWN")+SUMIFS(G:G,H:H,"UPI",D:D,"REPAID")+SUMIFS(G:G,H:H,"UPI",D:D,"GIVEN")+SUMIFS(G:G,H:H,"UPI",D:D,"MANDI")+SUMIFS(G:G,H:H,"UPI",D:D,"TRAVEL")+SUMIFS(G:G,H:H,"UPI",D:D,"FOOD")+SUMIFS(G:G,H:H,"UPI",D:D,"SALARY")+SUMIFS(G:G,H:H,"UPI",D:D,"BF_DISC")+SUMIFS(G:G,H:H,"UPI",D:D,"JB_PAID")+SUMIFS(G:G,H:H,"UPI",D:D,"JB_WITHDRAW")+SUMIFS(G:G,H:H,"UPI",D:D,"KK_WITHDRAW")+SUMIFS(G:G,H:H,"UPI",D:D,"COMM_WITHDRAW")+SUMIFS(G:G,H:H,"UPI",D:D,"PROFIT_WITHDRAW")+SUMIFS(G:G,H:H,"UPI",D:D,"PAID")+SUMIFS(G:G,H:H,"UPI",D:D,"MISC")+SUMIFS(G:G,H:H,"UPI",D:D,"OTHER")+SUMIFS(G:G,H:H,"UPI",D:D,"MHN_PERSONAL")+SUMIFS(G:G,H:H,"UPI",D:D,"ADJUSTED")+SUMIFS(G:G,H:H,"UPI",D:D,"PROFIT_TO_CAP")+SUMIFS(G:G,H:H,"TRANSFER",D:D,"PAYMENT")+SUMIFS(G:G,H:H,"TRANSFER",D:D,"MOTOR")+SUMIFS(G:G,H:H,"TRANSFER",D:D,"BHUSSA")+SUMIFS(G:G,H:H,"TRANSFER",D:D,"GAWALI")+SUMIFS(G:G,H:H,"TRANSFER",D:D,"CASH_ADV")+SUMIFS(G:G,H:H,"TRANSFER",D:D,"DISCOUNT")+SUMIFS(G:G,H:H,"TRANSFER",D:D,"WITHDRAWN")+SUMIFS(G:G,H:H,"TRANSFER",D:D,"REPAID")+SUMIFS(G:G,H:H,"TRANSFER",D:D,"GIVEN")+SUMIFS(G:G,H:H,"TRANSFER",D:D,"MANDI")+SUMIFS(G:G,H:H,"TRANSFER",D:D,"TRAVEL")+SUMIFS(G:G,H:H,"TRANSFER",D:D,"FOOD")+SUMIFS(G:G,H:H,"TRANSFER",D:D,"SALARY")+SUMIFS(G:G,H:H,"TRANSFER",D:D,"BF_DISC")+SUMIFS(G:G,H:H,"TRANSFER",D:D,"JB_PAID")+SUMIFS(G:G,H:H,"TRANSFER",D:D,"JB_WITHDRAW")+SUMIFS(G:G,H:H,"TRANSFER",D:D,"KK_WITHDRAW")+SUMIFS(G:G,H:H,"TRANSFER",D:D,"COMM_WITHDRAW")+SUMIFS(G:G,H:H,"TRANSFER",D:D,"PROFIT_WITHDRAW")+SUMIFS(G:G,H:H,"TRANSFER",D:D,"PAID")+SUMIFS(G:G,H:H,"TRANSFER",D:D,"MISC")+SUMIFS(G:G,H:H,"TRANSFER",D:D,"OTHER")+SUMIFS(G:G,H:H,"TRANSFER",D:D,"MHN_PERSONAL")+SUMIFS(G:G,H:H,"TRANSFER",D:D,"ADJUSTED")+SUMIFS(G:G,H:H,"TRANSFER",D:D,"PROFIT_TO_CAP")
A7: 4 | I7: Cash IN | J7: =SUMIFS(G:G,H:H,"CASH",D:D,"RECEIPT")+SUMIFS(G:G,H:H,"CASH",D:D,"TAKEN")+SUMIFS(G:G,H:H,"CASH",D:D,"RECEIVED")+SUMIFS(G:G,H:H,"CASH",D:D,"PROVISION")
A8: 5 | I8: Bank IN | J8: =SUMIFS(G:G,H:H,"BANK",D:D,"RECEIPT")+SUMIFS(G:G,H:H,"BANK",D:D,"TAKEN")+SUMIFS(G:G,H:H,"BANK",D:D,"RECEIVED")+SUMIFS(G:G,H:H,"BANK",D:D,"PROVISION")+SUMIFS(G:G,H:H,"UPI",D:D,"RECEIPT")+SUMIFS(G:G,H:H,"UPI",D:D,"TAKEN")+SUMIFS(G:G,H:H,"UPI",D:D,"RECEIVED")+SUMIFS(G:G,H:H,"UPI",D:D,"PROVISION")+SUMIFS(G:G,H:H,"TRANSFER",D:D,"RECEIPT")+SUMIFS(G:G,H:H,"TRANSFER",D:D,"TAKEN")+SUMIFS(G:G,H:H,"TRANSFER",D:D,"RECEIVED")+SUMIFS(G:G,H:H,"TRANSFER",D:D,"PROVISION")
A9: 6
A10: 7 | I10: CLOSING CASH | J10: =J2-J5+J7
A11: 8 | I11: CLOSING BANK | J11: =J3-J6+J8
A12: 9
A13: 10
A14: 11
A15: 12
A16: 13
A17: 14
A18: 15
A19: 16
A20: 17
A21: 18
A22: 19
A23: 20
... A1003: 1000

Sheet JV_Entries
A1: JOURNAL VOUCHER ENTRIES (Internal Adjustments)
A2: Use for: Dukandar-to-Dukandar transfers, Bepaari adjustments, any non-cash internal entries
A4: Sr | B4: Date | C4: Debit Type | D4: Debit Party | E4: Credit Type | F4: Credit Party | G4: Amount | H4: Narration
A5: 1
A6: 2
A7: 3
A8: 4
A9: 5
A10: 6
A11: 7
A12: 8
A13: 9
A14: 10
A15: 11
A16: 12
... A104: 100

Sheet Adjustments
A1: MANUAL ADJUSTMENTS (Corrections & Overrides)
A2: Use for: Opening balance corrections, error fixes, any manual override
A4: Sr | B4: Date | C4: Account Type | D4: Party | E4: DR/CR | F4: Amount | G4: Narration
A5: 1
A6: 2
A7: 3
A8: 4
A9: 5
A10: 6
A11: 7
A12: 8
A13: 9
A14: 10
A15: 11
A16: 12
... A104: 100

Sheet Bepaari_Ledger
A1: BEPAARI LEDGER
A2: Commission = Flat ₹/Goat if set, otherwise Comm%
A4: Sr | B4: Bepaari | C4: Comm% | D4: Flat₹ | E4: Opening | F4: Gross Sales | G4: Qty | H4: Commission | I4: KK | J4: JB | K4: Motor | L4: Bhussa | M4: Gawali | N4: Cash/Adv | O4: Other | P4: Tot.Deduct | Q4: Net Payable | R4: Payments | S4: JV Adj | T4: BALANCE
A5: 1 | B5: =IF(Masters!$B$3="","",Masters!$B$3) | C5: =IF(B5="","",Masters!$C$3) | D5: =IF(B5="","",IF(Masters!$D$3="","",Masters!$D$3)) | E5: =IF(B5="",0,Masters!$E$3) | F5: =SUMIF(Daily_Sales!$C:$C,B5,Daily_Sales!$G:$G) | G5: =SUMIF(Daily_Sales!$C:$C,B5,Daily_Sales!$E:$E) | H5: =IF(B5="",0,IF(D5<>"",D5*G5,F5*C5/100)) | I5: =IF(G5>0,Masters!$Y$3,0) | J5: =G5*Masters!$Y$4 | K5: =SUMIFS(Cash_Book!$G:$G,Cash_Book!$C:$C,"BEPAARI",Cash_Book!$D:$D,"MOTOR",Cash_Book!$E:$E,B5) | L5: =SUMIFS(Cash_Book!$G:$G,Cash_Book!$C:$C,"BEPAARI",Cash_Book!$D:$D,"BHUSSA",Cash_Book!$E:$E,B5) | M5: =SUMIFS(Cash_Book!$G:$G,Cash_Book!$C:$C,"BEPAARI",Cash_Book!$D:$D,"GAWALI",Cash_Book!$E:$E,B5) | N5: =SUMIFS(Cash_Book!$G:$G,Cash_Book!$C:$C,"BEPAARI",Cash_Book!$D:$D,"CASH_ADV",Cash_Book!$E:$E,B5) | O5: =SUMIFS(Cash_Book!$G:$G,Cash_Book!$C:$C,"BEPAARI",Cash_Book!$D:$D,"OTHER",Cash_Book!$E:$E,B5) | P5: =SUM(H5:O5) | Q5: =IF(B5="","",F5-P5+E5) | R5: =SUMIFS(Cash_Book!$G:$G,Cash_Book!$C:$C,"BEPAARI",Cash_Book!$D:$D,"PAYMENT",Cash_Book!$E:$E,B5) | S5: =SUMIFS(JV_Entries!$G:$G,JV_Entries!$C:$C,"BEPAARI",JV_Entries!$D:$D,B5)-SUMIFS(JV_Entries!$G:$G,JV_Entries!$E:$E,"BEPAARI",JV_Entries!$F:$F,B5) | T5: =IF(B5="","",Q5-R5+S5)
A6: 2 | B6: =IF(Masters!$B$4="","",Masters!$B$4) | C6: =IF(B6="","",Masters!$C$4) | D6: =IF(B6="","",IF(Masters!$D$4="","",Masters!$D$4)) | E6: =IF(B6="",0,Masters!$E$4) | F6: =SUMIF(Daily_Sales!$C:$C,B6,Daily_Sales!$G:$G) | G6: =SUMIF(Daily_Sales!$C:$C,B6,Daily_Sales!$E:$E) | H6: =IF(B6="",0,IF(D6<>"",D6*G6,F6*C6/100)) | I6: =IF(G6>0,Masters!$Y$3,0) | J6: =G6*Masters!$Y$4 | K6: =SUMIFS(Cash_Book!$G:$G,Cash_Book!$C:$C,"BEPAARI",Cash_Book!$D:$D,"MOTOR",Cash_Book!$E:$E,B6) | L6: =SUMIFS(Cash_Book!$G:$G,Cash_Book!$C:$C,"BEPAARI",Cash_Book!$D:$D,"BHUSSA",Cash_Book!$E:$E,B6) | M6: =SUMIFS(Cash_Book!$G:$G,Cash_Book!$C:$C,"BEPAARI",Cash_Book!$D:$D,"GAWALI",Cash_Book!$E:$E,B6) | N6: =SUMIFS(Cash_Book!$G:$G,Cash_Book!$C:$C,"BEPAARI",Cash_Book!$D:$D,"CASH_ADV",Cash_Book!$E:$E,B6) | O6: =SUMIFS(Cash_Book!$G:$G,Cash_Book!$C:$C,"BEPAARI",Cash_Book!$D:$D,"OTHER",Cash_Book!$E:$E,B6) | P6: =SUM(H6:O6) | Q6: =IF(B6="","",F6-P6+E6) | R6: =SUMIFS(Cash_Book!$G:$G,Cash_Book!$C:$C,"BEPAARI",Cash_Book!$D:$D,"PAYMENT",Cash_Book!$E:$E,B6) | S6: =SUMIFS(JV_Entries!$G:$G,JV_Entries!$C:$C,"BEPAARI",JV_Entries!$D:$D,B6)-SUMIFS(JV_Entries!$G:$G,JV_Entries!$E:$E,"BEPAARI",JV_Entries!$F:$F,B6) | T6: =IF(B6="","",Q6-R6+S6)
A7: 3 | B7: =IF(Masters!$B$5="","",Masters!$B$5) | C7: =IF(B7="","",Masters!$C$5) | D7: =IF(B7="","",IF(Masters!$D$5="","",Masters!$D$5)) | E7: =IF(B7="",0,Masters!$E$5) | F7: =SUMIF(Daily_Sales!$C:$C,B7,Daily_Sales!$G:$G) | G7: =SUMIF(Daily_Sales!$C:$C,B7,Daily_Sales!$E:$E) | H7: =IF(B7="",0,IF(D7<>"",D7*G7,F7*C7/100)) | I7: =IF(G7>0,Masters!$Y$3,0) | J7: =G7*Masters!$Y$4 | K7: =SUMIFS(Cash_Book!$G:$G,Cash_Book!$C:$C,"BEPAARI",Cash_Book!$D:$D,"MOTOR",Cash_Book!$E:$E,B7) | L7: =SUMIFS(Cash_Book!$G:$G,Cash_Book!$C:$C,"BEPAARI",Cash_Book!$D:$D,"BHUSSA",Cash_Book!$E:$E,B7) | M7: =SUMIFS(Cash_Book!$G:$G,Cash_Book!$C:$C,"BEPAARI",Cash_Book!$D:$D,"GAWALI",Cash_Book!$E:$E,B7) | N7: =SUMIFS(Cash_Book!$G:$G,Cash_Book!$C:$C,"BEPAARI",Cash_Book!$D:$D,"CASH_ADV",Cash_Book!$E:$E,B7) | O7: =SUMIFS(Cash_Book!$G:$G,Cash_Book!$C:$C,"BEPAARI",Cash_Book!$D:$D,"OTHER",Cash_Book!$E:$E,B7) | P7: =SUM(H7:O7) | Q7: =IF(B7="","",F7-P7+E7) | R7: =SUMIFS(Cash_Book!$G:$G,Cash_Book!$C:$C,"BEPAARI",Cash_Book!$D:$D,"PAYMENT",Cash_Book!$E:$E,B7) | S7: =SUMIFS(JV_Entries!$G:$G,JV_Entries!$C:$C,"BEPAARI",JV_Entries!$D:$D,B7)-SUMIFS(JV_Entries!$G:$G,JV_Entries!$E:$E,"BEPAARI",JV_Entries!$F:$F,B7) | T7: =IF(B7="","",Q7-R7+S7)
A8: 4 | B8: =IF(Masters!$B$6="","",Masters!$B$6) | C8: =IF(B8="","",Masters!$C$6) | D8: =IF(B8="","",IF(Masters!$D$6="","",Masters!$D$6)) | E8: =IF(B8="",0,Masters!$E$6) | F8: =SUMIF(Daily_Sales!$C:$C,B8,Daily_Sales!$G:$G) | G8: =SUMIF(Daily_Sales!$C:$C,B8,Daily_Sales!$E:$E) | H8: =IF(B8="",0,IF(D8<>"",D8*G8,F8*C8/100)) | I8: =IF(G8>0,Masters!$Y$3,0) | J8: =G8*Masters!$Y$4 | K8: =SUMIFS(Cash_Book!$G:$G,Cash_Book!$C:$C,"BEPAARI",Cash_Book!$D:$D,"MOTOR",Cash_Book!$E:$E,B8) | L8: =SUMIFS(Cash_Book!$G:$G,Cash_Book!$C:$C,"BEPAARI",Cash_Book!$D:$D,"BHUSSA",Cash_Book!$E:$E,B8) | M8: =SUMIFS(Cash_Book!$G:$G,Cash_Book!$C:$C,"BEPAARI",Cash_Book!$D:$D,"GAWALI",Cash_Book!$E:$E,B8) | N8: =SUMIFS(Cash_Book!$G:$G,Cash_Book!$C:$C,"BEPAARI",Cash_Book!$D:$D,"CASH_ADV",Cash_Book!$E:$E,B8) | O8: =SUMIFS(Cash_Book!$G:$G,Cash_Book!$C:$C,"BEPAARI",Cash_Book!$D:$D,"OTHER",Cash_Book!$E:$E,B8) | P8: =SUM(H8:O8) | Q8: =IF(B8="","",F8-P8+E8) | R8: =SUMIFS(Cash_Book!$G:$G,Cash_Book!$C:$C,"BEPAARI",Cash_Book!$D:$D,"PAYMENT",Cash_Book!$E:$E,B8) | S8: =SUMIFS(JV_Entries!$G:$G,JV_Entries!$C:$C,"BEPAARI",JV_Entries!$D:$D,B8)-SUMIFS(JV_Entries!$G:$G,JV_Entries!$E:$E,"BEPAARI",JV_Entries!$F:$F,B8) | T8: =IF(B8="","",Q8-R8+S8)
A9: 5 | B9: =IF(Masters!$B$7="","",Masters!$B$7) | C9: =IF(B9="","",Masters!$C$7) | D9: =IF(B9="","",IF(Masters!$D$7="","",Masters!$D$7)) | E9: =IF(B9="",0,Masters!$E$7) | F9: =SUMIF(Daily_Sales!$C:$C,B9,Daily_Sales!$G:$G) | G9: =SUMIF(Daily_Sales!$C:$C,B9,Daily_Sales!$E:$E) | H9: =IF(B9="",0,IF(D9<>"",D9*G9,F9*C9/100)) | I9: =IF(G9>0,Masters!$Y$3,0) | J9: =G9*Masters!$Y$4 | K9: =SUMIFS(Cash_Book!$G:$G,Cash_Book!$C:$C,"BEPAARI",Cash_Book!$D:$D,"MOTOR",Cash_Book!$E:$E,B9) | L9: =SUMIFS(Cash_Book!$G:$G,Cash_Book!$C:$C,"BEPAARI",Cash_Book!$D:$D,"BHUSSA",Cash_Book!$E:$E,B9) | M9: =SUMIFS(Cash_Book!$G:$G,Cash_Book!$C:$C,"BEPAARI",Cash_Book!$D:$D,"GAWALI",Cash_Book!$E:$E,B9) | N9: =SUMIFS(Cash_Book!$G:$G,Cash_Book!$C:$C,"BEPAARI",Cash_Book!$D:$D,"CASH_ADV",Cash_Book!$E:$E,B9) | O9: =SUMIFS(Cash_Book!$G:$G,Cash_Book!$C:$C,"BEPAARI",Cash_Book!$D:$D,"OTHER",Cash_Book!$E:$E,B9) | P9: =SUM(H9:O9) | Q9: =IF(B9="","",F9-P9+E9) | R9: =SUMIFS(Cash_Book!$G:$G,Cash_Book!$C:$C,"BEPAARI",Cash_Book!$D:$D,"PAYMENT",Cash_Book!$E:$E,B9) | S9: =SUMIFS(JV_Entries!$G:$G,JV_Entries!$C:$C,"BEPAARI",JV_Entries!$D:$D,B9)-SUMIFS(JV_Entries!$G:$G,JV_Entries!$E:$E,"BEPAARI",JV_Entries!$F:$F,B9) | T9: =IF(B9="","",Q9-R9+S9)
A10: 6 | B10: =IF(Masters!$B$8="","",Masters!$B$8) | C10: =IF(B10="","",Masters!$C$8) | D10: =IF(B10="","",IF(Masters!$D$8="","",Masters!$D$8)) | E10: =IF(B10="",0,Masters!$E$8) | F10: =SUMIF(Daily_Sales!$C:$C,B10,Daily_Sales!$G:$G) | G10: =SUMIF(Daily_Sales!$C:$C,B10,Daily_Sales!$E:$E) | H10: =IF(B10="",0,IF(D10<>"",D10*G10,F10*C10/100)) | I10: =IF(G10>0,Masters!$Y$3,0) | J10: =G10*Masters!$Y$4 | K10: =SUMIFS(Cash_Book!$G:$G,Cash_Book!$C:$C,"BEPAARI",Cash_Book!$D:$D,"MOTOR",Cash_Book!$E:$E,B10) | L10: =SUMIFS(Cash_Book!$G:$G,Cash_Book!$C:$C,"BEPAARI",Cash_Book!$D:$D,"BHUSSA",Cash_Book!$E:$E,B10) | M10: =SUMIFS(Cash_Book!$G:$G,Cash_Book!$C:$C,"BEPAARI",Cash_Book!$D:$D,"GAWALI",Cash_Book!$E:$E,B10) | N10: =SUMIFS(Cash_Book!$G:$G,Cash_Book!$C:$C,"BEPAARI",Cash_Book!$D:$D,"CASH_ADV",Cash_Book!$E:$E,B10) | O10: =SUMIFS(Cash_Book!$G:$G,Cash_Book!$C:$C,"BEPAARI",Cash_Book!$D:$D,"OTHER",Cash_Book!$E:$E,B10) | P10: =SUM(H10:O10) | Q10: =IF(B10="","",F10-P10+E10) | R10: =SUMIFS(Cash_Book!$G:$G,Cash_Book!$C:$C,"BEPAARI",Cash_Book!$D:$D,"PAYMENT",Cash_Book!$E:$E,B10) | S10: =SUMIFS(JV_Entries!$G:$G,JV_Entries!$C:$C,"BEPAARI",JV_Entries!$D:$D,B10)-SUMIFS(JV_Entries!$G:$G,JV_Entries!$E:$E,"BEPAARI",JV_Entries!$F:$F,B10) | T10: =IF(B10="","",Q10-R10+S10)
A11: 7 | B11: =IF(Masters!$B$9="","",Masters!$B$9) | C11: =IF(B11="","",Masters!$C$9) | D11: =IF(B11="","",IF(Masters!$D$9="","",Masters!$D$9)) | E11: =IF(B11="",0,Masters!$E$9) | F11: =SUMIF(Daily_Sales!$C:$C,B11,Daily_Sales!$G:$G) | G11: =SUMIF(Daily_Sales!$C:$C,B11,Daily_Sales!$E:$E) | H11: =IF(B11="",0,IF(D11<>"",D11*G11,F11*C11/100)) | I11: =IF(G11>0,Masters!$Y$3,0) | J11: =G11*Masters!$Y$4 | K11: =SUMIFS(Cash_Book!$G:$G,Cash_Book!$C:$C,"BEPAARI",Cash_Book!$D:$D,"MOTOR",Cash_Book!$E:$E,B11) | L11: =SUMIFS(Cash_Book!$G:$G,Cash_Book!$C:$C,"BEPAARI",Cash_Book!$D:$D,"BHUSSA",Cash_Book!$E:$E,B11) | M11: =SUMIFS(Cash_Book!$G:$G,Cash_Book!$C:$C,"BEPAARI",Cash_Book!$D:$D,"GAWALI",Cash_Book!$E:$E,B11) | N11: =SUMIFS(Cash_Book!$G:$G,Cash_Book!$C:$C,"BEPAARI",Cash_Book!$D:$D,"CASH_ADV",Cash_Book!$E:$E,B11) | O11: =SUMIFS(Cash_Book!$G:$G,Cash_Book!$C:$C,"BEPAARI",Cash_Book!$D:$D,"OTHER",Cash_Book!$E:$E,B11) | P11: =SUM(H11:O11) | Q11: =IF(B11="","",F11-P11+E11) | R11: =SUMIFS(Cash_Book!$G:$G,Cash_Book!$C:$C,"BEPAARI",Cash_Book!$D:$D,"PAYMENT",Cash_Book!$E:$E,B11) | S11: =SUMIFS(JV_Entries!$G:$G,JV_Entries!$C:$C,"BEPAARI",JV_Entries!$D:$D,B11)-SUMIFS(JV_Entries!$G:$G,JV_Entries!$E:$E,"BEPAARI",JV_Entries!$F:$F,B11) | T11: =IF(B11="","",Q11-R11+S11)
A12: 8 | B12: =IF(Masters!$B$10="","",Masters!$B$10) | C12: =IF(B12="","",Masters!$C$10) | D12: =IF(B12="","",IF(Masters!$D$10="","",Masters!$D$10)) | E12: =IF(B12="",0,Masters!$E$10) | F12: =SUMIF(Daily_Sales!$C:$C,B12,Daily_Sales!$G:$G) | G12: =SUMIF(Daily_Sales!$C:$C,B12,Daily_Sales!$E:$E) | H12: =IF(B12="",0,IF(D12<>"",D12*G12,F12*C12/100)) | I12: =IF(G12>0,Masters!$Y$3,0) | J12: =G12*Masters!$Y$4 | K12: =SUMIFS(Cash_Book!$G:$G,Cash_Book!$C:$C,"BEPAARI",Cash_Book!$D:$D,"MOTOR",Cash_Book!$E:$E,B12) | L12: =SUMIFS(Cash_Book!$G:$G,Cash_Book!$C:$C,"BEPAARI",Cash_Book!$D:$D,"BHUSSA",Cash_Book!$E:$E,B12) | M12: =SUMIFS(Cash_Book!$G:$G,Cash_Book!$C:$C,"BEPAARI",Cash_Book!$D:$D,"GAWALI",Cash_Book!$E:$E,B12) | N12: =SUMIFS(Cash_Book!$G:$G,Cash_Book!$C:$C,"BEPAARI",Cash_Book!$D:$D,"CASH_ADV",Cash_Book!$E:$E,B12) | O12: =SUMIFS(Cash_Book!$G:$G,Cash_Book!$C:$C,"BEPAARI",Cash_Book!$D:$D,"OTHER",Cash_Book!$E:$E,B12) | P12: =SUM(H12:O12) | Q12: =IF(B12="","",F12-P12+E12) | R12: =SUMIFS(Cash_Book!$G:$G,Cash_Book!$C:$C,"BEPAARI",Cash_Book!$D:$D,"PAYMENT",Cash_Book!$E:$E,B12) | S12: =SUMIFS(JV_Entries!$G:$G,JV_Entries!$C:$C,"BEPAARI",JV_Entries!$D:$D,B12)-SUMIFS(JV_Entries!$G:$G,JV_Entries!$E:$E,"BEPAARI",JV_Entries!$F:$F,B12) | T12: =IF(B12="","",Q12-R12+S12)
A13: 9 | B13: =IF(Masters!$B$11="","",Masters!$B$11) | C13: =IF(B13="","",Masters!$C$11) | D13: =IF(B13="","",IF(Masters!$D$11="","",Masters!$D$11)) | E13: =IF(B13="",0,Masters!$E$11) | F13: =SUMIF(Daily_Sales!$C:$C,B13,Daily_Sales!$G:$G) | G13: =SUMIF(Daily_Sales!$C:$C,B13,Daily_Sales!$E:$E) | H13: =IF(B13="",0,IF(D13<>"",D13*G13,F13*C13/100)) | I13: =IF(G13>0,Masters!$Y$3,0) | J13: =G13*Masters!$Y$4 | K13: =SUMIFS(Cash_Book!$G:$G,Cash_Book!$C:$C,"BEPAARI",Cash_Book!$D:$D,"MOTOR",Cash_Book!$E:$E,B13) | L13: =SUMIFS(Cash_Book!$G:$G,Cash_Book!$C:$C,"BEPAARI",Cash_Book!$D:$D,"BHUSSA",Cash_Book!$E:$E,B13) | M13: =SUMIFS(Cash_Book!$G:$G,Cash_Book!$C:$C,"BEPAARI",Cash_Book!$D:$D,"GAWALI",Cash_Book!$E:$E,B13) | N13: =SUMIFS(Cash_Book!$G:$G,Cash_Book!$C:$C,"BEPAARI",Cash_Book!$D:$D,"CASH_ADV",Cash_Book!$E:$E,B13) | O13: =SUMIFS(Cash_Book!$G:$G,Cash_Book!$C:$C,"BEPAARI",Cash_Book!$D:$D,"OTHER",Cash_Book!$E:$E,B13) | P13: =SUM(H13:O13) | Q13: =IF(B13="","",F13-P13+E13) | R13: =SUMIFS(Cash_Book!$G:$G,Cash_Book!$C:$C,"BEPAARI",Cash_Book!$D:$D,"PAYMENT",Cash_Book!$E:$E,B13) | S13: =SUMIFS(JV_Entries!$G:$G,JV_Entries!$C:$C,"BEPAARI",JV_Entries!$D:$D,B13)-SUMIFS(JV_Entries!$G:$G,JV_Entries!$E:$E,"BEPAARI",JV_Entries!$F:$F,B13) | T13: =IF(B13="","",Q13-R13+S13)
A14: 10 | B14: =IF(Masters!$B$12="","",Masters!$B$12) | C14: =IF(B14="","",Masters!$C$12) | D14: =IF(B14="","",IF(Masters!$D$12="","",Masters!$D$12)) | E14: =IF(B14="",0,Masters!$E$12) | F14: =SUMIF(Daily_Sales!$C:$C,B14,Daily_Sales!$G:$G) | G14: =SUMIF(Daily_Sales!$C:$C,B14,Daily_Sales!$E:$E) | H14: =IF(B14="",0,IF(D14<>"",D14*G14,F14*C14/100)) | I14: =IF(G14>0,Masters!$Y$3,0) | J14: =G14*Masters!$Y$4 | K14: =SUMIFS(Cash_Book!$G:$G,Cash_Book!$C:$C,"BEPAARI",Cash_Book!$D:$D,"MOTOR",Cash_Book!$E:$E,B14) | L14: =SUMIFS(Cash_Book!$G:$G,Cash_Book!$C:$C,"BEPAARI",Cash_Book!$D:$D,"BHUSSA",Cash_Book!$E:$E,B14) | M14: =SUMIFS(Cash_Book!$G:$G,Cash_Book!$C:$C,"BEPAARI",Cash_Book!$D:$D,"GAWALI",Cash_Book!$E:$E,B14) | N14: =SUMIFS(Cash_Book!$G:$G,Cash_Book!$C:$C,"BEPAARI",Cash_Book!$D:$D,"CASH_ADV",Cash_Book!$E:$E,B14) | O14: =SUMIFS(Cash_Book!$G:$G,Cash_Book!$C:$C,"BEPAARI",Cash_Book!$D:$D,"OTHER",Cash_Book!$E:$E,B14) | P14: =SUM(H14:O14) | Q14: =IF(B14="","",F14-P14+E14) | R14: =SUMIFS(Cash_Book!$G:$G,Cash_Book!$C:$C,"BEPAARI",Cash_Book!$D:$D,"PAYMENT",Cash_Book!$E:$E,B14) | S14: =SUMIFS(JV_Entries!$G:$G,JV_Entries!$C:$C,"BEPAARI",JV_Entries!$D:$D,B14)-SUMIFS(JV_Entries!$G:$G,JV_Entries!$E:$E,"BEPAARI",JV_Entries!$F:$F,B14) | T14: =IF(B14="","",Q14-R14+S14)
A15: 11 | B15: =IF(Masters!$B$13="","",Masters!$B$13) | C15: =IF(B15="","",Masters!$C$13) | D15: =IF(B15="","",IF(Masters!$D$13="","",Masters!$D$13)) | E15: =IF(B15="",0,Masters!$E$13) | F15: =SUMIF(Daily_Sales!$C:$C,B15,Daily_Sales!$G:$G) | G15: =SUMIF(Daily_Sales!$C:$C,B15,Daily_Sales!$E:$E) | H15: =IF(B15="",0,IF(D15<>"",D15*G15,F15*C15/100)) | I15: =IF(G15>0,Masters!$Y$3,0) | J15: =G15*Masters!$Y$4 | K15: =SUMIFS(Cash_Book!$G:$G,Cash_Book!$C:$C,"BEPAARI",Cash_Book!$D:$D,"MOTOR",Cash_Book!$E:$E,B15) | L15: =SUMIFS(Cash_Book!$G:$G,Cash_Book!$C:$C,"BEPAARI",Cash_Book!$D:$D,"BHUSSA",Cash_Book!$E:$E,B15) | M15: =SUMIFS(Cash_Book!$G:$G,Cash_Book!$C:$C,"BEPAARI",Cash_Book!$D:$D,"GAWALI",Cash_Book!$E:$E,B15) | N15: =SUMIFS(Cash_Book!$G:$G,Cash_Book!$C:$C,"BEPAARI",Cash_Book!$D:$D,"CASH_ADV",Cash_Book!$E:$E,B15) | O15: =SUMIFS(Cash_Book!$G:$G,Cash_Book!$C:$C,"BEPAARI",Cash_Book!$D:$D,"OTHER",Cash_Book!$E:$E,B15) | P15: =SUM(H15:O15) | Q15: =IF(B15="","",F15-P15+E15) | R15: =SUMIFS(Cash_Book!$G:$G,Cash_Book!$C:$C,"BEPAARI",Cash_Book!$D:$D,"PAYMENT",Cash_Book!$E:$E,B15) | S15: =SUMIFS(JV_Entries!$G:$G,JV_Entries!$C:$C,"BEPAARI",JV_Entries!$D:$D,B15)-SUMIFS(JV_Entries!$G:$G,JV_Entries!$E:$E,"BEPAARI",JV_Entries!$F:$F,B15) | T15: =IF(B15="","",Q15-R15+S15)
A16: 12 | B16: =IF(Masters!$B$14="","",Masters!$B$14) | C16: =IF(B16="","",Masters!$C$14) | D16: =IF(B16="","",IF(Masters!$D$14="","",Masters!$D$14)) | E16: =IF(B16="",0,Masters!$E$14) | F16: =SUMIF(Daily_Sales!$C:$C,B16,Daily_Sales!$G:$G) | G16: =SUMIF(Daily_Sales!$C:$C,B16,Daily_Sales!$E:$E) | H16: =IF(B16="",0,IF(D16<>"",D16*G16,F16*C16/100)) | I16: =IF(G16>0,Masters!$Y$3,0) | J16: =G16*Masters!$Y$4 | K16: =SUMIFS(Cash_Book!$G:$G,Cash_Book!$C:$C,"BEPAARI",Cash_Book!$D:$D,"MOTOR",Cash_Book!$E:$E,B16) | L16: =SUMIFS(Cash_Book!$G:$G,Cash_Book!$C:$C,"BEPAARI",Cash_Book!$D:$D,"BHUSSA",Cash_Book!$E:$E,B16) | M16: =SUMIFS(Cash_Book!$G:$G,Cash_Book!$C:$C,"BEPAARI",Cash_Book!$D:$D,"GAWALI",Cash_Book!$E:$E,B16) | N16: =SUMIFS(Cash_Book!$G:$G,Cash_Book!$C:$C,"BEPAARI",Cash_Book!$D:$D,"CASH_ADV",Cash_Book!$E:$E,B16) | O16: =SUMIFS(Cash_Book!$G:$G,Cash_Book!$C:$C,"BEPAARI",Cash_Book!$D:$D,"OTHER",Cash_Book!$E:$E,B16) | P16: =SUM(H16:O16) | Q16: =IF(B16="","",F16-P16+E16) | R16: =SUMIFS(Cash_Book!$G:$G,Cash_Book!$C:$C,"BEPAARI",Cash_Book!$D:$D,"PAYMENT",Cash_Book!$E:$E,B16) | S16: =SUMIFS(JV_Entries!$G:$G,JV_Entries!$C:$C,"BEPAARI",JV_Entries!$D:$D,B16)-SUMIFS(JV_Entries!$G:$G,JV_Entries!$E:$E,"BEPAARI",JV_Entries!$F:$F,B16) | T16: =IF(B16="","",Q16-R16+S16)
A17: 13 | B17: =IF(Masters!$B$15="","",Masters!$B$15) | C17: =IF(B17="","",Masters!$C$15) | D17: =IF(B17="","",IF(Masters!$D$15="","",Masters!$D$15)) | E17: =IF(B17="",0,Masters!$E$15) | F17: =SUMIF(Daily_Sales!$C:$C,B17,Daily_Sales!$G:$G) | G17: =SUMIF(Daily_Sales!$C:$C,B17,Daily_Sales!$E:$E) | H17: =IF(B17="",0,IF(D17<>"",D17*G17,F17*C17/100)) | I17: =IF(G17>0,Masters!$Y$3,0) | J17: =G17*Masters!$Y$4 | K17: =SUMIFS(Cash_Book!$G:$G,Cash_Book!$C:$C,"BEPAARI",Cash_Book!$D:$D,"MOTOR",Cash_Book!$E:$E,B17) | L17: =SUMIFS(Cash_Book!$G:$G,Cash_Book!$C:$C,"BEPAARI",Cash_Book!$D:$D,"BHUSSA",Cash_Book!$E:$E,B17) | M17: =SUMIFS(Cash_Book!$G:$G,Cash_Book!$C:$C,"BEPAARI",Cash_Book!$D:$D,"GAWALI",Cash_Book!$E:$E,B17) | N17: =SUMIFS(Cash_Book!$G:$G,Cash_Book!$C:$C,"BEPAARI",Cash_Book!$D:$D,"CASH_ADV",Cash_Book!$E:$E,B17) | O17: =SUMIFS(Cash_Book!$G:$G,Cash_Book!$C:$C,"BEPAARI",Cash_Book!$D:$D,"OTHER",Cash_Book!$E:$E,B17) | P17: =SUM(H17:O17) | Q17: =IF(B17="","",F17-P17+E17) | R17: =SUMIFS(Cash_Book!$G:$G,Cash_Book!$C:$C,"BEPAARI",Cash_Book!$D:$D,"PAYMENT",Cash_Book!$E:$E,B17) | S17: =SUMIFS(JV_Entries!$G:$G,JV_Entries!$C:$C,"BEPAARI",JV_Entries!$D:$D,B17)-SUMIFS(JV_Entries!$G:$G,JV_Entries!$E:$E,"BEPAARI",JV_Entries!$F:$F,B17) | T17: =IF(B17="","",Q17-R17+S17)
A18: 14 | B18: =IF(Masters!$B$16="","",Masters!$B$16) | C18: =IF(B18="","",Masters!$C$16) | D18: =IF(B18="","",IF(Masters!$D$16="","",Masters!$D$16)) | E18: =IF(B18="",0,Masters!$E$16) | F18: =SUMIF(Daily_Sales!$C:$C,B18,Daily_Sales!$G:$G) | G18: =SUMIF(Daily_Sales!$C:$C,B18,Daily_Sales!$E:$E) | H18: =IF(B18="",0,IF(D18<>"",D18*G18,F18*C18/100)) | I18: =IF(G18>0,Masters!$Y$3,0) | J18: =G18*Masters!$Y$4 | K18: =SUMIFS(Cash_Book!$G:$G,Cash_Book!$C:$C,"BEPAARI",Cash_Book!$D:$D,"MOTOR",Cash_Book!$E:$E,B18) | L18: =SUMIFS(Cash_Book!$G:$G,Cash_Book!$C:$C,"BEPAARI",Cash_Book!$D:$D,"BHUSSA",Cash_Book!$E:$E,B18) | M18: =SUMIFS(Cash_Book!$G:$G,Cash_Book!$C:$C,"BEPAARI",Cash_Book!$D:$D,"GAWALI",Cash_Book!$E:$E,B18) | N18: =SUMIFS(Cash_Book!$G:$G,Cash_Book!$C:$C,"BEPAARI",Cash_Book!$D:$D,"CASH_ADV",Cash_Book!$E:$E,B18) | O18: =SUMIFS(Cash_Book!$G:$G,Cash_Book!$C:$C,"BEPAARI",Cash_Book!$D:$D,"OTHER",Cash_Book!$E:$E,B18) | P18: =SUM(H18:O18) | Q18: =IF(B18="","",F18-P18+E18) | R18: =SUMIFS(Cash_Book!$G:$G,Cash_Book!$C:$C,"BEPAARI",Cash_Book!$D:$D,"PAYMENT",Cash_Book!$E:$E,B18) | S18: =SUMIFS(JV_Entries!$G:$G,JV_Entries!$C:$C,"BEPAARI",JV_Entries!$D:$D,B18)-SUMIFS(JV_Entries!$G:$G,JV_Entries!$E:$E,"BEPAARI",JV_Entries!$F:$F,B18) | T18: =IF(B18="","",Q18-R18+S18)
A19: 15 | B19: =IF(Masters!$B$17="","",Masters!$B$17) | C19: =IF(B19="","",Masters!$C$17) | D19: =IF(B19="","",IF(Masters!$D$17="","",Masters!$D$17)) | E19: =IF(B19="",0,Masters!$E$17) | F19: =SUMIF(Daily_Sales!$C:$C,B19,Daily_Sales!$G:$G) | G19: =SUMIF(Daily_Sales!$C:$C,B19,Daily_Sales!$E:$E) | H19: =IF(B19="",0,IF(D19<>"",D19*G19,F19*C19/100)) | I19: =IF(G19>0,Masters!$Y$3,0) | J19: =G19*Masters!$Y$4 | K19: =SUMIFS(Cash_Book!$G:$G,Cash_Book!$C:$C,"BEPAARI",Cash_Book!$D:$D,"MOTOR",Cash_Book!$E:$E,B19) | L19: =SUMIFS(Cash_Book!$G:$G,Cash_Book!$C:$C,"BEPAARI",Cash_Book!$D:$D,"BHUSSA",Cash_Book!$E:$E,B19) | M19: =SUMIFS(Cash_Book!$G:$G,Cash_Book!$C:$C,"BEPAARI",Cash_Book!$D:$D,"GAWALI",Cash_Book!$E:$E,B19) | N19: =SUMIFS(Cash_Book!$G:$G,Cash_Book!$C:$C,"BEPAARI",Cash_Book!$D:$D,"CASH_ADV",Cash_Book!$E:$E,B19) | O19: =SUMIFS(Cash_Book!$G:$G,Cash_Book!$C:$C,"BEPAARI",Cash_Book!$D:$D,"OTHER",Cash_Book!$E:$E,B19) | P19: =SUM(H19:O19) | Q19: =IF(B19="","",F19-P19+E19) | R19: =SUMIFS(Cash_Book!$G:$G,Cash_Book!$C:$C,"BEPAARI",Cash_Book!$D:$D,"PAYMENT",Cash_Book!$E:$E,B19) | S19: =SUMIFS(JV_Entries!$G:$G,JV_Entries!$C:$C,"BEPAARI",JV_Entries!$D:$D,B19)-SUMIFS(JV_Entries!$G:$G,JV_Entries!$E:$E,"BEPAARI",JV_Entries!$F:$F,B19) | T19: =IF(B19="","",Q19-R19+S19)
A20: 16 | B20: =IF(Masters!$B$18="","",Masters!$B$18) | C20: =IF(B20="","",Masters!$C$18) | D20: =IF(B20="","",IF(Masters!$D$18="","",Masters!$D$18)) | E20: =IF(B20="",0,Masters!$E$18) | F20: =SUMIF(Daily_Sales!$C:$C,B20,Daily_Sales!$G:$G) | G20: =SUMIF(Daily_Sales!$C:$C,B20,Daily_Sales!$E:$E) | H20: =IF(B20="",0,IF(D20<>"",D20*G20,F20*C20/100)) | I20: =IF(G20>0,Masters!$Y$3,0) | J20: =G20*Masters!$Y$4 | K20: =SUMIFS(Cash_Book!$G:$G,Cash_Book!$C:$C,"BEPAARI",Cash_Book!$D:$D,"MOTOR",Cash_Book!$E:$E,B20) | L20: =SUMIFS(Cash_Book!$G:$G,Cash_Book!$C:$C,"BEPAARI",Cash_Book!$D:$D,"BHUSSA",Cash_Book!$E:$E,B20) | M20: =SUMIFS(Cash_Book!$G:$G,Cash_Book!$C:$C,"BEPAARI",Cash_Book!$D:$D,"GAWALI",Cash_Book!$E:$E,B20) | N20: =SUMIFS(Cash_Book!$G:$G,Cash_Book!$C:$C,"BEPAARI",Cash_Book!$D:$D,"CASH_ADV",Cash_Book!$E:$E,B20) | O20: =SUMIFS(Cash_Book!$G:$G,Cash_Book!$C:$C,"BEPAARI",Cash_Book!$D:$D,"OTHER",Cash_Book!$E:$E,B20) | P20: =SUM(H20:O20) | Q20: =IF(B20="","",F20-P20+E20) | R20: =SUMIFS(Cash_Book!$G:$G,Cash_Book!$C:$C,"BEPAARI",Cash_Book!$D:$D,"PAYMENT",Cash_Book!$E:$E,B20) | S20: =SUMIFS(JV_Entries!$G:$G,JV_Entries!$C:$C,"BEPAARI",JV_Entries!$D:$D,B20)-SUMIFS(JV_Entries!$G:$G,JV_Entries!$E:$E,"BEPAARI",JV_Entries!$F:$F,B20) | T20: =IF(B20="","",Q20-R20+S20)
A21: 17 | B21: =IF(Masters!$B$19="","",Masters!$B$19) | C21: =IF(B21="","",Masters!$C$19) | D21: =IF(B21="","",IF(Masters!$D$19="","",Masters!$D$19)) | E21: =IF(B21="",0,Masters!$E$19) | F21: =SUMIF(Daily_Sales!$C:$C,B21,Daily_Sales!$G:$G) | G21: =SUMIF(Daily_Sales!$C:$C,B21,Daily_Sales!$E:$E) | H21: =IF(B21="",0,IF(D21<>"",D21*G21,F21*C21/100)) | I21: =IF(G21>0,Masters!$Y$3,0) | J21: =G21*Masters!$Y$4 | K21: =SUMIFS(Cash_Book!$G:$G,Cash_Book!$C:$C,"BEPAARI",Cash_Book!$D:$D,"MOTOR",Cash_Book!$E:$E,B21) | L21: =SUMIFS(Cash_Book!$G:$G,Cash_Book!$C:$C,"BEPAARI",Cash_Book!$D:$D,"BHUSSA",Cash_Book!$E:$E,B21) | M21: =SUMIFS(Cash_Book!$G:$G,Cash_Book!$C:$C,"BEPAARI",Cash_Book!$D:$D,"GAWALI",Cash_Book!$E:$E,B21) | N21: =SUMIFS(Cash_Book!$G:$G,Cash_Book!$C:$C,"BEPAARI",Cash_Book!$D:$D,"CASH_ADV",Cash_Book!$E:$E,B21) | O21: =SUMIFS(Cash_Book!$G:$G,Cash_Book!$C:$C,"BEPAARI",Cash_Book!$D:$D,"OTHER",Cash_Book!$E:$E,B21) | P21: =SUM(H21:O21) | Q21: =IF(B21="","",F21-P21+E21) | R21: =SUMIFS(Cash_Book!$G:$G,Cash_Book!$C:$C,"BEPAARI",Cash_Book!$D:$D,"PAYMENT",Cash_Book!$E:$E,B21) | S21: =SUMIFS(JV_Entries!$G:$G,JV_Entries!$C:$C,"BEPAARI",JV_Entries!$D:$D,B21)-SUMIFS(JV_Entries!$G:$G,JV_Entries!$E:$E,"BEPAARI",JV_Entries!$F:$F,B21) | T21: =IF(B21="","",Q21-R21+S21)
A22: 18 | B22: =IF(Masters!$B$20="","",Masters!$B$20) | C22: =IF(B22="","",Masters!$C$20) | D22: =IF(B22="","",IF(Masters!$D$20="","",Masters!$D$20)) | E22: =IF(B22="",0,Masters!$E$20) | F22: =SUMIF(Daily_Sales!$C:$C,B22,Daily_Sales!$G:$G) | G22: =SUMIF(Daily_Sales!$C:$C,B22,Daily_Sales!$E:$E) | H22: =IF(B22="",0,IF(D22<>"",D22*G22,F22*C22/100)) | I22: =IF(G22>0,Masters!$Y$3,0) | J22: =G22*Masters!$Y$4 | K22: =SUMIFS(Cash_Book!$G:$G,Cash_Book!$C:$C,"BEPAARI",Cash_Book!$D:$D,"MOTOR",Cash_Book!$E:$E,B22) | L22: =SUMIFS(Cash_Book!$G:$G,Cash_Book!$C:$C,"BEPAARI",Cash_Book!$D:$D,"BHUSSA",Cash_Book!$E:$E,B22) | M22: =SUMIFS(Cash_Book!$G:$G,Cash_Book!$C:$C,"BEPAARI",Cash_Book!$D:$D,"GAWALI",Cash_Book!$E:$E,B22) | N22: =SUMIFS(Cash_Book!$G:$G,Cash_Book!$C:$C,"BEPAARI",Cash_Book!$D:$D,"CASH_ADV",Cash_Book!$E:$E,B22) | O22: =SUMIFS(Cash_Book!$G:$G,Cash_Book!$C:$C,"BEPAARI",Cash_Book!$D:$D,"OTHER",Cash_Book!$E:$E,B22) | P22: =SUM(H22:O22) | Q22: =IF(B22="","",F22-P22+E22) | R22: =SUMIFS(Cash_Book!$G:$G,Cash_Book!$C:$C,"BEPAARI",Cash_Book!$D:$D,"PAYMENT",Cash_Book!$E:$E,B22) | S22: =SUMIFS(JV_Entries!$G:$G,JV_Entries!$C:$C,"BEPAARI",JV_Entries!$D:$D,B22)-SUMIFS(JV_Entries!$G:$G,JV_Entries!$E:$E,"BEPAARI",JV_Entries!$F:$F,B22) | T22: =IF(B22="","",Q22-R22+S22)
A23: 19 | B23: =IF(Masters!$B$21="","",Masters!$B$21) | C23: =IF(B23="","",Masters!$C$21) | D23: =IF(B23="","",IF(Masters!$D$21="","",Masters!$D$21)) | E23: =IF(B23="",0,Masters!$E$21) | F23: =SUMIF(Daily_Sales!$C:$C,B23,Daily_Sales!$G:$G) | G23: =SUMIF(Daily_Sales!$C:$C,B23,Daily_Sales!$E:$E) | H23: =IF(B23="",0,IF(D23<>"",D23*G23,F23*C23/100)) | I23: =IF(G23>0,Masters!$Y$3,0) | J23: =G23*Masters!$Y$4 | K23: =SUMIFS(Cash_Book!$G:$G,Cash_Book!$C:$C,"BEPAARI",Cash_Book!$D:$D,"MOTOR",Cash_Book!$E:$E,B23) | L23: =SUMIFS(Cash_Book!$G:$G,Cash_Book!$C:$C,"BEPAARI",Cash_Book!$D:$D,"BHUSSA",Cash_Book!$E:$E,B23) | M23: =SUMIFS(Cash_Book!$G:$G,Cash_Book!$C:$C,"BEPAARI",Cash_Book!$D:$D,"GAWALI",Cash_Book!$E:$E,B23) | N23: =SUMIFS(Cash_Book!$G:$G,Cash_Book!$C:$C,"BEPAARI",Cash_Book!$D:$D,"CASH_ADV",Cash_Book!$E:$E,B23) | O23: =SUMIFS(Cash_Book!$G:$G,Cash_Book!$C:$C,"BEPAARI",Cash_Book!$D:$D,"OTHER",Cash_Book!$E:$E,B23) | P23: =SUM(H23:O23) | Q23: =IF(B23="","",F23-P23+E23) | R23: =SUMIFS(Cash_Book!$G:$G,Cash_Book!$C:$C,"BEPAARI",Cash_Book!$D:$D,"PAYMENT",Cash_Book!$E:$E,B23) | S23: =SUMIFS(JV_Entries!$G:$G,JV_Entries!$C:$C,"BEPAARI",JV_Entries!$D:$D,B23)-SUMIFS(JV_Entries!$G:$G,JV_Entries!$E:$E,"BEPAARI",JV_Entries!$F:$F,B23) | T23: =IF(B23="","",Q23-R23+S23)
A24: 20 | B24: =IF(Masters!$B$22="","",Masters!$B$22) | C24: =IF(B24="","",Masters!$C$22) | D24: =IF(B24="","",IF(Masters!$D$22="","",Masters!$D$22)) | E24: =IF(B24="",0,Masters!$E$22) | F24: =SUMIF(Daily_Sales!$C:$C,B24,Daily_Sales!$G:$G) | G24: =SUMIF(Daily_Sales!$C:$C,B24,Daily_Sales!$E:$E) | H24: =IF(B24="",0,IF(D24<>"",D24*G24,F24*C24/100)) | I24: =IF(G24>0,Masters!$Y$3,0) | J24: =G24*Masters!$Y$4 | K24: =SUMIFS(Cash_Book!$G:$G,Cash_Book!$C:$C,"BEPAARI",Cash_Book!$D:$D,"MOTOR",Cash_Book!$E:$E,B24) | L24: =SUMIFS(Cash_Book!$G:$G,Cash_Book!$C:$C,"BEPAARI",Cash_Book!$D:$D,"BHUSSA",Cash_Book!$E:$E,B24) | M24: =SUMIFS(Cash_Book!$G:$G,Cash_Book!$C:$C,"BEPAARI",Cash_Book!$D:$D,"GAWALI",Cash_Book!$E:$E,B24) | N24: =SUMIFS(Cash_Book!$G:$G,Cash_Book!$C:$C,"BEPAARI",Cash_Book!$D:$D,"CASH_ADV",Cash_Book!$E:$E,B24) | O24: =SUMIFS(Cash_Book!$G:$G,Cash_Book!$C:$C,"BEPAARI",Cash_Book!$D:$D,"OTHER",Cash_Book!$E:$E,B24) | P24: =SUM(H24:O24) | Q24: =IF(B24="","",F24-P24+E24) | R24: =SUMIFS(Cash_Book!$G:$G,Cash_Book!$C:$C,"BEPAARI",Cash_Book!$D:$D,"PAYMENT",Cash_Book!$E:$E,B24) | S24: =SUMIFS(JV_Entries!$G:$G,JV_Entries!$C:$C,"BEPAARI",JV_Entries!$D:$D,B24)-SUMIFS(JV_Entries!$G:$G,JV_Entries!$E:$E,"BEPAARI",JV_Entries!$F:$F,B24) | T24: =IF(B24="","",Q24-R24+S24)
A25: 21 | B25: =IF(Masters!$B$23="","",Masters!$B$23) | C25: =IF(B25="","",Masters!$C$23) | D25: =IF(B25="","",IF(Masters!$D$23="","",Masters!$D$23)) | E25: =IF(B25="",0,Masters!$E$23) | F25: =SUMIF(Daily_Sales!$C:$C,B25,Daily_Sales!$G:$G) | G25: =SUMIF(Daily_Sales!$C:$C,B25,Daily_Sales!$E:$E) | H25: =IF(B25="",0,IF(D25<>"",D25*G25,F25*C25/100)) | I25: =IF(G25>0,Masters!$Y$3,0) | J25: =G25*Masters!$Y$4 | K25: =SUMIFS(Cash_Book!$G:$G,Cash_Book!$C:$C,"BEPAARI",Cash_Book!$D:$D,"MOTOR",Cash_Book!$E:$E,B25) | L25: =SUMIFS(Cash_Book!$G:$G,Cash_Book!$C:$C,"BEPAARI",Cash_Book!$D:$D,"BHUSSA",Cash_Book!$E:$E,B25) | M25: =SUMIFS(Cash_Book!$G:$G,Cash_Book!$C:$C,"BEPAARI",Cash_Book!$D:$D,"GAWALI",Cash_Book!$E:$E,B25) | N25: =SUMIFS(Cash_Book!$G:$G,Cash_Book!$C:$C,"BEPAARI",Cash_Book!$D:$D,"CASH_ADV",Cash_Book!$E:$E,B25) | O25: =SUMIFS(Cash_Book!$G:$G,Cash_Book!$C:$C,"BEPAARI",Cash_Book!$D:$D,"OTHER",Cash_Book!$E:$E,B25) | P25: =SUM(H25:O25) | Q25: =IF(B25="","",F25-P25+E25) | R25: =SUMIFS(Cash_Book!$G:$G,Cash_Book!$C:$C,"BEPAARI",Cash_Book!$D:$D,"PAYMENT",Cash_Book!$E:$E,B25) | S25: =SUMIFS(JV_Entries!$G:$G,JV_Entries!$C:$C,"BEPAARI",JV_Entries!$D:$D,B25)-SUMIFS(JV_Entries!$G:$G,JV_Entries!$E:$E,"BEPAARI",JV_Entries!$F:$F,B25) | T25: =IF(B25="","",Q25-R25+S25)
A26: 22 | B26: =IF(Masters!$B$24="","",Masters!$B$24) | C26: =IF(B26="","",Masters!$C$24) | D26: =IF(B26="","",IF(Masters!$D$24="","",Masters!$D$24)) | E26: =IF(B26="",0,Masters!$E$24) | F26: =SUMIF(Daily_Sales!$C:$C,B26,Daily_Sales!$G:$G) | G26: =SUMIF(Daily_Sales!$C:$C,B26,Daily_Sales!$E:$E) | H26: =IF(B26="",0,IF(D26<>"",D26*G26,F26*C26/100)) | I26: =IF(G26>0,Masters!$Y$3,0) | J26: =G26*Masters!$Y$4 | K26: =SUMIFS(Cash_Book!$G:$G,Cash_Book!$C:$C,"BEPAARI",Cash_Book!$D:$D,"MOTOR",Cash_Book!$E:$E,B26) | L26: =SUMIFS(Cash_Book!$G:$G,Cash_Book!$C:$C,"BEPAARI",Cash_Book!$D:$D,"BHUSSA",Cash_Book!$E:$E,B26) | M26: =SUMIFS(Cash_Book!$G:$G,Cash_Book!$C:$C,"BEPAARI",Cash_Book!$D:$D,"GAWALI",Cash_Book!$E:$E,B26) | N26: =SUMIFS(Cash_Book!$G:$G,Cash_Book!$C:$C,"BEPAARI",Cash_Book!$D:$D,"CASH_ADV",Cash_Book!$E:$E,B26) | O26: =SUMIFS(Cash_Book!$G:$G,Cash_Book!$C:$C,"BEPAARI",Cash_Book!$D:$D,"OTHER",Cash_Book!$E:$E,B26) | P26: =SUM(H26:O26) | Q26: =IF(B26="","",F26-P26+E26) | R26: =SUMIFS(Cash_Book!$G:$G,Cash_Book!$C:$C,"BEPAARI",Cash_Book!$D:$D,"PAYMENT",Cash_Book!$E:$E,B26) | S26: =SUMIFS(JV_Entries!$G:$G,JV_Entries!$C:$C,"BEPAARI",JV_Entries!$D:$D,B26)-SUMIFS(JV_Entries!$G:$G,JV_Entries!$E:$E,"BEPAARI",JV_Entries!$F:$F,B26) | T26: =IF(B26="","",Q26-R26+S26)
A27: 23 | B27: =IF(Masters!$B$25="","",Masters!$B$25) | C27: =IF(B27="","",Masters!$C$25) | D27: =IF(B27="","",IF(Masters!$D$25="","",Masters!$D$25)) | E27: =IF(B27="",0,Masters!$E$25) | F27: =SUMIF(Daily_Sales!$C:$C,B27,Daily_Sales!$G:$G) | G27: =SUMIF(Daily_Sales!$C:$C,B27,Daily_Sales!$E:$E) | H27: =IF(B27="",0,IF(D27<>"",D27*G27,F27*C27/100)) | I27: =IF(G27>0,Masters!$Y$3,0) | J27: =G27*Masters!$Y$4 | K27: =SUMIFS(Cash_Book!$G:$G,Cash_Book!$C:$C,"BEPAARI",Cash_Book!$D:$D,"MOTOR",Cash_Book!$E:$E,B27) | L27: =SUMIFS(Cash_Book!$G:$G,Cash_Book!$C:$C,"BEPAARI",Cash_Book!$D:$D,"BHUSSA",Cash_Book!$E:$E,B27) | M27: =SUMIFS(Cash_Book!$G:$G,Cash_Book!$C:$C,"BEPAARI",Cash_Book!$D:$D,"GAWALI",Cash_Book!$E:$E,B27) | N27: =SUMIFS(Cash_Book!$G:$G,Cash_Book!$C:$C,"BEPAARI",Cash_Book!$D:$D,"CASH_ADV",Cash_Book!$E:$E,B27) | O27: =SUMIFS(Cash_Book!$G:$G,Cash_Book!$C:$C,"BEPAARI",Cash_Book!$D:$D,"OTHER",Cash_Book!$E:$E,B27) | P27: =SUM(H27:O27) | Q27: =IF(B27="","",F27-P27+E27) | R27: =SUMIFS(Cash_Book!$G:$G,Cash_Book!$C:$C,"BEPAARI",Cash_Book!$D:$D,"PAYMENT",Cash_Book!$E:$E,B27) | S27: =SUMIFS(JV_Entries!$G:$G,JV_Entries!$C:$C,"BEPAARI",JV_Entries!$D:$D,B27)-SUMIFS(JV_Entries!$G:$G,JV_Entries!$E:$E,"BEPAARI",JV_Entries!$F:$F,B27) | T27: =IF(B27="","",Q27-R27+S27)
A28: 24 | B28: =IF(Masters!$B$26="","",Masters!$B$26) | C28: =IF(B28="","",Masters!$C$26) | D28: =IF(B28="","",IF(Masters!$D$26="","",Masters!$D$26)) | E28: =IF(B28="",0,Masters!$E$26) | F28: =SUMIF(Daily_Sales!$C:$C,B28,Daily_Sales!$G:$G) | G28: =SUMIF(Daily_Sales!$C:$C,B28,Daily_Sales!$E:$E) | H28: =IF(B28="",0,IF(D28<>"",D28*G28,F28*C28/100)) | I28: =IF(G28>0,Masters!$Y$3,0) | J28: =G28*Masters!$Y$4 | K28: =SUMIFS(Cash_Book!$G:$G,Cash_Book!$C:$C,"BEPAARI",Cash_Book!$D:$D,"MOTOR",Cash_Book!$E:$E,B28) | L28: =SUMIFS(Cash_Book!$G:$G,Cash_Book!$C:$C,"BEPAARI",Cash_Book!$D:$D,"BHUSSA",Cash_Book!$E:$E,B28) | M28: =SUMIFS(Cash_Book!$G:$G,Cash_Book!$C:$C,"BEPAARI",Cash_Book!$D:$D,"GAWALI",Cash_Book!$E:$E,B28) | N28: =SUMIFS(Cash_Book!$G:$G,Cash_Book!$C:$C,"BEPAARI",Cash_Book!$D:$D,"CASH_ADV",Cash_Book!$E:$E,B28) | O28: =SUMIFS(Cash_Book!$G:$G,Cash_Book!$C:$C,"BEPAARI",Cash_Book!$D:$D,"OTHER",Cash_Book!$E:$E,B28) | P28: =SUM(H28:O28) | Q28: =IF(B28="","",F28-P28+E28) | R28: =SUMIFS(Cash_Book!$G:$G,Cash_Book!$C:$C,"BEPAARI",Cash_Book!$D:$D,"PAYMENT",Cash_Book!$E:$E,B28) | S28: =SUMIFS(JV_Entries!$G:$G,JV_Entries!$C:$C,"BEPAARI",JV_Entries!$D:$D,B28)-SUMIFS(JV_Entries!$G:$G,JV_Entries!$E:$E,"BEPAARI",JV_Entries!$F:$F,B28) | T28: =IF(B28="","",Q28-R28+S28)
A29: 25 | B29: =IF(Masters!$B$27="","",Masters!$B$27) | C29: =IF(B29="","",Masters!$C$27) | D29: =IF(B29="","",IF(Masters!$D$27="","",Masters!$D$27)) | E29: =IF(B29="",0,Masters!$E$27) | F29: =SUMIF(Daily_Sales!$C:$C,B29,Daily_Sales!$G:$G) | G29: =SUMIF(Daily_Sales!$C:$C,B29,Daily_Sales!$E:$E) | H29: =IF(B29="",0,IF(D29<>"",D29*G29,F29*C29/100)) | I29: =IF(G29>0,Masters!$Y$3,0) | J29: =G29*Masters!$Y$4 | K29: =SUMIFS(Cash_Book!$G:$G,Cash_Book!$C:$C,"BEPAARI",Cash_Book!$D:$D,"MOTOR",Cash_Book!$E:$E,B29) | L29: =SUMIFS(Cash_Book!$G:$G,Cash_Book!$C:$C,"BEPAARI",Cash_Book!$D:$D,"BHUSSA",Cash_Book!$E:$E,B29) | M29: =SUMIFS(Cash_Book!$G:$G,Cash_Book!$C:$C,"BEPAARI",Cash_Book!$D:$D,"GAWALI",Cash_Book!$E:$E,B29) | N29: =SUMIFS(Cash_Book!$G:$G,Cash_Book!$C:$C,"BEPAARI",Cash_Book!$D:$D,"CASH_ADV",Cash_Book!$E:$E,B29) | O29: =SUMIFS(Cash_Book!$G:$G,Cash_Book!$C:$C,"BEPAARI",Cash_Book!$D:$D,"OTHER",Cash_Book!$E:$E,B29) | P29: =SUM(H29:O29) | Q29: =IF(B29="","",F29-P29+E29) | R29: =SUMIFS(Cash_Book!$G:$G,Cash_Book!$C:$C,"BEPAARI",Cash_Book!$D:$D,"PAYMENT",Cash_Book!$E:$E,B29) | S29: =SUMIFS(JV_Entries!$G:$G,JV_Entries!$C:$C,"BEPAARI",JV_Entries!$D:$D,B29)-SUMIFS(JV_Entries!$G:$G,JV_Entries!$E:$E,"BEPAARI",JV_Entries!$F:$F,B29) | T29: =IF(B29="","",Q29-R29+S29)
A30: 26 | B30: =IF(Masters!$B$28="","",Masters!$B$28) | C30: =IF(B30="","",Masters!$C$28) | D30: =IF(B30="","",IF(Masters!$D$28="","",Masters!$D$28)) | E30: =IF(B30="",0,Masters!$E$28) | F30: =SUMIF(Daily_Sales!$C:$C,B30,Daily_Sales!$G:$G) | G30: =SUMIF(Daily_Sales!$C:$C,B30,Daily_Sales!$E:$E) | H30: =IF(B30="",0,IF(D30<>"",D30*G30,F30*C30/100)) | I30: =IF(G30>0,Masters!$Y$3,0) | J30: =G30*Masters!$Y$4 | K30: =SUMIFS(Cash_Book!$G:$G,Cash_Book!$C:$C,"BEPAARI",Cash_Book!$D:$D,"MOTOR",Cash_Book!$E:$E,B30) | L30: =SUMIFS(Cash_Book!$G:$G,Cash_Book!$C:$C,"BEPAARI",Cash_Book!$D:$D,"BHUSSA",Cash_Book!$E:$E,B30) | M30: =SUMIFS(Cash_Book!$G:$G,Cash_Book!$C:$C,"BEPAARI",Cash_Book!$D:$D,"GAWALI",Cash_Book!$E:$E,B30) | N30: =SUMIFS(Cash_Book!$G:$G,Cash_Book!$C:$C,"BEPAARI",Cash_Book!$D:$D,"CASH_ADV",Cash_Book!$E:$E,B30) | O30: =SUMIFS(Cash_Book!$G:$G,Cash_Book!$C:$C,"BEPAARI",Cash_Book!$D:$D,"OTHER",Cash_Book!$E:$E,B30) | P30: =SUM(H30:O30) | Q30: =IF(B30="","",F30-P30+E30) | R30: =SUMIFS(Cash_Book!$G:$G,Cash_Book!$C:$C,"BEPAARI",Cash_Book!$D:$D,"PAYMENT",Cash_Book!$E:$E,B30) | S30: =SUMIFS(JV_Entries!$G:$G,JV_Entries!$C:$C,"BEPAARI",JV_Entries!$D:$D,B30)-SUMIFS(JV_Entries!$G:$G,JV_Entries!$E:$E,"BEPAARI",JV_Entries!$F:$F,B30) | T30: =IF(B30="","",Q30-R30+S30)
A31: 27 | B31: =IF(Masters!$B$29="","",Masters!$B$29) | C31: =IF(B31="","",Masters!$C$29) | D31: =IF(B31="","",IF(Masters!$D$29="","",Masters!$D$29)) | E31: =IF(B31="",0,Masters!$E$29) | F31: =SUMIF(Daily_Sales!$C:$C,B31,Daily_Sales!$G:$G) | G31: =SUMIF(Daily_Sales!$C:$C,B31,Daily_Sales!$E:$E) | H31: =IF(B31="",0,IF(D31<>"",D31*G31,F31*C31/100)) | I31: =IF(G31>0,Masters!$Y$3,0) | J31: =G31*Masters!$Y$4 | K31: =SUMIFS(Cash_Book!$G:$G,Cash_Book!$C:$C,"BEPAARI",Cash_Book!$D:$D,"MOTOR",Cash_Book!$E:$E,B31) | L31: =SUMIFS(Cash_Book!$G:$G,Cash_Book!$C:$C,"BEPAARI",Cash_Book!$D:$D,"BHUSSA",Cash_Book!$E:$E,B31) | M31: =SUMIFS(Cash_Book!$G:$G,Cash_Book!$C:$C,"BEPAARI",Cash_Book!$D:$D,"GAWALI",Cash_Book!$E:$E,B31) | N31: =SUMIFS(Cash_Book!$G:$G,Cash_Book!$C:$C,"BEPAARI",Cash_Book!$D:$D,"CASH_ADV",Cash_Book!$E:$E,B31) | O31: =SUMIFS(Cash_Book!$G:$G,Cash_Book!$C:$C,"BEPAARI",Cash_Book!$D:$D,"OTHER",Cash_Book!$E:$E,B31) | P31: =SUM(H31:O31) | Q31: =IF(B31="","",F31-P31+E31) | R31: =SUMIFS(Cash_Book!$G:$G,Cash_Book!$C:$C,"BEPAARI",Cash_Book!$D:$D,"PAYMENT",Cash_Book!$E:$E,B31) | S31: =SUMIFS(JV_Entries!$G:$G,JV_Entries!$C:$C,"BEPAARI",JV_Entries!$D:$D,B31)-SUMIFS(JV_Entries!$G:$G,JV_Entries!$E:$E,"BEPAARI",JV_Entries!$F:$F,B31) | T31: =IF(B31="","",Q31-R31+S31)
A32: 28 | B32: =IF(Masters!$B$30="","",Masters!$B$30) | C32: =IF(B32="","",Masters!$C$30) | D32: =IF(B32="","",IF(Masters!$D$30="","",Masters!$D$30)) | E32: =IF(B32="",0,Masters!$E$30) | F32: =SUMIF(Daily_Sales!$C:$C,B32,Daily_Sales!$G:$G) | G32: =SUMIF(Daily_Sales!$C:$C,B32,Daily_Sales!$E:$E) | H32: =IF(B32="",0,IF(D32<>"",D32*G32,F32*C32/100)) | I32: =IF(G32>0,Masters!$Y$3,0) | J32: =G32*Masters!$Y$4 | K32: =SUMIFS(Cash_Book!$G:$G,Cash_Book!$C:$C,"BEPAARI",Cash_Book!$D:$D,"MOTOR",Cash_Book!$E:$E,B32) | L32: =SUMIFS(Cash_Book!$G:$G,Cash_Book!$C:$C,"BEPAARI",Cash_Book!$D:$D,"BHUSSA",Cash_Book!$E:$E,B32) | M32: =SUMIFS(Cash_Book!$G:$G,Cash_Book!$C:$C,"BEPAARI",Cash_Book!$D:$D,"GAWALI",Cash_Book!$E:$E,B32) | N32: =SUMIFS(Cash_Book!$G:$G,Cash_Book!$C:$C,"BEPAARI",Cash_Book!$D:$D,"CASH_ADV",Cash_Book!$E:$E,B32) | O32: =SUMIFS(Cash_Book!$G:$G,Cash_Book!$C:$C,"BEPAARI",Cash_Book!$D:$D,"OTHER",Cash_Book!$E:$E,B32) | P32: =SUM(H32:O32) | Q32: =IF(B32="","",F32-P32+E32) | R32: =SUMIFS(Cash_Book!$G:$G,Cash_Book!$C:$C,"BEPAARI",Cash_Book!$D:$D,"PAYMENT",Cash_Book!$E:$E,B32) | S32: =SUMIFS(JV_Entries!$G:$G,JV_Entries!$C:$C,"BEPAARI",JV_Entries!$D:$D,B32)-SUMIFS(JV_Entries!$G:$G,JV_Entries!$E:$E,"BEPAARI",JV_Entries!$F:$F,B32) | T32: =IF(B32="","",Q32-R32+S32)
A33: 29 | B33: =IF(Masters!$B$31="","",Masters!$B$31) | C33: =IF(B33="","",Masters!$C$31) | D33: =IF(B33="","",IF(Masters!$D$31="","",Masters!$D$31)) | E33: =IF(B33="",0,Masters!$E$31) | F33: =SUMIF(Daily_Sales!$C:$C,B33,Daily_Sales!$G:$G) | G33: =SUMIF(Daily_Sales!$C:$C,B33,Daily_Sales!$E:$E) | H33: =IF(B33="",0,IF(D33<>"",D33*G33,F33*C33/100)) | I33: =IF(G33>0,Masters!$Y$3,0) | J33: =G33*Masters!$Y$4 | K33: =SUMIFS(Cash_Book!$G:$G,Cash_Book!$C:$C,"BEPAARI",Cash_Book!$D:$D,"MOTOR",Cash_Book!$E:$E,B33) | L33: =SUMIFS(Cash_Book!$G:$G,Cash_Book!$C:$C,"BEPAARI",Cash_Book!$D:$D,"BHUSSA",Cash_Book!$E:$E,B33) | M33: =SUMIFS(Cash_Book!$G:$G,Cash_Book!$C:$C,"BEPAARI",Cash_Book!$D:$D,"GAWALI",Cash_Book!$E:$E,B33) | N33: =SUMIFS(Cash_Book!$G:$G,Cash_Book!$C:$C,"BEPAARI",Cash_Book!$D:$D,"CASH_ADV",Cash_Book!$E:$E,B33) | O33: =SUMIFS(Cash_Book!$G:$G,Cash_Book!$C:$C,"BEPAARI",Cash_Book!$D:$D,"OTHER",Cash_Book!$E:$E,B33) | P33: =SUM(H33:O33) | Q33: =IF(B33="","",F33-P33+E33) | R33: =SUMIFS(Cash_Book!$G:$G,Cash_Book!$C:$C,"BEPAARI",Cash_Book!$D:$D,"PAYMENT",Cash_Book!$E:$E,B33) | S33: =SUMIFS(JV_Entries!$G:$G,JV_Entries!$C:$C,"BEPAARI",JV_Entries!$D:$D,B33)-SUMIFS(JV_Entries!$G:$G,JV_Entries!$E:$E,"BEPAARI",JV_Entries!$F:$F,B33) | T33: =IF(B33="","",Q33-R33+S33)
A34: 30 | B34: =IF(Masters!$B$32="","",Masters!$B$32) | C34: =IF(B34="","",Masters!$C$32) | D34: =IF(B34="","",IF(Masters!$D$32="","",Masters!$D$32)) | E34: =IF(B34="",0,Masters!$E$32) | F34: =SUMIF(Daily_Sales!$C:$C,B34,Daily_Sales!$G:$G) | G34: =SUMIF(Daily_Sales!$C:$C,B34,Daily_Sales!$E:$E) | H34: =IF(B34="",0,IF(D34<>"",D34*G34,F34*C34/100)) | I34: =IF(G34>0,Masters!$Y$3,0) | J34: =G34*Masters!$Y$4 | K34: =SUMIFS(Cash_Book!$G:$G,Cash_Book!$C:$C,"BEPAARI",Cash_Book!$D:$D,"MOTOR",Cash_Book!$E:$E,B34) | L34: =SUMIFS(Cash_Book!$G:$G,Cash_Book!$C:$C,"BEPAARI",Cash_Book!$D:$D,"BHUSSA",Cash_Book!$E:$E,B34) | M34: =SUMIFS(Cash_Book!$G:$G,Cash_Book!$C:$C,"BEPAARI",Cash_Book!$D:$D,"GAWALI",Cash_Book!$E:$E,B34) | N34: =SUMIFS(Cash_Book!$G:$G,Cash_Book!$C:$C,"BEPAARI",Cash_Book!$D:$D,"CASH_ADV",Cash_Book!$E:$E,B34) | O34: =SUMIFS(Cash_Book!$G:$G,Cash_Book!$C:$C,"BEPAARI",Cash_Book!$D:$D,"OTHER",Cash_Book!$E:$E,B34) | P34: =SUM(H34:O34) | Q34: =IF(B34="","",F34-P34+E34) | R34: =SUMIFS(Cash_Book!$G:$G,Cash_Book!$C:$C,"BEPAARI",Cash_Book!$D:$D,"PAYMENT",Cash_Book!$E:$E,B34) | S34: =SUMIFS(JV_Entries!$G:$G,JV_Entries!$C:$C,"BEPAARI",JV_Entries!$D:$D,B34)-SUMIFS(JV_Entries!$G:$G,JV_Entries!$E:$E,"BEPAARI",JV_Entries!$F:$F,B34) | T34: =IF(B34="","",Q34-R34+S34)
A35: 31 | B35: =IF(Masters!$B$33="","",Masters!$B$33) | C35: =IF(B35="","",Masters!$C$33) | D35: =IF(B35="","",IF(Masters!$D$33="","",Masters!$D$33)) | E35: =IF(B35="",0,Masters!$E$33) | F35: =SUMIF(Daily_Sales!$C:$C,B35,Daily_Sales!$G:$G) | G35: =SUMIF(Daily_Sales!$C:$C,B35,Daily_Sales!$E:$E) | H35: =IF(B35="",0,IF(D35<>"",D35*G35,F35*C35/100)) | I35: =IF(G35>0,Masters!$Y$3,0) | J35: =G35*Masters!$Y$4 | K35: =SUMIFS(Cash_Book!$G:$G,Cash_Book!$C:$C,"BEPAARI",Cash_Book!$D:$D,"MOTOR",Cash_Book!$E:$E,B35) | L35: =SUMIFS(Cash_Book!$G:$G,Cash_Book!$C:$C,"BEPAARI",Cash_Book!$D:$D,"BHUSSA",Cash_Book!$E:$E,B35) | M35: =SUMIFS(Cash_Book!$G:$G,Cash_Book!$C:$C,"BEPAARI",Cash_Book!$D:$D,"GAWALI",Cash_Book!$E:$E,B35) | N35: =SUMIFS(Cash_Book!$G:$G,Cash_Book!$C:$C,"BEPAARI",Cash_Book!$D:$D,"CASH_ADV",Cash_Book!$E:$E,B35) | O35: =SUMIFS(Cash_Book!$G:$G,Cash_Book!$C:$C,"BEPAARI",Cash_Book!$D:$D,"OTHER",Cash_Book!$E:$E,B35) | P35: =SUM(H35:O35) | Q35: =IF(B35="","",F35-P35+E35) | R35: =SUMIFS(Cash_Book!$G:$G,Cash_Book!$C:$C,"BEPAARI",Cash_Book!$D:$D,"PAYMENT",Cash_Book!$E:$E,B35) | S35: =SUMIFS(JV_Entries!$G:$G,JV_Entries!$C:$C,"BEPAARI",JV_Entries!$D:$D,B35)-SUMIFS(JV_Entries!$G:$G,JV_Entries!$E:$E,"BEPAARI",JV_Entries!$F:$F,B35) | T35: =IF(B35="","",Q35-R35+S35)
A36: 32 | B36: =IF(Masters!$B$34="","",Masters!$B$34) | C36: =IF(B36="","",Masters!$C$34) | D36: =IF(B36="","",IF(Masters!$D$34="","",Masters!$D$34)) | E36: =IF(B36="",0,Masters!$E$34) | F36: =SUMIF(Daily_Sales!$C:$C,B36,Daily_Sales!$G:$G) | G36: =SUMIF(Daily_Sales!$C:$C,B36,Daily_Sales!$E:$E) | H36: =IF(B36="",0,IF(D36<>"",D36*G36,F36*C36/100)) | I36: =IF(G36>0,Masters!$Y$3,0) | J36: =G36*Masters!$Y$4 | K36: =SUMIFS(Cash_Book!$G:$G,Cash_Book!$C:$C,"BEPAARI",Cash_Book!$D:$D,"MOTOR",Cash_Book!$E:$E,B36) | L36: =SUMIFS(Cash_Book!$G:$G,Cash_Book!$C:$C,"BEPAARI",Cash_Book!$D:$D,"BHUSSA",Cash_Book!$E:$E,B36) | M36: =SUMIFS(Cash_Book!$G:$G,Cash_Book!$C:$C,"BEPAARI",Cash_Book!$D:$D,"GAWALI",Cash_Book!$E:$E,B36) | N36: =SUMIFS(Cash_Book!$G:$G,Cash_Book!$C:$C,"BEPAARI",Cash_Book!$D:$D,"CASH_ADV",Cash_Book!$E:$E,B36) | O36: =SUMIFS(Cash_Book!$G:$G,Cash_Book!$C:$C,"BEPAARI",Cash_Book!$D:$D,"OTHER",Cash_Book!$E:$E,B36) | P36: =SUM(H36:O36) | Q36: =IF(B36="","",F36-P36+E36) | R36: =SUMIFS(Cash_Book!$G:$G,Cash_Book!$C:$C,"BEPAARI",Cash_Book!$D:$D,"PAYMENT",Cash_Book!$E:$E,B36) | S36: =SUMIFS(JV_Entries!$G:$G,JV_Entries!$C:$C,"BEPAARI",JV_Entries!$D:$D,B36)-SUMIFS(JV_Entries!$G:$G,JV_Entries!$E:$E,"BEPAARI",JV_Entries!$F:$F,B36) | T36: =IF(B36="","",Q36-R36+S36)
A37: 33 | B37: =IF(Masters!$B$35="","",Masters!$B$35) | C37: =IF(B37="","",Masters!$C$35) | D37: =IF(B37="","",IF(Masters!$D$35="","",Masters!$D$35)) | E37: =IF(B37="",0,Masters!$E$35) | F37: =SUMIF(Daily_Sales!$C:$C,B37,Daily_Sales!$G:$G) | G37: =SUMIF(Daily_Sales!$C:$C,B37,Daily_Sales!$E:$E) | H37: =IF(B37="",0,IF(D37<>"",D37*G37,F37*C37/100)) | I37: =IF(G37>0,Masters!$Y$3,0) | J37: =G37*Masters!$Y$4 | K37: =SUMIFS(Cash_Book!$G:$G,Cash_Book!$C:$C,"BEPAARI",Cash_Book!$D:$D,"MOTOR",Cash_Book!$E:$E,B37) | L37: =SUMIFS(Cash_Book!$G:$G,Cash_Book!$C:$C,"BEPAARI",Cash_Book!$D:$D,"BHUSSA",Cash_Book!$E:$E,B37) | M37: =SUMIFS(Cash_Book!$G:$G,Cash_Book!$C:$C,"BEPAARI",Cash_Book!$D:$D,"GAWALI",Cash_Book!$E:$E,B37) | N37: =SUMIFS(Cash_Book!$G:$G,Cash_Book!$C:$C,"BEPAARI",Cash_Book!$D:$D,"CASH_ADV",Cash_Book!$E:$E,B37) | O37: =SUMIFS(Cash_Book!$G:$G,Cash_Book!$C:$C,"BEPAARI",Cash_Book!$D:$D,"OTHER",Cash_Book!$E:$E,B37) | P37: =SUM(H37:O37) | Q37: =IF(B37="","",F37-P37+E37) | R37: =SUMIFS(Cash_Book!$G:$G,Cash_Book!$C:$C,"BEPAARI",Cash_Book!$D:$D,"PAYMENT",Cash_Book!$E:$E,B37) | S37: =SUMIFS(JV_Entries!$G:$G,JV_Entries!$C:$C,"BEPAARI",JV_Entries!$D:$D,B37)-SUMIFS(JV_Entries!$G:$G,JV_Entries!$E:$E,"BEPAARI",JV_Entries!$F:$F,B37) | T37: =IF(B37="","",Q37-R37+S37)
A38: 34 | B38: =IF(Masters!$B$36="","",Masters!$B$36) | C38: =IF(B38="","",Masters!$C$36) | D38: =IF(B38="","",IF(Masters!$D$36="","",Masters!$D$36)) | E38: =IF(B38="",0,Masters!$E$36) | F38: =SUMIF(Daily_Sales!$C:$C,B38,Daily_Sales!$G:$G) | G38: =SUMIF(Daily_Sales!$C:$C,B38,Daily_Sales!$E:$E) | H38: =IF(B38="",0,IF(D38<>"",D38*G38,F38*C38/100)) | I38: =IF(G38>0,Masters!$Y$3,0) | J38: =G38*Masters!$Y$4 | K38: =SUMIFS(Cash_Book!$G:$G,Cash_Book!$C:$C,"BEPAARI",Cash_Book!$D:$D,"MOTOR",Cash_Book!$E:$E,B38) | L38: =SUMIFS(Cash_Book!$G:$G,Cash_Book!$C:$C,"BEPAARI",Cash_Book!$D:$D,"BHUSSA",Cash_Book!$E:$E,B38) | M38: =SUMIFS(Cash_Book!$G:$G,Cash_Book!$C:$C,"BEPAARI",Cash_Book!$D:$D,"GAWALI",Cash_Book!$E:$E,B38) | N38: =SUMIFS(Cash_Book!$G:$G,Cash_Book!$C:$C,"BEPAARI",Cash_Book!$D:$D,"CASH_ADV",Cash_Book!$E:$E,B38) | O38: =SUMIFS(Cash_Book!$G:$G,Cash_Book!$C:$C,"BEPAARI",Cash_Book!$D:$D,"OTHER",Cash_Book!$E:$E,B38) | P38: =SUM(H38:O38) | Q38: =IF(B38="","",F38-P38+E38) | R38: =SUMIFS(Cash_Book!$G:$G,Cash_Book!$C:$C,"BEPAARI",Cash_Book!$D:$D,"PAYMENT",Cash_Book!$E:$E,B38) | S38: =SUMIFS(JV_Entries!$G:$G,JV_Entries!$C:$C,"BEPAARI",JV_Entries!$D:$D,B38)-SUMIFS(JV_Entries!$G:$G,JV_Entries!$E:$E,"BEPAARI",JV_Entries!$F:$F,B38) | T38: =IF(B38="","",Q38-R38+S38)
A39: 35 | B39: =IF(Masters!$B$37="","",Masters!$B$37) | C39: =IF(B39="","",Masters!$C$37) | D39: =IF(B39="","",IF(Masters!$D$37="","",Masters!$D$37)) | E39: =IF(B39="",0,Masters!$E$37) | F39: =SUMIF(Daily_Sales!$C:$C,B39,Daily_Sales!$G:$G) | G39: =SUMIF(Daily_Sales!$C:$C,B39,Daily_Sales!$E:$E) | H39: =IF(B39="",0,IF(D39<>"",D39*G39,F39*C39/100)) | I39: =IF(G39>0,Masters!$Y$3,0) | J39: =G39*Masters!$Y$4 | K39: =SUMIFS(Cash_Book!$G:$G,Cash_Book!$C:$C,"BEPAARI",Cash_Book!$D:$D,"MOTOR",Cash_Book!$E:$E,B39) | L39: =SUMIFS(Cash_Book!$G:$G,Cash_Book!$C:$C,"BEPAARI",Cash_Book!$D:$D,"BHUSSA",Cash_Book!$E:$E,B39) | M39: =SUMIFS(Cash_Book!$G:$G,Cash_Book!$C:$C,"BEPAARI",Cash_Book!$D:$D,"GAWALI",Cash_Book!$E:$E,B39) | N39: =SUMIFS(Cash_Book!$G:$G,Cash_Book!$C:$C,"BEPAARI",Cash_Book!$D:$D,"CASH_ADV",Cash_Book!$E:$E,B39) | O39: =SUMIFS(Cash_Book!$G:$G,Cash_Book!$C:$C,"BEPAARI",Cash_Book!$D:$D,"OTHER",Cash_Book!$E:$E,B39) | P39: =SUM(H39:O39) | Q39: =IF(B39="","",F39-P39+E39) | R39: =SUMIFS(Cash_Book!$G:$G,Cash_Book!$C:$C,"BEPAARI",Cash_Book!$D:$D,"PAYMENT",Cash_Book!$E:$E,B39) | S39: =SUMIFS(JV_Entries!$G:$G,JV_Entries!$C:$C,"BEPAARI",JV_Entries!$D:$D,B39)-SUMIFS(JV_Entries!$G:$G,JV_Entries!$E:$E,"BEPAARI",JV_Entries!$F:$F,B39) | T39: =IF(B39="","",Q39-R39+S39)
A40: 36 | B40: =IF(Masters!$B$38="","",Masters!$B$38) | C40: =IF(B40="","",Masters!$C$38) | D40: =IF(B40="","",IF(Masters!$D$38="","",Masters!$D$38)) | E40: =IF(B40="",0,Masters!$E$38) | F40: =SUMIF(Daily_Sales!$C:$C,B40,Daily_Sales!$G:$G) | G40: =SUMIF(Daily_Sales!$C:$C,B40,Daily_Sales!$E:$E) | H40: =IF(B40="",0,IF(D40<>"",D40*G40,F40*C40/100)) | I40: =IF(G40>0,Masters!$Y$3,0) | J40: =G40*Masters!$Y$4 | K40: =SUMIFS(Cash_Book!$G:$G,Cash_Book!$C:$C,"BEPAARI",Cash_Book!$D:$D,"MOTOR",Cash_Book!$E:$E,B40) | L40: =SUMIFS(Cash_Book!$G:$G,Cash_Book!$C:$C,"BEPAARI",Cash_Book!$D:$D,"BHUSSA",Cash_Book!$E:$E,B40) | M40: =SUMIFS(Cash_Book!$G:$G,Cash_Book!$C:$C,"BEPAARI",Cash_Book!$D:$D,"GAWALI",Cash_Book!$E:$E,B40) | N40: =SUMIFS(Cash_Book!$G:$G,Cash_Book!$C:$C,"BEPAARI",Cash_Book!$D:$D,"CASH_ADV",Cash_Book!$E:$E,B40) | O40: =SUMIFS(Cash_Book!$G:$G,Cash_Book!$C:$C,"BEPAARI",Cash_Book!$D:$D,"OTHER",Cash_Book!$E:$E,B40) | P40: =SUM(H40:O40) | Q40: =IF(B40="","",F40-P40+E40) | R40: =SUMIFS(Cash_Book!$G:$G,Cash_Book!$C:$C,"BEPAARI",Cash_Book!$D:$D,"PAYMENT",Cash_Book!$E:$E,B40) | S40: =SUMIFS(JV_Entries!$G:$G,JV_Entries!$C:$C,"BEPAARI",JV_Entries!$D:$D,B40)-SUMIFS(JV_Entries!$G:$G,JV_Entries!$E:$E,"BEPAARI",JV_Entries!$F:$F,B40) | T40: =IF(B40="","",Q40-R40+S40)
A41: 37 | B41: =IF(Masters!$B$39="","",Masters!$B$39) | C41: =IF(B41="","",Masters!$C$39) | D41: =IF(B41="","",IF(Masters!$D$39="","",Masters!$D$39)) | E41: =IF(B41="",0,Masters!$E$39) | F41: =SUMIF(Daily_Sales!$C:$C,B41,Daily_Sales!$G:$G) | G41: =SUMIF(Daily_Sales!$C:$C,B41,Daily_Sales!$E:$E) | H41: =IF(B41="",0,IF(D41<>"",D41*G41,F41*C41/100)) | I41: =IF(G41>0,Masters!$Y$3,0) | J41: =G41*Masters!$Y$4 | K41: =SUMIFS(Cash_Book!$G:$G,Cash_Book!$C:$C,"BEPAARI",Cash_Book!$D:$D,"MOTOR",Cash_Book!$E:$E,B41) | L41: =SUMIFS(Cash_Book!$G:$G,Cash_Book!$C:$C,"BEPAARI",Cash_Book!$D:$D,"BHUSSA",Cash_Book!$E:$E,B41) | M41: =SUMIFS(Cash_Book!$G:$G,Cash_Book!$C:$C,"BEPAARI",Cash_Book!$D:$D,"GAWALI",Cash_Book!$E:$E,B41) | N41: =SUMIFS(Cash_Book!$G:$G,Cash_Book!$C:$C,"BEPAARI",Cash_Book!$D:$D,"CASH_ADV",Cash_Book!$E:$E,B41) | O41: =SUMIFS(Cash_Book!$G:$G,Cash_Book!$C:$C,"BEPAARI",Cash_Book!$D:$D,"OTHER",Cash_Book!$E:$E,B41) | P41: =SUM(H41:O41) | Q41: =IF(B41="","",F41-P41+E41) | R41: =SUMIFS(Cash_Book!$G:$G,Cash_Book!$C:$C,"BEPAARI",Cash_Book!$D:$D,"PAYMENT",Cash_Book!$E:$E,B41) | S41: =SUMIFS(JV_Entries!$G:$G,JV_Entries!$C:$C,"BEPAARI",JV_Entries!$D:$D,B41)-SUMIFS(JV_Entries!$G:$G,JV_Entries!$E:$E,"BEPAARI",JV_Entries!$F:$F,B41) | T41: =IF(B41="","",Q41-R41+S41)
A42: 38 | B42: =IF(Masters!$B$40="","",Masters!$B$40) | C42: =IF(B42="","",Masters!$C$40) | D42: =IF(B42="","",IF(Masters!$D$40="","",Masters!$D$40)) | E42: =IF(B42="",0,Masters!$E$40) | F42: =SUMIF(Daily_Sales!$C:$C,B42,Daily_Sales!$G:$G) | G42: =SUMIF(Daily_Sales!$C:$C,B42,Daily_Sales!$E:$E) | H42: =IF(B42="",0,IF(D42<>"",D42*G42,F42*C42/100)) | I42: =IF(G42>0,Masters!$Y$3,0) | J42: =G42*Masters!$Y$4 | K42: =SUMIFS(Cash_Book!$G:$G,Cash_Book!$C:$C,"BEPAARI",Cash_Book!$D:$D,"MOTOR",Cash_Book!$E:$E,B42) | L42: =SUMIFS(Cash_Book!$G:$G,Cash_Book!$C:$C,"BEPAARI",Cash_Book!$D:$D,"BHUSSA",Cash_Book!$E:$E,B42) | M42: =SUMIFS(Cash_Book!$G:$G,Cash_Book!$C:$C,"BEPAARI",Cash_Book!$D:$D,"GAWALI",Cash_Book!$E:$E,B42) | N42: =SUMIFS(Cash_Book!$G:$G,Cash_Book!$C:$C,"BEPAARI",Cash_Book!$D:$D,"CASH_ADV",Cash_Book!$E:$E,B42) | O42: =SUMIFS(Cash_Book!$G:$G,Cash_Book!$C:$C,"BEPAARI",Cash_Book!$D:$D,"OTHER",Cash_Book!$E:$E,B42) | P42: =SUM(H42:O42) | Q42: =IF(B42="","",F42-P42+E42) | R42: =SUMIFS(Cash_Book!$G:$G,Cash_Book!$C:$C,"BEPAARI",Cash_Book!$D:$D,"PAYMENT",Cash_Book!$E:$E,B42) | S42: =SUMIFS(JV_Entries!$G:$G,JV_Entries!$C:$C,"BEPAARI",JV_Entries!$D:$D,B42)-SUMIFS(JV_Entries!$G:$G,JV_Entries!$E:$E,"BEPAARI",JV_Entries!$F:$F,B42) | T42: =IF(B42="","",Q42-R42+S42)
A43: 39 | B43: =IF(Masters!$B$41="","",Masters!$B$41) | C43: =IF(B43="","",Masters!$C$41) | D43: =IF(B43="","",IF(Masters!$D$41="","",Masters!$D$41)) | E43: =IF(B43="",0,Masters!$E$41) | F43: =SUMIF(Daily_Sales!$C:$C,B43,Daily_Sales!$G:$G) | G43: =SUMIF(Daily_Sales!$C:$C,B43,Daily_Sales!$E:$E) | H43: =IF(B43="",0,IF(D43<>"",D43*G43,F43*C43/100)) | I43: =IF(G43>0,Masters!$Y$3,0) | J43: =G43*Masters!$Y$4 | K43: =SUMIFS(Cash_Book!$G:$G,Cash_Book!$C:$C,"BEPAARI",Cash_Book!$D:$D,"MOTOR",Cash_Book!$E:$E,B43) | L43: =SUMIFS(Cash_Book!$G:$G,Cash_Book!$C:$C,"BEPAARI",Cash_Book!$D:$D,"BHUSSA",Cash_Book!$E:$E,B43) | M43: =SUMIFS(Cash_Book!$G:$G,Cash_Book!$C:$C,"BEPAARI",Cash_Book!$D:$D,"GAWALI",Cash_Book!$E:$E,B43) | N43: =SUMIFS(Cash_Book!$G:$G,Cash_Book!$C:$C,"BEPAARI",Cash_Book!$D:$D,"CASH_ADV",Cash_Book!$E:$E,B43) | O43: =SUMIFS(Cash_Book!$G:$G,Cash_Book!$C:$C,"BEPAARI",Cash_Book!$D:$D,"OTHER",Cash_Book!$E:$E,B43) | P43: =SUM(H43:O43) | Q43: =IF(B43="","",F43-P43+E43) | R43: =SUMIFS(Cash_Book!$G:$G,Cash_Book!$C:$C,"BEPAARI",Cash_Book!$D:$D,"PAYMENT",Cash_Book!$E:$E,B43) | S43: =SUMIFS(JV_Entries!$G:$G,JV_Entries!$C:$C,"BEPAARI",JV_Entries!$D:$D,B43)-SUMIFS(JV_Entries!$G:$G,JV_Entries!$E:$E,"BEPAARI",JV_Entries!$F:$F,B43) | T43: =IF(B43="","",Q43-R43+S43)
A44: 40 | B44: =IF(Masters!$B$42="","",Masters!$B$42) | C44: =IF(B44="","",Masters!$C$42) | D44: =IF(B44="","",IF(Masters!$D$42="","",Masters!$D$42)) | E44: =IF(B44="",0,Masters!$E$42) | F44: =SUMIF(Daily_Sales!$C:$C,B44,Daily_Sales!$G:$G) | G44: =SUMIF(Daily_Sales!$C:$C,B44,Daily_Sales!$E:$E) | H44: =IF(B44="",0,IF(D44<>"",D44*G44,F44*C44/100)) | I44: =IF(G44>0,Masters!$Y$3,0) | J44: =G44*Masters!$Y$4 | K44: =SUMIFS(Cash_Book!$G:$G,Cash_Book!$C:$C,"BEPAARI",Cash_Book!$D:$D,"MOTOR",Cash_Book!$E:$E,B44) | L44: =SUMIFS(Cash_Book!$G:$G,Cash_Book!$C:$C,"BEPAARI",Cash_Book!$D:$D,"BHUSSA",Cash_Book!$E:$E,B44) | M44: =SUMIFS(Cash_Book!$G:$G,Cash_Book!$C:$C,"BEPAARI",Cash_Book!$D:$D,"GAWALI",Cash_Book!$E:$E,B44) | N44: =SUMIFS(Cash_Book!$G:$G,Cash_Book!$C:$C,"BEPAARI",Cash_Book!$D:$D,"CASH_ADV",Cash_Book!$E:$E,B44) | O44: =SUMIFS(Cash_Book!$G:$G,Cash_Book!$C:$C,"BEPAARI",Cash_Book!$D:$D,"OTHER",Cash_Book!$E:$E,B44) | P44: =SUM(H44:O44) | Q44: =IF(B44="","",F44-P44+E44) | R44: =SUMIFS(Cash_Book!$G:$G,Cash_Book!$C:$C,"BEPAARI",Cash_Book!$D:$D,"PAYMENT",Cash_Book!$E:$E,B44) | S44: =SUMIFS(JV_Entries!$G:$G,JV_Entries!$C:$C,"BEPAARI",JV_Entries!$D:$D,B44)-SUMIFS(JV_Entries!$G:$G,JV_Entries!$E:$E,"BEPAARI",JV_Entries!$F:$F,B44) | T44: =IF(B44="","",Q44-R44+S44)
A45: 41 | B45: =IF(Masters!$B$43="","",Masters!$B$43) | C45: =IF(B45="","",Masters!$C$43) | D45: =IF(B45="","",IF(Masters!$D$43="","",Masters!$D$43)) | E45: =IF(B45="",0,Masters!$E$43) | F45: =SUMIF(Daily_Sales!$C:$C,B45,Daily_Sales!$G:$G) | G45: =SUMIF(Daily_Sales!$C:$C,B45,Daily_Sales!$E:$E) | H45: =IF(B45="",0,IF(D45<>"",D45*G45,F45*C45/100)) | I45: =IF(G45>0,Masters!$Y$3,0) | J45: =G45*Masters!$Y$4 | K45: =SUMIFS(Cash_Book!$G:$G,Cash_Book!$C:$C,"BEPAARI",Cash_Book!$D:$D,"MOTOR",Cash_Book!$E:$E,B45) | L45: =SUMIFS(Cash_Book!$G:$G,Cash_Book!$C:$C,"BEPAARI",Cash_Book!$D:$D,"BHUSSA",Cash_Book!$E:$E,B45) | M45: =SUMIFS(Cash_Book!$G:$G,Cash_Book!$C:$C,"BEPAARI",Cash_Book!$D:$D,"GAWALI",Cash_Book!$E:$E,B45) | N45: =SUMIFS(Cash_Book!$G:$G,Cash_Book!$C:$C,"BEPAARI",Cash_Book!$D:$D,"CASH_ADV",Cash_Book!$E:$E,B45) | O45: =SUMIFS(Cash_Book!$G:$G,Cash_Book!$C:$C,"BEPAARI",Cash_Book!$D:$D,"OTHER",Cash_Book!$E:$E,B45) | P45: =SUM(H45:O45) | Q45: =IF(B45="","",F45-P45+E45) | R45: =SUMIFS(Cash_Book!$G:$G,Cash_Book!$C:$C,"BEPAARI",Cash_Book!$D:$D,"PAYMENT",Cash_Book!$E:$E,B45) | S45: =SUMIFS(JV_Entries!$G:$G,JV_Entries!$C:$C,"BEPAARI",JV_Entries!$D:$D,B45)-SUMIFS(JV_Entries!$G:$G,JV_Entries!$E:$E,"BEPAARI",JV_Entries!$F:$F,B45) | T45: =IF(B45="","",Q45-R45+S45)
A46: 42 | B46: =IF(Masters!$B$44="","",Masters!$B$44) | C46: =IF(B46="","",Masters!$C$44) | D46: =IF(B46="","",IF(Masters!$D$44="","",Masters!$D$44)) | E46: =IF(B46="",0,Masters!$E$44) | F46: =SUMIF(Daily_Sales!$C:$C,B46,Daily_Sales!$G:$G) | G46: =SUMIF(Daily_Sales!$C:$C,B46,Daily_Sales!$E:$E) | H46: =IF(B46="",0,IF(D46<>"",D46*G46,F46*C46/100)) | I46: =IF(G46>0,Masters!$Y$3,0) | J46: =G46*Masters!$Y$4 | K46: =SUMIFS(Cash_Book!$G:$G,Cash_Book!$C:$C,"BEPAARI",Cash_Book!$D:$D,"MOTOR",Cash_Book!$E:$E,B46) | L46: =SUMIFS(Cash_Book!$G:$G,Cash_Book!$C:$C,"BEPAARI",Cash_Book!$D:$D,"BHUSSA",Cash_Book!$E:$E,B46) | M46: =SUMIFS(Cash_Book!$G:$G,Cash_Book!$C:$C,"BEPAARI",Cash_Book!$D:$D,"GAWALI",Cash_Book!$E:$E,B46) | N46: =SUMIFS(Cash_Book!$G:$G,Cash_Book!$C:$C,"BEPAARI",Cash_Book!$D:$D,"CASH_ADV",Cash_Book!$E:$E,B46) | O46: =SUMIFS(Cash_Book!$G:$G,Cash_Book!$C:$C,"BEPAARI",Cash_Book!$D:$D,"OTHER",Cash_Book!$E:$E,B46) | P46: =SUM(H46:O46) | Q46: =IF(B46="","",F46-P46+E46) | R46: =SUMIFS(Cash_Book!$G:$G,Cash_Book!$C:$C,"BEPAARI",Cash_Book!$D:$D,"PAYMENT",Cash_Book!$E:$E,B46) | S46: =SUMIFS(JV_Entries!$G:$G,JV_Entries!$C:$C,"BEPAARI",JV_Entries!$D:$D,B46)-SUMIFS(JV_Entries!$G:$G,JV_Entries!$E:$E,"BEPAARI",JV_Entries!$F:$F,B46) | T46: =IF(B46="","",Q46-R46+S46)
A47: 43 | B47: =IF(Masters!$B$45="","",Masters!$B$45) | C47: =IF(B47="","",Masters!$C$45) | D47: =IF(B47="","",IF(Masters!$D$45="","",Masters!$D$45)) | E47: =IF(B47="",0,Masters!$E$45) | F47: =SUMIF(Daily_Sales!$C:$C,B47,Daily_Sales!$G:$G) | G47: =SUMIF(Daily_Sales!$C:$C,B47,Daily_Sales!$E:$E) | H47: =IF(B47="",0,IF(D47<>"",D47*G47,F47*C47/100)) | I47: =IF(G47>0,Masters!$Y$3,0) | J47: =G47*Masters!$Y$4 | K47: =SUMIFS(Cash_Book!$G:$G,Cash_Book!$C:$C,"BEPAARI",Cash_Book!$D:$D,"MOTOR",Cash_Book!$E:$E,B47) | L47: =SUMIFS(Cash_Book!$G:$G,Cash_Book!$C:$C,"BEPAARI",Cash_Book!$D:$D,"BHUSSA",Cash_Book!$E:$E,B47) | M47: =SUMIFS(Cash_Book!$G:$G,Cash_Book!$C:$C,"BEPAARI",Cash_Book!$D:$D,"GAWALI",Cash_Book!$E:$E,B47) | N47: =SUMIFS(Cash_Book!$G:$G,Cash_Book!$C:$C,"BEPAARI",Cash_Book!$D:$D,"CASH_ADV",Cash_Book!$E:$E,B47) | O47: =SUMIFS(Cash_Book!$G:$G,Cash_Book!$C:$C,"BEPAARI",Cash_Book!$D:$D,"OTHER",Cash_Book!$E:$E,B47) | P47: =SUM(H47:O47) | Q47: =IF(B47="","",F47-P47+E47) | R47: =SUMIFS(Cash_Book!$G:$G,Cash_Book!$C:$C,"BEPAARI",Cash_Book!$D:$D,"PAYMENT",Cash_Book!$E:$E,B47) | S47: =SUMIFS(JV_Entries!$G:$G,JV_Entries!$C:$C,"BEPAARI",JV_Entries!$D:$D,B47)-SUMIFS(JV_Entries!$G:$G,JV_Entries!$E:$E,"BEPAARI",JV_Entries!$F:$F,B47) | T47: =IF(B47="","",Q47-R47+S47)
A48: 44 | B48: =IF(Masters!$B$46="","",Masters!$B$46) | C48: =IF(B48="","",Masters!$C$46) | D48: =IF(B48="","",IF(Masters!$D$46="","",Masters!$D$46)) | E48: =IF(B48="",0,Masters!$E$46) | F48: =SUMIF(Daily_Sales!$C:$C,B48,Daily_Sales!$G:$G) | G48: =SUMIF(Daily_Sales!$C:$C,B48,Daily_Sales!$E:$E) | H48: =IF(B48="",0,IF(D48<>"",D48*G48,F48*C48/100)) | I48: =IF(G48>0,Masters!$Y$3,0) | J48: =G48*Masters!$Y$4 | K48: =SUMIFS(Cash_Book!$G:$G,Cash_Book!$C:$C,"BEPAARI",Cash_Book!$D:$D,"MOTOR",Cash_Book!$E:$E,B48) | L48: =SUMIFS(Cash_Book!$G:$G,Cash_Book!$C:$C,"BEPAARI",Cash_Book!$D:$D,"BHUSSA",Cash_Book!$E:$E,B48) | M48: =SUMIFS(Cash_Book!$G:$G,Cash_Book!$C:$C,"BEPAARI",Cash_Book!$D:$D,"GAWALI",Cash_Book!$E:$E,B48) | N48: =SUMIFS(Cash_Book!$G:$G,Cash_Book!$C:$C,"BEPAARI",Cash_Book!$D:$D,"CASH_ADV",Cash_Book!$E:$E,B48) | O48: =SUMIFS(Cash_Book!$G:$G,Cash_Book!$C:$C,"BEPAARI",Cash_Book!$D:$D,"OTHER",Cash_Book!$E:$E,B48) | P48: =SUM(H48:O48) | Q48: =IF(B48="","",F48-P48+E48) | R48: =SUMIFS(Cash_Book!$G:$G,Cash_Book!$C:$C,"BEPAARI",Cash_Book!$D:$D,"PAYMENT",Cash_Book!$E:$E,B48) | S48: =SUMIFS(JV_Entries!$G:$G,JV_Entries!$C:$C,"BEPAARI",JV_Entries!$D:$D,B48)-SUMIFS(JV_Entries!$G:$G,JV_Entries!$E:$E,"BEPAARI",JV_Entries!$F:$F,B48) | T48: =IF(B48="","",Q48-R48+S48)
A49: 45 | B49: =IF(Masters!$B$47="","",Masters!$B$47) | C49: =IF(B49="","",Masters!$C$47) | D49: =IF(B49="","",IF(Masters!$D$47="","",Masters!$D$47)) | E49: =IF(B49="",0,Masters!$E$47) | F49: =SUMIF(Daily_Sales!$C:$C,B49,Daily_Sales!$G:$G) | G49: =SUMIF(Daily_Sales!$C:$C,B49,Daily_Sales!$E:$E) | H49: =IF(B49="",0,IF(D49<>"",D49*G49,F49*C49/100)) | I49: =IF(G49>0,Masters!$Y$3,0) | J49: =G49*Masters!$Y$4 | K49: =SUMIFS(Cash_Book!$G:$G,Cash_Book!$C:$C,"BEPAARI",Cash_Book!$D:$D,"MOTOR",Cash_Book!$E:$E,B49) | L49: =SUMIFS(Cash_Book!$G:$G,Cash_Book!$C:$C,"BEPAARI",Cash_Book!$D:$D,"BHUSSA",Cash_Book!$E:$E,B49) | M49: =SUMIFS(Cash_Book!$G:$G,Cash_Book!$C:$C,"BEPAARI",Cash_Book!$D:$D,"GAWALI",Cash_Book!$E:$E,B49) | N49: =SUMIFS(Cash_Book!$G:$G,Cash_Book!$C:$C,"BEPAARI",Cash_Book!$D:$D,"CASH_ADV",Cash_Book!$E:$E,B49) | O49: =SUMIFS(Cash_Book!$G:$G,Cash_Book!$C:$C,"BEPAARI",Cash_Book!$D:$D,"OTHER",Cash_Book!$E:$E,B49) | P49: =SUM(H49:O49) | Q49: =IF(B49="","",F49-P49+E49) | R49: =SUMIFS(Cash_Book!$G:$G,Cash_Book!$C:$C,"BEPAARI",Cash_Book!$D:$D,"PAYMENT",Cash_Book!$E:$E,B49) | S49: =SUMIFS(JV_Entries!$G:$G,JV_Entries!$C:$C,"BEPAARI",JV_Entries!$D:$D,B49)-SUMIFS(JV_Entries!$G:$G,JV_Entries!$E:$E,"BEPAARI",JV_Entries!$F:$F,B49) | T49: =IF(B49="","",Q49-R49+S49)
A50: 46 | B50: =IF(Masters!$B$48="","",Masters!$B$48) | C50: =IF(B50="","",Masters!$C$48) | D50: =IF(B50="","",IF(Masters!$D$48="","",Masters!$D$48)) | E50: =IF(B50="",0,Masters!$E$48) | F50: =SUMIF(Daily_Sales!$C:$C,B50,Daily_Sales!$G:$G) | G50: =SUMIF(Daily_Sales!$C:$C,B50,Daily_Sales!$E:$E) | H50: =IF(B50="",0,IF(D50<>"",D50*G50,F50*C50/100)) | I50: =IF(G50>0,Masters!$Y$3,0) | J50: =G50*Masters!$Y$4 | K50: =SUMIFS(Cash_Book!$G:$G,Cash_Book!$C:$C,"BEPAARI",Cash_Book!$D:$D,"MOTOR",Cash_Book!$E:$E,B50) | L50: =SUMIFS(Cash_Book!$G:$G,Cash_Book!$C:$C,"BEPAARI",Cash_Book!$D:$D,"BHUSSA",Cash_Book!$E:$E,B50) | M50: =SUMIFS(Cash_Book!$G:$G,Cash_Book!$C:$C,"BEPAARI",Cash_Book!$D:$D,"GAWALI",Cash_Book!$E:$E,B50) | N50: =SUMIFS(Cash_Book!$G:$G,Cash_Book!$C:$C,"BEPAARI",Cash_Book!$D:$D,"CASH_ADV",Cash_Book!$E:$E,B50) | O50: =SUMIFS(Cash_Book!$G:$G,Cash_Book!$C:$C,"BEPAARI",Cash_Book!$D:$D,"OTHER",Cash_Book!$E:$E,B50) | P50: =SUM(H50:O50) | Q50: =IF(B50="","",F50-P50+E50) | R50: =SUMIFS(Cash_Book!$G:$G,Cash_Book!$C:$C,"BEPAARI",Cash_Book!$D:$D,"PAYMENT",Cash_Book!$E:$E,B50) | S50: =SUMIFS(JV_Entries!$G:$G,JV_Entries!$C:$C,"BEPAARI",JV_Entries!$D:$D,B50)-SUMIFS(JV_Entries!$G:$G,JV_Entries!$E:$E,"BEPAARI",JV_Entries!$F:$F,B50) | T50: =IF(B50="","",Q50-R50+S50)
A51: 47 | B51: =IF(Masters!$B$49="","",Masters!$B$49) | C51: =IF(B51="","",Masters!$C$49) | D51: =IF(B51="","",IF(Masters!$D$49="","",Masters!$D$49)) | E51: =IF(B51="",0,Masters!$E$49) | F51: =SUMIF(Daily_Sales!$C:$C,B51,Daily_Sales!$G:$G) | G51: =SUMIF(Daily_Sales!$C:$C,B51,Daily_Sales!$E:$E) | H51: =IF(B51="",0,IF(D51<>"",D51*G51,F51*C51/100)) | I51: =IF(G51>0,Masters!$Y$3,0) | J51: =G51*Masters!$Y$4 | K51: =SUMIFS(Cash_Book!$G:$G,Cash_Book!$C:$C,"BEPAARI",Cash_Book!$D:$D,"MOTOR",Cash_Book!$E:$E,B51) | L51: =SUMIFS(Cash_Book!$G:$G,Cash_Book!$C:$C,"BEPAARI",Cash_Book!$D:$D,"BHUSSA",Cash_Book!$E:$E,B51) | M51: =SUMIFS(Cash_Book!$G:$G,Cash_Book!$C:$C,"BEPAARI",Cash_Book!$D:$D,"GAWALI",Cash_Book!$E:$E,B51) | N51: =SUMIFS(Cash_Book!$G:$G,Cash_Book!$C:$C,"BEPAARI",Cash_Book!$D:$D,"CASH_ADV",Cash_Book!$E:$E,B51) | O51: =SUMIFS(Cash_Book!$G:$G,Cash_Book!$C:$C,"BEPAARI",Cash_Book!$D:$D,"OTHER",Cash_Book!$E:$E,B51) | P51: =SUM(H51:O51) | Q51: =IF(B51="","",F51-P51+E51) | R51: =SUMIFS(Cash_Book!$G:$G,Cash_Book!$C:$C,"BEPAARI",Cash_Book!$D:$D,"PAYMENT",Cash_Book!$E:$E,B51) | S51: =SUMIFS(JV_Entries!$G:$G,JV_Entries!$C:$C,"BEPAARI",JV_Entries!$D:$D,B51)-SUMIFS(JV_Entries!$G:$G,JV_Entries!$E:$E,"BEPAARI",JV_Entries!$F:$F,B51) | T51: =IF(B51="","",Q51-R51+S51)
A52: 48 | B52: =IF(Masters!$B$50="","",Masters!$B$50) | C52: =IF(B52="","",Masters!$C$50) | D52: =IF(B52="","",IF(Masters!$D$50="","",Masters!$D$50)) | E52: =IF(B52="",0,Masters!$E$50) | F52: =SUMIF(Daily_Sales!$C:$C,B52,Daily_Sales!$G:$G) | G52: =SUMIF(Daily_Sales!$C:$C,B52,Daily_Sales!$E:$E) | H52: =IF(B52="",0,IF(D52<>"",D52*G52,F52*C52/100)) | I52: =IF(G52>0,Masters!$Y$3,0) | J52: =G52*Masters!$Y$4 | K52: =SUMIFS(Cash_Book!$G:$G,Cash_Book!$C:$C,"BEPAARI",Cash_Book!$D:$D,"MOTOR",Cash_Book!$E:$E,B52) | L52: =SUMIFS(Cash_Book!$G:$G,Cash_Book!$C:$C,"BEPAARI",Cash_Book!$D:$D,"BHUSSA",Cash_Book!$E:$E,B52) | M52: =SUMIFS(Cash_Book!$G:$G,Cash_Book!$C:$C,"BEPAARI",Cash_Book!$D:$D,"GAWALI",Cash_Book!$E:$E,B52) | N52: =SUMIFS(Cash_Book!$G:$G,Cash_Book!$C:$C,"BEPAARI",Cash_Book!$D:$D,"CASH_ADV",Cash_Book!$E:$E,B52) | O52: =SUMIFS(Cash_Book!$G:$G,Cash_Book!$C:$C,"BEPAARI",Cash_Book!$D:$D,"OTHER",Cash_Book!$E:$E,B52) | P52: =SUM(H52:O52) | Q52: =IF(B52="","",F52-P52+E52) | R52: =SUMIFS(Cash_Book!$G:$G,Cash_Book!$C:$C,"BEPAARI",Cash_Book!$D:$D,"PAYMENT",Cash_Book!$E:$E,B52) | S52: =SUMIFS(JV_Entries!$G:$G,JV_Entries!$C:$C,"BEPAARI",JV_Entries!$D:$D,B52)-SUMIFS(JV_Entries!$G:$G,JV_Entries!$E:$E,"BEPAARI",JV_Entries!$F:$F,B52) | T52: =IF(B52="","",Q52-R52+S52)
A53: 49 | B53: =IF(Masters!$B$51="","",Masters!$B$51) | C53: =IF(B53="","",Masters!$C$51) | D53: =IF(B53="","",IF(Masters!$D$51="","",Masters!$D$51)) | E53: =IF(B53="",0,Masters!$E$51) | F53: =SUMIF(Daily_Sales!$C:$C,B53,Daily_Sales!$G:$G) | G53: =SUMIF(Daily_Sales!$C:$C,B53,Daily_Sales!$E:$E) | H53: =IF(B53="",0,IF(D53<>"",D53*G53,F53*C53/100)) | I53: =IF(G53>0,Masters!$Y$3,0) | J53: =G53*Masters!$Y$4 | K53: =SUMIFS(Cash_Book!$G:$G,Cash_Book!$C:$C,"BEPAARI",Cash_Book!$D:$D,"MOTOR",Cash_Book!$E:$E,B53) | L53: =SUMIFS(Cash_Book!$G:$G,Cash_Book!$C:$C,"BEPAARI",Cash_Book!$D:$D,"BHUSSA",Cash_Book!$E:$E,B53) | M53: =SUMIFS(Cash_Book!$G:$G,Cash_Book!$C:$C,"BEPAARI",Cash_Book!$D:$D,"GAWALI",Cash_Book!$E:$E,B53) | N53: =SUMIFS(Cash_Book!$G:$G,Cash_Book!$C:$C,"BEPAARI",Cash_Book!$D:$D,"CASH_ADV",Cash_Book!$E:$E,B53) | O53: =SUMIFS(Cash_Book!$G:$G,Cash_Book!$C:$C,"BEPAARI",Cash_Book!$D:$D,"OTHER",Cash_Book!$E:$E,B53) | P53: =SUM(H53:O53) | Q53: =IF(B53="","",F53-P53+E53) | R53: =SUMIFS(Cash_Book!$G:$G,Cash_Book!$C:$C,"BEPAARI",Cash_Book!$D:$D,"PAYMENT",Cash_Book!$E:$E,B53) | S53: =SUMIFS(JV_Entries!$G:$G,JV_Entries!$C:$C,"BEPAARI",JV_Entries!$D:$D,B53)-SUMIFS(JV_Entries!$G:$G,JV_Entries!$E:$E,"BEPAARI",JV_Entries!$F:$F,B53) | T53: =IF(B53="","",Q53-R53+S53)
A54: 50 | B54: =IF(Masters!$B$52="","",Masters!$B$52) | C54: =IF(B54="","",Masters!$C$52) | D54: =IF(B54="","",IF(Masters!$D$52="","",Masters!$D$52)) | E54: =IF(B54="",0,Masters!$E$52) | F54: =SUMIF(Daily_Sales!$C:$C,B54,Daily_Sales!$G:$G) | G54: =SUMIF(Daily_Sales!$C:$C,B54,Daily_Sales!$E:$E) | H54: =IF(B54="",0,IF(D54<>"",D54*G54,F54*C54/100)) | I54: =IF(G54>0,Masters!$Y$3,0) | J54: =G54*Masters!$Y$4 | K54: =SUMIFS(Cash_Book!$G:$G,Cash_Book!$C:$C,"BEPAARI",Cash_Book!$D:$D,"MOTOR",Cash_Book!$E:$E,B54) | L54: =SUMIFS(Cash_Book!$G:$G,Cash_Book!$C:$C,"BEPAARI",Cash_Book!$D:$D,"BHUSSA",Cash_Book!$E:$E,B54) | M54: =SUMIFS(Cash_Book!$G:$G,Cash_Book!$C:$C,"BEPAARI",Cash_Book!$D:$D,"GAWALI",Cash_Book!$E:$E,B54) | N54: =SUMIFS(Cash_Book!$G:$G,Cash_Book!$C:$C,"BEPAARI",Cash_Book!$D:$D,"CASH_ADV",Cash_Book!$E:$E,B54) | O54: =SUMIFS(Cash_Book!$G:$G,Cash_Book!$C:$C,"BEPAARI",Cash_Book!$D:$D,"OTHER",Cash_Book!$E:$E,B54) | P54: =SUM(H54:O54) | Q54: =IF(B54="","",F54-P54+E54) | R54: =SUMIFS(Cash_Book!$G:$G,Cash_Book!$C:$C,"BEPAARI",Cash_Book!$D:$D,"PAYMENT",Cash_Book!$E:$E,B54) | S54: =SUMIFS(JV_Entries!$G:$G,JV_Entries!$C:$C,"BEPAARI",JV_Entries!$D:$D,B54)-SUMIFS(JV_Entries!$G:$G,JV_Entries!$E:$E,"BEPAARI",JV_Entries!$F:$F,B54) | T54: =IF(B54="","",Q54-R54+S54)
A55: TOTAL | E55: =SUM(E5:E54) | F55: =SUM(F5:F54) | G55: =SUM(G5:G54) | H55: =SUM(H5:H54) | I55: =SUM(I5:I54) | J55: =SUM(J5:J54) | K55: =SUM(K5:K54) | L55: =SUM(L5:L54) | ... T55: =SUM(T5:T54)
P57: For Balance Sheet:
Q58: Bepaari Payable (we owe) | T58: =SUMIF(T5:T54,">0",T5:T54)
Q59: Bepaari Overpaid (they owe) | T59: =-SUMIF(T5:T54,"<0",T5:T54)

Sheet Dukandar_Ledger
A1: DUKANDAR LEDGER
A3: Sr | B3: Dukandar | C3: Opening | D3: Purchases | E3: Discounts | F3: Net Receivable | G3: Receipts | H3: JV Adj | I3: BALANCE
A4: 1 | B4: =IF(Masters!$J$3="","",Masters!$J$3) | C4: =IF(B4="",0,Masters!$K$3) | D4: =SUMIF(Daily_Sales!$D:$D,B4,Daily_Sales!$G:$G) | E4: =SUMIF(Daily_Sales!$D:$D,B4,Daily_Sales!$H:$H) | F4: =IF(B4="","",D4-E4+C4) | G4: =SUMIFS(Cash_Book!$G:$G,Cash_Book!$C:$C,"DUKANDAR",Cash_Book!$D:$D,"RECEIPT",Cash_Book!$E:$E,B4) | H4: =SUMIFS(JV_Entries!$G:$G,JV_Entries!$E:$E,"DUKANDAR",JV_Entries!$F:$F,B4)-SUMIFS(JV_Entries!$G:$G,JV_Entries!$C:$C,"DUKANDAR",JV_Entries!$D:$D,B4) | I4: =IF(B4="","",F4-G4+H4)
A5: 2 | B5: =IF(Masters!$J$4="","",Masters!$J$4) | C5: =IF(B5="",0,Masters!$K$4) | D5: =SUMIF(Daily_Sales!$D:$D,B5,Daily_Sales!$G:$G) | E5: =SUMIF(Daily_Sales!$D:$D,B5,Daily_Sales!$H:$H) | F5: =IF(B5="","",D5-E5+C5) | G5: =SUMIFS(Cash_Book!$G:$G,Cash_Book!$C:$C,"DUKANDAR",Cash_Book!$D:$D,"RECEIPT",Cash_Book!$E:$E,B5) | H5: =SUMIFS(JV_Entries!$G:$G,JV_Entries!$E:$E,"DUKANDAR",JV_Entries!$F:$F,B5)-SUMIFS(JV_Entries!$G:$G,JV_Entries!$C:$C,"DUKANDAR",JV_Entries!$D:$D,B5) | I5: =IF(B5="","",F5-G5+H5)
A6: 3 | B6: =IF(Masters!$J$5="","",Masters!$J$5) | C6: =IF(B6="",0,Masters!$K$5) | D6: =SUMIF(Daily_Sales!$D:$D,B6,Daily_Sales!$G:$G) | E6: =SUMIF(Daily_Sales!$D:$D,B6,Daily_Sales!$H:$H) | F6: =IF(B6="","",D6-E6+C6) | G6: =SUMIFS(Cash_Book!$G:$G,Cash_Book!$C:$C,"DUKANDAR",Cash_Book!$D:$D,"RECEIPT",Cash_Book!$E:$E,B6) | H6: =SUMIFS(JV_Entries!$G:$G,JV_Entries!$E:$E,"DUKANDAR",JV_Entries!$F:$F,B6)-SUMIFS(JV_Entries!$G:$G,JV_Entries!$C:$C,"DUKANDAR",JV_Entries!$D:$D,B6) | I6: =IF(B6="","",F6-G6+H6)
A7: 4 | B7: =IF(Masters!$J$6="","",Masters!$J$6) | C7: =IF(B7="",0,Masters!$K$6) | D7: =SUMIF(Daily_Sales!$D:$D,B7,Daily_Sales!$G:$G) | E7: =SUMIF(Daily_Sales!$D:$D,B7,Daily_Sales!$H:$H) | F7: =IF(B7="","",D7-E7+C7) | G7: =SUMIFS(Cash_Book!$G:$G,Cash_Book!$C:$C,"DUKANDAR",Cash_Book!$D:$D,"RECEIPT",Cash_Book!$E:$E,B7) | H7: =SUMIFS(JV_Entries!$G:$G,JV_Entries!$E:$E,"DUKANDAR",JV_Entries!$F:$F,B7)-SUMIFS(JV_Entries!$G:$G,JV_Entries!$C:$C,"DUKANDAR",JV_Entries!$D:$D,B7) | I7: =IF(B7="","",F7-G7+H7)
A8: 5 | B8: =IF(Masters!$J$7="","",Masters!$J$7) | C8: =IF(B8="",0,Masters!$K$7) | D8: =SUMIF(Daily_Sales!$D:$D,B8,Daily_Sales!$G:$G) | E8: =SUMIF(Daily_Sales!$D:$D,B8,Daily_Sales!$H:$H) | F8: =IF(B8="","",D8-E8+C8) | G8: =SUMIFS(Cash_Book!$G:$G,Cash_Book!$C:$C,"DUKANDAR",Cash_Book!$D:$D,"RECEIPT",Cash_Book!$E:$E,B8) | H8: =SUMIFS(JV_Entries!$G:$G,JV_Entries!$E:$E,"DUKANDAR",JV_Entries!$F:$F,B8)-SUMIFS(JV_Entries!$G:$G,JV_Entries!$C:$C,"DUKANDAR",JV_Entries!$D:$D,B8) | I8: =IF(B8="","",F8-G8+H8)
A9: 6 | B9: =IF(Masters!$J$8="","",Masters!$J$8) | C9: =IF(B9="",0,Masters!$K$8) | D9: =SUMIF(Daily_Sales!$D:$D,B9,Daily_Sales!$G:$G) | E9: =SUMIF(Daily_Sales!$D:$D,B9,Daily_Sales!$H:$H) | F9: =IF(B9="","",D9-E9+C9) | G9: =SUMIFS(Cash_Book!$G:$G,Cash_Book!$C:$C,"DUKANDAR",Cash_Book!$D:$D,"RECEIPT",Cash_Book!$E:$E,B9) | H9: =SUMIFS(JV_Entries!$G:$G,JV_Entries!$E:$E,"DUKANDAR",JV_Entries!$F:$F,B9)-SUMIFS(JV_Entries!$G:$G,JV_Entries!$C:$C,"DUKANDAR",JV_Entries!$D:$D,B9) | I9: =IF(B9="","",F9-G9+H9)
A10: 7 | B10: =IF(Masters!$J$9="","",Masters!$J$9) | C10: =IF(B10="",0,Masters!$K$9) | D10: =SUMIF(Daily_Sales!$D:$D,B10,Daily_Sales!$G:$G) | E10: =SUMIF(Daily_Sales!$D:$D,B10,Daily_Sales!$H:$H) | F10: =IF(B10="","",D10-E10+C10) | G10: =SUMIFS(Cash_Book!$G:$G,Cash_Book!$C:$C,"DUKANDAR",Cash_Book!$D:$D,"RECEIPT",Cash_Book!$E:$E,B10) | H10: =SUMIFS(JV_Entries!$G:$G,JV_Entries!$E:$E,"DUKANDAR",JV_Entries!$F:$F,B10)-SUMIFS(JV_Entries!$G:$G,JV_Entries!$C:$C,"DUKANDAR",JV_Entries!$D:$D,B10) | I10: =IF(B10="","",F10-G10+H10)
A11: 8 | B11: =IF(Masters!$J$10="","",Masters!$J$10) | C11: =IF(B11="",0,Masters!$K$10) | D11: =SUMIF(Daily_Sales!$D:$D,B11,Daily_Sales!$G:$G) | E11: =SUMIF(Daily_Sales!$D:$D,B11,Daily_Sales!$H:$H) | F11: =IF(B11="","",D11-E11+C11) | G11: =SUMIFS(Cash_Book!$G:$G,Cash_Book!$C:$C,"DUKANDAR",Cash_Book!$D:$D,"RECEIPT",Cash_Book!$E:$E,B11) | H11: =SUMIFS(JV_Entries!$G:$G,JV_Entries!$E:$E,"DUKANDAR",JV_Entries!$F:$F,B11)-SUMIFS(JV_Entries!$G:$G,JV_Entries!$C:$C,"DUKANDAR",JV_Entries!$D:$D,B11) | I11: =IF(B11="","",F11-G11+H11)
A12: 9 | B12: =IF(Masters!$J$11="","",Masters!$J$11) | C12: =IF(B12="",0,Masters!$K$11) | D12: =SUMIF(Daily_Sales!$D:$D,B12,Daily_Sales!$G:$G) | E12: =SUMIF(Daily_Sales!$D:$D,B12,Daily_Sales!$H:$H) | F12: =IF(B12="","",D12-E12+C12) | G12: =SUMIFS(Cash_Book!$G:$G,Cash_Book!$C:$C,"DUKANDAR",Cash_Book!$D:$D,"RECEIPT",Cash_Book!$E:$E,B12) | H12: =SUMIFS(JV_Entries!$G:$G,JV_Entries!$E:$E,"DUKANDAR",JV_Entries!$F:$F,B12)-SUMIFS(JV_Entries!$G:$G,JV_Entries!$C:$C,"DUKANDAR",JV_Entries!$D:$D,B12) | I12: =IF(B12="","",F12-G12+H12)
A13: 10 | B13: =IF(Masters!$J$12="","",Masters!$J$12) | C13: =IF(B13="",0,Masters!$K$12) | D13: =SUMIF(Daily_Sales!$D:$D,B13,Daily_Sales!$G:$G) | E13: =SUMIF(Daily_Sales!$D:$D,B13,Daily_Sales!$H:$H) | F13: =IF(B13="","",D13-E13+C13) | G13: =SUMIFS(Cash_Book!$G:$G,Cash_Book!$C:$C,"DUKANDAR",Cash_Book!$D:$D,"RECEIPT",Cash_Book!$E:$E,B13) | H13: =SUMIFS(JV_Entries!$G:$G,JV_Entries!$E:$E,"DUKANDAR",JV_Entries!$F:$F,B13)-SUMIFS(JV_Entries!$G:$G,JV_Entries!$C:$C,"DUKANDAR",JV_Entries!$D:$D,B13) | I13: =IF(B13="","",F13-G13+H13)
A14: 11 | B14: =IF(Masters!$J$13="","",Masters!$J$13) | C14: =IF(B14="",0,Masters!$K$13) | D14: =SUMIF(Daily_Sales!$D:$D,B14,Daily_Sales!$G:$G) | E14: =SUMIF(Daily_Sales!$D:$D,B14,Daily_Sales!$H:$H) | F14: =IF(B14="","",D14-E14+C14) | G14: =SUMIFS(Cash_Book!$G:$G,Cash_Book!$C:$C,"DUKANDAR",Cash_Book!$D:$D,"RECEIPT",Cash_Book!$E:$E,B14) | H14: =SUMIFS(JV_Entries!$G:$G,JV_Entries!$E:$E,"DUKANDAR",JV_Entries!$F:$F,B14)-SUMIFS(JV_Entries!$G:$G,JV_Entries!$C:$C,"DUKANDAR",JV_Entries!$D:$D,B14) | I14: =IF(B14="","",F14-G14+H14)
A15: 12 | B15: =IF(Masters!$J$14="","",Masters!$J$14) | C15: =IF(B15="",0,Masters!$K$14) | D15: =SUMIF(Daily_Sales!$D:$D,B15,Daily_Sales!$G:$G) | E15: =SUMIF(Daily_Sales!$D:$D,B15,Daily_Sales!$H:$H) | F15: =IF(B15="","",D15-E15+C15) | G15: =SUMIFS(Cash_Book!$G:$G,Cash_Book!$C:$C,"DUKANDAR",Cash_Book!$D:$D,"RECEIPT",Cash_Book!$E:$E,B15) | H15: =SUMIFS(JV_Entries!$G:$G,JV_Entries!$E:$E,"DUKANDAR",JV_Entries!$F:$F,B15)-SUMIFS(JV_Entries!$G:$G,JV_Entries!$C:$C,"DUKANDAR",JV_Entries!$D:$D,B15) | I15: =IF(B15="","",F15-G15+H15)
A16: 13 | B16: =IF(Masters!$J$15="","",Masters!$J$15) | C16: =IF(B16="",0,Masters!$K$15) | D16: =SUMIF(Daily_Sales!$D:$D,B16,Daily_Sales!$G:$G) | E16: =SUMIF(Daily_Sales!$D:$D,B16,Daily_Sales!$H:$H) | F16: =IF(B16="","",D16-E16+C16) | G16: =SUMIFS(Cash_Book!$G:$G,Cash_Book!$C:$C,"DUKANDAR",Cash_Book!$D:$D,"RECEIPT",Cash_Book!$E:$E,B16) | H16: =SUMIFS(JV_Entries!$G:$G,JV_Entries!$E:$E,"DUKANDAR",JV_Entries!$F:$F,B16)-SUMIFS(JV_Entries!$G:$G,JV_Entries!$C:$C,"DUKANDAR",JV_Entries!$D:$D,B16) | I16: =IF(B16="","",F16-G16+H16)
A17: 14 | B17: =IF(Masters!$J$16="","",Masters!$J$16) | C17: =IF(B17="",0,Masters!$K$16) | D17: =SUMIF(Daily_Sales!$D:$D,B17,Daily_Sales!$G:$G) | E17: =SUMIF(Daily_Sales!$D:$D,B17,Daily_Sales!$H:$H) | F17: =IF(B17="","",D17-E17+C17) | G17: =SUMIFS(Cash_Book!$G:$G,Cash_Book!$C:$C,"DUKANDAR",Cash_Book!$D:$D,"RECEIPT",Cash_Book!$E:$E,B17) | H17: =SUMIFS(JV_Entries!$G:$G,JV_Entries!$E:$E,"DUKANDAR",JV_Entries!$F:$F,B17)-SUMIFS(JV_Entries!$G:$G,JV_Entries!$C:$C,"DUKANDAR",JV_Entries!$D:$D,B17) | I17: =IF(B17="","",F17-G17+H17)
A18: 15 | B18: =IF(Masters!$J$17="","",Masters!$J$17) | C18: =IF(B18="",0,Masters!$K$17) | D18: =SUMIF(Daily_Sales!$D:$D,B18,Daily_Sales!$G:$G) | E18: =SUMIF(Daily_Sales!$D:$D,B18,Daily_Sales!$H:$H) | F18: =IF(B18="","",D18-E18+C18) | G18: =SUMIFS(Cash_Book!$G:$G,Cash_Book!$C:$C,"DUKANDAR",Cash_Book!$D:$D,"RECEIPT",Cash_Book!$E:$E,B18) | H18: =SUMIFS(JV_Entries!$G:$G,JV_Entries!$E:$E,"DUKANDAR",JV_Entries!$F:$F,B18)-SUMIFS(JV_Entries!$G:$G,JV_Entries!$C:$C,"DUKANDAR",JV_Entries!$D:$D,B18) | I18: =IF(B18="","",F18-G18+H18)
A19: 16 | B19: =IF(Masters!$J$18="","",Masters!$J$18) | C19: =IF(B19="",0,Masters!$K$18) | D19: =SUMIF(Daily_Sales!$D:$D,B19,Daily_Sales!$G:$G) | E19: =SUMIF(Daily_Sales!$D:$D,B19,Daily_Sales!$H:$H) | F19: =IF(B19="","",D19-E19+C19) | G19: =SUMIFS(Cash_Book!$G:$G,Cash_Book!$C:$C,"DUKANDAR",Cash_Book!$D:$D,"RECEIPT",Cash_Book!$E:$E,B19) | H19: =SUMIFS(JV_Entries!$G:$G,JV_Entries!$E:$E,"DUKANDAR",JV_Entries!$F:$F,B19)-SUMIFS(JV_Entries!$G:$G,JV_Entries!$C:$C,"DUKANDAR",JV_Entries!$D:$D,B19) | I19: =IF(B19="","",F19-G19+H19)
A20: 17 | B20: =IF(Masters!$J$19="","",Masters!$J$19) | C20: =IF(B20="",0,Masters!$K$19) | D20: =SUMIF(Daily_Sales!$D:$D,B20,Daily_Sales!$G:$G) | E20: =SUMIF(Daily_Sales!$D:$D,B20,Daily_Sales!$H:$H) | F20: =IF(B20="","",D20-E20+C20) | G20: =SUMIFS(Cash_Book!$G:$G,Cash_Book!$C:$C,"DUKANDAR",Cash_Book!$D:$D,"RECEIPT",Cash_Book!$E:$E,B20) | H20: =SUMIFS(JV_Entries!$G:$G,JV_Entries!$E:$E,"DUKANDAR",JV_Entries!$F:$F,B20)-SUMIFS(JV_Entries!$G:$G,JV_Entries!$C:$C,"DUKANDAR",JV_Entries!$D:$D,B20) | I20: =IF(B20="","",F20-G20+H20)
A21: 18 | B21: =IF(Masters!$J$20="","",Masters!$J$20) | C21: =IF(B21="",0,Masters!$K$20) | D21: =SUMIF(Daily_Sales!$D:$D,B21,Daily_Sales!$G:$G) | E21: =SUMIF(Daily_Sales!$D:$D,B21,Daily_Sales!$H:$H) | F21: =IF(B21="","",D21-E21+C21) | G21: =SUMIFS(Cash_Book!$G:$G,Cash_Book!$C:$C,"DUKANDAR",Cash_Book!$D:$D,"RECEIPT",Cash_Book!$E:$E,B21) | H21: =SUMIFS(JV_Entries!$G:$G,JV_Entries!$E:$E,"DUKANDAR",JV_Entries!$F:$F,B21)-SUMIFS(JV_Entries!$G:$G,JV_Entries!$C:$C,"DUKANDAR",JV_Entries!$D:$D,B21) | I21: =IF(B21="","",F21-G21+H21)
A22: 19 | B22: =IF(Masters!$J$21="","",Masters!$J$21) | C22: =IF(B22="",0,Masters!$K$21) | D22: =SUMIF(Daily_Sales!$D:$D,B22,Daily_Sales!$G:$G) | E22: =SUMIF(Daily_Sales!$D:$D,B22,Daily_Sales!$H:$H) | F22: =IF(B22="","",D22-E22+C22) | G22: =SUMIFS(Cash_Book!$G:$G,Cash_Book!$C:$C,"DUKANDAR",Cash_Book!$D:$D,"RECEIPT",Cash_Book!$E:$E,B22) | H22: =SUMIFS(JV_Entries!$G:$G,JV_Entries!$E:$E,"DUKANDAR",JV_Entries!$F:$F,B22)-SUMIFS(JV_Entries!$G:$G,JV_Entries!$C:$C,"DUKANDAR",JV_Entries!$D:$D,B22) | I22: =IF(B22="","",F22-G22+H22)
A23: 20 | B23: =IF(Masters!$J$22="","",Masters!$J$22) | C23: =IF(B23="",0,Masters!$K$22) | D23: =SUMIF(Daily_Sales!$D:$D,B23,Daily_Sales!$G:$G) | E23: =SUMIF(Daily_Sales!$D:$D,B23,Daily_Sales!$H:$H) | F23: =IF(B23="","",D23-E23+C23) | G23: =SUMIFS(Cash_Book!$G:$G,Cash_Book!$C:$C,"DUKANDAR",Cash_Book!$D:$D,"RECEIPT",Cash_Book!$E:$E,B23) | H23: =SUMIFS(JV_Entries!$G:$G,JV_Entries!$E:$E,"DUKANDAR",JV_Entries!$F:$F,B23)-SUMIFS(JV_Entries!$G:$G,JV_Entries!$C:$C,"DUKANDAR",JV_Entries!$D:$D,B23) | I23: =IF(B23="","",F23-G23+H23)
A24: 21 | B24: =IF(Masters!$J$23="","",Masters!$J$23) | C24: =IF(B24="",0,Masters!$K$23) | D24: =SUMIF(Daily_Sales!$D:$D,B24,Daily_Sales!$G:$G) | E24: =SUMIF(Daily_Sales!$D:$D,B24,Daily_Sales!$H:$H) | F24: =IF(B24="","",D24-E24+C24) | G24: =SUMIFS(Cash_Book!$G:$G,Cash_Book!$C:$C,"DUKANDAR",Cash_Book!$D:$D,"RECEIPT",Cash_Book!$E:$E,B24) | H24: =SUMIFS(JV_Entries!$G:$G,JV_Entries!$E:$E,"DUKANDAR",JV_Entries!$F:$F,B24)-SUMIFS(JV_Entries!$G:$G,JV_Entries!$C:$C,"DUKANDAR",JV_Entries!$D:$D,B24) | I24: =IF(B24="","",F24-G24+H24)
A25: 22 | B25: =IF(Masters!$J$24="","",Masters!$J$24) | C25: =IF(B25="",0,Masters!$K$24) | D25: =SUMIF(Daily_Sales!$D:$D,B25,Daily_Sales!$G:$G) | E25: =SUMIF(Daily_Sales!$D:$D,B25,Daily_Sales!$H:$H) | F25: =IF(B25="","",D25-E25+C25) | G25: =SUMIFS(Cash_Book!$G:$G,Cash_Book!$C:$C,"DUKANDAR",Cash_Book!$D:$D,"RECEIPT",Cash_Book!$E:$E,B25) | H25: =SUMIFS(JV_Entries!$G:$G,JV_Entries!$E:$E,"DUKANDAR",JV_Entries!$F:$F,B25)-SUMIFS(JV_Entries!$G:$G,JV_Entries!$C:$C,"DUKANDAR",JV_Entries!$D:$D,B25) | I25: =IF(B25="","",F25-G25+H25)
A26: 23 | B26: =IF(Masters!$J$25="","",Masters!$J$25) | C26: =IF(B26="",0,Masters!$K$25) | D26: =SUMIF(Daily_Sales!$D:$D,B26,Daily_Sales!$G:$G) | E26: =SUMIF(Daily_Sales!$D:$D,B26,Daily_Sales!$H:$H) | F26: =IF(B26="","",D26-E26+C26) | G26: =SUMIFS(Cash_Book!$G:$G,Cash_Book!$C:$C,"DUKANDAR",Cash_Book!$D:$D,"RECEIPT",Cash_Book!$E:$E,B26) | H26: =SUMIFS(JV_Entries!$G:$G,JV_Entries!$E:$E,"DUKANDAR",JV_Entries!$F:$F,B26)-SUMIFS(JV_Entries!$G:$G,JV_Entries!$C:$C,"DUKANDAR",JV_Entries!$D:$D,B26) | I26: =IF(B26="","",F26-G26+H26)
A27: 24 | B27: =IF(Masters!$J$26="","",Masters!$J$26) | C27: =IF(B27="",0,Masters!$K$26) | D27: =SUMIF(Daily_Sales!$D:$D,B27,Daily_Sales!$G:$G) | E27: =SUMIF(Daily_Sales!$D:$D,B27,Daily_Sales!$H:$H) | F27: =IF(B27="","",D27-E27+C27) | G27: =SUMIFS(Cash_Book!$G:$G,Cash_Book!$C:$C,"DUKANDAR",Cash_Book!$D:$D,"RECEIPT",Cash_Book!$E:$E,B27) | H27: =SUMIFS(JV_Entries!$G:$G,JV_Entries!$E:$E,"DUKANDAR",JV_Entries!$F:$F,B27)-SUMIFS(JV_Entries!$G:$G,JV_Entries!$C:$C,"DUKANDAR",JV_Entries!$D:$D,B27) | I27: =IF(B27="","",F27-G27+H27)
A28: 25 | B28: =IF(Masters!$J$27="","",Masters!$J$27) | C28: =IF(B28="",0,Masters!$K$27) | D28: =SUMIF(Daily_Sales!$D:$D,B28,Daily_Sales!$G:$G) | E28: =SUMIF(Daily_Sales!$D:$D,B28,Daily_Sales!$H:$H) | F28: =IF(B28="","",D28-E28+C28) | G28: =SUMIFS(Cash_Book!$G:$G,Cash_Book!$C:$C,"DUKANDAR",Cash_Book!$D:$D,"RECEIPT",Cash_Book!$E:$E,B28) | H28: =SUMIFS(JV_Entries!$G:$G,JV_Entries!$E:$E,"DUKANDAR",JV_Entries!$F:$F,B28)-SUMIFS(JV_Entries!$G:$G,JV_Entries!$C:$C,"DUKANDAR",JV_Entries!$D:$D,B28) | I28: =IF(B28="","",F28-G28+H28)
A29: 26 | B29: =IF(Masters!$J$28="","",Masters!$J$28) | C29: =IF(B29="",0,Masters!$K$28) | D29: =SUMIF(Daily_Sales!$D:$D,B29,Daily_Sales!$G:$G) | E29: =SUMIF(Daily_Sales!$D:$D,B29,Daily_Sales!$H:$H) | F29: =IF(B29="","",D29-E29+C29) | G29: =SUMIFS(Cash_Book!$G:$G,Cash_Book!$C:$C,"DUKANDAR",Cash_Book!$D:$D,"RECEIPT",Cash_Book!$E:$E,B29) | H29: =SUMIFS(JV_Entries!$G:$G,JV_Entries!$E:$E,"DUKANDAR",JV_Entries!$F:$F,B29)-SUMIFS(JV_Entries!$G:$G,JV_Entries!$C:$C,"DUKANDAR",JV_Entries!$D:$D,B29) | I29: =IF(B29="","",F29-G29+H29)
A30: 27 | B30: =IF(Masters!$J$29="","",Masters!$J$29) | C30: =IF(B30="",0,Masters!$K$29) | D30: =SUMIF(Daily_Sales!$D:$D,B30,Daily_Sales!$G:$G) | E30: =SUMIF(Daily_Sales!$D:$D,B30,Daily_Sales!$H:$H) | F30: =IF(B30="","",D30-E30+C30) | G30: =SUMIFS(Cash_Book!$G:$G,Cash_Book!$C:$C,"DUKANDAR",Cash_Book!$D:$D,"RECEIPT",Cash_Book!$E:$E,B30) | H30: =SUMIFS(JV_Entries!$G:$G,JV_Entries!$E:$E,"DUKANDAR",JV_Entries!$F:$F,B30)-SUMIFS(JV_Entries!$G:$G,JV_Entries!$C:$C,"DUKANDAR",JV_Entries!$D:$D,B30) | I30: =IF(B30="","",F30-G30+H30)
A31: 28 | B31: =IF(Masters!$J$30="","",Masters!$J$30) | C31: =IF(B31="",0,Masters!$K$30) | D31: =SUMIF(Daily_Sales!$D:$D,B31,Daily_Sales!$G:$G) | E31: =SUMIF(Daily_Sales!$D:$D,B31,Daily_Sales!$H:$H) | F31: =IF(B31="","",D31-E31+C31) | G31: =SUMIFS(Cash_Book!$G:$G,Cash_Book!$C:$C,"DUKANDAR",Cash_Book!$D:$D,"RECEIPT",Cash_Book!$E:$E,B31) | H31: =SUMIFS(JV_Entries!$G:$G,JV_Entries!$E:$E,"DUKANDAR",JV_Entries!$F:$F,B31)-SUMIFS(JV_Entries!$G:$G,JV_Entries!$C:$C,"DUKANDAR",JV_Entries!$D:$D,B31) | I31: =IF(B31="","",F31-G31+H31)
A32: 29 | B32: =IF(Masters!$J$31="","",Masters!$J$31) | C32: =IF(B32="",0,Masters!$K$31) | D32: =SUMIF(Daily_Sales!$D:$D,B32,Daily_Sales!$G:$G) | E32: =SUMIF(Daily_Sales!$D:$D,B32,Daily_Sales!$H:$H) | F32: =IF(B32="","",D32-E32+C32) | G32: =SUMIFS(Cash_Book!$G:$G,Cash_Book!$C:$C,"DUKANDAR",Cash_Book!$D:$D,"RECEIPT",Cash_Book!$E:$E,B32) | H32: =SUMIFS(JV_Entries!$G:$G,JV_Entries!$E:$E,"DUKANDAR",JV_Entries!$F:$F,B32)-SUMIFS(JV_Entries!$G:$G,JV_Entries!$C:$C,"DUKANDAR",JV_Entries!$D:$D,B32) | I32: =IF(B32="","",F32-G32+H32)
A33: 30 | B33: =IF(Masters!$J$32="","",Masters!$J$32) | C33: =IF(B33="",0,Masters!$K$32) | D33: =SUMIF(Daily_Sales!$D:$D,B33,Daily_Sales!$G:$G) | E33: =SUMIF(Daily_Sales!$D:$D,B33,Daily_Sales!$H:$H) | F33: =IF(B33="","",D33-E33+C33) | G33: =SUMIFS(Cash_Book!$G:$G,Cash_Book!$C:$C,"DUKANDAR",Cash_Book!$D:$D,"RECEIPT",Cash_Book!$E:$E,B33) | H33: =SUMIFS(JV_Entries!$G:$G,JV_Entries!$E:$E,"DUKANDAR",JV_Entries!$F:$F,B33)-SUMIFS(JV_Entries!$G:$G,JV_Entries!$C:$C,"DUKANDAR",JV_Entries!$D:$D,B33) | I33: =IF(B33="","",F33-G33+H33)
A34: 31 | B34: =IF(Masters!$J$33="","",Masters!$J$33) | C34: =IF(B34="",0,Masters!$K$33) | D34: =SUMIF(Daily_Sales!$D:$D,B34,Daily_Sales!$G:$G) | E34: =SUMIF(Daily_Sales!$D:$D,B34,Daily_Sales!$H:$H) | F34: =IF(B34="","",D34-E34+C34) | G34: =SUMIFS(Cash_Book!$G:$G,Cash_Book!$C:$C,"DUKANDAR",Cash_Book!$D:$D,"RECEIPT",Cash_Book!$E:$E,B34) | H34: =SUMIFS(JV_Entries!$G:$G,JV_Entries!$E:$E,"DUKANDAR",JV_Entries!$F:$F,B34)-SUMIFS(JV_Entries!$G:$G,JV_Entries!$C:$C,"DUKANDAR",JV_Entries!$D:$D,B34) | I34: =IF(B34="","",F34-G34+H34)
A35: 32 | B35: =IF(Masters!$J$34="","",Masters!$J$34) | C35: =IF(B35="",0,Masters!$K$34) | D35: =SUMIF(Daily_Sales!$D:$D,B35,Daily_Sales!$G:$G) | E35: =SUMIF(Daily_Sales!$D:$D,B35,Daily_Sales!$H:$H) | F35: =IF(B35="","",D35-E35+C35) | G35: =SUMIFS(Cash_Book!$G:$G,Cash_Book!$C:$C,"DUKANDAR",Cash_Book!$D:$D,"RECEIPT",Cash_Book!$E:$E,B35) | H35: =SUMIFS(JV_Entries!$G:$G,JV_Entries!$E:$E,"DUKANDAR",JV_Entries!$F:$F,B35)-SUMIFS(JV_Entries!$G:$G,JV_Entries!$C:$C,"DUKANDAR",JV_Entries!$D:$D,B35) | I35: =IF(B35="","",F35-G35+H35)
A36: 33 | B36: =IF(Masters!$J$35="","",Masters!$J$35) | C36: =IF(B36="",0,Masters!$K$35) | D36: =SUMIF(Daily_Sales!$D:$D,B36,Daily_Sales!$G:$G) | E36: =SUMIF(Daily_Sales!$D:$D,B36,Daily_Sales!$H:$H) | F36: =IF(B36="","",D36-E36+C36) | G36: =SUMIFS(Cash_Book!$G:$G,Cash_Book!$C:$C,"DUKANDAR",Cash_Book!$D:$D,"RECEIPT",Cash_Book!$E:$E,B36) | H36: =SUMIFS(JV_Entries!$G:$G,JV_Entries!$E:$E,"DUKANDAR",JV_Entries!$F:$F,B36)-SUMIFS(JV_Entries!$G:$G,JV_Entries!$C:$C,"DUKANDAR",JV_Entries!$D:$D,B36) | I36: =IF(B36="","",F36-G36+H36)
A37: 34 | B37: =IF(Masters!$J$36="","",Masters!$J$36) | C37: =IF(B37="",0,Masters!$K$36) | D37: =SUMIF(Daily_Sales!$D:$D,B37,Daily_Sales!$G:$G) | E37: =SUMIF(Daily_Sales!$D:$D,B37,Daily_Sales!$H:$H) | F37: =IF(B37="","",D37-E37+C37) | G37: =SUMIFS(Cash_Book!$G:$G,Cash_Book!$C:$C,"DUKANDAR",Cash_Book!$D:$D,"RECEIPT",Cash_Book!$E:$E,B37) | H37: =SUMIFS(JV_Entries!$G:$G,JV_Entries!$E:$E,"DUKANDAR",JV_Entries!$F:$F,B37)-SUMIFS(JV_Entries!$G:$G,JV_Entries!$C:$C,"DUKANDAR",JV_Entries!$D:$D,B37) | I37: =IF(B37="","",F37-G37+H37)
A38: 35 | B38: =IF(Masters!$J$37="","",Masters!$J$37) | C38: =IF(B38="",0,Masters!$K$37) | D38: =SUMIF(Daily_Sales!$D:$D,B38,Daily_Sales!$G:$G) | E38: =SUMIF(Daily_Sales!$D:$D,B38,Daily_Sales!$H:$H) | F38: =IF(B38="","",D38-E38+C38) | G38: =SUMIFS(Cash_Book!$G:$G,Cash_Book!$C:$C,"DUKANDAR",Cash_Book!$D:$D,"RECEIPT",Cash_Book!$E:$E,B38) | H38: =SUMIFS(JV_Entries!$G:$G,JV_Entries!$E:$E,"DUKANDAR",JV_Entries!$F:$F,B38)-SUMIFS(JV_Entries!$G:$G,JV_Entries!$C:$C,"DUKANDAR",JV_Entries!$D:$D,B38) | I38: =IF(B38="","",F38-G38+H38)
A39: 36 | B39: =IF(Masters!$J$38="","",Masters!$J$38) | C39: =IF(B39="",0,Masters!$K$38) | D39: =SUMIF(Daily_Sales!$D:$D,B39,Daily_Sales!$G:$G) | E39: =SUMIF(Daily_Sales!$D:$D,B39,Daily_Sales!$H:$H) | F39: =IF(B39="","",D39-E39+C39) | G39: =SUMIFS(Cash_Book!$G:$G,Cash_Book!$C:$C,"DUKANDAR",Cash_Book!$D:$D,"RECEIPT",Cash_Book!$E:$E,B39) | H39: =SUMIFS(JV_Entries!$G:$G,JV_Entries!$E:$E,"DUKANDAR",JV_Entries!$F:$F,B39)-SUMIFS(JV_Entries!$G:$G,JV_Entries!$C:$C,"DUKANDAR",JV_Entries!$D:$D,B39) | I39: =IF(B39="","",F39-G39+H39)
A40: 37 | B40: =IF(Masters!$J$39="","",Masters!$J$39) | C40: =IF(B40="",0,Masters!$K$39) | D40: =SUMIF(Daily_Sales!$D:$D,B40,Daily_Sales!$G:$G) | E40: =SUMIF(Daily_Sales!$D:$D,B40,Daily_Sales!$H:$H) | F40: =IF(B40="","",D40-E40+C40) | G40: =SUMIFS(Cash_Book!$G:$G,Cash_Book!$C:$C,"DUKANDAR",Cash_Book!$D:$D,"RECEIPT",Cash_Book!$E:$E,B40) | H40: =SUMIFS(JV_Entries!$G:$G,JV_Entries!$E:$E,"DUKANDAR",JV_Entries!$F:$F,B40)-SUMIFS(JV_Entries!$G:$G,JV_Entries!$C:$C,"DUKANDAR",JV_Entries!$D:$D,B40) | I40: =IF(B40="","",F40-G40+H40)
A41: 38 | B41: =IF(Masters!$J$40="","",Masters!$J$40) | C41: =IF(B41="",0,Masters!$K$40) | D41: =SUMIF(Daily_Sales!$D:$D,B41,Daily_Sales!$G:$G) | E41: =SUMIF(Daily_Sales!$D:$D,B41,Daily_Sales!$H:$H) | F41: =IF(B41="","",D41-E41+C41) | G41: =SUMIFS(Cash_Book!$G:$G,Cash_Book!$C:$C,"DUKANDAR",Cash_Book!$D:$D,"RECEIPT",Cash_Book!$E:$E,B41) | H41: =SUMIFS(JV_Entries!$G:$G,JV_Entries!$E:$E,"DUKANDAR",JV_Entries!$F:$F,B41)-SUMIFS(JV_Entries!$G:$G,JV_Entries!$C:$C,"DUKANDAR",JV_Entries!$D:$D,B41) | I41: =IF(B41="","",F41-G41+H41)
A42: 39 | B42: =IF(Masters!$J$41="","",Masters!$J$41) | C42: =IF(B42="",0,Masters!$K$41) | D42: =SUMIF(Daily_Sales!$D:$D,B42,Daily_Sales!$G:$G) | E42: =SUMIF(Daily_Sales!$D:$D,B42,Daily_Sales!$H:$H) | F42: =IF(B42="","",D42-E42+C42) | G42: =SUMIFS(Cash_Book!$G:$G,Cash_Book!$C:$C,"DUKANDAR",Cash_Book!$D:$D,"RECEIPT",Cash_Book!$E:$E,B42) | H42: =SUMIFS(JV_Entries!$G:$G,JV_Entries!$E:$E,"DUKANDAR",JV_Entries!$F:$F,B42)-SUMIFS(JV_Entries!$G:$G,JV_Entries!$C:$C,"DUKANDAR",JV_Entries!$D:$D,B42) | I42: =IF(B42="","",F42-G42+H42)
A43: 40 | B43: =IF(Masters!$J$42="","",Masters!$J$42) | C43: =IF(B43="",0,Masters!$K$42) | D43: =SUMIF(Daily_Sales!$D:$D,B43,Daily_Sales!$G:$G) | E43: =SUMIF(Daily_Sales!$D:$D,B43,Daily_Sales!$H:$H) | F43: =IF(B43="","",D43-E43+C43) | G43: =SUMIFS(Cash_Book!$G:$G,Cash_Book!$C:$C,"DUKANDAR",Cash_Book!$D:$D,"RECEIPT",Cash_Book!$E:$E,B43) | H43: =SUMIFS(JV_Entries!$G:$G,JV_Entries!$E:$E,"DUKANDAR",JV_Entries!$F:$F,B43)-SUMIFS(JV_Entries!$G:$G,JV_Entries!$C:$C,"DUKANDAR",JV_Entries!$D:$D,B43) | I43: =IF(B43="","",F43-G43+H43)
A44: 41 | B44: =IF(Masters!$J$43="","",Masters!$J$43) | C44: =IF(B44="",0,Masters!$K$43) | D44: =SUMIF(Daily_Sales!$D:$D,B44,Daily_Sales!$G:$G) | E44: =SUMIF(Daily_Sales!$D:$D,B44,Daily_Sales!$H:$H) | F44: =IF(B44="","",D44-E44+C44) | G44: =SUMIFS(Cash_Book!$G:$G,Cash_Book!$C:$C,"DUKANDAR",Cash_Book!$D:$D,"RECEIPT",Cash_Book!$E:$E,B44) | H44: =SUMIFS(JV_Entries!$G:$G,JV_Entries!$E:$E,"DUKANDAR",JV_Entries!$F:$F,B44)-SUMIFS(JV_Entries!$G:$G,JV_Entries!$C:$C,"DUKANDAR",JV_Entries!$D:$D,B44) | I44: =IF(B44="","",F44-G44+H44)
A45: 42 | B45: =IF(Masters!$J$44="","",Masters!$J$44) | C45: =IF(B45="",0,Masters!$K$44) | D45: =SUMIF(Daily_Sales!$D:$D,B45,Daily_Sales!$G:$G) | E45: =SUMIF(Daily_Sales!$D:$D,B45,Daily_Sales!$H:$H) | F45: =IF(B45="","",D45-E45+C45) | G45: =SUMIFS(Cash_Book!$G:$G,Cash_Book!$C:$C,"DUKANDAR",Cash_Book!$D:$D,"RECEIPT",Cash_Book!$E:$E,B45) | H45: =SUMIFS(JV_Entries!$G:$G,JV_Entries!$E:$E,"DUKANDAR",JV_Entries!$F:$F,B45)-SUMIFS(JV_Entries!$G:$G,JV_Entries!$C:$C,"DUKANDAR",JV_Entries!$D:$D,B45) | I45: =IF(B45="","",F45-G45+H45)
A46: 43 | B46: =IF(Masters!$J$45="","",Masters!$J$45) | C46: =IF(B46="",0,Masters!$K$45) | D46: =SUMIF(Daily_Sales!$D:$D,B46,Daily_Sales!$G:$G) | E46: =SUMIF(Daily_Sales!$D:$D,B46,Daily_Sales!$H:$H) | F46: =IF(B46="","",D46-E46+C46) | G46: =SUMIFS(Cash_Book!$G:$G,Cash_Book!$C:$C,"DUKANDAR",Cash_Book!$D:$D,"RECEIPT",Cash_Book!$E:$E,B46) | H46: =SUMIFS(JV_Entries!$G:$G,JV_Entries!$E:$E,"DUKANDAR",JV_Entries!$F:$F,B46)-SUMIFS(JV_Entries!$G:$G,JV_Entries!$C:$C,"DUKANDAR",JV_Entries!$D:$D,B46) | I46: =IF(B46="","",F46-G46+H46)
A47: 44 | B47: =IF(Masters!$J$46="","",Masters!$J$46) | C47: =IF(B47="",0,Masters!$K$46) | D47: =SUMIF(Daily_Sales!$D:$D,B47,Daily_Sales!$G:$G) | E47: =SUMIF(Daily_Sales!$D:$D,B47,Daily_Sales!$H:$H) | F47: =IF(B47="","",D47-E47+C47) | G47: =SUMIFS(Cash_Book!$G:$G,Cash_Book!$C:$C,"DUKANDAR",Cash_Book!$D:$D,"RECEIPT",Cash_Book!$E:$E,B47) | H47: =SUMIFS(JV_Entries!$G:$G,JV_Entries!$E:$E,"DUKANDAR",JV_Entries!$F:$F,B47)-SUMIFS(JV_Entries!$G:$G,JV_Entries!$C:$C,"DUKANDAR",JV_Entries!$D:$D,B47) | I47: =IF(B47="","",F47-G47+H47)
A48: 45 | B48: =IF(Masters!$J$47="","",Masters!$J$47) | C48: =IF(B48="",0,Masters!$K$47) | D48: =SUMIF(Daily_Sales!$D:$D,B48,Daily_Sales!$G:$G) | E48: =SUMIF(Daily_Sales!$D:$D,B48,Daily_Sales!$H:$H) | F48: =IF(B48="","",D48-E48+C48) | G48: =SUMIFS(Cash_Book!$G:$G,Cash_Book!$C:$C,"DUKANDAR",Cash_Book!$D:$D,"RECEIPT",Cash_Book!$E:$E,B48) | H48: =SUMIFS(JV_Entries!$G:$G,JV_Entries!$E:$E,"DUKANDAR",JV_Entries!$F:$F,B48)-SUMIFS(JV_Entries!$G:$G,JV_Entries!$C:$C,"DUKANDAR",JV_Entries!$D:$D,B48) | I48: =IF(B48="","",F48-G48+H48)
A49: 46 | B49: =IF(Masters!$J$48="","",Masters!$J$48) | C49: =IF(B49="",0,Masters!$K$48) | D49: =SUMIF(Daily_Sales!$D:$D,B49,Daily_Sales!$G:$G) | E49: =SUMIF(Daily_Sales!$D:$D,B49,Daily_Sales!$H:$H) | F49: =IF(B49="","",D49-E49+C49) | G49: =SUMIFS(Cash_Book!$G:$G,Cash_Book!$C:$C,"DUKANDAR",Cash_Book!$D:$D,"RECEIPT",Cash_Book!$E:$E,B49) | H49: =SUMIFS(JV_Entries!$G:$G,JV_Entries!$E:$E,"DUKANDAR",JV_Entries!$F:$F,B49)-SUMIFS(JV_Entries!$G:$G,JV_Entries!$C:$C,"DUKANDAR",JV_Entries!$D:$D,B49) | I49: =IF(B49="","",F49-G49+H49)
A50: 47 | B50: =IF(Masters!$J$49="","",Masters!$J$49) | C50: =IF(B50="",0,Masters!$K$49) | D50: =SUMIF(Daily_Sales!$D:$D,B50,Daily_Sales!$G:$G) | E50: =SUMIF(Daily_Sales!$D:$D,B50,Daily_Sales!$H:$H) | F50: =IF(B50="","",D50-E50+C50) | G50: =SUMIFS(Cash_Book!$G:$G,Cash_Book!$C:$C,"DUKANDAR",Cash_Book!$D:$D,"RECEIPT",Cash_Book!$E:$E,B50) | H50: =SUMIFS(JV_Entries!$G:$G,JV_Entries!$E:$E,"DUKANDAR",JV_Entries!$F:$F,B50)-SUMIFS(JV_Entries!$G:$G,JV_Entries!$C:$C,"DUKANDAR",JV_Entries!$D:$D,B50) | I50: =IF(B50="","",F50-G50+H50)
A51: 48 | B51: =IF(Masters!$J$50="","",Masters!$J$50) | C51: =IF(B51="",0,Masters!$K$50) | D51: =SUMIF(Daily_Sales!$D:$D,B51,Daily_Sales!$G:$G) | E51: =SUMIF(Daily_Sales!$D:$D,B51,Daily_Sales!$H:$H) | F51: =IF(B51="","",D51-E51+C51) | G51: =SUMIFS(Cash_Book!$G:$G,Cash_Book!$C:$C,"DUKANDAR",Cash_Book!$D:$D,"RECEIPT",Cash_Book!$E:$E,B51) | H51: =SUMIFS(JV_Entries!$G:$G,JV_Entries!$E:$E,"DUKANDAR",JV_Entries!$F:$F,B51)-SUMIFS(JV_Entries!$G:$G,JV_Entries!$C:$C,"DUKANDAR",JV_Entries!$D:$D,B51) | I51: =IF(B51="","",F51-G51+H51)
A52: 49 | B52: =IF(Masters!$J$51="","",Masters!$J$51) | C52: =IF(B52="",0,Masters!$K$51) | D52: =SUMIF(Daily_Sales!$D:$D,B52,Daily_Sales!$G:$G) | E52: =SUMIF(Daily_Sales!$D:$D,B52,Daily_Sales!$H:$H) | F52: =IF(B52="","",D52-E52+C52) | G52: =SUMIFS(Cash_Book!$G:$G,Cash_Book!$C:$C,"DUKANDAR",Cash_Book!$D:$D,"RECEIPT",Cash_Book!$E:$E,B52) | H52: =SUMIFS(JV_Entries!$G:$G,JV_Entries!$E:$E,"DUKANDAR",JV_Entries!$F:$F,B52)-SUMIFS(JV_Entries!$G:$G,JV_Entries!$C:$C,"DUKANDAR",JV_Entries!$D:$D,B52) | I52: =IF(B52="","",F52-G52+H52)
A53: 50 | B53: =IF(Masters!$J$52="","",Masters!$J$52) | C53: =IF(B53="",0,Masters!$K$52) | D53: =SUMIF(Daily_Sales!$D:$D,B53,Daily_Sales!$G:$G) | E53: =SUMIF(Daily_Sales!$D:$D,B53,Daily_Sales!$H:$H) | F53: =IF(B53="","",D53-E53+C53) | G53: =SUMIFS(Cash_Book!$G:$G,Cash_Book!$C:$C,"DUKANDAR",Cash_Book!$D:$D,"RECEIPT",Cash_Book!$E:$E,B53) | H53: =SUMIFS(JV_Entries!$G:$G,JV_Entries!$E:$E,"DUKANDAR",JV_Entries!$F:$F,B53)-SUMIFS(JV_Entries!$G:$G,JV_Entries!$C:$C,"DUKANDAR",JV_Entries!$D:$D,B53) | I53: =IF(B53="","",F53-G53+H53)
A54: TOTAL | B54: PATTI | C54: =SUM(C4:C53) | D54: =SUM(D4:D53) | E54: =SUM(E4:E53) | F54: =SUM(F4:F53) | G54: =SUM(G4:G53) | H54: =SUM(H4:H53) | I54: =SUM(I4:I53)
E56: For Balance Sheet:
F57: Dukandar Receivable (they owe) | I57: =SUMIF(I4:I53,">0",I4:I53)
F58: Dukandar Overpaid (we owe) | I58: =-SUMIF(I4:I53,"<0",I4:I53)

Sheet Capital_Loan_Ledger
A1: CAPITAL & LOAN LEDGER (All Investors/Lenders)
A3: Sr | B3: Party Name | C3: Type | D3: Opening Bal | E3: Taken (+) | F3: Withdrawn/Repaid (-) | G3: CURRENT BALANCE
A4: 1 | B4: =IF(Masters!$P$3="","",Masters!$P$3) | C4: =IF(B4="","",Masters!$R$3) | D4: =IF(B4="",0,Masters!$Q$3) | E4: =IF(B4="",0,SUMIFS(Cash_Book!$G:$G,Cash_Book!$C:$C,C4,Cash_Book!$D:$D,"TAKEN",Cash_Book!$E:$E,B4)+SUMIFS(Cash_Book!$G:$G,Cash_Book!$C:$C,C4,Cash_Book!$D:$D,"PROFIT_TO_CAP",Cash_Book!$E:$E,B4)) | F4: =IF(B4="",0,SUMIFS(Cash_Book!$G:$G,Cash_Book!$C:$C,C4,Cash_Book!$D:$D,"WITHDRAWN",Cash_Book!$E:$E,B4)+SUMIFS(Cash_Book!$G:$G,Cash_Book!$C:$C,C4,Cash_Book!$D:$D,"REPAID",Cash_Book!$E:$E,B4)) | G4: =IF(B4="","",D4+E4-F4)
A5: 2 | B5: =IF(Masters!$P$4="","",Masters!$P$4) | C5: =IF(B5="","",Masters!$R$4) | D5: =IF(B5="",0,Masters!$Q$4) | E5: =IF(B5="",0,SUMIFS(Cash_Book!$G:$G,Cash_Book!$C:$C,C5,Cash_Book!$D:$D,"TAKEN",Cash_Book!$E:$E,B5)+SUMIFS(Cash_Book!$G:$G,Cash_Book!$C:$C,C5,Cash_Book!$D:$D,"PROFIT_TO_CAP",Cash_Book!$E:$E,B5)) | F5: =IF(B5="",0,SUMIFS(Cash_Book!$G:$G,Cash_Book!$C:$C,C5,Cash_Book!$D:$D,"WITHDRAWN",Cash_Book!$E:$E,B5)+SUMIFS(Cash_Book!$G:$G,Cash_Book!$C:$C,C5,Cash_Book!$D:$D,"REPAID",Cash_Book!$E:$E,B5)) | G5: =IF(B5="","",D5+E5-F5)
A6: 3 | B6: =IF(Masters!$P$5="","",Masters!$P$5) | C6: =IF(B6="","",Masters!$R$5) | D6: =IF(B6="",0,Masters!$Q$5) | E6: =IF(B6="",0,SUMIFS(Cash_Book!$G:$G,Cash_Book!$C:$C,C6,Cash_Book!$D:$D,"TAKEN",Cash_Book!$E:$E,B6)+SUMIFS(Cash_Book!$G:$G,Cash_Book!$C:$C,C6,Cash_Book!$D:$D,"PROFIT_TO_CAP",Cash_Book!$E:$E,B6)) | F6: =IF(B6="",0,SUMIFS(Cash_Book!$G:$G,Cash_Book!$C:$C,C6,Cash_Book!$D:$D,"WITHDRAWN",Cash_Book!$E:$E,B6)+SUMIFS(Cash_Book!$G:$G,Cash_Book!$C:$C,C6,Cash_Book!$D:$D,"REPAID",Cash_Book!$E:$E,B6)) | G6: =IF(B6="","",D6+E6-F6)
A7: 4 | B7: =IF(Masters!$P$6="","",Masters!$P$6) | C7: =IF(B7="","",Masters!$R$6) | D7: =IF(B7="",0,Masters!$Q$6) | E7: =IF(B7="",0,SUMIFS(Cash_Book!$G:$G,Cash_Book!$C:$C,C7,Cash_Book!$D:$D,"TAKEN",Cash_Book!$E:$E,B7)+SUMIFS(Cash_Book!$G:$G,Cash_Book!$C:$C,C7,Cash_Book!$D:$D,"PROFIT_TO_CAP",Cash_Book!$E:$E,B7)) | F7: =IF(B7="",0,SUMIFS(Cash_Book!$G:$G,Cash_Book!$C:$C,C7,Cash_Book!$D:$D,"WITHDRAWN",Cash_Book!$E:$E,B7)+SUMIFS(Cash_Book!$G:$G,Cash_Book!$C:$C,C7,Cash_Book!$D:$D,"REPAID",Cash_Book!$E:$E,B7)) | G7: =IF(B7="","",D7+E7-F7)
A8: 5 | B8: =IF(Masters!$P$7="","",Masters!$P$7) | C8: =IF(B8="","",Masters!$R$7) | D8: =IF(B8="",0,Masters!$Q$7) | E8: =IF(B8="",0,SUMIFS(Cash_Book!$G:$G,Cash_Book!$C:$C,C8,Cash_Book!$D:$D,"TAKEN",Cash_Book!$E:$E,B8)+SUMIFS(Cash_Book!$G:$G,Cash_Book!$C:$C,C8,Cash_Book!$D:$D,"PROFIT_TO_CAP",Cash_Book!$E:$E,B8)) | F8: =IF(B8="",0,SUMIFS(Cash_Book!$G:$G,Cash_Book!$C:$C,C8,Cash_Book!$D:$D,"WITHDRAWN",Cash_Book!$E:$E,B8)+SUMIFS(Cash_Book!$G:$G,Cash_Book!$C:$C,C8,Cash_Book!$D:$D,"REPAID",Cash_Book!$E:$E,B8)) | G8: =IF(B8="","",D8+E8-F8)
A9: 6 | B9: =IF(Masters!$P$8="","",Masters!$P$8) | C9: =IF(B9="","",Masters!$R$8) | D9: =IF(B9="",0,Masters!$Q$8) | E9: =IF(B9="",0,SUMIFS(Cash_Book!$G:$G,Cash_Book!$C:$C,C9,Cash_Book!$D:$D,"TAKEN",Cash_Book!$E:$E,B9)+SUMIFS(Cash_Book!$G:$G,Cash_Book!$C:$C,C9,Cash_Book!$D:$D,"PROFIT_TO_CAP",Cash_Book!$E:$E,B9)) | F9: =IF(B9="",0,SUMIFS(Cash_Book!$G:$G,Cash_Book!$C:$C,C9,Cash_Book!$D:$D,"WITHDRAWN",Cash_Book!$E:$E,B9)+SUMIFS(Cash_Book!$G:$G,Cash_Book!$C:$C,C9,Cash_Book!$D:$D,"REPAID",Cash_Book!$E:$E,B9)) | G9: =IF(B9="","",D9+E9-F9)
A10: 7 | B10: =IF(Masters!$P$9="","",Masters!$P$9) | C10: =IF(B10="","",Masters!$R$9) | D10: =IF(B10="",0,Masters!$Q$9) | E10: =IF(B10="",0,SUMIFS(Cash_Book!$G:$G,Cash_Book!$C:$C,C10,Cash_Book!$D:$D,"TAKEN",Cash_Book!$E:$E,B10)+SUMIFS(Cash_Book!$G:$G,Cash_Book!$C:$C,C10,Cash_Book!$D:$D,"PROFIT_TO_CAP",Cash_Book!$E:$E,B10)) | F10: =IF(B10="",0,SUMIFS(Cash_Book!$G:$G,Cash_Book!$C:$C,C10,Cash_Book!$D:$D,"WITHDRAWN",Cash_Book!$E:$E,B10)+SUMIFS(Cash_Book!$G:$G,Cash_Book!$C:$C,C10,Cash_Book!$D:$D,"REPAID",Cash_Book!$E:$E,B10)) | G10: =IF(B10="","",D10+E10-F10)
A11: 8 | B11: =IF(Masters!$P$10="","",Masters!$P$10) | C11: =IF(B11="","",Masters!$R$10) | D11: =IF(B11="",0,Masters!$Q$10) | E11: =IF(B11="",0,SUMIFS(Cash_Book!$G:$G,Cash_Book!$C:$C,C11,Cash_Book!$D:$D,"TAKEN",Cash_Book!$E:$E,B11)+SUMIFS(Cash_Book!$G:$G,Cash_Book!$C:$C,C11,Cash_Book!$D:$D,"PROFIT_TO_CAP",Cash_Book!$E:$E,B11)) | F11: =IF(B11="",0,SUMIFS(Cash_Book!$G:$G,Cash_Book!$C:$C,C11,Cash_Book!$D:$D,"WITHDRAWN",Cash_Book!$E:$E,B11)+SUMIFS(Cash_Book!$G:$G,Cash_Book!$C:$C,C11,Cash_Book!$D:$D,"REPAID",Cash_Book!$E:$E,B11)) | G11: =IF(B11="","",D11+E11-F11)
A12: 9 | B12: =IF(Masters!$P$11="","",Masters!$P$11) | C12: =IF(B12="","",Masters!$R$11) | D12: =IF(B12="",0,Masters!$Q$11) | E12: =IF(B12="",0,SUMIFS(Cash_Book!$G:$G,Cash_Book!$C:$C,C12,Cash_Book!$D:$D,"TAKEN",Cash_Book!$E:$E,B12)+SUMIFS(Cash_Book!$G:$G,Cash_Book!$C:$C,C12,Cash_Book!$D:$D,"PROFIT_TO_CAP",Cash_Book!$E:$E,B12)) | F12: =IF(B12="",0,SUMIFS(Cash_Book!$G:$G,Cash_Book!$C:$C,C12,Cash_Book!$D:$D,"WITHDRAWN",Cash_Book!$E:$E,B12)+SUMIFS(Cash_Book!$G:$G,Cash_Book!$C:$C,C12,Cash_Book!$D:$D,"REPAID",Cash_Book!$E:$E,B12)) | G12: =IF(B12="","",D12+E12-F12)
A13: 10 | B13: =IF(Masters!$P$12="","",Masters!$P$12) | C13: =IF(B13="","",Masters!$R$12) | D13: =IF(B13="",0,Masters!$Q$12) | E13: =IF(B13="",0,SUMIFS(Cash_Book!$G:$G,Cash_Book!$C:$C,C13,Cash_Book!$D:$D,"TAKEN",Cash_Book!$E:$E,B13)+SUMIFS(Cash_Book!$G:$G,Cash_Book!$C:$C,C13,Cash_Book!$D:$D,"PROFIT_TO_CAP",Cash_Book!$E:$E,B13)) | F13: =IF(B13="",0,SUMIFS(Cash_Book!$G:$G,Cash_Book!$C:$C,C13,Cash_Book!$D:$D,"WITHDRAWN",Cash_Book!$E:$E,B13)+SUMIFS(Cash_Book!$G:$G,Cash_Book!$C:$C,C13,Cash_Book!$D:$D,"REPAID",Cash_Book!$E:$E,B13)) | G13: =IF(B13="","",D13+E13-F13)
A14: 11 | B14: =IF(Masters!$P$13="","",Masters!$P$13) | C14: =IF(B14="","",Masters!$R$13) | D14: =IF(B14="",0,Masters!$Q$13) | E14: =IF(B14="",0,SUMIFS(Cash_Book!$G:$G,Cash_Book!$C:$C,C14,Cash_Book!$D:$D,"TAKEN",Cash_Book!$E:$E,B14)+SUMIFS(Cash_Book!$G:$G,Cash_Book!$C:$C,C14,Cash_Book!$D:$D,"PROFIT_TO_CAP",Cash_Book!$E:$E,B14)) | F14: =IF(B14="",0,SUMIFS(Cash_Book!$G:$G,Cash_Book!$C:$C,C14,Cash_Book!$D:$D,"WITHDRAWN",Cash_Book!$E:$E,B14)+SUMIFS(Cash_Book!$G:$G,Cash_Book!$C:$C,C14,Cash_Book!$D:$D,"REPAID",Cash_Book!$E:$E,B14)) | G14: =IF(B14="","",D14+E14-F14)
A15: 12 | B15: =IF(Masters!$P$14="","",Masters!$P$14) | C15: =IF(B15="","",Masters!$R$14) | D15: =IF(B15="",0,Masters!$Q$14) | E15: =IF(B15="",0,SUMIFS(Cash_Book!$G:$G,Cash_Book!$C:$C,C15,Cash_Book!$D:$D,"TAKEN",Cash_Book!$E:$E,B15)+SUMIFS(Cash_Book!$G:$G,Cash_Book!$C:$C,C15,Cash_Book!$D:$D,"PROFIT_TO_CAP",Cash_Book!$E:$E,B15)) | F15: =IF(B15="",0,SUMIFS(Cash_Book!$G:$G,Cash_Book!$C:$C,C15,Cash_Book!$D:$D,"WITHDRAWN",Cash_Book!$E:$E,B15)+SUMIFS(Cash_Book!$G:$G,Cash_Book!$C:$C,C15,Cash_Book!$D:$D,"REPAID",Cash_Book!$E:$E,B15)) | G15: =IF(B15="","",D15+E15-F15)
A16: 13 | B16: =IF(Masters!$P$15="","",Masters!$P$15) | C16: =IF(B16="","",Masters!$R$15) | D16: =IF(B16="",0,Masters!$Q$15) | E16: =IF(B16="",0,SUMIFS(Cash_Book!$G:$G,Cash_Book!$C:$C,C16,Cash_Book!$D:$D,"TAKEN",Cash_Book!$E:$E,B16)+SUMIFS(Cash_Book!$G:$G,Cash_Book!$C:$C,C16,Cash_Book!$D:$D,"PROFIT_TO_CAP",Cash_Book!$E:$E,B16)) | F16: =IF(B16="",0,SUMIFS(Cash_Book!$G:$G,Cash_Book!$C:$C,C16,Cash_Book!$D:$D,"WITHDRAWN",Cash_Book!$E:$E,B16)+SUMIFS(Cash_Book!$G:$G,Cash_Book!$C:$C,C16,Cash_Book!$D:$D,"REPAID",Cash_Book!$E:$E,B16)) | G16: =IF(B16="","",D16+E16-F16)
A17: 14 | B17: =IF(Masters!$P$16="","",Masters!$P$16) | C17: =IF(B17="","",Masters!$R$16) | D17: =IF(B17="",0,Masters!$Q$16) | E17: =IF(B17="",0,SUMIFS(Cash_Book!$G:$G,Cash_Book!$C:$C,C17,Cash_Book!$D:$D,"TAKEN",Cash_Book!$E:$E,B17)+SUMIFS(Cash_Book!$G:$G,Cash_Book!$C:$C,C17,Cash_Book!$D:$D,"PROFIT_TO_CAP",Cash_Book!$E:$E,B17)) | F17: =IF(B17="",0,SUMIFS(Cash_Book!$G:$G,Cash_Book!$C:$C,C17,Cash_Book!$D:$D,"WITHDRAWN",Cash_Book!$E:$E,B17)+SUMIFS(Cash_Book!$G:$G,Cash_Book!$C:$C,C17,Cash_Book!$D:$D,"REPAID",Cash_Book!$E:$E,B17)) | G17: =IF(B17="","",D17+E17-F17)
A18: 15 | B18: =IF(Masters!$P$17="","",Masters!$P$17) | C18: =IF(B18="","",Masters!$R$17) | D18: =IF(B18="",0,Masters!$Q$17) | E18: =IF(B18="",0,SUMIFS(Cash_Book!$G:$G,Cash_Book!$C:$C,C18,Cash_Book!$D:$D,"TAKEN",Cash_Book!$E:$E,B18)+SUMIFS(Cash_Book!$G:$G,Cash_Book!$C:$C,C18,Cash_Book!$D:$D,"PROFIT_TO_CAP",Cash_Book!$E:$E,B18)) | F18: =IF(B18="",0,SUMIFS(Cash_Book!$G:$G,Cash_Book!$C:$C,C18,Cash_Book!$D:$D,"WITHDRAWN",Cash_Book!$E:$E,B18)+SUMIFS(Cash_Book!$G:$G,Cash_Book!$C:$C,C18,Cash_Book!$D:$D,"REPAID",Cash_Book!$E:$E,B18)) | G18: =IF(B18="","",D18+E18-F18)
A19: 16 | B19: =IF(Masters!$P$18="","",Masters!$P$18) | C19: =IF(B19="","",Masters!$R$18) | D19: =IF(B19="",0,Masters!$Q$18) | E19: =IF(B19="",0,SUMIFS(Cash_Book!$G:$G,Cash_Book!$C:$C,C19,Cash_Book!$D:$D,"TAKEN",Cash_Book!$E:$E,B19)+SUMIFS(Cash_Book!$G:$G,Cash_Book!$C:$C,C19,Cash_Book!$D:$D,"PROFIT_TO_CAP",Cash_Book!$E:$E,B19)) | F19: =IF(B19="",0,SUMIFS(Cash_Book!$G:$G,Cash_Book!$C:$C,C19,Cash_Book!$D:$D,"WITHDRAWN",Cash_Book!$E:$E,B19)+SUMIFS(Cash_Book!$G:$G,Cash_Book!$C:$C,C19,Cash_Book!$D:$D,"REPAID",Cash_Book!$E:$E,B19)) | G19: =IF(B19="","",D19+E19-F19)
A20: 17 | B20: =IF(Masters!$P$19="","",Masters!$P$19) | C20: =IF(B20="","",Masters!$R$19) | D20: =IF(B20="",0,Masters!$Q$19) | E20: =IF(B20="",0,SUMIFS(Cash_Book!$G:$G,Cash_Book!$C:$C,C20,Cash_Book!$D:$D,"TAKEN",Cash_Book!$E:$E,B20)+SUMIFS(Cash_Book!$G:$G,Cash_Book!$C:$C,C20,Cash_Book!$D:$D,"PROFIT_TO_CAP",Cash_Book!$E:$E,B20)) | F20: =IF(B20="",0,SUMIFS(Cash_Book!$G:$G,Cash_Book!$C:$C,C20,Cash_Book!$D:$D,"WITHDRAWN",Cash_Book!$E:$E,B20)+SUMIFS(Cash_Book!$G:$G,Cash_Book!$C:$C,C20,Cash_Book!$D:$D,"REPAID",Cash_Book!$E:$E,B20)) | G20: =IF(B20="","",D20+E20-F20)
A21: 18 | B21: =IF(Masters!$P$20="","",Masters!$P$20) | C21: =IF(B21="","",Masters!$R$20) | D21: =IF(B21="",0,Masters!$Q$20) | E21: =IF(B21="",0,SUMIFS(Cash_Book!$G:$G,Cash_Book!$C:$C,C21,Cash_Book!$D:$D,"TAKEN",Cash_Book!$E:$E,B21)+SUMIFS(Cash_Book!$G:$G,Cash_Book!$C:$C,C21,Cash_Book!$D:$D,"PROFIT_TO_CAP",Cash_Book!$E:$E,B21)) | F21: =IF(B21="",0,SUMIFS(Cash_Book!$G:$G,Cash_Book!$C:$C,C21,Cash_Book!$D:$D,"WITHDRAWN",Cash_Book!$E:$E,B21)+SUMIFS(Cash_Book!$G:$G,Cash_Book!$C:$C,C21,Cash_Book!$D:$D,"REPAID",Cash_Book!$E:$E,B21)) | G21: =IF(B21="","",D21+E21-F21)
A22: 19 | B22: =IF(Masters!$P$21="","",Masters!$P$21) | C22: =IF(B22="","",Masters!$R$21) | D22: =IF(B22="",0,Masters!$Q$21) | E22: =IF(B22="",0,SUMIFS(Cash_Book!$G:$G,Cash_Book!$C:$C,C22,Cash_Book!$D:$D,"TAKEN",Cash_Book!$E:$E,B22)+SUMIFS(Cash_Book!$G:$G,Cash_Book!$C:$C,C22,Cash_Book!$D:$D,"PROFIT_TO_CAP",Cash_Book!$E:$E,B22)) | F22: =IF(B22="",0,SUMIFS(Cash_Book!$G:$G,Cash_Book!$C:$C,C22,Cash_Book!$D:$D,"WITHDRAWN",Cash_Book!$E:$E,B22)+SUMIFS(Cash_Book!$G:$G,Cash_Book!$C:$C,C22,Cash_Book!$D:$D,"REPAID",Cash_Book!$E:$E,B22)) | G22: =IF(B22="","",D22+E22-F22)
A23: 20 | B23: =IF(Masters!$P$22="","",Masters!$P$22) | C23: =IF(B23="","",Masters!$R$22) | D23: =IF(B23="",0,Masters!$Q$22) | E23: =IF(B23="",0,SUMIFS(Cash_Book!$G:$G,Cash_Book!$C:$C,C23,Cash_Book!$D:$D,"TAKEN",Cash_Book!$E:$E,B23)+SUMIFS(Cash_Book!$G:$G,Cash_Book!$C:$C,C23,Cash_Book!$D:$D,"PROFIT_TO_CAP",Cash_Book!$E:$E,B23)) | F23: =IF(B23="",0,SUMIFS(Cash_Book!$G:$G,Cash_Book!$C:$C,C23,Cash_Book!$D:$D,"WITHDRAWN",Cash_Book!$E:$E,B23)+SUMIFS(Cash_Book!$G:$G,Cash_Book!$C:$C,C23,Cash_Book!$D:$D,"REPAID",Cash_Book!$E:$E,B23)) | G23: =IF(B23="","",D23+E23-F23)
A24: 21 | B24: =IF(Masters!$P$23="","",Masters!$P$23) | C24: =IF(B24="","",Masters!$R$23) | D24: =IF(B24="",0,Masters!$Q$23) | E24: =IF(B24="",0,SUMIFS(Cash_Book!$G:$G,Cash_Book!$C:$C,C24,Cash_Book!$D:$D,"TAKEN",Cash_Book!$E:$E,B24)+SUMIFS(Cash_Book!$G:$G,Cash_Book!$C:$C,C24,Cash_Book!$D:$D,"PROFIT_TO_CAP",Cash_Book!$E:$E,B24)) | F24: =IF(B24="",0,SUMIFS(Cash_Book!$G:$G,Cash_Book!$C:$C,C24,Cash_Book!$D:$D,"WITHDRAWN",Cash_Book!$E:$E,B24)+SUMIFS(Cash_Book!$G:$G,Cash_Book!$C:$C,C24,Cash_Book!$D:$D,"REPAID",Cash_Book!$E:$E,B24)) | G24: =IF(B24="","",D24+E24-F24)
A25: 22 | B25: =IF(Masters!$P$24="","",Masters!$P$24) | C25: =IF(B25="","",Masters!$R$24) | D25: =IF(B25="",0,Masters!$Q$24) | E25: =IF(B25="",0,SUMIFS(Cash_Book!$G:$G,Cash_Book!$C:$C,C25,Cash_Book!$D:$D,"TAKEN",Cash_Book!$E:$E,B25)+SUMIFS(Cash_Book!$G:$G,Cash_Book!$C:$C,C25,Cash_Book!$D:$D,"PROFIT_TO_CAP",Cash_Book!$E:$E,B25)) | F25: =IF(B25="",0,SUMIFS(Cash_Book!$G:$G,Cash_Book!$C:$C,C25,Cash_Book!$D:$D,"WITHDRAWN",Cash_Book!$E:$E,B25)+SUMIFS(Cash_Book!$G:$G,Cash_Book!$C:$C,C25,Cash_Book!$D:$D,"REPAID",Cash_Book!$E:$E,B25)) | G25: =IF(B25="","",D25+E25-F25)
A26: 23 | B26: =IF(Masters!$P$25="","",Masters!$P$25) | C26: =IF(B26="","",Masters!$R$25) | D26: =IF(B26="",0,Masters!$Q$25) | E26: =IF(B26="",0,SUMIFS(Cash_Book!$G:$G,Cash_Book!$C:$C,C26,Cash_Book!$D:$D,"TAKEN",Cash_Book!$E:$E,B26)+SUMIFS(Cash_Book!$G:$G,Cash_Book!$C:$C,C26,Cash_Book!$D:$D,"PROFIT_TO_CAP",Cash_Book!$E:$E,B26)) | F26: =IF(B26="",0,SUMIFS(Cash_Book!$G:$G,Cash_Book!$C:$C,C26,Cash_Book!$D:$D,"WITHDRAWN",Cash_Book!$E:$E,B26)+SUMIFS(Cash_Book!$G:$G,Cash_Book!$C:$C,C26,Cash_Book!$D:$D,"REPAID",Cash_Book!$E:$E,B26)) | G26: =IF(B26="","",D26+E26-F26)
A27: 24 | B27: =IF(Masters!$P$26="","",Masters!$P$26) | C27: =IF(B27="","",Masters!$R$26) | D27: =IF(B27="",0,Masters!$Q$26) | E27: =IF(B27="",0,SUMIFS(Cash_Book!$G:$G,Cash_Book!$C:$C,C27,Cash_Book!$D:$D,"TAKEN",Cash_Book!$E:$E,B27)+SUMIFS(Cash_Book!$G:$G,Cash_Book!$C:$C,C27,Cash_Book!$D:$D,"PROFIT_TO_CAP",Cash_Book!$E:$E,B27)) | F27: =IF(B27="",0,SUMIFS(Cash_Book!$G:$G,Cash_Book!$C:$C,C27,Cash_Book!$D:$D,"WITHDRAWN",Cash_Book!$E:$E,B27)+SUMIFS(Cash_Book!$G:$G,Cash_Book!$C:$C,C27,Cash_Book!$D:$D,"REPAID",Cash_Book!$E:$E,B27)) | G27: =IF(B27="","",D27+E27-F27)
A28: 25 | B28: =IF(Masters!$P$27="","",Masters!$P$27) | C28: =IF(B28="","",Masters!$R$27) | D28: =IF(B28="",0,Masters!$Q$27) | E28: =IF(B28="",0,SUMIFS(Cash_Book!$G:$G,Cash_Book!$C:$C,C28,Cash_Book!$D:$D,"TAKEN",Cash_Book!$E:$E,B28)+SUMIFS(Cash_Book!$G:$G,Cash_Book!$C:$C,C28,Cash_Book!$D:$D,"PROFIT_TO_CAP",Cash_Book!$E:$E,B28)) | F28: =IF(B28="",0,SUMIFS(Cash_Book!$G:$G,Cash_Book!$C:$C,C28,Cash_Book!$D:$D,"WITHDRAWN",Cash_Book!$E:$E,B28)+SUMIFS(Cash_Book!$G:$G,Cash_Book!$C:$C,C28,Cash_Book!$D:$D,"REPAID",Cash_Book!$E:$E,B28)) | G28: =IF(B28="","",D28+E28-F28)
A29: 26 | B29: =IF(Masters!$P$28="","",Masters!$P$28) | C29: =IF(B29="","",Masters!$R$28) | D29: =IF(B29="",0,Masters!$Q$28) | E29: =IF(B29="",0,SUMIFS(Cash_Book!$G:$G,Cash_Book!$C:$C,C29,Cash_Book!$D:$D,"TAKEN",Cash_Book!$E:$E,B29)+SUMIFS(Cash_Book!$G:$G,Cash_Book!$C:$C,C29,Cash_Book!$D:$D,"PROFIT_TO_CAP",Cash_Book!$E:$E,B29)) | F29: =IF(B29="",0,SUMIFS(Cash_Book!$G:$G,Cash_Book!$C:$C,C29,Cash_Book!$D:$D,"WITHDRAWN",Cash_Book!$E:$E,B29)+SUMIFS(Cash_Book!$G:$G,Cash_Book!$C:$C,C29,Cash_Book!$D:$D,"REPAID",Cash_Book!$E:$E,B29)) | G29: =IF(B29="","",D29+E29-F29)
A30: 27 | B30: =IF(Masters!$P$29="","",Masters!$P$29) | C30: =IF(B30="","",Masters!$R$29) | D30: =IF(B30="",0,Masters!$Q$29) | E30: =IF(B30="",0,SUMIFS(Cash_Book!$G:$G,Cash_Book!$C:$C,C30,Cash_Book!$D:$D,"TAKEN",Cash_Book!$E:$E,B30)+SUMIFS(Cash_Book!$G:$G,Cash_Book!$C:$C,C30,Cash_Book!$D:$D,"PROFIT_TO_CAP",Cash_Book!$E:$E,B30)) | F30: =IF(B30="",0,SUMIFS(Cash_Book!$G:$G,Cash_Book!$C:$C,C30,Cash_Book!$D:$D,"WITHDRAWN",Cash_Book!$E:$E,B30)+SUMIFS(Cash_Book!$G:$G,Cash_Book!$C:$C,C30,Cash_Book!$D:$D,"REPAID",Cash_Book!$E:$E,B30)) | G30: =IF(B30="","",D30+E30-F30)
A31: 28 | B31: =IF(Masters!$P$30="","",Masters!$P$30) | C31: =IF(B31="","",Masters!$R$30) | D31: =IF(B31="",0,Masters!$Q$30) | E31: =IF(B31="",0,SUMIFS(Cash_Book!$G:$G,Cash_Book!$C:$C,C31,Cash_Book!$D:$D,"TAKEN",Cash_Book!$E:$E,B31)+SUMIFS(Cash_Book!$G:$G,Cash_Book!$C:$C,C31,Cash_Book!$D:$D,"PROFIT_TO_CAP",Cash_Book!$E:$E,B31)) | F31: =IF(B31="",0,SUMIFS(Cash_Book!$G:$G,Cash_Book!$C:$C,C31,Cash_Book!$D:$D,"WITHDRAWN",Cash_Book!$E:$E,B31)+SUMIFS(Cash_Book!$G:$G,Cash_Book!$C:$C,C31,Cash_Book!$D:$D,"REPAID",Cash_Book!$E:$E,B31)) | G31: =IF(B31="","",D31+E31-F31)
A32: 29 | B32: =IF(Masters!$P$31="","",Masters!$P$31) | C32: =IF(B32="","",Masters!$R$31) | D32: =IF(B32="",0,Masters!$Q$31) | E32: =IF(B32="",0,SUMIFS(Cash_Book!$G:$G,Cash_Book!$C:$C,C32,Cash_Book!$D:$D,"TAKEN",Cash_Book!$E:$E,B32)+SUMIFS(Cash_Book!$G:$G,Cash_Book!$C:$C,C32,Cash_Book!$D:$D,"PROFIT_TO_CAP",Cash_Book!$E:$E,B32)) | F32: =IF(B32="",0,SUMIFS(Cash_Book!$G:$G,Cash_Book!$C:$C,C32,Cash_Book!$D:$D,"WITHDRAWN",Cash_Book!$E:$E,B32)+SUMIFS(Cash_Book!$G:$G,Cash_Book!$C:$C,C32,Cash_Book!$D:$D,"REPAID",Cash_Book!$E:$E,B32)) | G32: =IF(B32="","",D32+E32-F32)
A33: 30 | B33: =IF(Masters!$P$32="","",Masters!$P$32) | C33: =IF(B33="","",Masters!$R$32) | D33: =IF(B33="",0,Masters!$Q$32) | E33: =IF(B33="",0,SUMIFS(Cash_Book!$G:$G,Cash_Book!$C:$C,C33,Cash_Book!$D:$D,"TAKEN",Cash_Book!$E:$E,B33)+SUMIFS(Cash_Book!$G:$G,Cash_Book!$C:$C,C33,Cash_Book!$D:$D,"PROFIT_TO_CAP",Cash_Book!$E:$E,B33)) | F33: =IF(B33="",0,SUMIFS(Cash_Book!$G:$G,Cash_Book!$C:$C,C33,Cash_Book!$D:$D,"WITHDRAWN",Cash_Book!$E:$E,B33)+SUMIFS(Cash_Book!$G:$G,Cash_Book!$C:$C,C33,Cash_Book!$D:$D,"REPAID",Cash_Book!$E:$E,B33)) | G33: =IF(B33="","",D33+E33-F33)
A35: TOTALS BY TYPE:
B36: CAPITAL Total | D36: =SUMIF(C4:C33,"CAPITAL",D4:D33) | E36: =SUMIF(C4:C33,"CAPITAL",E4:E33) | F36: =SUMIF(C4:C33,"CAPITAL",F4:F33) | G36: =SUMIF(C4:C33,"CAPITAL",G4:G33)
B37: LOAN Total | D37: =SUMIF(C4:C33,"LOAN",D4:D33) | E37: =SUMIF(C4:C33,"LOAN",E4:E33) | F37: =SUMIF(C4:C33,"LOAN",F4:F33) | G37: =SUMIF(C4:C33,"LOAN",G4:G33)
B38: AMANAT Total | D38: =SUMIF(C4:C33,"AMANAT",D4:D33) | E38: =SUMIF(C4:C33,"AMANAT",E4:E33) | F38: =SUMIF(C4:C33,"AMANAT",F4:F33) | G38: =SUMIF(C4:C33,"AMANAT",G4:G33)
B40: GRAND TOTAL | D40: =SUM(D36:D38) | G40: =SUM(G36:G38)

Sheet Bepaari_Aakda
A1: BEPAARI SETTLEMENT SLIP (AAKDA)
A3: SELECT BEPAARI:
A6: A. SALES
A7: Qty Sold | B7: =SUMIF(Daily_Sales!$C:$C,$B$3,Daily_Sales!$E:$E)
A8: Gross Sales | B8: =SUMIF(Daily_Sales!$C:$C,$B$3,Daily_Sales!$G:$G)
A10: B. DEDUCTIONS
A11: Commission Type | B11: =IF(IFERROR(INDEX(Masters!$D:$D,MATCH($B$3,Masters!$B:$B,0)),"")="","% Based","Flat ₹/Goat")
A12: Commission % | B12: =IFERROR(INDEX(Masters!$C:$C,MATCH($B$3,Masters!$B:$B,0)),4)
A13: Flat ₹/Goat | B13: =IFERROR(INDEX(Masters!$D:$D,MATCH($B$3,Masters!$B:$B,0)),"")
A14: Commission Amt | B14: =IF(B14<>"",B14*B8,B9*B13/100)
A15: KK (Fixed) | B15: =IF(B8>0,Masters!$Y$3,0)
A16: JB | B16: =B8*Masters!$Y$4
A17: Motor | B17: =SUMIFS(Cash_Book!$G:$G,Cash_Book!$C:$C,"BEPAARI",Cash_Book!$D:$D,"MOTOR",Cash_Book!$E:$E,$B$3)
A18: Bhussa | B18: =SUMIFS(Cash_Book!$G:$G,Cash_Book!$C:$C,"BEPAARI",Cash_Book!$D:$D,"BHUSSA",Cash_Book!$E:$E,$B$3)
A19: Gawali | B19: =SUMIFS(Cash_Book!$G:$G,Cash_Book!$C:$C,"BEPAARI",Cash_Book!$D:$D,"GAWALI",Cash_Book!$E:$E,$B$3)
A20: Cash/Adv | B20: =SUMIFS(Cash_Book!$G:$G,Cash_Book!$C:$C,"BEPAARI",Cash_Book!$D:$D,"CASH_ADV",Cash_Book!$E:$E,$B$3)
A21: TOTAL DEDUCTIONS | B21: =SUM(B15:B21)
A23: C. CALCULATION
A24: Gross Sales | B24: =B9
A25: (-) Deductions | B25: =B22
A26: (+) Opening Bal | B26: =IFERROR(INDEX(Masters!$E:$E,MATCH($B$3,Masters!$B:$B,0)),0)
A27: NET PAYABLE | B27: =B25-B26+B27
A29: D. PAYMENTS & ADJUSTMENTS
A30: Payments Made | B30: =SUMIFS(Cash_Book!$G:$G,Cash_Book!$C:$C,"BEPAARI",Cash_Book!$D:$D,"PAYMENT",Cash_Book!$E:$E,$B$3)
A31: JV Adjustments | B31: =SUMIFS(JV_Entries!$G:$G,JV_Entries!$C:$C,"BEPAARI",JV_Entries!$D:$D,$B$3)-SUMIFS(JV_Entries!$G:$G,JV_Entries!$E:$E,"BEPAARI",JV_Entries!$F:$F,$B$3)
A33: BALANCE DUE | B33: =B28-B31+B32

Sheet Balance_Sheet
A1: BALANCE SHEET | E1: LIABILITIES = ASSETS
A3: LIABILITIES (We Owe) | D3: ASSETS (We Have / Owed to Us)
A4: Particulars | B4: Amount | D4: Particulars | E4: Amount
A5: CAPITAL: | D5: CASH BALANCE | E5: =Cash_Book!J10
A6: =IF(AND(Capital_Loan_Ledger!B4<>"",Capital_Loan_Ledger!C4="CAPITAL")," "&Capital_Loan_Ledger!B4,"") | B6: =IF(A6="","",Capital_Loan_Ledger!G4)
A7: =IF(AND(Capital_Loan_Ledger!B5<>"",Capital_Loan_Ledger!C5="CAPITAL")," "&Capital_Loan_Ledger!B5,"") | B7: =IF(A7="","",Capital_Loan_Ledger!G5) | D7: BANK BALANCE | E7: =Cash_Book!J11
A8: =IF(AND(Capital_Loan_Ledger!B6<>"",Capital_Loan_Ledger!C6="CAPITAL")," "&Capital_Loan_Ledger!B6,"") | B8: =IF(A8="","",Capital_Loan_Ledger!G6)
A9: =IF(AND(Capital_Loan_Ledger!B7<>"",Capital_Loan_Ledger!C7="CAPITAL")," "&Capital_Loan_Ledger!B7,"") | B9: =IF(A9="","",Capital_Loan_Ledger!G7) | D9: PATTI (Dukandar Receivable):
A10: =IF(AND(Capital_Loan_Ledger!B8<>"",Capital_Loan_Ledger!C8="CAPITAL")," "&Capital_Loan_Ledger!B8,"") | B10: =IF(A10="","",Capital_Loan_Ledger!G8) | D10: Net Receivable | E10: =Dukandar_Ledger!I57
A11: =IF(AND(Capital_Loan_Ledger!B9<>"",Capital_Loan_Ledger!C9="CAPITAL")," "&Capital_Loan_Ledger!B9,"") | B11: =IF(A11="","",Capital_Loan_Ledger!G9)
A12: =IF(AND(Capital_Loan_Ledger!B10<>"",Capital_Loan_Ledger!C10="CAPITAL")," "&Capital_Loan_Ledger!B10,"") | B12: =IF(A12="","",Capital_Loan_Ledger!G10) | D12: BEPAARI ADVANCES (Overpaid):
A13: =IF(AND(Capital_Loan_Ledger!B11<>"",Capital_Loan_Ledger!C11="CAPITAL")," "&Capital_Loan_Ledger!B11,"") | B13: =IF(A13="","",Capital_Loan_Ledger!G11) | D13: Total Overpaid | E13: =Bepaari_Ledger!T59
A14: =IF(AND(Capital_Loan_Ledger!B12<>"",Capital_Loan_Ledger!C12="CAPITAL")," "&Capital_Loan_Ledger!B12,"") | B14: =IF(A14="","",Capital_Loan_Ledger!G12)
A15: =IF(AND(Capital_Loan_Ledger!B13<>"",Capital_Loan_Ledger!C13="CAPITAL")," "&Capital_Loan_Ledger!B13,"") | B15: =IF(A15="","",Capital_Loan_Ledger!G13) | D15: ADVANCES GIVEN (Net):
A16: Capital Total | B16: =Capital_Loan_Ledger!G36 | D16: Given - Received | E16: =SUMIFS(Cash_Book!$G:$G,Cash_Book!$D:$D,"GIVEN")-SUMIFS(Cash_Book!$G:$G,Cash_Book!$D:$D,"RECEIVED")
A18: LOANS: | D18: MANDI EXPENSES:
A19: =IF(AND(Capital_Loan_Ledger!B4<>"",Capital_Loan_Ledger!C4="LOAN")," "&Capital_Loan_Ledger!B4,"") | B19: =IF(A19="","",Capital_Loan_Ledger!G4) | D19: B/F | E19: =Masters!$Y$16
A20: =IF(AND(Capital_Loan_Ledger!B5<>"",Capital_Loan_Ledger!C5="LOAN")," "&Capital_Loan_Ledger!B5,"") | B20: =IF(A20="","",Capital_Loan_Ledger!G5) | D20: (+) Current Period | E20: =SUMIFS(Cash_Book!$G:$G,Cash_Book!$D:$D,"MANDI")+SUMIFS(Cash_Book!$G:$G,Cash_Book!$D:$D,"TRAVEL")+SUMIFS(Cash_Book!$G:$G,Cash_Book!$D:$D,"FOOD")+SUMIFS(Cash_Book!$G:$G,Cash_Book!$D:$D,"SALARY")+SUMIFS(Cash_Book!$G:$G,Cash_Book!$D:$D,"MISC")+SUMIFS(Cash_Book!$G:$G,Cash_Book!$D:$D,"OTHER")
A21: =IF(AND(Capital_Loan_Ledger!B6<>"",Capital_Loan_Ledger!C6="LOAN")," "&Capital_Loan_Ledger!B6,"") | B21: =IF(A21="","",Capital_Loan_Ledger!G6) | D21: Mandi Exp Total | E21: =E19+E20
A22: =IF(AND(Capital_Loan_Ledger!B7<>"",Capital_Loan_Ledger!C7="LOAN")," "&Capital_Loan_Ledger!B7,"") | B22: =IF(A22="","",Capital_Loan_Ledger!G7)
A23: =IF(AND(Capital_Loan_Ledger!B8<>"",Capital_Loan_Ledger!C8="LOAN")," "&Capital_Loan_Ledger!B8,"") | B23: =IF(A23="","",Capital_Loan_Ledger!G8) | D23: BF DISCOUNT:
A24: =IF(AND(Capital_Loan_Ledger!B9<>"",Capital_Loan_Ledger!C9="LOAN")," "&Capital_Loan_Ledger!B9,"") | B24: =IF(A24="","",Capital_Loan_Ledger!G9) | D24: B/F | E24: =Masters!$Y$17
A25: =IF(AND(Capital_Loan_Ledger!B10<>"",Capital_Loan_Ledger!C10="LOAN")," "&Capital_Loan_Ledger!B10,"") | B25: =IF(A25="","",Capital_Loan_Ledger!G10) | D25: (+) Current Period | E25: =SUMIFS(Cash_Book!$G:$G,Cash_Book!$D:$D,"BF_DISC")
A26: =IF(AND(Capital_Loan_Ledger!B11<>"",Capital_Loan_Ledger!C11="LOAN")," "&Capital_Loan_Ledger!B11,"") | B26: =IF(A26="","",Capital_Loan_Ledger!G11) | D26: BF Discount Total | E26: =E24+E25
A27: =IF(AND(Capital_Loan_Ledger!B12<>"",Capital_Loan_Ledger!C12="LOAN")," "&Capital_Loan_Ledger!B12,"") | B27: =IF(A27="","",Capital_Loan_Ledger!G12)
A28: =IF(AND(Capital_Loan_Ledger!B13<>"",Capital_Loan_Ledger!C13="LOAN")," "&Capital_Loan_Ledger!B13,"") | B28: =IF(A28="","",Capital_Loan_Ledger!G13) | D28: MHN PERSONAL (Drawings):
A29: Loans Total | B29: =Capital_Loan_Ledger!G37 | D29: B/F | E29: =Masters!$Y$18
D30: (+) Paid to MHN | E30: =SUMIFS(Cash_Book!$G:$G,Cash_Book!$D:$D,"MHN_PERSONAL")
A31: AMANAT: | D31: (-) Adjusted | E31: =-SUMIFS(Cash_Book!$G:$G,Cash_Book!$D:$D,"ADJUSTED")
A32: =IF(AND(Capital_Loan_Ledger!B4<>"",Capital_Loan_Ledger!C4="AMANAT")," "&Capital_Loan_Ledger!B4,"") | B32: =IF(A32="","",Capital_Loan_Ledger!G4) | D32: MHN Personal Total | E32: =E29+E30+E31
A33: =IF(AND(Capital_Loan_Ledger!B5<>"",Capital_Loan_Ledger!C5="AMANAT")," "&Capital_Loan_Ledger!B5,"") | B33: =IF(A33="","",Capital_Loan_Ledger!G5)
A34: =IF(AND(Capital_Loan_Ledger!B6<>"",Capital_Loan_Ledger!C6="AMANAT")," "&Capital_Loan_Ledger!B6,"") | B34: =IF(A34="","",Capital_Loan_Ledger!G6)
A35: =IF(AND(Capital_Loan_Ledger!B7<>"",Capital_Loan_Ledger!C7="AMANAT")," "&Capital_Loan_Ledger!B7,"") | B35: =IF(A35="","",Capital_Loan_Ledger!G7)
A36: =IF(AND(Capital_Loan_Ledger!B8<>"",Capital_Loan_Ledger!C8="AMANAT")," "&Capital_Loan_Ledger!B8,"") | B36: =IF(A36="","",Capital_Loan_Ledger!G8)
A37: =IF(AND(Capital_Loan_Ledger!B9<>"",Capital_Loan_Ledger!C9="AMANAT")," "&Capital_Loan_Ledger!B9,"") | B37: =IF(A37="","",Capital_Loan_Ledger!G9)
A38: =IF(AND(Capital_Loan_Ledger!B10<>"",Capital_Loan_Ledger!C10="AMANAT")," "&Capital_Loan_Ledger!B10,"") | B38: =IF(A38="","",Capital_Loan_Ledger!G10)
A39: =IF(AND(Capital_Loan_Ledger!B11<>"",Capital_Loan_Ledger!C11="AMANAT")," "&Capital_Loan_Ledger!B11,"") | B39: =IF(A39="","",Capital_Loan_Ledger!G11)
A40: =IF(AND(Capital_Loan_Ledger!B12<>"",Capital_Loan_Ledger!C12="AMANAT")," "&Capital_Loan_Ledger!B12,"") | B40: =IF(A40="","",Capital_Loan_Ledger!G12)
A41: =IF(AND(Capital_Loan_Ledger!B13<>"",Capital_Loan_Ledger!C13="AMANAT")," "&Capital_Loan_Ledger!B13,"") | B41: =IF(A41="","",Capital_Loan_Ledger!G13)
A42: Amanat Total | B42: =Capital_Loan_Ledger!G38
A44: BEPAARI PAYABLES:
A45: Net Payable | B45: =Bepaari_Ledger!T58
A47: DUKANDAR ADVANCES (Overpaid):
A48: Total Overpaid | B48: =Dukandar_Ledger!I58
A50: COMMISSION:
A51: B/F | B51: =Masters!$Y$13
A52: (+) Earned (Net) | B52: =Bepaari_Ledger!H55-Dukandar_Ledger!E54
A53: (-) Withdrawn | B53: =-SUMIFS(Cash_Book!$G:$G,Cash_Book!$D:$D,"COMM_WITHDRAW")
A54: Commission Balance | B54: =B51+B52+B53
A56: JB:
A57: B/F | B57: =Masters!$Y$10
A58: (+) Collected | B58: =Bepaari_Ledger!J55
A59: (-) Paid to Market | B59: =-SUMIFS(Cash_Book!$G:$G,Cash_Book!$D:$D,"JB_PAID")
A60: (-) Withdrawn | B60: =-SUMIFS(Cash_Book!$G:$G,Cash_Book!$D:$D,"JB_WITHDRAW")
A61: JB Balance | B61: =B57+B58+B59+B60
A63: KK:
A64: B/F | B64: =Masters!$Y$11
A65: (+) Collected | B65: =Bepaari_Ledger!I55
A66: (-) Withdrawn | B66: =-SUMIFS(Cash_Book!$G:$G,Cash_Book!$D:$D,"KK_WITHDRAW")
A67: KK Balance | B67: =B64+B65+B66
A69: ZAKAT PAYABLE:
A70: B/F + Provision - Paid | B70: =Masters!$Y$12+SUMIFS(Cash_Book!$G:$G,Cash_Book!$D:$D,"PROVISION")-SUMIFS(Cash_Book!$G:$G,Cash_Book!$D:$D,"PAID")
A72: TOTAL LIABILITIES | B72: =B16+B29+B42+B45+B48+B54+B61+B67+B70 | D72: TOTAL ASSETS | E72: =E5+E7+E10+E13+E16+E21+E26+E32
A74: DIFFERENCE (Should be 0) | B74: =B72-E72

Sheet Commission_Summary
A1: COMMISSION & PROFIT SUMMARY
A3: GROSS SALES | B3: =Bepaari_Ledger!F55
A4: TOTAL GOATS SOLD | B4: =Bepaari_Ledger!G55
A6: INCOME:
A7: Commission Earned | B7: =Bepaari_Ledger!H55
A8: (-) Discounts Given | B8: =-Dukandar_Ledger!E54
A9: Net Commission | B9: =B6+B7
A10: JB Collected | B10: =Bepaari_Ledger!J55
A11: KK Collected | B11: =Bepaari_Ledger!I55
A12: TOTAL INCOME | B12: =B8+B9+B10
A14: EXPENSES:
A15: Mandi/Business | B15: =SUMIFS(Cash_Book!$G:$G,Cash_Book!$D:$D,"MANDI")+SUMIFS(Cash_Book!$G:$G,Cash_Book!$D:$D,"TRAVEL")+SUMIFS(Cash_Book!$G:$G,Cash_Book!$D:$D,"FOOD")+SUMIFS(Cash_Book!$G:$G,Cash_Book!$D:$D,"SALARY")+SUMIFS(Cash_Book!$G:$G,Cash_Book!$D:$D,"MISC")+SUMIFS(Cash_Book!$G:$G,Cash_Book!$D:$D,"OTHER")
A16: BF Discount | B16: =SUMIFS(Cash_Book!$G:$G,Cash_Book!$D:$D,"BF_DISC")
A17: JB Paid | B17: =SUMIFS(Cash_Book!$G:$G,Cash_Book!$D:$D,"JB_PAID")
A18: TOTAL EXPENSES | B18: =B14+B15+B16
A20: NET PROFIT/LOSS | B20: =B11-B17
