Workbook

Sheet Masters
A1: BEPAARI MASTER | H1: DUKANDAR MASTER | N1: CAPITAL/LOAN PARTIES | S1: ADVANCE PARTIES | W1: SETTINGS
A2: Sr | B2: Bepaari Name | C2: Comm% | D2: Opening Bal | E2: Phone | F2: Remarks | H2: Sr | I2: Dukandar Name | J2: Opening Bal | K2: Phone | L2: Remarks | N2: Sr | O2: Party Name | P2: Opening Bal | Q2: Type | S2: Sr | T2: Party Name | U2: Opening Bal | W2: Commission Rate (%) | X2: 4
A3: 1 | B3: ABUL HASAN | C3: 4 | D3: 0 | H3: 1 | I3: SAKIM | J3: 0 | N3: 1 | O3: MHN | P3: 0 | Q3: CAPITAL | S3: 1 | W3: KK Fixed (₹/Bepari) | X3: 100
A4: 2 | B4: SHARAFAT | C4: 4 | D4: 0 | H4: 2 | I4: SHARIK | J4: 0 | N4: 2 | O4: SHAKIL GHODEGAON | P4: 0 | Q4: LOAN | S4: 2 | W4: JB Rate (₹/Goat) | X4: 10
A5: 3 | B5: SHARIK | C5: 4 | D5: 0 | H5: 3 | I5: YUNUS | J5: 0 | N5: 3 | S5: 3
A6: 4 | B6: JUNAID | C6: 4 | D6: 0 | H6: 4 | I6: MUDASSIR | J6: 0 | N6: 4 | S6: 4 | W6: Opening Cash | X6: 0
A7: 5 | B7: ANNU SHARIF | C7: 4 | D7: 0 | H7: 5 | I7: ARIF | J7: 0 | N7: 5 | S7: 5 | W7: Opening Bank | X7: 0
A8: 6 | B8: GAYYUR | C8: 4 | D8: 0 | H8: 6 | I8: SHOEB BYCULLA | J8: 0 | N8: 6 | S8: 6
A9: 7 | B9: ARIF KK | C9: 4 | D9: 0 | H9: 7 | I9: ISLAM D | J9: 0 | N9: 7 | S9: 7 | W9: ZAKAT Opening Payable | X9: 0
A10: 8 | B10: KISHOR | C10: 4 | D10: 0 | H10: 8 | I10: MEHMOOD MADH | J10: 0 | N10: 8 | S10: 8
A11: 9 | B11: SHOEB BYCULLA | C11: 4 | D11: 0 | H11: 9 | I11: MOBIN CHIPLUN | J11: 0 | N11: 9 | S11: 9
A12: 10 | B12: MAULANA | C12: 4 | D12: 0 | H12: 10 | I12: JALIL | J12: 0 | N12: 10 | S12: 10
A13: 11 | B13: ISLAM D | C13: 4 | D13: 0 | H13: 11 | I13: IRFAN JOGESHWARI | J13: 0 | N13: 11 | S13: 11
A14: 12 | B14: SALIM RAJ | C14: 4 | D14: 0 | H14: 12 | I14: YUNUS DOMBIVLI | J14: 0 | N14: 12 | S14: 12
A15: 13 | B15: MEHMOOD MADH | C15: 4 | D15: 0 | H15: 13 | I15: IFTEKHAR PUNE | J15: 0 | N15: 13 | S15: 13
A16: 14 | B16: ANAS RAJ | C16: 4 | D16: 0 | H16: 14 | I16: LALA/ASIF | J16: 0 | N16: 14 | S16: 14
A17: 15 | B17: MOBIN CHIPLUN | C17: 4 | D17: 0 | H17: 15 | I17: JAFER KASHIMIRA | J17: 0 | N17: 15 | S17: 15
A18: 16 | B18: AYAZ | C18: 4 | D18: 0 | H18: 16 | I18: CHAND | J18: 0 | N18: 16 | S18: 16
A19: 17 | B19: JALIL | C19: 4 | D19: 0 | H19: 17 | I19: ASIF GOREGAON | J19: 0 | N19: 17 | S19: 17
A20: 18 | B20: NEERAJ | C20: 4 | D20: 0 | H20: 18 | I20: CHINTU SHUJALPUR | J20: 0 | N20: 18 | S20: 18
A21: 19 | B21: IRFAN JOGESHWARI | C21: 4 | D21: 0 | H21: 19 | I21: VAZIR | J21: 0 | N21: 19 | S21: 19
A22: 20 | B22: CHINTU SHUJALPUR | C22: 4 | D22: 0 | H22: 20 | I22: AKRAM | J22: 0 | N22: 20 | S22: 20
A23: 21 | H23: 21 | I23: NADEEM BHIWANDI | J23: 0 | N23: 21 | S23: 21
A24: 22 | H24: 22 | I24: SHAKIL KON | J24: 0 | N24: 22 | S24: 22
A25: 23 | H25: 23 | I25: PARVEZ | J25: 0
A26: 24 | H26: 24
A27: 25 | H27: 25
A28: 26 | H28: 26
A29: 27 | H29: 27
A30: 28 | H30: 28
A31: 29 | H31: 29
A32: 30 | H32: 30
A33: 31 | H33: 31
A34: 32 | H34: 32
A35: 33 | H35: 33
A36: 34 | H36: 34
A37: 35 | H37: 35
... A79: 77 | H79: 77

Sheet Daily_Sales
A1: DAILY SALES (Bepaari → Dukandar)
A2: This feeds: Bepaari Ledger, Dukandar Ledger, Commission
A3: Sr | B3: Date | C3: Bepaari | D3: Dukandar | E3: Qty | F3: Rate | G3: Gross | H3: Discount | I3: Net
A4: 1 | G4: =IF(E4="","",E4*F4) | I4: =IF(G4="","",G4-IF(H4="",0,H4))
A5: 2 | G5: =IF(E5="","",E5*F5) | I5: =IF(G5="","",G5-IF(H5="",0,H5))
A6: 3 | G6: =IF(E6="","",E6*F6) | I6: =IF(G6="","",G6-IF(H6="",0,H6))
A7: 4 | G7: =IF(E7="","",E7*F7) | I7: =IF(G7="","",G7-IF(H7="",0,H7))
A8: 5 | G8: =IF(E8="","",E8*F8) | I8: =IF(G8="","",G8-IF(H8="",0,H8))
A9: 6 | G9: =IF(E9="","",E9*F9) | I9: =IF(G9="","",G9-IF(H9="",0,H9))
A10: 7 | G10: =IF(E10="","",E10*F10) | I10: =IF(G10="","",G10-IF(H10="",0,H10))
A11: 8 | G11: =IF(E11="","",E11*F11) | I11: =IF(G11="","",G11-IF(H11="",0,H11))
A12: 9 | G12: =IF(E12="","",E12*F12) | I12: =IF(G12="","",G12-IF(H12="",0,H12))
A13: 10 | G13: =IF(E13="","",E13*F13) | I13: =IF(G13="","",G13-IF(H13="",0,H13))
A14: 11 | G14: =IF(E14="","",E14*F14) | I14: =IF(G14="","",G14-IF(H14="",0,H14))
A15: 12 | G15: =IF(E15="","",E15*F15) | I15: =IF(G15="","",G15-IF(H15="",0,H15))
... A1003: 1000 | G1003: =IF(E1003="","",E1003*F1003) | I1003: =IF(G1003="","",G1003-IF(H1003="",0,H1003))

Sheet Cash_Book
A1: CASH BOOK (All Transactions) | L1: CASH/BANK SUMMARY
A2: BEP expenses in OUT cols. ZAKAT: PROVISION=provision, PAID=payment | K2: Opening Cash | L2: =Masters!$X$6
A3: Sr | B3: Date | C3: Type | D3: Sub-Type | E3: Party | F3: Particulars | G3: Cash OUT | H3: Bank OUT | I3: Cash IN | J3: Bank IN | K3: Opening Bank | L3: =Masters!$X$7
A4: 1 | K4: Total Cash OUT | L4: =SUM(G:G)
A5: 2 | K5: Total Bank OUT | L5: =SUM(H:H)
A6: 3 | K6: Total Cash IN | L6: =SUM(I:I)
A7: 4 | K7: Total Bank IN | L7: =SUM(J:J)
A8: 5 | K8: CLOSING CASH | L8: =L2-L4+L6
A9: 6 | K9: CLOSING BANK | L9: =L3-L5+L7
A10: 7
A11: 8
A12: 9
A13: 10
A14: 11
A15: 12
A16: 13
A17: 14
A18: 15
A19: 16
A20: 17
A21: 18
... A2003: 2000

Sheet Bepaari_Ledger
A1: BEPAARI LEDGER (Auto-calculated)
A2: From: Daily_Sales + Cash_Book (Type=BEPAARI)
A4: Sr | B4: Bepaari | C4: Comm% | D4: Opening | E4: Gross Sales | F4: Qty | G4: Commission | H4: KK | I4: JB | J4: Motor | K4: Bhussa | L4: Gawali | M4: Cash/Adv | N4: Other | O4: Tot.Deduct | P4: Net Payable | Q4: Payments | R4: BALANCE
A5: 1 | B5: =IF(Masters!$B$3="","",Masters!$B$3) | C5: =IF(B5="","",Masters!$C$3) | D5: =IF(B5="",0,Masters!$D$3) | E5: =SUMIF(Daily_Sales!$C:$C,B5,Daily_Sales!$G:$G) | F5: =SUMIF(Daily_Sales!$C:$C,B5,Daily_Sales!$E:$E) | G5: =IF(B5="",0,E5*C5/100) | H5: =IF(F5>0,Masters!$X$3,0) | I5: =F5*Masters!$X$4 | J5: =SUMIFS(Cash_Book!$G:$G,Cash_Book!$C:$C,"BEPAARI",Cash_Book!$D:$D,"MOTOR",Cash_Book!$E:$E,B5)+SUMIFS(Cash_Book!$H:$H,Cash_Book!$C:$C,"BEPAARI",Cash_Book!$D:$D,"MOTOR",Cash_Book!$E:$E,B5) | K5: =SUMIFS(Cash_Book!$G:$G,Cash_Book!$C:$C,"BEPAARI",Cash_Book!$D:$D,"BHUSSA",Cash_Book!$E:$E,B5)+SUMIFS(Cash_Book!$H:$H,Cash_Book!$C:$C,"BEPAARI",Cash_Book!$D:$D,"BHUSSA",Cash_Book!$E:$E,B5) | L5: =SUMIFS(Cash_Book!$G:$G,Cash_Book!$C:$C,"BEPAARI",Cash_Book!$D:$D,"GAWALI",Cash_Book!$E:$E,B5)+SUMIFS(Cash_Book!$H:$H,Cash_Book!$C:$C,"BEPAARI",Cash_Book!$D:$D,"GAWALI",Cash_Book!$E:$E,B5) | M5: =SUMIFS(Cash_Book!$G:$G,Cash_Book!$C:$C,"BEPAARI",Cash_Book!$D:$D,"CASH_ADV",Cash_Book!$E:$E,B5)+SUMIFS(Cash_Book!$H:$H,Cash_Book!$C:$C,"BEPAARI",Cash_Book!$D:$D,"CASH_ADV",Cash_Book!$E:$E,B5) | N5: =SUMIFS(Cash_Book!$G:$G,Cash_Book!$C:$C,"BEPAARI",Cash_Book!$D:$D,"OTHER",Cash_Book!$E:$E,B5)+SUMIFS(Cash_Book!$H:$H,Cash_Book!$C:$C,"BEPAARI",Cash_Book!$D:$D,"OTHER",Cash_Book!$E:$E,B5) | O5: =SUM(G5:N5) | P5: =IF(B5="","",E5-O5+D5) | Q5: =SUMIFS(Cash_Book!$G:$G,Cash_Book!$C:$C,"BEPAARI",Cash_Book!$D:$D,"PAYMENT",Cash_Book!$E:$E,B5)+SUMIFS(Cash_Book!$H:$H,Cash_Book!$C:$C,"BEPAARI",Cash_Book!$D:$D,"PAYMENT",Cash_Book!$E:$E,B5) | R5: =IF(B5="","",P5-Q5)
A6: 2 | B6: =IF(Masters!$B$4="","",Masters!$B$4) | C6: =IF(B6="","",Masters!$C$4) | D6: =IF(B6="",0,Masters!$D$4) | E6: =SUMIF(Daily_Sales!$C:$C,B6,Daily_Sales!$G:$G) | F6: =SUMIF(Daily_Sales!$C:$C,B6,Daily_Sales!$E:$E) | G6: =IF(B6="",0,E6*C6/100) | H6: =IF(F6>0,Masters!$X$3,0) | I6: =F6*Masters!$X$4 | J6: =SUMIFS(Cash_Book!$G:$G,Cash_Book!$C:$C,"BEPAARI",Cash_Book!$D:$D,"MOTOR",Cash_Book!$E:$E,B6)+SUMIFS(Cash_Book!$H:$H,Cash_Book!$C:$C,"BEPAARI",Cash_Book!$D:$D,"MOTOR",Cash_Book!$E:$E,B6) | K6: =SUMIFS(Cash_Book!$G:$G,Cash_Book!$C:$C,"BEPAARI",Cash_Book!$D:$D,"BHUSSA",Cash_Book!$E:$E,B6)+SUMIFS(Cash_Book!$H:$H,Cash_Book!$C:$C,"BEPAARI",Cash_Book!$D:$D,"BHUSSA",Cash_Book!$E:$E,B6) | L6: =SUMIFS(Cash_Book!$G:$G,Cash_Book!$C:$C,"BEPAARI",Cash_Book!$D:$D,"GAWALI",Cash_Book!$E:$E,B6)+SUMIFS(Cash_Book!$H:$H,Cash_Book!$C:$C,"BEPAARI",Cash_Book!$D:$D,"GAWALI",Cash_Book!$E:$E,B6) | M6: =SUMIFS(Cash_Book!$G:$G,Cash_Book!$C:$C,"BEPAARI",Cash_Book!$D:$D,"CASH_ADV",Cash_Book!$E:$E,B6)+SUMIFS(Cash_Book!$H:$H,Cash_Book!$C:$C,"BEPAARI",Cash_Book!$D:$D,"CASH_ADV",Cash_Book!$E:$E,B6) | N6: =SUMIFS(Cash_Book!$G:$G,Cash_Book!$C:$C,"BEPAARI",Cash_Book!$D:$D,"OTHER",Cash_Book!$E:$E,B6)+SUMIFS(Cash_Book!$H:$H,Cash_Book!$C:$C,"BEPAARI",Cash_Book!$D:$D,"OTHER",Cash_Book!$E:$E,B6) | O6: =SUM(G6:N6) | P6: =IF(B6="","",E6-O6+D6) | Q6: =SUMIFS(Cash_Book!$G:$G,Cash_Book!$C:$C,"BEPAARI",Cash_Book!$D:$D,"PAYMENT",Cash_Book!$E:$E,B6)+SUMIFS(Cash_Book!$H:$H,Cash_Book!$C:$C,"BEPAARI",Cash_Book!$D:$D,"PAYMENT",Cash_Book!$E:$E,B6) | R6: =IF(B6="","",P6-Q6)
A7: 3 | B7: =IF(Masters!$B$5="","",Masters!$B$5) | C7: =IF(B7="","",Masters!$C$5) | D7: =IF(B7="",0,Masters!$D$5) | E7: =SUMIF(Daily_Sales!$C:$C,B7,Daily_Sales!$G:$G) | F7: =SUMIF(Daily_Sales!$C:$C,B7,Daily_Sales!$E:$E) | G7: =IF(B7="",0,E7*C7/100) | H7: =IF(F7>0,Masters!$X$3,0) | I7: =F7*Masters!$X$4 | J7: =SUMIFS(Cash_Book!$G:$G,Cash_Book!$C:$C,"BEPAARI",Cash_Book!$D:$D,"MOTOR",Cash_Book!$E:$E,B7)+SUMIFS(Cash_Book!$H:$H,Cash_Book!$C:$C,"BEPAARI",Cash_Book!$D:$D,"MOTOR",Cash_Book!$E:$E,B7) | K7: =SUMIFS(Cash_Book!$G:$G,Cash_Book!$C:$C,"BEPAARI",Cash_Book!$D:$D,"BHUSSA",Cash_Book!$E:$E,B7)+SUMIFS(Cash_Book!$H:$H,Cash_Book!$C:$C,"BEPAARI",Cash_Book!$D:$D,"BHUSSA",Cash_Book!$E:$E,B7) | L7: =SUMIFS(Cash_Book!$G:$G,Cash_Book!$C:$C,"BEPAARI",Cash_Book!$D:$D,"GAWALI",Cash_Book!$E:$E,B7)+SUMIFS(Cash_Book!$H:$H,Cash_Book!$C:$C,"BEPAARI",Cash_Book!$D:$D,"GAWALI",Cash_Book!$E:$E,B7) | M7: =SUMIFS(Cash_Book!$G:$G,Cash_Book!$C:$C,"BEPAARI",Cash_Book!$D:$D,"CASH_ADV",Cash_Book!$E:$E,B7)+SUMIFS(Cash_Book!$H:$H,Cash_Book!$C:$C,"BEPAARI",Cash_Book!$D:$D,"CASH_ADV",Cash_Book!$E:$E,B7) | N7: =SUMIFS(Cash_Book!$G:$G,Cash_Book!$C:$C,"BEPAARI",Cash_Book!$D:$D,"OTHER",Cash_Book!$E:$E,B7)+SUMIFS(Cash_Book!$H:$H,Cash_Book!$C:$C,"BEPAARI",Cash_Book!$D:$D,"OTHER",Cash_Book!$E:$E,B7) | O7: =SUM(G7:N7) | P7: =IF(B7="","",E7-O7+D7) | Q7: =SUMIFS(Cash_Book!$G:$G,Cash_Book!$C:$C,"BEPAARI",Cash_Book!$D:$D,"PAYMENT",Cash_Book!$E:$E,B7)+SUMIFS(Cash_Book!$H:$H,Cash_Book!$C:$C,"BEPAARI",Cash_Book!$D:$D,"PAYMENT",Cash_Book!$E:$E,B7) | R7: =IF(B7="","",P7-Q7)
A8: 4 | B8: =IF(Masters!$B$6="","",Masters!$B$6) | C8: =IF(B8="","",Masters!$C$6) | D8: =IF(B8="",0,Masters!$D$6) | E8: =SUMIF(Daily_Sales!$C:$C,B8,Daily_Sales!$G:$G) | F8: =SUMIF(Daily_Sales!$C:$C,B8,Daily_Sales!$E:$E) | G8: =IF(B8="",0,E8*C8/100) | H8: =IF(F8>0,Masters!$X$3,0) | I8: =F8*Masters!$X$4 | J8: =SUMIFS(Cash_Book!$G:$G,Cash_Book!$C:$C,"BEPAARI",Cash_Book!$D:$D,"MOTOR",Cash_Book!$E:$E,B8)+SUMIFS(Cash_Book!$H:$H,Cash_Book!$C:$C,"BEPAARI",Cash_Book!$D:$D,"MOTOR",Cash_Book!$E:$E,B8) | K8: =SUMIFS(Cash_Book!$G:$G,Cash_Book!$C:$C,"BEPAARI",Cash_Book!$D:$D,"BHUSSA",Cash_Book!$E:$E,B8)+SUMIFS(Cash_Book!$H:$H,Cash_Book!$C:$C,"BEPAARI",Cash_Book!$D:$D,"BHUSSA",Cash_Book!$E:$E,B8) | L8: =SUMIFS(Cash_Book!$G:$G,Cash_Book!$C:$C,"BEPAARI",Cash_Book!$D:$D,"GAWALI",Cash_Book!$E:$E,B8)+SUMIFS(Cash_Book!$H:$H,Cash_Book!$C:$C,"BEPAARI",Cash_Book!$D:$D,"GAWALI",Cash_Book!$E:$E,B8) | M8: =SUMIFS(Cash_Book!$G:$G,Cash_Book!$C:$C,"BEPAARI",Cash_Book!$D:$D,"CASH_ADV",Cash_Book!$E:$E,B8)+SUMIFS(Cash_Book!$H:$H,Cash_Book!$C:$C,"BEPAARI",Cash_Book!$D:$D,"CASH_ADV",Cash_Book!$E:$E,B8) | N8: =SUMIFS(Cash_Book!$G:$G,Cash_Book!$C:$C,"BEPAARI",Cash_Book!$D:$D,"OTHER",Cash_Book!$E:$E,B8)+SUMIFS(Cash_Book!$H:$H,Cash_Book!$C:$C,"BEPAARI",Cash_Book!$D:$D,"OTHER",Cash_Book!$E:$E,B8) | O8: =SUM(G8:N8) | P8: =IF(B8="","",E8-O8+D8) | Q8: =SUMIFS(Cash_Book!$G:$G,Cash_Book!$C:$C,"BEPAARI",Cash_Book!$D:$D,"PAYMENT",Cash_Book!$E:$E,B8)+SUMIFS(Cash_Book!$H:$H,Cash_Book!$C:$C,"BEPAARI",Cash_Book!$D:$D,"PAYMENT",Cash_Book!$E:$E,B8) | R8: =IF(B8="","",P8-Q8)
A9: 5 | B9: =IF(Masters!$B$7="","",Masters!$B$7) | C9: =IF(B9="","",Masters!$C$7) | D9: =IF(B9="",0,Masters!$D$7) | E9: =SUMIF(Daily_Sales!$C:$C,B9,Daily_Sales!$G:$G) | F9: =SUMIF(Daily_Sales!$C:$C,B9,Daily_Sales!$E:$E) | G9: =IF(B9="",0,E9*C9/100) | H9: =IF(F9>0,Masters!$X$3,0) | I9: =F9*Masters!$X$4 | J9: =SUMIFS(Cash_Book!$G:$G,Cash_Book!$C:$C,"BEPAARI",Cash_Book!$D:$D,"MOTOR",Cash_Book!$E:$E,B9)+SUMIFS(Cash_Book!$H:$H,Cash_Book!$C:$C,"BEPAARI",Cash_Book!$D:$D,"MOTOR",Cash_Book!$E:$E,B9) | K9: =SUMIFS(Cash_Book!$G:$G,Cash_Book!$C:$C,"BEPAARI",Cash_Book!$D:$D,"BHUSSA",Cash_Book!$E:$E,B9)+SUMIFS(Cash_Book!$H:$H,Cash_Book!$C:$C,"BEPAARI",Cash_Book!$D:$D,"BHUSSA",Cash_Book!$E:$E,B9) | L9: =SUMIFS(Cash_Book!$G:$G,Cash_Book!$C:$C,"BEPAARI",Cash_Book!$D:$D,"GAWALI",Cash_Book!$E:$E,B9)+SUMIFS(Cash_Book!$H:$H,Cash_Book!$C:$C,"BEPAARI",Cash_Book!$D:$D,"GAWALI",Cash_Book!$E:$E,B9) | M9: =SUMIFS(Cash_Book!$G:$G,Cash_Book!$C:$C,"BEPAARI",Cash_Book!$D:$D,"CASH_ADV",Cash_Book!$E:$E,B9)+SUMIFS(Cash_Book!$H:$H,Cash_Book!$C:$C,"BEPAARI",Cash_Book!$D:$D,"CASH_ADV",Cash_Book!$E:$E,B9) | N9: =SUMIFS(Cash_Book!$G:$G,Cash_Book!$C:$C,"BEPAARI",Cash_Book!$D:$D,"OTHER",Cash_Book!$E:$E,B9)+SUMIFS(Cash_Book!$H:$H,Cash_Book!$C:$C,"BEPAARI",Cash_Book!$D:$D,"OTHER",Cash_Book!$E:$E,B9) | O9: =SUM(G9:N9) | P9: =IF(B9="","",E9-O9+D9) | Q9: =SUMIFS(Cash_Book!$G:$G,Cash_Book!$C:$C,"BEPAARI",Cash_Book!$D:$D,"PAYMENT",Cash_Book!$E:$E,B9)+SUMIFS(Cash_Book!$H:$H,Cash_Book!$C:$C,"BEPAARI",Cash_Book!$D:$D,"PAYMENT",Cash_Book!$E:$E,B9) | R9: =IF(B9="","",P9-Q9)
A10: 6 | B10: =IF(Masters!$B$8="","",Masters!$B$8) | C10: =IF(B10="","",Masters!$C$8) | D10: =IF(B10="",0,Masters!$D$8) | E10: =SUMIF(Daily_Sales!$C:$C,B10,Daily_Sales!$G:$G) | F10: =SUMIF(Daily_Sales!$C:$C,B10,Daily_Sales!$E:$E) | G10: =IF(B10="",0,E10*C10/100) | H10: =IF(F10>0,Masters!$X$3,0) | I10: =F10*Masters!$X$4 | J10: =SUMIFS(Cash_Book!$G:$G,Cash_Book!$C:$C,"BEPAARI",Cash_Book!$D:$D,"MOTOR",Cash_Book!$E:$E,B10)+SUMIFS(Cash_Book!$H:$H,Cash_Book!$C:$C,"BEPAARI",Cash_Book!$D:$D,"MOTOR",Cash_Book!$E:$E,B10) | K10: =SUMIFS(Cash_Book!$G:$G,Cash_Book!$C:$C,"BEPAARI",Cash_Book!$D:$D,"BHUSSA",Cash_Book!$E:$E,B10)+SUMIFS(Cash_Book!$H:$H,Cash_Book!$C:$C,"BEPAARI",Cash_Book!$D:$D,"BHUSSA",Cash_Book!$E:$E,B10) | L10: =SUMIFS(Cash_Book!$G:$G,Cash_Book!$C:$C,"BEPAARI",Cash_Book!$D:$D,"GAWALI",Cash_Book!$E:$E,B10)+SUMIFS(Cash_Book!$H:$H,Cash_Book!$C:$C,"BEPAARI",Cash_Book!$D:$D,"GAWALI",Cash_Book!$E:$E,B10) | M10: =SUMIFS(Cash_Book!$G:$G,Cash_Book!$C:$C,"BEPAARI",Cash_Book!$D:$D,"CASH_ADV",Cash_Book!$E:$E,B10)+SUMIFS(Cash_Book!$H:$H,Cash_Book!$C:$C,"BEPAARI",Cash_Book!$D:$D,"CASH_ADV",Cash_Book!$E:$E,B10) | N10: =SUMIFS(Cash_Book!$G:$G,Cash_Book!$C:$C,"BEPAARI",Cash_Book!$D:$D,"OTHER",Cash_Book!$E:$E,B10)+SUMIFS(Cash_Book!$H:$H,Cash_Book!$C:$C,"BEPAARI",Cash_Book!$D:$D,"OTHER",Cash_Book!$E:$E,B10) | O10: =SUM(G10:N10) | P10: =IF(B10="","",E10-O10+D10) | Q10: =SUMIFS(Cash_Book!$G:$G,Cash_Book!$C:$C,"BEPAARI",Cash_Book!$D:$D,"PAYMENT",Cash_Book!$E:$E,B10)+SUMIFS(Cash_Book!$H:$H,Cash_Book!$C:$C,"BEPAARI",Cash_Book!$D:$D,"PAYMENT",Cash_Book!$E:$E,B10) | R10: =IF(B10="","",P10-Q10)
A11: 7 | B11: =IF(Masters!$B$9="","",Masters!$B$9) | C11: =IF(B11="","",Masters!$C$9) | D11: =IF(B11="",0,Masters!$D$9) | E11: =SUMIF(Daily_Sales!$C:$C,B11,Daily_Sales!$G:$G) | F11: =SUMIF(Daily_Sales!$C:$C,B11,Daily_Sales!$E:$E) | G11: =IF(B11="",0,E11*C11/100) | H11: =IF(F11>0,Masters!$X$3,0) | I11: =F11*Masters!$X$4 | J11: =SUMIFS(Cash_Book!$G:$G,Cash_Book!$C:$C,"BEPAARI",Cash_Book!$D:$D,"MOTOR",Cash_Book!$E:$E,B11)+SUMIFS(Cash_Book!$H:$H,Cash_Book!$C:$C,"BEPAARI",Cash_Book!$D:$D,"MOTOR",Cash_Book!$E:$E,B11) | K11: =SUMIFS(Cash_Book!$G:$G,Cash_Book!$C:$C,"BEPAARI",Cash_Book!$D:$D,"BHUSSA",Cash_Book!$E:$E,B11)+SUMIFS(Cash_Book!$H:$H,Cash_Book!$C:$C,"BEPAARI",Cash_Book!$D:$D,"BHUSSA",Cash_Book!$E:$E,B11) | L11: =SUMIFS(Cash_Book!$G:$G,Cash_Book!$C:$C,"BEPAARI",Cash_Book!$D:$D,"GAWALI",Cash_Book!$E:$E,B11)+SUMIFS(Cash_Book!$H:$H,Cash_Book!$C:$C,"BEPAARI",Cash_Book!$D:$D,"GAWALI",Cash_Book!$E:$E,B11) | M11: =SUMIFS(Cash_Book!$G:$G,Cash_Book!$C:$C,"BEPAARI",Cash_Book!$D:$D,"CASH_ADV",Cash_Book!$E:$E,B11)+SUMIFS(Cash_Book!$H:$H,Cash_Book!$C:$C,"BEPAARI",Cash_Book!$D:$D,"CASH_ADV",Cash_Book!$E:$E,B11) | N11: =SUMIFS(Cash_Book!$G:$G,Cash_Book!$C:$C,"BEPAARI",Cash_Book!$D:$D,"OTHER",Cash_Book!$E:$E,B11)+SUMIFS(Cash_Book!$H:$H,Cash_Book!$C:$C,"BEPAARI",Cash_Book!$D:$D,"OTHER",Cash_Book!$E:$E,B11) | O11: =SUM(G11:N11) | P11: =IF(B11="","",E11-O11+D11) | Q11: =SUMIFS(Cash_Book!$G:$G,Cash_Book!$C:$C,"BEPAARI",Cash_Book!$D:$D,"PAYMENT",Cash_Book!$E:$E,B11)+SUMIFS(Cash_Book!$H:$H,Cash_Book!$C:$C,"BEPAARI",Cash_Book!$D:$D,"PAYMENT",Cash_Book!$E:$E,B11) | R11: =IF(B11="","",P11-Q11)
A12: 8 | B12: =IF(Masters!$B$10="","",Masters!$B$10) | C12: =IF(B12="","",Masters!$C$10) | D12: =IF(B12="",0,Masters!$D$10) | E12: =SUMIF(Daily_Sales!$C:$C,B12,Daily_Sales!$G:$G) | F12: =SUMIF(Daily_Sales!$C:$C,B12,Daily_Sales!$E:$E) | G12: =IF(B12="",0,E12*C12/100) | H12: =IF(F12>0,Masters!$X$3,0) | I12: =F12*Masters!$X$4 | J12: =SUMIFS(Cash_Book!$G:$G,Cash_Book!$C:$C,"BEPAARI",Cash_Book!$D:$D,"MOTOR",Cash_Book!$E:$E,B12)+SUMIFS(Cash_Book!$H:$H,Cash_Book!$C:$C,"BEPAARI",Cash_Book!$D:$D,"MOTOR",Cash_Book!$E:$E,B12) | K12: =SUMIFS(Cash_Book!$G:$G,Cash_Book!$C:$C,"BEPAARI",Cash_Book!$D:$D,"BHUSSA",Cash_Book!$E:$E,B12)+SUMIFS(Cash_Book!$H:$H,Cash_Book!$C:$C,"BEPAARI",Cash_Book!$D:$D,"BHUSSA",Cash_Book!$E:$E,B12) | L12: =SUMIFS(Cash_Book!$G:$G,Cash_Book!$C:$C,"BEPAARI",Cash_Book!$D:$D,"GAWALI",Cash_Book!$E:$E,B12)+SUMIFS(Cash_Book!$H:$H,Cash_Book!$C:$C,"BEPAARI",Cash_Book!$D:$D,"GAWALI",Cash_Book!$E:$E,B12) | M12: =SUMIFS(Cash_Book!$G:$G,Cash_Book!$C:$C,"BEPAARI",Cash_Book!$D:$D,"CASH_ADV",Cash_Book!$E:$E,B12)+SUMIFS(Cash_Book!$H:$H,Cash_Book!$C:$C,"BEPAARI",Cash_Book!$D:$D,"CASH_ADV",Cash_Book!$E:$E,B12) | N12: =SUMIFS(Cash_Book!$G:$G,Cash_Book!$C:$C,"BEPAARI",Cash_Book!$D:$D,"OTHER",Cash_Book!$E:$E,B12)+SUMIFS(Cash_Book!$H:$H,Cash_Book!$C:$C,"BEPAARI",Cash_Book!$D:$D,"OTHER",Cash_Book!$E:$E,B12) | O12: =SUM(G12:N12) | P12: =IF(B12="","",E12-O12+D12) | Q12: =SUMIFS(Cash_Book!$G:$G,Cash_Book!$C:$C,"BEPAARI",Cash_Book!$D:$D,"PAYMENT",Cash_Book!$E:$E,B12)+SUMIFS(Cash_Book!$H:$H,Cash_Book!$C:$C,"BEPAARI",Cash_Book!$D:$D,"PAYMENT",Cash_Book!$E:$E,B12) | R12: =IF(B12="","",P12-Q12)
A13: 9 | B13: =IF(Masters!$B$11="","",Masters!$B$11) | C13: =IF(B13="","",Masters!$C$11) | D13: =IF(B13="",0,Masters!$D$11) | E13: =SUMIF(Daily_Sales!$C:$C,B13,Daily_Sales!$G:$G) | F13: =SUMIF(Daily_Sales!$C:$C,B13,Daily_Sales!$E:$E) | G13: =IF(B13="",0,E13*C13/100) | H13: =IF(F13>0,Masters!$X$3,0) | I13: =F13*Masters!$X$4 | J13: =SUMIFS(Cash_Book!$G:$G,Cash_Book!$C:$C,"BEPAARI",Cash_Book!$D:$D,"MOTOR",Cash_Book!$E:$E,B13)+SUMIFS(Cash_Book!$H:$H,Cash_Book!$C:$C,"BEPAARI",Cash_Book!$D:$D,"MOTOR",Cash_Book!$E:$E,B13) | K13: =SUMIFS(Cash_Book!$G:$G,Cash_Book!$C:$C,"BEPAARI",Cash_Book!$D:$D,"BHUSSA",Cash_Book!$E:$E,B13)+SUMIFS(Cash_Book!$H:$H,Cash_Book!$C:$C,"BEPAARI",Cash_Book!$D:$D,"BHUSSA",Cash_Book!$E:$E,B13) | L13: =SUMIFS(Cash_Book!$G:$G,Cash_Book!$C:$C,"BEPAARI",Cash_Book!$D:$D,"GAWALI",Cash_Book!$E:$E,B13)+SUMIFS(Cash_Book!$H:$H,Cash_Book!$C:$C,"BEPAARI",Cash_Book!$D:$D,"GAWALI",Cash_Book!$E:$E,B13) | M13: =SUMIFS(Cash_Book!$G:$G,Cash_Book!$C:$C,"BEPAARI",Cash_Book!$D:$D,"CASH_ADV",Cash_Book!$E:$E,B13)+SUMIFS(Cash_Book!$H:$H,Cash_Book!$C:$C,"BEPAARI",Cash_Book!$D:$D,"CASH_ADV",Cash_Book!$E:$E,B13) | N13: =SUMIFS(Cash_Book!$G:$G,Cash_Book!$C:$C,"BEPAARI",Cash_Book!$D:$D,"OTHER",Cash_Book!$E:$E,B13)+SUMIFS(Cash_Book!$H:$H,Cash_Book!$C:$C,"BEPAARI",Cash_Book!$D:$D,"OTHER",Cash_Book!$E:$E,B13) | O13: =SUM(G13:N13) | P13: =IF(B13="","",E13-O13+D13) | Q13: =SUMIFS(Cash_Book!$G:$G,Cash_Book!$C:$C,"BEPAARI",Cash_Book!$D:$D,"PAYMENT",Cash_Book!$E:$E,B13)+SUMIFS(Cash_Book!$H:$H,Cash_Book!$C:$C,"BEPAARI",Cash_Book!$D:$D,"PAYMENT",Cash_Book!$E:$E,B13) | R13: =IF(B13="","",P13-Q13)
A14: 10 | B14: =IF(Masters!$B$12="","",Masters!$B$12) | C14: =IF(B14="","",Masters!$C$12) | D14: =IF(B14="",0,Masters!$D$12) | E14: =SUMIF(Daily_Sales!$C:$C,B14,Daily_Sales!$G:$G) | F14: =SUMIF(Daily_Sales!$C:$C,B14,Daily_Sales!$E:$E) | G14: =IF(B14="",0,E14*C14/100) | H14: =IF(F14>0,Masters!$X$3,0) | I14: =F14*Masters!$X$4 | J14: =SUMIFS(Cash_Book!$G:$G,Cash_Book!$C:$C,"BEPAARI",Cash_Book!$D:$D,"MOTOR",Cash_Book!$E:$E,B14)+SUMIFS(Cash_Book!$H:$H,Cash_Book!$C:$C,"BEPAARI",Cash_Book!$D:$D,"MOTOR",Cash_Book!$E:$E,B14) | K14: =SUMIFS(Cash_Book!$G:$G,Cash_Book!$C:$C,"BEPAARI",Cash_Book!$D:$D,"BHUSSA",Cash_Book!$E:$E,B14)+SUMIFS(Cash_Book!$H:$H,Cash_Book!$C:$C,"BEPAARI",Cash_Book!$D:$D,"BHUSSA",Cash_Book!$E:$E,B14) | L14: =SUMIFS(Cash_Book!$G:$G,Cash_Book!$C:$C,"BEPAARI",Cash_Book!$D:$D,"GAWALI",Cash_Book!$E:$E,B14)+SUMIFS(Cash_Book!$H:$H,Cash_Book!$C:$C,"BEPAARI",Cash_Book!$D:$D,"GAWALI",Cash_Book!$E:$E,B14) | M14: =SUMIFS(Cash_Book!$G:$G,Cash_Book!$C:$C,"BEPAARI",Cash_Book!$D:$D,"CASH_ADV",Cash_Book!$E:$E,B14)+SUMIFS(Cash_Book!$H:$H,Cash_Book!$C:$C,"BEPAARI",Cash_Book!$D:$D,"CASH_ADV",Cash_Book!$E:$E,B14) | N14: =SUMIFS(Cash_Book!$G:$G,Cash_Book!$C:$C,"BEPAARI",Cash_Book!$D:$D,"OTHER",Cash_Book!$E:$E,B14)+SUMIFS(Cash_Book!$H:$H,Cash_Book!$C:$C,"BEPAARI",Cash_Book!$D:$D,"OTHER",Cash_Book!$E:$E,B14) | O14: =SUM(G14:N14) | P14: =IF(B14="","",E14-O14+D14) | Q14: =SUMIFS(Cash_Book!$G:$G,Cash_Book!$C:$C,"BEPAARI",Cash_Book!$D:$D,"PAYMENT",Cash_Book!$E:$E,B14)+SUMIFS(Cash_Book!$H:$H,Cash_Book!$C:$C,"BEPAARI",Cash_Book!$D:$D,"PAYMENT",Cash_Book!$E:$E,B14) | R14: =IF(B14="","",P14-Q14)
A15: 11 | B15: =IF(Masters!$B$13="","",Masters!$B$13) | C15: =IF(B15="","",Masters!$C$13) | D15: =IF(B15="",0,Masters!$D$13) | E15: =SUMIF(Daily_Sales!$C:$C,B15,Daily_Sales!$G:$G) | F15: =SUMIF(Daily_Sales!$C:$C,B15,Daily_Sales!$E:$E) | G15: =IF(B15="",0,E15*C15/100) | H15: =IF(F15>0,Masters!$X$3,0) | I15: =F15*Masters!$X$4 | J15: =SUMIFS(Cash_Book!$G:$G,Cash_Book!$C:$C,"BEPAARI",Cash_Book!$D:$D,"MOTOR",Cash_Book!$E:$E,B15)+SUMIFS(Cash_Book!$H:$H,Cash_Book!$C:$C,"BEPAARI",Cash_Book!$D:$D,"MOTOR",Cash_Book!$E:$E,B15) | K15: =SUMIFS(Cash_Book!$G:$G,Cash_Book!$C:$C,"BEPAARI",Cash_Book!$D:$D,"BHUSSA",Cash_Book!$E:$E,B15)+SUMIFS(Cash_Book!$H:$H,Cash_Book!$C:$C,"BEPAARI",Cash_Book!$D:$D,"BHUSSA",Cash_Book!$E:$E,B15) | L15: =SUMIFS(Cash_Book!$G:$G,Cash_Book!$C:$C,"BEPAARI",Cash_Book!$D:$D,"GAWALI",Cash_Book!$E:$E,B15)+SUMIFS(Cash_Book!$H:$H,Cash_Book!$C:$C,"BEPAARI",Cash_Book!$D:$D,"GAWALI",Cash_Book!$E:$E,B15) | M15: =SUMIFS(Cash_Book!$G:$G,Cash_Book!$C:$C,"BEPAARI",Cash_Book!$D:$D,"CASH_ADV",Cash_Book!$E:$E,B15)+SUMIFS(Cash_Book!$H:$H,Cash_Book!$C:$C,"BEPAARI",Cash_Book!$D:$D,"CASH_ADV",Cash_Book!$E:$E,B15) | N15: =SUMIFS(Cash_Book!$G:$G,Cash_Book!$C:$C,"BEPAARI",Cash_Book!$D:$D,"OTHER",Cash_Book!$E:$E,B15)+SUMIFS(Cash_Book!$H:$H,Cash_Book!$C:$C,"BEPAARI",Cash_Book!$D:$D,"OTHER",Cash_Book!$E:$E,B15) | O15: =SUM(G15:N15) | P15: =IF(B15="","",E15-O15+D15) | Q15: =SUMIFS(Cash_Book!$G:$G,Cash_Book!$C:$C,"BEPAARI",Cash_Book!$D:$D,"PAYMENT",Cash_Book!$E:$E,B15)+SUMIFS(Cash_Book!$H:$H,Cash_Book!$C:$C,"BEPAARI",Cash_Book!$D:$D,"PAYMENT",Cash_Book!$E:$E,B15) | R15: =IF(B15="","",P15-Q15)
A16: 12 | B16: =IF(Masters!$B$14="","",Masters!$B$14) | C16: =IF(B16="","",Masters!$C$14) | D16: =IF(B16="",0,Masters!$D$14) | E16: =SUMIF(Daily_Sales!$C:$C,B16,Daily_Sales!$G:$G) | F16: =SUMIF(Daily_Sales!$C:$C,B16,Daily_Sales!$E:$E) | G16: =IF(B16="",0,E16*C16/100) | H16: =IF(F16>0,Masters!$X$3,0) | I16: =F16*Masters!$X$4 | J16: =SUMIFS(Cash_Book!$G:$G,Cash_Book!$C:$C,"BEPAARI",Cash_Book!$D:$D,"MOTOR",Cash_Book!$E:$E,B16)+SUMIFS(Cash_Book!$H:$H,Cash_Book!$C:$C,"BEPAARI",Cash_Book!$D:$D,"MOTOR",Cash_Book!$E:$E,B16) | K16: =SUMIFS(Cash_Book!$G:$G,Cash_Book!$C:$C,"BEPAARI",Cash_Book!$D:$D,"BHUSSA",Cash_Book!$E:$E,B16)+SUMIFS(Cash_Book!$H:$H,Cash_Book!$C:$C,"BEPAARI",Cash_Book!$D:$D,"BHUSSA",Cash_Book!$E:$E,B16) | L16: =SUMIFS(Cash_Book!$G:$G,Cash_Book!$C:$C,"BEPAARI",Cash_Book!$D:$D,"GAWALI",Cash_Book!$E:$E,B16)+SUMIFS(Cash_Book!$H:$H,Cash_Book!$C:$C,"BEPAARI",Cash_Book!$D:$D,"GAWALI",Cash_Book!$E:$E,B16) | M16: =SUMIFS(Cash_Book!$G:$G,Cash_Book!$C:$C,"BEPAARI",Cash_Book!$D:$D,"CASH_ADV",Cash_Book!$E:$E,B16)+SUMIFS(Cash_Book!$H:$H,Cash_Book!$C:$C,"BEPAARI",Cash_Book!$D:$D,"CASH_ADV",Cash_Book!$E:$E,B16) | N16: =SUMIFS(Cash_Book!$G:$G,Cash_Book!$C:$C,"BEPAARI",Cash_Book!$D:$D,"OTHER",Cash_Book!$E:$E,B16)+SUMIFS(Cash_Book!$H:$H,Cash_Book!$C:$C,"BEPAARI",Cash_Book!$D:$D,"OTHER",Cash_Book!$E:$E,B16) | O16: =SUM(G16:N16) | P16: =IF(B16="","",E16-O16+D16) | Q16: =SUMIFS(Cash_Book!$G:$G,Cash_Book!$C:$C,"BEPAARI",Cash_Book!$D:$D,"PAYMENT",Cash_Book!$E:$E,B16)+SUMIFS(Cash_Book!$H:$H,Cash_Book!$C:$C,"BEPAARI",Cash_Book!$D:$D,"PAYMENT",Cash_Book!$E:$E,B16) | R16: =IF(B16="","",P16-Q16)
A17: 13 | B17: =IF(Masters!$B$15="","",Masters!$B$15) | C17: =IF(B17="","",Masters!$C$15) | D17: =IF(B17="",0,Masters!$D$15) | E17: =SUMIF(Daily_Sales!$C:$C,B17,Daily_Sales!$G:$G) | F17: =SUMIF(Daily_Sales!$C:$C,B17,Daily_Sales!$E:$E) | G17: =IF(B17="",0,E17*C17/100) | H17: =IF(F17>0,Masters!$X$3,0) | I17: =F17*Masters!$X$4 | J17: =SUMIFS(Cash_Book!$G:$G,Cash_Book!$C:$C,"BEPAARI",Cash_Book!$D:$D,"MOTOR",Cash_Book!$E:$E,B17)+SUMIFS(Cash_Book!$H:$H,Cash_Book!$C:$C,"BEPAARI",Cash_Book!$D:$D,"MOTOR",Cash_Book!$E:$E,B17) | K17: =SUMIFS(Cash_Book!$G:$G,Cash_Book!$C:$C,"BEPAARI",Cash_Book!$D:$D,"BHUSSA",Cash_Book!$E:$E,B17)+SUMIFS(Cash_Book!$H:$H,Cash_Book!$C:$C,"BEPAARI",Cash_Book!$D:$D,"BHUSSA",Cash_Book!$E:$E,B17) | L17: =SUMIFS(Cash_Book!$G:$G,Cash_Book!$C:$C,"BEPAARI",Cash_Book!$D:$D,"GAWALI",Cash_Book!$E:$E,B17)+SUMIFS(Cash_Book!$H:$H,Cash_Book!$C:$C,"BEPAARI",Cash_Book!$D:$D,"GAWALI",Cash_Book!$E:$E,B17) | M17: =SUMIFS(Cash_Book!$G:$G,Cash_Book!$C:$C,"BEPAARI",Cash_Book!$D:$D,"CASH_ADV",Cash_Book!$E:$E,B17)+SUMIFS(Cash_Book!$H:$H,Cash_Book!$C:$C,"BEPAARI",Cash_Book!$D:$D,"CASH_ADV",Cash_Book!$E:$E,B17) | N17: =SUMIFS(Cash_Book!$G:$G,Cash_Book!$C:$C,"BEPAARI",Cash_Book!$D:$D,"OTHER",Cash_Book!$E:$E,B17)+SUMIFS(Cash_Book!$H:$H,Cash_Book!$C:$C,"BEPAARI",Cash_Book!$D:$D,"OTHER",Cash_Book!$E:$E,B17) | O17: =SUM(G17:N17) | P17: =IF(B17="","",E17-O17+D17) | Q17: =SUMIFS(Cash_Book!$G:$G,Cash_Book!$C:$C,"BEPAARI",Cash_Book!$D:$D,"PAYMENT",Cash_Book!$E:$E,B17)+SUMIFS(Cash_Book!$H:$H,Cash_Book!$C:$C,"BEPAARI",Cash_Book!$D:$D,"PAYMENT",Cash_Book!$E:$E,B17) | R17: =IF(B17="","",P17-Q17)
A18: 14 | B18: =IF(Masters!$B$16="","",Masters!$B$16) | C18: =IF(B18="","",Masters!$C$16) | D18: =IF(B18="",0,Masters!$D$16) | E18: =SUMIF(Daily_Sales!$C:$C,B18,Daily_Sales!$G:$G) | F18: =SUMIF(Daily_Sales!$C:$C,B18,Daily_Sales!$E:$E) | G18: =IF(B18="",0,E18*C18/100) | H18: =IF(F18>0,Masters!$X$3,0) | I18: =F18*Masters!$X$4 | J18: =SUMIFS(Cash_Book!$G:$G,Cash_Book!$C:$C,"BEPAARI",Cash_Book!$D:$D,"MOTOR",Cash_Book!$E:$E,B18)+SUMIFS(Cash_Book!$H:$H,Cash_Book!$C:$C,"BEPAARI",Cash_Book!$D:$D,"MOTOR",Cash_Book!$E:$E,B18) | K18: =SUMIFS(Cash_Book!$G:$G,Cash_Book!$C:$C,"BEPAARI",Cash_Book!$D:$D,"BHUSSA",Cash_Book!$E:$E,B18)+SUMIFS(Cash_Book!$H:$H,Cash_Book!$C:$C,"BEPAARI",Cash_Book!$D:$D,"BHUSSA",Cash_Book!$E:$E,B18) | L18: =SUMIFS(Cash_Book!$G:$G,Cash_Book!$C:$C,"BEPAARI",Cash_Book!$D:$D,"GAWALI",Cash_Book!$E:$E,B18)+SUMIFS(Cash_Book!$H:$H,Cash_Book!$C:$C,"BEPAARI",Cash_Book!$D:$D,"GAWALI",Cash_Book!$E:$E,B18) | M18: =SUMIFS(Cash_Book!$G:$G,Cash_Book!$C:$C,"BEPAARI",Cash_Book!$D:$D,"CASH_ADV",Cash_Book!$E:$E,B18)+SUMIFS(Cash_Book!$H:$H,Cash_Book!$C:$C,"BEPAARI",Cash_Book!$D:$D,"CASH_ADV",Cash_Book!$E:$E,B18) | N18: =SUMIFS(Cash_Book!$G:$G,Cash_Book!$C:$C,"BEPAARI",Cash_Book!$D:$D,"OTHER",Cash_Book!$E:$E,B18)+SUMIFS(Cash_Book!$H:$H,Cash_Book!$C:$C,"BEPAARI",Cash_Book!$D:$D,"OTHER",Cash_Book!$E:$E,B18) | O18: =SUM(G18:N18) | P18: =IF(B18="","",E18-O18+D18) | Q18: =SUMIFS(Cash_Book!$G:$G,Cash_Book!$C:$C,"BEPAARI",Cash_Book!$D:$D,"PAYMENT",Cash_Book!$E:$E,B18)+SUMIFS(Cash_Book!$H:$H,Cash_Book!$C:$C,"BEPAARI",Cash_Book!$D:$D,"PAYMENT",Cash_Book!$E:$E,B18) | R18: =IF(B18="","",P18-Q18)
A19: 15 | B19: =IF(Masters!$B$17="","",Masters!$B$17) | C19: =IF(B19="","",Masters!$C$17) | D19: =IF(B19="",0,Masters!$D$17) | E19: =SUMIF(Daily_Sales!$C:$C,B19,Daily_Sales!$G:$G) | F19: =SUMIF(Daily_Sales!$C:$C,B19,Daily_Sales!$E:$E) | G19: =IF(B19="",0,E19*C19/100) | H19: =IF(F19>0,Masters!$X$3,0) | I19: =F19*Masters!$X$4 | J19: =SUMIFS(Cash_Book!$G:$G,Cash_Book!$C:$C,"BEPAARI",Cash_Book!$D:$D,"MOTOR",Cash_Book!$E:$E,B19)+SUMIFS(Cash_Book!$H:$H,Cash_Book!$C:$C,"BEPAARI",Cash_Book!$D:$D,"MOTOR",Cash_Book!$E:$E,B19) | K19: =SUMIFS(Cash_Book!$G:$G,Cash_Book!$C:$C,"BEPAARI",Cash_Book!$D:$D,"BHUSSA",Cash_Book!$E:$E,B19)+SUMIFS(Cash_Book!$H:$H,Cash_Book!$C:$C,"BEPAARI",Cash_Book!$D:$D,"BHUSSA",Cash_Book!$E:$E,B19) | L19: =SUMIFS(Cash_Book!$G:$G,Cash_Book!$C:$C,"BEPAARI",Cash_Book!$D:$D,"GAWALI",Cash_Book!$E:$E,B19)+SUMIFS(Cash_Book!$H:$H,Cash_Book!$C:$C,"BEPAARI",Cash_Book!$D:$D,"GAWALI",Cash_Book!$E:$E,B19) | M19: =SUMIFS(Cash_Book!$G:$G,Cash_Book!$C:$C,"BEPAARI",Cash_Book!$D:$D,"CASH_ADV",Cash_Book!$E:$E,B19)+SUMIFS(Cash_Book!$H:$H,Cash_Book!$C:$C,"BEPAARI",Cash_Book!$D:$D,"CASH_ADV",Cash_Book!$E:$E,B19) | N19: =SUMIFS(Cash_Book!$G:$G,Cash_Book!$C:$C,"BEPAARI",Cash_Book!$D:$D,"OTHER",Cash_Book!$E:$E,B19)+SUMIFS(Cash_Book!$H:$H,Cash_Book!$C:$C,"BEPAARI",Cash_Book!$D:$D,"OTHER",Cash_Book!$E:$E,B19) | O19: =SUM(G19:N19) | P19: =IF(B19="","",E19-O19+D19) | Q19: =SUMIFS(Cash_Book!$G:$G,Cash_Book!$C:$C,"BEPAARI",Cash_Book!$D:$D,"PAYMENT",Cash_Book!$E:$E,B19)+SUMIFS(Cash_Book!$H:$H,Cash_Book!$C:$C,"BEPAARI",Cash_Book!$D:$D,"PAYMENT",Cash_Book!$E:$E,B19) | R19: =IF(B19="","",P19-Q19)
A20: 16 | B20: =IF(Masters!$B$18="","",Masters!$B$18) | C20: =IF(B20="","",Masters!$C$18) | D20: =IF(B20="",0,Masters!$D$18) | E20: =SUMIF(Daily_Sales!$C:$C,B20,Daily_Sales!$G:$G) | F20: =SUMIF(Daily_Sales!$C:$C,B20,Daily_Sales!$E:$E) | G20: =IF(B20="",0,E20*C20/100) | H20: =IF(F20>0,Masters!$X$3,0) | I20: =F20*Masters!$X$4 | J20: =SUMIFS(Cash_Book!$G:$G,Cash_Book!$C:$C,"BEPAARI",Cash_Book!$D:$D,"MOTOR",Cash_Book!$E:$E,B20)+SUMIFS(Cash_Book!$H:$H,Cash_Book!$C:$C,"BEPAARI",Cash_Book!$D:$D,"MOTOR",Cash_Book!$E:$E,B20) | K20: =SUMIFS(Cash_Book!$G:$G,Cash_Book!$C:$C,"BEPAARI",Cash_Book!$D:$D,"BHUSSA",Cash_Book!$E:$E,B20)+SUMIFS(Cash_Book!$H:$H,Cash_Book!$C:$C,"BEPAARI",Cash_Book!$D:$D,"BHUSSA",Cash_Book!$E:$E,B20) | L20: =SUMIFS(Cash_Book!$G:$G,Cash_Book!$C:$C,"BEPAARI",Cash_Book!$D:$D,"GAWALI",Cash_Book!$E:$E,B20)+SUMIFS(Cash_Book!$H:$H,Cash_Book!$C:$C,"BEPAARI",Cash_Book!$D:$D,"GAWALI",Cash_Book!$E:$E,B20) | M20: =SUMIFS(Cash_Book!$G:$G,Cash_Book!$C:$C,"BEPAARI",Cash_Book!$D:$D,"CASH_ADV",Cash_Book!$E:$E,B20)+SUMIFS(Cash_Book!$H:$H,Cash_Book!$C:$C,"BEPAARI",Cash_Book!$D:$D,"CASH_ADV",Cash_Book!$E:$E,B20) | N20: =SUMIFS(Cash_Book!$G:$G,Cash_Book!$C:$C,"BEPAARI",Cash_Book!$D:$D,"OTHER",Cash_Book!$E:$E,B20)+SUMIFS(Cash_Book!$H:$H,Cash_Book!$C:$C,"BEPAARI",Cash_Book!$D:$D,"OTHER",Cash_Book!$E:$E,B20) | O20: =SUM(G20:N20) | P20: =IF(B20="","",E20-O20+D20) | Q20: =SUMIFS(Cash_Book!$G:$G,Cash_Book!$C:$C,"BEPAARI",Cash_Book!$D:$D,"PAYMENT",Cash_Book!$E:$E,B20)+SUMIFS(Cash_Book!$H:$H,Cash_Book!$C:$C,"BEPAARI",Cash_Book!$D:$D,"PAYMENT",Cash_Book!$E:$E,B20) | R20: =IF(B20="","",P20-Q20)
A21: 17 | B21: =IF(Masters!$B$19="","",Masters!$B$19) | C21: =IF(B21="","",Masters!$C$19) | D21: =IF(B21="",0,Masters!$D$19) | E21: =SUMIF(Daily_Sales!$C:$C,B21,Daily_Sales!$G:$G) | F21: =SUMIF(Daily_Sales!$C:$C,B21,Daily_Sales!$E:$E) | G21: =IF(B21="",0,E21*C21/100) | H21: =IF(F21>0,Masters!$X$3,0) | I21: =F21*Masters!$X$4 | J21: =SUMIFS(Cash_Book!$G:$G,Cash_Book!$C:$C,"BEPAARI",Cash_Book!$D:$D,"MOTOR",Cash_Book!$E:$E,B21)+SUMIFS(Cash_Book!$H:$H,Cash_Book!$C:$C,"BEPAARI",Cash_Book!$D:$D,"MOTOR",Cash_Book!$E:$E,B21) | K21: =SUMIFS(Cash_Book!$G:$G,Cash_Book!$C:$C,"BEPAARI",Cash_Book!$D:$D,"BHUSSA",Cash_Book!$E:$E,B21)+SUMIFS(Cash_Book!$H:$H,Cash_Book!$C:$C,"BEPAARI",Cash_Book!$D:$D,"BHUSSA",Cash_Book!$E:$E,B21) | L21: =SUMIFS(Cash_Book!$G:$G,Cash_Book!$C:$C,"BEPAARI",Cash_Book!$D:$D,"GAWALI",Cash_Book!$E:$E,B21)+SUMIFS(Cash_Book!$H:$H,Cash_Book!$C:$C,"BEPAARI",Cash_Book!$D:$D,"GAWALI",Cash_Book!$E:$E,B21) | M21: =SUMIFS(Cash_Book!$G:$G,Cash_Book!$C:$C,"BEPAARI",Cash_Book!$D:$D,"CASH_ADV",Cash_Book!$E:$E,B21)+SUMIFS(Cash_Book!$H:$H,Cash_Book!$C:$C,"BEPAARI",Cash_Book!$D:$D,"CASH_ADV",Cash_Book!$E:$E,B21) | N21: =SUMIFS(Cash_Book!$G:$G,Cash_Book!$C:$C,"BEPAARI",Cash_Book!$D:$D,"OTHER",Cash_Book!$E:$E,B21)+SUMIFS(Cash_Book!$H:$H,Cash_Book!$C:$C,"BEPAARI",Cash_Book!$D:$D,"OTHER",Cash_Book!$E:$E,B21) | O21: =SUM(G21:N21) | P21: =IF(B21="","",E21-O21+D21) | Q21: =SUMIFS(Cash_Book!$G:$G,Cash_Book!$C:$C,"BEPAARI",Cash_Book!$D:$D,"PAYMENT",Cash_Book!$E:$E,B21)+SUMIFS(Cash_Book!$H:$H,Cash_Book!$C:$C,"BEPAARI",Cash_Book!$D:$D,"PAYMENT",Cash_Book!$E:$E,B21) | R21: =IF(B21="","",P21-Q21)
A22: 18 | B22: =IF(Masters!$B$20="","",Masters!$B$20) | C22: =IF(B22="","",Masters!$C$20) | D22: =IF(B22="",0,Masters!$D$20) | E22: =SUMIF(Daily_Sales!$C:$C,B22,Daily_Sales!$G:$G) | F22: =SUMIF(Daily_Sales!$C:$C,B22,Daily_Sales!$E:$E) | G22: =IF(B22="",0,E22*C22/100) | H22: =IF(F22>0,Masters!$X$3,0) | I22: =F22*Masters!$X$4 | J22: =SUMIFS(Cash_Book!$G:$G,Cash_Book!$C:$C,"BEPAARI",Cash_Book!$D:$D,"MOTOR",Cash_Book!$E:$E,B22)+SUMIFS(Cash_Book!$H:$H,Cash_Book!$C:$C,"BEPAARI",Cash_Book!$D:$D,"MOTOR",Cash_Book!$E:$E,B22) | K22: =SUMIFS(Cash_Book!$G:$G,Cash_Book!$C:$C,"BEPAARI",Cash_Book!$D:$D,"BHUSSA",Cash_Book!$E:$E,B22)+SUMIFS(Cash_Book!$H:$H,Cash_Book!$C:$C,"BEPAARI",Cash_Book!$D:$D,"BHUSSA",Cash_Book!$E:$E,B22) | L22: =SUMIFS(Cash_Book!$G:$G,Cash_Book!$C:$C,"BEPAARI",Cash_Book!$D:$D,"GAWALI",Cash_Book!$E:$E,B22)+SUMIFS(Cash_Book!$H:$H,Cash_Book!$C:$C,"BEPAARI",Cash_Book!$D:$D,"GAWALI",Cash_Book!$E:$E,B22) | M22: =SUMIFS(Cash_Book!$G:$G,Cash_Book!$C:$C,"BEPAARI",Cash_Book!$D:$D,"CASH_ADV",Cash_Book!$E:$E,B22)+SUMIFS(Cash_Book!$H:$H,Cash_Book!$C:$C,"BEPAARI",Cash_Book!$D:$D,"CASH_ADV",Cash_Book!$E:$E,B22) | N22: =SUMIFS(Cash_Book!$G:$G,Cash_Book!$C:$C,"BEPAARI",Cash_Book!$D:$D,"OTHER",Cash_Book!$E:$E,B22)+SUMIFS(Cash_Book!$H:$H,Cash_Book!$C:$C,"BEPAARI",Cash_Book!$D:$D,"OTHER",Cash_Book!$E:$E,B22) | O22: =SUM(G22:N22) | P22: =IF(B22="","",E22-O22+D22) | Q22: =SUMIFS(Cash_Book!$G:$G,Cash_Book!$C:$C,"BEPAARI",Cash_Book!$D:$D,"PAYMENT",Cash_Book!$E:$E,B22)+SUMIFS(Cash_Book!$H:$H,Cash_Book!$C:$C,"BEPAARI",Cash_Book!$D:$D,"PAYMENT",Cash_Book!$E:$E,B22) | R22: =IF(B22="","",P22-Q22)
A23: 19 | B23: =IF(Masters!$B$21="","",Masters!$B$21) | C23: =IF(B23="","",Masters!$C$21) | D23: =IF(B23="",0,Masters!$D$21) | E23: =SUMIF(Daily_Sales!$C:$C,B23,Daily_Sales!$G:$G) | F23: =SUMIF(Daily_Sales!$C:$C,B23,Daily_Sales!$E:$E) | G23: =IF(B23="",0,E23*C23/100) | H23: =IF(F23>0,Masters!$X$3,0) | I23: =F23*Masters!$X$4 | J23: =SUMIFS(Cash_Book!$G:$G,Cash_Book!$C:$C,"BEPAARI",Cash_Book!$D:$D,"MOTOR",Cash_Book!$E:$E,B23)+SUMIFS(Cash_Book!$H:$H,Cash_Book!$C:$C,"BEPAARI",Cash_Book!$D:$D,"MOTOR",Cash_Book!$E:$E,B23) | K23: =SUMIFS(Cash_Book!$G:$G,Cash_Book!$C:$C,"BEPAARI",Cash_Book!$D:$D,"BHUSSA",Cash_Book!$E:$E,B23)+SUMIFS(Cash_Book!$H:$H,Cash_Book!$C:$C,"BEPAARI",Cash_Book!$D:$D,"BHUSSA",Cash_Book!$E:$E,B23) | L23: =SUMIFS(Cash_Book!$G:$G,Cash_Book!$C:$C,"BEPAARI",Cash_Book!$D:$D,"GAWALI",Cash_Book!$E:$E,B23)+SUMIFS(Cash_Book!$H:$H,Cash_Book!$C:$C,"BEPAARI",Cash_Book!$D:$D,"GAWALI",Cash_Book!$E:$E,B23) | M23: =SUMIFS(Cash_Book!$G:$G,Cash_Book!$C:$C,"BEPAARI",Cash_Book!$D:$D,"CASH_ADV",Cash_Book!$E:$E,B23)+SUMIFS(Cash_Book!$H:$H,Cash_Book!$C:$C,"BEPAARI",Cash_Book!$D:$D,"CASH_ADV",Cash_Book!$E:$E,B23) | N23: =SUMIFS(Cash_Book!$G:$G,Cash_Book!$C:$C,"BEPAARI",Cash_Book!$D:$D,"OTHER",Cash_Book!$E:$E,B23)+SUMIFS(Cash_Book!$H:$H,Cash_Book!$C:$C,"BEPAARI",Cash_Book!$D:$D,"OTHER",Cash_Book!$E:$E,B23) | O23: =SUM(G23:N23) | P23: =IF(B23="","",E23-O23+D23) | Q23: =SUMIFS(Cash_Book!$G:$G,Cash_Book!$C:$C,"BEPAARI",Cash_Book!$D:$D,"PAYMENT",Cash_Book!$E:$E,B23)+SUMIFS(Cash_Book!$H:$H,Cash_Book!$C:$C,"BEPAARI",Cash_Book!$D:$D,"PAYMENT",Cash_Book!$E:$E,B23) | R23: =IF(B23="","",P23-Q23)
A24: 20 | B24: =IF(Masters!$B$22="","",Masters!$B$22) | C24: =IF(B24="","",Masters!$C$22) | D24: =IF(B24="",0,Masters!$D$22) | E24: =SUMIF(Daily_Sales!$C:$C,B24,Daily_Sales!$G:$G) | F24: =SUMIF(Daily_Sales!$C:$C,B24,Daily_Sales!$E:$E) | G24: =IF(B24="",0,E24*C24/100) | H24: =IF(F24>0,Masters!$X$3,0) | I24: =F24*Masters!$X$4 | J24: =SUMIFS(Cash_Book!$G:$G,Cash_Book!$C:$C,"BEPAARI",Cash_Book!$D:$D,"MOTOR",Cash_Book!$E:$E,B24)+SUMIFS(Cash_Book!$H:$H,Cash_Book!$C:$C,"BEPAARI",Cash_Book!$D:$D,"MOTOR",Cash_Book!$E:$E,B24) | K24: =SUMIFS(Cash_Book!$G:$G,Cash_Book!$C:$C,"BEPAARI",Cash_Book!$D:$D,"BHUSSA",Cash_Book!$E:$E,B24)+SUMIFS(Cash_Book!$H:$H,Cash_Book!$C:$C,"BEPAARI",Cash_Book!$D:$D,"BHUSSA",Cash_Book!$E:$E,B24) | L24: =SUMIFS(Cash_Book!$G:$G,Cash_Book!$C:$C,"BEPAARI",Cash_Book!$D:$D,"GAWALI",Cash_Book!$E:$E,B24)+SUMIFS(Cash_Book!$H:$H,Cash_Book!$C:$C,"BEPAARI",Cash_Book!$D:$D,"GAWALI",Cash_Book!$E:$E,B24) | M24: =SUMIFS(Cash_Book!$G:$G,Cash_Book!$C:$C,"BEPAARI",Cash_Book!$D:$D,"CASH_ADV",Cash_Book!$E:$E,B24)+SUMIFS(Cash_Book!$H:$H,Cash_Book!$C:$C,"BEPAARI",Cash_Book!$D:$D,"CASH_ADV",Cash_Book!$E:$E,B24) | N24: =SUMIFS(Cash_Book!$G:$G,Cash_Book!$C:$C,"BEPAARI",Cash_Book!$D:$D,"OTHER",Cash_Book!$E:$E,B24)+SUMIFS(Cash_Book!$H:$H,Cash_Book!$C:$C,"BEPAARI",Cash_Book!$D:$D,"OTHER",Cash_Book!$E:$E,B24) | O24: =SUM(G24:N24) | P24: =IF(B24="","",E24-O24+D24) | Q24: =SUMIFS(Cash_Book!$G:$G,Cash_Book!$C:$C,"BEPAARI",Cash_Book!$D:$D,"PAYMENT",Cash_Book!$E:$E,B24)+SUMIFS(Cash_Book!$H:$H,Cash_Book!$C:$C,"BEPAARI",Cash_Book!$D:$D,"PAYMENT",Cash_Book!$E:$E,B24) | R24: =IF(B24="","",P24-Q24)
A25: 21 | B25: =IF(Masters!$B$23="","",Masters!$B$23) | C25: =IF(B25="","",Masters!$C$23) | D25: =IF(B25="",0,Masters!$D$23) | E25: =SUMIF(Daily_Sales!$C:$C,B25,Daily_Sales!$G:$G) | F25: =SUMIF(Daily_Sales!$C:$C,B25,Daily_Sales!$E:$E) | G25: =IF(B25="",0,E25*C25/100) | H25: =IF(F25>0,Masters!$X$3,0) | I25: =F25*Masters!$X$4 | J25: =SUMIFS(Cash_Book!$G:$G,Cash_Book!$C:$C,"BEPAARI",Cash_Book!$D:$D,"MOTOR",Cash_Book!$E:$E,B25)+SUMIFS(Cash_Book!$H:$H,Cash_Book!$C:$C,"BEPAARI",Cash_Book!$D:$D,"MOTOR",Cash_Book!$E:$E,B25) | K25: =SUMIFS(Cash_Book!$G:$G,Cash_Book!$C:$C,"BEPAARI",Cash_Book!$D:$D,"BHUSSA",Cash_Book!$E:$E,B25)+SUMIFS(Cash_Book!$H:$H,Cash_Book!$C:$C,"BEPAARI",Cash_Book!$D:$D,"BHUSSA",Cash_Book!$E:$E,B25) | L25: =SUMIFS(Cash_Book!$G:$G,Cash_Book!$C:$C,"BEPAARI",Cash_Book!$D:$D,"GAWALI",Cash_Book!$E:$E,B25)+SUMIFS(Cash_Book!$H:$H,Cash_Book!$C:$C,"BEPAARI",Cash_Book!$D:$D,"GAWALI",Cash_Book!$E:$E,B25) | M25: =SUMIFS(Cash_Book!$G:$G,Cash_Book!$C:$C,"BEPAARI",Cash_Book!$D:$D,"CASH_ADV",Cash_Book!$E:$E,B25)+SUMIFS(Cash_Book!$H:$H,Cash_Book!$C:$C,"BEPAARI",Cash_Book!$D:$D,"CASH_ADV",Cash_Book!$E:$E,B25) | N25: =SUMIFS(Cash_Book!$G:$G,Cash_Book!$C:$C,"BEPAARI",Cash_Book!$D:$D,"OTHER",Cash_Book!$E:$E,B25)+SUMIFS(Cash_Book!$H:$H,Cash_Book!$C:$C,"BEPAARI",Cash_Book!$D:$D,"OTHER",Cash_Book!$E:$E,B25) | O25: =SUM(G25:N25) | P25: =IF(B25="","",E25-O25+D25) | Q25: =SUMIFS(Cash_Book!$G:$G,Cash_Book!$C:$C,"BEPAARI",Cash_Book!$D:$D,"PAYMENT",Cash_Book!$E:$E,B25)+SUMIFS(Cash_Book!$H:$H,Cash_Book!$C:$C,"BEPAARI",Cash_Book!$D:$D,"PAYMENT",Cash_Book!$E:$E,B25) | R25: =IF(B25="","",P25-Q25)
A26: 22 | B26: =IF(Masters!$B$24="","",Masters!$B$24) | C26: =IF(B26="","",Masters!$C$24) | D26: =IF(B26="",0,Masters!$D$24) | E26: =SUMIF(Daily_Sales!$C:$C,B26,Daily_Sales!$G:$G) | F26: =SUMIF(Daily_Sales!$C:$C,B26,Daily_Sales!$E:$E) | G26: =IF(B26="",0,E26*C26/100) | H26: =IF(F26>0,Masters!$X$3,0) | I26: =F26*Masters!$X$4 | J26: =SUMIFS(Cash_Book!$G:$G,Cash_Book!$C:$C,"BEPAARI",Cash_Book!$D:$D,"MOTOR",Cash_Book!$E:$E,B26)+SUMIFS(Cash_Book!$H:$H,Cash_Book!$C:$C,"BEPAARI",Cash_Book!$D:$D,"MOTOR",Cash_Book!$E:$E,B26) | K26: =SUMIFS(Cash_Book!$G:$G,Cash_Book!$C:$C,"BEPAARI",Cash_Book!$D:$D,"BHUSSA",Cash_Book!$E:$E,B26)+SUMIFS(Cash_Book!$H:$H,Cash_Book!$C:$C,"BEPAARI",Cash_Book!$D:$D,"BHUSSA",Cash_Book!$E:$E,B26) | L26: =SUMIFS(Cash_Book!$G:$G,Cash_Book!$C:$C,"BEPAARI",Cash_Book!$D:$D,"GAWALI",Cash_Book!$E:$E,B26)+SUMIFS(Cash_Book!$H:$H,Cash_Book!$C:$C,"BEPAARI",Cash_Book!$D:$D,"GAWALI",Cash_Book!$E:$E,B26) | M26: =SUMIFS(Cash_Book!$G:$G,Cash_Book!$C:$C,"BEPAARI",Cash_Book!$D:$D,"CASH_ADV",Cash_Book!$E:$E,B26)+SUMIFS(Cash_Book!$H:$H,Cash_Book!$C:$C,"BEPAARI",Cash_Book!$D:$D,"CASH_ADV",Cash_Book!$E:$E,B26) | N26: =SUMIFS(Cash_Book!$G:$G,Cash_Book!$C:$C,"BEPAARI",Cash_Book!$D:$D,"OTHER",Cash_Book!$E:$E,B26)+SUMIFS(Cash_Book!$H:$H,Cash_Book!$C:$C,"BEPAARI",Cash_Book!$D:$D,"OTHER",Cash_Book!$E:$E,B26) | O26: =SUM(G26:N26) | P26: =IF(B26="","",E26-O26+D26) | Q26: =SUMIFS(Cash_Book!$G:$G,Cash_Book!$C:$C,"BEPAARI",Cash_Book!$D:$D,"PAYMENT",Cash_Book!$E:$E,B26)+SUMIFS(Cash_Book!$H:$H,Cash_Book!$C:$C,"BEPAARI",Cash_Book!$D:$D,"PAYMENT",Cash_Book!$E:$E,B26) | R26: =IF(B26="","",P26-Q26)
A27: 23 | B27: =IF(Masters!$B$25="","",Masters!$B$25) | C27: =IF(B27="","",Masters!$C$25) | D27: =IF(B27="",0,Masters!$D$25) | E27: =SUMIF(Daily_Sales!$C:$C,B27,Daily_Sales!$G:$G) | F27: =SUMIF(Daily_Sales!$C:$C,B27,Daily_Sales!$E:$E) | G27: =IF(B27="",0,E27*C27/100) | H27: =IF(F27>0,Masters!$X$3,0) | I27: =F27*Masters!$X$4 | J27: =SUMIFS(Cash_Book!$G:$G,Cash_Book!$C:$C,"BEPAARI",Cash_Book!$D:$D,"MOTOR",Cash_Book!$E:$E,B27)+SUMIFS(Cash_Book!$H:$H,Cash_Book!$C:$C,"BEPAARI",Cash_Book!$D:$D,"MOTOR",Cash_Book!$E:$E,B27) | K27: =SUMIFS(Cash_Book!$G:$G,Cash_Book!$C:$C,"BEPAARI",Cash_Book!$D:$D,"BHUSSA",Cash_Book!$E:$E,B27)+SUMIFS(Cash_Book!$H:$H,Cash_Book!$C:$C,"BEPAARI",Cash_Book!$D:$D,"BHUSSA",Cash_Book!$E:$E,B27) | L27: =SUMIFS(Cash_Book!$G:$G,Cash_Book!$C:$C,"BEPAARI",Cash_Book!$D:$D,"GAWALI",Cash_Book!$E:$E,B27)+SUMIFS(Cash_Book!$H:$H,Cash_Book!$C:$C,"BEPAARI",Cash_Book!$D:$D,"GAWALI",Cash_Book!$E:$E,B27) | M27: =SUMIFS(Cash_Book!$G:$G,Cash_Book!$C:$C,"BEPAARI",Cash_Book!$D:$D,"CASH_ADV",Cash_Book!$E:$E,B27)+SUMIFS(Cash_Book!$H:$H,Cash_Book!$C:$C,"BEPAARI",Cash_Book!$D:$D,"CASH_ADV",Cash_Book!$E:$E,B27) | N27: =SUMIFS(Cash_Book!$G:$G,Cash_Book!$C:$C,"BEPAARI",Cash_Book!$D:$D,"OTHER",Cash_Book!$E:$E,B27)+SUMIFS(Cash_Book!$H:$H,Cash_Book!$C:$C,"BEPAARI",Cash_Book!$D:$D,"OTHER",Cash_Book!$E:$E,B27) | O27: =SUM(G27:N27) | P27: =IF(B27="","",E27-O27+D27) | Q27: =SUMIFS(Cash_Book!$G:$G,Cash_Book!$C:$C,"BEPAARI",Cash_Book!$D:$D,"PAYMENT",Cash_Book!$E:$E,B27)+SUMIFS(Cash_Book!$H:$H,Cash_Book!$C:$C,"BEPAARI",Cash_Book!$D:$D,"PAYMENT",Cash_Book!$E:$E,B27) | R27: =IF(B27="","",P27-Q27)
A28: 24 | B28: =IF(Masters!$B$26="","",Masters!$B$26) | C28: =IF(B28="","",Masters!$C$26) | D28: =IF(B28="",0,Masters!$D$26) | E28: =SUMIF(Daily_Sales!$C:$C,B28,Daily_Sales!$G:$G) | F28: =SUMIF(Daily_Sales!$C:$C,B28,Daily_Sales!$E:$E) | G28: =IF(B28="",0,E28*C28/100) | H28: =IF(F28>0,Masters!$X$3,0) | I28: =F28*Masters!$X$4 | J28: =SUMIFS(Cash_Book!$G:$G,Cash_Book!$C:$C,"BEPAARI",Cash_Book!$D:$D,"MOTOR",Cash_Book!$E:$E,B28)+SUMIFS(Cash_Book!$H:$H,Cash_Book!$C:$C,"BEPAARI",Cash_Book!$D:$D,"MOTOR",Cash_Book!$E:$E,B28) | K28: =SUMIFS(Cash_Book!$G:$G,Cash_Book!$C:$C,"BEPAARI",Cash_Book!$D:$D,"BHUSSA",Cash_Book!$E:$E,B28)+SUMIFS(Cash_Book!$H:$H,Cash_Book!$C:$C,"BEPAARI",Cash_Book!$D:$D,"BHUSSA",Cash_Book!$E:$E,B28) | L28: =SUMIFS(Cash_Book!$G:$G,Cash_Book!$C:$C,"BEPAARI",Cash_Book!$D:$D,"GAWALI",Cash_Book!$E:$E,B28)+SUMIFS(Cash_Book!$H:$H,Cash_Book!$C:$C,"BEPAARI",Cash_Book!$D:$D,"GAWALI",Cash_Book!$E:$E,B28) | M28: =SUMIFS(Cash_Book!$G:$G,Cash_Book!$C:$C,"BEPAARI",Cash_Book!$D:$D,"CASH_ADV",Cash_Book!$E:$E,B28)+SUMIFS(Cash_Book!$H:$H,Cash_Book!$C:$C,"BEPAARI",Cash_Book!$D:$D,"CASH_ADV",Cash_Book!$E:$E,B28) | N28: =SUMIFS(Cash_Book!$G:$G,Cash_Book!$C:$C,"BEPAARI",Cash_Book!$D:$D,"OTHER",Cash_Book!$E:$E,B28)+SUMIFS(Cash_Book!$H:$H,Cash_Book!$C:$C,"BEPAARI",Cash_Book!$D:$D,"OTHER",Cash_Book!$E:$E,B28) | O28: =SUM(G28:N28) | P28: =IF(B28="","",E28-O28+D28) | Q28: =SUMIFS(Cash_Book!$G:$G,Cash_Book!$C:$C,"BEPAARI",Cash_Book!$D:$D,"PAYMENT",Cash_Book!$E:$E,B28)+SUMIFS(Cash_Book!$H:$H,Cash_Book!$C:$C,"BEPAARI",Cash_Book!$D:$D,"PAYMENT",Cash_Book!$E:$E,B28) | R28: =IF(B28="","",P28-Q28)
A29: 25 | B29: =IF(Masters!$B$27="","",Masters!$B$27) | C29: =IF(B29="","",Masters!$C$27) | D29: =IF(B29="",0,Masters!$D$27) | E29: =SUMIF(Daily_Sales!$C:$C,B29,Daily_Sales!$G:$G) | F29: =SUMIF(Daily_Sales!$C:$C,B29,Daily_Sales!$E:$E) | G29: =IF(B29="",0,E29*C29/100) | H29: =IF(F29>0,Masters!$X$3,0) | I29: =F29*Masters!$X$4 | J29: =SUMIFS(Cash_Book!$G:$G,Cash_Book!$C:$C,"BEPAARI",Cash_Book!$D:$D,"MOTOR",Cash_Book!$E:$E,B29)+SUMIFS(Cash_Book!$H:$H,Cash_Book!$C:$C,"BEPAARI",Cash_Book!$D:$D,"MOTOR",Cash_Book!$E:$E,B29) | K29: =SUMIFS(Cash_Book!$G:$G,Cash_Book!$C:$C,"BEPAARI",Cash_Book!$D:$D,"BHUSSA",Cash_Book!$E:$E,B29)+SUMIFS(Cash_Book!$H:$H,Cash_Book!$C:$C,"BEPAARI",Cash_Book!$D:$D,"BHUSSA",Cash_Book!$E:$E,B29) | L29: =SUMIFS(Cash_Book!$G:$G,Cash_Book!$C:$C,"BEPAARI",Cash_Book!$D:$D,"GAWALI",Cash_Book!$E:$E,B29)+SUMIFS(Cash_Book!$H:$H,Cash_Book!$C:$C,"BEPAARI",Cash_Book!$D:$D,"GAWALI",Cash_Book!$E:$E,B29) | M29: =SUMIFS(Cash_Book!$G:$G,Cash_Book!$C:$C,"BEPAARI",Cash_Book!$D:$D,"CASH_ADV",Cash_Book!$E:$E,B29)+SUMIFS(Cash_Book!$H:$H,Cash_Book!$C:$C,"BEPAARI",Cash_Book!$D:$D,"CASH_ADV",Cash_Book!$E:$E,B29) | N29: =SUMIFS(Cash_Book!$G:$G,Cash_Book!$C:$C,"BEPAARI",Cash_Book!$D:$D,"OTHER",Cash_Book!$E:$E,B29)+SUMIFS(Cash_Book!$H:$H,Cash_Book!$C:$C,"BEPAARI",Cash_Book!$D:$D,"OTHER",Cash_Book!$E:$E,B29) | O29: =SUM(G29:N29) | P29: =IF(B29="","",E29-O29+D29) | Q29: =SUMIFS(Cash_Book!$G:$G,Cash_Book!$C:$C,"BEPAARI",Cash_Book!$D:$D,"PAYMENT",Cash_Book!$E:$E,B29)+SUMIFS(Cash_Book!$H:$H,Cash_Book!$C:$C,"BEPAARI",Cash_Book!$D:$D,"PAYMENT",Cash_Book!$E:$E,B29) | R29: =IF(B29="","",P29-Q29)
A30: 26 | B30: =IF(Masters!$B$28="","",Masters!$B$28) | C30: =IF(B30="","",Masters!$C$28) | D30: =IF(B30="",0,Masters!$D$28) | E30: =SUMIF(Daily_Sales!$C:$C,B30,Daily_Sales!$G:$G) | F30: =SUMIF(Daily_Sales!$C:$C,B30,Daily_Sales!$E:$E) | G30: =IF(B30="",0,E30*C30/100) | H30: =IF(F30>0,Masters!$X$3,0) | I30: =F30*Masters!$X$4 | J30: =SUMIFS(Cash_Book!$G:$G,Cash_Book!$C:$C,"BEPAARI",Cash_Book!$D:$D,"MOTOR",Cash_Book!$E:$E,B30)+SUMIFS(Cash_Book!$H:$H,Cash_Book!$C:$C,"BEPAARI",Cash_Book!$D:$D,"MOTOR",Cash_Book!$E:$E,B30) | K30: =SUMIFS(Cash_Book!$G:$G,Cash_Book!$C:$C,"BEPAARI",Cash_Book!$D:$D,"BHUSSA",Cash_Book!$E:$E,B30)+SUMIFS(Cash_Book!$H:$H,Cash_Book!$C:$C,"BEPAARI",Cash_Book!$D:$D,"BHUSSA",Cash_Book!$E:$E,B30) | L30: =SUMIFS(Cash_Book!$G:$G,Cash_Book!$C:$C,"BEPAARI",Cash_Book!$D:$D,"GAWALI",Cash_Book!$E:$E,B30)+SUMIFS(Cash_Book!$H:$H,Cash_Book!$C:$C,"BEPAARI",Cash_Book!$D:$D,"GAWALI",Cash_Book!$E:$E,B30) | M30: =SUMIFS(Cash_Book!$G:$G,Cash_Book!$C:$C,"BEPAARI",Cash_Book!$D:$D,"CASH_ADV",Cash_Book!$E:$E,B30)+SUMIFS(Cash_Book!$H:$H,Cash_Book!$C:$C,"BEPAARI",Cash_Book!$D:$D,"CASH_ADV",Cash_Book!$E:$E,B30) | N30: =SUMIFS(Cash_Book!$G:$G,Cash_Book!$C:$C,"BEPAARI",Cash_Book!$D:$D,"OTHER",Cash_Book!$E:$E,B30)+SUMIFS(Cash_Book!$H:$H,Cash_Book!$C:$C,"BEPAARI",Cash_Book!$D:$D,"OTHER",Cash_Book!$E:$E,B30) | O30: =SUM(G30:N30) | P30: =IF(B30="","",E30-O30+D30) | Q30: =SUMIFS(Cash_Book!$G:$G,Cash_Book!$C:$C,"BEPAARI",Cash_Book!$D:$D,"PAYMENT",Cash_Book!$E:$E,B30)+SUMIFS(Cash_Book!$H:$H,Cash_Book!$C:$C,"BEPAARI",Cash_Book!$D:$D,"PAYMENT",Cash_Book!$E:$E,B30) | R30: =IF(B30="","",P30-Q30)
A31: 27 | B31: =IF(Masters!$B$29="","",Masters!$B$29) | C31: =IF(B31="","",Masters!$C$29) | D31: =IF(B31="",0,Masters!$D$29) | E31: =SUMIF(Daily_Sales!$C:$C,B31,Daily_Sales!$G:$G) | F31: =SUMIF(Daily_Sales!$C:$C,B31,Daily_Sales!$E:$E) | G31: =IF(B31="",0,E31*C31/100) | H31: =IF(F31>0,Masters!$X$3,0) | I31: =F31*Masters!$X$4 | J31: =SUMIFS(Cash_Book!$G:$G,Cash_Book!$C:$C,"BEPAARI",Cash_Book!$D:$D,"MOTOR",Cash_Book!$E:$E,B31)+SUMIFS(Cash_Book!$H:$H,Cash_Book!$C:$C,"BEPAARI",Cash_Book!$D:$D,"MOTOR",Cash_Book!$E:$E,B31) | K31: =SUMIFS(Cash_Book!$G:$G,Cash_Book!$C:$C,"BEPAARI",Cash_Book!$D:$D,"BHUSSA",Cash_Book!$E:$E,B31)+SUMIFS(Cash_Book!$H:$H,Cash_Book!$C:$C,"BEPAARI",Cash_Book!$D:$D,"BHUSSA",Cash_Book!$E:$E,B31) | L31: =SUMIFS(Cash_Book!$G:$G,Cash_Book!$C:$C,"BEPAARI",Cash_Book!$D:$D,"GAWALI",Cash_Book!$E:$E,B31)+SUMIFS(Cash_Book!$H:$H,Cash_Book!$C:$C,"BEPAARI",Cash_Book!$D:$D,"GAWALI",Cash_Book!$E:$E,B31) | M31: =SUMIFS(Cash_Book!$G:$G,Cash_Book!$C:$C,"BEPAARI",Cash_Book!$D:$D,"CASH_ADV",Cash_Book!$E:$E,B31)+SUMIFS(Cash_Book!$H:$H,Cash_Book!$C:$C,"BEPAARI",Cash_Book!$D:$D,"CASH_ADV",Cash_Book!$E:$E,B31) | N31: =SUMIFS(Cash_Book!$G:$G,Cash_Book!$C:$C,"BEPAARI",Cash_Book!$D:$D,"OTHER",Cash_Book!$E:$E,B31)+SUMIFS(Cash_Book!$H:$H,Cash_Book!$C:$C,"BEPAARI",Cash_Book!$D:$D,"OTHER",Cash_Book!$E:$E,B31) | O31: =SUM(G31:N31) | P31: =IF(B31="","",E31-O31+D31) | Q31: =SUMIFS(Cash_Book!$G:$G,Cash_Book!$C:$C,"BEPAARI",Cash_Book!$D:$D,"PAYMENT",Cash_Book!$E:$E,B31)+SUMIFS(Cash_Book!$H:$H,Cash_Book!$C:$C,"BEPAARI",Cash_Book!$D:$D,"PAYMENT",Cash_Book!$E:$E,B31) | R31: =IF(B31="","",P31-Q31)
A32: 28 | B32: =IF(Masters!$B$30="","",Masters!$B$30) | C32: =IF(B32="","",Masters!$C$30) | D32: =IF(B32="",0,Masters!$D$30) | E32: =SUMIF(Daily_Sales!$C:$C,B32,Daily_Sales!$G:$G) | F32: =SUMIF(Daily_Sales!$C:$C,B32,Daily_Sales!$E:$E) | G32: =IF(B32="",0,E32*C32/100) | H32: =IF(F32>0,Masters!$X$3,0) | I32: =F32*Masters!$X$4 | J32: =SUMIFS(Cash_Book!$G:$G,Cash_Book!$C:$C,"BEPAARI",Cash_Book!$D:$D,"MOTOR",Cash_Book!$E:$E,B32)+SUMIFS(Cash_Book!$H:$H,Cash_Book!$C:$C,"BEPAARI",Cash_Book!$D:$D,"MOTOR",Cash_Book!$E:$E,B32) | K32: =SUMIFS(Cash_Book!$G:$G,Cash_Book!$C:$C,"BEPAARI",Cash_Book!$D:$D,"BHUSSA",Cash_Book!$E:$E,B32)+SUMIFS(Cash_Book!$H:$H,Cash_Book!$C:$C,"BEPAARI",Cash_Book!$D:$D,"BHUSSA",Cash_Book!$E:$E,B32) | L32: =SUMIFS(Cash_Book!$G:$G,Cash_Book!$C:$C,"BEPAARI",Cash_Book!$D:$D,"GAWALI",Cash_Book!$E:$E,B32)+SUMIFS(Cash_Book!$H:$H,Cash_Book!$C:$C,"BEPAARI",Cash_Book!$D:$D,"GAWALI",Cash_Book!$E:$E,B32) | M32: =SUMIFS(Cash_Book!$G:$G,Cash_Book!$C:$C,"BEPAARI",Cash_Book!$D:$D,"CASH_ADV",Cash_Book!$E:$E,B32)+SUMIFS(Cash_Book!$H:$H,Cash_Book!$C:$C,"BEPAARI",Cash_Book!$D:$D,"CASH_ADV",Cash_Book!$E:$E,B32) | N32: =SUMIFS(Cash_Book!$G:$G,Cash_Book!$C:$C,"BEPAARI",Cash_Book!$D:$D,"OTHER",Cash_Book!$E:$E,B32)+SUMIFS(Cash_Book!$H:$H,Cash_Book!$C:$C,"BEPAARI",Cash_Book!$D:$D,"OTHER",Cash_Book!$E:$E,B32) | O32: =SUM(G32:N32) | P32: =IF(B32="","",E32-O32+D32) | Q32: =SUMIFS(Cash_Book!$G:$G,Cash_Book!$C:$C,"BEPAARI",Cash_Book!$D:$D,"PAYMENT",Cash_Book!$E:$E,B32)+SUMIFS(Cash_Book!$H:$H,Cash_Book!$C:$C,"BEPAARI",Cash_Book!$D:$D,"PAYMENT",Cash_Book!$E:$E,B32) | R32: =IF(B32="","",P32-Q32)
A33: 29 | B33: =IF(Masters!$B$31="","",Masters!$B$31) | C33: =IF(B33="","",Masters!$C$31) | D33: =IF(B33="",0,Masters!$D$31) | E33: =SUMIF(Daily_Sales!$C:$C,B33,Daily_Sales!$G:$G) | F33: =SUMIF(Daily_Sales!$C:$C,B33,Daily_Sales!$E:$E) | G33: =IF(B33="",0,E33*C33/100) | H33: =IF(F33>0,Masters!$X$3,0) | I33: =F33*Masters!$X$4 | J33: =SUMIFS(Cash_Book!$G:$G,Cash_Book!$C:$C,"BEPAARI",Cash_Book!$D:$D,"MOTOR",Cash_Book!$E:$E,B33)+SUMIFS(Cash_Book!$H:$H,Cash_Book!$C:$C,"BEPAARI",Cash_Book!$D:$D,"MOTOR",Cash_Book!$E:$E,B33) | K33: =SUMIFS(Cash_Book!$G:$G,Cash_Book!$C:$C,"BEPAARI",Cash_Book!$D:$D,"BHUSSA",Cash_Book!$E:$E,B33)+SUMIFS(Cash_Book!$H:$H,Cash_Book!$C:$C,"BEPAARI",Cash_Book!$D:$D,"BHUSSA",Cash_Book!$E:$E,B33) | L33: =SUMIFS(Cash_Book!$G:$G,Cash_Book!$C:$C,"BEPAARI",Cash_Book!$D:$D,"GAWALI",Cash_Book!$E:$E,B33)+SUMIFS(Cash_Book!$H:$H,Cash_Book!$C:$C,"BEPAARI",Cash_Book!$D:$D,"GAWALI",Cash_Book!$E:$E,B33) | M33: =SUMIFS(Cash_Book!$G:$G,Cash_Book!$C:$C,"BEPAARI",Cash_Book!$D:$D,"CASH_ADV",Cash_Book!$E:$E,B33)+SUMIFS(Cash_Book!$H:$H,Cash_Book!$C:$C,"BEPAARI",Cash_Book!$D:$D,"CASH_ADV",Cash_Book!$E:$E,B33) | N33: =SUMIFS(Cash_Book!$G:$G,Cash_Book!$C:$C,"BEPAARI",Cash_Book!$D:$D,"OTHER",Cash_Book!$E:$E,B33)+SUMIFS(Cash_Book!$H:$H,Cash_Book!$C:$C,"BEPAARI",Cash_Book!$D:$D,"OTHER",Cash_Book!$E:$E,B33) | O33: =SUM(G33:N33) | P33: =IF(B33="","",E33-O33+D33) | Q33: =SUMIFS(Cash_Book!$G:$G,Cash_Book!$C:$C,"BEPAARI",Cash_Book!$D:$D,"PAYMENT",Cash_Book!$E:$E,B33)+SUMIFS(Cash_Book!$H:$H,Cash_Book!$C:$C,"BEPAARI",Cash_Book!$D:$D,"PAYMENT",Cash_Book!$E:$E,B33) | R33: =IF(B33="","",P33-Q33)
A34: 30 | B34: =IF(Masters!$B$32="","",Masters!$B$32) | C34: =IF(B34="","",Masters!$C$32) | D34: =IF(B34="",0,Masters!$D$32) | E34: =SUMIF(Daily_Sales!$C:$C,B34,Daily_Sales!$G:$G) | F34: =SUMIF(Daily_Sales!$C:$C,B34,Daily_Sales!$E:$E) | G34: =IF(B34="",0,E34*C34/100) | H34: =IF(F34>0,Masters!$X$3,0) | I34: =F34*Masters!$X$4 | J34: =SUMIFS(Cash_Book!$G:$G,Cash_Book!$C:$C,"BEPAARI",Cash_Book!$D:$D,"MOTOR",Cash_Book!$E:$E,B34)+SUMIFS(Cash_Book!$H:$H,Cash_Book!$C:$C,"BEPAARI",Cash_Book!$D:$D,"MOTOR",Cash_Book!$E:$E,B34) | K34: =SUMIFS(Cash_Book!$G:$G,Cash_Book!$C:$C,"BEPAARI",Cash_Book!$D:$D,"BHUSSA",Cash_Book!$E:$E,B34)+SUMIFS(Cash_Book!$H:$H,Cash_Book!$C:$C,"BEPAARI",Cash_Book!$D:$D,"BHUSSA",Cash_Book!$E:$E,B34) | L34: =SUMIFS(Cash_Book!$G:$G,Cash_Book!$C:$C,"BEPAARI",Cash_Book!$D:$D,"GAWALI",Cash_Book!$E:$E,B34)+SUMIFS(Cash_Book!$H:$H,Cash_Book!$C:$C,"BEPAARI",Cash_Book!$D:$D,"GAWALI",Cash_Book!$E:$E,B34) | M34: =SUMIFS(Cash_Book!$G:$G,Cash_Book!$C:$C,"BEPAARI",Cash_Book!$D:$D,"CASH_ADV",Cash_Book!$E:$E,B34)+SUMIFS(Cash_Book!$H:$H,Cash_Book!$C:$C,"BEPAARI",Cash_Book!$D:$D,"CASH_ADV",Cash_Book!$E:$E,B34) | N34: =SUMIFS(Cash_Book!$G:$G,Cash_Book!$C:$C,"BEPAARI",Cash_Book!$D:$D,"OTHER",Cash_Book!$E:$E,B34)+SUMIFS(Cash_Book!$H:$H,Cash_Book!$C:$C,"BEPAARI",Cash_Book!$D:$D,"OTHER",Cash_Book!$E:$E,B34) | O34: =SUM(G34:N34) | P34: =IF(B34="","",E34-O34+D34) | Q34: =SUMIFS(Cash_Book!$G:$G,Cash_Book!$C:$C,"BEPAARI",Cash_Book!$D:$D,"PAYMENT",Cash_Book!$E:$E,B34)+SUMIFS(Cash_Book!$H:$H,Cash_Book!$C:$C,"BEPAARI",Cash_Book!$D:$D,"PAYMENT",Cash_Book!$E:$E,B34) | R34: =IF(B34="","",P34-Q34)
A35: 31 | B35: =IF(Masters!$B$33="","",Masters!$B$33) | C35: =IF(B35="","",Masters!$C$33) | D35: =IF(B35="",0,Masters!$D$33) | E35: =SUMIF(Daily_Sales!$C:$C,B35,Daily_Sales!$G:$G) | F35: =SUMIF(Daily_Sales!$C:$C,B35,Daily_Sales!$E:$E) | G35: =IF(B35="",0,E35*C35/100) | H35: =IF(F35>0,Masters!$X$3,0) | I35: =F35*Masters!$X$4 | J35: =SUMIFS(Cash_Book!$G:$G,Cash_Book!$C:$C,"BEPAARI",Cash_Book!$D:$D,"MOTOR",Cash_Book!$E:$E,B35)+SUMIFS(Cash_Book!$H:$H,Cash_Book!$C:$C,"BEPAARI",Cash_Book!$D:$D,"MOTOR",Cash_Book!$E:$E,B35) | K35: =SUMIFS(Cash_Book!$G:$G,Cash_Book!$C:$C,"BEPAARI",Cash_Book!$D:$D,"BHUSSA",Cash_Book!$E:$E,B35)+SUMIFS(Cash_Book!$H:$H,Cash_Book!$C:$C,"BEPAARI",Cash_Book!$D:$D,"BHUSSA",Cash_Book!$E:$E,B35) | L35: =SUMIFS(Cash_Book!$G:$G,Cash_Book!$C:$C,"BEPAARI",Cash_Book!$D:$D,"GAWALI",Cash_Book!$E:$E,B35)+SUMIFS(Cash_Book!$H:$H,Cash_Book!$C:$C,"BEPAARI",Cash_Book!$D:$D,"GAWALI",Cash_Book!$E:$E,B35) | M35: =SUMIFS(Cash_Book!$G:$G,Cash_Book!$C:$C,"BEPAARI",Cash_Book!$D:$D,"CASH_ADV",Cash_Book!$E:$E,B35)+SUMIFS(Cash_Book!$H:$H,Cash_Book!$C:$C,"BEPAARI",Cash_Book!$D:$D,"CASH_ADV",Cash_Book!$E:$E,B35) | N35: =SUMIFS(Cash_Book!$G:$G,Cash_Book!$C:$C,"BEPAARI",Cash_Book!$D:$D,"OTHER",Cash_Book!$E:$E,B35)+SUMIFS(Cash_Book!$H:$H,Cash_Book!$C:$C,"BEPAARI",Cash_Book!$D:$D,"OTHER",Cash_Book!$E:$E,B35) | O35: =SUM(G35:N35) | P35: =IF(B35="","",E35-O35+D35) | Q35: =SUMIFS(Cash_Book!$G:$G,Cash_Book!$C:$C,"BEPAARI",Cash_Book!$D:$D,"PAYMENT",Cash_Book!$E:$E,B35)+SUMIFS(Cash_Book!$H:$H,Cash_Book!$C:$C,"BEPAARI",Cash_Book!$D:$D,"PAYMENT",Cash_Book!$E:$E,B35) | R35: =IF(B35="","",P35-Q35)
A36: 32 | B36: =IF(Masters!$B$34="","",Masters!$B$34) | C36: =IF(B36="","",Masters!$C$34) | D36: =IF(B36="",0,Masters!$D$34) | E36: =SUMIF(Daily_Sales!$C:$C,B36,Daily_Sales!$G:$G) | F36: =SUMIF(Daily_Sales!$C:$C,B36,Daily_Sales!$E:$E) | G36: =IF(B36="",0,E36*C36/100) | H36: =IF(F36>0,Masters!$X$3,0) | I36: =F36*Masters!$X$4 | J36: =SUMIFS(Cash_Book!$G:$G,Cash_Book!$C:$C,"BEPAARI",Cash_Book!$D:$D,"MOTOR",Cash_Book!$E:$E,B36)+SUMIFS(Cash_Book!$H:$H,Cash_Book!$C:$C,"BEPAARI",Cash_Book!$D:$D,"MOTOR",Cash_Book!$E:$E,B36) | K36: =SUMIFS(Cash_Book!$G:$G,Cash_Book!$C:$C,"BEPAARI",Cash_Book!$D:$D,"BHUSSA",Cash_Book!$E:$E,B36)+SUMIFS(Cash_Book!$H:$H,Cash_Book!$C:$C,"BEPAARI",Cash_Book!$D:$D,"BHUSSA",Cash_Book!$E:$E,B36) | L36: =SUMIFS(Cash_Book!$G:$G,Cash_Book!$C:$C,"BEPAARI",Cash_Book!$D:$D,"GAWALI",Cash_Book!$E:$E,B36)+SUMIFS(Cash_Book!$H:$H,Cash_Book!$C:$C,"BEPAARI",Cash_Book!$D:$D,"GAWALI",Cash_Book!$E:$E,B36) | M36: =SUMIFS(Cash_Book!$G:$G,Cash_Book!$C:$C,"BEPAARI",Cash_Book!$D:$D,"CASH_ADV",Cash_Book!$E:$E,B36)+SUMIFS(Cash_Book!$H:$H,Cash_Book!$C:$C,"BEPAARI",Cash_Book!$D:$D,"CASH_ADV",Cash_Book!$E:$E,B36) | N36: =SUMIFS(Cash_Book!$G:$G,Cash_Book!$C:$C,"BEPAARI",Cash_Book!$D:$D,"OTHER",Cash_Book!$E:$E,B36)+SUMIFS(Cash_Book!$H:$H,Cash_Book!$C:$C,"BEPAARI",Cash_Book!$D:$D,"OTHER",Cash_Book!$E:$E,B36) | O36: =SUM(G36:N36) | P36: =IF(B36="","",E36-O36+D36) | Q36: =SUMIFS(Cash_Book!$G:$G,Cash_Book!$C:$C,"BEPAARI",Cash_Book!$D:$D,"PAYMENT",Cash_Book!$E:$E,B36)+SUMIFS(Cash_Book!$H:$H,Cash_Book!$C:$C,"BEPAARI",Cash_Book!$D:$D,"PAYMENT",Cash_Book!$E:$E,B36) | R36: =IF(B36="","",P36-Q36)
A37: 33 | B37: =IF(Masters!$B$35="","",Masters!$B$35) | C37: =IF(B37="","",Masters!$C$35) | D37: =IF(B37="",0,Masters!$D$35) | E37: =SUMIF(Daily_Sales!$C:$C,B37,Daily_Sales!$G:$G) | F37: =SUMIF(Daily_Sales!$C:$C,B37,Daily_Sales!$E:$E) | G37: =IF(B37="",0,E37*C37/100) | H37: =IF(F37>0,Masters!$X$3,0) | I37: =F37*Masters!$X$4 | J37: =SUMIFS(Cash_Book!$G:$G,Cash_Book!$C:$C,"BEPAARI",Cash_Book!$D:$D,"MOTOR",Cash_Book!$E:$E,B37)+SUMIFS(Cash_Book!$H:$H,Cash_Book!$C:$C,"BEPAARI",Cash_Book!$D:$D,"MOTOR",Cash_Book!$E:$E,B37) | K37: =SUMIFS(Cash_Book!$G:$G,Cash_Book!$C:$C,"BEPAARI",Cash_Book!$D:$D,"BHUSSA",Cash_Book!$E:$E,B37)+SUMIFS(Cash_Book!$H:$H,Cash_Book!$C:$C,"BEPAARI",Cash_Book!$D:$D,"BHUSSA",Cash_Book!$E:$E,B37) | L37: =SUMIFS(Cash_Book!$G:$G,Cash_Book!$C:$C,"BEPAARI",Cash_Book!$D:$D,"GAWALI",Cash_Book!$E:$E,B37)+SUMIFS(Cash_Book!$H:$H,Cash_Book!$C:$C,"BEPAARI",Cash_Book!$D:$D,"GAWALI",Cash_Book!$E:$E,B37) | M37: =SUMIFS(Cash_Book!$G:$G,Cash_Book!$C:$C,"BEPAARI",Cash_Book!$D:$D,"CASH_ADV",Cash_Book!$E:$E,B37)+SUMIFS(Cash_Book!$H:$H,Cash_Book!$C:$C,"BEPAARI",Cash_Book!$D:$D,"CASH_ADV",Cash_Book!$E:$E,B37) | N37: =SUMIFS(Cash_Book!$G:$G,Cash_Book!$C:$C,"BEPAARI",Cash_Book!$D:$D,"OTHER",Cash_Book!$E:$E,B37)+SUMIFS(Cash_Book!$H:$H,Cash_Book!$C:$C,"BEPAARI",Cash_Book!$D:$D,"OTHER",Cash_Book!$E:$E,B37) | O37: =SUM(G37:N37) | P37: =IF(B37="","",E37-O37+D37) | Q37: =SUMIFS(Cash_Book!$G:$G,Cash_Book!$C:$C,"BEPAARI",Cash_Book!$D:$D,"PAYMENT",Cash_Book!$E:$E,B37)+SUMIFS(Cash_Book!$H:$H,Cash_Book!$C:$C,"BEPAARI",Cash_Book!$D:$D,"PAYMENT",Cash_Book!$E:$E,B37) | R37: =IF(B37="","",P37-Q37)
A38: 34 | B38: =IF(Masters!$B$36="","",Masters!$B$36) | C38: =IF(B38="","",Masters!$C$36) | D38: =IF(B38="",0,Masters!$D$36) | E38: =SUMIF(Daily_Sales!$C:$C,B38,Daily_Sales!$G:$G) | F38: =SUMIF(Daily_Sales!$C:$C,B38,Daily_Sales!$E:$E) | G38: =IF(B38="",0,E38*C38/100) | H38: =IF(F38>0,Masters!$X$3,0) | I38: =F38*Masters!$X$4 | J38: =SUMIFS(Cash_Book!$G:$G,Cash_Book!$C:$C,"BEPAARI",Cash_Book!$D:$D,"MOTOR",Cash_Book!$E:$E,B38)+SUMIFS(Cash_Book!$H:$H,Cash_Book!$C:$C,"BEPAARI",Cash_Book!$D:$D,"MOTOR",Cash_Book!$E:$E,B38) | K38: =SUMIFS(Cash_Book!$G:$G,Cash_Book!$C:$C,"BEPAARI",Cash_Book!$D:$D,"BHUSSA",Cash_Book!$E:$E,B38)+SUMIFS(Cash_Book!$H:$H,Cash_Book!$C:$C,"BEPAARI",Cash_Book!$D:$D,"BHUSSA",Cash_Book!$E:$E,B38) | L38: =SUMIFS(Cash_Book!$G:$G,Cash_Book!$C:$C,"BEPAARI",Cash_Book!$D:$D,"GAWALI",Cash_Book!$E:$E,B38)+SUMIFS(Cash_Book!$H:$H,Cash_Book!$C:$C,"BEPAARI",Cash_Book!$D:$D,"GAWALI",Cash_Book!$E:$E,B38) | M38: =SUMIFS(Cash_Book!$G:$G,Cash_Book!$C:$C,"BEPAARI",Cash_Book!$D:$D,"CASH_ADV",Cash_Book!$E:$E,B38)+SUMIFS(Cash_Book!$H:$H,Cash_Book!$C:$C,"BEPAARI",Cash_Book!$D:$D,"CASH_ADV",Cash_Book!$E:$E,B38) | N38: =SUMIFS(Cash_Book!$G:$G,Cash_Book!$C:$C,"BEPAARI",Cash_Book!$D:$D,"OTHER",Cash_Book!$E:$E,B38)+SUMIFS(Cash_Book!$H:$H,Cash_Book!$C:$C,"BEPAARI",Cash_Book!$D:$D,"OTHER",Cash_Book!$E:$E,B38) | O38: =SUM(G38:N38) | P38: =IF(B38="","",E38-O38+D38) | Q38: =SUMIFS(Cash_Book!$G:$G,Cash_Book!$C:$C,"BEPAARI",Cash_Book!$D:$D,"PAYMENT",Cash_Book!$E:$E,B38)+SUMIFS(Cash_Book!$H:$H,Cash_Book!$C:$C,"BEPAARI",Cash_Book!$D:$D,"PAYMENT",Cash_Book!$E:$E,B38) | R38: =IF(B38="","",P38-Q38)
A39: 35 | B39: =IF(Masters!$B$37="","",Masters!$B$37) | C39: =IF(B39="","",Masters!$C$37) | D39: =IF(B39="",0,Masters!$D$37) | E39: =SUMIF(Daily_Sales!$C:$C,B39,Daily_Sales!$G:$G) | F39: =SUMIF(Daily_Sales!$C:$C,B39,Daily_Sales!$E:$E) | G39: =IF(B39="",0,E39*C39/100) | H39: =IF(F39>0,Masters!$X$3,0) | I39: =F39*Masters!$X$4 | J39: =SUMIFS(Cash_Book!$G:$G,Cash_Book!$C:$C,"BEPAARI",Cash_Book!$D:$D,"MOTOR",Cash_Book!$E:$E,B39)+SUMIFS(Cash_Book!$H:$H,Cash_Book!$C:$C,"BEPAARI",Cash_Book!$D:$D,"MOTOR",Cash_Book!$E:$E,B39) | K39: =SUMIFS(Cash_Book!$G:$G,Cash_Book!$C:$C,"BEPAARI",Cash_Book!$D:$D,"BHUSSA",Cash_Book!$E:$E,B39)+SUMIFS(Cash_Book!$H:$H,Cash_Book!$C:$C,"BEPAARI",Cash_Book!$D:$D,"BHUSSA",Cash_Book!$E:$E,B39) | L39: =SUMIFS(Cash_Book!$G:$G,Cash_Book!$C:$C,"BEPAARI",Cash_Book!$D:$D,"GAWALI",Cash_Book!$E:$E,B39)+SUMIFS(Cash_Book!$H:$H,Cash_Book!$C:$C,"BEPAARI",Cash_Book!$D:$D,"GAWALI",Cash_Book!$E:$E,B39) | M39: =SUMIFS(Cash_Book!$G:$G,Cash_Book!$C:$C,"BEPAARI",Cash_Book!$D:$D,"CASH_ADV",Cash_Book!$E:$E,B39)+SUMIFS(Cash_Book!$H:$H,Cash_Book!$C:$C,"BEPAARI",Cash_Book!$D:$D,"CASH_ADV",Cash_Book!$E:$E,B39) | N39: =SUMIFS(Cash_Book!$G:$G,Cash_Book!$C:$C,"BEPAARI",Cash_Book!$D:$D,"OTHER",Cash_Book!$E:$E,B39)+SUMIFS(Cash_Book!$H:$H,Cash_Book!$C:$C,"BEPAARI",Cash_Book!$D:$D,"OTHER",Cash_Book!$E:$E,B39) | O39: =SUM(G39:N39) | P39: =IF(B39="","",E39-O39+D39) | Q39: =SUMIFS(Cash_Book!$G:$G,Cash_Book!$C:$C,"BEPAARI",Cash_Book!$D:$D,"PAYMENT",Cash_Book!$E:$E,B39)+SUMIFS(Cash_Book!$H:$H,Cash_Book!$C:$C,"BEPAARI",Cash_Book!$D:$D,"PAYMENT",Cash_Book!$E:$E,B39) | R39: =IF(B39="","",P39-Q39)
A40: 36 | B40: =IF(Masters!$B$38="","",Masters!$B$38) | C40: =IF(B40="","",Masters!$C$38) | D40: =IF(B40="",0,Masters!$D$38) | E40: =SUMIF(Daily_Sales!$C:$C,B40,Daily_Sales!$G:$G) | F40: =SUMIF(Daily_Sales!$C:$C,B40,Daily_Sales!$E:$E) | G40: =IF(B40="",0,E40*C40/100) | H40: =IF(F40>0,Masters!$X$3,0) | I40: =F40*Masters!$X$4 | J40: =SUMIFS(Cash_Book!$G:$G,Cash_Book!$C:$C,"BEPAARI",Cash_Book!$D:$D,"MOTOR",Cash_Book!$E:$E,B40)+SUMIFS(Cash_Book!$H:$H,Cash_Book!$C:$C,"BEPAARI",Cash_Book!$D:$D,"MOTOR",Cash_Book!$E:$E,B40) | K40: =SUMIFS(Cash_Book!$G:$G,Cash_Book!$C:$C,"BEPAARI",Cash_Book!$D:$D,"BHUSSA",Cash_Book!$E:$E,B40)+SUMIFS(Cash_Book!$H:$H,Cash_Book!$C:$C,"BEPAARI",Cash_Book!$D:$D,"BHUSSA",Cash_Book!$E:$E,B40) | L40: =SUMIFS(Cash_Book!$G:$G,Cash_Book!$C:$C,"BEPAARI",Cash_Book!$D:$D,"GAWALI",Cash_Book!$E:$E,B40)+SUMIFS(Cash_Book!$H:$H,Cash_Book!$C:$C,"BEPAARI",Cash_Book!$D:$D,"GAWALI",Cash_Book!$E:$E,B40) | M40: =SUMIFS(Cash_Book!$G:$G,Cash_Book!$C:$C,"BEPAARI",Cash_Book!$D:$D,"CASH_ADV",Cash_Book!$E:$E,B40)+SUMIFS(Cash_Book!$H:$H,Cash_Book!$C:$C,"BEPAARI",Cash_Book!$D:$D,"CASH_ADV",Cash_Book!$E:$E,B40) | N40: =SUMIFS(Cash_Book!$G:$G,Cash_Book!$C:$C,"BEPAARI",Cash_Book!$D:$D,"OTHER",Cash_Book!$E:$E,B40)+SUMIFS(Cash_Book!$H:$H,Cash_Book!$C:$C,"BEPAARI",Cash_Book!$D:$D,"OTHER",Cash_Book!$E:$E,B40) | O40: =SUM(G40:N40) | P40: =IF(B40="","",E40-O40+D40) | Q40: =SUMIFS(Cash_Book!$G:$G,Cash_Book!$C:$C,"BEPAARI",Cash_Book!$D:$D,"PAYMENT",Cash_Book!$E:$E,B40)+SUMIFS(Cash_Book!$H:$H,Cash_Book!$C:$C,"BEPAARI",Cash_Book!$D:$D,"PAYMENT",Cash_Book!$E:$E,B40) | R40: =IF(B40="","",P40-Q40)
A41: 37 | B41: =IF(Masters!$B$39="","",Masters!$B$39) | C41: =IF(B41="","",Masters!$C$39) | D41: =IF(B41="",0,Masters!$D$39) | E41: =SUMIF(Daily_Sales!$C:$C,B41,Daily_Sales!$G:$G) | F41: =SUMIF(Daily_Sales!$C:$C,B41,Daily_Sales!$E:$E) | G41: =IF(B41="",0,E41*C41/100) | H41: =IF(F41>0,Masters!$X$3,0) | I41: =F41*Masters!$X$4 | J41: =SUMIFS(Cash_Book!$G:$G,Cash_Book!$C:$C,"BEPAARI",Cash_Book!$D:$D,"MOTOR",Cash_Book!$E:$E,B41)+SUMIFS(Cash_Book!$H:$H,Cash_Book!$C:$C,"BEPAARI",Cash_Book!$D:$D,"MOTOR",Cash_Book!$E:$E,B41) | K41: =SUMIFS(Cash_Book!$G:$G,Cash_Book!$C:$C,"BEPAARI",Cash_Book!$D:$D,"BHUSSA",Cash_Book!$E:$E,B41)+SUMIFS(Cash_Book!$H:$H,Cash_Book!$C:$C,"BEPAARI",Cash_Book!$D:$D,"BHUSSA",Cash_Book!$E:$E,B41) | L41: =SUMIFS(Cash_Book!$G:$G,Cash_Book!$C:$C,"BEPAARI",Cash_Book!$D:$D,"GAWALI",Cash_Book!$E:$E,B41)+SUMIFS(Cash_Book!$H:$H,Cash_Book!$C:$C,"BEPAARI",Cash_Book!$D:$D,"GAWALI",Cash_Book!$E:$E,B41) | M41: =SUMIFS(Cash_Book!$G:$G,Cash_Book!$C:$C,"BEPAARI",Cash_Book!$D:$D,"CASH_ADV",Cash_Book!$E:$E,B41)+SUMIFS(Cash_Book!$H:$H,Cash_Book!$C:$C,"BEPAARI",Cash_Book!$D:$D,"CASH_ADV",Cash_Book!$E:$E,B41) | N41: =SUMIFS(Cash_Book!$G:$G,Cash_Book!$C:$C,"BEPAARI",Cash_Book!$D:$D,"OTHER",Cash_Book!$E:$E,B41)+SUMIFS(Cash_Book!$H:$H,Cash_Book!$C:$C,"BEPAARI",Cash_Book!$D:$D,"OTHER",Cash_Book!$E:$E,B41) | O41: =SUM(G41:N41) | P41: =IF(B41="","",E41-O41+D41) | Q41: =SUMIFS(Cash_Book!$G:$G,Cash_Book!$C:$C,"BEPAARI",Cash_Book!$D:$D,"PAYMENT",Cash_Book!$E:$E,B41)+SUMIFS(Cash_Book!$H:$H,Cash_Book!$C:$C,"BEPAARI",Cash_Book!$D:$D,"PAYMENT",Cash_Book!$E:$E,B41) | R41: =IF(B41="","",P41-Q41)
A42: 38 | B42: =IF(Masters!$B$40="","",Masters!$B$40) | C42: =IF(B42="","",Masters!$C$40) | D42: =IF(B42="",0,Masters!$D$40) | E42: =SUMIF(Daily_Sales!$C:$C,B42,Daily_Sales!$G:$G) | F42: =SUMIF(Daily_Sales!$C:$C,B42,Daily_Sales!$E:$E) | G42: =IF(B42="",0,E42*C42/100) | H42: =IF(F42>0,Masters!$X$3,0) | I42: =F42*Masters!$X$4 | J42: =SUMIFS(Cash_Book!$G:$G,Cash_Book!$C:$C,"BEPAARI",Cash_Book!$D:$D,"MOTOR",Cash_Book!$E:$E,B42)+SUMIFS(Cash_Book!$H:$H,Cash_Book!$C:$C,"BEPAARI",Cash_Book!$D:$D,"MOTOR",Cash_Book!$E:$E,B42) | K42: =SUMIFS(Cash_Book!$G:$G,Cash_Book!$C:$C,"BEPAARI",Cash_Book!$D:$D,"BHUSSA",Cash_Book!$E:$E,B42)+SUMIFS(Cash_Book!$H:$H,Cash_Book!$C:$C,"BEPAARI",Cash_Book!$D:$D,"BHUSSA",Cash_Book!$E:$E,B42) | L42: =SUMIFS(Cash_Book!$G:$G,Cash_Book!$C:$C,"BEPAARI",Cash_Book!$D:$D,"GAWALI",Cash_Book!$E:$E,B42)+SUMIFS(Cash_Book!$H:$H,Cash_Book!$C:$C,"BEPAARI",Cash_Book!$D:$D,"GAWALI",Cash_Book!$E:$E,B42) | M42: =SUMIFS(Cash_Book!$G:$G,Cash_Book!$C:$C,"BEPAARI",Cash_Book!$D:$D,"CASH_ADV",Cash_Book!$E:$E,B42)+SUMIFS(Cash_Book!$H:$H,Cash_Book!$C:$C,"BEPAARI",Cash_Book!$D:$D,"CASH_ADV",Cash_Book!$E:$E,B42) | N42: =SUMIFS(Cash_Book!$G:$G,Cash_Book!$C:$C,"BEPAARI",Cash_Book!$D:$D,"OTHER",Cash_Book!$E:$E,B42)+SUMIFS(Cash_Book!$H:$H,Cash_Book!$C:$C,"BEPAARI",Cash_Book!$D:$D,"OTHER",Cash_Book!$E:$E,B42) | O42: =SUM(G42:N42) | P42: =IF(B42="","",E42-O42+D42) | Q42: =SUMIFS(Cash_Book!$G:$G,Cash_Book!$C:$C,"BEPAARI",Cash_Book!$D:$D,"PAYMENT",Cash_Book!$E:$E,B42)+SUMIFS(Cash_Book!$H:$H,Cash_Book!$C:$C,"BEPAARI",Cash_Book!$D:$D,"PAYMENT",Cash_Book!$E:$E,B42) | R42: =IF(B42="","",P42-Q42)
A43: 39 | B43: =IF(Masters!$B$41="","",Masters!$B$41) | C43: =IF(B43="","",Masters!$C$41) | D43: =IF(B43="",0,Masters!$D$41) | E43: =SUMIF(Daily_Sales!$C:$C,B43,Daily_Sales!$G:$G) | F43: =SUMIF(Daily_Sales!$C:$C,B43,Daily_Sales!$E:$E) | G43: =IF(B43="",0,E43*C43/100) | H43: =IF(F43>0,Masters!$X$3,0) | I43: =F43*Masters!$X$4 | J43: =SUMIFS(Cash_Book!$G:$G,Cash_Book!$C:$C,"BEPAARI",Cash_Book!$D:$D,"MOTOR",Cash_Book!$E:$E,B43)+SUMIFS(Cash_Book!$H:$H,Cash_Book!$C:$C,"BEPAARI",Cash_Book!$D:$D,"MOTOR",Cash_Book!$E:$E,B43) | K43: =SUMIFS(Cash_Book!$G:$G,Cash_Book!$C:$C,"BEPAARI",Cash_Book!$D:$D,"BHUSSA",Cash_Book!$E:$E,B43)+SUMIFS(Cash_Book!$H:$H,Cash_Book!$C:$C,"BEPAARI",Cash_Book!$D:$D,"BHUSSA",Cash_Book!$E:$E,B43) | L43: =SUMIFS(Cash_Book!$G:$G,Cash_Book!$C:$C,"BEPAARI",Cash_Book!$D:$D,"GAWALI",Cash_Book!$E:$E,B43)+SUMIFS(Cash_Book!$H:$H,Cash_Book!$C:$C,"BEPAARI",Cash_Book!$D:$D,"GAWALI",Cash_Book!$E:$E,B43) | M43: =SUMIFS(Cash_Book!$G:$G,Cash_Book!$C:$C,"BEPAARI",Cash_Book!$D:$D,"CASH_ADV",Cash_Book!$E:$E,B43)+SUMIFS(Cash_Book!$H:$H,Cash_Book!$C:$C,"BEPAARI",Cash_Book!$D:$D,"CASH_ADV",Cash_Book!$E:$E,B43) | N43: =SUMIFS(Cash_Book!$G:$G,Cash_Book!$C:$C,"BEPAARI",Cash_Book!$D:$D,"OTHER",Cash_Book!$E:$E,B43)+SUMIFS(Cash_Book!$H:$H,Cash_Book!$C:$C,"BEPAARI",Cash_Book!$D:$D,"OTHER",Cash_Book!$E:$E,B43) | O43: =SUM(G43:N43) | P43: =IF(B43="","",E43-O43+D43) | Q43: =SUMIFS(Cash_Book!$G:$G,Cash_Book!$C:$C,"BEPAARI",Cash_Book!$D:$D,"PAYMENT",Cash_Book!$E:$E,B43)+SUMIFS(Cash_Book!$H:$H,Cash_Book!$C:$C,"BEPAARI",Cash_Book!$D:$D,"PAYMENT",Cash_Book!$E:$E,B43) | R43: =IF(B43="","",P43-Q43)
A44: 40 | B44: =IF(Masters!$B$42="","",Masters!$B$42) | C44: =IF(B44="","",Masters!$C$42) | D44: =IF(B44="",0,Masters!$D$42) | E44: =SUMIF(Daily_Sales!$C:$C,B44,Daily_Sales!$G:$G) | F44: =SUMIF(Daily_Sales!$C:$C,B44,Daily_Sales!$E:$E) | G44: =IF(B44="",0,E44*C44/100) | H44: =IF(F44>0,Masters!$X$3,0) | I44: =F44*Masters!$X$4 | J44: =SUMIFS(Cash_Book!$G:$G,Cash_Book!$C:$C,"BEPAARI",Cash_Book!$D:$D,"MOTOR",Cash_Book!$E:$E,B44)+SUMIFS(Cash_Book!$H:$H,Cash_Book!$C:$C,"BEPAARI",Cash_Book!$D:$D,"MOTOR",Cash_Book!$E:$E,B44) | K44: =SUMIFS(Cash_Book!$G:$G,Cash_Book!$C:$C,"BEPAARI",Cash_Book!$D:$D,"BHUSSA",Cash_Book!$E:$E,B44)+SUMIFS(Cash_Book!$H:$H,Cash_Book!$C:$C,"BEPAARI",Cash_Book!$D:$D,"BHUSSA",Cash_Book!$E:$E,B44) | L44: =SUMIFS(Cash_Book!$G:$G,Cash_Book!$C:$C,"BEPAARI",Cash_Book!$D:$D,"GAWALI",Cash_Book!$E:$E,B44)+SUMIFS(Cash_Book!$H:$H,Cash_Book!$C:$C,"BEPAARI",Cash_Book!$D:$D,"GAWALI",Cash_Book!$E:$E,B44) | M44: =SUMIFS(Cash_Book!$G:$G,Cash_Book!$C:$C,"BEPAARI",Cash_Book!$D:$D,"CASH_ADV",Cash_Book!$E:$E,B44)+SUMIFS(Cash_Book!$H:$H,Cash_Book!$C:$C,"BEPAARI",Cash_Book!$D:$D,"CASH_ADV",Cash_Book!$E:$E,B44) | N44: =SUMIFS(Cash_Book!$G:$G,Cash_Book!$C:$C,"BEPAARI",Cash_Book!$D:$D,"OTHER",Cash_Book!$E:$E,B44)+SUMIFS(Cash_Book!$H:$H,Cash_Book!$C:$C,"BEPAARI",Cash_Book!$D:$D,"OTHER",Cash_Book!$E:$E,B44) | O44: =SUM(G44:N44) | P44: =IF(B44="","",E44-O44+D44) | Q44: =SUMIFS(Cash_Book!$G:$G,Cash_Book!$C:$C,"BEPAARI",Cash_Book!$D:$D,"PAYMENT",Cash_Book!$E:$E,B44)+SUMIFS(Cash_Book!$H:$H,Cash_Book!$C:$C,"BEPAARI",Cash_Book!$D:$D,"PAYMENT",Cash_Book!$E:$E,B44) | R44: =IF(B44="","",P44-Q44)
A45: 41 | B45: =IF(Masters!$B$43="","",Masters!$B$43) | C45: =IF(B45="","",Masters!$C$43) | D45: =IF(B45="",0,Masters!$D$43) | E45: =SUMIF(Daily_Sales!$C:$C,B45,Daily_Sales!$G:$G) | F45: =SUMIF(Daily_Sales!$C:$C,B45,Daily_Sales!$E:$E) | G45: =IF(B45="",0,E45*C45/100) | H45: =IF(F45>0,Masters!$X$3,0) | I45: =F45*Masters!$X$4 | J45: =SUMIFS(Cash_Book!$G:$G,Cash_Book!$C:$C,"BEPAARI",Cash_Book!$D:$D,"MOTOR",Cash_Book!$E:$E,B45)+SUMIFS(Cash_Book!$H:$H,Cash_Book!$C:$C,"BEPAARI",Cash_Book!$D:$D,"MOTOR",Cash_Book!$E:$E,B45) | K45: =SUMIFS(Cash_Book!$G:$G,Cash_Book!$C:$C,"BEPAARI",Cash_Book!$D:$D,"BHUSSA",Cash_Book!$E:$E,B45)+SUMIFS(Cash_Book!$H:$H,Cash_Book!$C:$C,"BEPAARI",Cash_Book!$D:$D,"BHUSSA",Cash_Book!$E:$E,B45) | L45: =SUMIFS(Cash_Book!$G:$G,Cash_Book!$C:$C,"BEPAARI",Cash_Book!$D:$D,"GAWALI",Cash_Book!$E:$E,B45)+SUMIFS(Cash_Book!$H:$H,Cash_Book!$C:$C,"BEPAARI",Cash_Book!$D:$D,"GAWALI",Cash_Book!$E:$E,B45) | M45: =SUMIFS(Cash_Book!$G:$G,Cash_Book!$C:$C,"BEPAARI",Cash_Book!$D:$D,"CASH_ADV",Cash_Book!$E:$E,B45)+SUMIFS(Cash_Book!$H:$H,Cash_Book!$C:$C,"BEPAARI",Cash_Book!$D:$D,"CASH_ADV",Cash_Book!$E:$E,B45) | N45: =SUMIFS(Cash_Book!$G:$G,Cash_Book!$C:$C,"BEPAARI",Cash_Book!$D:$D,"OTHER",Cash_Book!$E:$E,B45)+SUMIFS(Cash_Book!$H:$H,Cash_Book!$C:$C,"BEPAARI",Cash_Book!$D:$D,"OTHER",Cash_Book!$E:$E,B45) | O45: =SUM(G45:N45) | P45: =IF(B45="","",E45-O45+D45) | Q45: =SUMIFS(Cash_Book!$G:$G,Cash_Book!$C:$C,"BEPAARI",Cash_Book!$D:$D,"PAYMENT",Cash_Book!$E:$E,B45)+SUMIFS(Cash_Book!$H:$H,Cash_Book!$C:$C,"BEPAARI",Cash_Book!$D:$D,"PAYMENT",Cash_Book!$E:$E,B45) | R45: =IF(B45="","",P45-Q45)
A46: 42 | B46: =IF(Masters!$B$44="","",Masters!$B$44) | C46: =IF(B46="","",Masters!$C$44) | D46: =IF(B46="",0,Masters!$D$44) | E46: =SUMIF(Daily_Sales!$C:$C,B46,Daily_Sales!$G:$G) | F46: =SUMIF(Daily_Sales!$C:$C,B46,Daily_Sales!$E:$E) | G46: =IF(B46="",0,E46*C46/100) | H46: =IF(F46>0,Masters!$X$3,0) | I46: =F46*Masters!$X$4 | J46: =SUMIFS(Cash_Book!$G:$G,Cash_Book!$C:$C,"BEPAARI",Cash_Book!$D:$D,"MOTOR",Cash_Book!$E:$E,B46)+SUMIFS(Cash_Book!$H:$H,Cash_Book!$C:$C,"BEPAARI",Cash_Book!$D:$D,"MOTOR",Cash_Book!$E:$E,B46) | K46: =SUMIFS(Cash_Book!$G:$G,Cash_Book!$C:$C,"BEPAARI",Cash_Book!$D:$D,"BHUSSA",Cash_Book!$E:$E,B46)+SUMIFS(Cash_Book!$H:$H,Cash_Book!$C:$C,"BEPAARI",Cash_Book!$D:$D,"BHUSSA",Cash_Book!$E:$E,B46) | L46: =SUMIFS(Cash_Book!$G:$G,Cash_Book!$C:$C,"BEPAARI",Cash_Book!$D:$D,"GAWALI",Cash_Book!$E:$E,B46)+SUMIFS(Cash_Book!$H:$H,Cash_Book!$C:$C,"BEPAARI",Cash_Book!$D:$D,"GAWALI",Cash_Book!$E:$E,B46) | M46: =SUMIFS(Cash_Book!$G:$G,Cash_Book!$C:$C,"BEPAARI",Cash_Book!$D:$D,"CASH_ADV",Cash_Book!$E:$E,B46)+SUMIFS(Cash_Book!$H:$H,Cash_Book!$C:$C,"BEPAARI",Cash_Book!$D:$D,"CASH_ADV",Cash_Book!$E:$E,B46) | N46: =SUMIFS(Cash_Book!$G:$G,Cash_Book!$C:$C,"BEPAARI",Cash_Book!$D:$D,"OTHER",Cash_Book!$E:$E,B46)+SUMIFS(Cash_Book!$H:$H,Cash_Book!$C:$C,"BEPAARI",Cash_Book!$D:$D,"OTHER",Cash_Book!$E:$E,B46) | O46: =SUM(G46:N46) | P46: =IF(B46="","",E46-O46+D46) | Q46: =SUMIFS(Cash_Book!$G:$G,Cash_Book!$C:$C,"BEPAARI",Cash_Book!$D:$D,"PAYMENT",Cash_Book!$E:$E,B46)+SUMIFS(Cash_Book!$H:$H,Cash_Book!$C:$C,"BEPAARI",Cash_Book!$D:$D,"PAYMENT",Cash_Book!$E:$E,B46) | R46: =IF(B46="","",P46-Q46)
A47: 43 | B47: =IF(Masters!$B$45="","",Masters!$B$45) | C47: =IF(B47="","",Masters!$C$45) | D47: =IF(B47="",0,Masters!$D$45) | E47: =SUMIF(Daily_Sales!$C:$C,B47,Daily_Sales!$G:$G) | F47: =SUMIF(Daily_Sales!$C:$C,B47,Daily_Sales!$E:$E) | G47: =IF(B47="",0,E47*C47/100) | H47: =IF(F47>0,Masters!$X$3,0) | I47: =F47*Masters!$X$4 | J47: =SUMIFS(Cash_Book!$G:$G,Cash_Book!$C:$C,"BEPAARI",Cash_Book!$D:$D,"MOTOR",Cash_Book!$E:$E,B47)+SUMIFS(Cash_Book!$H:$H,Cash_Book!$C:$C,"BEPAARI",Cash_Book!$D:$D,"MOTOR",Cash_Book!$E:$E,B47) | K47: =SUMIFS(Cash_Book!$G:$G,Cash_Book!$C:$C,"BEPAARI",Cash_Book!$D:$D,"BHUSSA",Cash_Book!$E:$E,B47)+SUMIFS(Cash_Book!$H:$H,Cash_Book!$C:$C,"BEPAARI",Cash_Book!$D:$D,"BHUSSA",Cash_Book!$E:$E,B47) | L47: =SUMIFS(Cash_Book!$G:$G,Cash_Book!$C:$C,"BEPAARI",Cash_Book!$D:$D,"GAWALI",Cash_Book!$E:$E,B47)+SUMIFS(Cash_Book!$H:$H,Cash_Book!$C:$C,"BEPAARI",Cash_Book!$D:$D,"GAWALI",Cash_Book!$E:$E,B47) | M47: =SUMIFS(Cash_Book!$G:$G,Cash_Book!$C:$C,"BEPAARI",Cash_Book!$D:$D,"CASH_ADV",Cash_Book!$E:$E,B47)+SUMIFS(Cash_Book!$H:$H,Cash_Book!$C:$C,"BEPAARI",Cash_Book!$D:$D,"CASH_ADV",Cash_Book!$E:$E,B47) | N47: =SUMIFS(Cash_Book!$G:$G,Cash_Book!$C:$C,"BEPAARI",Cash_Book!$D:$D,"OTHER",Cash_Book!$E:$E,B47)+SUMIFS(Cash_Book!$H:$H,Cash_Book!$C:$C,"BEPAARI",Cash_Book!$D:$D,"OTHER",Cash_Book!$E:$E,B47) | O47: =SUM(G47:N47) | P47: =IF(B47="","",E47-O47+D47) | Q47: =SUMIFS(Cash_Book!$G:$G,Cash_Book!$C:$C,"BEPAARI",Cash_Book!$D:$D,"PAYMENT",Cash_Book!$E:$E,B47)+SUMIFS(Cash_Book!$H:$H,Cash_Book!$C:$C,"BEPAARI",Cash_Book!$D:$D,"PAYMENT",Cash_Book!$E:$E,B47) | R47: =IF(B47="","",P47-Q47)
A48: 44 | B48: =IF(Masters!$B$46="","",Masters!$B$46) | C48: =IF(B48="","",Masters!$C$46) | D48: =IF(B48="",0,Masters!$D$46) | E48: =SUMIF(Daily_Sales!$C:$C,B48,Daily_Sales!$G:$G) | F48: =SUMIF(Daily_Sales!$C:$C,B48,Daily_Sales!$E:$E) | G48: =IF(B48="",0,E48*C48/100) | H48: =IF(F48>0,Masters!$X$3,0) | I48: =F48*Masters!$X$4 | J48: =SUMIFS(Cash_Book!$G:$G,Cash_Book!$C:$C,"BEPAARI",Cash_Book!$D:$D,"MOTOR",Cash_Book!$E:$E,B48)+SUMIFS(Cash_Book!$H:$H,Cash_Book!$C:$C,"BEPAARI",Cash_Book!$D:$D,"MOTOR",Cash_Book!$E:$E,B48) | K48: =SUMIFS(Cash_Book!$G:$G,Cash_Book!$C:$C,"BEPAARI",Cash_Book!$D:$D,"BHUSSA",Cash_Book!$E:$E,B48)+SUMIFS(Cash_Book!$H:$H,Cash_Book!$C:$C,"BEPAARI",Cash_Book!$D:$D,"BHUSSA",Cash_Book!$E:$E,B48) | L48: =SUMIFS(Cash_Book!$G:$G,Cash_Book!$C:$C,"BEPAARI",Cash_Book!$D:$D,"GAWALI",Cash_Book!$E:$E,B48)+SUMIFS(Cash_Book!$H:$H,Cash_Book!$C:$C,"BEPAARI",Cash_Book!$D:$D,"GAWALI",Cash_Book!$E:$E,B48) | M48: =SUMIFS(Cash_Book!$G:$G,Cash_Book!$C:$C,"BEPAARI",Cash_Book!$D:$D,"CASH_ADV",Cash_Book!$E:$E,B48)+SUMIFS(Cash_Book!$H:$H,Cash_Book!$C:$C,"BEPAARI",Cash_Book!$D:$D,"CASH_ADV",Cash_Book!$E:$E,B48) | N48: =SUMIFS(Cash_Book!$G:$G,Cash_Book!$C:$C,"BEPAARI",Cash_Book!$D:$D,"OTHER",Cash_Book!$E:$E,B48)+SUMIFS(Cash_Book!$H:$H,Cash_Book!$C:$C,"BEPAARI",Cash_Book!$D:$D,"OTHER",Cash_Book!$E:$E,B48) | O48: =SUM(G48:N48) | P48: =IF(B48="","",E48-O48+D48) | Q48: =SUMIFS(Cash_Book!$G:$G,Cash_Book!$C:$C,"BEPAARI",Cash_Book!$D:$D,"PAYMENT",Cash_Book!$E:$E,B48)+SUMIFS(Cash_Book!$H:$H,Cash_Book!$C:$C,"BEPAARI",Cash_Book!$D:$D,"PAYMENT",Cash_Book!$E:$E,B48) | R48: =IF(B48="","",P48-Q48)
A49: 45 | B49: =IF(Masters!$B$47="","",Masters!$B$47) | C49: =IF(B49="","",Masters!$C$47) | D49: =IF(B49="",0,Masters!$D$47) | E49: =SUMIF(Daily_Sales!$C:$C,B49,Daily_Sales!$G:$G) | F49: =SUMIF(Daily_Sales!$C:$C,B49,Daily_Sales!$E:$E) | G49: =IF(B49="",0,E49*C49/100) | H49: =IF(F49>0,Masters!$X$3,0) | I49: =F49*Masters!$X$4 | J49: =SUMIFS(Cash_Book!$G:$G,Cash_Book!$C:$C,"BEPAARI",Cash_Book!$D:$D,"MOTOR",Cash_Book!$E:$E,B49)+SUMIFS(Cash_Book!$H:$H,Cash_Book!$C:$C,"BEPAARI",Cash_Book!$D:$D,"MOTOR",Cash_Book!$E:$E,B49) | K49: =SUMIFS(Cash_Book!$G:$G,Cash_Book!$C:$C,"BEPAARI",Cash_Book!$D:$D,"BHUSSA",Cash_Book!$E:$E,B49)+SUMIFS(Cash_Book!$H:$H,Cash_Book!$C:$C,"BEPAARI",Cash_Book!$D:$D,"BHUSSA",Cash_Book!$E:$E,B49) | L49: =SUMIFS(Cash_Book!$G:$G,Cash_Book!$C:$C,"BEPAARI",Cash_Book!$D:$D,"GAWALI",Cash_Book!$E:$E,B49)+SUMIFS(Cash_Book!$H:$H,Cash_Book!$C:$C,"BEPAARI",Cash_Book!$D:$D,"GAWALI",Cash_Book!$E:$E,B49) | M49: =SUMIFS(Cash_Book!$G:$G,Cash_Book!$C:$C,"BEPAARI",Cash_Book!$D:$D,"CASH_ADV",Cash_Book!$E:$E,B49)+SUMIFS(Cash_Book!$H:$H,Cash_Book!$C:$C,"BEPAARI",Cash_Book!$D:$D,"CASH_ADV",Cash_Book!$E:$E,B49) | N49: =SUMIFS(Cash_Book!$G:$G,Cash_Book!$C:$C,"BEPAARI",Cash_Book!$D:$D,"OTHER",Cash_Book!$E:$E,B49)+SUMIFS(Cash_Book!$H:$H,Cash_Book!$C:$C,"BEPAARI",Cash_Book!$D:$D,"OTHER",Cash_Book!$E:$E,B49) | O49: =SUM(G49:N49) | P49: =IF(B49="","",E49-O49+D49) | Q49: =SUMIFS(Cash_Book!$G:$G,Cash_Book!$C:$C,"BEPAARI",Cash_Book!$D:$D,"PAYMENT",Cash_Book!$E:$E,B49)+SUMIFS(Cash_Book!$H:$H,Cash_Book!$C:$C,"BEPAARI",Cash_Book!$D:$D,"PAYMENT",Cash_Book!$E:$E,B49) | R49: =IF(B49="","",P49-Q49)
A50: 46 | B50: =IF(Masters!$B$48="","",Masters!$B$48) | C50: =IF(B50="","",Masters!$C$48) | D50: =IF(B50="",0,Masters!$D$48) | E50: =SUMIF(Daily_Sales!$C:$C,B50,Daily_Sales!$G:$G) | F50: =SUMIF(Daily_Sales!$C:$C,B50,Daily_Sales!$E:$E) | G50: =IF(B50="",0,E50*C50/100) | H50: =IF(F50>0,Masters!$X$3,0) | I50: =F50*Masters!$X$4 | J50: =SUMIFS(Cash_Book!$G:$G,Cash_Book!$C:$C,"BEPAARI",Cash_Book!$D:$D,"MOTOR",Cash_Book!$E:$E,B50)+SUMIFS(Cash_Book!$H:$H,Cash_Book!$C:$C,"BEPAARI",Cash_Book!$D:$D,"MOTOR",Cash_Book!$E:$E,B50) | K50: =SUMIFS(Cash_Book!$G:$G,Cash_Book!$C:$C,"BEPAARI",Cash_Book!$D:$D,"BHUSSA",Cash_Book!$E:$E,B50)+SUMIFS(Cash_Book!$H:$H,Cash_Book!$C:$C,"BEPAARI",Cash_Book!$D:$D,"BHUSSA",Cash_Book!$E:$E,B50) | L50: =SUMIFS(Cash_Book!$G:$G,Cash_Book!$C:$C,"BEPAARI",Cash_Book!$D:$D,"GAWALI",Cash_Book!$E:$E,B50)+SUMIFS(Cash_Book!$H:$H,Cash_Book!$C:$C,"BEPAARI",Cash_Book!$D:$D,"GAWALI",Cash_Book!$E:$E,B50) | M50: =SUMIFS(Cash_Book!$G:$G,Cash_Book!$C:$C,"BEPAARI",Cash_Book!$D:$D,"CASH_ADV",Cash_Book!$E:$E,B50)+SUMIFS(Cash_Book!$H:$H,Cash_Book!$C:$C,"BEPAARI",Cash_Book!$D:$D,"CASH_ADV",Cash_Book!$E:$E,B50) | N50: =SUMIFS(Cash_Book!$G:$G,Cash_Book!$C:$C,"BEPAARI",Cash_Book!$D:$D,"OTHER",Cash_Book!$E:$E,B50)+SUMIFS(Cash_Book!$H:$H,Cash_Book!$C:$C,"BEPAARI",Cash_Book!$D:$D,"OTHER",Cash_Book!$E:$E,B50) | O50: =SUM(G50:N50) | P50: =IF(B50="","",E50-O50+D50) | Q50: =SUMIFS(Cash_Book!$G:$G,Cash_Book!$C:$C,"BEPAARI",Cash_Book!$D:$D,"PAYMENT",Cash_Book!$E:$E,B50)+SUMIFS(Cash_Book!$H:$H,Cash_Book!$C:$C,"BEPAARI",Cash_Book!$D:$D,"PAYMENT",Cash_Book!$E:$E,B50) | R50: =IF(B50="","",P50-Q50)
A51: 47 | B51: =IF(Masters!$B$49="","",Masters!$B$49) | C51: =IF(B51="","",Masters!$C$49) | D51: =IF(B51="",0,Masters!$D$49) | E51: =SUMIF(Daily_Sales!$C:$C,B51,Daily_Sales!$G:$G) | F51: =SUMIF(Daily_Sales!$C:$C,B51,Daily_Sales!$E:$E) | G51: =IF(B51="",0,E51*C51/100) | H51: =IF(F51>0,Masters!$X$3,0) | I51: =F51*Masters!$X$4 | J51: =SUMIFS(Cash_Book!$G:$G,Cash_Book!$C:$C,"BEPAARI",Cash_Book!$D:$D,"MOTOR",Cash_Book!$E:$E,B51)+SUMIFS(Cash_Book!$H:$H,Cash_Book!$C:$C,"BEPAARI",Cash_Book!$D:$D,"MOTOR",Cash_Book!$E:$E,B51) | K51: =SUMIFS(Cash_Book!$G:$G,Cash_Book!$C:$C,"BEPAARI",Cash_Book!$D:$D,"BHUSSA",Cash_Book!$E:$E,B51)+SUMIFS(Cash_Book!$H:$H,Cash_Book!$C:$C,"BEPAARI",Cash_Book!$D:$D,"BHUSSA",Cash_Book!$E:$E,B51) | L51: =SUMIFS(Cash_Book!$G:$G,Cash_Book!$C:$C,"BEPAARI",Cash_Book!$D:$D,"GAWALI",Cash_Book!$E:$E,B51)+SUMIFS(Cash_Book!$H:$H,Cash_Book!$C:$C,"BEPAARI",Cash_Book!$D:$D,"GAWALI",Cash_Book!$E:$E,B51) | M51: =SUMIFS(Cash_Book!$G:$G,Cash_Book!$C:$C,"BEPAARI",Cash_Book!$D:$D,"CASH_ADV",Cash_Book!$E:$E,B51)+SUMIFS(Cash_Book!$H:$H,Cash_Book!$C:$C,"BEPAARI",Cash_Book!$D:$D,"CASH_ADV",Cash_Book!$E:$E,B51) | N51: =SUMIFS(Cash_Book!$G:$G,Cash_Book!$C:$C,"BEPAARI",Cash_Book!$D:$D,"OTHER",Cash_Book!$E:$E,B51)+SUMIFS(Cash_Book!$H:$H,Cash_Book!$C:$C,"BEPAARI",Cash_Book!$D:$D,"OTHER",Cash_Book!$E:$E,B51) | O51: =SUM(G51:N51) | P51: =IF(B51="","",E51-O51+D51) | Q51: =SUMIFS(Cash_Book!$G:$G,Cash_Book!$C:$C,"BEPAARI",Cash_Book!$D:$D,"PAYMENT",Cash_Book!$E:$E,B51)+SUMIFS(Cash_Book!$H:$H,Cash_Book!$C:$C,"BEPAARI",Cash_Book!$D:$D,"PAYMENT",Cash_Book!$E:$E,B51) | R51: =IF(B51="","",P51-Q51)
A52: 48 | B52: =IF(Masters!$B$50="","",Masters!$B$50) | C52: =IF(B52="","",Masters!$C$50) | D52: =IF(B52="",0,Masters!$D$50) | E52: =SUMIF(Daily_Sales!$C:$C,B52,Daily_Sales!$G:$G) | F52: =SUMIF(Daily_Sales!$C:$C,B52,Daily_Sales!$E:$E) | G52: =IF(B52="",0,E52*C52/100) | H52: =IF(F52>0,Masters!$X$3,0) | I52: =F52*Masters!$X$4 | J52: =SUMIFS(Cash_Book!$G:$G,Cash_Book!$C:$C,"BEPAARI",Cash_Book!$D:$D,"MOTOR",Cash_Book!$E:$E,B52)+SUMIFS(Cash_Book!$H:$H,Cash_Book!$C:$C,"BEPAARI",Cash_Book!$D:$D,"MOTOR",Cash_Book!$E:$E,B52) | K52: =SUMIFS(Cash_Book!$G:$G,Cash_Book!$C:$C,"BEPAARI",Cash_Book!$D:$D,"BHUSSA",Cash_Book!$E:$E,B52)+SUMIFS(Cash_Book!$H:$H,Cash_Book!$C:$C,"BEPAARI",Cash_Book!$D:$D,"BHUSSA",Cash_Book!$E:$E,B52) | L52: =SUMIFS(Cash_Book!$G:$G,Cash_Book!$C:$C,"BEPAARI",Cash_Book!$D:$D,"GAWALI",Cash_Book!$E:$E,B52)+SUMIFS(Cash_Book!$H:$H,Cash_Book!$C:$C,"BEPAARI",Cash_Book!$D:$D,"GAWALI",Cash_Book!$E:$E,B52) | M52: =SUMIFS(Cash_Book!$G:$G,Cash_Book!$C:$C,"BEPAARI",Cash_Book!$D:$D,"CASH_ADV",Cash_Book!$E:$E,B52)+SUMIFS(Cash_Book!$H:$H,Cash_Book!$C:$C,"BEPAARI",Cash_Book!$D:$D,"CASH_ADV",Cash_Book!$E:$E,B52) | N52: =SUMIFS(Cash_Book!$G:$G,Cash_Book!$C:$C,"BEPAARI",Cash_Book!$D:$D,"OTHER",Cash_Book!$E:$E,B52)+SUMIFS(Cash_Book!$H:$H,Cash_Book!$C:$C,"BEPAARI",Cash_Book!$D:$D,"OTHER",Cash_Book!$E:$E,B52) | O52: =SUM(G52:N52) | P52: =IF(B52="","",E52-O52+D52) | Q52: =SUMIFS(Cash_Book!$G:$G,Cash_Book!$C:$C,"BEPAARI",Cash_Book!$D:$D,"PAYMENT",Cash_Book!$E:$E,B52)+SUMIFS(Cash_Book!$H:$H,Cash_Book!$C:$C,"BEPAARI",Cash_Book!$D:$D,"PAYMENT",Cash_Book!$E:$E,B52) | R52: =IF(B52="","",P52-Q52)
A53: 49 | B53: =IF(Masters!$B$51="","",Masters!$B$51) | C53: =IF(B53="","",Masters!$C$51) | D53: =IF(B53="",0,Masters!$D$51) | E53: =SUMIF(Daily_Sales!$C:$C,B53,Daily_Sales!$G:$G) | F53: =SUMIF(Daily_Sales!$C:$C,B53,Daily_Sales!$E:$E) | G53: =IF(B53="",0,E53*C53/100) | H53: =IF(F53>0,Masters!$X$3,0) | I53: =F53*Masters!$X$4 | J53: =SUMIFS(Cash_Book!$G:$G,Cash_Book!$C:$C,"BEPAARI",Cash_Book!$D:$D,"MOTOR",Cash_Book!$E:$E,B53)+SUMIFS(Cash_Book!$H:$H,Cash_Book!$C:$C,"BEPAARI",Cash_Book!$D:$D,"MOTOR",Cash_Book!$E:$E,B53) | K53: =SUMIFS(Cash_Book!$G:$G,Cash_Book!$C:$C,"BEPAARI",Cash_Book!$D:$D,"BHUSSA",Cash_Book!$E:$E,B53)+SUMIFS(Cash_Book!$H:$H,Cash_Book!$C:$C,"BEPAARI",Cash_Book!$D:$D,"BHUSSA",Cash_Book!$E:$E,B53) | L53: =SUMIFS(Cash_Book!$G:$G,Cash_Book!$C:$C,"BEPAARI",Cash_Book!$D:$D,"GAWALI",Cash_Book!$E:$E,B53)+SUMIFS(Cash_Book!$H:$H,Cash_Book!$C:$C,"BEPAARI",Cash_Book!$D:$D,"GAWALI",Cash_Book!$E:$E,B53) | M53: =SUMIFS(Cash_Book!$G:$G,Cash_Book!$C:$C,"BEPAARI",Cash_Book!$D:$D,"CASH_ADV",Cash_Book!$E:$E,B53)+SUMIFS(Cash_Book!$H:$H,Cash_Book!$C:$C,"BEPAARI",Cash_Book!$D:$D,"CASH_ADV",Cash_Book!$E:$E,B53) | N53: =SUMIFS(Cash_Book!$G:$G,Cash_Book!$C:$C,"BEPAARI",Cash_Book!$D:$D,"OTHER",Cash_Book!$E:$E,B53)+SUMIFS(Cash_Book!$H:$H,Cash_Book!$C:$C,"BEPAARI",Cash_Book!$D:$D,"OTHER",Cash_Book!$E:$E,B53) | O53: =SUM(G53:N53) | P53: =IF(B53="","",E53-O53+D53) | Q53: =SUMIFS(Cash_Book!$G:$G,Cash_Book!$C:$C,"BEPAARI",Cash_Book!$D:$D,"PAYMENT",Cash_Book!$E:$E,B53)+SUMIFS(Cash_Book!$H:$H,Cash_Book!$C:$C,"BEPAARI",Cash_Book!$D:$D,"PAYMENT",Cash_Book!$E:$E,B53) | R53: =IF(B53="","",P53-Q53)
A54: 50 | B54: =IF(Masters!$B$52="","",Masters!$B$52) | C54: =IF(B54="","",Masters!$C$52) | D54: =IF(B54="",0,Masters!$D$52) | E54: =SUMIF(Daily_Sales!$C:$C,B54,Daily_Sales!$G:$G) | F54: =SUMIF(Daily_Sales!$C:$C,B54,Daily_Sales!$E:$E) | G54: =IF(B54="",0,E54*C54/100) | H54: =IF(F54>0,Masters!$X$3,0) | I54: =F54*Masters!$X$4 | J54: =SUMIFS(Cash_Book!$G:$G,Cash_Book!$C:$C,"BEPAARI",Cash_Book!$D:$D,"MOTOR",Cash_Book!$E:$E,B54)+SUMIFS(Cash_Book!$H:$H,Cash_Book!$C:$C,"BEPAARI",Cash_Book!$D:$D,"MOTOR",Cash_Book!$E:$E,B54) | K54: =SUMIFS(Cash_Book!$G:$G,Cash_Book!$C:$C,"BEPAARI",Cash_Book!$D:$D,"BHUSSA",Cash_Book!$E:$E,B54)+SUMIFS(Cash_Book!$H:$H,Cash_Book!$C:$C,"BEPAARI",Cash_Book!$D:$D,"BHUSSA",Cash_Book!$E:$E,B54) | L54: =SUMIFS(Cash_Book!$G:$G,Cash_Book!$C:$C,"BEPAARI",Cash_Book!$D:$D,"GAWALI",Cash_Book!$E:$E,B54)+SUMIFS(Cash_Book!$H:$H,Cash_Book!$C:$C,"BEPAARI",Cash_Book!$D:$D,"GAWALI",Cash_Book!$E:$E,B54) | M54: =SUMIFS(Cash_Book!$G:$G,Cash_Book!$C:$C,"BEPAARI",Cash_Book!$D:$D,"CASH_ADV",Cash_Book!$E:$E,B54)+SUMIFS(Cash_Book!$H:$H,Cash_Book!$C:$C,"BEPAARI",Cash_Book!$D:$D,"CASH_ADV",Cash_Book!$E:$E,B54) | N54: =SUMIFS(Cash_Book!$G:$G,Cash_Book!$C:$C,"BEPAARI",Cash_Book!$D:$D,"OTHER",Cash_Book!$E:$E,B54)+SUMIFS(Cash_Book!$H:$H,Cash_Book!$C:$C,"BEPAARI",Cash_Book!$D:$D,"OTHER",Cash_Book!$E:$E,B54) | O54: =SUM(G54:N54) | P54: =IF(B54="","",E54-O54+D54) | Q54: =SUMIFS(Cash_Book!$G:$G,Cash_Book!$C:$C,"BEPAARI",Cash_Book!$D:$D,"PAYMENT",Cash_Book!$E:$E,B54)+SUMIFS(Cash_Book!$H:$H,Cash_Book!$C:$C,"BEPAARI",Cash_Book!$D:$D,"PAYMENT",Cash_Book!$E:$E,B54) | R54: =IF(B54="","",P54-Q54)
A55: 51 | B55: =IF(Masters!$B$53="","",Masters!$B$53) | C55: =IF(B55="","",Masters!$C$53) | D55: =IF(B55="",0,Masters!$D$53) | E55: =SUMIF(Daily_Sales!$C:$C,B55,Daily_Sales!$G:$G) | F55: =SUMIF(Daily_Sales!$C:$C,B55,Daily_Sales!$E:$E) | G55: =IF(B55="",0,E55*C55/100) | H55: =IF(F55>0,Masters!$X$3,0) | I55: =F55*Masters!$X$4 | J55: =SUMIFS(Cash_Book!$G:$G,Cash_Book!$C:$C,"BEPAARI",Cash_Book!$D:$D,"MOTOR",Cash_Book!$E:$E,B55)+SUMIFS(Cash_Book!$H:$H,Cash_Book!$C:$C,"BEPAARI",Cash_Book!$D:$D,"MOTOR",Cash_Book!$E:$E,B55) | K55: =SUMIFS(Cash_Book!$G:$G,Cash_Book!$C:$C,"BEPAARI",Cash_Book!$D:$D,"BHUSSA",Cash_Book!$E:$E,B55)+SUMIFS(Cash_Book!$H:$H,Cash_Book!$C:$C,"BEPAARI",Cash_Book!$D:$D,"BHUSSA",Cash_Book!$E:$E,B55) | L55: =SUMIFS(Cash_Book!$G:$G,Cash_Book!$C:$C,"BEPAARI",Cash_Book!$D:$D,"GAWALI",Cash_Book!$E:$E,B55)+SUMIFS(Cash_Book!$H:$H,Cash_Book!$C:$C,"BEPAARI",Cash_Book!$D:$D,"GAWALI",Cash_Book!$E:$E,B55) | M55: =SUMIFS(Cash_Book!$G:$G,Cash_Book!$C:$C,"BEPAARI",Cash_Book!$D:$D,"CASH_ADV",Cash_Book!$E:$E,B55)+SUMIFS(Cash_Book!$H:$H,Cash_Book!$C:$C,"BEPAARI",Cash_Book!$D:$D,"CASH_ADV",Cash_Book!$E:$E,B55) | N55: =SUMIFS(Cash_Book!$G:$G,Cash_Book!$C:$C,"BEPAARI",Cash_Book!$D:$D,"OTHER",Cash_Book!$E:$E,B55)+SUMIFS(Cash_Book!$H:$H,Cash_Book!$C:$C,"BEPAARI",Cash_Book!$D:$D,"OTHER",Cash_Book!$E:$E,B55) | O55: =SUM(G55:N55) | P55: =IF(B55="","",E55-O55+D55) | Q55: =SUMIFS(Cash_Book!$G:$G,Cash_Book!$C:$C,"BEPAARI",Cash_Book!$D:$D,"PAYMENT",Cash_Book!$E:$E,B55)+SUMIFS(Cash_Book!$H:$H,Cash_Book!$C:$C,"BEPAARI",Cash_Book!$D:$D,"PAYMENT",Cash_Book!$E:$E,B55) | R55: =IF(B55="","",P55-Q55)
A56: 52 | B56: =IF(Masters!$B$54="","",Masters!$B$54) | C56: =IF(B56="","",Masters!$C$54) | D56: =IF(B56="",0,Masters!$D$54) | E56: =SUMIF(Daily_Sales!$C:$C,B56,Daily_Sales!$G:$G) | F56: =SUMIF(Daily_Sales!$C:$C,B56,Daily_Sales!$E:$E) | G56: =IF(B56="",0,E56*C56/100) | H56: =IF(F56>0,Masters!$X$3,0) | I56: =F56*Masters!$X$4 | J56: =SUMIFS(Cash_Book!$G:$G,Cash_Book!$C:$C,"BEPAARI",Cash_Book!$D:$D,"MOTOR",Cash_Book!$E:$E,B56)+SUMIFS(Cash_Book!$H:$H,Cash_Book!$C:$C,"BEPAARI",Cash_Book!$D:$D,"MOTOR",Cash_Book!$E:$E,B56) | K56: =SUMIFS(Cash_Book!$G:$G,Cash_Book!$C:$C,"BEPAARI",Cash_Book!$D:$D,"BHUSSA",Cash_Book!$E:$E,B56)+SUMIFS(Cash_Book!$H:$H,Cash_Book!$C:$C,"BEPAARI",Cash_Book!$D:$D,"BHUSSA",Cash_Book!$E:$E,B56) | L56: =SUMIFS(Cash_Book!$G:$G,Cash_Book!$C:$C,"BEPAARI",Cash_Book!$D:$D,"GAWALI",Cash_Book!$E:$E,B56)+SUMIFS(Cash_Book!$H:$H,Cash_Book!$C:$C,"BEPAARI",Cash_Book!$D:$D,"GAWALI",Cash_Book!$E:$E,B56) | M56: =SUMIFS(Cash_Book!$G:$G,Cash_Book!$C:$C,"BEPAARI",Cash_Book!$D:$D,"CASH_ADV",Cash_Book!$E:$E,B56)+SUMIFS(Cash_Book!$H:$H,Cash_Book!$C:$C,"BEPAARI",Cash_Book!$D:$D,"CASH_ADV",Cash_Book!$E:$E,B56) | N56: =SUMIFS(Cash_Book!$G:$G,Cash_Book!$C:$C,"BEPAARI",Cash_Book!$D:$D,"OTHER",Cash_Book!$E:$E,B56)+SUMIFS(Cash_Book!$H:$H,Cash_Book!$C:$C,"BEPAARI",Cash_Book!$D:$D,"OTHER",Cash_Book!$E:$E,B56) | O56: =SUM(G56:N56) | P56: =IF(B56="","",E56-O56+D56) | Q56: =SUMIFS(Cash_Book!$G:$G,Cash_Book!$C:$C,"BEPAARI",Cash_Book!$D:$D,"PAYMENT",Cash_Book!$E:$E,B56)+SUMIFS(Cash_Book!$H:$H,Cash_Book!$C:$C,"BEPAARI",Cash_Book!$D:$D,"PAYMENT",Cash_Book!$E:$E,B56) | R56: =IF(B56="","",P56-Q56)
A57: 53 | B57: =IF(Masters!$B$55="","",Masters!$B$55) | C57: =IF(B57="","",Masters!$C$55) | D57: =IF(B57="",0,Masters!$D$55) | E57: =SUMIF(Daily_Sales!$C:$C,B57,Daily_Sales!$G:$G) | F57: =SUMIF(Daily_Sales!$C:$C,B57,Daily_Sales!$E:$E) | G57: =IF(B57="",0,E57*C57/100) | H57: =IF(F57>0,Masters!$X$3,0) | I57: =F57*Masters!$X$4 | J57: =SUMIFS(Cash_Book!$G:$G,Cash_Book!$C:$C,"BEPAARI",Cash_Book!$D:$D,"MOTOR",Cash_Book!$E:$E,B57)+SUMIFS(Cash_Book!$H:$H,Cash_Book!$C:$C,"BEPAARI",Cash_Book!$D:$D,"MOTOR",Cash_Book!$E:$E,B57) | K57: =SUMIFS(Cash_Book!$G:$G,Cash_Book!$C:$C,"BEPAARI",Cash_Book!$D:$D,"BHUSSA",Cash_Book!$E:$E,B57)+SUMIFS(Cash_Book!$H:$H,Cash_Book!$C:$C,"BEPAARI",Cash_Book!$D:$D,"BHUSSA",Cash_Book!$E:$E,B57) | L57: =SUMIFS(Cash_Book!$G:$G,Cash_Book!$C:$C,"BEPAARI",Cash_Book!$D:$D,"GAWALI",Cash_Book!$E:$E,B57)+SUMIFS(Cash_Book!$H:$H,Cash_Book!$C:$C,"BEPAARI",Cash_Book!$D:$D,"GAWALI",Cash_Book!$E:$E,B57) | M57: =SUMIFS(Cash_Book!$G:$G,Cash_Book!$C:$C,"BEPAARI",Cash_Book!$D:$D,"CASH_ADV",Cash_Book!$E:$E,B57)+SUMIFS(Cash_Book!$H:$H,Cash_Book!$C:$C,"BEPAARI",Cash_Book!$D:$D,"CASH_ADV",Cash_Book!$E:$E,B57) | N57: =SUMIFS(Cash_Book!$G:$G,Cash_Book!$C:$C,"BEPAARI",Cash_Book!$D:$D,"OTHER",Cash_Book!$E:$E,B57)+SUMIFS(Cash_Book!$H:$H,Cash_Book!$C:$C,"BEPAARI",Cash_Book!$D:$D,"OTHER",Cash_Book!$E:$E,B57) | O57: =SUM(G57:N57) | P57: =IF(B57="","",E57-O57+D57) | Q57: =SUMIFS(Cash_Book!$G:$G,Cash_Book!$C:$C,"BEPAARI",Cash_Book!$D:$D,"PAYMENT",Cash_Book!$E:$E,B57)+SUMIFS(Cash_Book!$H:$H,Cash_Book!$C:$C,"BEPAARI",Cash_Book!$D:$D,"PAYMENT",Cash_Book!$E:$E,B57) | R57: =IF(B57="","",P57-Q57)
A58: 54 | B58: =IF(Masters!$B$56="","",Masters!$B$56) | C58: =IF(B58="","",Masters!$C$56) | D58: =IF(B58="",0,Masters!$D$56) | E58: =SUMIF(Daily_Sales!$C:$C,B58,Daily_Sales!$G:$G) | F58: =SUMIF(Daily_Sales!$C:$C,B58,Daily_Sales!$E:$E) | G58: =IF(B58="",0,E58*C58/100) | H58: =IF(F58>0,Masters!$X$3,0) | I58: =F58*Masters!$X$4 | J58: =SUMIFS(Cash_Book!$G:$G,Cash_Book!$C:$C,"BEPAARI",Cash_Book!$D:$D,"MOTOR",Cash_Book!$E:$E,B58)+SUMIFS(Cash_Book!$H:$H,Cash_Book!$C:$C,"BEPAARI",Cash_Book!$D:$D,"MOTOR",Cash_Book!$E:$E,B58) | K58: =SUMIFS(Cash_Book!$G:$G,Cash_Book!$C:$C,"BEPAARI",Cash_Book!$D:$D,"BHUSSA",Cash_Book!$E:$E,B58)+SUMIFS(Cash_Book!$H:$H,Cash_Book!$C:$C,"BEPAARI",Cash_Book!$D:$D,"BHUSSA",Cash_Book!$E:$E,B58) | L58: =SUMIFS(Cash_Book!$G:$G,Cash_Book!$C:$C,"BEPAARI",Cash_Book!$D:$D,"GAWALI",Cash_Book!$E:$E,B58)+SUMIFS(Cash_Book!$H:$H,Cash_Book!$C:$C,"BEPAARI",Cash_Book!$D:$D,"GAWALI",Cash_Book!$E:$E,B58) | M58: =SUMIFS(Cash_Book!$G:$G,Cash_Book!$C:$C,"BEPAARI",Cash_Book!$D:$D,"CASH_ADV",Cash_Book!$E:$E,B58)+SUMIFS(Cash_Book!$H:$H,Cash_Book!$C:$C,"BEPAARI",Cash_Book!$D:$D,"CASH_ADV",Cash_Book!$E:$E,B58) | N58: =SUMIFS(Cash_Book!$G:$G,Cash_Book!$C:$C,"BEPAARI",Cash_Book!$D:$D,"OTHER",Cash_Book!$E:$E,B58)+SUMIFS(Cash_Book!$H:$H,Cash_Book!$C:$C,"BEPAARI",Cash_Book!$D:$D,"OTHER",Cash_Book!$E:$E,B58) | O58: =SUM(G58:N58) | P58: =IF(B58="","",E58-O58+D58) | Q58: =SUMIFS(Cash_Book!$G:$G,Cash_Book!$C:$C,"BEPAARI",Cash_Book!$D:$D,"PAYMENT",Cash_Book!$E:$E,B58)+SUMIFS(Cash_Book!$H:$H,Cash_Book!$C:$C,"BEPAARI",Cash_Book!$D:$D,"PAYMENT",Cash_Book!$E:$E,B58) | R58: =IF(B58="","",P58-Q58)
A59: 55 | B59: =IF(Masters!$B$57="","",Masters!$B$57) | C59: =IF(B59="","",Masters!$C$57) | D59: =IF(B59="",0,Masters!$D$57) | E59: =SUMIF(Daily_Sales!$C:$C,B59,Daily_Sales!$G:$G) | F59: =SUMIF(Daily_Sales!$C:$C,B59,Daily_Sales!$E:$E) | G59: =IF(B59="",0,E59*C59/100) | H59: =IF(F59>0,Masters!$X$3,0) | I59: =F59*Masters!$X$4 | J59: =SUMIFS(Cash_Book!$G:$G,Cash_Book!$C:$C,"BEPAARI",Cash_Book!$D:$D,"MOTOR",Cash_Book!$E:$E,B59)+SUMIFS(Cash_Book!$H:$H,Cash_Book!$C:$C,"BEPAARI",Cash_Book!$D:$D,"MOTOR",Cash_Book!$E:$E,B59) | K59: =SUMIFS(Cash_Book!$G:$G,Cash_Book!$C:$C,"BEPAARI",Cash_Book!$D:$D,"BHUSSA",Cash_Book!$E:$E,B59)+SUMIFS(Cash_Book!$H:$H,Cash_Book!$C:$C,"BEPAARI",Cash_Book!$D:$D,"BHUSSA",Cash_Book!$E:$E,B59) | L59: =SUMIFS(Cash_Book!$G:$G,Cash_Book!$C:$C,"BEPAARI",Cash_Book!$D:$D,"GAWALI",Cash_Book!$E:$E,B59)+SUMIFS(Cash_Book!$H:$H,Cash_Book!$C:$C,"BEPAARI",Cash_Book!$D:$D,"GAWALI",Cash_Book!$E:$E,B59) | M59: =SUMIFS(Cash_Book!$G:$G,Cash_Book!$C:$C,"BEPAARI",Cash_Book!$D:$D,"CASH_ADV",Cash_Book!$E:$E,B59)+SUMIFS(Cash_Book!$H:$H,Cash_Book!$C:$C,"BEPAARI",Cash_Book!$D:$D,"CASH_ADV",Cash_Book!$E:$E,B59) | N59: =SUMIFS(Cash_Book!$G:$G,Cash_Book!$C:$C,"BEPAARI",Cash_Book!$D:$D,"OTHER",Cash_Book!$E:$E,B59)+SUMIFS(Cash_Book!$H:$H,Cash_Book!$C:$C,"BEPAARI",Cash_Book!$D:$D,"OTHER",Cash_Book!$E:$E,B59) | O59: =SUM(G59:N59) | P59: =IF(B59="","",E59-O59+D59) | Q59: =SUMIFS(Cash_Book!$G:$G,Cash_Book!$C:$C,"BEPAARI",Cash_Book!$D:$D,"PAYMENT",Cash_Book!$E:$E,B59)+SUMIFS(Cash_Book!$H:$H,Cash_Book!$C:$C,"BEPAARI",Cash_Book!$D:$D,"PAYMENT",Cash_Book!$E:$E,B59) | R59: =IF(B59="","",P59-Q59)
A60: 56 | B60: =IF(Masters!$B$58="","",Masters!$B$58) | C60: =IF(B60="","",Masters!$C$58) | D60: =IF(B60="",0,Masters!$D$58) | E60: =SUMIF(Daily_Sales!$C:$C,B60,Daily_Sales!$G:$G) | F60: =SUMIF(Daily_Sales!$C:$C,B60,Daily_Sales!$E:$E) | G60: =IF(B60="",0,E60*C60/100) | H60: =IF(F60>0,Masters!$X$3,0) | I60: =F60*Masters!$X$4 | J60: =SUMIFS(Cash_Book!$G:$G,Cash_Book!$C:$C,"BEPAARI",Cash_Book!$D:$D,"MOTOR",Cash_Book!$E:$E,B60)+SUMIFS(Cash_Book!$H:$H,Cash_Book!$C:$C,"BEPAARI",Cash_Book!$D:$D,"MOTOR",Cash_Book!$E:$E,B60) | K60: =SUMIFS(Cash_Book!$G:$G,Cash_Book!$C:$C,"BEPAARI",Cash_Book!$D:$D,"BHUSSA",Cash_Book!$E:$E,B60)+SUMIFS(Cash_Book!$H:$H,Cash_Book!$C:$C,"BEPAARI",Cash_Book!$D:$D,"BHUSSA",Cash_Book!$E:$E,B60) | L60: =SUMIFS(Cash_Book!$G:$G,Cash_Book!$C:$C,"BEPAARI",Cash_Book!$D:$D,"GAWALI",Cash_Book!$E:$E,B60)+SUMIFS(Cash_Book!$H:$H,Cash_Book!$C:$C,"BEPAARI",Cash_Book!$D:$D,"GAWALI",Cash_Book!$E:$E,B60) | M60: =SUMIFS(Cash_Book!$G:$G,Cash_Book!$C:$C,"BEPAARI",Cash_Book!$D:$D,"CASH_ADV",Cash_Book!$E:$E,B60)+SUMIFS(Cash_Book!$H:$H,Cash_Book!$C:$C,"BEPAARI",Cash_Book!$D:$D,"CASH_ADV",Cash_Book!$E:$E,B60) | N60: =SUMIFS(Cash_Book!$G:$G,Cash_Book!$C:$C,"BEPAARI",Cash_Book!$D:$D,"OTHER",Cash_Book!$E:$E,B60)+SUMIFS(Cash_Book!$H:$H,Cash_Book!$C:$C,"BEPAARI",Cash_Book!$D:$D,"OTHER",Cash_Book!$E:$E,B60) | O60: =SUM(G60:N60) | P60: =IF(B60="","",E60-O60+D60) | Q60: =SUMIFS(Cash_Book!$G:$G,Cash_Book!$C:$C,"BEPAARI",Cash_Book!$D:$D,"PAYMENT",Cash_Book!$E:$E,B60)+SUMIFS(Cash_Book!$H:$H,Cash_Book!$C:$C,"BEPAARI",Cash_Book!$D:$D,"PAYMENT",Cash_Book!$E:$E,B60) | R60: =IF(B60="","",P60-Q60)
A61: 57 | B61: =IF(Masters!$B$59="","",Masters!$B$59) | C61: =IF(B61="","",Masters!$C$59) | D61: =IF(B61="",0,Masters!$D$59) | E61: =SUMIF(Daily_Sales!$C:$C,B61,Daily_Sales!$G:$G) | F61: =SUMIF(Daily_Sales!$C:$C,B61,Daily_Sales!$E:$E) | G61: =IF(B61="",0,E61*C61/100) | H61: =IF(F61>0,Masters!$X$3,0) | I61: =F61*Masters!$X$4 | J61: =SUMIFS(Cash_Book!$G:$G,Cash_Book!$C:$C,"BEPAARI",Cash_Book!$D:$D,"MOTOR",Cash_Book!$E:$E,B61)+SUMIFS(Cash_Book!$H:$H,Cash_Book!$C:$C,"BEPAARI",Cash_Book!$D:$D,"MOTOR",Cash_Book!$E:$E,B61) | K61: =SUMIFS(Cash_Book!$G:$G,Cash_Book!$C:$C,"BEPAARI",Cash_Book!$D:$D,"BHUSSA",Cash_Book!$E:$E,B61)+SUMIFS(Cash_Book!$H:$H,Cash_Book!$C:$C,"BEPAARI",Cash_Book!$D:$D,"BHUSSA",Cash_Book!$E:$E,B61) | L61: =SUMIFS(Cash_Book!$G:$G,Cash_Book!$C:$C,"BEPAARI",Cash_Book!$D:$D,"GAWALI",Cash_Book!$E:$E,B61)+SUMIFS(Cash_Book!$H:$H,Cash_Book!$C:$C,"BEPAARI",Cash_Book!$D:$D,"GAWALI",Cash_Book!$E:$E,B61) | M61: =SUMIFS(Cash_Book!$G:$G,Cash_Book!$C:$C,"BEPAARI",Cash_Book!$D:$D,"CASH_ADV",Cash_Book!$E:$E,B61)+SUMIFS(Cash_Book!$H:$H,Cash_Book!$C:$C,"BEPAARI",Cash_Book!$D:$D,"CASH_ADV",Cash_Book!$E:$E,B61) | N61: =SUMIFS(Cash_Book!$G:$G,Cash_Book!$C:$C,"BEPAARI",Cash_Book!$D:$D,"OTHER",Cash_Book!$E:$E,B61)+SUMIFS(Cash_Book!$H:$H,Cash_Book!$C:$C,"BEPAARI",Cash_Book!$D:$D,"OTHER",Cash_Book!$E:$E,B61) | O61: =SUM(G61:N61) | P61: =IF(B61="","",E61-O61+D61) | Q61: =SUMIFS(Cash_Book!$G:$G,Cash_Book!$C:$C,"BEPAARI",Cash_Book!$D:$D,"PAYMENT",Cash_Book!$E:$E,B61)+SUMIFS(Cash_Book!$H:$H,Cash_Book!$C:$C,"BEPAARI",Cash_Book!$D:$D,"PAYMENT",Cash_Book!$E:$E,B61) | R61: =IF(B61="","",P61-Q61)
A62: 58 | B62: =IF(Masters!$B$60="","",Masters!$B$60) | C62: =IF(B62="","",Masters!$C$60) | D62: =IF(B62="",0,Masters!$D$60) | E62: =SUMIF(Daily_Sales!$C:$C,B62,Daily_Sales!$G:$G) | F62: =SUMIF(Daily_Sales!$C:$C,B62,Daily_Sales!$E:$E) | G62: =IF(B62="",0,E62*C62/100) | H62: =IF(F62>0,Masters!$X$3,0) | I62: =F62*Masters!$X$4 | J62: =SUMIFS(Cash_Book!$G:$G,Cash_Book!$C:$C,"BEPAARI",Cash_Book!$D:$D,"MOTOR",Cash_Book!$E:$E,B62)+SUMIFS(Cash_Book!$H:$H,Cash_Book!$C:$C,"BEPAARI",Cash_Book!$D:$D,"MOTOR",Cash_Book!$E:$E,B62) | K62: =SUMIFS(Cash_Book!$G:$G,Cash_Book!$C:$C,"BEPAARI",Cash_Book!$D:$D,"BHUSSA",Cash_Book!$E:$E,B62)+SUMIFS(Cash_Book!$H:$H,Cash_Book!$C:$C,"BEPAARI",Cash_Book!$D:$D,"BHUSSA",Cash_Book!$E:$E,B62) | L62: =SUMIFS(Cash_Book!$G:$G,Cash_Book!$C:$C,"BEPAARI",Cash_Book!$D:$D,"GAWALI",Cash_Book!$E:$E,B62)+SUMIFS(Cash_Book!$H:$H,Cash_Book!$C:$C,"BEPAARI",Cash_Book!$D:$D,"GAWALI",Cash_Book!$E:$E,B62) | M62: =SUMIFS(Cash_Book!$G:$G,Cash_Book!$C:$C,"BEPAARI",Cash_Book!$D:$D,"CASH_ADV",Cash_Book!$E:$E,B62)+SUMIFS(Cash_Book!$H:$H,Cash_Book!$C:$C,"BEPAARI",Cash_Book!$D:$D,"CASH_ADV",Cash_Book!$E:$E,B62) | N62: =SUMIFS(Cash_Book!$G:$G,Cash_Book!$C:$C,"BEPAARI",Cash_Book!$D:$D,"OTHER",Cash_Book!$E:$E,B62)+SUMIFS(Cash_Book!$H:$H,Cash_Book!$C:$C,"BEPAARI",Cash_Book!$D:$D,"OTHER",Cash_Book!$E:$E,B62) | O62: =SUM(G62:N62) | P62: =IF(B62="","",E62-O62+D62) | Q62: =SUMIFS(Cash_Book!$G:$G,Cash_Book!$C:$C,"BEPAARI",Cash_Book!$D:$D,"PAYMENT",Cash_Book!$E:$E,B62)+SUMIFS(Cash_Book!$H:$H,Cash_Book!$C:$C,"BEPAARI",Cash_Book!$D:$D,"PAYMENT",Cash_Book!$E:$E,B62) | R62: =IF(B62="","",P62-Q62)
A63: 59 | B63: =IF(Masters!$B$61="","",Masters!$B$61) | C63: =IF(B63="","",Masters!$C$61) | D63: =IF(B63="",0,Masters!$D$61) | E63: =SUMIF(Daily_Sales!$C:$C,B63,Daily_Sales!$G:$G) | F63: =SUMIF(Daily_Sales!$C:$C,B63,Daily_Sales!$E:$E) | G63: =IF(B63="",0,E63*C63/100) | H63: =IF(F63>0,Masters!$X$3,0) | I63: =F63*Masters!$X$4 | J63: =SUMIFS(Cash_Book!$G:$G,Cash_Book!$C:$C,"BEPAARI",Cash_Book!$D:$D,"MOTOR",Cash_Book!$E:$E,B63)+SUMIFS(Cash_Book!$H:$H,Cash_Book!$C:$C,"BEPAARI",Cash_Book!$D:$D,"MOTOR",Cash_Book!$E:$E,B63) | K63: =SUMIFS(Cash_Book!$G:$G,Cash_Book!$C:$C,"BEPAARI",Cash_Book!$D:$D,"BHUSSA",Cash_Book!$E:$E,B63)+SUMIFS(Cash_Book!$H:$H,Cash_Book!$C:$C,"BEPAARI",Cash_Book!$D:$D,"BHUSSA",Cash_Book!$E:$E,B63) | L63: =SUMIFS(Cash_Book!$G:$G,Cash_Book!$C:$C,"BEPAARI",Cash_Book!$D:$D,"GAWALI",Cash_Book!$E:$E,B63)+SUMIFS(Cash_Book!$H:$H,Cash_Book!$C:$C,"BEPAARI",Cash_Book!$D:$D,"GAWALI",Cash_Book!$E:$E,B63) | M63: =SUMIFS(Cash_Book!$G:$G,Cash_Book!$C:$C,"BEPAARI",Cash_Book!$D:$D,"CASH_ADV",Cash_Book!$E:$E,B63)+SUMIFS(Cash_Book!$H:$H,Cash_Book!$C:$C,"BEPAARI",Cash_Book!$D:$D,"CASH_ADV",Cash_Book!$E:$E,B63) | N63: =SUMIFS(Cash_Book!$G:$G,Cash_Book!$C:$C,"BEPAARI",Cash_Book!$D:$D,"OTHER",Cash_Book!$E:$E,B63)+SUMIFS(Cash_Book!$H:$H,Cash_Book!$C:$C,"BEPAARI",Cash_Book!$D:$D,"OTHER",Cash_Book!$E:$E,B63) | O63: =SUM(G63:N63) | P63: =IF(B63="","",E63-O63+D63) | Q63: =SUMIFS(Cash_Book!$G:$G,Cash_Book!$C:$C,"BEPAARI",Cash_Book!$D:$D,"PAYMENT",Cash_Book!$E:$E,B63)+SUMIFS(Cash_Book!$H:$H,Cash_Book!$C:$C,"BEPAARI",Cash_Book!$D:$D,"PAYMENT",Cash_Book!$E:$E,B63) | R63: =IF(B63="","",P63-Q63)
A64: 60 | B64: =IF(Masters!$B$62="","",Masters!$B$62) | C64: =IF(B64="","",Masters!$C$62) | D64: =IF(B64="",0,Masters!$D$62) | E64: =SUMIF(Daily_Sales!$C:$C,B64,Daily_Sales!$G:$G) | F64: =SUMIF(Daily_Sales!$C:$C,B64,Daily_Sales!$E:$E) | G64: =IF(B64="",0,E64*C64/100) | H64: =IF(F64>0,Masters!$X$3,0) | I64: =F64*Masters!$X$4 | J64: =SUMIFS(Cash_Book!$G:$G,Cash_Book!$C:$C,"BEPAARI",Cash_Book!$D:$D,"MOTOR",Cash_Book!$E:$E,B64)+SUMIFS(Cash_Book!$H:$H,Cash_Book!$C:$C,"BEPAARI",Cash_Book!$D:$D,"MOTOR",Cash_Book!$E:$E,B64) | K64: =SUMIFS(Cash_Book!$G:$G,Cash_Book!$C:$C,"BEPAARI",Cash_Book!$D:$D,"BHUSSA",Cash_Book!$E:$E,B64)+SUMIFS(Cash_Book!$H:$H,Cash_Book!$C:$C,"BEPAARI",Cash_Book!$D:$D,"BHUSSA",Cash_Book!$E:$E,B64) | L64: =SUMIFS(Cash_Book!$G:$G,Cash_Book!$C:$C,"BEPAARI",Cash_Book!$D:$D,"GAWALI",Cash_Book!$E:$E,B64)+SUMIFS(Cash_Book!$H:$H,Cash_Book!$C:$C,"BEPAARI",Cash_Book!$D:$D,"GAWALI",Cash_Book!$E:$E,B64) | M64: =SUMIFS(Cash_Book!$G:$G,Cash_Book!$C:$C,"BEPAARI",Cash_Book!$D:$D,"CASH_ADV",Cash_Book!$E:$E,B64)+SUMIFS(Cash_Book!$H:$H,Cash_Book!$C:$C,"BEPAARI",Cash_Book!$D:$D,"CASH_ADV",Cash_Book!$E:$E,B64) | N64: =SUMIFS(Cash_Book!$G:$G,Cash_Book!$C:$C,"BEPAARI",Cash_Book!$D:$D,"OTHER",Cash_Book!$E:$E,B64)+SUMIFS(Cash_Book!$H:$H,Cash_Book!$C:$C,"BEPAARI",Cash_Book!$D:$D,"OTHER",Cash_Book!$E:$E,B64) | O64: =SUM(G64:N64) | P64: =IF(B64="","",E64-O64+D64) | Q64: =SUMIFS(Cash_Book!$G:$G,Cash_Book!$C:$C,"BEPAARI",Cash_Book!$D:$D,"PAYMENT",Cash_Book!$E:$E,B64)+SUMIFS(Cash_Book!$H:$H,Cash_Book!$C:$C,"BEPAARI",Cash_Book!$D:$D,"PAYMENT",Cash_Book!$E:$E,B64) | R64: =IF(B64="","",P64-Q64)
A65: 61 | B65: =IF(Masters!$B$63="","",Masters!$B$63) | C65: =IF(B65="","",Masters!$C$63) | D65: =IF(B65="",0,Masters!$D$63) | E65: =SUMIF(Daily_Sales!$C:$C,B65,Daily_Sales!$G:$G) | F65: =SUMIF(Daily_Sales!$C:$C,B65,Daily_Sales!$E:$E) | G65: =IF(B65="",0,E65*C65/100) | H65: =IF(F65>0,Masters!$X$3,0) | I65: =F65*Masters!$X$4 | J65: =SUMIFS(Cash_Book!$G:$G,Cash_Book!$C:$C,"BEPAARI",Cash_Book!$D:$D,"MOTOR",Cash_Book!$E:$E,B65)+SUMIFS(Cash_Book!$H:$H,Cash_Book!$C:$C,"BEPAARI",Cash_Book!$D:$D,"MOTOR",Cash_Book!$E:$E,B65) | K65: =SUMIFS(Cash_Book!$G:$G,Cash_Book!$C:$C,"BEPAARI",Cash_Book!$D:$D,"BHUSSA",Cash_Book!$E:$E,B65)+SUMIFS(Cash_Book!$H:$H,Cash_Book!$C:$C,"BEPAARI",Cash_Book!$D:$D,"BHUSSA",Cash_Book!$E:$E,B65) | L65: =SUMIFS(Cash_Book!$G:$G,Cash_Book!$C:$C,"BEPAARI",Cash_Book!$D:$D,"GAWALI",Cash_Book!$E:$E,B65)+SUMIFS(Cash_Book!$H:$H,Cash_Book!$C:$C,"BEPAARI",Cash_Book!$D:$D,"GAWALI",Cash_Book!$E:$E,B65) | M65: =SUMIFS(Cash_Book!$G:$G,Cash_Book!$C:$C,"BEPAARI",Cash_Book!$D:$D,"CASH_ADV",Cash_Book!$E:$E,B65)+SUMIFS(Cash_Book!$H:$H,Cash_Book!$C:$C,"BEPAARI",Cash_Book!$D:$D,"CASH_ADV",Cash_Book!$E:$E,B65) | N65: =SUMIFS(Cash_Book!$G:$G,Cash_Book!$C:$C,"BEPAARI",Cash_Book!$D:$D,"OTHER",Cash_Book!$E:$E,B65)+SUMIFS(Cash_Book!$H:$H,Cash_Book!$C:$C,"BEPAARI",Cash_Book!$D:$D,"OTHER",Cash_Book!$E:$E,B65) | O65: =SUM(G65:N65) | P65: =IF(B65="","",E65-O65+D65) | Q65: =SUMIFS(Cash_Book!$G:$G,Cash_Book!$C:$C,"BEPAARI",Cash_Book!$D:$D,"PAYMENT",Cash_Book!$E:$E,B65)+SUMIFS(Cash_Book!$H:$H,Cash_Book!$C:$C,"BEPAARI",Cash_Book!$D:$D,"PAYMENT",Cash_Book!$E:$E,B65) | R65: =IF(B65="","",P65-Q65)
A66: 62 | B66: =IF(Masters!$B$64="","",Masters!$B$64) | C66: =IF(B66="","",Masters!$C$64) | D66: =IF(B66="",0,Masters!$D$64) | E66: =SUMIF(Daily_Sales!$C:$C,B66,Daily_Sales!$G:$G) | F66: =SUMIF(Daily_Sales!$C:$C,B66,Daily_Sales!$E:$E) | G66: =IF(B66="",0,E66*C66/100) | H66: =IF(F66>0,Masters!$X$3,0) | I66: =F66*Masters!$X$4 | J66: =SUMIFS(Cash_Book!$G:$G,Cash_Book!$C:$C,"BEPAARI",Cash_Book!$D:$D,"MOTOR",Cash_Book!$E:$E,B66)+SUMIFS(Cash_Book!$H:$H,Cash_Book!$C:$C,"BEPAARI",Cash_Book!$D:$D,"MOTOR",Cash_Book!$E:$E,B66) | K66: =SUMIFS(Cash_Book!$G:$G,Cash_Book!$C:$C,"BEPAARI",Cash_Book!$D:$D,"BHUSSA",Cash_Book!$E:$E,B66)+SUMIFS(Cash_Book!$H:$H,Cash_Book!$C:$C,"BEPAARI",Cash_Book!$D:$D,"BHUSSA",Cash_Book!$E:$E,B66) | L66: =SUMIFS(Cash_Book!$G:$G,Cash_Book!$C:$C,"BEPAARI",Cash_Book!$D:$D,"GAWALI",Cash_Book!$E:$E,B66)+SUMIFS(Cash_Book!$H:$H,Cash_Book!$C:$C,"BEPAARI",Cash_Book!$D:$D,"GAWALI",Cash_Book!$E:$E,B66) | M66: =SUMIFS(Cash_Book!$G:$G,Cash_Book!$C:$C,"BEPAARI",Cash_Book!$D:$D,"CASH_ADV",Cash_Book!$E:$E,B66)+SUMIFS(Cash_Book!$H:$H,Cash_Book!$C:$C,"BEPAARI",Cash_Book!$D:$D,"CASH_ADV",Cash_Book!$E:$E,B66) | N66: =SUMIFS(Cash_Book!$G:$G,Cash_Book!$C:$C,"BEPAARI",Cash_Book!$D:$D,"OTHER",Cash_Book!$E:$E,B66)+SUMIFS(Cash_Book!$H:$H,Cash_Book!$C:$C,"BEPAARI",Cash_Book!$D:$D,"OTHER",Cash_Book!$E:$E,B66) | O66: =SUM(G66:N66) | P66: =IF(B66="","",E66-O66+D66) | Q66: =SUMIFS(Cash_Book!$G:$G,Cash_Book!$C:$C,"BEPAARI",Cash_Book!$D:$D,"PAYMENT",Cash_Book!$E:$E,B66)+SUMIFS(Cash_Book!$H:$H,Cash_Book!$C:$C,"BEPAARI",Cash_Book!$D:$D,"PAYMENT",Cash_Book!$E:$E,B66) | R66: =IF(B66="","",P66-Q66)
A67: 63 | B67: =IF(Masters!$B$65="","",Masters!$B$65) | C67: =IF(B67="","",Masters!$C$65) | D67: =IF(B67="",0,Masters!$D$65) | E67: =SUMIF(Daily_Sales!$C:$C,B67,Daily_Sales!$G:$G) | F67: =SUMIF(Daily_Sales!$C:$C,B67,Daily_Sales!$E:$E) | G67: =IF(B67="",0,E67*C67/100) | H67: =IF(F67>0,Masters!$X$3,0) | I67: =F67*Masters!$X$4 | J67: =SUMIFS(Cash_Book!$G:$G,Cash_Book!$C:$C,"BEPAARI",Cash_Book!$D:$D,"MOTOR",Cash_Book!$E:$E,B67)+SUMIFS(Cash_Book!$H:$H,Cash_Book!$C:$C,"BEPAARI",Cash_Book!$D:$D,"MOTOR",Cash_Book!$E:$E,B67) | K67: =SUMIFS(Cash_Book!$G:$G,Cash_Book!$C:$C,"BEPAARI",Cash_Book!$D:$D,"BHUSSA",Cash_Book!$E:$E,B67)+SUMIFS(Cash_Book!$H:$H,Cash_Book!$C:$C,"BEPAARI",Cash_Book!$D:$D,"BHUSSA",Cash_Book!$E:$E,B67) | L67: =SUMIFS(Cash_Book!$G:$G,Cash_Book!$C:$C,"BEPAARI",Cash_Book!$D:$D,"GAWALI",Cash_Book!$E:$E,B67)+SUMIFS(Cash_Book!$H:$H,Cash_Book!$C:$C,"BEPAARI",Cash_Book!$D:$D,"GAWALI",Cash_Book!$E:$E,B67) | M67: =SUMIFS(Cash_Book!$G:$G,Cash_Book!$C:$C,"BEPAARI",Cash_Book!$D:$D,"CASH_ADV",Cash_Book!$E:$E,B67)+SUMIFS(Cash_Book!$H:$H,Cash_Book!$C:$C,"BEPAARI",Cash_Book!$D:$D,"CASH_ADV",Cash_Book!$E:$E,B67) | N67: =SUMIFS(Cash_Book!$G:$G,Cash_Book!$C:$C,"BEPAARI",Cash_Book!$D:$D,"OTHER",Cash_Book!$E:$E,B67)+SUMIFS(Cash_Book!$H:$H,Cash_Book!$C:$C,"BEPAARI",Cash_Book!$D:$D,"OTHER",Cash_Book!$E:$E,B67) | O67: =SUM(G67:N67) | P67: =IF(B67="","",E67-O67+D67) | Q67: =SUMIFS(Cash_Book!$G:$G,Cash_Book!$C:$C,"BEPAARI",Cash_Book!$D:$D,"PAYMENT",Cash_Book!$E:$E,B67)+SUMIFS(Cash_Book!$H:$H,Cash_Book!$C:$C,"BEPAARI",Cash_Book!$D:$D,"PAYMENT",Cash_Book!$E:$E,B67) | R67: =IF(B67="","",P67-Q67)
A68: 64 | B68: =IF(Masters!$B$66="","",Masters!$B$66) | C68: =IF(B68="","",Masters!$C$66) | D68: =IF(B68="",0,Masters!$D$66) | E68: =SUMIF(Daily_Sales!$C:$C,B68,Daily_Sales!$G:$G) | F68: =SUMIF(Daily_Sales!$C:$C,B68,Daily_Sales!$E:$E) | G68: =IF(B68="",0,E68*C68/100) | H68: =IF(F68>0,Masters!$X$3,0) | I68: =F68*Masters!$X$4 | J68: =SUMIFS(Cash_Book!$G:$G,Cash_Book!$C:$C,"BEPAARI",Cash_Book!$D:$D,"MOTOR",Cash_Book!$E:$E,B68)+SUMIFS(Cash_Book!$H:$H,Cash_Book!$C:$C,"BEPAARI",Cash_Book!$D:$D,"MOTOR",Cash_Book!$E:$E,B68) | K68: =SUMIFS(Cash_Book!$G:$G,Cash_Book!$C:$C,"BEPAARI",Cash_Book!$D:$D,"BHUSSA",Cash_Book!$E:$E,B68)+SUMIFS(Cash_Book!$H:$H,Cash_Book!$C:$C,"BEPAARI",Cash_Book!$D:$D,"BHUSSA",Cash_Book!$E:$E,B68) | L68: =SUMIFS(Cash_Book!$G:$G,Cash_Book!$C:$C,"BEPAARI",Cash_Book!$D:$D,"GAWALI",Cash_Book!$E:$E,B68)+SUMIFS(Cash_Book!$H:$H,Cash_Book!$C:$C,"BEPAARI",Cash_Book!$D:$D,"GAWALI",Cash_Book!$E:$E,B68) | M68: =SUMIFS(Cash_Book!$G:$G,Cash_Book!$C:$C,"BEPAARI",Cash_Book!$D:$D,"CASH_ADV",Cash_Book!$E:$E,B68)+SUMIFS(Cash_Book!$H:$H,Cash_Book!$C:$C,"BEPAARI",Cash_Book!$D:$D,"CASH_ADV",Cash_Book!$E:$E,B68) | N68: =SUMIFS(Cash_Book!$G:$G,Cash_Book!$C:$C,"BEPAARI",Cash_Book!$D:$D,"OTHER",Cash_Book!$E:$E,B68)+SUMIFS(Cash_Book!$H:$H,Cash_Book!$C:$C,"BEPAARI",Cash_Book!$D:$D,"OTHER",Cash_Book!$E:$E,B68) | O68: =SUM(G68:N68) | P68: =IF(B68="","",E68-O68+D68) | Q68: =SUMIFS(Cash_Book!$G:$G,Cash_Book!$C:$C,"BEPAARI",Cash_Book!$D:$D,"PAYMENT",Cash_Book!$E:$E,B68)+SUMIFS(Cash_Book!$H:$H,Cash_Book!$C:$C,"BEPAARI",Cash_Book!$D:$D,"PAYMENT",Cash_Book!$E:$E,B68) | R68: =IF(B68="","",P68-Q68)
A69: 65 | B69: =IF(Masters!$B$67="","",Masters!$B$67) | C69: =IF(B69="","",Masters!$C$67) | D69: =IF(B69="",0,Masters!$D$67) | E69: =SUMIF(Daily_Sales!$C:$C,B69,Daily_Sales!$G:$G) | F69: =SUMIF(Daily_Sales!$C:$C,B69,Daily_Sales!$E:$E) | G69: =IF(B69="",0,E69*C69/100) | H69: =IF(F69>0,Masters!$X$3,0) | I69: =F69*Masters!$X$4 | J69: =SUMIFS(Cash_Book!$G:$G,Cash_Book!$C:$C,"BEPAARI",Cash_Book!$D:$D,"MOTOR",Cash_Book!$E:$E,B69)+SUMIFS(Cash_Book!$H:$H,Cash_Book!$C:$C,"BEPAARI",Cash_Book!$D:$D,"MOTOR",Cash_Book!$E:$E,B69) | K69: =SUMIFS(Cash_Book!$G:$G,Cash_Book!$C:$C,"BEPAARI",Cash_Book!$D:$D,"BHUSSA",Cash_Book!$E:$E,B69)+SUMIFS(Cash_Book!$H:$H,Cash_Book!$C:$C,"BEPAARI",Cash_Book!$D:$D,"BHUSSA",Cash_Book!$E:$E,B69) | L69: =SUMIFS(Cash_Book!$G:$G,Cash_Book!$C:$C,"BEPAARI",Cash_Book!$D:$D,"GAWALI",Cash_Book!$E:$E,B69)+SUMIFS(Cash_Book!$H:$H,Cash_Book!$C:$C,"BEPAARI",Cash_Book!$D:$D,"GAWALI",Cash_Book!$E:$E,B69) | M69: =SUMIFS(Cash_Book!$G:$G,Cash_Book!$C:$C,"BEPAARI",Cash_Book!$D:$D,"CASH_ADV",Cash_Book!$E:$E,B69)+SUMIFS(Cash_Book!$H:$H,Cash_Book!$C:$C,"BEPAARI",Cash_Book!$D:$D,"CASH_ADV",Cash_Book!$E:$E,B69) | N69: =SUMIFS(Cash_Book!$G:$G,Cash_Book!$C:$C,"BEPAARI",Cash_Book!$D:$D,"OTHER",Cash_Book!$E:$E,B69)+SUMIFS(Cash_Book!$H:$H,Cash_Book!$C:$C,"BEPAARI",Cash_Book!$D:$D,"OTHER",Cash_Book!$E:$E,B69) | O69: =SUM(G69:N69) | P69: =IF(B69="","",E69-O69+D69) | Q69: =SUMIFS(Cash_Book!$G:$G,Cash_Book!$C:$C,"BEPAARI",Cash_Book!$D:$D,"PAYMENT",Cash_Book!$E:$E,B69)+SUMIFS(Cash_Book!$H:$H,Cash_Book!$C:$C,"BEPAARI",Cash_Book!$D:$D,"PAYMENT",Cash_Book!$E:$E,B69) | R69: =IF(B69="","",P69-Q69)
A70: 66 | B70: =IF(Masters!$B$68="","",Masters!$B$68) | C70: =IF(B70="","",Masters!$C$68) | D70: =IF(B70="",0,Masters!$D$68) | E70: =SUMIF(Daily_Sales!$C:$C,B70,Daily_Sales!$G:$G) | F70: =SUMIF(Daily_Sales!$C:$C,B70,Daily_Sales!$E:$E) | G70: =IF(B70="",0,E70*C70/100) | H70: =IF(F70>0,Masters!$X$3,0) | I70: =F70*Masters!$X$4 | J70: =SUMIFS(Cash_Book!$G:$G,Cash_Book!$C:$C,"BEPAARI",Cash_Book!$D:$D,"MOTOR",Cash_Book!$E:$E,B70)+SUMIFS(Cash_Book!$H:$H,Cash_Book!$C:$C,"BEPAARI",Cash_Book!$D:$D,"MOTOR",Cash_Book!$E:$E,B70) | K70: =SUMIFS(Cash_Book!$G:$G,Cash_Book!$C:$C,"BEPAARI",Cash_Book!$D:$D,"BHUSSA",Cash_Book!$E:$E,B70)+SUMIFS(Cash_Book!$H:$H,Cash_Book!$C:$C,"BEPAARI",Cash_Book!$D:$D,"BHUSSA",Cash_Book!$E:$E,B70) | L70: =SUMIFS(Cash_Book!$G:$G,Cash_Book!$C:$C,"BEPAARI",Cash_Book!$D:$D,"GAWALI",Cash_Book!$E:$E,B70)+SUMIFS(Cash_Book!$H:$H,Cash_Book!$C:$C,"BEPAARI",Cash_Book!$D:$D,"GAWALI",Cash_Book!$E:$E,B70) | M70: =SUMIFS(Cash_Book!$G:$G,Cash_Book!$C:$C,"BEPAARI",Cash_Book!$D:$D,"CASH_ADV",Cash_Book!$E:$E,B70)+SUMIFS(Cash_Book!$H:$H,Cash_Book!$C:$C,"BEPAARI",Cash_Book!$D:$D,"CASH_ADV",Cash_Book!$E:$E,B70) | N70: =SUMIFS(Cash_Book!$G:$G,Cash_Book!$C:$C,"BEPAARI",Cash_Book!$D:$D,"OTHER",Cash_Book!$E:$E,B70)+SUMIFS(Cash_Book!$H:$H,Cash_Book!$C:$C,"BEPAARI",Cash_Book!$D:$D,"OTHER",Cash_Book!$E:$E,B70) | O70: =SUM(G70:N70) | P70: =IF(B70="","",E70-O70+D70) | Q70: =SUMIFS(Cash_Book!$G:$G,Cash_Book!$C:$C,"BEPAARI",Cash_Book!$D:$D,"PAYMENT",Cash_Book!$E:$E,B70)+SUMIFS(Cash_Book!$H:$H,Cash_Book!$C:$C,"BEPAARI",Cash_Book!$D:$D,"PAYMENT",Cash_Book!$E:$E,B70) | R70: =IF(B70="","",P70-Q70)
A71: 67 | B71: =IF(Masters!$B$69="","",Masters!$B$69) | C71: =IF(B71="","",Masters!$C$69) | D71: =IF(B71="",0,Masters!$D$69) | E71: =SUMIF(Daily_Sales!$C:$C,B71,Daily_Sales!$G:$G) | F71: =SUMIF(Daily_Sales!$C:$C,B71,Daily_Sales!$E:$E) | G71: =IF(B71="",0,E71*C71/100) | H71: =IF(F71>0,Masters!$X$3,0) | I71: =F71*Masters!$X$4 | J71: =SUMIFS(Cash_Book!$G:$G,Cash_Book!$C:$C,"BEPAARI",Cash_Book!$D:$D,"MOTOR",Cash_Book!$E:$E,B71)+SUMIFS(Cash_Book!$H:$H,Cash_Book!$C:$C,"BEPAARI",Cash_Book!$D:$D,"MOTOR",Cash_Book!$E:$E,B71) | K71: =SUMIFS(Cash_Book!$G:$G,Cash_Book!$C:$C,"BEPAARI",Cash_Book!$D:$D,"BHUSSA",Cash_Book!$E:$E,B71)+SUMIFS(Cash_Book!$H:$H,Cash_Book!$C:$C,"BEPAARI",Cash_Book!$D:$D,"BHUSSA",Cash_Book!$E:$E,B71) | L71: =SUMIFS(Cash_Book!$G:$G,Cash_Book!$C:$C,"BEPAARI",Cash_Book!$D:$D,"GAWALI",Cash_Book!$E:$E,B71)+SUMIFS(Cash_Book!$H:$H,Cash_Book!$C:$C,"BEPAARI",Cash_Book!$D:$D,"GAWALI",Cash_Book!$E:$E,B71) | M71: =SUMIFS(Cash_Book!$G:$G,Cash_Book!$C:$C,"BEPAARI",Cash_Book!$D:$D,"CASH_ADV",Cash_Book!$E:$E,B71)+SUMIFS(Cash_Book!$H:$H,Cash_Book!$C:$C,"BEPAARI",Cash_Book!$D:$D,"CASH_ADV",Cash_Book!$E:$E,B71) | N71: =SUMIFS(Cash_Book!$G:$G,Cash_Book!$C:$C,"BEPAARI",Cash_Book!$D:$D,"OTHER",Cash_Book!$E:$E,B71)+SUMIFS(Cash_Book!$H:$H,Cash_Book!$C:$C,"BEPAARI",Cash_Book!$D:$D,"OTHER",Cash_Book!$E:$E,B71) | O71: =SUM(G71:N71) | P71: =IF(B71="","",E71-O71+D71) | Q71: =SUMIFS(Cash_Book!$G:$G,Cash_Book!$C:$C,"BEPAARI",Cash_Book!$D:$D,"PAYMENT",Cash_Book!$E:$E,B71)+SUMIFS(Cash_Book!$H:$H,Cash_Book!$C:$C,"BEPAARI",Cash_Book!$D:$D,"PAYMENT",Cash_Book!$E:$E,B71) | R71: =IF(B71="","",P71-Q71)
A72: 68 | B72: =IF(Masters!$B$70="","",Masters!$B$70) | C72: =IF(B72="","",Masters!$C$70) | D72: =IF(B72="",0,Masters!$D$70) | E72: =SUMIF(Daily_Sales!$C:$C,B72,Daily_Sales!$G:$G) | F72: =SUMIF(Daily_Sales!$C:$C,B72,Daily_Sales!$E:$E) | G72: =IF(B72="",0,E72*C72/100) | H72: =IF(F72>0,Masters!$X$3,0) | I72: =F72*Masters!$X$4 | J72: =SUMIFS(Cash_Book!$G:$G,Cash_Book!$C:$C,"BEPAARI",Cash_Book!$D:$D,"MOTOR",Cash_Book!$E:$E,B72)+SUMIFS(Cash_Book!$H:$H,Cash_Book!$C:$C,"BEPAARI",Cash_Book!$D:$D,"MOTOR",Cash_Book!$E:$E,B72) | K72: =SUMIFS(Cash_Book!$G:$G,Cash_Book!$C:$C,"BEPAARI",Cash_Book!$D:$D,"BHUSSA",Cash_Book!$E:$E,B72)+SUMIFS(Cash_Book!$H:$H,Cash_Book!$C:$C,"BEPAARI",Cash_Book!$D:$D,"BHUSSA",Cash_Book!$E:$E,B72) | L72: =SUMIFS(Cash_Book!$G:$G,Cash_Book!$C:$C,"BEPAARI",Cash_Book!$D:$D,"GAWALI",Cash_Book!$E:$E,B72)+SUMIFS(Cash_Book!$H:$H,Cash_Book!$C:$C,"BEPAARI",Cash_Book!$D:$D,"GAWALI",Cash_Book!$E:$E,B72) | M72: =SUMIFS(Cash_Book!$G:$G,Cash_Book!$C:$C,"BEPAARI",Cash_Book!$D:$D,"CASH_ADV",Cash_Book!$E:$E,B72)+SUMIFS(Cash_Book!$H:$H,Cash_Book!$C:$C,"BEPAARI",Cash_Book!$D:$D,"CASH_ADV",Cash_Book!$E:$E,B72) | N72: =SUMIFS(Cash_Book!$G:$G,Cash_Book!$C:$C,"BEPAARI",Cash_Book!$D:$D,"OTHER",Cash_Book!$E:$E,B72)+SUMIFS(Cash_Book!$H:$H,Cash_Book!$C:$C,"BEPAARI",Cash_Book!$D:$D,"OTHER",Cash_Book!$E:$E,B72) | O72: =SUM(G72:N72) | P72: =IF(B72="","",E72-O72+D72) | Q72: =SUMIFS(Cash_Book!$G:$G,Cash_Book!$C:$C,"BEPAARI",Cash_Book!$D:$D,"PAYMENT",Cash_Book!$E:$E,B72)+SUMIFS(Cash_Book!$H:$H,Cash_Book!$C:$C,"BEPAARI",Cash_Book!$D:$D,"PAYMENT",Cash_Book!$E:$E,B72) | R72: =IF(B72="","",P72-Q72)
A73: 69 | B73: =IF(Masters!$B$71="","",Masters!$B$71) | C73: =IF(B73="","",Masters!$C$71) | D73: =IF(B73="",0,Masters!$D$71) | E73: =SUMIF(Daily_Sales!$C:$C,B73,Daily_Sales!$G:$G) | F73: =SUMIF(Daily_Sales!$C:$C,B73,Daily_Sales!$E:$E) | G73: =IF(B73="",0,E73*C73/100) | H73: =IF(F73>0,Masters!$X$3,0) | I73: =F73*Masters!$X$4 | J73: =SUMIFS(Cash_Book!$G:$G,Cash_Book!$C:$C,"BEPAARI",Cash_Book!$D:$D,"MOTOR",Cash_Book!$E:$E,B73)+SUMIFS(Cash_Book!$H:$H,Cash_Book!$C:$C,"BEPAARI",Cash_Book!$D:$D,"MOTOR",Cash_Book!$E:$E,B73) | K73: =SUMIFS(Cash_Book!$G:$G,Cash_Book!$C:$C,"BEPAARI",Cash_Book!$D:$D,"BHUSSA",Cash_Book!$E:$E,B73)+SUMIFS(Cash_Book!$H:$H,Cash_Book!$C:$C,"BEPAARI",Cash_Book!$D:$D,"BHUSSA",Cash_Book!$E:$E,B73) | L73: =SUMIFS(Cash_Book!$G:$G,Cash_Book!$C:$C,"BEPAARI",Cash_Book!$D:$D,"GAWALI",Cash_Book!$E:$E,B73)+SUMIFS(Cash_Book!$H:$H,Cash_Book!$C:$C,"BEPAARI",Cash_Book!$D:$D,"GAWALI",Cash_Book!$E:$E,B73) | M73: =SUMIFS(Cash_Book!$G:$G,Cash_Book!$C:$C,"BEPAARI",Cash_Book!$D:$D,"CASH_ADV",Cash_Book!$E:$E,B73)+SUMIFS(Cash_Book!$H:$H,Cash_Book!$C:$C,"BEPAARI",Cash_Book!$D:$D,"CASH_ADV",Cash_Book!$E:$E,B73) | N73: =SUMIFS(Cash_Book!$G:$G,Cash_Book!$C:$C,"BEPAARI",Cash_Book!$D:$D,"OTHER",Cash_Book!$E:$E,B73)+SUMIFS(Cash_Book!$H:$H,Cash_Book!$C:$C,"BEPAARI",Cash_Book!$D:$D,"OTHER",Cash_Book!$E:$E,B73) | O73: =SUM(G73:N73) | P73: =IF(B73="","",E73-O73+D73) | Q73: =SUMIFS(Cash_Book!$G:$G,Cash_Book!$C:$C,"BEPAARI",Cash_Book!$D:$D,"PAYMENT",Cash_Book!$E:$E,B73)+SUMIFS(Cash_Book!$H:$H,Cash_Book!$C:$C,"BEPAARI",Cash_Book!$D:$D,"PAYMENT",Cash_Book!$E:$E,B73) | R73: =IF(B73="","",P73-Q73)
A74: 70 | B74: =IF(Masters!$B$72="","",Masters!$B$72) | C74: =IF(B74="","",Masters!$C$72) | D74: =IF(B74="",0,Masters!$D$72) | E74: =SUMIF(Daily_Sales!$C:$C,B74,Daily_Sales!$G:$G) | F74: =SUMIF(Daily_Sales!$C:$C,B74,Daily_Sales!$E:$E) | G74: =IF(B74="",0,E74*C74/100) | H74: =IF(F74>0,Masters!$X$3,0) | I74: =F74*Masters!$X$4 | J74: =SUMIFS(Cash_Book!$G:$G,Cash_Book!$C:$C,"BEPAARI",Cash_Book!$D:$D,"MOTOR",Cash_Book!$E:$E,B74)+SUMIFS(Cash_Book!$H:$H,Cash_Book!$C:$C,"BEPAARI",Cash_Book!$D:$D,"MOTOR",Cash_Book!$E:$E,B74) | K74: =SUMIFS(Cash_Book!$G:$G,Cash_Book!$C:$C,"BEPAARI",Cash_Book!$D:$D,"BHUSSA",Cash_Book!$E:$E,B74)+SUMIFS(Cash_Book!$H:$H,Cash_Book!$C:$C,"BEPAARI",Cash_Book!$D:$D,"BHUSSA",Cash_Book!$E:$E,B74) | L74: =SUMIFS(Cash_Book!$G:$G,Cash_Book!$C:$C,"BEPAARI",Cash_Book!$D:$D,"GAWALI",Cash_Book!$E:$E,B74)+SUMIFS(Cash_Book!$H:$H,Cash_Book!$C:$C,"BEPAARI",Cash_Book!$D:$D,"GAWALI",Cash_Book!$E:$E,B74) | M74: =SUMIFS(Cash_Book!$G:$G,Cash_Book!$C:$C,"BEPAARI",Cash_Book!$D:$D,"CASH_ADV",Cash_Book!$E:$E,B74)+SUMIFS(Cash_Book!$H:$H,Cash_Book!$C:$C,"BEPAARI",Cash_Book!$D:$D,"CASH_ADV",Cash_Book!$E:$E,B74) | N74: =SUMIFS(Cash_Book!$G:$G,Cash_Book!$C:$C,"BEPAARI",Cash_Book!$D:$D,"OTHER",Cash_Book!$E:$E,B74)+SUMIFS(Cash_Book!$H:$H,Cash_Book!$C:$C,"BEPAARI",Cash_Book!$D:$D,"OTHER",Cash_Book!$E:$E,B74) | O74: =SUM(G74:N74) | P74: =IF(B74="","",E74-O74+D74) | Q74: =SUMIFS(Cash_Book!$G:$G,Cash_Book!$C:$C,"BEPAARI",Cash_Book!$D:$D,"PAYMENT",Cash_Book!$E:$E,B74)+SUMIFS(Cash_Book!$H:$H,Cash_Book!$C:$C,"BEPAARI",Cash_Book!$D:$D,"PAYMENT",Cash_Book!$E:$E,B74) | R74: =IF(B74="","",P74-Q74)
A75: 71 | B75: =IF(Masters!$B$73="","",Masters!$B$73) | C75: =IF(B75="","",Masters!$C$73) | D75: =IF(B75="",0,Masters!$D$73) | E75: =SUMIF(Daily_Sales!$C:$C,B75,Daily_Sales!$G:$G) | F75: =SUMIF(Daily_Sales!$C:$C,B75,Daily_Sales!$E:$E) | G75: =IF(B75="",0,E75*C75/100) | H75: =IF(F75>0,Masters!$X$3,0) | I75: =F75*Masters!$X$4 | J75: =SUMIFS(Cash_Book!$G:$G,Cash_Book!$C:$C,"BEPAARI",Cash_Book!$D:$D,"MOTOR",Cash_Book!$E:$E,B75)+SUMIFS(Cash_Book!$H:$H,Cash_Book!$C:$C,"BEPAARI",Cash_Book!$D:$D,"MOTOR",Cash_Book!$E:$E,B75) | K75: =SUMIFS(Cash_Book!$G:$G,Cash_Book!$C:$C,"BEPAARI",Cash_Book!$D:$D,"BHUSSA",Cash_Book!$E:$E,B75)+SUMIFS(Cash_Book!$H:$H,Cash_Book!$C:$C,"BEPAARI",Cash_Book!$D:$D,"BHUSSA",Cash_Book!$E:$E,B75) | L75: =SUMIFS(Cash_Book!$G:$G,Cash_Book!$C:$C,"BEPAARI",Cash_Book!$D:$D,"GAWALI",Cash_Book!$E:$E,B75)+SUMIFS(Cash_Book!$H:$H,Cash_Book!$C:$C,"BEPAARI",Cash_Book!$D:$D,"GAWALI",Cash_Book!$E:$E,B75) | M75: =SUMIFS(Cash_Book!$G:$G,Cash_Book!$C:$C,"BEPAARI",Cash_Book!$D:$D,"CASH_ADV",Cash_Book!$E:$E,B75)+SUMIFS(Cash_Book!$H:$H,Cash_Book!$C:$C,"BEPAARI",Cash_Book!$D:$D,"CASH_ADV",Cash_Book!$E:$E,B75) | N75: =SUMIFS(Cash_Book!$G:$G,Cash_Book!$C:$C,"BEPAARI",Cash_Book!$D:$D,"OTHER",Cash_Book!$E:$E,B75)+SUMIFS(Cash_Book!$H:$H,Cash_Book!$C:$C,"BEPAARI",Cash_Book!$D:$D,"OTHER",Cash_Book!$E:$E,B75) | O75: =SUM(G75:N75) | P75: =IF(B75="","",E75-O75+D75) | Q75: =SUMIFS(Cash_Book!$G:$G,Cash_Book!$C:$C,"BEPAARI",Cash_Book!$D:$D,"PAYMENT",Cash_Book!$E:$E,B75)+SUMIFS(Cash_Book!$H:$H,Cash_Book!$C:$C,"BEPAARI",Cash_Book!$D:$D,"PAYMENT",Cash_Book!$E:$E,B75) | R75: =IF(B75="","",P75-Q75)
A76: 72 | B76: =IF(Masters!$B$74="","",Masters!$B$74) | C76: =IF(B76="","",Masters!$C$74) | D76: =IF(B76="",0,Masters!$D$74) | E76: =SUMIF(Daily_Sales!$C:$C,B76,Daily_Sales!$G:$G) | F76: =SUMIF(Daily_Sales!$C:$C,B76,Daily_Sales!$E:$E) | G76: =IF(B76="",0,E76*C76/100) | H76: =IF(F76>0,Masters!$X$3,0) | I76: =F76*Masters!$X$4 | J76: =SUMIFS(Cash_Book!$G:$G,Cash_Book!$C:$C,"BEPAARI",Cash_Book!$D:$D,"MOTOR",Cash_Book!$E:$E,B76)+SUMIFS(Cash_Book!$H:$H,Cash_Book!$C:$C,"BEPAARI",Cash_Book!$D:$D,"MOTOR",Cash_Book!$E:$E,B76) | K76: =SUMIFS(Cash_Book!$G:$G,Cash_Book!$C:$C,"BEPAARI",Cash_Book!$D:$D,"BHUSSA",Cash_Book!$E:$E,B76)+SUMIFS(Cash_Book!$H:$H,Cash_Book!$C:$C,"BEPAARI",Cash_Book!$D:$D,"BHUSSA",Cash_Book!$E:$E,B76) | L76: =SUMIFS(Cash_Book!$G:$G,Cash_Book!$C:$C,"BEPAARI",Cash_Book!$D:$D,"GAWALI",Cash_Book!$E:$E,B76)+SUMIFS(Cash_Book!$H:$H,Cash_Book!$C:$C,"BEPAARI",Cash_Book!$D:$D,"GAWALI",Cash_Book!$E:$E,B76) | M76: =SUMIFS(Cash_Book!$G:$G,Cash_Book!$C:$C,"BEPAARI",Cash_Book!$D:$D,"CASH_ADV",Cash_Book!$E:$E,B76)+SUMIFS(Cash_Book!$H:$H,Cash_Book!$C:$C,"BEPAARI",Cash_Book!$D:$D,"CASH_ADV",Cash_Book!$E:$E,B76) | N76: =SUMIFS(Cash_Book!$G:$G,Cash_Book!$C:$C,"BEPAARI",Cash_Book!$D:$D,"OTHER",Cash_Book!$E:$E,B76)+SUMIFS(Cash_Book!$H:$H,Cash_Book!$C:$C,"BEPAARI",Cash_Book!$D:$D,"OTHER",Cash_Book!$E:$E,B76) | O76: =SUM(G76:N76) | P76: =IF(B76="","",E76-O76+D76) | Q76: =SUMIFS(Cash_Book!$G:$G,Cash_Book!$C:$C,"BEPAARI",Cash_Book!$D:$D,"PAYMENT",Cash_Book!$E:$E,B76)+SUMIFS(Cash_Book!$H:$H,Cash_Book!$C:$C,"BEPAARI",Cash_Book!$D:$D,"PAYMENT",Cash_Book!$E:$E,B76) | R76: =IF(B76="","",P76-Q76)
A77: 73 | B77: =IF(Masters!$B$75="","",Masters!$B$75) | C77: =IF(B77="","",Masters!$C$75) | D77: =IF(B77="",0,Masters!$D$75) | E77: =SUMIF(Daily_Sales!$C:$C,B77,Daily_Sales!$G:$G) | F77: =SUMIF(Daily_Sales!$C:$C,B77,Daily_Sales!$E:$E) | G77: =IF(B77="",0,E77*C77/100) | H77: =IF(F77>0,Masters!$X$3,0) | I77: =F77*Masters!$X$4 | J77: =SUMIFS(Cash_Book!$G:$G,Cash_Book!$C:$C,"BEPAARI",Cash_Book!$D:$D,"MOTOR",Cash_Book!$E:$E,B77)+SUMIFS(Cash_Book!$H:$H,Cash_Book!$C:$C,"BEPAARI",Cash_Book!$D:$D,"MOTOR",Cash_Book!$E:$E,B77) | K77: =SUMIFS(Cash_Book!$G:$G,Cash_Book!$C:$C,"BEPAARI",Cash_Book!$D:$D,"BHUSSA",Cash_Book!$E:$E,B77)+SUMIFS(Cash_Book!$H:$H,Cash_Book!$C:$C,"BEPAARI",Cash_Book!$D:$D,"BHUSSA",Cash_Book!$E:$E,B77) | L77: =SUMIFS(Cash_Book!$G:$G,Cash_Book!$C:$C,"BEPAARI",Cash_Book!$D:$D,"GAWALI",Cash_Book!$E:$E,B77)+SUMIFS(Cash_Book!$H:$H,Cash_Book!$C:$C,"BEPAARI",Cash_Book!$D:$D,"GAWALI",Cash_Book!$E:$E,B77) | M77: =SUMIFS(Cash_Book!$G:$G,Cash_Book!$C:$C,"BEPAARI",Cash_Book!$D:$D,"CASH_ADV",Cash_Book!$E:$E,B77)+SUMIFS(Cash_Book!$H:$H,Cash_Book!$C:$C,"BEPAARI",Cash_Book!$D:$D,"CASH_ADV",Cash_Book!$E:$E,B77) | N77: =SUMIFS(Cash_Book!$G:$G,Cash_Book!$C:$C,"BEPAARI",Cash_Book!$D:$D,"OTHER",Cash_Book!$E:$E,B77)+SUMIFS(Cash_Book!$H:$H,Cash_Book!$C:$C,"BEPAARI",Cash_Book!$D:$D,"OTHER",Cash_Book!$E:$E,B77) | O77: =SUM(G77:N77) | P77: =IF(B77="","",E77-O77+D77) | Q77: =SUMIFS(Cash_Book!$G:$G,Cash_Book!$C:$C,"BEPAARI",Cash_Book!$D:$D,"PAYMENT",Cash_Book!$E:$E,B77)+SUMIFS(Cash_Book!$H:$H,Cash_Book!$C:$C,"BEPAARI",Cash_Book!$D:$D,"PAYMENT",Cash_Book!$E:$E,B77) | R77: =IF(B77="","",P77-Q77)
A78: 74 | B78: =IF(Masters!$B$76="","",Masters!$B$76) | C78: =IF(B78="","",Masters!$C$76) | D78: =IF(B78="",0,Masters!$D$76) | E78: =SUMIF(Daily_Sales!$C:$C,B78,Daily_Sales!$G:$G) | F78: =SUMIF(Daily_Sales!$C:$C,B78,Daily_Sales!$E:$E) | G78: =IF(B78="",0,E78*C78/100) | H78: =IF(F78>0,Masters!$X$3,0) | I78: =F78*Masters!$X$4 | J78: =SUMIFS(Cash_Book!$G:$G,Cash_Book!$C:$C,"BEPAARI",Cash_Book!$D:$D,"MOTOR",Cash_Book!$E:$E,B78)+SUMIFS(Cash_Book!$H:$H,Cash_Book!$C:$C,"BEPAARI",Cash_Book!$D:$D,"MOTOR",Cash_Book!$E:$E,B78) | K78: =SUMIFS(Cash_Book!$G:$G,Cash_Book!$C:$C,"BEPAARI",Cash_Book!$D:$D,"BHUSSA",Cash_Book!$E:$E,B78)+SUMIFS(Cash_Book!$H:$H,Cash_Book!$C:$C,"BEPAARI",Cash_Book!$D:$D,"BHUSSA",Cash_Book!$E:$E,B78) | L78: =SUMIFS(Cash_Book!$G:$G,Cash_Book!$C:$C,"BEPAARI",Cash_Book!$D:$D,"GAWALI",Cash_Book!$E:$E,B78)+SUMIFS(Cash_Book!$H:$H,Cash_Book!$C:$C,"BEPAARI",Cash_Book!$D:$D,"GAWALI",Cash_Book!$E:$E,B78) | M78: =SUMIFS(Cash_Book!$G:$G,Cash_Book!$C:$C,"BEPAARI",Cash_Book!$D:$D,"CASH_ADV",Cash_Book!$E:$E,B78)+SUMIFS(Cash_Book!$H:$H,Cash_Book!$C:$C,"BEPAARI",Cash_Book!$D:$D,"CASH_ADV",Cash_Book!$E:$E,B78) | N78: =SUMIFS(Cash_Book!$G:$G,Cash_Book!$C:$C,"BEPAARI",Cash_Book!$D:$D,"OTHER",Cash_Book!$E:$E,B78)+SUMIFS(Cash_Book!$H:$H,Cash_Book!$C:$C,"BEPAARI",Cash_Book!$D:$D,"OTHER",Cash_Book!$E:$E,B78) | O78: =SUM(G78:N78) | P78: =IF(B78="","",E78-O78+D78) | Q78: =SUMIFS(Cash_Book!$G:$G,Cash_Book!$C:$C,"BEPAARI",Cash_Book!$D:$D,"PAYMENT",Cash_Book!$E:$E,B78)+SUMIFS(Cash_Book!$H:$H,Cash_Book!$C:$C,"BEPAARI",Cash_Book!$D:$D,"PAYMENT",Cash_Book!$E:$E,B78) | R78: =IF(B78="","",P78-Q78)
A79: 75 | B79: =IF(Masters!$B$77="","",Masters!$B$77) | C79: =IF(B79="","",Masters!$C$77) | D79: =IF(B79="",0,Masters!$D$77) | E79: =SUMIF(Daily_Sales!$C:$C,B79,Daily_Sales!$G:$G) | F79: =SUMIF(Daily_Sales!$C:$C,B79,Daily_Sales!$E:$E) | G79: =IF(B79="",0,E79*C79/100) | H79: =IF(F79>0,Masters!$X$3,0) | I79: =F79*Masters!$X$4 | J79: =SUMIFS(Cash_Book!$G:$G,Cash_Book!$C:$C,"BEPAARI",Cash_Book!$D:$D,"MOTOR",Cash_Book!$E:$E,B79)+SUMIFS(Cash_Book!$H:$H,Cash_Book!$C:$C,"BEPAARI",Cash_Book!$D:$D,"MOTOR",Cash_Book!$E:$E,B79) | K79: =SUMIFS(Cash_Book!$G:$G,Cash_Book!$C:$C,"BEPAARI",Cash_Book!$D:$D,"BHUSSA",Cash_Book!$E:$E,B79)+SUMIFS(Cash_Book!$H:$H,Cash_Book!$C:$C,"BEPAARI",Cash_Book!$D:$D,"BHUSSA",Cash_Book!$E:$E,B79) | L79: =SUMIFS(Cash_Book!$G:$G,Cash_Book!$C:$C,"BEPAARI",Cash_Book!$D:$D,"GAWALI",Cash_Book!$E:$E,B79)+SUMIFS(Cash_Book!$H:$H,Cash_Book!$C:$C,"BEPAARI",Cash_Book!$D:$D,"GAWALI",Cash_Book!$E:$E,B79) | M79: =SUMIFS(Cash_Book!$G:$G,Cash_Book!$C:$C,"BEPAARI",Cash_Book!$D:$D,"CASH_ADV",Cash_Book!$E:$E,B79)+SUMIFS(Cash_Book!$H:$H,Cash_Book!$C:$C,"BEPAARI",Cash_Book!$D:$D,"CASH_ADV",Cash_Book!$E:$E,B79) | N79: =SUMIFS(Cash_Book!$G:$G,Cash_Book!$C:$C,"BEPAARI",Cash_Book!$D:$D,"OTHER",Cash_Book!$E:$E,B79)+SUMIFS(Cash_Book!$H:$H,Cash_Book!$C:$C,"BEPAARI",Cash_Book!$D:$D,"OTHER",Cash_Book!$E:$E,B79) | O79: =SUM(G79:N79) | P79: =IF(B79="","",E79-O79+D79) | Q79: =SUMIFS(Cash_Book!$G:$G,Cash_Book!$C:$C,"BEPAARI",Cash_Book!$D:$D,"PAYMENT",Cash_Book!$E:$E,B79)+SUMIFS(Cash_Book!$H:$H,Cash_Book!$C:$C,"BEPAARI",Cash_Book!$D:$D,"PAYMENT",Cash_Book!$E:$E,B79) | R79: =IF(B79="","",P79-Q79)
A80: 76 | B80: =IF(Masters!$B$78="","",Masters!$B$78) | C80: =IF(B80="","",Masters!$C$78) | D80: =IF(B80="",0,Masters!$D$78) | E80: =SUMIF(Daily_Sales!$C:$C,B80,Daily_Sales!$G:$G) | F80: =SUMIF(Daily_Sales!$C:$C,B80,Daily_Sales!$E:$E) | G80: =IF(B80="",0,E80*C80/100) | H80: =IF(F80>0,Masters!$X$3,0) | I80: =F80*Masters!$X$4 | J80: =SUMIFS(Cash_Book!$G:$G,Cash_Book!$C:$C,"BEPAARI",Cash_Book!$D:$D,"MOTOR",Cash_Book!$E:$E,B80)+SUMIFS(Cash_Book!$H:$H,Cash_Book!$C:$C,"BEPAARI",Cash_Book!$D:$D,"MOTOR",Cash_Book!$E:$E,B80) | K80: =SUMIFS(Cash_Book!$G:$G,Cash_Book!$C:$C,"BEPAARI",Cash_Book!$D:$D,"BHUSSA",Cash_Book!$E:$E,B80)+SUMIFS(Cash_Book!$H:$H,Cash_Book!$C:$C,"BEPAARI",Cash_Book!$D:$D,"BHUSSA",Cash_Book!$E:$E,B80) | L80: =SUMIFS(Cash_Book!$G:$G,Cash_Book!$C:$C,"BEPAARI",Cash_Book!$D:$D,"GAWALI",Cash_Book!$E:$E,B80)+SUMIFS(Cash_Book!$H:$H,Cash_Book!$C:$C,"BEPAARI",Cash_Book!$D:$D,"GAWALI",Cash_Book!$E:$E,B80) | M80: =SUMIFS(Cash_Book!$G:$G,Cash_Book!$C:$C,"BEPAARI",Cash_Book!$D:$D,"CASH_ADV",Cash_Book!$E:$E,B80)+SUMIFS(Cash_Book!$H:$H,Cash_Book!$C:$C,"BEPAARI",Cash_Book!$D:$D,"CASH_ADV",Cash_Book!$E:$E,B80) | N80: =SUMIFS(Cash_Book!$G:$G,Cash_Book!$C:$C,"BEPAARI",Cash_Book!$D:$D,"OTHER",Cash_Book!$E:$E,B80)+SUMIFS(Cash_Book!$H:$H,Cash_Book!$C:$C,"BEPAARI",Cash_Book!$D:$D,"OTHER",Cash_Book!$E:$E,B80) | O80: =SUM(G80:N80) | P80: =IF(B80="","",E80-O80+D80) | Q80: =SUMIFS(Cash_Book!$G:$G,Cash_Book!$C:$C,"BEPAARI",Cash_Book!$D:$D,"PAYMENT",Cash_Book!$E:$E,B80)+SUMIFS(Cash_Book!$H:$H,Cash_Book!$C:$C,"BEPAARI",Cash_Book!$D:$D,"PAYMENT",Cash_Book!$E:$E,B80) | R80: =IF(B80="","",P80-Q80)
A81: 77 | B81: =IF(Masters!$B$79="","",Masters!$B$79) | C81: =IF(B81="","",Masters!$C$79) | D81: =IF(B81="",0,Masters!$D$79) | E81: =SUMIF(Daily_Sales!$C:$C,B81,Daily_Sales!$G:$G) | F81: =SUMIF(Daily_Sales!$C:$C,B81,Daily_Sales!$E:$E) | G81: =IF(B81="",0,E81*C81/100) | H81: =IF(F81>0,Masters!$X$3,0) | I81: =F81*Masters!$X$4 | J81: =SUMIFS(Cash_Book!$G:$G,Cash_Book!$C:$C,"BEPAARI",Cash_Book!$D:$D,"MOTOR",Cash_Book!$E:$E,B81)+SUMIFS(Cash_Book!$H:$H,Cash_Book!$C:$C,"BEPAARI",Cash_Book!$D:$D,"MOTOR",Cash_Book!$E:$E,B81) | K81: =SUMIFS(Cash_Book!$G:$G,Cash_Book!$C:$C,"BEPAARI",Cash_Book!$D:$D,"BHUSSA",Cash_Book!$E:$E,B81)+SUMIFS(Cash_Book!$H:$H,Cash_Book!$C:$C,"BEPAARI",Cash_Book!$D:$D,"BHUSSA",Cash_Book!$E:$E,B81) | L81: =SUMIFS(Cash_Book!$G:$G,Cash_Book!$C:$C,"BEPAARI",Cash_Book!$D:$D,"GAWALI",Cash_Book!$E:$E,B81)+SUMIFS(Cash_Book!$H:$H,Cash_Book!$C:$C,"BEPAARI",Cash_Book!$D:$D,"GAWALI",Cash_Book!$E:$E,B81) | M81: =SUMIFS(Cash_Book!$G:$G,Cash_Book!$C:$C,"BEPAARI",Cash_Book!$D:$D,"CASH_ADV",Cash_Book!$E:$E,B81)+SUMIFS(Cash_Book!$H:$H,Cash_Book!$C:$C,"BEPAARI",Cash_Book!$D:$D,"CASH_ADV",Cash_Book!$E:$E,B81) | N81: =SUMIFS(Cash_Book!$G:$G,Cash_Book!$C:$C,"BEPAARI",Cash_Book!$D:$D,"OTHER",Cash_Book!$E:$E,B81)+SUMIFS(Cash_Book!$H:$H,Cash_Book!$C:$C,"BEPAARI",Cash_Book!$D:$D,"OTHER",Cash_Book!$E:$E,B81) | O81: =SUM(G81:N81) | P81: =IF(B81="","",E81-O81+D81) | Q81: =SUMIFS(Cash_Book!$G:$G,Cash_Book!$C:$C,"BEPAARI",Cash_Book!$D:$D,"PAYMENT",Cash_Book!$E:$E,B81)+SUMIFS(Cash_Book!$H:$H,Cash_Book!$C:$C,"BEPAARI",Cash_Book!$D:$D,"PAYMENT",Cash_Book!$E:$E,B81) | R81: =IF(B81="","",P81-Q81)
A82: TOTAL | D82: =SUM(D5:D81) | E82: =SUM(E5:E81) | F82: =SUM(F5:F81) | G82: =SUM(G5:G81) | H82: =SUM(H5:H81) | I82: =SUM(I5:I81) | J82: =SUM(J5:J81) | K82: =SUM(K5:K81) | ... R82: =SUM(R5:R81)

Sheet Dukandar_Ledger
A1: DUKANDAR LEDGER (Auto-calculated)
A2: From: Daily_Sales + Cash_Book (Type=DUKANDAR)
A3: Sr | B3: Dukandar | C3: Opening | D3: Purchases | E3: Discounts | F3: Net Receivable | G3: Receipts | H3: BALANCE
A4: 1 | B4: =IF(Masters!$I$3="","",Masters!$I$3) | C4: =IF(B4="",0,Masters!$J$3) | D4: =SUMIF(Daily_Sales!$D:$D,B4,Daily_Sales!$G:$G) | E4: =SUMIF(Daily_Sales!$D:$D,B4,Daily_Sales!$H:$H) | F4: =IF(B4="","",D4-E4+C4) | G4: =SUMIFS(Cash_Book!$I:$I,Cash_Book!$C:$C,"DUKANDAR",Cash_Book!$D:$D,"RECEIPT",Cash_Book!$E:$E,B4)+SUMIFS(Cash_Book!$J:$J,Cash_Book!$C:$C,"DUKANDAR",Cash_Book!$D:$D,"RECEIPT",Cash_Book!$E:$E,B4) | H4: =IF(B4="","",F4-G4)
A5: 2 | B5: =IF(Masters!$I$4="","",Masters!$I$4) | C5: =IF(B5="",0,Masters!$J$4) | D5: =SUMIF(Daily_Sales!$D:$D,B5,Daily_Sales!$G:$G) | E5: =SUMIF(Daily_Sales!$D:$D,B5,Daily_Sales!$H:$H) | F5: =IF(B5="","",D5-E5+C5) | G5: =SUMIFS(Cash_Book!$I:$I,Cash_Book!$C:$C,"DUKANDAR",Cash_Book!$D:$D,"RECEIPT",Cash_Book!$E:$E,B5)+SUMIFS(Cash_Book!$J:$J,Cash_Book!$C:$C,"DUKANDAR",Cash_Book!$D:$D,"RECEIPT",Cash_Book!$E:$E,B5) | H5: =IF(B5="","",F5-G5)
A6: 3 | B6: =IF(Masters!$I$5="","",Masters!$I$5) | C6: =IF(B6="",0,Masters!$J$5) | D6: =SUMIF(Daily_Sales!$D:$D,B6,Daily_Sales!$G:$G) | E6: =SUMIF(Daily_Sales!$D:$D,B6,Daily_Sales!$H:$H) | F6: =IF(B6="","",D6-E6+C6) | G6: =SUMIFS(Cash_Book!$I:$I,Cash_Book!$C:$C,"DUKANDAR",Cash_Book!$D:$D,"RECEIPT",Cash_Book!$E:$E,B6)+SUMIFS(Cash_Book!$J:$J,Cash_Book!$C:$C,"DUKANDAR",Cash_Book!$D:$D,"RECEIPT",Cash_Book!$E:$E,B6) | H6: =IF(B6="","",F6-G6)
A7: 4 | B7: =IF(Masters!$I$6="","",Masters!$I$6) | C7: =IF(B7="",0,Masters!$J$6) | D7: =SUMIF(Daily_Sales!$D:$D,B7,Daily_Sales!$G:$G) | E7: =SUMIF(Daily_Sales!$D:$D,B7,Daily_Sales!$H:$H) | F7: =IF(B7="","",D7-E7+C7) | G7: =SUMIFS(Cash_Book!$I:$I,Cash_Book!$C:$C,"DUKANDAR",Cash_Book!$D:$D,"RECEIPT",Cash_Book!$E:$E,B7)+SUMIFS(Cash_Book!$J:$J,Cash_Book!$C:$C,"DUKANDAR",Cash_Book!$D:$D,"RECEIPT",Cash_Book!$E:$E,B7) | H7: =IF(B7="","",F7-G7)
A8: 5 | B8: =IF(Masters!$I$7="","",Masters!$I$7) | C8: =IF(B8="",0,Masters!$J$7) | D8: =SUMIF(Daily_Sales!$D:$D,B8,Daily_Sales!$G:$G) | E8: =SUMIF(Daily_Sales!$D:$D,B8,Daily_Sales!$H:$H) | F8: =IF(B8="","",D8-E8+C8) | G8: =SUMIFS(Cash_Book!$I:$I,Cash_Book!$C:$C,"DUKANDAR",Cash_Book!$D:$D,"RECEIPT",Cash_Book!$E:$E,B8)+SUMIFS(Cash_Book!$J:$J,Cash_Book!$C:$C,"DUKANDAR",Cash_Book!$D:$D,"RECEIPT",Cash_Book!$E:$E,B8) | H8: =IF(B8="","",F8-G8)
A9: 6 | B9: =IF(Masters!$I$8="","",Masters!$I$8) | C9: =IF(B9="",0,Masters!$J$8) | D9: =SUMIF(Daily_Sales!$D:$D,B9,Daily_Sales!$G:$G) | E9: =SUMIF(Daily_Sales!$D:$D,B9,Daily_Sales!$H:$H) | F9: =IF(B9="","",D9-E9+C9) | G9: =SUMIFS(Cash_Book!$I:$I,Cash_Book!$C:$C,"DUKANDAR",Cash_Book!$D:$D,"RECEIPT",Cash_Book!$E:$E,B9)+SUMIFS(Cash_Book!$J:$J,Cash_Book!$C:$C,"DUKANDAR",Cash_Book!$D:$D,"RECEIPT",Cash_Book!$E:$E,B9) | H9: =IF(B9="","",F9-G9)
A10: 7 | B10: =IF(Masters!$I$9="","",Masters!$I$9) | C10: =IF(B10="",0,Masters!$J$9) | D10: =SUMIF(Daily_Sales!$D:$D,B10,Daily_Sales!$G:$G) | E10: =SUMIF(Daily_Sales!$D:$D,B10,Daily_Sales!$H:$H) | F10: =IF(B10="","",D10-E10+C10) | G10: =SUMIFS(Cash_Book!$I:$I,Cash_Book!$C:$C,"DUKANDAR",Cash_Book!$D:$D,"RECEIPT",Cash_Book!$E:$E,B10)+SUMIFS(Cash_Book!$J:$J,Cash_Book!$C:$C,"DUKANDAR",Cash_Book!$D:$D,"RECEIPT",Cash_Book!$E:$E,B10) | H10: =IF(B10="","",F10-G10)
A11: 8 | B11: =IF(Masters!$I$10="","",Masters!$I$10) | C11: =IF(B11="",0,Masters!$J$10) | D11: =SUMIF(Daily_Sales!$D:$D,B11,Daily_Sales!$G:$G) | E11: =SUMIF(Daily_Sales!$D:$D,B11,Daily_Sales!$H:$H) | F11: =IF(B11="","",D11-E11+C11) | G11: =SUMIFS(Cash_Book!$I:$I,Cash_Book!$C:$C,"DUKANDAR",Cash_Book!$D:$D,"RECEIPT",Cash_Book!$E:$E,B11)+SUMIFS(Cash_Book!$J:$J,Cash_Book!$C:$C,"DUKANDAR",Cash_Book!$D:$D,"RECEIPT",Cash_Book!$E:$E,B11) | H11: =IF(B11="","",F11-G11)
A12: 9 | B12: =IF(Masters!$I$11="","",Masters!$I$11) | C12: =IF(B12="",0,Masters!$J$11) | D12: =SUMIF(Daily_Sales!$D:$D,B12,Daily_Sales!$G:$G) | E12: =SUMIF(Daily_Sales!$D:$D,B12,Daily_Sales!$H:$H) | F12: =IF(B12="","",D12-E12+C12) | G12: =SUMIFS(Cash_Book!$I:$I,Cash_Book!$C:$C,"DUKANDAR",Cash_Book!$D:$D,"RECEIPT",Cash_Book!$E:$E,B12)+SUMIFS(Cash_Book!$J:$J,Cash_Book!$C:$C,"DUKANDAR",Cash_Book!$D:$D,"RECEIPT",Cash_Book!$E:$E,B12) | H12: =IF(B12="","",F12-G12)
A13: 10 | B13: =IF(Masters!$I$12="","",Masters!$I$12) | C13: =IF(B13="",0,Masters!$J$12) | D13: =SUMIF(Daily_Sales!$D:$D,B13,Daily_Sales!$G:$G) | E13: =SUMIF(Daily_Sales!$D:$D,B13,Daily_Sales!$H:$H) | F13: =IF(B13="","",D13-E13+C13) | G13: =SUMIFS(Cash_Book!$I:$I,Cash_Book!$C:$C,"DUKANDAR",Cash_Book!$D:$D,"RECEIPT",Cash_Book!$E:$E,B13)+SUMIFS(Cash_Book!$J:$J,Cash_Book!$C:$C,"DUKANDAR",Cash_Book!$D:$D,"RECEIPT",Cash_Book!$E:$E,B13) | H13: =IF(B13="","",F13-G13)
A14: 11 | B14: =IF(Masters!$I$13="","",Masters!$I$13) | C14: =IF(B14="",0,Masters!$J$13) | D14: =SUMIF(Daily_Sales!$D:$D,B14,Daily_Sales!$G:$G) | E14: =SUMIF(Daily_Sales!$D:$D,B14,Daily_Sales!$H:$H) | F14: =IF(B14="","",D14-E14+C14) | G14: =SUMIFS(Cash_Book!$I:$I,Cash_Book!$C:$C,"DUKANDAR",Cash_Book!$D:$D,"RECEIPT",Cash_Book!$E:$E,B14)+SUMIFS(Cash_Book!$J:$J,Cash_Book!$C:$C,"DUKANDAR",Cash_Book!$D:$D,"RECEIPT",Cash_Book!$E:$E,B14) | H14: =IF(B14="","",F14-G14)
A15: 12 | B15: =IF(Masters!$I$14="","",Masters!$I$14) | C15: =IF(B15="",0,Masters!$J$14) | D15: =SUMIF(Daily_Sales!$D:$D,B15,Daily_Sales!$G:$G) | E15: =SUMIF(Daily_Sales!$D:$D,B15,Daily_Sales!$H:$H) | F15: =IF(B15="","",D15-E15+C15) | G15: =SUMIFS(Cash_Book!$I:$I,Cash_Book!$C:$C,"DUKANDAR",Cash_Book!$D:$D,"RECEIPT",Cash_Book!$E:$E,B15)+SUMIFS(Cash_Book!$J:$J,Cash_Book!$C:$C,"DUKANDAR",Cash_Book!$D:$D,"RECEIPT",Cash_Book!$E:$E,B15) | H15: =IF(B15="","",F15-G15)
A16: 13 | B16: =IF(Masters!$I$15="","",Masters!$I$15) | C16: =IF(B16="",0,Masters!$J$15) | D16: =SUMIF(Daily_Sales!$D:$D,B16,Daily_Sales!$G:$G) | E16: =SUMIF(Daily_Sales!$D:$D,B16,Daily_Sales!$H:$H) | F16: =IF(B16="","",D16-E16+C16) | G16: =SUMIFS(Cash_Book!$I:$I,Cash_Book!$C:$C,"DUKANDAR",Cash_Book!$D:$D,"RECEIPT",Cash_Book!$E:$E,B16)+SUMIFS(Cash_Book!$J:$J,Cash_Book!$C:$C,"DUKANDAR",Cash_Book!$D:$D,"RECEIPT",Cash_Book!$E:$E,B16) | H16: =IF(B16="","",F16-G16)
A17: 14 | B17: =IF(Masters!$I$16="","",Masters!$I$16) | C17: =IF(B17="",0,Masters!$J$16) | D17: =SUMIF(Daily_Sales!$D:$D,B17,Daily_Sales!$G:$G) | E17: =SUMIF(Daily_Sales!$D:$D,B17,Daily_Sales!$H:$H) | F17: =IF(B17="","",D17-E17+C17) | G17: =SUMIFS(Cash_Book!$I:$I,Cash_Book!$C:$C,"DUKANDAR",Cash_Book!$D:$D,"RECEIPT",Cash_Book!$E:$E,B17)+SUMIFS(Cash_Book!$J:$J,Cash_Book!$C:$C,"DUKANDAR",Cash_Book!$D:$D,"RECEIPT",Cash_Book!$E:$E,B17) | H17: =IF(B17="","",F17-G17)
A18: 15 | B18: =IF(Masters!$I$17="","",Masters!$I$17) | C18: =IF(B18="",0,Masters!$J$17) | D18: =SUMIF(Daily_Sales!$D:$D,B18,Daily_Sales!$G:$G) | E18: =SUMIF(Daily_Sales!$D:$D,B18,Daily_Sales!$H:$H) | F18: =IF(B18="","",D18-E18+C18) | G18: =SUMIFS(Cash_Book!$I:$I,Cash_Book!$C:$C,"DUKANDAR",Cash_Book!$D:$D,"RECEIPT",Cash_Book!$E:$E,B18)+SUMIFS(Cash_Book!$J:$J,Cash_Book!$C:$C,"DUKANDAR",Cash_Book!$D:$D,"RECEIPT",Cash_Book!$E:$E,B18) | H18: =IF(B18="","",F18-G18)
A19: 16 | B19: =IF(Masters!$I$18="","",Masters!$I$18) | C19: =IF(B19="",0,Masters!$J$18) | D19: =SUMIF(Daily_Sales!$D:$D,B19,Daily_Sales!$G:$G) | E19: =SUMIF(Daily_Sales!$D:$D,B19,Daily_Sales!$H:$H) | F19: =IF(B19="","",D19-E19+C19) | G19: =SUMIFS(Cash_Book!$I:$I,Cash_Book!$C:$C,"DUKANDAR",Cash_Book!$D:$D,"RECEIPT",Cash_Book!$E:$E,B19)+SUMIFS(Cash_Book!$J:$J,Cash_Book!$C:$C,"DUKANDAR",Cash_Book!$D:$D,"RECEIPT",Cash_Book!$E:$E,B19) | H19: =IF(B19="","",F19-G19)
A20: 17 | B20: =IF(Masters!$I$19="","",Masters!$I$19) | C20: =IF(B20="",0,Masters!$J$19) | D20: =SUMIF(Daily_Sales!$D:$D,B20,Daily_Sales!$G:$G) | E20: =SUMIF(Daily_Sales!$D:$D,B20,Daily_Sales!$H:$H) | F20: =IF(B20="","",D20-E20+C20) | G20: =SUMIFS(Cash_Book!$I:$I,Cash_Book!$C:$C,"DUKANDAR",Cash_Book!$D:$D,"RECEIPT",Cash_Book!$E:$E,B20)+SUMIFS(Cash_Book!$J:$J,Cash_Book!$C:$C,"DUKANDAR",Cash_Book!$D:$D,"RECEIPT",Cash_Book!$E:$E,B20) | H20: =IF(B20="","",F20-G20)
A21: 18 | B21: =IF(Masters!$I$20="","",Masters!$I$20) | C21: =IF(B21="",0,Masters!$J$20) | D21: =SUMIF(Daily_Sales!$D:$D,B21,Daily_Sales!$G:$G) | E21: =SUMIF(Daily_Sales!$D:$D,B21,Daily_Sales!$H:$H) | F21: =IF(B21="","",D21-E21+C21) | G21: =SUMIFS(Cash_Book!$I:$I,Cash_Book!$C:$C,"DUKANDAR",Cash_Book!$D:$D,"RECEIPT",Cash_Book!$E:$E,B21)+SUMIFS(Cash_Book!$J:$J,Cash_Book!$C:$C,"DUKANDAR",Cash_Book!$D:$D,"RECEIPT",Cash_Book!$E:$E,B21) | H21: =IF(B21="","",F21-G21)
A22: 19 | B22: =IF(Masters!$I$21="","",Masters!$I$21) | C22: =IF(B22="",0,Masters!$J$21) | D22: =SUMIF(Daily_Sales!$D:$D,B22,Daily_Sales!$G:$G) | E22: =SUMIF(Daily_Sales!$D:$D,B22,Daily_Sales!$H:$H) | F22: =IF(B22="","",D22-E22+C22) | G22: =SUMIFS(Cash_Book!$I:$I,Cash_Book!$C:$C,"DUKANDAR",Cash_Book!$D:$D,"RECEIPT",Cash_Book!$E:$E,B22)+SUMIFS(Cash_Book!$J:$J,Cash_Book!$C:$C,"DUKANDAR",Cash_Book!$D:$D,"RECEIPT",Cash_Book!$E:$E,B22) | H22: =IF(B22="","",F22-G22)
A23: 20 | B23: =IF(Masters!$I$22="","",Masters!$I$22) | C23: =IF(B23="",0,Masters!$J$22) | D23: =SUMIF(Daily_Sales!$D:$D,B23,Daily_Sales!$G:$G) | E23: =SUMIF(Daily_Sales!$D:$D,B23,Daily_Sales!$H:$H) | F23: =IF(B23="","",D23-E23+C23) | G23: =SUMIFS(Cash_Book!$I:$I,Cash_Book!$C:$C,"DUKANDAR",Cash_Book!$D:$D,"RECEIPT",Cash_Book!$E:$E,B23)+SUMIFS(Cash_Book!$J:$J,Cash_Book!$C:$C,"DUKANDAR",Cash_Book!$D:$D,"RECEIPT",Cash_Book!$E:$E,B23) | H23: =IF(B23="","",F23-G23)
A24: 21 | B24: =IF(Masters!$I$23="","",Masters!$I$23) | C24: =IF(B24="",0,Masters!$J$23) | D24: =SUMIF(Daily_Sales!$D:$D,B24,Daily_Sales!$G:$G) | E24: =SUMIF(Daily_Sales!$D:$D,B24,Daily_Sales!$H:$H) | F24: =IF(B24="","",D24-E24+C24) | G24: =SUMIFS(Cash_Book!$I:$I,Cash_Book!$C:$C,"DUKANDAR",Cash_Book!$D:$D,"RECEIPT",Cash_Book!$E:$E,B24)+SUMIFS(Cash_Book!$J:$J,Cash_Book!$C:$C,"DUKANDAR",Cash_Book!$D:$D,"RECEIPT",Cash_Book!$E:$E,B24) | H24: =IF(B24="","",F24-G24)
A25: 22 | B25: =IF(Masters!$I$24="","",Masters!$I$24) | C25: =IF(B25="",0,Masters!$J$24) | D25: =SUMIF(Daily_Sales!$D:$D,B25,Daily_Sales!$G:$G) | E25: =SUMIF(Daily_Sales!$D:$D,B25,Daily_Sales!$H:$H) | F25: =IF(B25="","",D25-E25+C25) | G25: =SUMIFS(Cash_Book!$I:$I,Cash_Book!$C:$C,"DUKANDAR",Cash_Book!$D:$D,"RECEIPT",Cash_Book!$E:$E,B25)+SUMIFS(Cash_Book!$J:$J,Cash_Book!$C:$C,"DUKANDAR",Cash_Book!$D:$D,"RECEIPT",Cash_Book!$E:$E,B25) | H25: =IF(B25="","",F25-G25)
A26: 23 | B26: =IF(Masters!$I$25="","",Masters!$I$25) | C26: =IF(B26="",0,Masters!$J$25) | D26: =SUMIF(Daily_Sales!$D:$D,B26,Daily_Sales!$G:$G) | E26: =SUMIF(Daily_Sales!$D:$D,B26,Daily_Sales!$H:$H) | F26: =IF(B26="","",D26-E26+C26) | G26: =SUMIFS(Cash_Book!$I:$I,Cash_Book!$C:$C,"DUKANDAR",Cash_Book!$D:$D,"RECEIPT",Cash_Book!$E:$E,B26)+SUMIFS(Cash_Book!$J:$J,Cash_Book!$C:$C,"DUKANDAR",Cash_Book!$D:$D,"RECEIPT",Cash_Book!$E:$E,B26) | H26: =IF(B26="","",F26-G26)
A27: 24 | B27: =IF(Masters!$I$26="","",Masters!$I$26) | C27: =IF(B27="",0,Masters!$J$26) | D27: =SUMIF(Daily_Sales!$D:$D,B27,Daily_Sales!$G:$G) | E27: =SUMIF(Daily_Sales!$D:$D,B27,Daily_Sales!$H:$H) | F27: =IF(B27="","",D27-E27+C27) | G27: =SUMIFS(Cash_Book!$I:$I,Cash_Book!$C:$C,"DUKANDAR",Cash_Book!$D:$D,"RECEIPT",Cash_Book!$E:$E,B27)+SUMIFS(Cash_Book!$J:$J,Cash_Book!$C:$C,"DUKANDAR",Cash_Book!$D:$D,"RECEIPT",Cash_Book!$E:$E,B27) | H27: =IF(B27="","",F27-G27)
A28: 25 | B28: =IF(Masters!$I$27="","",Masters!$I$27) | C28: =IF(B28="",0,Masters!$J$27) | D28: =SUMIF(Daily_Sales!$D:$D,B28,Daily_Sales!$G:$G) | E28: =SUMIF(Daily_Sales!$D:$D,B28,Daily_Sales!$H:$H) | F28: =IF(B28="","",D28-E28+C28) | G28: =SUMIFS(Cash_Book!$I:$I,Cash_Book!$C:$C,"DUKANDAR",Cash_Book!$D:$D,"RECEIPT",Cash_Book!$E:$E,B28)+SUMIFS(Cash_Book!$J:$J,Cash_Book!$C:$C,"DUKANDAR",Cash_Book!$D:$D,"RECEIPT",Cash_Book!$E:$E,B28) | H28: =IF(B28="","",F28-G28)
A29: 26 | B29: =IF(Masters!$I$28="","",Masters!$I$28) | C29: =IF(B29="",0,Masters!$J$28) | D29: =SUMIF(Daily_Sales!$D:$D,B29,Daily_Sales!$G:$G) | E29: =SUMIF(Daily_Sales!$D:$D,B29,Daily_Sales!$H:$H) | F29: =IF(B29="","",D29-E29+C29) | G29: =SUMIFS(Cash_Book!$I:$I,Cash_Book!$C:$C,"DUKANDAR",Cash_Book!$D:$D,"RECEIPT",Cash_Book!$E:$E,B29)+SUMIFS(Cash_Book!$J:$J,Cash_Book!$C:$C,"DUKANDAR",Cash_Book!$D:$D,"RECEIPT",Cash_Book!$E:$E,B29) | H29: =IF(B29="","",F29-G29)
A30: 27 | B30: =IF(Masters!$I$29="","",Masters!$I$29) | C30: =IF(B30="",0,Masters!$J$29) | D30: =SUMIF(Daily_Sales!$D:$D,B30,Daily_Sales!$G:$G) | E30: =SUMIF(Daily_Sales!$D:$D,B30,Daily_Sales!$H:$H) | F30: =IF(B30="","",D30-E30+C30) | G30: =SUMIFS(Cash_Book!$I:$I,Cash_Book!$C:$C,"DUKANDAR",Cash_Book!$D:$D,"RECEIPT",Cash_Book!$E:$E,B30)+SUMIFS(Cash_Book!$J:$J,Cash_Book!$C:$C,"DUKANDAR",Cash_Book!$D:$D,"RECEIPT",Cash_Book!$E:$E,B30) | H30: =IF(B30="","",F30-G30)
A31: 28 | B31: =IF(Masters!$I$30="","",Masters!$I$30) | C31: =IF(B31="",0,Masters!$J$30) | D31: =SUMIF(Daily_Sales!$D:$D,B31,Daily_Sales!$G:$G) | E31: =SUMIF(Daily_Sales!$D:$D,B31,Daily_Sales!$H:$H) | F31: =IF(B31="","",D31-E31+C31) | G31: =SUMIFS(Cash_Book!$I:$I,Cash_Book!$C:$C,"DUKANDAR",Cash_Book!$D:$D,"RECEIPT",Cash_Book!$E:$E,B31)+SUMIFS(Cash_Book!$J:$J,Cash_Book!$C:$C,"DUKANDAR",Cash_Book!$D:$D,"RECEIPT",Cash_Book!$E:$E,B31) | H31: =IF(B31="","",F31-G31)
A32: 29 | B32: =IF(Masters!$I$31="","",Masters!$I$31) | C32: =IF(B32="",0,Masters!$J$31) | D32: =SUMIF(Daily_Sales!$D:$D,B32,Daily_Sales!$G:$G) | E32: =SUMIF(Daily_Sales!$D:$D,B32,Daily_Sales!$H:$H) | F32: =IF(B32="","",D32-E32+C32) | G32: =SUMIFS(Cash_Book!$I:$I,Cash_Book!$C:$C,"DUKANDAR",Cash_Book!$D:$D,"RECEIPT",Cash_Book!$E:$E,B32)+SUMIFS(Cash_Book!$J:$J,Cash_Book!$C:$C,"DUKANDAR",Cash_Book!$D:$D,"RECEIPT",Cash_Book!$E:$E,B32) | H32: =IF(B32="","",F32-G32)
A33: 30 | B33: =IF(Masters!$I$32="","",Masters!$I$32) | C33: =IF(B33="",0,Masters!$J$32) | D33: =SUMIF(Daily_Sales!$D:$D,B33,Daily_Sales!$G:$G) | E33: =SUMIF(Daily_Sales!$D:$D,B33,Daily_Sales!$H:$H) | F33: =IF(B33="","",D33-E33+C33) | G33: =SUMIFS(Cash_Book!$I:$I,Cash_Book!$C:$C,"DUKANDAR",Cash_Book!$D:$D,"RECEIPT",Cash_Book!$E:$E,B33)+SUMIFS(Cash_Book!$J:$J,Cash_Book!$C:$C,"DUKANDAR",Cash_Book!$D:$D,"RECEIPT",Cash_Book!$E:$E,B33) | H33: =IF(B33="","",F33-G33)
A34: 31 | B34: =IF(Masters!$I$33="","",Masters!$I$33) | C34: =IF(B34="",0,Masters!$J$33) | D34: =SUMIF(Daily_Sales!$D:$D,B34,Daily_Sales!$G:$G) | E34: =SUMIF(Daily_Sales!$D:$D,B34,Daily_Sales!$H:$H) | F34: =IF(B34="","",D34-E34+C34) | G34: =SUMIFS(Cash_Book!$I:$I,Cash_Book!$C:$C,"DUKANDAR",Cash_Book!$D:$D,"RECEIPT",Cash_Book!$E:$E,B34)+SUMIFS(Cash_Book!$J:$J,Cash_Book!$C:$C,"DUKANDAR",Cash_Book!$D:$D,"RECEIPT",Cash_Book!$E:$E,B34) | H34: =IF(B34="","",F34-G34)
A35: 32 | B35: =IF(Masters!$I$34="","",Masters!$I$34) | C35: =IF(B35="",0,Masters!$J$34) | D35: =SUMIF(Daily_Sales!$D:$D,B35,Daily_Sales!$G:$G) | E35: =SUMIF(Daily_Sales!$D:$D,B35,Daily_Sales!$H:$H) | F35: =IF(B35="","",D35-E35+C35) | G35: =SUMIFS(Cash_Book!$I:$I,Cash_Book!$C:$C,"DUKANDAR",Cash_Book!$D:$D,"RECEIPT",Cash_Book!$E:$E,B35)+SUMIFS(Cash_Book!$J:$J,Cash_Book!$C:$C,"DUKANDAR",Cash_Book!$D:$D,"RECEIPT",Cash_Book!$E:$E,B35) | H35: =IF(B35="","",F35-G35)
A36: 33 | B36: =IF(Masters!$I$35="","",Masters!$I$35) | C36: =IF(B36="",0,Masters!$J$35) | D36: =SUMIF(Daily_Sales!$D:$D,B36,Daily_Sales!$G:$G) | E36: =SUMIF(Daily_Sales!$D:$D,B36,Daily_Sales!$H:$H) | F36: =IF(B36="","",D36-E36+C36) | G36: =SUMIFS(Cash_Book!$I:$I,Cash_Book!$C:$C,"DUKANDAR",Cash_Book!$D:$D,"RECEIPT",Cash_Book!$E:$E,B36)+SUMIFS(Cash_Book!$J:$J,Cash_Book!$C:$C,"DUKANDAR",Cash_Book!$D:$D,"RECEIPT",Cash_Book!$E:$E,B36) | H36: =IF(B36="","",F36-G36)
A37: 34 | B37: =IF(Masters!$I$36="","",Masters!$I$36) | C37: =IF(B37="",0,Masters!$J$36) | D37: =SUMIF(Daily_Sales!$D:$D,B37,Daily_Sales!$G:$G) | E37: =SUMIF(Daily_Sales!$D:$D,B37,Daily_Sales!$H:$H) | F37: =IF(B37="","",D37-E37+C37) | G37: =SUMIFS(Cash_Book!$I:$I,Cash_Book!$C:$C,"DUKANDAR",Cash_Book!$D:$D,"RECEIPT",Cash_Book!$E:$E,B37)+SUMIFS(Cash_Book!$J:$J,Cash_Book!$C:$C,"DUKANDAR",Cash_Book!$D:$D,"RECEIPT",Cash_Book!$E:$E,B37) | H37: =IF(B37="","",F37-G37)
A38: 35 | B38: =IF(Masters!$I$37="","",Masters!$I$37) | C38: =IF(B38="",0,Masters!$J$37) | D38: =SUMIF(Daily_Sales!$D:$D,B38,Daily_Sales!$G:$G) | E38: =SUMIF(Daily_Sales!$D:$D,B38,Daily_Sales!$H:$H) | F38: =IF(B38="","",D38-E38+C38) | G38: =SUMIFS(Cash_Book!$I:$I,Cash_Book!$C:$C,"DUKANDAR",Cash_Book!$D:$D,"RECEIPT",Cash_Book!$E:$E,B38)+SUMIFS(Cash_Book!$J:$J,Cash_Book!$C:$C,"DUKANDAR",Cash_Book!$D:$D,"RECEIPT",Cash_Book!$E:$E,B38) | H38: =IF(B38="","",F38-G38)
A39: 36 | B39: =IF(Masters!$I$38="","",Masters!$I$38) | C39: =IF(B39="",0,Masters!$J$38) | D39: =SUMIF(Daily_Sales!$D:$D,B39,Daily_Sales!$G:$G) | E39: =SUMIF(Daily_Sales!$D:$D,B39,Daily_Sales!$H:$H) | F39: =IF(B39="","",D39-E39+C39) | G39: =SUMIFS(Cash_Book!$I:$I,Cash_Book!$C:$C,"DUKANDAR",Cash_Book!$D:$D,"RECEIPT",Cash_Book!$E:$E,B39)+SUMIFS(Cash_Book!$J:$J,Cash_Book!$C:$C,"DUKANDAR",Cash_Book!$D:$D,"RECEIPT",Cash_Book!$E:$E,B39) | H39: =IF(B39="","",F39-G39)
A40: 37 | B40: =IF(Masters!$I$39="","",Masters!$I$39) | C40: =IF(B40="",0,Masters!$J$39) | D40: =SUMIF(Daily_Sales!$D:$D,B40,Daily_Sales!$G:$G) | E40: =SUMIF(Daily_Sales!$D:$D,B40,Daily_Sales!$H:$H) | F40: =IF(B40="","",D40-E40+C40) | G40: =SUMIFS(Cash_Book!$I:$I,Cash_Book!$C:$C,"DUKANDAR",Cash_Book!$D:$D,"RECEIPT",Cash_Book!$E:$E,B40)+SUMIFS(Cash_Book!$J:$J,Cash_Book!$C:$C,"DUKANDAR",Cash_Book!$D:$D,"RECEIPT",Cash_Book!$E:$E,B40) | H40: =IF(B40="","",F40-G40)
A41: 38 | B41: =IF(Masters!$I$40="","",Masters!$I$40) | C41: =IF(B41="",0,Masters!$J$40) | D41: =SUMIF(Daily_Sales!$D:$D,B41,Daily_Sales!$G:$G) | E41: =SUMIF(Daily_Sales!$D:$D,B41,Daily_Sales!$H:$H) | F41: =IF(B41="","",D41-E41+C41) | G41: =SUMIFS(Cash_Book!$I:$I,Cash_Book!$C:$C,"DUKANDAR",Cash_Book!$D:$D,"RECEIPT",Cash_Book!$E:$E,B41)+SUMIFS(Cash_Book!$J:$J,Cash_Book!$C:$C,"DUKANDAR",Cash_Book!$D:$D,"RECEIPT",Cash_Book!$E:$E,B41) | H41: =IF(B41="","",F41-G41)
A42: 39 | B42: =IF(Masters!$I$41="","",Masters!$I$41) | C42: =IF(B42="",0,Masters!$J$41) | D42: =SUMIF(Daily_Sales!$D:$D,B42,Daily_Sales!$G:$G) | E42: =SUMIF(Daily_Sales!$D:$D,B42,Daily_Sales!$H:$H) | F42: =IF(B42="","",D42-E42+C42) | G42: =SUMIFS(Cash_Book!$I:$I,Cash_Book!$C:$C,"DUKANDAR",Cash_Book!$D:$D,"RECEIPT",Cash_Book!$E:$E,B42)+SUMIFS(Cash_Book!$J:$J,Cash_Book!$C:$C,"DUKANDAR",Cash_Book!$D:$D,"RECEIPT",Cash_Book!$E:$E,B42) | H42: =IF(B42="","",F42-G42)
A43: 40 | B43: =IF(Masters!$I$42="","",Masters!$I$42) | C43: =IF(B43="",0,Masters!$J$42) | D43: =SUMIF(Daily_Sales!$D:$D,B43,Daily_Sales!$G:$G) | E43: =SUMIF(Daily_Sales!$D:$D,B43,Daily_Sales!$H:$H) | F43: =IF(B43="","",D43-E43+C43) | G43: =SUMIFS(Cash_Book!$I:$I,Cash_Book!$C:$C,"DUKANDAR",Cash_Book!$D:$D,"RECEIPT",Cash_Book!$E:$E,B43)+SUMIFS(Cash_Book!$J:$J,Cash_Book!$C:$C,"DUKANDAR",Cash_Book!$D:$D,"RECEIPT",Cash_Book!$E:$E,B43) | H43: =IF(B43="","",F43-G43)
A44: 41 | B44: =IF(Masters!$I$43="","",Masters!$I$43) | C44: =IF(B44="",0,Masters!$J$43) | D44: =SUMIF(Daily_Sales!$D:$D,B44,Daily_Sales!$G:$G) | E44: =SUMIF(Daily_Sales!$D:$D,B44,Daily_Sales!$H:$H) | F44: =IF(B44="","",D44-E44+C44) | G44: =SUMIFS(Cash_Book!$I:$I,Cash_Book!$C:$C,"DUKANDAR",Cash_Book!$D:$D,"RECEIPT",Cash_Book!$E:$E,B44)+SUMIFS(Cash_Book!$J:$J,Cash_Book!$C:$C,"DUKANDAR",Cash_Book!$D:$D,"RECEIPT",Cash_Book!$E:$E,B44) | H44: =IF(B44="","",F44-G44)
A45: 42 | B45: =IF(Masters!$I$44="","",Masters!$I$44) | C45: =IF(B45="",0,Masters!$J$44) | D45: =SUMIF(Daily_Sales!$D:$D,B45,Daily_Sales!$G:$G) | E45: =SUMIF(Daily_Sales!$D:$D,B45,Daily_Sales!$H:$H) | F45: =IF(B45="","",D45-E45+C45) | G45: =SUMIFS(Cash_Book!$I:$I,Cash_Book!$C:$C,"DUKANDAR",Cash_Book!$D:$D,"RECEIPT",Cash_Book!$E:$E,B45)+SUMIFS(Cash_Book!$J:$J,Cash_Book!$C:$C,"DUKANDAR",Cash_Book!$D:$D,"RECEIPT",Cash_Book!$E:$E,B45) | H45: =IF(B45="","",F45-G45)
A46: 43 | B46: =IF(Masters!$I$45="","",Masters!$I$45) | C46: =IF(B46="",0,Masters!$J$45) | D46: =SUMIF(Daily_Sales!$D:$D,B46,Daily_Sales!$G:$G) | E46: =SUMIF(Daily_Sales!$D:$D,B46,Daily_Sales!$H:$H) | F46: =IF(B46="","",D46-E46+C46) | G46: =SUMIFS(Cash_Book!$I:$I,Cash_Book!$C:$C,"DUKANDAR",Cash_Book!$D:$D,"RECEIPT",Cash_Book!$E:$E,B46)+SUMIFS(Cash_Book!$J:$J,Cash_Book!$C:$C,"DUKANDAR",Cash_Book!$D:$D,"RECEIPT",Cash_Book!$E:$E,B46) | H46: =IF(B46="","",F46-G46)
A47: 44 | B47: =IF(Masters!$I$46="","",Masters!$I$46) | C47: =IF(B47="",0,Masters!$J$46) | D47: =SUMIF(Daily_Sales!$D:$D,B47,Daily_Sales!$G:$G) | E47: =SUMIF(Daily_Sales!$D:$D,B47,Daily_Sales!$H:$H) | F47: =IF(B47="","",D47-E47+C47) | G47: =SUMIFS(Cash_Book!$I:$I,Cash_Book!$C:$C,"DUKANDAR",Cash_Book!$D:$D,"RECEIPT",Cash_Book!$E:$E,B47)+SUMIFS(Cash_Book!$J:$J,Cash_Book!$C:$C,"DUKANDAR",Cash_Book!$D:$D,"RECEIPT",Cash_Book!$E:$E,B47) | H47: =IF(B47="","",F47-G47)
A48: 45 | B48: =IF(Masters!$I$47="","",Masters!$I$47) | C48: =IF(B48="",0,Masters!$J$47) | D48: =SUMIF(Daily_Sales!$D:$D,B48,Daily_Sales!$G:$G) | E48: =SUMIF(Daily_Sales!$D:$D,B48,Daily_Sales!$H:$H) | F48: =IF(B48="","",D48-E48+C48) | G48: =SUMIFS(Cash_Book!$I:$I,Cash_Book!$C:$C,"DUKANDAR",Cash_Book!$D:$D,"RECEIPT",Cash_Book!$E:$E,B48)+SUMIFS(Cash_Book!$J:$J,Cash_Book!$C:$C,"DUKANDAR",Cash_Book!$D:$D,"RECEIPT",Cash_Book!$E:$E,B48) | H48: =IF(B48="","",F48-G48)
A49: 46 | B49: =IF(Masters!$I$48="","",Masters!$I$48) | C49: =IF(B49="",0,Masters!$J$48) | D49: =SUMIF(Daily_Sales!$D:$D,B49,Daily_Sales!$G:$G) | E49: =SUMIF(Daily_Sales!$D:$D,B49,Daily_Sales!$H:$H) | F49: =IF(B49="","",D49-E49+C49) | G49: =SUMIFS(Cash_Book!$I:$I,Cash_Book!$C:$C,"DUKANDAR",Cash_Book!$D:$D,"RECEIPT",Cash_Book!$E:$E,B49)+SUMIFS(Cash_Book!$J:$J,Cash_Book!$C:$C,"DUKANDAR",Cash_Book!$D:$D,"RECEIPT",Cash_Book!$E:$E,B49) | H49: =IF(B49="","",F49-G49)
A50: 47 | B50: =IF(Masters!$I$49="","",Masters!$I$49) | C50: =IF(B50="",0,Masters!$J$49) | D50: =SUMIF(Daily_Sales!$D:$D,B50,Daily_Sales!$G:$G) | E50: =SUMIF(Daily_Sales!$D:$D,B50,Daily_Sales!$H:$H) | F50: =IF(B50="","",D50-E50+C50) | G50: =SUMIFS(Cash_Book!$I:$I,Cash_Book!$C:$C,"DUKANDAR",Cash_Book!$D:$D,"RECEIPT",Cash_Book!$E:$E,B50)+SUMIFS(Cash_Book!$J:$J,Cash_Book!$C:$C,"DUKANDAR",Cash_Book!$D:$D,"RECEIPT",Cash_Book!$E:$E,B50) | H50: =IF(B50="","",F50-G50)
A51: 48 | B51: =IF(Masters!$I$50="","",Masters!$I$50) | C51: =IF(B51="",0,Masters!$J$50) | D51: =SUMIF(Daily_Sales!$D:$D,B51,Daily_Sales!$G:$G) | E51: =SUMIF(Daily_Sales!$D:$D,B51,Daily_Sales!$H:$H) | F51: =IF(B51="","",D51-E51+C51) | G51: =SUMIFS(Cash_Book!$I:$I,Cash_Book!$C:$C,"DUKANDAR",Cash_Book!$D:$D,"RECEIPT",Cash_Book!$E:$E,B51)+SUMIFS(Cash_Book!$J:$J,Cash_Book!$C:$C,"DUKANDAR",Cash_Book!$D:$D,"RECEIPT",Cash_Book!$E:$E,B51) | H51: =IF(B51="","",F51-G51)
A52: 49 | B52: =IF(Masters!$I$51="","",Masters!$I$51) | C52: =IF(B52="",0,Masters!$J$51) | D52: =SUMIF(Daily_Sales!$D:$D,B52,Daily_Sales!$G:$G) | E52: =SUMIF(Daily_Sales!$D:$D,B52,Daily_Sales!$H:$H) | F52: =IF(B52="","",D52-E52+C52) | G52: =SUMIFS(Cash_Book!$I:$I,Cash_Book!$C:$C,"DUKANDAR",Cash_Book!$D:$D,"RECEIPT",Cash_Book!$E:$E,B52)+SUMIFS(Cash_Book!$J:$J,Cash_Book!$C:$C,"DUKANDAR",Cash_Book!$D:$D,"RECEIPT",Cash_Book!$E:$E,B52) | H52: =IF(B52="","",F52-G52)
A53: 50 | B53: =IF(Masters!$I$52="","",Masters!$I$52) | C53: =IF(B53="",0,Masters!$J$52) | D53: =SUMIF(Daily_Sales!$D:$D,B53,Daily_Sales!$G:$G) | E53: =SUMIF(Daily_Sales!$D:$D,B53,Daily_Sales!$H:$H) | F53: =IF(B53="","",D53-E53+C53) | G53: =SUMIFS(Cash_Book!$I:$I,Cash_Book!$C:$C,"DUKANDAR",Cash_Book!$D:$D,"RECEIPT",Cash_Book!$E:$E,B53)+SUMIFS(Cash_Book!$J:$J,Cash_Book!$C:$C,"DUKANDAR",Cash_Book!$D:$D,"RECEIPT",Cash_Book!$E:$E,B53) | H53: =IF(B53="","",F53-G53)
A54: 51 | B54: =IF(Masters!$I$53="","",Masters!$I$53) | C54: =IF(B54="",0,Masters!$J$53) | D54: =SUMIF(Daily_Sales!$D:$D,B54,Daily_Sales!$G:$G) | E54: =SUMIF(Daily_Sales!$D:$D,B54,Daily_Sales!$H:$H) | F54: =IF(B54="","",D54-E54+C54) | G54: =SUMIFS(Cash_Book!$I:$I,Cash_Book!$C:$C,"DUKANDAR",Cash_Book!$D:$D,"RECEIPT",Cash_Book!$E:$E,B54)+SUMIFS(Cash_Book!$J:$J,Cash_Book!$C:$C,"DUKANDAR",Cash_Book!$D:$D,"RECEIPT",Cash_Book!$E:$E,B54) | H54: =IF(B54="","",F54-G54)
A55: 52 | B55: =IF(Masters!$I$54="","",Masters!$I$54) | C55: =IF(B55="",0,Masters!$J$54) | D55: =SUMIF(Daily_Sales!$D:$D,B55,Daily_Sales!$G:$G) | E55: =SUMIF(Daily_Sales!$D:$D,B55,Daily_Sales!$H:$H) | F55: =IF(B55="","",D55-E55+C55) | G55: =SUMIFS(Cash_Book!$I:$I,Cash_Book!$C:$C,"DUKANDAR",Cash_Book!$D:$D,"RECEIPT",Cash_Book!$E:$E,B55)+SUMIFS(Cash_Book!$J:$J,Cash_Book!$C:$C,"DUKANDAR",Cash_Book!$D:$D,"RECEIPT",Cash_Book!$E:$E,B55) | H55: =IF(B55="","",F55-G55)
A56: 53 | B56: =IF(Masters!$I$55="","",Masters!$I$55) | C56: =IF(B56="",0,Masters!$J$55) | D56: =SUMIF(Daily_Sales!$D:$D,B56,Daily_Sales!$G:$G) | E56: =SUMIF(Daily_Sales!$D:$D,B56,Daily_Sales!$H:$H) | F56: =IF(B56="","",D56-E56+C56) | G56: =SUMIFS(Cash_Book!$I:$I,Cash_Book!$C:$C,"DUKANDAR",Cash_Book!$D:$D,"RECEIPT",Cash_Book!$E:$E,B56)+SUMIFS(Cash_Book!$J:$J,Cash_Book!$C:$C,"DUKANDAR",Cash_Book!$D:$D,"RECEIPT",Cash_Book!$E:$E,B56) | H56: =IF(B56="","",F56-G56)
A57: 54 | B57: =IF(Masters!$I$56="","",Masters!$I$56) | C57: =IF(B57="",0,Masters!$J$56) | D57: =SUMIF(Daily_Sales!$D:$D,B57,Daily_Sales!$G:$G) | E57: =SUMIF(Daily_Sales!$D:$D,B57,Daily_Sales!$H:$H) | F57: =IF(B57="","",D57-E57+C57) | G57: =SUMIFS(Cash_Book!$I:$I,Cash_Book!$C:$C,"DUKANDAR",Cash_Book!$D:$D,"RECEIPT",Cash_Book!$E:$E,B57)+SUMIFS(Cash_Book!$J:$J,Cash_Book!$C:$C,"DUKANDAR",Cash_Book!$D:$D,"RECEIPT",Cash_Book!$E:$E,B57) | H57: =IF(B57="","",F57-G57)
A58: 55 | B58: =IF(Masters!$I$57="","",Masters!$I$57) | C58: =IF(B58="",0,Masters!$J$57) | D58: =SUMIF(Daily_Sales!$D:$D,B58,Daily_Sales!$G:$G) | E58: =SUMIF(Daily_Sales!$D:$D,B58,Daily_Sales!$H:$H) | F58: =IF(B58="","",D58-E58+C58) | G58: =SUMIFS(Cash_Book!$I:$I,Cash_Book!$C:$C,"DUKANDAR",Cash_Book!$D:$D,"RECEIPT",Cash_Book!$E:$E,B58)+SUMIFS(Cash_Book!$J:$J,Cash_Book!$C:$C,"DUKANDAR",Cash_Book!$D:$D,"RECEIPT",Cash_Book!$E:$E,B58) | H58: =IF(B58="","",F58-G58)
A59: 56 | B59: =IF(Masters!$I$58="","",Masters!$I$58) | C59: =IF(B59="",0,Masters!$J$58) | D59: =SUMIF(Daily_Sales!$D:$D,B59,Daily_Sales!$G:$G) | E59: =SUMIF(Daily_Sales!$D:$D,B59,Daily_Sales!$H:$H) | F59: =IF(B59="","",D59-E59+C59) | G59: =SUMIFS(Cash_Book!$I:$I,Cash_Book!$C:$C,"DUKANDAR",Cash_Book!$D:$D,"RECEIPT",Cash_Book!$E:$E,B59)+SUMIFS(Cash_Book!$J:$J,Cash_Book!$C:$C,"DUKANDAR",Cash_Book!$D:$D,"RECEIPT",Cash_Book!$E:$E,B59) | H59: =IF(B59="","",F59-G59)
A60: 57 | B60: =IF(Masters!$I$59="","",Masters!$I$59) | C60: =IF(B60="",0,Masters!$J$59) | D60: =SUMIF(Daily_Sales!$D:$D,B60,Daily_Sales!$G:$G) | E60: =SUMIF(Daily_Sales!$D:$D,B60,Daily_Sales!$H:$H) | F60: =IF(B60="","",D60-E60+C60) | G60: =SUMIFS(Cash_Book!$I:$I,Cash_Book!$C:$C,"DUKANDAR",Cash_Book!$D:$D,"RECEIPT",Cash_Book!$E:$E,B60)+SUMIFS(Cash_Book!$J:$J,Cash_Book!$C:$C,"DUKANDAR",Cash_Book!$D:$D,"RECEIPT",Cash_Book!$E:$E,B60) | H60: =IF(B60="","",F60-G60)
A61: 58 | B61: =IF(Masters!$I$60="","",Masters!$I$60) | C61: =IF(B61="",0,Masters!$J$60) | D61: =SUMIF(Daily_Sales!$D:$D,B61,Daily_Sales!$G:$G) | E61: =SUMIF(Daily_Sales!$D:$D,B61,Daily_Sales!$H:$H) | F61: =IF(B61="","",D61-E61+C61) | G61: =SUMIFS(Cash_Book!$I:$I,Cash_Book!$C:$C,"DUKANDAR",Cash_Book!$D:$D,"RECEIPT",Cash_Book!$E:$E,B61)+SUMIFS(Cash_Book!$J:$J,Cash_Book!$C:$C,"DUKANDAR",Cash_Book!$D:$D,"RECEIPT",Cash_Book!$E:$E,B61) | H61: =IF(B61="","",F61-G61)
A62: 59 | B62: =IF(Masters!$I$61="","",Masters!$I$61) | C62: =IF(B62="",0,Masters!$J$61) | D62: =SUMIF(Daily_Sales!$D:$D,B62,Daily_Sales!$G:$G) | E62: =SUMIF(Daily_Sales!$D:$D,B62,Daily_Sales!$H:$H) | F62: =IF(B62="","",D62-E62+C62) | G62: =SUMIFS(Cash_Book!$I:$I,Cash_Book!$C:$C,"DUKANDAR",Cash_Book!$D:$D,"RECEIPT",Cash_Book!$E:$E,B62)+SUMIFS(Cash_Book!$J:$J,Cash_Book!$C:$C,"DUKANDAR",Cash_Book!$D:$D,"RECEIPT",Cash_Book!$E:$E,B62) | H62: =IF(B62="","",F62-G62)
A63: 60 | B63: =IF(Masters!$I$62="","",Masters!$I$62) | C63: =IF(B63="",0,Masters!$J$62) | D63: =SUMIF(Daily_Sales!$D:$D,B63,Daily_Sales!$G:$G) | E63: =SUMIF(Daily_Sales!$D:$D,B63,Daily_Sales!$H:$H) | F63: =IF(B63="","",D63-E63+C63) | G63: =SUMIFS(Cash_Book!$I:$I,Cash_Book!$C:$C,"DUKANDAR",Cash_Book!$D:$D,"RECEIPT",Cash_Book!$E:$E,B63)+SUMIFS(Cash_Book!$J:$J,Cash_Book!$C:$C,"DUKANDAR",Cash_Book!$D:$D,"RECEIPT",Cash_Book!$E:$E,B63) | H63: =IF(B63="","",F63-G63)
A64: 61 | B64: =IF(Masters!$I$63="","",Masters!$I$63) | C64: =IF(B64="",0,Masters!$J$63) | D64: =SUMIF(Daily_Sales!$D:$D,B64,Daily_Sales!$G:$G) | E64: =SUMIF(Daily_Sales!$D:$D,B64,Daily_Sales!$H:$H) | F64: =IF(B64="","",D64-E64+C64) | G64: =SUMIFS(Cash_Book!$I:$I,Cash_Book!$C:$C,"DUKANDAR",Cash_Book!$D:$D,"RECEIPT",Cash_Book!$E:$E,B64)+SUMIFS(Cash_Book!$J:$J,Cash_Book!$C:$C,"DUKANDAR",Cash_Book!$D:$D,"RECEIPT",Cash_Book!$E:$E,B64) | H64: =IF(B64="","",F64-G64)
A65: 62 | B65: =IF(Masters!$I$64="","",Masters!$I$64) | C65: =IF(B65="",0,Masters!$J$64) | D65: =SUMIF(Daily_Sales!$D:$D,B65,Daily_Sales!$G:$G) | E65: =SUMIF(Daily_Sales!$D:$D,B65,Daily_Sales!$H:$H) | F65: =IF(B65="","",D65-E65+C65) | G65: =SUMIFS(Cash_Book!$I:$I,Cash_Book!$C:$C,"DUKANDAR",Cash_Book!$D:$D,"RECEIPT",Cash_Book!$E:$E,B65)+SUMIFS(Cash_Book!$J:$J,Cash_Book!$C:$C,"DUKANDAR",Cash_Book!$D:$D,"RECEIPT",Cash_Book!$E:$E,B65) | H65: =IF(B65="","",F65-G65)
A66: 63 | B66: =IF(Masters!$I$65="","",Masters!$I$65) | C66: =IF(B66="",0,Masters!$J$65) | D66: =SUMIF(Daily_Sales!$D:$D,B66,Daily_Sales!$G:$G) | E66: =SUMIF(Daily_Sales!$D:$D,B66,Daily_Sales!$H:$H) | F66: =IF(B66="","",D66-E66+C66) | G66: =SUMIFS(Cash_Book!$I:$I,Cash_Book!$C:$C,"DUKANDAR",Cash_Book!$D:$D,"RECEIPT",Cash_Book!$E:$E,B66)+SUMIFS(Cash_Book!$J:$J,Cash_Book!$C:$C,"DUKANDAR",Cash_Book!$D:$D,"RECEIPT",Cash_Book!$E:$E,B66) | H66: =IF(B66="","",F66-G66)
A67: 64 | B67: =IF(Masters!$I$66="","",Masters!$I$66) | C67: =IF(B67="",0,Masters!$J$66) | D67: =SUMIF(Daily_Sales!$D:$D,B67,Daily_Sales!$G:$G) | E67: =SUMIF(Daily_Sales!$D:$D,B67,Daily_Sales!$H:$H) | F67: =IF(B67="","",D67-E67+C67) | G67: =SUMIFS(Cash_Book!$I:$I,Cash_Book!$C:$C,"DUKANDAR",Cash_Book!$D:$D,"RECEIPT",Cash_Book!$E:$E,B67)+SUMIFS(Cash_Book!$J:$J,Cash_Book!$C:$C,"DUKANDAR",Cash_Book!$D:$D,"RECEIPT",Cash_Book!$E:$E,B67) | H67: =IF(B67="","",F67-G67)
A68: 65 | B68: =IF(Masters!$I$67="","",Masters!$I$67) | C68: =IF(B68="",0,Masters!$J$67) | D68: =SUMIF(Daily_Sales!$D:$D,B68,Daily_Sales!$G:$G) | E68: =SUMIF(Daily_Sales!$D:$D,B68,Daily_Sales!$H:$H) | F68: =IF(B68="","",D68-E68+C68) | G68: =SUMIFS(Cash_Book!$I:$I,Cash_Book!$C:$C,"DUKANDAR",Cash_Book!$D:$D,"RECEIPT",Cash_Book!$E:$E,B68)+SUMIFS(Cash_Book!$J:$J,Cash_Book!$C:$C,"DUKANDAR",Cash_Book!$D:$D,"RECEIPT",Cash_Book!$E:$E,B68) | H68: =IF(B68="","",F68-G68)
A69: 66 | B69: =IF(Masters!$I$68="","",Masters!$I$68) | C69: =IF(B69="",0,Masters!$J$68) | D69: =SUMIF(Daily_Sales!$D:$D,B69,Daily_Sales!$G:$G) | E69: =SUMIF(Daily_Sales!$D:$D,B69,Daily_Sales!$H:$H) | F69: =IF(B69="","",D69-E69+C69) | G69: =SUMIFS(Cash_Book!$I:$I,Cash_Book!$C:$C,"DUKANDAR",Cash_Book!$D:$D,"RECEIPT",Cash_Book!$E:$E,B69)+SUMIFS(Cash_Book!$J:$J,Cash_Book!$C:$C,"DUKANDAR",Cash_Book!$D:$D,"RECEIPT",Cash_Book!$E:$E,B69) | H69: =IF(B69="","",F69-G69)
A70: 67 | B70: =IF(Masters!$I$69="","",Masters!$I$69) | C70: =IF(B70="",0,Masters!$J$69) | D70: =SUMIF(Daily_Sales!$D:$D,B70,Daily_Sales!$G:$G) | E70: =SUMIF(Daily_Sales!$D:$D,B70,Daily_Sales!$H:$H) | F70: =IF(B70="","",D70-E70+C70) | G70: =SUMIFS(Cash_Book!$I:$I,Cash_Book!$C:$C,"DUKANDAR",Cash_Book!$D:$D,"RECEIPT",Cash_Book!$E:$E,B70)+SUMIFS(Cash_Book!$J:$J,Cash_Book!$C:$C,"DUKANDAR",Cash_Book!$D:$D,"RECEIPT",Cash_Book!$E:$E,B70) | H70: =IF(B70="","",F70-G70)
A71: 68 | B71: =IF(Masters!$I$70="","",Masters!$I$70) | C71: =IF(B71="",0,Masters!$J$70) | D71: =SUMIF(Daily_Sales!$D:$D,B71,Daily_Sales!$G:$G) | E71: =SUMIF(Daily_Sales!$D:$D,B71,Daily_Sales!$H:$H) | F71: =IF(B71="","",D71-E71+C71) | G71: =SUMIFS(Cash_Book!$I:$I,Cash_Book!$C:$C,"DUKANDAR",Cash_Book!$D:$D,"RECEIPT",Cash_Book!$E:$E,B71)+SUMIFS(Cash_Book!$J:$J,Cash_Book!$C:$C,"DUKANDAR",Cash_Book!$D:$D,"RECEIPT",Cash_Book!$E:$E,B71) | H71: =IF(B71="","",F71-G71)
A72: 69 | B72: =IF(Masters!$I$71="","",Masters!$I$71) | C72: =IF(B72="",0,Masters!$J$71) | D72: =SUMIF(Daily_Sales!$D:$D,B72,Daily_Sales!$G:$G) | E72: =SUMIF(Daily_Sales!$D:$D,B72,Daily_Sales!$H:$H) | F72: =IF(B72="","",D72-E72+C72) | G72: =SUMIFS(Cash_Book!$I:$I,Cash_Book!$C:$C,"DUKANDAR",Cash_Book!$D:$D,"RECEIPT",Cash_Book!$E:$E,B72)+SUMIFS(Cash_Book!$J:$J,Cash_Book!$C:$C,"DUKANDAR",Cash_Book!$D:$D,"RECEIPT",Cash_Book!$E:$E,B72) | H72: =IF(B72="","",F72-G72)
A73: 70 | B73: =IF(Masters!$I$72="","",Masters!$I$72) | C73: =IF(B73="",0,Masters!$J$72) | D73: =SUMIF(Daily_Sales!$D:$D,B73,Daily_Sales!$G:$G) | E73: =SUMIF(Daily_Sales!$D:$D,B73,Daily_Sales!$H:$H) | F73: =IF(B73="","",D73-E73+C73) | G73: =SUMIFS(Cash_Book!$I:$I,Cash_Book!$C:$C,"DUKANDAR",Cash_Book!$D:$D,"RECEIPT",Cash_Book!$E:$E,B73)+SUMIFS(Cash_Book!$J:$J,Cash_Book!$C:$C,"DUKANDAR",Cash_Book!$D:$D,"RECEIPT",Cash_Book!$E:$E,B73) | H73: =IF(B73="","",F73-G73)
A74: 71 | B74: =IF(Masters!$I$73="","",Masters!$I$73) | C74: =IF(B74="",0,Masters!$J$73) | D74: =SUMIF(Daily_Sales!$D:$D,B74,Daily_Sales!$G:$G) | E74: =SUMIF(Daily_Sales!$D:$D,B74,Daily_Sales!$H:$H) | F74: =IF(B74="","",D74-E74+C74) | G74: =SUMIFS(Cash_Book!$I:$I,Cash_Book!$C:$C,"DUKANDAR",Cash_Book!$D:$D,"RECEIPT",Cash_Book!$E:$E,B74)+SUMIFS(Cash_Book!$J:$J,Cash_Book!$C:$C,"DUKANDAR",Cash_Book!$D:$D,"RECEIPT",Cash_Book!$E:$E,B74) | H74: =IF(B74="","",F74-G74)
A75: 72 | B75: =IF(Masters!$I$74="","",Masters!$I$74) | C75: =IF(B75="",0,Masters!$J$74) | D75: =SUMIF(Daily_Sales!$D:$D,B75,Daily_Sales!$G:$G) | E75: =SUMIF(Daily_Sales!$D:$D,B75,Daily_Sales!$H:$H) | F75: =IF(B75="","",D75-E75+C75) | G75: =SUMIFS(Cash_Book!$I:$I,Cash_Book!$C:$C,"DUKANDAR",Cash_Book!$D:$D,"RECEIPT",Cash_Book!$E:$E,B75)+SUMIFS(Cash_Book!$J:$J,Cash_Book!$C:$C,"DUKANDAR",Cash_Book!$D:$D,"RECEIPT",Cash_Book!$E:$E,B75) | H75: =IF(B75="","",F75-G75)
A76: 73 | B76: =IF(Masters!$I$75="","",Masters!$I$75) | C76: =IF(B76="",0,Masters!$J$75) | D76: =SUMIF(Daily_Sales!$D:$D,B76,Daily_Sales!$G:$G) | E76: =SUMIF(Daily_Sales!$D:$D,B76,Daily_Sales!$H:$H) | F76: =IF(B76="","",D76-E76+C76) | G76: =SUMIFS(Cash_Book!$I:$I,Cash_Book!$C:$C,"DUKANDAR",Cash_Book!$D:$D,"RECEIPT",Cash_Book!$E:$E,B76)+SUMIFS(Cash_Book!$J:$J,Cash_Book!$C:$C,"DUKANDAR",Cash_Book!$D:$D,"RECEIPT",Cash_Book!$E:$E,B76) | H76: =IF(B76="","",F76-G76)
A77: 74 | B77: =IF(Masters!$I$76="","",Masters!$I$76) | C77: =IF(B77="",0,Masters!$J$76) | D77: =SUMIF(Daily_Sales!$D:$D,B77,Daily_Sales!$G:$G) | E77: =SUMIF(Daily_Sales!$D:$D,B77,Daily_Sales!$H:$H) | F77: =IF(B77="","",D77-E77+C77) | G77: =SUMIFS(Cash_Book!$I:$I,Cash_Book!$C:$C,"DUKANDAR",Cash_Book!$D:$D,"RECEIPT",Cash_Book!$E:$E,B77)+SUMIFS(Cash_Book!$J:$J,Cash_Book!$C:$C,"DUKANDAR",Cash_Book!$D:$D,"RECEIPT",Cash_Book!$E:$E,B77) | H77: =IF(B77="","",F77-G77)
A78: 75 | B78: =IF(Masters!$I$77="","",Masters!$I$77) | C78: =IF(B78="",0,Masters!$J$77) | D78: =SUMIF(Daily_Sales!$D:$D,B78,Daily_Sales!$G:$G) | E78: =SUMIF(Daily_Sales!$D:$D,B78,Daily_Sales!$H:$H) | F78: =IF(B78="","",D78-E78+C78) | G78: =SUMIFS(Cash_Book!$I:$I,Cash_Book!$C:$C,"DUKANDAR",Cash_Book!$D:$D,"RECEIPT",Cash_Book!$E:$E,B78)+SUMIFS(Cash_Book!$J:$J,Cash_Book!$C:$C,"DUKANDAR",Cash_Book!$D:$D,"RECEIPT",Cash_Book!$E:$E,B78) | H78: =IF(B78="","",F78-G78)
A79: 76 | B79: =IF(Masters!$I$78="","",Masters!$I$78) | C79: =IF(B79="",0,Masters!$J$78) | D79: =SUMIF(Daily_Sales!$D:$D,B79,Daily_Sales!$G:$G) | E79: =SUMIF(Daily_Sales!$D:$D,B79,Daily_Sales!$H:$H) | F79: =IF(B79="","",D79-E79+C79) | G79: =SUMIFS(Cash_Book!$I:$I,Cash_Book!$C:$C,"DUKANDAR",Cash_Book!$D:$D,"RECEIPT",Cash_Book!$E:$E,B79)+SUMIFS(Cash_Book!$J:$J,Cash_Book!$C:$C,"DUKANDAR",Cash_Book!$D:$D,"RECEIPT",Cash_Book!$E:$E,B79) | H79: =IF(B79="","",F79-G79)
A80: 77 | B80: =IF(Masters!$I$79="","",Masters!$I$79) | C80: =IF(B80="",0,Masters!$J$79) | D80: =SUMIF(Daily_Sales!$D:$D,B80,Daily_Sales!$G:$G) | E80: =SUMIF(Daily_Sales!$D:$D,B80,Daily_Sales!$H:$H) | F80: =IF(B80="","",D80-E80+C80) | G80: =SUMIFS(Cash_Book!$I:$I,Cash_Book!$C:$C,"DUKANDAR",Cash_Book!$D:$D,"RECEIPT",Cash_Book!$E:$E,B80)+SUMIFS(Cash_Book!$J:$J,Cash_Book!$C:$C,"DUKANDAR",Cash_Book!$D:$D,"RECEIPT",Cash_Book!$E:$E,B80) | H80: =IF(B80="","",F80-G80)
A81: TOTAL | B81: PATTI (Total O/S) | C81: =SUM(C4:C80) | D81: =SUM(D4:D80) | E81: =SUM(E4:E80) | F81: =SUM(F4:F80) | G81: =SUM(G4:G80) | H81: =SUM(H4:H80)

Sheet Bepaari_Aakda
A1: BEPAARI SETTLEMENT SLIP (AAKDA)
A3: SELECT BEPAARI:
A4: DATE:
A7: A. SALES
A8: Qty Sold | B8: =SUMIF(Daily_Sales!$C:$C,$B$3,Daily_Sales!$E:$E)
A9: Gross Sales | B9: =SUMIF(Daily_Sales!$C:$C,$B$3,Daily_Sales!$G:$G)
A11: B. DEDUCTIONS
A12: Commission % | B12: =IFERROR(INDEX(Masters!$C:$C,MATCH($B$3,Masters!$B:$B,0)),4)
A13: Commission Amt | B13: =B9*B12/100
A14: KK (Fixed) | B14: =IF(B8>0,Masters!$X$3,0)
A15: JB (₹10/goat) | B15: =B8*Masters!$X$4
A16: Motor | B16: =SUMIFS(Cash_Book!$G:$G,Cash_Book!$C:$C,"BEPAARI",Cash_Book!$D:$D,"MOTOR",Cash_Book!$E:$E,$B$3)+SUMIFS(Cash_Book!$H:$H,Cash_Book!$C:$C,"BEPAARI",Cash_Book!$D:$D,"MOTOR",Cash_Book!$E:$E,$B$3)
A17: Bhussa | B17: =SUMIFS(Cash_Book!$G:$G,Cash_Book!$C:$C,"BEPAARI",Cash_Book!$D:$D,"BHUSSA",Cash_Book!$E:$E,$B$3)+SUMIFS(Cash_Book!$H:$H,Cash_Book!$C:$C,"BEPAARI",Cash_Book!$D:$D,"BHUSSA",Cash_Book!$E:$E,$B$3)
A18: Gawali | B18: =SUMIFS(Cash_Book!$G:$G,Cash_Book!$C:$C,"BEPAARI",Cash_Book!$D:$D,"GAWALI",Cash_Book!$E:$E,$B$3)+SUMIFS(Cash_Book!$H:$H,Cash_Book!$C:$C,"BEPAARI",Cash_Book!$D:$D,"GAWALI",Cash_Book!$E:$E,$B$3)
A19: Cash/Advance | B19: =SUMIFS(Cash_Book!$G:$G,Cash_Book!$C:$C,"BEPAARI",Cash_Book!$D:$D,"CASH_ADV",Cash_Book!$E:$E,$B$3)+SUMIFS(Cash_Book!$H:$H,Cash_Book!$C:$C,"BEPAARI",Cash_Book!$D:$D,"CASH_ADV",Cash_Book!$E:$E,$B$3)
A20: TOTAL DEDUCTIONS | B20: =SUM(B13:B19)
A22: C. CALCULATION
A23: Gross Sales | B23: =B9
A24: (-) Deductions | B24: =B20
A25: (+) Opening Bal | B25: =IFERROR(INDEX(Masters!$D:$D,MATCH($B$3,Masters!$B:$B,0)),0)
A26: NET PAYABLE | B26: =B23-B24+B25
A28: D. PAYMENTS
A29: Payments Made | B29: =SUMIFS(Cash_Book!$G:$G,Cash_Book!$C:$C,"BEPAARI",Cash_Book!$D:$D,"PAYMENT",Cash_Book!$E:$E,$B$3)+SUMIFS(Cash_Book!$H:$H,Cash_Book!$C:$C,"BEPAARI",Cash_Book!$D:$D,"PAYMENT",Cash_Book!$E:$E,$B$3)
A31: BALANCE DUE | B31: =B26-B29

Sheet Balance_Sheet
A1: BALANCE SHEET | E1: LIABILITIES = ASSETS
A3: LIABILITIES (We Owe) | D3: ASSETS (We Have / Owed to Us)
A4: Particulars | B4: Amount | D4: Particulars | E4: Amount
A5: CAPITAL: | D5: CASH BALANCE: | E5: =Cash_Book!L8
A6: Opening + Received | B6: =SUM(Masters!$P$3:$P$24)+SUMIFS(Cash_Book!$I:$I,Cash_Book!$C:$C,"CAPITAL",Cash_Book!$D:$D,"TAKEN")+SUMIFS(Cash_Book!$J:$J,Cash_Book!$C:$C,"CAPITAL",Cash_Book!$D:$D,"TAKEN")-SUMIFS(Cash_Book!$G:$G,Cash_Book!$C:$C,"CAPITAL",Cash_Book!$D:$D,"WITHDRAWN")-SUMIFS(Cash_Book!$H:$H,Cash_Book!$C:$C,"CAPITAL",Cash_Book!$D:$D,"WITHDRAWN")
D7: BANK BALANCE: | E7: =Cash_Book!L9
A8: LOANS/AMANAT:
A9: Taken - Repaid | B9: =SUMIFS(Cash_Book!$I:$I,Cash_Book!$C:$C,"LOAN",Cash_Book!$D:$D,"TAKEN")+SUMIFS(Cash_Book!$J:$J,Cash_Book!$C:$C,"LOAN",Cash_Book!$D:$D,"TAKEN")-SUMIFS(Cash_Book!$G:$G,Cash_Book!$C:$C,"LOAN",Cash_Book!$D:$D,"REPAID")-SUMIFS(Cash_Book!$H:$H,Cash_Book!$C:$C,"LOAN",Cash_Book!$D:$D,"REPAID") | D9: PATTI (Dukandar O/S):
D10: From Ledger | E10: =Dukandar_Ledger!H81
A11: BEPAARI PAYABLES:
A12: From Ledger | B12: =Bepaari_Ledger!R82 | D12: ADVANCES GIVEN:
D13: Given - Received | E13: =SUMIFS(Cash_Book!$G:$G,Cash_Book!$C:$C,"ADVANCE",Cash_Book!$D:$D,"GIVEN")+SUMIFS(Cash_Book!$H:$H,Cash_Book!$C:$C,"ADVANCE",Cash_Book!$D:$D,"GIVEN")-SUMIFS(Cash_Book!$I:$I,Cash_Book!$C:$C,"ADVANCE",Cash_Book!$D:$D,"RECEIVED")-SUMIFS(Cash_Book!$J:$J,Cash_Book!$C:$C,"ADVANCE",Cash_Book!$D:$D,"RECEIVED")
A14: COMMISSION (Net):
A15: Gross - Discounts | B15: =Bepaari_Ledger!G82-Dukandar_Ledger!E81 | D15: EXPENSES:
D16: Mandi/Business | E16: =SUMIFS(Cash_Book!$G:$G,Cash_Book!$C:$C,"EXPENSE",Cash_Book!$D:$D,"MANDI")+SUMIFS(Cash_Book!$H:$H,Cash_Book!$C:$C,"EXPENSE",Cash_Book!$D:$D,"MANDI")+SUMIFS(Cash_Book!$G:$G,Cash_Book!$C:$C,"EXPENSE",Cash_Book!$D:$D,"TRAVEL")+SUMIFS(Cash_Book!$H:$H,Cash_Book!$C:$C,"EXPENSE",Cash_Book!$D:$D,"TRAVEL")+SUMIFS(Cash_Book!$G:$G,Cash_Book!$C:$C,"EXPENSE",Cash_Book!$D:$D,"FOOD")+SUMIFS(Cash_Book!$H:$H,Cash_Book!$C:$C,"EXPENSE",Cash_Book!$D:$D,"FOOD")+SUMIFS(Cash_Book!$G:$G,Cash_Book!$C:$C,"EXPENSE",Cash_Book!$D:$D,"SALARY")+SUMIFS(Cash_Book!$H:$H,Cash_Book!$C:$C,"EXPENSE",Cash_Book!$D:$D,"SALARY")+SUMIFS(Cash_Book!$G:$G,Cash_Book!$C:$C,"EXPENSE",Cash_Book!$D:$D,"OTHER")+SUMIFS(Cash_Book!$H:$H,Cash_Book!$C:$C,"EXPENSE",Cash_Book!$D:$D,"OTHER")
A17: JB COLLECTED: | B17: =Bepaari_Ledger!I82 | D17: BF Discount (Expense) | E17: =SUMIFS(Cash_Book!$G:$G,Cash_Book!$C:$C,"EXPENSE",Cash_Book!$D:$D,"BF_DISC")+SUMIFS(Cash_Book!$H:$H,Cash_Book!$C:$C,"EXPENSE",Cash_Book!$D:$D,"BF_DISC")
A18: KK COLLECTED: | B18: =Bepaari_Ledger!H82 | D18: JB Paid to Market | E18: =SUMIFS(Cash_Book!$G:$G,Cash_Book!$C:$C,"EXPENSE",Cash_Book!$D:$D,"JB_PAID")+SUMIFS(Cash_Book!$H:$H,Cash_Book!$C:$C,"EXPENSE",Cash_Book!$D:$D,"JB_PAID")
A20: ZAKAT PAYABLE:
A21: Opening + Provision - Paid | B21: =Masters!$X$9+SUMIFS(Cash_Book!$I:$I,Cash_Book!$C:$C,"ZAKAT",Cash_Book!$D:$D,"PROVISION")+SUMIFS(Cash_Book!$J:$J,Cash_Book!$C:$C,"ZAKAT",Cash_Book!$D:$D,"PROVISION")-SUMIFS(Cash_Book!$G:$G,Cash_Book!$C:$C,"ZAKAT",Cash_Book!$D:$D,"PAID")-SUMIFS(Cash_Book!$H:$H,Cash_Book!$C:$C,"ZAKAT",Cash_Book!$D:$D,"PAID")
A23: TOTAL LIABILITIES | B23: =B6+B9+B12+B15+B17+B18+B21 | D23: TOTAL ASSETS | E23: =E5+E7+E10+E13+E16+E17+E18
A25: DIFFERENCE (Should be 0) | B25: =B23-E23

Sheet Commission_Summary
A1: COMMISSION & PROFIT SUMMARY
A3: GROSS SALES | B3: =Bepaari_Ledger!E82
A4: TOTAL GOATS SOLD | B4: =Bepaari_Ledger!F82
A6: INCOME:
A7: Commission Earned | B7: =Bepaari_Ledger!G82
A8: (-) Discounts Given | B8: =-Dukandar_Ledger!E81
A9: Net Commission | B9: =B6+B7
A10: JB Collected | B10: =Bepaari_Ledger!I82
A11: KK Collected | B11: =Bepaari_Ledger!H82
A12: TOTAL INCOME | B12: =B8+B9+B10
A14: EXPENSES:
A15: Mandi/Business | B15: =SUMIFS(Cash_Book!$G:$G,Cash_Book!$C:$C,"EXPENSE",Cash_Book!$D:$D,"MANDI")+SUMIFS(Cash_Book!$H:$H,Cash_Book!$C:$C,"EXPENSE",Cash_Book!$D:$D,"MANDI")+SUMIFS(Cash_Book!$G:$G,Cash_Book!$C:$C,"EXPENSE",Cash_Book!$D:$D,"TRAVEL")+SUMIFS(Cash_Book!$H:$H,Cash_Book!$C:$C,"EXPENSE",Cash_Book!$D:$D,"TRAVEL")+SUMIFS(Cash_Book!$G:$G,Cash_Book!$C:$C,"EXPENSE",Cash_Book!$D:$D,"FOOD")+SUMIFS(Cash_Book!$H:$H,Cash_Book!$C:$C,"EXPENSE",Cash_Book!$D:$D,"FOOD")+SUMIFS(Cash_Book!$G:$G,Cash_Book!$C:$C,"EXPENSE",Cash_Book!$D:$D,"SALARY")+SUMIFS(Cash_Book!$H:$H,Cash_Book!$C:$C,"EXPENSE",Cash_Book!$D:$D,"SALARY")+SUMIFS(Cash_Book!$G:$G,Cash_Book!$C:$C,"EXPENSE",Cash_Book!$D:$D,"OTHER")+SUMIFS(Cash_Book!$H:$H,Cash_Book!$C:$C,"EXPENSE",Cash_Book!$D:$D,"OTHER")
A16: BF Discount (Expense) | B16: =SUMIFS(Cash_Book!$G:$G,Cash_Book!$C:$C,"EXPENSE",Cash_Book!$D:$D,"BF_DISC")+SUMIFS(Cash_Book!$H:$H,Cash_Book!$C:$C,"EXPENSE",Cash_Book!$D:$D,"BF_DISC")
A17: JB Paid to Market | B17: =SUMIFS(Cash_Book!$G:$G,Cash_Book!$C:$C,"EXPENSE",Cash_Book!$D:$D,"JB_PAID")+SUMIFS(Cash_Book!$H:$H,Cash_Book!$C:$C,"EXPENSE",Cash_Book!$D:$D,"JB_PAID")
A18: TOTAL EXPENSES | B18: =B14+B15+B16
A20: NET PROFIT/LOSS | B20: =B11-B17
