Workbook

Sheet Instructions
A1: MANDI MASTER - Commission Agent Accounting System
A3: HOW TO USE THIS WORKBOOK:
A5: STEP 1: Setup Masters (One-time)
A6: → Go to 'Masters' sheet
A7: → Add all your Bepaari names with their commission type (% or Per Piece)
A8: → Add all your Dukandar names
A9: → Enter Opening Balances for existing parties
A11: STEP 2: Daily Entry (Each Mandi Day)
A12: → Go to 'Daily_Sales' sheet
A13: → Enter each sale: Date, Bepaari, Dukandar, Qty, Rate, Discount (if any)
A14: → Go to 'Bepaari_Expenses' sheet
A15: → Enter Bepaari expenses: Motor, Bhussa, Jagah Bhada, Gawali, Karkuni, Cash/Advance
... A33: Created: 18-Mar-2026

Sheet Masters
A1: BEPAARI MASTER | H1: DUKANDAR MASTER | M1: EXPENSE TYPES
A2: Sr. | B2: Bepaari Name | C2: Commission Type | D2: Commission Value | E2: Opening Balance | F2: Remarks | H2: Sr. | I2: Dukandar Name | J2: Opening Balance | K2: Remarks | M2: Sr. | N2: Expense Code | O2: Expense Name
A3: 1 | B3: ABUL HASAN | C3: % | D3: 4 | E3: 0 | F3: Sample - Delete or edit | H3: 1 | I3: IRFAN JOG | J3: 0 | K3: Sample | M3: 1 | N3: MOTOR | O3: Motor Bhada (Transport)
A4: 2 | B4: SHARAFAT | C4: % | D4: 4 | E4: 0 | H4: 2 | I4: SALIM | J4: 0 | M4: 2 | N4: BHUSSA | O4: Bhussa (Fodder)
A5: 3 | B5: JUNAID | C5: Per Piece | D5: 200 | E5: 0 | F5: ₹200 per goat | H5: 3 | I5: YUNUS | J5: 0 | M5: 3 | N5: JB | O5: Jagah Bhada (Space Rent)
A6: 4 | H6: 4 | M6: 4 | N6: GAWALI | O6: Gawali (Handlers)
A7: 5 | H7: 5 | M7: 5 | N7: KK | O7: Karkuni (Clerical)
A8: 6 | H8: 6 | M8: 6 | N8: CASH | O8: Cash Given / Advance
A9: 7 | H9: 7 | M9: 7 | N9: OTHER | O9: Other Expenses
A10: 8 | H10: 8
A11: 9 | H11: 9
A12: 10 | H12: 10
A13: 11 | H13: 11
A14: 12 | H14: 12
A15: 13 | H15: 13
A16: 14 | H16: 14
A17: 15 | H17: 15
A18: 16 | H18: 16
A19: 17 | H19: 17
A20: 18 | H20: 18
A21: 19 | H21: 19
... A51: 49 | H51: 49

Sheet Daily_Sales
A1: DAILY SALES ENTRY
A2: Sr. | B2: Date | C2: Bepaari Name | D2: Dukandar Name | E2: Qty (Goats) | F2: Rate (₹/Goat) | G2: Gross Total | H2: Dukandar Discount | I2: Net Amount | J2: Remarks
A3: 1 | G3: =IF(E3="","",E3*F3) | I3: =IF(G3="","",G3-IF(H3="",0,H3))
A4: 2 | G4: =IF(E4="","",E4*F4) | I4: =IF(G4="","",G4-IF(H4="",0,H4))
A5: 3 | G5: =IF(E5="","",E5*F5) | I5: =IF(G5="","",G5-IF(H5="",0,H5))
A6: 4 | G6: =IF(E6="","",E6*F6) | I6: =IF(G6="","",G6-IF(H6="",0,H6))
A7: 5 | G7: =IF(E7="","",E7*F7) | I7: =IF(G7="","",G7-IF(H7="",0,H7))
A8: 6 | G8: =IF(E8="","",E8*F8) | I8: =IF(G8="","",G8-IF(H8="",0,H8))
A9: 7 | G9: =IF(E9="","",E9*F9) | I9: =IF(G9="","",G9-IF(H9="",0,H9))
A10: 8 | G10: =IF(E10="","",E10*F10) | I10: =IF(G10="","",G10-IF(H10="",0,H10))
A11: 9 | G11: =IF(E11="","",E11*F11) | I11: =IF(G11="","",G11-IF(H11="",0,H11))
A12: 10 | G12: =IF(E12="","",E12*F12) | I12: =IF(G12="","",G12-IF(H12="",0,H12))
A13: 11 | G13: =IF(E13="","",E13*F13) | I13: =IF(G13="","",G13-IF(H13="",0,H13))
A14: 12 | G14: =IF(E14="","",E14*F14) | I14: =IF(G14="","",G14-IF(H14="",0,H14))
... A502: 500 | G502: =IF(E502="","",E502*F502) | I502: =IF(G502="","",G502-IF(H502="",0,H502))

Sheet Bepaari_Expenses
A1: BEPAARI EXPENSES ENTRY
A2: Sr. | B2: Date | C2: Bepaari Name | D2: Expense Type | E2: Amount (₹) | F2: Remarks
A3: 1
A4: 2
A5: 3
A6: 4
A7: 5
A8: 6
A9: 7
A10: 8
A11: 9
A12: 10
A13: 11
A14: 12
... A502: 500

Sheet Bepaari_Payments
A1: BEPAARI PAYMENTS (Money Paid to Bepaari)
A2: Sr. | B2: Date | C2: Bepaari Name | D2: Mode | E2: Amount (₹) | F2: Reference/Remarks
A3: 1
A4: 2
A5: 3
A6: 4
A7: 5
A8: 6
A9: 7
A10: 8
A11: 9
A12: 10
A13: 11
A14: 12
... A502: 500

Sheet Dukandar_Receipts
A1: DUKANDAR RECEIPTS (Money Received from Dukandar)
A2: Sr. | B2: Date | C2: Dukandar Name | D2: Mode | E2: Amount (₹) | F2: Reference/Remarks
A3: 1
A4: 2
A5: 3
A6: 4
A7: 5
A8: 6
A9: 7
A10: 8
A11: 9
A12: 10
A13: 11
A14: 12
... A502: 500

Sheet Bepaari_Ledger
A1: BEPAARI LEDGER SUMMARY
A2: (Auto-calculated from Daily_Sales, Bepaari_Expenses & Bepaari_Payments)
A4: Sr. | B4: Bepaari Name | C4: Comm. Type | D4: Comm. Value | E4: Opening Bal. | F4: Total Sales | G4: Total Qty | H4: Commission | I4: Total Expenses | J4: Gross Payable | K4: Payments Made | L4: Closing Balance
A5: 1 | B5: =IF(Masters!B3="","",Masters!B3) | C5: =IF(Masters!C3="","",Masters!C3) | D5: =IF(Masters!D3="","",Masters!D3) | E5: =IF(Masters!E3="",0,Masters!E3) | F5: =SUMIF(Daily_Sales!C:C,B5,Daily_Sales!G:G) | G5: =SUMIF(Daily_Sales!C:C,B5,Daily_Sales!E:E) | H5: =IF(B5="","",IF(C5="%",F5*D5/100,G5*D5)) | I5: =SUMIF(Bepaari_Expenses!C:C,B5,Bepaari_Expenses!E:E) | J5: =IF(B5="","",F5-H5-I5+E5) | K5: =SUMIF(Bepaari_Payments!C:C,B5,Bepaari_Payments!E:E) | L5: =IF(B5="","",J5-K5)
A6: 2 | B6: =IF(Masters!B4="","",Masters!B4) | C6: =IF(Masters!C4="","",Masters!C4) | D6: =IF(Masters!D4="","",Masters!D4) | E6: =IF(Masters!E4="",0,Masters!E4) | F6: =SUMIF(Daily_Sales!C:C,B6,Daily_Sales!G:G) | G6: =SUMIF(Daily_Sales!C:C,B6,Daily_Sales!E:E) | H6: =IF(B6="","",IF(C6="%",F6*D6/100,G6*D6)) | I6: =SUMIF(Bepaari_Expenses!C:C,B6,Bepaari_Expenses!E:E) | J6: =IF(B6="","",F6-H6-I6+E6) | K6: =SUMIF(Bepaari_Payments!C:C,B6,Bepaari_Payments!E:E) | L6: =IF(B6="","",J6-K6)
A7: 3 | B7: =IF(Masters!B5="","",Masters!B5) | C7: =IF(Masters!C5="","",Masters!C5) | D7: =IF(Masters!D5="","",Masters!D5) | E7: =IF(Masters!E5="",0,Masters!E5) | F7: =SUMIF(Daily_Sales!C:C,B7,Daily_Sales!G:G) | G7: =SUMIF(Daily_Sales!C:C,B7,Daily_Sales!E:E) | H7: =IF(B7="","",IF(C7="%",F7*D7/100,G7*D7)) | I7: =SUMIF(Bepaari_Expenses!C:C,B7,Bepaari_Expenses!E:E) | J7: =IF(B7="","",F7-H7-I7+E7) | K7: =SUMIF(Bepaari_Payments!C:C,B7,Bepaari_Payments!E:E) | L7: =IF(B7="","",J7-K7)
A8: 4 | B8: =IF(Masters!B6="","",Masters!B6) | C8: =IF(Masters!C6="","",Masters!C6) | D8: =IF(Masters!D6="","",Masters!D6) | E8: =IF(Masters!E6="",0,Masters!E6) | F8: =SUMIF(Daily_Sales!C:C,B8,Daily_Sales!G:G) | G8: =SUMIF(Daily_Sales!C:C,B8,Daily_Sales!E:E) | H8: =IF(B8="","",IF(C8="%",F8*D8/100,G8*D8)) | I8: =SUMIF(Bepaari_Expenses!C:C,B8,Bepaari_Expenses!E:E) | J8: =IF(B8="","",F8-H8-I8+E8) | K8: =SUMIF(Bepaari_Payments!C:C,B8,Bepaari_Payments!E:E) | L8: =IF(B8="","",J8-K8)
A9: 5 | B9: =IF(Masters!B7="","",Masters!B7) | C9: =IF(Masters!C7="","",Masters!C7) | D9: =IF(Masters!D7="","",Masters!D7) | E9: =IF(Masters!E7="",0,Masters!E7) | F9: =SUMIF(Daily_Sales!C:C,B9,Daily_Sales!G:G) | G9: =SUMIF(Daily_Sales!C:C,B9,Daily_Sales!E:E) | H9: =IF(B9="","",IF(C9="%",F9*D9/100,G9*D9)) | I9: =SUMIF(Bepaari_Expenses!C:C,B9,Bepaari_Expenses!E:E) | J9: =IF(B9="","",F9-H9-I9+E9) | K9: =SUMIF(Bepaari_Payments!C:C,B9,Bepaari_Payments!E:E) | L9: =IF(B9="","",J9-K9)
A10: 6 | B10: =IF(Masters!B8="","",Masters!B8) | C10: =IF(Masters!C8="","",Masters!C8) | D10: =IF(Masters!D8="","",Masters!D8) | E10: =IF(Masters!E8="",0,Masters!E8) | F10: =SUMIF(Daily_Sales!C:C,B10,Daily_Sales!G:G) | G10: =SUMIF(Daily_Sales!C:C,B10,Daily_Sales!E:E) | H10: =IF(B10="","",IF(C10="%",F10*D10/100,G10*D10)) | I10: =SUMIF(Bepaari_Expenses!C:C,B10,Bepaari_Expenses!E:E) | J10: =IF(B10="","",F10-H10-I10+E10) | K10: =SUMIF(Bepaari_Payments!C:C,B10,Bepaari_Payments!E:E) | L10: =IF(B10="","",J10-K10)
A11: 7 | B11: =IF(Masters!B9="","",Masters!B9) | C11: =IF(Masters!C9="","",Masters!C9) | D11: =IF(Masters!D9="","",Masters!D9) | E11: =IF(Masters!E9="",0,Masters!E9) | F11: =SUMIF(Daily_Sales!C:C,B11,Daily_Sales!G:G) | G11: =SUMIF(Daily_Sales!C:C,B11,Daily_Sales!E:E) | H11: =IF(B11="","",IF(C11="%",F11*D11/100,G11*D11)) | I11: =SUMIF(Bepaari_Expenses!C:C,B11,Bepaari_Expenses!E:E) | J11: =IF(B11="","",F11-H11-I11+E11) | K11: =SUMIF(Bepaari_Payments!C:C,B11,Bepaari_Payments!E:E) | L11: =IF(B11="","",J11-K11)
A12: 8 | B12: =IF(Masters!B10="","",Masters!B10) | C12: =IF(Masters!C10="","",Masters!C10) | D12: =IF(Masters!D10="","",Masters!D10) | E12: =IF(Masters!E10="",0,Masters!E10) | F12: =SUMIF(Daily_Sales!C:C,B12,Daily_Sales!G:G) | G12: =SUMIF(Daily_Sales!C:C,B12,Daily_Sales!E:E) | H12: =IF(B12="","",IF(C12="%",F12*D12/100,G12*D12)) | I12: =SUMIF(Bepaari_Expenses!C:C,B12,Bepaari_Expenses!E:E) | J12: =IF(B12="","",F12-H12-I12+E12) | K12: =SUMIF(Bepaari_Payments!C:C,B12,Bepaari_Payments!E:E) | L12: =IF(B12="","",J12-K12)
A13: 9 | B13: =IF(Masters!B11="","",Masters!B11) | C13: =IF(Masters!C11="","",Masters!C11) | D13: =IF(Masters!D11="","",Masters!D11) | E13: =IF(Masters!E11="",0,Masters!E11) | F13: =SUMIF(Daily_Sales!C:C,B13,Daily_Sales!G:G) | G13: =SUMIF(Daily_Sales!C:C,B13,Daily_Sales!E:E) | H13: =IF(B13="","",IF(C13="%",F13*D13/100,G13*D13)) | I13: =SUMIF(Bepaari_Expenses!C:C,B13,Bepaari_Expenses!E:E) | J13: =IF(B13="","",F13-H13-I13+E13) | K13: =SUMIF(Bepaari_Payments!C:C,B13,Bepaari_Payments!E:E) | L13: =IF(B13="","",J13-K13)
A14: 10 | B14: =IF(Masters!B12="","",Masters!B12) | C14: =IF(Masters!C12="","",Masters!C12) | D14: =IF(Masters!D12="","",Masters!D12) | E14: =IF(Masters!E12="",0,Masters!E12) | F14: =SUMIF(Daily_Sales!C:C,B14,Daily_Sales!G:G) | G14: =SUMIF(Daily_Sales!C:C,B14,Daily_Sales!E:E) | H14: =IF(B14="","",IF(C14="%",F14*D14/100,G14*D14)) | I14: =SUMIF(Bepaari_Expenses!C:C,B14,Bepaari_Expenses!E:E) | J14: =IF(B14="","",F14-H14-I14+E14) | K14: =SUMIF(Bepaari_Payments!C:C,B14,Bepaari_Payments!E:E) | L14: =IF(B14="","",J14-K14)
A15: 11 | B15: =IF(Masters!B13="","",Masters!B13) | C15: =IF(Masters!C13="","",Masters!C13) | D15: =IF(Masters!D13="","",Masters!D13) | E15: =IF(Masters!E13="",0,Masters!E13) | F15: =SUMIF(Daily_Sales!C:C,B15,Daily_Sales!G:G) | G15: =SUMIF(Daily_Sales!C:C,B15,Daily_Sales!E:E) | H15: =IF(B15="","",IF(C15="%",F15*D15/100,G15*D15)) | I15: =SUMIF(Bepaari_Expenses!C:C,B15,Bepaari_Expenses!E:E) | J15: =IF(B15="","",F15-H15-I15+E15) | K15: =SUMIF(Bepaari_Payments!C:C,B15,Bepaari_Payments!E:E) | L15: =IF(B15="","",J15-K15)
A16: 12 | B16: =IF(Masters!B14="","",Masters!B14) | C16: =IF(Masters!C14="","",Masters!C14) | D16: =IF(Masters!D14="","",Masters!D14) | E16: =IF(Masters!E14="",0,Masters!E14) | F16: =SUMIF(Daily_Sales!C:C,B16,Daily_Sales!G:G) | G16: =SUMIF(Daily_Sales!C:C,B16,Daily_Sales!E:E) | H16: =IF(B16="","",IF(C16="%",F16*D16/100,G16*D16)) | I16: =SUMIF(Bepaari_Expenses!C:C,B16,Bepaari_Expenses!E:E) | J16: =IF(B16="","",F16-H16-I16+E16) | K16: =SUMIF(Bepaari_Payments!C:C,B16,Bepaari_Payments!E:E) | L16: =IF(B16="","",J16-K16)
... A53: 49 | B53: =IF(Masters!B51="","",Masters!B51) | C53: =IF(Masters!C51="","",Masters!C51) | D53: =IF(Masters!D51="","",Masters!D51) | E53: =IF(Masters!E51="",0,Masters!E51) | F53: =SUMIF(Daily_Sales!C:C,B53,Daily_Sales!G:G) | G53: =SUMIF(Daily_Sales!C:C,B53,Daily_Sales!E:E) | H53: =IF(B53="","",IF(C53="%",F53*D53/100,G53*D53)) | I53: =SUMIF(Bepaari_Expenses!C:C,B53,Bepaari_Expenses!E:E) | J53: =IF(B53="","",F53-H53-I53+E53) | K53: =SUMIF(Bepaari_Payments!C:C,B53,Bepaari_Payments!E:E) | L53: =IF(B53="","",J53-K53)
A54: TOTAL | E54: =SUM(E5:E53) | F54: =SUM(F5:F53) | G54: =SUM(G5:G53) | H54: =SUM(H5:H53) | I54: =SUM(I5:I53) | J54: =SUM(J5:J53) | K54: =SUM(K5:K53) | L54: =SUM(L5:L53)

Sheet Dukandar_Ledger
A1: DUKANDAR LEDGER SUMMARY
A2: (Auto-calculated from Daily_Sales & Dukandar_Receipts)
A4: Sr. | B4: Dukandar Name | C4: Opening Bal. | D4: Total Purchases | E4: Total Discounts | F4: Net Receivable | G4: Receipts | H4: Closing Balance
A5: 1 | B5: =IF(Masters!I3="","",Masters!I3) | C5: =IF(Masters!J3="",0,Masters!J3) | D5: =SUMIF(Daily_Sales!D:D,B5,Daily_Sales!G:G) | E5: =SUMIF(Daily_Sales!D:D,B5,Daily_Sales!H:H) | F5: =IF(B5="","",D5-E5+C5) | G5: =SUMIF(Dukandar_Receipts!C:C,B5,Dukandar_Receipts!E:E) | H5: =IF(B5="","",F5-G5)
A6: 2 | B6: =IF(Masters!I4="","",Masters!I4) | C6: =IF(Masters!J4="",0,Masters!J4) | D6: =SUMIF(Daily_Sales!D:D,B6,Daily_Sales!G:G) | E6: =SUMIF(Daily_Sales!D:D,B6,Daily_Sales!H:H) | F6: =IF(B6="","",D6-E6+C6) | G6: =SUMIF(Dukandar_Receipts!C:C,B6,Dukandar_Receipts!E:E) | H6: =IF(B6="","",F6-G6)
A7: 3 | B7: =IF(Masters!I5="","",Masters!I5) | C7: =IF(Masters!J5="",0,Masters!J5) | D7: =SUMIF(Daily_Sales!D:D,B7,Daily_Sales!G:G) | E7: =SUMIF(Daily_Sales!D:D,B7,Daily_Sales!H:H) | F7: =IF(B7="","",D7-E7+C7) | G7: =SUMIF(Dukandar_Receipts!C:C,B7,Dukandar_Receipts!E:E) | H7: =IF(B7="","",F7-G7)
A8: 4 | B8: =IF(Masters!I6="","",Masters!I6) | C8: =IF(Masters!J6="",0,Masters!J6) | D8: =SUMIF(Daily_Sales!D:D,B8,Daily_Sales!G:G) | E8: =SUMIF(Daily_Sales!D:D,B8,Daily_Sales!H:H) | F8: =IF(B8="","",D8-E8+C8) | G8: =SUMIF(Dukandar_Receipts!C:C,B8,Dukandar_Receipts!E:E) | H8: =IF(B8="","",F8-G8)
A9: 5 | B9: =IF(Masters!I7="","",Masters!I7) | C9: =IF(Masters!J7="",0,Masters!J7) | D9: =SUMIF(Daily_Sales!D:D,B9,Daily_Sales!G:G) | E9: =SUMIF(Daily_Sales!D:D,B9,Daily_Sales!H:H) | F9: =IF(B9="","",D9-E9+C9) | G9: =SUMIF(Dukandar_Receipts!C:C,B9,Dukandar_Receipts!E:E) | H9: =IF(B9="","",F9-G9)
A10: 6 | B10: =IF(Masters!I8="","",Masters!I8) | C10: =IF(Masters!J8="",0,Masters!J8) | D10: =SUMIF(Daily_Sales!D:D,B10,Daily_Sales!G:G) | E10: =SUMIF(Daily_Sales!D:D,B10,Daily_Sales!H:H) | F10: =IF(B10="","",D10-E10+C10) | G10: =SUMIF(Dukandar_Receipts!C:C,B10,Dukandar_Receipts!E:E) | H10: =IF(B10="","",F10-G10)
A11: 7 | B11: =IF(Masters!I9="","",Masters!I9) | C11: =IF(Masters!J9="",0,Masters!J9) | D11: =SUMIF(Daily_Sales!D:D,B11,Daily_Sales!G:G) | E11: =SUMIF(Daily_Sales!D:D,B11,Daily_Sales!H:H) | F11: =IF(B11="","",D11-E11+C11) | G11: =SUMIF(Dukandar_Receipts!C:C,B11,Dukandar_Receipts!E:E) | H11: =IF(B11="","",F11-G11)
A12: 8 | B12: =IF(Masters!I10="","",Masters!I10) | C12: =IF(Masters!J10="",0,Masters!J10) | D12: =SUMIF(Daily_Sales!D:D,B12,Daily_Sales!G:G) | E12: =SUMIF(Daily_Sales!D:D,B12,Daily_Sales!H:H) | F12: =IF(B12="","",D12-E12+C12) | G12: =SUMIF(Dukandar_Receipts!C:C,B12,Dukandar_Receipts!E:E) | H12: =IF(B12="","",F12-G12)
A13: 9 | B13: =IF(Masters!I11="","",Masters!I11) | C13: =IF(Masters!J11="",0,Masters!J11) | D13: =SUMIF(Daily_Sales!D:D,B13,Daily_Sales!G:G) | E13: =SUMIF(Daily_Sales!D:D,B13,Daily_Sales!H:H) | F13: =IF(B13="","",D13-E13+C13) | G13: =SUMIF(Dukandar_Receipts!C:C,B13,Dukandar_Receipts!E:E) | H13: =IF(B13="","",F13-G13)
A14: 10 | B14: =IF(Masters!I12="","",Masters!I12) | C14: =IF(Masters!J12="",0,Masters!J12) | D14: =SUMIF(Daily_Sales!D:D,B14,Daily_Sales!G:G) | E14: =SUMIF(Daily_Sales!D:D,B14,Daily_Sales!H:H) | F14: =IF(B14="","",D14-E14+C14) | G14: =SUMIF(Dukandar_Receipts!C:C,B14,Dukandar_Receipts!E:E) | H14: =IF(B14="","",F14-G14)
A15: 11 | B15: =IF(Masters!I13="","",Masters!I13) | C15: =IF(Masters!J13="",0,Masters!J13) | D15: =SUMIF(Daily_Sales!D:D,B15,Daily_Sales!G:G) | E15: =SUMIF(Daily_Sales!D:D,B15,Daily_Sales!H:H) | F15: =IF(B15="","",D15-E15+C15) | G15: =SUMIF(Dukandar_Receipts!C:C,B15,Dukandar_Receipts!E:E) | H15: =IF(B15="","",F15-G15)
A16: 12 | B16: =IF(Masters!I14="","",Masters!I14) | C16: =IF(Masters!J14="",0,Masters!J14) | D16: =SUMIF(Daily_Sales!D:D,B16,Daily_Sales!G:G) | E16: =SUMIF(Daily_Sales!D:D,B16,Daily_Sales!H:H) | F16: =IF(B16="","",D16-E16+C16) | G16: =SUMIF(Dukandar_Receipts!C:C,B16,Dukandar_Receipts!E:E) | H16: =IF(B16="","",F16-G16)
... A53: 49 | B53: =IF(Masters!I51="","",Masters!I51) | C53: =IF(Masters!J51="",0,Masters!J51) | D53: =SUMIF(Daily_Sales!D:D,B53,Daily_Sales!G:G) | E53: =SUMIF(Daily_Sales!D:D,B53,Daily_Sales!H:H) | F53: =IF(B53="","",D53-E53+C53) | G53: =SUMIF(Dukandar_Receipts!C:C,B53,Dukandar_Receipts!E:E) | H53: =IF(B53="","",F53-G53)
A54: TOTAL | C54: =SUM(C5:C53) | D54: =SUM(D5:D53) | E54: =SUM(E5:E53) | F54: =SUM(F5:F53) | G54: =SUM(G5:G53) | H54: =SUM(H5:H53)

Sheet Bepaari_Aakda
A1: BEPAARI SETTLEMENT SLIP (AAKDA)
A3: SELECT BEPAARI:
A4: DATE:
A6: SETTLEMENT DETAILS
A7: A. SALES SUMMARY
A8: Total Qty (Goats) | B8: =SUMIF(Daily_Sales!C:C,B3,Daily_Sales!E:E)
A9: Gross Sales Value | B9: =SUMIF(Daily_Sales!C:C,B3,Daily_Sales!G:G)
A11: B. DEDUCTIONS
A12: Commission | B12: =IFERROR(VLOOKUP(B3,Masters!B:E,4,FALSE),0)
A13: Commission Type | B13: =IFERROR(VLOOKUP(B3,Masters!B:D,3,FALSE),"")
A14: Commission Amount | B14: =IF(A13="%",A9*A12/100,A8*A12)
A15: Motor Bhada | B15: =SUMIFS(Bepaari_Expenses!E:E,Bepaari_Expenses!C:C,B3,Bepaari_Expenses!D:D,"MOTOR")
A16: Bhussa | B16: =SUMIFS(Bepaari_Expenses!E:E,Bepaari_Expenses!C:C,B3,Bepaari_Expenses!D:D,"BHUSSA")
A17: Jagah Bhada | B17: =SUMIFS(Bepaari_Expenses!E:E,Bepaari_Expenses!C:C,B3,Bepaari_Expenses!D:D,"JB")
A18: Gawali | B18: =SUMIFS(Bepaari_Expenses!E:E,Bepaari_Expenses!C:C,B3,Bepaari_Expenses!D:D,"GAWALI")
A19: Karkuni | B19: =SUMIFS(Bepaari_Expenses!E:E,Bepaari_Expenses!C:C,B3,Bepaari_Expenses!D:D,"KK")
A20: Cash/Advance | B20: =SUMIFS(Bepaari_Expenses!E:E,Bepaari_Expenses!C:C,B3,Bepaari_Expenses!D:D,"CASH")
A21: Other Expenses | B21: =SUMIFS(Bepaari_Expenses!E:E,Bepaari_Expenses!C:C,B3,Bepaari_Expenses!D:D,"OTHER")
A22: TOTAL DEDUCTIONS | B22: =SUM(A14:A21)
A24: C. NET CALCULATION
A25: Gross Sales | B25: =A9
A26: Less: Total Deductions | B26: =A22
A27: Opening Balance | B27: =IFERROR(VLOOKUP(B3,Masters!B:E,4,FALSE),0)
A28: NET PAYABLE TO BEPAARI | B28: =A25-A26+A27
A30: D. PAYMENTS MADE
A31: Total Payments | B31: =SUMIF(Bepaari_Payments!C:C,B3,Bepaari_Payments!E:E)
A33: BALANCE DUE | B33: =A28-A31

Sheet Daily_Summary
A1: DAILY BUSINESS SUMMARY
A2: Enter date to see that day's summary
A4: SELECT DATE:
A6: TODAY'S TRADING SUMMARY
A7: Total Goats Sold | B7: =SUMIF(Daily_Sales!B:B,B4,Daily_Sales!E:E)
A8: Gross Sales Value | B8: =SUMIF(Daily_Sales!B:B,B4,Daily_Sales!G:G)
A9: Total Discounts Given | B9: =SUMIF(Daily_Sales!B:B,B4,Daily_Sales!H:H)
A10: Net Sales | B10: =B9-B10
A12: EXPENSES (for the day)
A13: Total Bepaari Expenses | B13: =SUMIF(Bepaari_Expenses!B:B,B4,Bepaari_Expenses!E:E)
A15: COMMISSION EARNED (Approx.)
A16: Estimated @ 4% | B16: =B9*0.04
A18: PAYMENTS/RECEIPTS
A19: Paid to Bepaaris | B19: =SUMIF(Bepaari_Payments!B:B,B4,Bepaari_Payments!E:E)
A20: Received from Dukandars | B20: =SUMIF(Dukandar_Receipts!B:B,B4,Dukandar_Receipts!E:E)
A21: Net Cash Flow | B21: =B21-B20
